Workbook

Sheet Summary
A1: Dosa Coffee - Kolkata | B1: Department | C1: 46113 | D1: 46143 | E1: 46174 | F1: 46204 | G1: 46235 | H1: 46266 | I1: 46296 | J1: 46327 | K1: 46357 | L1: 46388 | M1: 46419 | N1: 46447 | O1: FY 2025-26
A2: Food Cost Calculation
A3: Opening Stock | B3: Procurement | C3: ='Ideal Plaza'!B3+'Salt Lake JC -21'!B3+'Forum Mall'!B3+'Lake Town'!B3+'Quest Mall'!B3+'Rosedale Plaza'!B3+'Mani Square Mall'!B3+'Forum Rangoli'!B3+CSC!B3+Jameslong!B3+Technopolis!B3+Santoshpur!B3+'Chinar Park'!B3+'Lake Road'!B3+Kalikapur!B3+'Event Sales'!B3+'Sector 1'!B3 -> 447329 | D3: ='Ideal Plaza'!C3+'Salt Lake JC -21'!C3+'Forum Mall'!C3+'Lake Town'!C3+'Quest Mall'!C3+'Rosedale Plaza'!C3+'Mani Square Mall'!C3+'Forum Rangoli'!C3+CSC!C3+Jameslong!C3+Technopolis!C3+Santoshpur!C3+'Chinar Park'!C3+'Lake Road'!C3+Kalikapur!C3+'Event Sales'!C3+'Sector 1'!C3 -> 526715.46 | E3: ='Ideal Plaza'!D3+'Salt Lake JC -21'!D3+'Forum Mall'!D3+'Lake Town'!D3+'Quest Mall'!D3+'Rosedale Plaza'!D3+'Mani Square Mall'!D3+'Forum Rangoli'!D3+CSC!D3+Jameslong!D3+Technopolis!D3+Santoshpur!D3+'Chinar Park'!D3+'Lake Road'!D3+Kalikapur!D3+'Event Sales'!D3+'Sector 1'!D3 -> 493813.25 | F3: ='Ideal Plaza'!E3+'Salt Lake JC -21'!E3+'Forum Mall'!E3+'Lake Town'!E3+'Quest Mall'!E3+'Rosedale Plaza'!E3+'Mani Square Mall'!E3+'Forum Rangoli'!E3+CSC!E3+Jameslong!E3+Technopolis!E3+Santoshpur!E3+'Chinar Park'!E3+'Lake Road'!E3+Kalikapur!E3+'Event Sales'!E3+'Sector 1'!E3 -> 508615.44 | G3: ='Ideal Plaza'!F3+'Salt Lake JC -21'!F3+'Forum Mall'!F3+'Lake Town'!F3+'Quest Mall'!F3+'Rosedale Plaza'!F3+'Mani Square Mall'!F3+'Forum Rangoli'!F3+CSC!F3+Jameslong!F3+Technopolis!F3+Santoshpur!F3+'Chinar Park'!F3+'Lake Road'!F3+Kalikapur!F3+'Event Sales'!F3+'Sector 1'!F3 -> 427633.73 | H3: ='Ideal Plaza'!G3+'Salt Lake JC -21'!G3+'Forum Mall'!G3+'Lake Town'!G3+'Quest Mall'!G3+'Rosedale Plaza'!G3+'Mani Square Mall'!G3+'Forum Rangoli'!G3+CSC!G3+Jameslong!G3+Technopolis!G3+Santoshpur!G3+'Chinar Park'!G3+'Lake Road'!G3+Kalikapur!G3+'Event Sales'!G3+'Sector 1'!G3 -> 445238.45 | I3: ='Ideal Plaza'!H3+'Salt Lake JC -21'!H3+'Forum Mall'!H3+'Lake Town'!H3+'Quest Mall'!H3+'Rosedale Plaza'!H3+'Mani Square Mall'!H3+'Forum Rangoli'!H3+CSC!H3+Jameslong!H3+Technopolis!H3+Santoshpur!H3+'Chinar Park'!H3+'Lake Road'!H3+Kalikapur!H3+'Event Sales'!H3+'Sector 1'!H3 -> 450578.72 | J3: ='Ideal Plaza'!I3+'Salt Lake JC -21'!I3+'Forum Mall'!I3+'Lake Town'!I3+'Quest Mall'!I3+'Rosedale Plaza'!I3+'Mani Square Mall'!I3+'Forum Rangoli'!I3+CSC!I3+Jameslong!I3+Technopolis!I3+Santoshpur!I3+'Chinar Park'!I3+'Lake Road'!I3+Kalikapur!I3+'Event Sales'!I3+'Sector 1'!I3 -> 0 | ... N3: ='Ideal Plaza'!M3+'Salt Lake JC -21'!M3+'Forum Mall'!M3+'Lake Town'!M3+'Quest Mall'!M3+'Rosedale Plaza'!M3+'Mani Square Mall'!M3+'Forum Rangoli'!M3+CSC!M3+Jameslong!M3+Technopolis!M3+Santoshpur!M3+'Chinar Park'!M3+'Lake Road'!M3+Kalikapur!M3+'Event Sales'!M3+'Sector 1'!M3 -> 0 | R3: ='Central Kitchen - Kolkata'!F6 -> 6907308
A4: Purchases Food (Less Purchase Return) | B4: Procurement | C4: ='Ideal Plaza'!B4+'Salt Lake JC -21'!B4+'Forum Mall'!B4+'Lake Town'!B4+'Quest Mall'!B4+'Rosedale Plaza'!B4+'Mani Square Mall'!B4+'Forum Rangoli'!B4+CSC!B4+Jameslong!B4+Technopolis!B4+Santoshpur!B4+'Chinar Park'!B4+'Lake Road'!B4+Kalikapur!B4+'Event Sales'!B4+'Sector 1'!B4+140608 -> 5564785.3 | D4: ='Ideal Plaza'!C4+'Salt Lake JC -21'!C4+'Forum Mall'!C4+'Lake Town'!C4+'Quest Mall'!C4+'Rosedale Plaza'!C4+'Mani Square Mall'!C4+'Forum Rangoli'!C4+CSC!C4+Jameslong!C4+Technopolis!C4+Santoshpur!C4+'Chinar Park'!C4+'Lake Road'!C4+Kalikapur!C4+'Event Sales'!C4+'Sector 1'!C4+372700 -> 6109164.4 | E4: ='Ideal Plaza'!D4+'Salt Lake JC -21'!D4+'Forum Mall'!D4+'Lake Town'!D4+'Quest Mall'!D4+'Rosedale Plaza'!D4+'Mani Square Mall'!D4+'Forum Rangoli'!D4+CSC!D4+Jameslong!D4+Technopolis!D4+Santoshpur!D4+'Chinar Park'!D4+'Lake Road'!D4+Kalikapur!D4+'Event Sales'!D4+'Sector 1'!D4+122665 -> 6056091.9 | F4: ='Ideal Plaza'!E4+'Salt Lake JC -21'!E4+'Forum Mall'!E4+'Lake Town'!E4+'Quest Mall'!E4+'Rosedale Plaza'!E4+'Mani Square Mall'!E4+'Forum Rangoli'!E4+CSC!E4+Jameslong!E4+Technopolis!E4+Santoshpur!E4+'Chinar Park'!E4+'Lake Road'!E4+Kalikapur!E4+'Event Sales'!E4+'Sector 1'!E4 -> 6114107.9 | G4: ='Ideal Plaza'!F4+'Salt Lake JC -21'!F4+'Forum Mall'!F4+'Lake Town'!F4+'Quest Mall'!F4+'Rosedale Plaza'!F4+'Mani Square Mall'!F4+'Forum Rangoli'!F4+CSC!F4+Jameslong!F4+Technopolis!F4+Santoshpur!F4+'Chinar Park'!F4+'Lake Road'!F4+Kalikapur!F4+'Event Sales'!F4+'Sector 1'!F4+153979 -> 6907307.7 | H4: ='Ideal Plaza'!G4+'Salt Lake JC -21'!G4+'Forum Mall'!G4+'Lake Town'!G4+'Quest Mall'!G4+'Rosedale Plaza'!G4+'Mani Square Mall'!G4+'Forum Rangoli'!G4+CSC!G4+Jameslong!G4+Technopolis!G4+Santoshpur!G4+'Chinar Park'!G4+'Lake Road'!G4+Kalikapur!G4+'Event Sales'!G4+'Sector 1'!G4+79474 -> 6135736.4 | I4: ='Ideal Plaza'!H4+'Salt Lake JC -21'!H4+'Forum Mall'!H4+'Lake Town'!H4+'Quest Mall'!H4+'Rosedale Plaza'!H4+'Mani Square Mall'!H4+'Forum Rangoli'!H4+CSC!H4+Jameslong!H4+Technopolis!H4+Santoshpur!H4+'Chinar Park'!H4+'Lake Road'!H4+Kalikapur!H4+'Event Sales'!H4+'Sector 1'!H4 -> 0 | J4: ='Ideal Plaza'!I4+'Salt Lake JC -21'!I4+'Forum Mall'!I4+'Lake Town'!I4+'Quest Mall'!I4+'Rosedale Plaza'!I4+'Mani Square Mall'!I4+'Forum Rangoli'!I4+CSC!I4+Jameslong!I4+Technopolis!I4+Santoshpur!I4+'Chinar Park'!I4+'Lake Road'!I4+Kalikapur!I4+'Event Sales'!I4+'Sector 1'!I4 -> 0 | K4: ='Ideal Plaza'!J4+'Salt Lake JC -21'!J4+'Forum Mall'!J4+'Lake Town'!J4+'Quest Mall'!J4+'Rosedale Plaza'!J4+'Mani Square Mall'!J4+'Forum Rangoli'!J4+CSC!J4+Jameslong!J4+Technopolis!J4+Santoshpur!J4+'Chinar Park'!J4+'Lake Road'!J4+Kalikapur!J4+'Event Sales'!J4+'Sector 1'!J4 -> 0 | L4: ='Ideal Plaza'!K4+'Salt Lake JC -21'!K4+'Forum Mall'!K4+'Lake Town'!K4+'Quest Mall'!K4+'Rosedale Plaza'!K4+'Mani Square Mall'!K4+'Forum Rangoli'!K4+CSC!K4+Jameslong!K4+Technopolis!K4+Santoshpur!K4+'Chinar Park'!K4+'Lake Road'!K4+Kalikapur!K4+'Event Sales'!K4+'Sector 1'!K4 -> 0 | M4: ='Ideal Plaza'!L4+'Salt Lake JC -21'!L4+'Forum Mall'!L4+'Lake Town'!L4+'Quest Mall'!L4+'Rosedale Plaza'!L4+'Mani Square Mall'!L4+'Forum Rangoli'!L4+CSC!L4+Jameslong!L4+Technopolis!L4+Santoshpur!L4+'Chinar Park'!L4+'Lake Road'!L4+Kalikapur!L4+'Event Sales'!L4+'Sector 1'!L4 -> 0 | N4: ='Ideal Plaza'!M4+'Salt Lake JC -21'!M4+'Forum Mall'!M4+'Lake Town'!M4+'Quest Mall'!M4+'Rosedale Plaza'!M4+'Mani Square Mall'!M4+'Forum Rangoli'!M4+CSC!M4+Jameslong!M4+Technopolis!M4+Santoshpur!M4+'Chinar Park'!M4+'Lake Road'!M4+Kalikapur!M4+'Event Sales'!M4+'Sector 1'!M4 -> 0 | O4: =sum(C4:N4) -> 36887194 | R4: =G4-R3 -> -0.29
A5: Transferred Out | B5: Procurement | C5: ='Ideal Plaza'!B5+'Salt Lake JC -21'!B5+'Forum Mall'!B5+'Lake Town'!B5+'Quest Mall'!B5+'Rosedale Plaza'!B5+'Mani Square Mall'!B5+'Forum Rangoli'!B5+CSC!B5+Jameslong!B5+Technopolis!B5+Santoshpur!B5+'Chinar Park'!B5+'Lake Road'!B5+Kalikapur!B5+'Event Sales'!B5+'Sector 1'!B5 -> 13904.56 | D5: ='Ideal Plaza'!C5+'Salt Lake JC -21'!C5+'Forum Mall'!C5+'Lake Town'!C5+'Quest Mall'!C5+'Rosedale Plaza'!C5+'Mani Square Mall'!C5+'Forum Rangoli'!C5+CSC!C5+Jameslong!C5+Technopolis!C5+Santoshpur!C5+'Chinar Park'!C5+'Lake Road'!C5+Kalikapur!C5+'Event Sales'!C5+'Sector 1'!C5 -> 12778.38 | E5: ='Ideal Plaza'!D5+'Salt Lake JC -21'!D5+'Forum Mall'!D5+'Lake Town'!D5+'Quest Mall'!D5+'Rosedale Plaza'!D5+'Mani Square Mall'!D5+'Forum Rangoli'!D5+CSC!D5+Jameslong!D5+Technopolis!D5+Santoshpur!D5+'Chinar Park'!D5+'Lake Road'!D5+Kalikapur!D5+'Event Sales'!D5+'Sector 1'!D5 -> 7693.46 | F5: ='Ideal Plaza'!E5+'Salt Lake JC -21'!E5+'Forum Mall'!E5+'Lake Town'!E5+'Quest Mall'!E5+'Rosedale Plaza'!E5+'Mani Square Mall'!E5+'Forum Rangoli'!E5+CSC!E5+Jameslong!E5+Technopolis!E5+Santoshpur!E5+'Chinar Park'!E5+'Lake Road'!E5+Kalikapur!E5+'Event Sales'!E5+'Sector 1'!E5 -> 13696.73 | G5: ='Ideal Plaza'!F5+'Salt Lake JC -21'!F5+'Forum Mall'!F5+'Lake Town'!F5+'Quest Mall'!F5+'Rosedale Plaza'!F5+'Mani Square Mall'!F5+'Forum Rangoli'!F5+CSC!F5+Jameslong!F5+Technopolis!F5+Santoshpur!F5+'Chinar Park'!F5+'Lake Road'!F5+Kalikapur!F5+'Event Sales'!F5+'Sector 1'!F5 -> 12730.2 | H5: ='Ideal Plaza'!G5+'Salt Lake JC -21'!G5+'Forum Mall'!G5+'Lake Town'!G5+'Quest Mall'!G5+'Rosedale Plaza'!G5+'Mani Square Mall'!G5+'Forum Rangoli'!G5+CSC!G5+Jameslong!G5+Technopolis!G5+Santoshpur!G5+'Chinar Park'!G5+'Lake Road'!G5+Kalikapur!G5+'Event Sales'!G5+'Sector 1'!G5 -> 18574.71 | I5: ='Ideal Plaza'!H5+'Salt Lake JC -21'!H5+'Forum Mall'!H5+'Lake Town'!H5+'Quest Mall'!H5+'Rosedale Plaza'!H5+'Mani Square Mall'!H5+'Forum Rangoli'!H5+CSC!H5+Jameslong!H5+Technopolis!H5+Santoshpur!H5+'Chinar Park'!H5+'Lake Road'!H5+Kalikapur!H5+'Event Sales'!H5+'Sector 1'!H5 -> 0 | J5: ='Ideal Plaza'!I5+'Salt Lake JC -21'!I5+'Forum Mall'!I5+'Lake Town'!I5+'Quest Mall'!I5+'Rosedale Plaza'!I5+'Mani Square Mall'!I5+'Forum Rangoli'!I5+CSC!I5+Jameslong!I5+Technopolis!I5+Santoshpur!I5+'Chinar Park'!I5+'Lake Road'!I5+Kalikapur!I5+'Event Sales'!I5+'Sector 1'!I5 -> 0 | ... N5: ='Ideal Plaza'!M5+'Salt Lake JC -21'!M5+'Forum Mall'!M5+'Lake Town'!M5+'Quest Mall'!M5+'Rosedale Plaza'!M5+'Mani Square Mall'!M5+'Forum Rangoli'!M5+CSC!M5+Jameslong!M5+Technopolis!M5+Santoshpur!M5+'Chinar Park'!M5+'Lake Road'!M5+Kalikapur!M5+'Event Sales'!M5+'Sector 1'!M5 -> 0 | O5: =sum(C5:N5) -> 79378.04
A6: Wastage & Date Expired | B6: Procurement | C6: ='Ideal Plaza'!B6+'Salt Lake JC -21'!B6+'Forum Mall'!B6+'Lake Town'!B6+'Quest Mall'!B6+'Rosedale Plaza'!B6+'Mani Square Mall'!B6+'Forum Rangoli'!B6+CSC!B6+Jameslong!B6+Technopolis!B6+Santoshpur!B6+'Chinar Park'!B6+'Lake Road'!B6+Kalikapur!B6+'Event Sales'!B6+'Sector 1'!B6 -> 190296.11 | D6: ='Ideal Plaza'!C6+'Salt Lake JC -21'!C6+'Forum Mall'!C6+'Lake Town'!C6+'Quest Mall'!C6+'Rosedale Plaza'!C6+'Mani Square Mall'!C6+'Forum Rangoli'!C6+CSC!C6+Jameslong!C6+Technopolis!C6+Santoshpur!C6+'Chinar Park'!C6+'Lake Road'!C6+Kalikapur!C6+'Event Sales'!C6+'Sector 1'!C6 -> 204666.46 | E6: ='Ideal Plaza'!D6+'Salt Lake JC -21'!D6+'Forum Mall'!D6+'Lake Town'!D6+'Quest Mall'!D6+'Rosedale Plaza'!D6+'Mani Square Mall'!D6+'Forum Rangoli'!D6+CSC!D6+Jameslong!D6+Technopolis!D6+Santoshpur!D6+'Chinar Park'!D6+'Lake Road'!D6+Kalikapur!D6+'Event Sales'!D6+'Sector 1'!D6 -> 205928.27 | F6: ='Ideal Plaza'!E6+'Salt Lake JC -21'!E6+'Forum Mall'!E6+'Lake Town'!E6+'Quest Mall'!E6+'Rosedale Plaza'!E6+'Mani Square Mall'!E6+'Forum Rangoli'!E6+CSC!E6+Jameslong!E6+Technopolis!E6+Santoshpur!E6+'Chinar Park'!E6+'Lake Road'!E6+Kalikapur!E6+'Event Sales'!E6+'Sector 1'!E6 -> 220814.31 | G6: ='Ideal Plaza'!F6+'Salt Lake JC -21'!F6+'Forum Mall'!F6+'Lake Town'!F6+'Quest Mall'!F6+'Rosedale Plaza'!F6+'Mani Square Mall'!F6+'Forum Rangoli'!F6+CSC!F6+Jameslong!F6+Technopolis!F6+Santoshpur!F6+'Chinar Park'!F6+'Lake Road'!F6+Kalikapur!F6+'Event Sales'!F6+'Sector 1'!F6 -> 281646.38 | H6: ='Ideal Plaza'!G6+'Salt Lake JC -21'!G6+'Forum Mall'!G6+'Lake Town'!G6+'Quest Mall'!G6+'Rosedale Plaza'!G6+'Mani Square Mall'!G6+'Forum Rangoli'!G6+CSC!G6+Jameslong!G6+Technopolis!G6+Santoshpur!G6+'Chinar Park'!G6+'Lake Road'!G6+Kalikapur!G6+'Event Sales'!G6+'Sector 1'!G6 -> 301691.69 | I6: ='Ideal Plaza'!H6+'Salt Lake JC -21'!H6+'Forum Mall'!H6+'Lake Town'!H6+'Quest Mall'!H6+'Rosedale Plaza'!H6+'Mani Square Mall'!H6+'Forum Rangoli'!H6+CSC!H6+Jameslong!H6+Technopolis!H6+Santoshpur!H6+'Chinar Park'!H6+'Lake Road'!H6+Kalikapur!H6+'Event Sales'!H6+'Sector 1'!H6 -> 0 | J6: ='Ideal Plaza'!I6+'Salt Lake JC -21'!I6+'Forum Mall'!I6+'Lake Town'!I6+'Quest Mall'!I6+'Rosedale Plaza'!I6+'Mani Square Mall'!I6+'Forum Rangoli'!I6+CSC!I6+Jameslong!I6+Technopolis!I6+Santoshpur!I6+'Chinar Park'!I6+'Lake Road'!I6+Kalikapur!I6+'Event Sales'!I6+'Sector 1'!I6 -> 0 | ... N6: ='Ideal Plaza'!M6+'Salt Lake JC -21'!M6+'Forum Mall'!M6+'Lake Town'!M6+'Quest Mall'!M6+'Rosedale Plaza'!M6+'Mani Square Mall'!M6+'Forum Rangoli'!M6+CSC!M6+Jameslong!M6+Technopolis!M6+Santoshpur!M6+'Chinar Park'!M6+'Lake Road'!M6+Kalikapur!M6+'Event Sales'!M6+'Sector 1'!M6 -> 0 | O6: =sum(C6:N6) -> 1405043.2
A7: Closing Stock | B7: Procurement | C7: ='Ideal Plaza'!B7+'Salt Lake JC -21'!B7+'Forum Mall'!B7+'Lake Town'!B7+'Quest Mall'!B7+'Rosedale Plaza'!B7+'Mani Square Mall'!B7+'Forum Rangoli'!B7+CSC!B7+Jameslong!B7+Technopolis!B7+Santoshpur!B7+'Chinar Park'!B7+'Lake Road'!B7+Kalikapur!B7+'Event Sales'!B7+'Sector 1'!B7 -> 526715.46 | D7: ='Ideal Plaza'!C7+'Salt Lake JC -21'!C7+'Forum Mall'!C7+'Lake Town'!C7+'Quest Mall'!C7+'Rosedale Plaza'!C7+'Mani Square Mall'!C7+'Forum Rangoli'!C7+CSC!C7+Jameslong!C7+Technopolis!C7+Santoshpur!C7+'Chinar Park'!C7+'Lake Road'!C7+Kalikapur!C7+'Event Sales'!C7+'Sector 1'!C7 -> 493813.25 | E7: ='Ideal Plaza'!D7+'Salt Lake JC -21'!D7+'Forum Mall'!D7+'Lake Town'!D7+'Quest Mall'!D7+'Rosedale Plaza'!D7+'Mani Square Mall'!D7+'Forum Rangoli'!D7+CSC!D7+Jameslong!D7+Technopolis!D7+Santoshpur!D7+'Chinar Park'!D7+'Lake Road'!D7+Kalikapur!D7+'Event Sales'!D7+'Sector 1'!D7 -> 508615.44 | F7: ='Ideal Plaza'!E7+'Salt Lake JC -21'!E7+'Forum Mall'!E7+'Lake Town'!E7+'Quest Mall'!E7+'Rosedale Plaza'!E7+'Mani Square Mall'!E7+'Forum Rangoli'!E7+CSC!E7+Jameslong!E7+Technopolis!E7+Santoshpur!E7+'Chinar Park'!E7+'Lake Road'!E7+Kalikapur!E7+'Event Sales'!E7+'Sector 1'!E7 -> 427633.73 | G7: ='Ideal Plaza'!F7+'Salt Lake JC -21'!F7+'Forum Mall'!F7+'Lake Town'!F7+'Quest Mall'!F7+'Rosedale Plaza'!F7+'Mani Square Mall'!F7+'Forum Rangoli'!F7+CSC!F7+Jameslong!F7+Technopolis!F7+Santoshpur!F7+'Chinar Park'!F7+'Lake Road'!F7+Kalikapur!F7+'Event Sales'!F7+'Sector 1'!F7 -> 445238.45 | H7: ='Ideal Plaza'!G7+'Salt Lake JC -21'!G7+'Forum Mall'!G7+'Lake Town'!G7+'Quest Mall'!G7+'Rosedale Plaza'!G7+'Mani Square Mall'!G7+'Forum Rangoli'!G7+CSC!G7+Jameslong!G7+Technopolis!G7+Santoshpur!G7+'Chinar Park'!G7+'Lake Road'!G7+Kalikapur!G7+'Event Sales'!G7+'Sector 1'!G7 -> 450578.72 | I7: ='Ideal Plaza'!H7+'Salt Lake JC -21'!H7+'Forum Mall'!H7+'Lake Town'!H7+'Quest Mall'!H7+'Rosedale Plaza'!H7+'Mani Square Mall'!H7+'Forum Rangoli'!H7+CSC!H7+Jameslong!H7+Technopolis!H7+Santoshpur!H7+'Chinar Park'!H7+'Lake Road'!H7+Kalikapur!H7+'Event Sales'!H7+'Sector 1'!H7 -> 0 | J7: ='Ideal Plaza'!I7+'Salt Lake JC -21'!I7+'Forum Mall'!I7+'Lake Town'!I7+'Quest Mall'!I7+'Rosedale Plaza'!I7+'Mani Square Mall'!I7+'Forum Rangoli'!I7+CSC!I7+Jameslong!I7+Technopolis!I7+Santoshpur!I7+'Chinar Park'!I7+'Lake Road'!I7+Kalikapur!I7+'Event Sales'!I7+'Sector 1'!I7 -> 0 | ... N7: ='Ideal Plaza'!M7+'Salt Lake JC -21'!M7+'Forum Mall'!M7+'Lake Town'!M7+'Quest Mall'!M7+'Rosedale Plaza'!M7+'Mani Square Mall'!M7+'Forum Rangoli'!M7+CSC!M7+Jameslong!M7+Technopolis!M7+Santoshpur!M7+'Chinar Park'!M7+'Lake Road'!M7+Kalikapur!M7+'Event Sales'!M7+'Sector 1'!M7 -> 0 | O7: =sum(C7:N7) -> 2852595
A9: Gross Revenue | B9: Operation | C9: ='Ideal Plaza'!B9+'Salt Lake JC -21'!B9+'Forum Mall'!B9+'Lake Town'!B9+'Quest Mall'!B9+'Rosedale Plaza'!B9+'Mani Square Mall'!B9+'Forum Rangoli'!B9+CSC!B9+Jameslong!B9+Technopolis!B9+Santoshpur!B9+'Chinar Park'!B9+'Lake Road'!B9+Kalikapur!B9+'Event Sales'!B9+'Sector 1'!B9 -> 23538283 | D9: ='Ideal Plaza'!C9+'Salt Lake JC -21'!C9+'Forum Mall'!C9+'Lake Town'!C9+'Quest Mall'!C9+'Rosedale Plaza'!C9+'Mani Square Mall'!C9+'Forum Rangoli'!C9+CSC!C9+Jameslong!C9+Technopolis!C9+Santoshpur!C9+'Chinar Park'!C9+'Lake Road'!C9+Kalikapur!C9+'Event Sales'!C9+'Sector 1'!C9 -> 26036501 | E9: ='Ideal Plaza'!D9+'Salt Lake JC -21'!D9+'Forum Mall'!D9+'Lake Town'!D9+'Quest Mall'!D9+'Rosedale Plaza'!D9+'Mani Square Mall'!D9+'Forum Rangoli'!D9+CSC!D9+Jameslong!D9+Technopolis!D9+Santoshpur!D9+'Chinar Park'!D9+'Lake Road'!D9+Kalikapur!D9+'Event Sales'!D9+'Sector 1'!D9 -> 24955324 | F9: ='Ideal Plaza'!E9+'Salt Lake JC -21'!E9+'Forum Mall'!E9+'Lake Town'!E9+'Quest Mall'!E9+'Rosedale Plaza'!E9+'Mani Square Mall'!E9+'Forum Rangoli'!E9+CSC!E9+Jameslong!E9+Technopolis!E9+Santoshpur!E9+'Chinar Park'!E9+'Lake Road'!E9+Kalikapur!E9+'Event Sales'!E9+'Sector 1'!E9 -> 25713135 | G9: ='Ideal Plaza'!F9+'Salt Lake JC -21'!F9+'Forum Mall'!F9+'Lake Town'!F9+'Quest Mall'!F9+'Rosedale Plaza'!F9+'Mani Square Mall'!F9+'Forum Rangoli'!F9+CSC!F9+Jameslong!F9+Technopolis!F9+Santoshpur!F9+'Chinar Park'!F9+'Lake Road'!F9+Kalikapur!F9+'Event Sales'!F9+'Sector 1'!F9 -> 27975795 | H9: ='Ideal Plaza'!G9+'Salt Lake JC -21'!G9+'Forum Mall'!G9+'Lake Town'!G9+'Quest Mall'!G9+'Rosedale Plaza'!G9+'Mani Square Mall'!G9+'Forum Rangoli'!G9+CSC!G9+Jameslong!G9+Technopolis!G9+Santoshpur!G9+'Chinar Park'!G9+'Lake Road'!G9+Kalikapur!G9+'Event Sales'!G9+'Sector 1'!G9 -> 25745713 | I9: ='Ideal Plaza'!H9+'Salt Lake JC -21'!H9+'Forum Mall'!H9+'Lake Town'!H9+'Quest Mall'!H9+'Rosedale Plaza'!H9+'Mani Square Mall'!H9+'Forum Rangoli'!H9+CSC!H9+Jameslong!H9+Technopolis!H9+Santoshpur!H9+'Chinar Park'!H9+'Lake Road'!H9+Kalikapur!H9+'Event Sales'!H9+'Sector 1'!H9 -> 0 | J9: ='Ideal Plaza'!I9+'Salt Lake JC -21'!I9+'Forum Mall'!I9+'Lake Town'!I9+'Quest Mall'!I9+'Rosedale Plaza'!I9+'Mani Square Mall'!I9+'Forum Rangoli'!I9+CSC!I9+Jameslong!I9+Technopolis!I9+Santoshpur!I9+'Chinar Park'!I9+'Lake Road'!I9+Kalikapur!I9+'Event Sales'!I9+'Sector 1'!I9 -> 0 | ... N9: ='Ideal Plaza'!M9+'Salt Lake JC -21'!M9+'Forum Mall'!M9+'Lake Town'!M9+'Quest Mall'!M9+'Rosedale Plaza'!M9+'Mani Square Mall'!M9+'Forum Rangoli'!M9+CSC!M9+Jameslong!M9+Technopolis!M9+Santoshpur!M9+'Chinar Park'!M9+'Lake Road'!M9+Kalikapur!M9+'Event Sales'!M9+'Sector 1'!M9 -> 0 | O9: =+SUM(C9:N9) -> 1.5396475e+08
A10: Catering & Fairs | B10: Operation | C10: ='Ideal Plaza'!B10+'Salt Lake JC -21'!B10+'Forum Mall'!B10+'Lake Town'!B10+'Quest Mall'!B10+'Rosedale Plaza'!B10+'Mani Square Mall'!B10+'Forum Rangoli'!B10+CSC!B10+Jameslong!B10+Technopolis!B10+Santoshpur!B10+'Chinar Park'!B10+'Lake Road'!B10+Kalikapur!B10+'Event Sales'!B10+'Sector 1'!B10 -> 0 | D10: ='Ideal Plaza'!C10+'Salt Lake JC -21'!C10+'Forum Mall'!C10+'Lake Town'!C10+'Quest Mall'!C10+'Rosedale Plaza'!C10+'Mani Square Mall'!C10+'Forum Rangoli'!C10+CSC!C10+Jameslong!C10+Technopolis!C10+Santoshpur!C10+'Chinar Park'!C10+'Lake Road'!C10+Kalikapur!C10+'Event Sales'!C10+'Sector 1'!C10 -> 0 | E10: ='Ideal Plaza'!D10+'Salt Lake JC -21'!D10+'Forum Mall'!D10+'Lake Town'!D10+'Quest Mall'!D10+'Rosedale Plaza'!D10+'Mani Square Mall'!D10+'Forum Rangoli'!D10+CSC!D10+Jameslong!D10+Technopolis!D10+Santoshpur!D10+'Chinar Park'!D10+'Lake Road'!D10+Kalikapur!D10+'Event Sales'!D10+'Sector 1'!D10 -> 0 | F10: ='Ideal Plaza'!E10+'Salt Lake JC -21'!E10+'Forum Mall'!E10+'Lake Town'!E10+'Quest Mall'!E10+'Rosedale Plaza'!E10+'Mani Square Mall'!E10+'Forum Rangoli'!E10+CSC!E10+Jameslong!E10+Technopolis!E10+Santoshpur!E10+'Chinar Park'!E10+'Lake Road'!E10+Kalikapur!E10+'Event Sales'!E10+'Sector 1'!E10 -> 0 | G10: ='Ideal Plaza'!F10+'Salt Lake JC -21'!F10+'Forum Mall'!F10+'Lake Town'!F10+'Quest Mall'!F10+'Rosedale Plaza'!F10+'Mani Square Mall'!F10+'Forum Rangoli'!F10+CSC!F10+Jameslong!F10+Technopolis!F10+Santoshpur!F10+'Chinar Park'!F10+'Lake Road'!F10+Kalikapur!F10+'Event Sales'!F10+'Sector 1'!F10 -> 0 | H10: ='Ideal Plaza'!G10+'Salt Lake JC -21'!G10+'Forum Mall'!G10+'Lake Town'!G10+'Quest Mall'!G10+'Rosedale Plaza'!G10+'Mani Square Mall'!G10+'Forum Rangoli'!G10+CSC!G10+Jameslong!G10+Technopolis!G10+Santoshpur!G10+'Chinar Park'!G10+'Lake Road'!G10+Kalikapur!G10+'Event Sales'!G10+'Sector 1'!G10 -> 0 | I10: ='Ideal Plaza'!H10+'Salt Lake JC -21'!H10+'Forum Mall'!H10+'Lake Town'!H10+'Quest Mall'!H10+'Rosedale Plaza'!H10+'Mani Square Mall'!H10+'Forum Rangoli'!H10+CSC!H10+Jameslong!H10+Technopolis!H10+Santoshpur!H10+'Chinar Park'!H10+'Lake Road'!H10+Kalikapur!H10+'Event Sales'!H10+'Sector 1'!H10 -> 0 | J10: ='Ideal Plaza'!I10+'Salt Lake JC -21'!I10+'Forum Mall'!I10+'Lake Town'!I10+'Quest Mall'!I10+'Rosedale Plaza'!I10+'Mani Square Mall'!I10+'Forum Rangoli'!I10+CSC!I10+Jameslong!I10+Technopolis!I10+Santoshpur!I10+'Chinar Park'!I10+'Lake Road'!I10+Kalikapur!I10+'Event Sales'!I10+'Sector 1'!I10 -> 0 | ... N10: ='Ideal Plaza'!M10+'Salt Lake JC -21'!M10+'Forum Mall'!M10+'Lake Town'!M10+'Quest Mall'!M10+'Rosedale Plaza'!M10+'Mani Square Mall'!M10+'Forum Rangoli'!M10+CSC!M10+Jameslong!M10+Technopolis!M10+Santoshpur!M10+'Chinar Park'!M10+'Lake Road'!M10+Kalikapur!M10+'Event Sales'!M10+'Sector 1'!M10 -> 0 | O10: =+SUM(C10:N10) -> 0
A11: Less Tax | B11: Operation | C11: ='Ideal Plaza'!B11+'Salt Lake JC -21'!B11+'Forum Mall'!B11+'Lake Town'!B11+'Quest Mall'!B11+'Rosedale Plaza'!B11+'Mani Square Mall'!B11+'Forum Rangoli'!B11+CSC!B11+Jameslong!B11+Technopolis!B11+Santoshpur!B11+'Chinar Park'!B11+'Lake Road'!B11+Kalikapur!B11+'Event Sales'!B11+'Sector 1'!B11 -> 1120870.6 | D11: ='Ideal Plaza'!C11+'Salt Lake JC -21'!C11+'Forum Mall'!C11+'Lake Town'!C11+'Quest Mall'!C11+'Rosedale Plaza'!C11+'Mani Square Mall'!C11+'Forum Rangoli'!C11+CSC!C11+Jameslong!C11+Technopolis!C11+Santoshpur!C11+'Chinar Park'!C11+'Lake Road'!C11+Kalikapur!C11+'Event Sales'!C11+'Sector 1'!C11 -> 1239833.4 | E11: ='Ideal Plaza'!D11+'Salt Lake JC -21'!D11+'Forum Mall'!D11+'Lake Town'!D11+'Quest Mall'!D11+'Rosedale Plaza'!D11+'Mani Square Mall'!D11+'Forum Rangoli'!D11+CSC!D11+Jameslong!D11+Technopolis!D11+Santoshpur!D11+'Chinar Park'!D11+'Lake Road'!D11+Kalikapur!D11+'Event Sales'!D11+'Sector 1'!D11 -> 1188348.8 | F11: ='Ideal Plaza'!E11+'Salt Lake JC -21'!E11+'Forum Mall'!E11+'Lake Town'!E11+'Quest Mall'!E11+'Rosedale Plaza'!E11+'Mani Square Mall'!E11+'Forum Rangoli'!E11+CSC!E11+Jameslong!E11+Technopolis!E11+Santoshpur!E11+'Chinar Park'!E11+'Lake Road'!E11+Kalikapur!E11+'Event Sales'!E11+'Sector 1'!E11 -> 1224435 | G11: ='Ideal Plaza'!F11+'Salt Lake JC -21'!F11+'Forum Mall'!F11+'Lake Town'!F11+'Quest Mall'!F11+'Rosedale Plaza'!F11+'Mani Square Mall'!F11+'Forum Rangoli'!F11+CSC!F11+Jameslong!F11+Technopolis!F11+Santoshpur!F11+'Chinar Park'!F11+'Lake Road'!F11+Kalikapur!F11+'Event Sales'!F11+'Sector 1'!F11 -> 1332180.7 | H11: ='Ideal Plaza'!G11+'Salt Lake JC -21'!G11+'Forum Mall'!G11+'Lake Town'!G11+'Quest Mall'!G11+'Rosedale Plaza'!G11+'Mani Square Mall'!G11+'Forum Rangoli'!G11+CSC!G11+Jameslong!G11+Technopolis!G11+Santoshpur!G11+'Chinar Park'!G11+'Lake Road'!G11+Kalikapur!G11+'Event Sales'!G11+'Sector 1'!G11 -> 1225986.3 | I11: ='Ideal Plaza'!H11+'Salt Lake JC -21'!H11+'Forum Mall'!H11+'Lake Town'!H11+'Quest Mall'!H11+'Rosedale Plaza'!H11+'Mani Square Mall'!H11+'Forum Rangoli'!H11+CSC!H11+Jameslong!H11+Technopolis!H11+Santoshpur!H11+'Chinar Park'!H11+'Lake Road'!H11+Kalikapur!H11+'Event Sales'!H11+'Sector 1'!H11 -> 0 | J11: ='Ideal Plaza'!I11+'Salt Lake JC -21'!I11+'Forum Mall'!I11+'Lake Town'!I11+'Quest Mall'!I11+'Rosedale Plaza'!I11+'Mani Square Mall'!I11+'Forum Rangoli'!I11+CSC!I11+Jameslong!I11+Technopolis!I11+Santoshpur!I11+'Chinar Park'!I11+'Lake Road'!I11+Kalikapur!I11+'Event Sales'!I11+'Sector 1'!I11 -> 0 | ... N11: ='Ideal Plaza'!M11+'Salt Lake JC -21'!M11+'Forum Mall'!M11+'Lake Town'!M11+'Quest Mall'!M11+'Rosedale Plaza'!M11+'Mani Square Mall'!M11+'Forum Rangoli'!M11+CSC!M11+Jameslong!M11+Technopolis!M11+Santoshpur!M11+'Chinar Park'!M11+'Lake Road'!M11+Kalikapur!M11+'Event Sales'!M11+'Sector 1'!M11 -> 0 | O11: =+SUM(C11:N11) -> 7331654.8
A12: Less Commission | B12: Operation | C12: ='Ideal Plaza'!B12+'Salt Lake JC -21'!B12+'Forum Mall'!B12+'Lake Town'!B12+'Quest Mall'!B12+'Rosedale Plaza'!B12+'Mani Square Mall'!B12+'Forum Rangoli'!B12+CSC!B12+Jameslong!B12+Technopolis!B12+Santoshpur!B12+'Chinar Park'!B12+'Lake Road'!B12+Kalikapur!B12+'Event Sales'!B12+'Sector 1'!B12 -> 2078483.9 | D12: ='Ideal Plaza'!C12+'Salt Lake JC -21'!C12+'Forum Mall'!C12+'Lake Town'!C12+'Quest Mall'!C12+'Rosedale Plaza'!C12+'Mani Square Mall'!C12+'Forum Rangoli'!C12+CSC!C12+Jameslong!C12+Technopolis!C12+Santoshpur!C12+'Chinar Park'!C12+'Lake Road'!C12+Kalikapur!C12+'Event Sales'!C12+'Sector 1'!C12 -> 2248672.2 | E12: ='Ideal Plaza'!D12+'Salt Lake JC -21'!D12+'Forum Mall'!D12+'Lake Town'!D12+'Quest Mall'!D12+'Rosedale Plaza'!D12+'Mani Square Mall'!D12+'Forum Rangoli'!D12+CSC!D12+Jameslong!D12+Technopolis!D12+Santoshpur!D12+'Chinar Park'!D12+'Lake Road'!D12+Kalikapur!D12+'Event Sales'!D12+'Sector 1'!D12 -> 2098372.9 | F12: ='Ideal Plaza'!E12+'Salt Lake JC -21'!E12+'Forum Mall'!E12+'Lake Town'!E12+'Quest Mall'!E12+'Rosedale Plaza'!E12+'Mani Square Mall'!E12+'Forum Rangoli'!E12+CSC!E12+Jameslong!E12+Technopolis!E12+Santoshpur!E12+'Chinar Park'!E12+'Lake Road'!E12+Kalikapur!E12+'Event Sales'!E12+'Sector 1'!E12 -> 2312388.2 | G12: ='Ideal Plaza'!F12+'Salt Lake JC -21'!F12+'Forum Mall'!F12+'Lake Town'!F12+'Quest Mall'!F12+'Rosedale Plaza'!F12+'Mani Square Mall'!F12+'Forum Rangoli'!F12+CSC!F12+Jameslong!F12+Technopolis!F12+Santoshpur!F12+'Chinar Park'!F12+'Lake Road'!F12+Kalikapur!F12+'Event Sales'!F12+'Sector 1'!F12 -> 2501416 | H12: ='Ideal Plaza'!G12+'Salt Lake JC -21'!G12+'Forum Mall'!G12+'Lake Town'!G12+'Quest Mall'!G12+'Rosedale Plaza'!G12+'Mani Square Mall'!G12+'Forum Rangoli'!G12+CSC!G12+Jameslong!G12+Technopolis!G12+Santoshpur!G12+'Chinar Park'!G12+'Lake Road'!G12+Kalikapur!G12+'Event Sales'!G12+'Sector 1'!G12 -> 2325503.8 | I12: ='Ideal Plaza'!H12+'Salt Lake JC -21'!H12+'Forum Mall'!H12+'Lake Town'!H12+'Quest Mall'!H12+'Rosedale Plaza'!H12+'Mani Square Mall'!H12+'Forum Rangoli'!H12+CSC!H12+Jameslong!H12+Technopolis!H12+Santoshpur!H12+'Chinar Park'!H12+'Lake Road'!H12+Kalikapur!H12+'Event Sales'!H12+'Sector 1'!H12 -> 0 | J12: ='Ideal Plaza'!I12+'Salt Lake JC -21'!I12+'Forum Mall'!I12+'Lake Town'!I12+'Quest Mall'!I12+'Rosedale Plaza'!I12+'Mani Square Mall'!I12+'Forum Rangoli'!I12+CSC!I12+Jameslong!I12+Technopolis!I12+Santoshpur!I12+'Chinar Park'!I12+'Lake Road'!I12+Kalikapur!I12+'Event Sales'!I12+'Sector 1'!I12 -> 0 | ... N12: ='Ideal Plaza'!M12+'Salt Lake JC -21'!M12+'Forum Mall'!M12+'Lake Town'!M12+'Quest Mall'!M12+'Rosedale Plaza'!M12+'Mani Square Mall'!M12+'Forum Rangoli'!M12+CSC!M12+Jameslong!M12+Technopolis!M12+Santoshpur!M12+'Chinar Park'!M12+'Lake Road'!M12+Kalikapur!M12+'Event Sales'!M12+'Sector 1'!M12 -> 0 | O12: =+SUM(C12:N12) -> 13564837
A13: Commission % | C13: =C12/C9 -> 0.088302274 | D13: =D12/D9 -> 0.086366145 | E13: =E12/E9 -> 0.08408518 | F13: =F12/F9 -> 0.089930231 | G13: =G12/G9 -> 0.089413578 | H13: =H12/H9 -> 0.090325866 | I13: =I12/I9 -> #DIV/0! | J13: =J12/J9 -> #DIV/0! | ... N13: =N12/N9 -> #DIV/0!
A14: Net Revenues from F&B Sales | C14: =C9+C10-C11-C12 -> 20338929 | D14: =D9+D10-D11-D12 -> 22547995 | E14: =E9+E10-E11-E12 -> 21668602 | F14: =F9+F10-F11-F12 -> 22176312 | G14: =G9+G10-G11-G12 -> 24142199 | H14: =H9+H10-H11-H12 -> 22194223 | I14: =I9+I10-I11-I12 -> 0 | J14: =J9+J10-J11-J12 -> 0 | ... N14: =N9+N10-N11-N12 -> 0 | O14: =sum(C14:N14) -> 1.3306826e+08 | P14: =O14/$O$14 -> 1
A15: F&B Cost | B15: Operation | C15: =C3+C4-C5-C7 -> 5471494.3 | D15: =D3+D4-D5-D7 -> 6129288.3 | E15: =E3+E4-E5-E7 -> 6033596.2 | F15: =F3+F4-F5-F7 -> 6181392.9 | G15: =G3+G4-G5-G7 -> 6876972.8 | H15: =H3+H4-H5-H7 -> 6111821.4 | I15: =I3+I4-I5-I7 -> 450578.72 | J15: =J3+J4-J5-J7 -> 0 | ... N15: =N3+N4-N5-N7 -> 0 | O15: =sum(C15:N15) -> 37255145 | P15: =O15/$O$14 -> 0.27997018
A16: Electricity | B16: Operation | C16: ='Ideal Plaza'!B15+'Salt Lake JC -21'!B15+'Forum Mall'!B15+'Lake Town'!B15+'Quest Mall'!B15+'Rosedale Plaza'!B15+'Mani Square Mall'!B15+'Forum Rangoli'!B15+CSC!B17+Jameslong!B15+Technopolis!B15+Santoshpur!B15+'Chinar Park'!B15+'Lake Road'!B15+Kalikapur!B15+'Event Sales'!B15+'Sector 1'!B15 -> 885727.04 | D16: ='Ideal Plaza'!C15+'Salt Lake JC -21'!C15+'Forum Mall'!C15+'Lake Town'!C15+'Quest Mall'!C15+'Rosedale Plaza'!C15+'Mani Square Mall'!C15+'Forum Rangoli'!C15+CSC!C15+Jameslong!C15+Technopolis!C15+Santoshpur!C15+'Chinar Park'!C15+'Lake Road'!C15+Kalikapur!C15+'Event Sales'!C15+'Sector 1'!C15 -> 959247.54 | E16: ='Ideal Plaza'!D15+'Salt Lake JC -21'!D15+'Forum Mall'!D15+'Lake Town'!D15+'Quest Mall'!D15+'Rosedale Plaza'!D15+'Mani Square Mall'!D15+'Forum Rangoli'!D15+CSC!D15+Jameslong!D15+Technopolis!D15+Santoshpur!D15+'Chinar Park'!D15+'Lake Road'!D15+Kalikapur!D15+'Event Sales'!D15+'Sector 1'!D15 -> 925105.63 | F16: ='Ideal Plaza'!E15+'Salt Lake JC -21'!E15+'Forum Mall'!E15+'Lake Town'!E15+'Quest Mall'!E15+'Rosedale Plaza'!E15+'Mani Square Mall'!E15+'Forum Rangoli'!E15+CSC!E15+Jameslong!E15+Technopolis!E15+Santoshpur!E15+'Chinar Park'!E15+'Lake Road'!E15+Kalikapur!E15+'Event Sales'!E15+'Sector 1'!E15 -> 909978.12 | G16: ='Ideal Plaza'!F15+'Salt Lake JC -21'!F15+'Forum Mall'!F15+'Lake Town'!F15+'Quest Mall'!F15+'Rosedale Plaza'!F15+'Mani Square Mall'!F15+'Forum Rangoli'!F15+CSC!F15+Jameslong!F15+Technopolis!F15+Santoshpur!F15+'Chinar Park'!F15+'Lake Road'!F15+Kalikapur!F15+'Event Sales'!F15+'Sector 1'!F15 -> 920092.26 | H16: ='Ideal Plaza'!G15+'Salt Lake JC -21'!G15+'Forum Mall'!G15+'Lake Town'!G15+'Quest Mall'!G15+'Rosedale Plaza'!G15+'Mani Square Mall'!G15+'Forum Rangoli'!G15+CSC!G15+Jameslong!G15+Technopolis!G15+Santoshpur!G15+'Chinar Park'!G15+'Lake Road'!G15+Kalikapur!G15+'Event Sales'!G15+'Sector 1'!G15 -> 895687.64 | I16: ='Ideal Plaza'!H15+'Salt Lake JC -21'!H15+'Forum Mall'!H15+'Lake Town'!H15+'Quest Mall'!H15+'Rosedale Plaza'!H15+'Mani Square Mall'!H15+'Forum Rangoli'!H15+CSC!H15+Jameslong!H15+Technopolis!H15+Santoshpur!H15+'Chinar Park'!H15+'Lake Road'!H15+Kalikapur!H15+'Event Sales'!H15+'Sector 1'!H15 -> 0 | J16: ='Ideal Plaza'!I15+'Salt Lake JC -21'!I15+'Forum Mall'!I15+'Lake Town'!I15+'Quest Mall'!I15+'Rosedale Plaza'!I15+'Mani Square Mall'!I15+'Forum Rangoli'!I15+CSC!I15+Jameslong!I15+Technopolis!I15+Santoshpur!I15+'Chinar Park'!I15+'Lake Road'!I15+Kalikapur!I15+'Event Sales'!I15+'Sector 1'!I15 -> 0 | K16: ='Ideal Plaza'!J15+'Salt Lake JC -21'!J15+'Forum Mall'!J15+'Lake Town'!J15+'Quest Mall'!J15+'Rosedale Plaza'!J15+'Mani Square Mall'!J15+'Forum Rangoli'!J15+CSC!J15+Jameslong!J15+Technopolis!J15+Santoshpur!J15+'Chinar Park'!J15+'Lake Road'!J15+Kalikapur!J15+'Event Sales'!J15+'Sector 1'!J15 -> 0 | ... N16: ='Ideal Plaza'!M15+'Salt Lake JC -21'!M15+'Forum Mall'!M15+'Lake Town'!M15+'Quest Mall'!M15+'Rosedale Plaza'!M15+'Mani Square Mall'!M15+'Forum Rangoli'!M15+CSC!M15+Jameslong!M15+Technopolis!M15+Santoshpur!M15+'Chinar Park'!M15+'Lake Road'!M15+Kalikapur!M15+'Event Sales'!M15+'Sector 1'!M15 -> 0 | O16: =sum(C16:N16) -> 5495838.2 | P16: =O16/$O$14 -> 0.041300895
A17: Telephone/Internet | B17: Operation | C17: ='Ideal Plaza'!B16+'Salt Lake JC -21'!B16+'Forum Mall'!B16+'Lake Town'!B16+'Quest Mall'!B16+'Rosedale Plaza'!B16+'Mani Square Mall'!B16+'Forum Rangoli'!B16+CSC!B16+Jameslong!B16+Technopolis!B16+Santoshpur!B16+'Chinar Park'!B16+'Lake Road'!B16+Kalikapur!B16+'Event Sales'!B16+'Sector 1'!B16 -> 13456.93 | D17: ='Ideal Plaza'!C16+'Salt Lake JC -21'!C16+'Forum Mall'!C16+'Lake Town'!C16+'Quest Mall'!C16+'Rosedale Plaza'!C16+'Mani Square Mall'!C16+'Forum Rangoli'!C16+CSC!C16+Jameslong!C16+Technopolis!C16+Santoshpur!C16+'Chinar Park'!C16+'Lake Road'!C16+Kalikapur!C16+'Event Sales'!C16+'Sector 1'!C16 -> 13956.93 | E17: ='Ideal Plaza'!D16+'Salt Lake JC -21'!D16+'Forum Mall'!D16+'Lake Town'!D16+'Quest Mall'!D16+'Rosedale Plaza'!D16+'Mani Square Mall'!D16+'Forum Rangoli'!D16+CSC!D16+Jameslong!D16+Technopolis!D16+Santoshpur!D16+'Chinar Park'!D16+'Lake Road'!D16+Kalikapur!D16+'Event Sales'!D16+'Sector 1'!D16 -> 13956.93 | F17: ='Ideal Plaza'!E16+'Salt Lake JC -21'!E16+'Forum Mall'!E16+'Lake Town'!E16+'Quest Mall'!E16+'Rosedale Plaza'!E16+'Mani Square Mall'!E16+'Forum Rangoli'!E16+CSC!E16+Jameslong!E16+Technopolis!E16+Santoshpur!E16+'Chinar Park'!E16+'Lake Road'!E16+Kalikapur!E16+'Event Sales'!E16+'Sector 1'!E16 -> 14315.263 | G17: ='Ideal Plaza'!F16+'Salt Lake JC -21'!F16+'Forum Mall'!F16+'Lake Town'!F16+'Quest Mall'!F16+'Rosedale Plaza'!F16+'Mani Square Mall'!F16+'Forum Rangoli'!F16+CSC!F16+Jameslong!F16+Technopolis!F16+Santoshpur!F16+'Chinar Park'!F16+'Lake Road'!F16+Kalikapur!F16+'Event Sales'!F16+'Sector 1'!F16 -> 12052.443 | H17: ='Ideal Plaza'!G16+'Salt Lake JC -21'!G16+'Forum Mall'!G16+'Lake Town'!G16+'Quest Mall'!G16+'Rosedale Plaza'!G16+'Mani Square Mall'!G16+'Forum Rangoli'!G16+CSC!G16+Jameslong!G16+Technopolis!G16+Santoshpur!G16+'Chinar Park'!G16+'Lake Road'!G16+Kalikapur!G16+'Event Sales'!G16+'Sector 1'!G16 -> 11849.443 | I17: ='Ideal Plaza'!H16+'Salt Lake JC -21'!H16+'Forum Mall'!H16+'Lake Town'!H16+'Quest Mall'!H16+'Rosedale Plaza'!H16+'Mani Square Mall'!H16+'Forum Rangoli'!H16+CSC!H16+Jameslong!H16+Technopolis!H16+Santoshpur!H16+'Chinar Park'!H16+'Lake Road'!H16+Kalikapur!H16+'Event Sales'!H16+'Sector 1'!H16 -> 948.33333 | J17: ='Ideal Plaza'!I16+'Salt Lake JC -21'!I16+'Forum Mall'!I16+'Lake Town'!I16+'Quest Mall'!I16+'Rosedale Plaza'!I16+'Mani Square Mall'!I16+'Forum Rangoli'!I16+CSC!I16+Jameslong!I16+Technopolis!I16+Santoshpur!I16+'Chinar Park'!H16+'Lake Road'!I16+Kalikapur!I16+'Event Sales'!I16+'Sector 1'!I16 -> 948.33333 | K17: ='Ideal Plaza'!J16+'Salt Lake JC -21'!J16+'Forum Mall'!J16+'Lake Town'!J16+'Quest Mall'!J16+'Rosedale Plaza'!J16+'Mani Square Mall'!J16+'Forum Rangoli'!J16+CSC!J16+Jameslong!J16+Technopolis!J16+Santoshpur!J16+'Chinar Park'!J16+'Lake Road'!J16+Kalikapur!J16+'Event Sales'!J16+'Sector 1'!J16 -> 948.33333 | L17: ='Ideal Plaza'!K16+'Salt Lake JC -21'!K16+'Forum Mall'!K16+'Lake Town'!K16+'Quest Mall'!K16+'Rosedale Plaza'!K16+'Mani Square Mall'!K16+'Forum Rangoli'!K16+CSC!K16+Jameslong!K16+Technopolis!K16+Santoshpur!K16+'Chinar Park'!K16+'Lake Road'!K16+Kalikapur!K16+'Event Sales'!K16+'Sector 1'!K16 -> 948.33333 | M17: ='Ideal Plaza'!L16+'Salt Lake JC -21'!L16+'Forum Mall'!L16+'Lake Town'!L16+'Quest Mall'!L16+'Rosedale Plaza'!L16+'Mani Square Mall'!L16+'Forum Rangoli'!L16+CSC!L16+Jameslong!L16+Technopolis!L16+Santoshpur!L16+'Chinar Park'!L16+'Lake Road'!L16+Kalikapur!L16+'Event Sales'!L16+'Sector 1'!L16 -> 948.33333 | N17: ='Ideal Plaza'!M16+'Salt Lake JC -21'!M16+'Forum Mall'!M16+'Lake Town'!M16+'Quest Mall'!M16+'Rosedale Plaza'!M16+'Mani Square Mall'!M16+'Forum Rangoli'!M16+CSC!M16+Jameslong!M16+Technopolis!M16+Santoshpur!M16+'Chinar Park'!M16+'Lake Road'!M16+Kalikapur!M16+'Event Sales'!M16+'Sector 1'!M16 -> 948.33333 | O17: =sum(C17:N17) -> 85277.94 | P17: =O17/$O$14 -> 0.00064085861
A18: Gas | B18: Operation | C18: ='Ideal Plaza'!B17+'Salt Lake JC -21'!B17+'Forum Mall'!B17+'Lake Town'!B17+'Quest Mall'!B17+'Rosedale Plaza'!B17+'Mani Square Mall'!B17+'Forum Rangoli'!B17+CSC!B17+Jameslong!B17+Technopolis!B17+Santoshpur!B17+'Chinar Park'!B17+'Lake Road'!B17+Kalikapur!B17+'Event Sales'!B17+'Sector 1'!B17 -> 238567 | D18: ='Ideal Plaza'!C17+'Salt Lake JC -21'!C17+'Forum Mall'!C17+'Lake Town'!C17+'Quest Mall'!C17+'Rosedale Plaza'!C17+'Mani Square Mall'!C17+'Forum Rangoli'!C17+CSC!C17+Jameslong!C17+Technopolis!C17+Santoshpur!C17+'Chinar Park'!C17+'Lake Road'!C17+Kalikapur!C17+'Event Sales'!C17+'Sector 1'!C17 -> 654017.84 | E18: ='Ideal Plaza'!D17+'Salt Lake JC -21'!D17+'Forum Mall'!D17+'Lake Town'!D17+'Quest Mall'!D17+'Rosedale Plaza'!D17+'Mani Square Mall'!D17+'Forum Rangoli'!D17+CSC!D17+Jameslong!D17+Technopolis!D17+Santoshpur!D17+'Chinar Park'!D17+'Lake Road'!D17+Kalikapur!D17+'Event Sales'!D17+'Sector 1'!D17 -> 643074.78 | F18: ='Ideal Plaza'!E17+'Salt Lake JC -21'!E17+'Forum Mall'!E17+'Lake Town'!E17+'Quest Mall'!E17+'Rosedale Plaza'!E17+'Mani Square Mall'!E17+'Forum Rangoli'!E17+CSC!E17+Jameslong!E17+Technopolis!E17+Santoshpur!E17+'Chinar Park'!E17+'Lake Road'!E17+Kalikapur!E17+'Event Sales'!E17+'Sector 1'!E17 -> 676849 | G18: ='Ideal Plaza'!F17+'Salt Lake JC -21'!F17+'Forum Mall'!F17+'Lake Town'!F17+'Quest Mall'!F17+'Rosedale Plaza'!F17+'Mani Square Mall'!F17+'Forum Rangoli'!F17+CSC!F17+Jameslong!F17+Technopolis!F17+Santoshpur!F17+'Chinar Park'!F17+'Lake Road'!F17+Kalikapur!F17+'Event Sales'!F17+'Sector 1'!F17 -> 603302.5 | H18: ='Ideal Plaza'!G17+'Salt Lake JC -21'!G17+'Forum Mall'!G17+'Lake Town'!G17+'Quest Mall'!G17+'Rosedale Plaza'!G17+'Mani Square Mall'!G17+'Forum Rangoli'!G17+CSC!G17+Jameslong!G17+Technopolis!G17+Santoshpur!G17+'Chinar Park'!G17+'Lake Road'!G17+Kalikapur!G17+'Event Sales'!G17+'Sector 1'!G17 -> 588948 | I18: ='Ideal Plaza'!H17+'Salt Lake JC -21'!H17+'Forum Mall'!H17+'Lake Town'!H17+'Quest Mall'!H17+'Rosedale Plaza'!H17+'Mani Square Mall'!H17+'Forum Rangoli'!H17+CSC!H17+Jameslong!H17+Technopolis!H17+Santoshpur!H17+'Chinar Park'!H17+'Lake Road'!H17+Kalikapur!H17+'Event Sales'!H17+'Sector 1'!H17 -> 0 | J18: ='Ideal Plaza'!I17+'Salt Lake JC -21'!I17+'Forum Mall'!I17+'Lake Town'!I17+'Quest Mall'!I17+'Rosedale Plaza'!I17+'Mani Square Mall'!I17+'Forum Rangoli'!I17+CSC!I17+Jameslong!I17+Technopolis!I17+Santoshpur!I17+'Chinar Park'!I17+'Lake Road'!I17+Kalikapur!I17+'Event Sales'!I17+'Sector 1'!I17 -> 0 | ... N18: ='Ideal Plaza'!M17+'Salt Lake JC -21'!M17+'Forum Mall'!M17+'Lake Town'!M17+'Quest Mall'!M17+'Rosedale Plaza'!M17+'Mani Square Mall'!M17+'Forum Rangoli'!M17+CSC!M17+Jameslong!M17+Technopolis!M17+Santoshpur!M17+'Chinar Park'!M17+'Lake Road'!M17+Kalikapur!M17+'Event Sales'!M17+'Sector 1'!M17 -> 0 | O18: =sum(C18:N18) -> 3404759.1 | P18: =O18/$O$14 -> 0.025586561
A19: Rent & Revenue Share | B19: Accounts | C19: ='Ideal Plaza'!B18+'Salt Lake JC -21'!B18+'Forum Mall'!B18+'Lake Town'!B18+'Quest Mall'!B18+'Rosedale Plaza'!B18+'Mani Square Mall'!B18+'Forum Rangoli'!B18+CSC!B18+Jameslong!B18+Technopolis!B18+Santoshpur!B18+'Chinar Park'!B18+'Lake Road'!B18+Kalikapur!B18+'Event Sales'!B18+'Sector 1'!B18 -> 2187486.8 | D19: ='Ideal Plaza'!C18+'Salt Lake JC -21'!C18+'Forum Mall'!C18+'Lake Town'!C18+'Quest Mall'!C18+'Rosedale Plaza'!C18+'Mani Square Mall'!C18+'Forum Rangoli'!C18+CSC!C18+Jameslong!C18+Technopolis!C18+Santoshpur!C18+'Chinar Park'!C18+'Lake Road'!C18+Kalikapur!C18+'Event Sales'!C18+'Sector 1'!C18 -> 2326525.1 | E19: ='Ideal Plaza'!D18+'Salt Lake JC -21'!D18+'Forum Mall'!D18+'Lake Town'!D18+'Quest Mall'!D18+'Rosedale Plaza'!D18+'Mani Square Mall'!D18+'Forum Rangoli'!D18+CSC!D18+Jameslong!D18+Technopolis!D18+Santoshpur!D18+'Chinar Park'!D18+'Lake Road'!D18+Kalikapur!D18+'Event Sales'!D18+'Sector 1'!D18 -> 2320904 | F19: ='Ideal Plaza'!E18+'Salt Lake JC -21'!E18+'Forum Mall'!E18+'Lake Town'!E18+'Quest Mall'!E18+'Rosedale Plaza'!E18+'Mani Square Mall'!E18+'Forum Rangoli'!E18+CSC!E18+Jameslong!E18+Technopolis!E18+Santoshpur!E18+'Chinar Park'!E18+'Lake Road'!E18+Kalikapur!E18+'Event Sales'!E18+'Sector 1'!E18 -> 2364561 | G19: ='Ideal Plaza'!F18+'Salt Lake JC -21'!F18+'Forum Mall'!F18+'Lake Town'!F18+'Quest Mall'!F18+'Rosedale Plaza'!F18+'Mani Square Mall'!F18+'Forum Rangoli'!F18+CSC!F18+Jameslong!F18+Technopolis!F18+Santoshpur!F18+'Chinar Park'!F18+'Lake Road'!F18+Kalikapur!F18+'Event Sales'!F18+'Sector 1'!F18 -> 2473572 | H19: ='Ideal Plaza'!G18+'Salt Lake JC -21'!G18+'Forum Mall'!G18+'Lake Town'!G18+'Quest Mall'!G18+'Rosedale Plaza'!G18+'Mani Square Mall'!G18+'Forum Rangoli'!G18+CSC!G18+Jameslong!G18+Technopolis!G18+Santoshpur!G18+'Chinar Park'!G18+'Lake Road'!G18+Kalikapur!G18+'Event Sales'!G18+'Sector 1'!G18 -> 2367593 | I19: ='Ideal Plaza'!H18+'Salt Lake JC -21'!H18+'Forum Mall'!H18+'Lake Town'!H18+'Quest Mall'!H18+'Rosedale Plaza'!H18+'Mani Square Mall'!H18+'Forum Rangoli'!H18+CSC!H18+Jameslong!H18+Technopolis!H18+Santoshpur!H18+'Chinar Park'!H18+'Lake Road'!H18+Kalikapur!H18+'Event Sales'!H18+'Sector 1'!H18 -> 0 | J19: ='Ideal Plaza'!I18+'Salt Lake JC -21'!I18+'Forum Mall'!I18+'Lake Town'!I18+'Quest Mall'!I18+'Rosedale Plaza'!I18+'Mani Square Mall'!I18+'Forum Rangoli'!I18+CSC!I18+Jameslong!I18+Technopolis!I18+Santoshpur!I18+'Chinar Park'!I18+'Lake Road'!I18+Kalikapur!I18+'Event Sales'!I18+'Sector 1'!I18 -> 0 | ... N19: ='Ideal Plaza'!M18+'Salt Lake JC -21'!M18+'Forum Mall'!M18+'Lake Town'!M18+'Quest Mall'!M18+'Rosedale Plaza'!M18+'Mani Square Mall'!M18+'Forum Rangoli'!M18+CSC!M18+Jameslong!M18+Technopolis!M18+Santoshpur!M18+'Chinar Park'!M18+'Lake Road'!M18+Kalikapur!M18+'Event Sales'!M18+'Sector 1'!M18 -> 0 | O19: =sum(C19:N19) -> 14040642 | P19: =O19/$O$14 -> 0.10551458
A20: Software | B20: Operation | C20: ='Ideal Plaza'!B19+'Salt Lake JC -21'!B19+'Forum Mall'!B19+'Lake Town'!B19+'Quest Mall'!B19+'Rosedale Plaza'!B19+'Mani Square Mall'!B19+'Forum Rangoli'!B19+CSC!B19+Jameslong!B19+Technopolis!B19+Santoshpur!B19+'Chinar Park'!B19+'Lake Road'!B19+Kalikapur!B19+'Event Sales'!B19+'Sector 1'!B19 -> 72993.57 | D20: ='Ideal Plaza'!C19+'Salt Lake JC -21'!C19+'Forum Mall'!C19+'Lake Town'!C19+'Quest Mall'!C19+'Rosedale Plaza'!C19+'Mani Square Mall'!C19+'Forum Rangoli'!C19+CSC!C19+Jameslong!C19+Technopolis!C19+Santoshpur!C19+'Chinar Park'!C19+'Lake Road'!C19+Kalikapur!C19+'Event Sales'!C19+'Sector 1'!C19 -> 72993.57 | E20: ='Ideal Plaza'!D19+'Salt Lake JC -21'!D19+'Forum Mall'!D19+'Lake Town'!D19+'Quest Mall'!D19+'Rosedale Plaza'!D19+'Mani Square Mall'!D19+'Forum Rangoli'!D19+CSC!D19+Jameslong!D19+Technopolis!D19+Santoshpur!D19+'Chinar Park'!D19+'Lake Road'!D19+Kalikapur!D19+'Event Sales'!D19+'Sector 1'!D19 -> 72993.57 | F20: ='Ideal Plaza'!E19+'Salt Lake JC -21'!E19+'Forum Mall'!E19+'Lake Town'!E19+'Quest Mall'!E19+'Rosedale Plaza'!E19+'Mani Square Mall'!E19+'Forum Rangoli'!E19+CSC!E19+Jameslong!E19+Technopolis!E19+Santoshpur!E19+'Chinar Park'!E19+'Lake Road'!E19+Kalikapur!E19+'Event Sales'!E19+'Sector 1'!E19 -> 72993.57 | G20: ='Ideal Plaza'!F19+'Salt Lake JC -21'!F19+'Forum Mall'!F19+'Lake Town'!F19+'Quest Mall'!F19+'Rosedale Plaza'!F19+'Mani Square Mall'!F19+'Forum Rangoli'!F19+CSC!F19+Jameslong!F19+Technopolis!F19+Santoshpur!F19+'Chinar Park'!F19+'Lake Road'!F19+Kalikapur!F19+'Event Sales'!F19+'Sector 1'!F19 -> 73035.07 | H20: ='Ideal Plaza'!G19+'Salt Lake JC -21'!G19+'Forum Mall'!G19+'Lake Town'!G19+'Quest Mall'!G19+'Rosedale Plaza'!G19+'Mani Square Mall'!G19+'Forum Rangoli'!G19+CSC!G19+Jameslong!G19+Technopolis!G19+Santoshpur!G19+'Chinar Park'!G19+'Lake Road'!G19+Kalikapur!G19+'Event Sales'!G19+'Sector 1'!G19 -> 73035.07 | I20: ='Ideal Plaza'!H19+'Salt Lake JC -21'!H19+'Forum Mall'!H19+'Lake Town'!H19+'Quest Mall'!H19+'Rosedale Plaza'!H19+'Mani Square Mall'!H19+'Forum Rangoli'!H19+CSC!H19+Jameslong!H19+Technopolis!H19+Santoshpur!H19+'Chinar Park'!H19+'Lake Road'!H19+Kalikapur!H19+'Event Sales'!H19+'Sector 1'!H19 -> 11534.5 | J20: ='Ideal Plaza'!I19+'Salt Lake JC -21'!I19+'Forum Mall'!I19+'Lake Town'!I19+'Quest Mall'!I19+'Rosedale Plaza'!I19+'Mani Square Mall'!I19+'Forum Rangoli'!I19+CSC!I19+Jameslong!I19+Technopolis!I19+Santoshpur!I19+'Chinar Park'!I19+'Lake Road'!I19+Kalikapur!I19+'Event Sales'!I19+'Sector 1'!I19 -> 11534.5 | ... N20: ='Ideal Plaza'!M19+'Salt Lake JC -21'!M19+'Forum Mall'!M19+'Lake Town'!M19+'Quest Mall'!M19+'Rosedale Plaza'!M19+'Mani Square Mall'!M19+'Forum Rangoli'!M19+CSC!M19+Jameslong!M19+Technopolis!M19+Santoshpur!M19+'Chinar Park'!M19+'Lake Road'!M19+Kalikapur!M19+'Event Sales'!M19+'Sector 1'!M19 -> 11534.5 | O20: =sum(C20:N20) -> 507251.42 | P20: =O20/$O$14 -> 0.003811964
A21: Staff Salary | B21: HR | C21: ='Ideal Plaza'!B20+'Salt Lake JC -21'!B20+'Forum Mall'!B20+'Lake Town'!B20+'Quest Mall'!B20+'Rosedale Plaza'!B20+'Mani Square Mall'!B20+'Forum Rangoli'!B20+CSC!B20+Jameslong!B20+Technopolis!B20+Santoshpur!B20+'Chinar Park'!B20+'Lake Road'!B20+Kalikapur!B20+'Event Sales'!B20+'Sector 1'!B20 -> 3298909 | D21: ='Ideal Plaza'!C20+'Salt Lake JC -21'!C20+'Forum Mall'!C20+'Lake Town'!C20+'Quest Mall'!C20+'Rosedale Plaza'!C20+'Mani Square Mall'!C20+'Forum Rangoli'!C20+CSC!C20+Jameslong!C20+Technopolis!C20+Santoshpur!C20+'Chinar Park'!C20+'Lake Road'!C20+Kalikapur!C20+'Event Sales'!C20+'Sector 1'!C20 -> 3578266 | E21: ='Ideal Plaza'!D20+'Salt Lake JC -21'!D20+'Forum Mall'!D20+'Lake Town'!D20+'Quest Mall'!D20+'Rosedale Plaza'!D20+'Mani Square Mall'!D20+'Forum Rangoli'!D20+CSC!D20+Jameslong!D20+Technopolis!D20+Santoshpur!D20+'Chinar Park'!D20+'Lake Road'!D20+Kalikapur!D20+'Event Sales'!D20+'Sector 1'!D20 -> 3621953.4 | F21: ='Ideal Plaza'!E20+'Salt Lake JC -21'!E20+'Forum Mall'!E20+'Lake Town'!E20+'Quest Mall'!E20+'Rosedale Plaza'!E20+'Mani Square Mall'!E20+'Forum Rangoli'!E20+CSC!E20+Jameslong!E20+Technopolis!E20+Santoshpur!E20+'Chinar Park'!E20+'Lake Road'!E20+Kalikapur!E20+'Event Sales'!E20+'Sector 1'!E20 -> 3670111.9 | G21: ='Ideal Plaza'!F20+'Salt Lake JC -21'!F20+'Forum Mall'!F20+'Lake Town'!F20+'Quest Mall'!F20+'Rosedale Plaza'!F20+'Mani Square Mall'!F20+'Forum Rangoli'!F20+CSC!F20+Jameslong!F20+Technopolis!F20+Santoshpur!F20+'Chinar Park'!F20+'Lake Road'!F20+Kalikapur!F20+'Event Sales'!F20+'Sector 1'!F20 -> 3488719 | H21: ='Ideal Plaza'!G20+'Salt Lake JC -21'!G20+'Forum Mall'!G20+'Lake Town'!G20+'Quest Mall'!G20+'Rosedale Plaza'!G20+'Mani Square Mall'!G20+'Forum Rangoli'!G20+CSC!G20+Jameslong!G20+Technopolis!G20+Santoshpur!G20+'Chinar Park'!G20+'Lake Road'!G20+Kalikapur!G20+'Event Sales'!G20+'Sector 1'!G20 -> 3541701 | I21: ='Ideal Plaza'!H20+'Salt Lake JC -21'!H20+'Forum Mall'!H20+'Lake Town'!H20+'Quest Mall'!H20+'Rosedale Plaza'!H20+'Mani Square Mall'!H20+'Forum Rangoli'!H20+CSC!H20+Jameslong!H20+Technopolis!H20+Santoshpur!H20+'Chinar Park'!H20+'Lake Road'!H20+Kalikapur!H20+'Event Sales'!H20+'Sector 1'!H20 -> 0 | J21: ='Ideal Plaza'!I20+'Salt Lake JC -21'!I20+'Forum Mall'!I20+'Lake Town'!I20+'Quest Mall'!I20+'Rosedale Plaza'!I20+'Mani Square Mall'!I20+'Forum Rangoli'!I20+CSC!I20+Jameslong!I20+Technopolis!I20+Santoshpur!I20+'Chinar Park'!I20+'Lake Road'!I20+Kalikapur!I20+'Event Sales'!I20+'Sector 1'!I20 -> 0 | ... N21: ='Ideal Plaza'!M20+'Salt Lake JC -21'!M20+'Forum Mall'!M20+'Lake Town'!M20+'Quest Mall'!M20+'Rosedale Plaza'!M20+'Mani Square Mall'!M20+'Forum Rangoli'!M20+CSC!M20+Jameslong!M20+Technopolis!M20+Santoshpur!M20+'Chinar Park'!M20+'Lake Road'!M20+Kalikapur!M20+'Event Sales'!M20+'Sector 1'!M20 -> 0 | O21: =sum(C21:N21) -> 21199660 | P21: =O21/$O$14 -> 0.15931418
A22: AMC | B22: Operation | C22: ='Ideal Plaza'!B21+'Salt Lake JC -21'!B21+'Forum Mall'!B21+'Lake Town'!B21+'Quest Mall'!B21+'Rosedale Plaza'!B21+'Mani Square Mall'!B21+'Forum Rangoli'!B21+CSC!B21+Jameslong!B21+Technopolis!B21+Santoshpur!B21+'Chinar Park'!B21+'Lake Road'!B21+Kalikapur!B21+'Event Sales'!B21+'Sector 1'!B21 -> 125462 | D22: ='Ideal Plaza'!C21+'Salt Lake JC -21'!C21+'Forum Mall'!C21+'Lake Town'!C21+'Quest Mall'!C21+'Rosedale Plaza'!C21+'Mani Square Mall'!C21+'Forum Rangoli'!C21+CSC!C21+Jameslong!C21+Technopolis!C21+Santoshpur!C21+'Chinar Park'!C21+'Lake Road'!C21+Kalikapur!C21+'Event Sales'!C21+'Sector 1'!C21 -> 136575 | E22: ='Ideal Plaza'!D21+'Salt Lake JC -21'!D21+'Forum Mall'!D21+'Lake Town'!D21+'Quest Mall'!D21+'Rosedale Plaza'!D21+'Mani Square Mall'!D21+'Forum Rangoli'!D21+CSC!D21+Jameslong!D21+Technopolis!D21+Santoshpur!D21+'Chinar Park'!D21+'Lake Road'!D21+Kalikapur!D21+'Event Sales'!D21+'Sector 1'!D21 -> 128253 | F22: ='Ideal Plaza'!E21+'Salt Lake JC -21'!E21+'Forum Mall'!E21+'Lake Town'!E21+'Quest Mall'!E21+'Rosedale Plaza'!E21+'Mani Square Mall'!E21+'Forum Rangoli'!E21+CSC!E21+Jameslong!E21+Technopolis!E21+Santoshpur!E21+'Chinar Park'!E21+'Lake Road'!E21+Kalikapur!E21+'Event Sales'!E21+'Sector 1'!E21 -> 124135 | G22: ='Ideal Plaza'!F21+'Salt Lake JC -21'!F21+'Forum Mall'!F21+'Lake Town'!F21+'Quest Mall'!F21+'Rosedale Plaza'!F21+'Mani Square Mall'!F21+'Forum Rangoli'!F21+CSC!F21+Jameslong!F21+Technopolis!F21+Santoshpur!F21+'Chinar Park'!F21+'Lake Road'!F21+Kalikapur!F21+'Event Sales'!F21+'Sector 1'!F21 -> 130632 | H22: ='Ideal Plaza'!G21+'Salt Lake JC -21'!G21+'Forum Mall'!G21+'Lake Town'!G21+'Quest Mall'!G21+'Rosedale Plaza'!G21+'Mani Square Mall'!G21+'Forum Rangoli'!G21+CSC!G21+Jameslong!G21+Technopolis!G21+Santoshpur!G21+'Chinar Park'!G21+'Lake Road'!G21+Kalikapur!G21+'Event Sales'!G21+'Sector 1'!G21 -> 130632 | I22: ='Ideal Plaza'!H21+'Salt Lake JC -21'!H21+'Forum Mall'!H21+'Lake Town'!H21+'Quest Mall'!H21+'Rosedale Plaza'!H21+'Mani Square Mall'!H21+'Forum Rangoli'!H21+CSC!H21+Jameslong!H21+Technopolis!H21+Santoshpur!H21+'Chinar Park'!H21+'Lake Road'!H21+Kalikapur!H21+'Event Sales'!H21+'Sector 1'!H21 -> 0 | J22: ='Ideal Plaza'!I21+'Salt Lake JC -21'!I21+'Forum Mall'!I21+'Lake Town'!I21+'Quest Mall'!I21+'Rosedale Plaza'!I21+'Mani Square Mall'!I21+'Forum Rangoli'!I21+CSC!I21+Jameslong!I21+Technopolis!I21+Santoshpur!I21+'Chinar Park'!I21+'Lake Road'!I21+Kalikapur!I21+'Event Sales'!I21+'Sector 1'!I21 -> 0 | ... N22: ='Ideal Plaza'!M21+'Salt Lake JC -21'!M21+'Forum Mall'!M21+'Lake Town'!M21+'Quest Mall'!M21+'Rosedale Plaza'!M21+'Mani Square Mall'!M21+'Forum Rangoli'!M21+CSC!M21+Jameslong!M21+Technopolis!M21+Santoshpur!M21+'Chinar Park'!M21+'Lake Road'!M21+Kalikapur!M21+'Event Sales'!M21+'Sector 1'!M21 -> 0 | O22: =sum(C22:N22) -> 775689 | P22: =O22/$O$14 -> 0.0058292564
A23: Subscription | B23: Operation | C23: ='Ideal Plaza'!B22+'Salt Lake JC -21'!B22+'Forum Mall'!B22+'Lake Town'!B22+'Quest Mall'!B22+'Rosedale Plaza'!B22+'Mani Square Mall'!B22+'Forum Rangoli'!B22+CSC!B22+Jameslong!B22+Technopolis!B22+Santoshpur!B22+'Chinar Park'!B22+'Lake Road'!B22+Kalikapur!B22+'Event Sales'!B22+'Sector 1'!B22 -> 50296.36 | D23: ='Ideal Plaza'!C22+'Salt Lake JC -21'!C22+'Forum Mall'!C22+'Lake Town'!C22+'Quest Mall'!C22+'Rosedale Plaza'!C22+'Mani Square Mall'!C22+'Forum Rangoli'!C22+CSC!C22+Jameslong!C22+Technopolis!C22+Santoshpur!C22+'Chinar Park'!C22+'Lake Road'!C22+Kalikapur!C22+'Event Sales'!C22+'Sector 1'!C22 -> 50296.36 | E23: ='Ideal Plaza'!D22+'Salt Lake JC -21'!D22+'Forum Mall'!D22+'Lake Town'!D22+'Quest Mall'!D22+'Rosedale Plaza'!D22+'Mani Square Mall'!D22+'Forum Rangoli'!D22+CSC!D22+Jameslong!D22+Technopolis!D22+Santoshpur!D22+'Chinar Park'!D22+'Lake Road'!D22+Kalikapur!D22+'Event Sales'!D22+'Sector 1'!D22 -> 50296.36 | F23: ='Ideal Plaza'!E22+'Salt Lake JC -21'!E22+'Forum Mall'!E22+'Lake Town'!E22+'Quest Mall'!E22+'Rosedale Plaza'!E22+'Mani Square Mall'!E22+'Forum Rangoli'!E22+CSC!E22+Jameslong!E22+Technopolis!E22+Santoshpur!E22+'Chinar Park'!E22+'Lake Road'!E22+Kalikapur!E22+'Event Sales'!E22+'Sector 1'!E22 -> 50296.36 | G23: ='Ideal Plaza'!F22+'Salt Lake JC -21'!F22+'Forum Mall'!F22+'Lake Town'!F22+'Quest Mall'!F22+'Rosedale Plaza'!F22+'Mani Square Mall'!F22+'Forum Rangoli'!F22+CSC!F22+Jameslong!F22+Technopolis!F22+Santoshpur!F22+'Chinar Park'!F22+'Lake Road'!F22+Kalikapur!F22+'Event Sales'!F22+'Sector 1'!F22 -> 50296.36 | H23: ='Ideal Plaza'!G22+'Salt Lake JC -21'!G22+'Forum Mall'!G22+'Lake Town'!G22+'Quest Mall'!G22+'Rosedale Plaza'!G22+'Mani Square Mall'!G22+'Forum Rangoli'!G22+CSC!G22+Jameslong!G22+Technopolis!G22+Santoshpur!G22+'Chinar Park'!G22+'Lake Road'!G22+Kalikapur!G22+'Event Sales'!G22+'Sector 1'!G22 -> 50296.36 | I23: ='Ideal Plaza'!H22+'Salt Lake JC -21'!H22+'Forum Mall'!H22+'Lake Town'!H22+'Quest Mall'!H22+'Rosedale Plaza'!H22+'Mani Square Mall'!H22+'Forum Rangoli'!H22+CSC!H22+Jameslong!H22+Technopolis!H22+Santoshpur!H22+'Chinar Park'!H22+'Lake Road'!H22+Kalikapur!H22+'Event Sales'!H22+'Sector 1'!H22 -> 18919.16 | J23: ='Ideal Plaza'!I22+'Salt Lake JC -21'!I22+'Forum Mall'!I22+'Lake Town'!I22+'Quest Mall'!I22+'Rosedale Plaza'!I22+'Mani Square Mall'!I22+'Forum Rangoli'!I22+CSC!I22+Jameslong!I22+Technopolis!I22+Santoshpur!I22+'Chinar Park'!I22+'Lake Road'!I22+Kalikapur!I22+'Event Sales'!I22+'Sector 1'!I22 -> 17490.44 | ... N23: ='Ideal Plaza'!M22+'Salt Lake JC -21'!M22+'Forum Mall'!M22+'Lake Town'!M22+'Quest Mall'!M22+'Rosedale Plaza'!M22+'Mani Square Mall'!M22+'Forum Rangoli'!M22+CSC!M22+Jameslong!M22+Technopolis!M22+Santoshpur!M22+'Chinar Park'!M22+'Lake Road'!M22+Kalikapur!M22+'Event Sales'!M22+'Sector 1'!M22 -> 17490.44 | O23: =sum(C23:N23) -> 408149.52 | P23: =O23/$O$14 -> 0.0030672192
A24: Insurance | B24: Development | C24: ='Ideal Plaza'!B23+'Salt Lake JC -21'!B23+'Forum Mall'!B23+'Lake Town'!B23+'Quest Mall'!B23+'Rosedale Plaza'!B23+'Mani Square Mall'!B23+'Forum Rangoli'!B23+CSC!B23+Jameslong!B23+Technopolis!B23+Santoshpur!B23+'Chinar Park'!B23+'Lake Road'!B23+Kalikapur!B23+'Event Sales'!B23+'Sector 1'!B23 -> 14966.188 | D24: ='Ideal Plaza'!C23+'Salt Lake JC -21'!C23+'Forum Mall'!C23+'Lake Town'!C23+'Quest Mall'!C23+'Rosedale Plaza'!C23+'Mani Square Mall'!C23+'Forum Rangoli'!C23+CSC!C23+Jameslong!C23+Technopolis!C23+Santoshpur!C23+'Chinar Park'!C23+'Lake Road'!C23+Kalikapur!C23+'Event Sales'!C23+'Sector 1'!C23 -> 25502.658 | E24: ='Ideal Plaza'!D23+'Salt Lake JC -21'!D23+'Forum Mall'!D23+'Lake Town'!D23+'Quest Mall'!D23+'Rosedale Plaza'!D23+'Mani Square Mall'!D23+'Forum Rangoli'!D23+CSC!D23+Jameslong!D23+Technopolis!D23+Santoshpur!D23+'Chinar Park'!D23+'Lake Road'!D23+Kalikapur!D23+'Event Sales'!D23+'Sector 1'!D23 -> 25502.658 | F24: ='Ideal Plaza'!E23+'Salt Lake JC -21'!E23+'Forum Mall'!E23+'Lake Town'!E23+'Quest Mall'!E23+'Rosedale Plaza'!E23+'Mani Square Mall'!E23+'Forum Rangoli'!E23+CSC!E23+Jameslong!E23+Technopolis!E23+Santoshpur!E23+'Chinar Park'!E23+'Lake Road'!E23+Kalikapur!E23+'Event Sales'!E23+'Sector 1'!E23 -> 25502.658 | G24: ='Ideal Plaza'!F23+'Salt Lake JC -21'!F23+'Forum Mall'!F23+'Lake Town'!F23+'Quest Mall'!F23+'Rosedale Plaza'!F23+'Mani Square Mall'!F23+'Forum Rangoli'!F23+CSC!F23+Jameslong!F23+Technopolis!F23+Santoshpur!F23+'Chinar Park'!F23+'Lake Road'!F23+Kalikapur!F23+'Event Sales'!F23+'Sector 1'!F23 -> 25502.658 | H24: ='Ideal Plaza'!G23+'Salt Lake JC -21'!G23+'Forum Mall'!G23+'Lake Town'!G23+'Quest Mall'!G23+'Rosedale Plaza'!G23+'Mani Square Mall'!G23+'Forum Rangoli'!G23+CSC!G23+Jameslong!G23+Technopolis!G23+Santoshpur!G23+'Chinar Park'!G23+'Lake Road'!G23+Kalikapur!G23+'Event Sales'!G23+'Sector 1'!G23 -> 25502.658 | I24: ='Ideal Plaza'!H23+'Salt Lake JC -21'!H23+'Forum Mall'!H23+'Lake Town'!H23+'Quest Mall'!H23+'Rosedale Plaza'!H23+'Mani Square Mall'!H23+'Forum Rangoli'!H23+CSC!H23+Jameslong!H23+Technopolis!H23+Santoshpur!H23+'Chinar Park'!H23+'Lake Road'!H23+Kalikapur!H23+'Event Sales'!H23+'Sector 1'!H23 -> 25502.658 | J24: ='Ideal Plaza'!I23+'Salt Lake JC -21'!I23+'Forum Mall'!I23+'Lake Town'!I23+'Quest Mall'!I23+'Rosedale Plaza'!I23+'Mani Square Mall'!I23+'Forum Rangoli'!I23+CSC!I23+Jameslong!I23+Technopolis!I23+Santoshpur!I23+'Chinar Park'!I23+'Lake Road'!I23+Kalikapur!I23+'Event Sales'!I23+'Sector 1'!I23 -> 25502.658 | ... N24: ='Ideal Plaza'!M23+'Salt Lake JC -21'!M23+'Forum Mall'!M23+'Lake Town'!M23+'Quest Mall'!M23+'Rosedale Plaza'!M23+'Mani Square Mall'!M23+'Forum Rangoli'!M23+CSC!M23+Jameslong!M23+Technopolis!M23+Santoshpur!M23+'Chinar Park'!M23+'Lake Road'!M23+Kalikapur!M23+'Event Sales'!M23+'Sector 1'!M23 -> 25502.658 | O24: =sum(C24:N24) -> 295495.43 | P24: =O24/$O$14 -> 0.0022206305
A25: Repairs & Maintenance | B25: Operation | C25: ='Ideal Plaza'!B24+'Salt Lake JC -21'!B24+'Forum Mall'!B24+'Lake Town'!B24+'Quest Mall'!B24+'Rosedale Plaza'!B24+'Mani Square Mall'!B24+'Forum Rangoli'!B24+CSC!B24+Jameslong!B24+Technopolis!B24+Santoshpur!B24+'Chinar Park'!B24+'Lake Road'!B24+Kalikapur!B24+'Event Sales'!B24+'Sector 1'!B24 -> 58719.22 | D25: ='Ideal Plaza'!C24+'Salt Lake JC -21'!C24+'Forum Mall'!C24+'Lake Town'!C24+'Quest Mall'!C24+'Rosedale Plaza'!C24+'Mani Square Mall'!C24+'Forum Rangoli'!C24+CSC!C24+Jameslong!C24+Technopolis!C24+Santoshpur!C24+'Chinar Park'!C24+'Lake Road'!C24+Kalikapur!C24+'Event Sales'!C24+'Sector 1'!C24 -> 53248 | E25: ='Ideal Plaza'!D24+'Salt Lake JC -21'!D24+'Forum Mall'!D24+'Lake Town'!D24+'Quest Mall'!D24+'Rosedale Plaza'!D24+'Mani Square Mall'!D24+'Forum Rangoli'!D24+CSC!D24+Jameslong!D24+Technopolis!D24+Santoshpur!D24+'Chinar Park'!D24+'Lake Road'!D24+Kalikapur!D24+'Event Sales'!D24+'Sector 1'!D24 -> 228298 | F25: ='Ideal Plaza'!E24+'Salt Lake JC -21'!E24+'Forum Mall'!E24+'Lake Town'!E24+'Quest Mall'!E24+'Rosedale Plaza'!E24+'Mani Square Mall'!E24+'Forum Rangoli'!E24+CSC!E24+Jameslong!E24+Technopolis!E24+Santoshpur!E24+'Chinar Park'!E24+'Lake Road'!E24+Kalikapur!E24+'Event Sales'!E24+'Sector 1'!E24 -> 140553 | G25: ='Ideal Plaza'!F24+'Salt Lake JC -21'!F24+'Forum Mall'!F24+'Lake Town'!F24+'Quest Mall'!F24+'Rosedale Plaza'!F24+'Mani Square Mall'!F24+'Forum Rangoli'!F24+CSC!F24+Jameslong!F24+Technopolis!F24+Santoshpur!F24+'Chinar Park'!F24+'Lake Road'!F24+Kalikapur!F24+'Event Sales'!F24+'Sector 1'!F24 -> 542734 | H25: ='Ideal Plaza'!G24+'Salt Lake JC -21'!G24+'Forum Mall'!G24+'Lake Town'!G24+'Quest Mall'!G24+'Rosedale Plaza'!G24+'Mani Square Mall'!G24+'Forum Rangoli'!G24+CSC!G24+Jameslong!G24+Technopolis!G24+Santoshpur!G24+'Chinar Park'!G24+'Lake Road'!G24+Kalikapur!G24+'Event Sales'!G24+'Sector 1'!G24 -> 89813 | I25: ='Ideal Plaza'!H24+'Salt Lake JC -21'!H24+'Forum Mall'!H24+'Lake Town'!H24+'Quest Mall'!H24+'Rosedale Plaza'!H24+'Mani Square Mall'!H24+'Forum Rangoli'!H24+CSC!H24+Jameslong!H24+Technopolis!H24+Santoshpur!H24+'Chinar Park'!H24+'Lake Road'!H24+Kalikapur!H24+'Event Sales'!H24+'Sector 1'!H24 -> 0 | J25: ='Ideal Plaza'!I24+'Salt Lake JC -21'!I24+'Forum Mall'!I24+'Lake Town'!I24+'Quest Mall'!I24+'Rosedale Plaza'!I24+'Mani Square Mall'!I24+'Forum Rangoli'!I24+CSC!I24+Jameslong!I24+Technopolis!I24+Santoshpur!I24+'Chinar Park'!I24+'Lake Road'!I24+Kalikapur!I24+'Event Sales'!I24+'Sector 1'!I24 -> 0 | ... N25: ='Ideal Plaza'!M24+'Salt Lake JC -21'!M24+'Forum Mall'!M24+'Lake Town'!M24+'Quest Mall'!M24+'Rosedale Plaza'!M24+'Mani Square Mall'!M24+'Forum Rangoli'!M24+CSC!M24+Jameslong!M24+Technopolis!M24+Santoshpur!M24+'Chinar Park'!M24+'Lake Road'!M24+Kalikapur!M24+'Event Sales'!M24+'Sector 1'!M24 -> 0 | O25: =sum(C25:N25) -> 1113365.2 | P25: =O25/$O$14 -> 0.0083668729
A26: Miscellaneous Expenses | B26: Accounts | C26: ='Ideal Plaza'!B25+'Salt Lake JC -21'!B25+'Forum Mall'!B25+'Lake Town'!B25+'Quest Mall'!B25+'Rosedale Plaza'!B25+'Mani Square Mall'!B25+'Forum Rangoli'!B25+CSC!B25+Jameslong!B25+Technopolis!B25+Santoshpur!B25+'Chinar Park'!B25+'Lake Road'!B25+Kalikapur!B25+'Event Sales'!B25+'Sector 1'!B25 -> 157014.64 | D26: ='Ideal Plaza'!C25+'Salt Lake JC -21'!C25+'Forum Mall'!C25+'Lake Town'!C25+'Quest Mall'!C25+'Rosedale Plaza'!C25+'Mani Square Mall'!C25+'Forum Rangoli'!C25+CSC!C25+Jameslong!C25+Technopolis!C25+Santoshpur!C25+'Chinar Park'!C25+'Lake Road'!C25+Kalikapur!C25+'Event Sales'!C25+'Sector 1'!C25 -> 416061.46 | E26: ='Ideal Plaza'!D25+'Salt Lake JC -21'!D25+'Forum Mall'!D25+'Lake Town'!D25+'Quest Mall'!D25+'Rosedale Plaza'!D25+'Mani Square Mall'!D25+'Forum Rangoli'!D25+CSC!D25+Jameslong!D25+Technopolis!D25+Santoshpur!D25+'Chinar Park'!D25+'Lake Road'!D25+Kalikapur!D25+'Event Sales'!D25+'Sector 1'!D25 -> 187253.33 | F26: ='Ideal Plaza'!E25+'Salt Lake JC -21'!E25+'Forum Mall'!E25+'Lake Town'!E25+'Quest Mall'!E25+'Rosedale Plaza'!E25+'Mani Square Mall'!E25+'Forum Rangoli'!E25+CSC!E25+Jameslong!E25+Technopolis!E25+Santoshpur!E25+'Chinar Park'!E25+'Lake Road'!E25+Kalikapur!E25+'Event Sales'!E25+'Sector 1'!E25 -> 443123.53 | G26: ='Ideal Plaza'!F25+'Salt Lake JC -21'!F25+'Forum Mall'!F25+'Lake Town'!F25+'Quest Mall'!F25+'Rosedale Plaza'!F25+'Mani Square Mall'!F25+'Forum Rangoli'!F25+CSC!F25+Jameslong!F25+Technopolis!F25+Santoshpur!F25+'Chinar Park'!F25+'Lake Road'!F25+Kalikapur!F25+'Event Sales'!F25+'Sector 1'!F25 -> 202752.69 | H26: ='Ideal Plaza'!G25+'Salt Lake JC -21'!G25+'Forum Mall'!G25+'Lake Town'!G25+'Quest Mall'!G25+'Rosedale Plaza'!G25+'Mani Square Mall'!G25+'Forum Rangoli'!G25+CSC!G25+Jameslong!G25+Technopolis!G25+Santoshpur!G25+'Chinar Park'!G25+'Lake Road'!G25+Kalikapur!G25+'Event Sales'!G25+'Sector 1'!G25 -> 372301.15 | I26: ='Ideal Plaza'!H25+'Salt Lake JC -21'!H25+'Forum Mall'!H25+'Lake Town'!H25+'Quest Mall'!H25+'Rosedale Plaza'!H25+'Mani Square Mall'!H25+'Forum Rangoli'!H25+CSC!H25+Jameslong!H25+Technopolis!H25+Santoshpur!H25+'Chinar Park'!H25+'Lake Road'!H25+Kalikapur!H25+'Event Sales'!H25+'Sector 1'!H25 -> 31375.083 | J26: ='Ideal Plaza'!I25+'Salt Lake JC -21'!I25+'Forum Mall'!I25+'Lake Town'!I25+'Quest Mall'!I25+'Rosedale Plaza'!I25+'Mani Square Mall'!I25+'Forum Rangoli'!I25+CSC!I25+Jameslong!I25+Technopolis!I25+Santoshpur!I25+'Chinar Park'!I25+'Lake Road'!I25+Kalikapur!I25+'Event Sales'!I25+'Sector 1'!I25 -> 31375.083 | ... N26: ='Ideal Plaza'!M25+'Salt Lake JC -21'!M25+'Forum Mall'!M25+'Lake Town'!M25+'Quest Mall'!M25+'Rosedale Plaza'!M25+'Mani Square Mall'!M25+'Forum Rangoli'!M25+CSC!M25+Jameslong!M25+Technopolis!M25+Santoshpur!M25+'Chinar Park'!M25+'Lake Road'!M25+Kalikapur!M25+'Event Sales'!M25+'Sector 1'!M25 -> 31375.083 | O26: =sum(C26:N26) -> 1966757.3 | P26: =O26/$O$14 -> 0.014780063
A27: CAM | B27: Accounts | C27: ='Ideal Plaza'!B26+'Salt Lake JC -21'!B26+'Forum Mall'!B26+'Lake Town'!B26+'Quest Mall'!B26+'Rosedale Plaza'!B26+'Mani Square Mall'!B26+'Forum Rangoli'!B26+CSC!B26+Jameslong!B26+Technopolis!B26+Santoshpur!B26+'Chinar Park'!B26+'Lake Road'!B26+Kalikapur!B26+'Event Sales'!B26+'Sector 1'!B26 -> 380861.14 | D27: ='Ideal Plaza'!C26+'Salt Lake JC -21'!C26+'Forum Mall'!C26+'Lake Town'!C26+'Quest Mall'!C26+'Rosedale Plaza'!C26+'Mani Square Mall'!C26+'Forum Rangoli'!C26+CSC!C26+Jameslong!C26+Technopolis!C26+Santoshpur!C26+'Chinar Park'!C26+'Lake Road'!C26+Kalikapur!C26+'Event Sales'!C26+'Sector 1'!C26 -> 381213.14 | E27: ='Ideal Plaza'!D26+'Salt Lake JC -21'!D26+'Forum Mall'!D26+'Lake Town'!D26+'Quest Mall'!D26+'Rosedale Plaza'!D26+'Mani Square Mall'!D26+'Forum Rangoli'!D26+CSC!D26+Jameslong!D26+Technopolis!D26+Santoshpur!D26+'Chinar Park'!D26+'Lake Road'!D26+Kalikapur!D26+'Event Sales'!D26+'Sector 1'!D26 -> 382727.14 | F27: ='Ideal Plaza'!E26+'Salt Lake JC -21'!E26+'Forum Mall'!E26+'Lake Town'!E26+'Quest Mall'!E26+'Rosedale Plaza'!E26+'Mani Square Mall'!E26+'Forum Rangoli'!E26+CSC!E26+Jameslong!E26+Technopolis!E26+Santoshpur!E26+'Chinar Park'!E26+'Lake Road'!E26+Kalikapur!E26+'Event Sales'!E26+'Sector 1'!E26 -> 395255.14 | G27: ='Ideal Plaza'!F26+'Salt Lake JC -21'!F26+'Forum Mall'!F26+'Lake Town'!F26+'Quest Mall'!F26+'Rosedale Plaza'!F26+'Mani Square Mall'!F26+'Forum Rangoli'!F26+CSC!F26+Jameslong!F26+Technopolis!F26+Santoshpur!F26+'Chinar Park'!F26+'Lake Road'!F26+Kalikapur!F26+'Event Sales'!F26+'Sector 1'!F26 -> 395442.14 | H27: ='Ideal Plaza'!G26+'Salt Lake JC -21'!G26+'Forum Mall'!G26+'Lake Town'!G26+'Quest Mall'!G26+'Rosedale Plaza'!G26+'Mani Square Mall'!G26+'Forum Rangoli'!G26+CSC!G26+Jameslong!G26+Technopolis!G26+Santoshpur!G26+'Chinar Park'!G26+'Lake Road'!G26+Kalikapur!G26+'Event Sales'!G26+'Sector 1'!G26 -> 395166.14 | I27: ='Ideal Plaza'!H26+'Salt Lake JC -21'!H26+'Forum Mall'!H26+'Lake Town'!H26+'Quest Mall'!H26+'Rosedale Plaza'!H26+'Mani Square Mall'!H26+'Forum Rangoli'!H26+CSC!H26+Jameslong!H26+Technopolis!H26+Santoshpur!H26+'Chinar Park'!H26+'Lake Road'!H26+Kalikapur!H26+'Event Sales'!H26+'Sector 1'!H26 -> 0 | J27: ='Ideal Plaza'!I26+'Salt Lake JC -21'!I26+'Forum Mall'!I26+'Lake Town'!I26+'Quest Mall'!I26+'Rosedale Plaza'!I26+'Mani Square Mall'!I26+'Forum Rangoli'!I26+CSC!I26+Jameslong!I26+Technopolis!I26+Santoshpur!I26+'Chinar Park'!I26+'Lake Road'!I26+Kalikapur!I26+'Event Sales'!I26+'Sector 1'!I26 -> 0 | ... N27: ='Ideal Plaza'!M26+'Salt Lake JC -21'!M26+'Forum Mall'!M26+'Lake Town'!M26+'Quest Mall'!M26+'Rosedale Plaza'!M26+'Mani Square Mall'!M26+'Forum Rangoli'!M26+CSC!M26+Jameslong!M26+Technopolis!M26+Santoshpur!M26+'Chinar Park'!M26+'Lake Road'!M26+Kalikapur!M26+'Event Sales'!M26+'Sector 1'!M26 -> 0 | O27: =sum(C27:N27) -> 2330664.8 | P27: =O27/$O$14 -> 0.017514807
A28: Advertisement Expenses | B28: Accounts | C28: ='Ads Account'!B17 -> 811748.22 | D28: ='Ads Account'!C17 -> 907161.2 | E28: ='Ads Account'!D17 -> 470257.39 | F28: ='Ads Account'!E17 -> 1156117.1 | G28: ='Ads Account'!F17 -> 727103.47 | H28: ='Ads Account'!G17 -> 1066072.1 | I28: ='Ads Account'!H17 -> 0 | J28: ='Ads Account'!I17 -> 0 | ... N28: ='Ads Account'!M17 -> 0 | O28: =sum(C28:N28) -> 5138459.5 | P28: =O28/$O$14 -> 0.038615215
A29: HO+CK Cost | B29: Accounts | C29: ='Ideal Plaza'!B27+'Salt Lake JC -21'!B27+'Forum Mall'!B27+'Lake Town'!B27+'Quest Mall'!B27+'Rosedale Plaza'!B27+'Mani Square Mall'!B27+'Forum Rangoli'!B27+CSC!B27+Jameslong!B27+Technopolis!B27+Santoshpur!B27+'Chinar Park'!B27+'Lake Road'!B27+Kalikapur!B27+'Event Sales'!B27+'Sector 1'!B27 -> 4515808.5 | D29: ='Ideal Plaza'!C27+'Salt Lake JC -21'!C27+'Forum Mall'!C27+'Lake Town'!C27+'Quest Mall'!C27+'Rosedale Plaza'!C27+'Mani Square Mall'!C27+'Forum Rangoli'!C27+CSC!C27+Jameslong!C27+Technopolis!C27+Santoshpur!C27+'Chinar Park'!C27+'Lake Road'!C27+Kalikapur!C27+'Event Sales'!C27+'Sector 1'!C27 -> 4737028.8 | E29: ='Ideal Plaza'!D27+'Salt Lake JC -21'!D27+'Forum Mall'!D27+'Lake Town'!D27+'Quest Mall'!D27+'Rosedale Plaza'!D27+'Mani Square Mall'!D27+'Forum Rangoli'!D27+CSC!D27+Jameslong!D27+Technopolis!D27+Santoshpur!D27+'Chinar Park'!D27+'Lake Road'!D27+Kalikapur!D27+'Event Sales'!D27+'Sector 1'!D27 -> 4747803.6 | F29: ='Ideal Plaza'!E27+'Salt Lake JC -21'!E27+'Forum Mall'!E27+'Lake Town'!E27+'Quest Mall'!E27+'Rosedale Plaza'!E27+'Mani Square Mall'!E27+'Forum Rangoli'!E27+CSC!E27+Jameslong!E27+Technopolis!E27+Santoshpur!E27+'Chinar Park'!E27+'Lake Road'!E27+Kalikapur!E27+'Event Sales'!E27+'Sector 1'!E27 -> 4850901.3 | G29: ='Ideal Plaza'!F27+'Salt Lake JC -21'!F27+'Forum Mall'!F27+'Lake Town'!F27+'Quest Mall'!F27+'Rosedale Plaza'!F27+'Mani Square Mall'!F27+'Forum Rangoli'!F27+CSC!F27+Jameslong!F27+Technopolis!F27+Santoshpur!F27+'Chinar Park'!F27+'Lake Road'!F27+Kalikapur!F27+'Event Sales'!F27+'Sector 1'!F27 -> 4793202 | H29: ='Ideal Plaza'!G27+'Salt Lake JC -21'!G27+'Forum Mall'!G27+'Lake Town'!G27+'Quest Mall'!G27+'Rosedale Plaza'!G27+'Mani Square Mall'!G27+'Forum Rangoli'!G27+CSC!G27+Jameslong!G27+Technopolis!G27+Santoshpur!G27+'Chinar Park'!G27+'Lake Road'!G27+Kalikapur!G27+'Event Sales'!G27+'Sector 1'!G27 -> 4972571.1 | I29: ='Ideal Plaza'!H27+'Salt Lake JC -21'!H27+'Forum Mall'!H27+'Lake Town'!H27+'Quest Mall'!H27+'Rosedale Plaza'!H27+'Mani Square Mall'!H27+'Forum Rangoli'!H27+CSC!H27+Jameslong!H27+Technopolis!H27+Santoshpur!H27+'Chinar Park'!H27+'Lake Road'!H27+Kalikapur!H27+'Event Sales'!H27+'Sector 1'!H27 -> #DIV/0! | J29: ='Ideal Plaza'!I27+'Salt Lake JC -21'!I27+'Forum Mall'!I27+'Lake Town'!I27+'Quest Mall'!I27+'Rosedale Plaza'!I27+'Mani Square Mall'!I27+'Forum Rangoli'!I27+CSC!I27+Jameslong!I27+Technopolis!I27+Santoshpur!I27+'Chinar Park'!I27+'Lake Road'!I27+Kalikapur!I27+'Event Sales'!I27+'Sector 1'!I27 -> #DIV/0! | ... N29: ='Ideal Plaza'!M27+'Salt Lake JC -21'!M27+'Forum Mall'!M27+'Lake Town'!M27+'Quest Mall'!M27+'Rosedale Plaza'!M27+'Mani Square Mall'!M27+'Forum Rangoli'!M27+CSC!M27+Jameslong!M27+Technopolis!M27+Santoshpur!M27+'Chinar Park'!M27+'Lake Road'!M27+Kalikapur!M27+'Event Sales'!M27+'Sector 1'!M27 -> #DIV/0! | O29: =sum(C29:N29) -> #DIV/0! | P29: =O29/$O$14 -> #DIV/0!
A30: Operating Expenses | C30: =+SUM(C15:C29) -> 18283511 | D30: =+SUM(D15:D29) -> 20441382 | E30: =+SUM(E15:E29) -> 19851976 | F30: =+SUM(F15:F29) -> 21076086 | G30: =+SUM(G15:G29) -> 21315411 | H30: =+SUM(H15:H29) -> 20692990 | I30: =+SUM(I15:I29) -> #DIV/0! | J30: =+SUM(J15:J29) -> #DIV/0! | ... N30: =+SUM(N15:N29) -> #DIV/0! | O30: =sum(C30:N30) -> #DIV/0! | P30: =O30/$O$14 -> #DIV/0!
A31: Store Level EBITDA | C31: =C14-C30 -> 2055417.9 | D31: =D14-D30 -> 2106613.5 | E31: =E14-E30 -> 1816626.2 | F31: =F14-F30 -> 1100225.8 | G31: =G14-G30 -> 2826787.3 | H31: =H14-H30 -> 1501232.9 | I31: =I14-I30 -> #DIV/0! | J31: =J14-J30 -> #DIV/0! | ... N31: =N14-N30 -> #DIV/0! | O31: =sum(C31:N31) -> #DIV/0! | P31: =O31/$O$14 -> #DIV/0!
A32: EBIDTA Margin % | C32: =C31/C14 -> 0.10105831 | D32: =D31/D14 -> 0.093427973 | E32: =E31/E14 -> 0.083836798 | F32: =F31/F14 -> 0.049612661 | G32: =G31/G14 -> 0.11708906 | H32: =H31/H14 -> 0.067640703 | I32: =I31/I14 -> #DIV/0! | J32: =J31/J14 -> #DIV/0! | ... N32: =N31/N14 -> #DIV/0! | P32: =AVERAGE(C32:N32) -> #DIV/0!
A33: Food Cost | C33: =C15/C14 -> 0.26901585 | D33: =D15/D14 -> 0.27183296 | E33: =E15/E14 -> 0.2784488 | F33: =(F15/F14) -> 0.27873855 | G33: =(G15/G14) -> 0.28485279 | H33: =(H15/H14) -> 0.27537893 | I33: =(I15/I14) -> #DIV/0! | J33: =(J15/J14) -> #DIV/0! | K33: =(K15/K14) -> #DIV/0! | L33: =(L15/L14) -> #DIV/0! | M33: =(M15/M14) -> #DIV/0! | N33: =(N15/N14) -> #DIV/0! | P33: =AVERAGE(C33:N33) -> #DIV/0!

Sheet Ideal Plaza
A1: Dosa Coffee - Ideal Plaza | B1: =Summary!C1 -> 46113 | C1: =Summary!D1 -> 46143 | D1: =Summary!E1 -> 46174 | E1: =Summary!F1 -> 46204 | F1: =Summary!G1 -> 46235 | G1: =Summary!H1 -> 46266 | H1: =Summary!I1 -> 46296 | I1: =Summary!J1 -> 46327 | ... M1: =Summary!N1 -> 46447 | N1: FY 2025-26
A2: Food Cost Calculation
A3: Opening Stock | B3: 47397 | C3: =B7 -> 58327.95 | D3: =C7 -> 52335.8 | E3: =D7 -> 53854 | F3: =E7 -> 53640 | G3: =F7 -> 45238.66 | H3: =G7 -> 56345 | I3: =H7 | J3: =I7 | ... M3: =L7 | N3: =+SUM(J3:L3) -> 0
A4: Purchases Food (Less Purchase Return) | B4: 732427.58 | C4: 770769.34 | D4: 800355.47 | E4: 886262 | F4: =973696.34-488.9 -> 973207.44 | G4: 847800 | N4: =sum(B4:M4) -> 5010821.8
A5: Transferred Out | B5: 2191.04 | C5: =2867.68-778.37 -> 2089.31 | D5: 1631.31 | E5: 2084 | F5: 1703.61 | G5: 712.87 | N5: =+SUM(J5:L5) -> 0
A6: Wastage & Date Expired | B6: 23024.37 | C6: 25314 | D6: 24302.51 | E6: 22763 | F6: 26718.18 | G6: 23545.76 | N6: =+SUM(J6:L6) -> 0
A7: Closing Stock | B7: 58327.95 | C7: 52335.8 | D7: 53854 | E7: 53640 | F7: 45238.66 | G7: 56345 | N7: =sum(B7:M7) -> 319741.41
A9: Gross Revenue | B9: =2937485.15*1.05+74137.09*1.05 -> 3162203.4 | C9: =3392746.51*1.05+82143.75*1.05 -> 3648634.8 | D9: =3029420.51*1.05+73425.44*1.05 -> 3257988.2 | E9: =3285796.94*1.05+85414.34*1.05 -> 3539771.8 | F9: =3719187.2*1.05 -> 3905146.6 | G9: =3306302*1.05+90896.75*1.05 -> 3567058.7 | N9: =+SUM(B9:M9) -> 21080803
A10: Catering & Fairs | B10: 0 | C10: 0 | D10: 0 | E10: 0 | F10: 0 | G10: 0 | H10: 0 | I10: 0 | J10: 0 | K10: 0 | L10: 0 | M10: 0 | N10: =+SUM(B10:M10) -> 0
A11: Less: Tax | B11: =(B9+B10)/1.05*0.05 -> 150581.11 | C11: =(C9+C10)/1.05*0.05 -> 173744.51 | D11: =(D9+D10)/1.05*0.05 -> 155142.3 | E11: =(E9+E10)/1.05*0.05 -> 168560.56 | F11: =(F9+F10)/1.05*0.05 -> 185959.36 | G11: =(G9+G10)/1.05*0.05 -> 169859.94 | H11: =(H9+H10)/1.05*0.05 -> 0 | I11: =(I9+I10)/1.05*0.05 -> 0 | ... M11: =(M9+M10)/1.05*0.05 -> 0 | N11: =+SUM(B11:M11) -> 1003847.8
A12: Less: Commission | B12: =172104.69*1.18+107023.36*1.18+20018.29*1.18+(3145.36-28.69)*1.18+190.72*1.18 -> 356895.4 | C12: =190609.99*1.18+108477.94*1.18+270.75*1.18+4182.11*1.18+403.52+42158.73*1.18 -> 408328.95 | D12: =1313.64*1.18+147914.73*1.05+1433.13*1.18+479.8*1.18+170161.13*1.18 -> 359907.95 | E12: =198071.19*1.18+1262.08*1.18+174506.02*1.18 -> 441130.36 | F12: =257084.05*1.18+160826.95*1.18+2131.47*1.18 -> 495650.11 | G12: =211008.82*1.18+159441.1*1.18+1181.99*1.18+286.92*1.18 -> 438864.22 | N12: =+SUM(B12:M12) -> 2500777
A13: Net Revenues from F&B Sales | B13: =B9+B10-B11-B12 -> 2654726.8 | C13: =C9+C10-C11-C12 -> 3066561.3 | D13: =D9+D10-D11-D12 -> 2742938 | E13: =E9+E10-E11-E12 -> 2930080.9 | F13: =F9+F10-F11-F12 -> 3223537.1 | G13: =G9+G10-G11-G12 -> 2958334.5 | H13: =H9+H10-H11-H12 -> 0 | I13: =I9+I10-I11-I12 -> 0 | ... M13: =M9+M10-M11-M12 -> 0 | N13: =sum(B13:M13) -> 17576179
A14: F&B Cost | B14: =+B3+B4-B5-B7 -> 719305.59 | C14: =+C3+C4-C5-C7 -> 774672.18 | D14: =+D3+D4-D5-D7 -> 797205.96 | E14: =+E3+E4-E5-E7 -> 884392 | F14: =+F3+F4-F5-F7 -> 979905.17 | G14: =+G3+G4-G5-G7 -> 835980.79 | H14: =+H3+H4-H5-H7 -> 56345 | I14: =+I3+I4-I5-I7 -> 0 | ... M14: =+M3+M4-M5-M7 -> 0 | N14: =sum(B14:M14) -> 5047806.7 | O14: =N14/$N$13 -> 0.28719591
A15: Electricity | B15: =136893 -> 136893 | C15: =146483 -> 146483 | D15: 143708 | E15: 143067 | F15: 146239 | G15: 131272 | N15: =sum(B15:M15) -> 847662 | O15: =N15/$N$13 -> 0.048227889
A16: Telephone/Internet | B16: 2500 | C16: 2500 | D16: 2500 | E16: 2500 | F16: =3540/12 -> 295 | G16: =3540/12 -> 295 | H16: =3540/12 -> 295 | I16: =3540/12 -> 295 | J16: =3540/12 -> 295 | K16: =3540/12 -> 295 | L16: =3540/12 -> 295 | M16: =3540/12 -> 295 | N16: =sum(B16:M16) -> 12360 | O16: =N16/$N$13 -> 0.00070322453
A17: Gas | B17: =8832 -> 8832 | C17: =12808+12808+12808 -> 38424 | D17: 48832 | E17: 49304 | F17: =41963 -> 41963 | G17: =36517 -> 36517 | N17: =sum(B17:M17) -> 223872 | O17: =N17/$N$13 -> 0.01273724
A18: Rent & Revenue Share | B18: =185850 -> 185850 | C18: =185850 -> 185850 | D18: =195143 -> 195143 | E18: =195143 -> 195143 | F18: =195143 -> 195143 | G18: =195143 -> 195143 | N18: =sum(B18:M18) -> 1152272 | O18: =N18/$N$13 -> 0.065558733
A19: Software | B19: 3761 | C19: 3761 | D19: 3761 | E19: 3761 | F19: 3761 | G19: 3761 | N19: =sum(B19:M19) -> 22566 | O19: =N19/$N$13 -> 0.0012838968
A20: Staff Salary & Bonus | B20: =25960+30483+15617+444894 -> 516954 | C20: =21240+25960+468921 -> 516121 | D20: =21240+5192+25960+431827+37480 -> 521699 | E20: =37480+25960+450879.73+6424+30077 -> 550820.73 | F20: =8746+444418+36902 -> 490066 | G20: =38261+449705 -> 487966 | N20: =sum(B20:M20) -> 3083626.7 | O20: =N20/$N$13 -> 0.17544352
A21: AMC | B21: =1200+5145+2850+2974+2478 -> 14647 | C21: =1200+5145+2850+2974+2478 -> 14647 | D21: =1200+1580+3271+2726+5145 -> 13922 | E21: =5145+3271+2726+1200 -> 12342 | F21: =1200+3271+2726+5145 -> 12342 | G21: =1200+3271+2726+5145 -> 12342 | N21: =sum(B21:M21) -> 80242 | O21: =N21/$N$13 -> 0.0045653837
A22: Subscription | B22: =2516.16/3+18000/3+9813/12+7080/12 -> 8246.47 | C22: =2516.16/3+18000/3+9813/12+7080/12 -> 8246.47 | D22: =2516.16/3+18000/3+9813/12+7080/12 -> 8246.47 | E22: =2516.16/3+18000/3+9813/12+7080/12 -> 8246.47 | F22: =2516.16/3+18000/3+9813/12+7080/12 -> 8246.47 | G22: =2516.16/3+18000/3+9813/12+7080/12 -> 8246.47 | H22: =2516.16/3+18000/3+9813/12 -> 7656.47 | I22: =2516.16/3+18000/3+9813/12 -> 7656.47 | J22: =2516.16/3+18000/3+9813/12 -> 7656.47 | K22: =2516.16/3+18000/3+9813/12 -> 7656.47 | L22: =2516.16/3+18000/3+9813/12 -> 7656.47 | M22: =2516.16/3+18000/3+9813/12 -> 7656.47 | N22: =sum(B22:M22) -> 95417.64 | O22: =N22/$N$13 -> 0.0054288046
A23: Insurance Premium | B23: 1380 | C23: =1698 -> 1698 | D23: =1698 -> 1698 | E23: =1698 -> 1698 | F23: =1698 -> 1698 | G23: =1698 -> 1698 | H23: =1698 -> 1698 | I23: =1698 -> 1698 | J23: =1698 -> 1698 | ... M23: =1698 -> 1698 | N23: =sum(B23:M23) -> 20058 | O23: =N23/$N$13 -> 0.0011412037
A24: Repairs & Maintenance | B24: =925 -> 925 | C24: 10961 | D24: 40209 | E24: ='Misc Exp'!B133 -> 36728 | F24: ='Misc Exp'!B90 -> 31373 | G24: ='Misc Exp'!B43 -> 18364 | N24: =sum(B24:M24) -> 138560 | O24: =N24/$N$13 -> 0.0078833973
A25: Miscellaneous Expenses | B25: =48492/12+9930.53 -> 13971.53 | C25: =48492/12+44519.03 -> 48560.03 | D25: =48492/12+16308 -> 20349 | E25: =48492/12+'Misc Exp'!B126 -> 48814.343 | F25: =48492/12+'Misc Exp'!B84 -> 19955.28 | G25: =48492/12+'Misc Exp'!B38 -> 82504.39 | H25: =48492/12 -> 4041 | I25: =48492/12 -> 4041 | J25: =48492/12 -> 4041 | K25: =48492/12 -> 4041 | L25: =48492/12 -> 4041 | M25: =48492/12 -> 4041 | N25: =sum(B25:M25) -> 258400.57 | O25: =N25/$N$13 -> 0.014701749
A26: CAM | B26: =13335 -> 13335 | C26: 13687 | D26: 13645 | E26: 13926 | F26: 13704 | G26: =13428 -> 13428 | N26: =sum(B26:M26) -> 81725 | O26: =N26/$N$13 -> 0.0046497593
A27: HO+CK Cost | B27: =HO!D25 -> 589423.28 | C27: =HO!H25 -> 644243.05 | D27: =HO!L25 -> 601004.65 | E27: =HO!P25 -> 640933.15 | F27: =HO!D44 -> 640002.37 | G27: =HO!H44 -> 662808.92 | H27: =HO!L44 -> #DIV/0! | I27: =HO!P44 -> #DIV/0! | J27: =HO!D63 -> #DIV/0! | K27: =HO!H63 -> #DIV/0! | L27: =HO!L63 -> #DIV/0! | M27: =HO!P63 -> #DIV/0! | N27: =sum(B27:M27) -> #DIV/0! | O27: =N27/$N$13 -> #DIV/0!
A28: Operating Expenses | B28: =+SUM(B14:B27) -> 2216023.9 | C28: =+SUM(C14:C27) -> 2409853.7 | D28: =+SUM(D14:D27) -> 2411923.1 | E28: =+SUM(E14:E27) -> 2591675.7 | F28: =+SUM(F14:F27) -> 2584693.3 | G28: =+SUM(G14:G27) -> 2490326.6 | H28: =+SUM(H14:H27) -> #DIV/0! | I28: =+SUM(I14:I27) -> #DIV/0! | ... M28: =+SUM(M14:M27) -> #DIV/0! | N28: =sum(B28:M28) -> #DIV/0! | O28: =N28/$N$13 -> #DIV/0!
A29: Store Level EBITDA | B29: =B13-B28 -> 438702.97 | C29: =C13-C28 -> 656707.57 | D29: =D13-D28 -> 331014.91 | E29: =E13-E28 -> 338405.22 | F29: =F13-F28 -> 638843.8 | G29: =G13-G28 -> 468007.96 | H29: =H13-H28 -> #DIV/0! | I29: =I13-I28 -> #DIV/0! | ... M29: =M13-M28 -> #DIV/0! | N29: =sum(B29:M29) -> #DIV/0! | O29: =N29/$N$13 -> #DIV/0!
A30: Food Cost | B30: =(B14/B13) -> 0.27095277 | C30: =(C14/C13) -> 0.25261917 | D30: =(D14/D13) -> 0.29063944 | E30: =(E14/E13) -> 0.30183194 | F30: =(F14/F13) -> 0.30398446 | G30: =(G14/G13) -> 0.28258494 | H30: =(H14/H13) -> #DIV/0! | I30: =(I14/I13) -> #DIV/0! | ... M30: =(M14/M13) -> #DIV/0!

Sheet Salt Lake JC -21
A1: Dosa Coffee - Salt Lake JC 21 | B1: =Summary!C1 -> 46113 | C1: =Summary!D1 -> 46143 | D1: =Summary!E1 -> 46174 | E1: =Summary!F1 -> 46204 | F1: =Summary!G1 -> 46235 | G1: =Summary!H1 -> 46266 | H1: =Summary!I1 -> 46296 | I1: =Summary!J1 -> 46327 | ... M1: =Summary!N1 -> 46447 | N1: FY 2025-26
A2: Food Cost Calculation
A3: Opening Stock | B3: 35428 | C3: =B7 -> 37509.58 | D3: =C7 -> 34989.66 | E3: =D7 -> 36958 | F3: =E7 -> 30595 | G3: =F7 -> 31908.61 | H3: =G7 -> 33044 | I3: =H7 | J3: =I7 | ... M3: =L7 | N3: =+SUM(J3:L3) -> 0
A4: Purchases Food (Less Purchase Return) | B4: 562871.61 | C4: 588181.83 | D4: =579008-5538 -> 573470 | E4: 568791.8 | F4: 623082 | G4: 574798.71 | N4: =sum(B4:M4) -> 3491196
A5: Transferred Out | B5: 1111.76 | C5: 1179 | D5: 389 | E5: 1445 | F5: 1421 | G5: 1007.31 | N5: =+SUM(J5:L5) -> 0
A6: Wastage & Date Expired | B6: 24335.4 | C6: 26774.59 | D6: 23288 | E6: 27085.61 | F6: 24981 | G6: 22543 | N6: =+SUM(J6:L6) -> 0
A7: Closing Stock | B7: 37509.58 | C7: 34989.66 | D7: 36958 | E7: 30595 | F7: 31908.61 | G7: 33044 | N7: =sum(B7:M7) -> 205004.85
A9: Gross Revenue | B9: =2479117.74*1.05+24151.95*1.05 -> 2628433.2 | C9: =2625741.6*1.05+23977.21*1.05 -> 2782204.8 | D9: =2480097.36*1.05+20453.15*1.05 -> 2625578 | E9: =2568455*1.05+19718.68*1.05 -> 2717582.4 | F9: =2796976.77*1.05 -> 2936825.6 | G9: =2568529.88*1.05+25756.48*1.05 -> 2724000.7 | N9: =+SUM(B9:M9) -> 16414625
A10: Catering & Fairs | N10: =+SUM(B10:M10) -> 0
A11: Less Tax | B11: =(B9+B10)/1.05*0.05 -> 125163.48 | C11: =(C9+C10)/1.05*0.05 -> 132485.94 | D11: =(D9+D10)/1.05*0.05 -> 125027.53 | E11: =(E9+E10)/1.05*0.05 -> 129408.68 | F11: =(F9+F10)/1.05*0.05 -> 139848.84 | G11: =(G9+G10)/1.05*0.05 -> 129714.32 | H11: =(H9+H10)/1.05*0.05 -> 0 | I11: =(I9+I10)/1.05*0.05 -> 0 | ... M11: =(M9+M10)/1.05*0.05 -> 0 | N11: =+SUM(B11:M11) -> 781648.79
A12: Less Commission | B12: =1166.78*1.18+55763.41*1.18+63565.48*1.18+11853.41*1.18+2254.16*1.18+42.47*1.18 -> 158881.94 | C12: =56973.6*1.18+54806.19*1.18+204.09*1.18+2165.46*1.18+18083.24*1.18 -> 156034.44 | D12: =48654.68*1.18+69683.37*1.18+1531.33*1.18+126.32*1.18 -> 141594.93 | E12: =47290.76*1.18+1408.79*1.18+12.91*1.18+75378.6*1.18 -> 146427.45 | F12: =63616.54*1.18+82617.64*1.18+2049*1.18 -> 174974.15 | G12: =60807.64*1.18+77132.64*1.18+1742.77*1.18+55.05*1.18 -> 164890.96 | N12: =+SUM(B12:M12) -> 942803.87
A13: Net Revenues from F&B Sales | B13: =B9+B10-B11-B12 -> 2344387.8 | C13: =C9+C10-C11-C12 -> 2493684.4 | D13: =D9+D10-D11-D12 -> 2358955.6 | E13: =E9+E10-E11-E12 -> 2441746.2 | F13: =F9+F10-F11-F12 -> 2622002.6 | G13: =G9+G10-G11-G12 -> 2429395.4 | H13: =H9+H10-H11-H12 -> 0 | I13: =I9+I10-I11-I12 -> 0 | ... M13: =M9+M10-M11-M12 -> 0 | N13: =sum(B13:M13) -> 14690172
A14: F&B Cost | B14: =+B3+B4-B5-B7 -> 559678.27 | C14: =+C3+C4-C5-C7 -> 589522.75 | D14: =+D3+D4-D5-D7 -> 571112.66 | E14: =+E3+E4-E5-E7 -> 573709.8 | F14: =+F3+F4-F5-F7 -> 620347.39 | G14: =+G3+G4-G5-G7 -> 572656.01 | H14: =+H3+H4-H5-H7 -> 33044 | I14: =+I3+I4-I5-I7 -> 0 | ... M14: =+M3+M4-M5-M7 -> 0 | N14: =sum(B14:M14) -> 3520070.9 | O14: =N14/$N$13 -> 0.23962081
A15: Electricity | B15: 90862 | C15: 88404 | D15: 91315 | E15: 88033 | F15: 85413 | G15: 92617 | N15: =sum(B15:M15) -> 536644 | O15: =N15/$N$13 -> 0.036530818
A16: Telephone/Internet | B16: =1357 -> 1357 | C16: =1357 -> 1357 | D16: 1357 | E16: =1357 -> 1357 | F16: =1357 -> 1357 | G16: =1357 -> 1357 | N16: =sum(B16:M16) -> 8142 | O16: =N16/$N$13 -> 0.00055424811
A17: Gas | B17: 0 | C17: 0 | D17: 0 | E17: 0 | F17: 0 | G17: 0 | N17: =sum(B17:M17) -> 0 | O17: =N17/$N$13 -> 0
A18: Rent & Revenue Share | B18: =109740+149156 -> 258896 | C18: =109740+164549 -> 274289 | D18: =109740+149266 -> 259006 | E18: =109740+158254 -> 267994 | F18: =109740+179680 -> 289420 | G18: =109740+158515 -> 268255 | N18: =sum(B18:M18) -> 1617860 | O18: =N18/$N$13 -> 0.11013214
A19: Software | B19: 3761 | C19: 3761 | D19: 3761 | E19: 3761 | F19: 3761 | G19: 3761 | N19: =sum(B19:M19) -> 22566 | O19: =N19/$N$13 -> 0.0015361291
A20: Staff Salary & Bonus | B20: =7808+1200+11000+320386 -> 340394 | C20: =11000+317125+26317+20302+5192 -> 379936 | D20: =26317+11000+332662+10385 -> 380364 | E20: =11000+15577+376925.7+30891 -> 434393.7 | F20: =309604.32+15577+11000 -> 336181.32 | G20: =15000+11000+308833 -> 334833 | N20: =sum(B20:M20) -> 2206102 | O20: =N20/$N$13 -> 0.15017537
A21: AMC | B21: =2950+2478+2478 -> 7906 | C21: =2950+2478+2478 -> 7906 | D21: =2726+2726+2950 -> 8402 | E21: =2950+2726+2726 -> 8402 | F21: =7875+2726+2726+2950 -> 16277 | G21: =7875+2726+2726+2950 -> 16277 | N21: =sum(B21:M21) -> 65170 | O21: =N21/$N$13 -> 0.0044362993
A22: Subscription | B22: =2516.16/3+24000/3+9813/12+7080/12 -> 10246.47 | C22: =2516.16/3+24000/3+9813/12+7080/12 -> 10246.47 | D22: =2516.16/3+24000/3+9813/12+7080/12 -> 10246.47 | E22: =2516.16/3+24000/3+9813/12+7080/12 -> 10246.47 | F22: =2516.16/3+24000/3+9813/12+7080/12 -> 10246.47 | G22: =2516.16/3+24000/3+9813/12+7080/12 -> 10246.47 | H22: =9813/12 -> 817.75 | I22: =9813/12 -> 817.75 | J22: =9813/12 -> 817.75 | K22: =9813/12 -> 817.75 | L22: =9813/12 -> 817.75 | M22: =9813/12 -> 817.75 | N22: =sum(B22:M22) -> 66385.32 | O22: =N22/$N$13 -> 0.0045190295
A23: Insurance Premium | B23: =7616.9/12+1353/12 -> 747.49167 | C23: =7616.9/12+1353/12 -> 747.49167 | D23: =7616.9/12+1353/12 -> 747.49167 | E23: =7616.9/12+1353/12 -> 747.49167 | F23: =7616.9/12+1353/12 -> 747.49167 | G23: =7616.9/12+1353/12 -> 747.49167 | H23: =7616.9/12+1353/12 -> 747.49167 | I23: =7616.9/12+1353/12 -> 747.49167 | ... M23: =7616.9/12+1353/12 -> 747.49167 | N23: =sum(B23:M23) -> 8969.9 | O23: =N23/$N$13 -> 0.00061060551
A24: Repairs & Maintenance | B24: =18814.58 -> 18814.58 | C24: =998 -> 998 | D24: 42830 | E24: ='Misc Exp'!H133 -> 16840 | F24: ='Misc Exp'!H90 -> 18157 | G24: ='Misc Exp'!H43 -> 23121 | N24: =sum(B24:M24) -> 120760.58 | O24: =N24/$N$13 -> 0.0082205015
A25: Miscellaneous Expenses | B25: =8700/12 -> 725 | C25: =8700/12+40098.94 -> 40823.94 | D25: =8700/12+25110 -> 25835 | E25: =8700/12+'Misc Exp'!H126 -> 36758.978 | F25: =8700/12+'Misc Exp'!H84 -> 22486.69 | G25: =8700/12+'Misc Exp'!H38 -> 28794.2 | H25: =8700/12 -> 725 | I25: =8700/12 -> 725 | J25: =8700/12 -> 725 | K25: =8700/12 -> 725 | L25: =8700/12 -> 725 | M25: =8700/12 -> 725 | N25: =sum(B25:M25) -> 159773.81 | O25: =N25/$N$13 -> 0.010876238
A26: CAM | B26: =14160 -> 14160 | C26: 14160 | D26: 14160 | E26: 14160 | F26: 14160 | G26: 14160 | N26: =sum(B26:M26) -> 84960 | O26: =N26/$N$13 -> 0.0057834585
A27: HO+CK Cost | B27: =HO!D26 -> 520519.36 | C27: =HO!H26 -> 523889.36 | D27: =HO!L26 -> 516870.34 | E27: =HO!P26 -> 534113.61 | F27: =HO!D45 -> 520573.47 | G27: =HO!H45 -> 544301.17 | H27: =HO!L45 -> #DIV/0! | I27: =HO!P45 -> #DIV/0! | J27: =HO!D64 -> #DIV/0! | K27: =HO!H64 -> #DIV/0! | L27: =HO!L64 -> #DIV/0! | M27: =HO!P64 -> #DIV/0! | N27: =sum(B27:M27) -> #DIV/0! | O27: =N27/$N$13 -> #DIV/0!
A28: Operating Expenses | B28: =+SUM(B14:B27) -> 1828067.2 | C28: =+SUM(C14:C27) -> 1936041 | D28: =+SUM(D14:D27) -> 1926007 | E28: =+SUM(E14:E27) -> 1990517.1 | F28: =+SUM(F14:F27) -> 1939127.8 | G28: =+SUM(G14:G27) -> 1911126.3 | H28: =+SUM(H14:H27) -> #DIV/0! | I28: =+SUM(I14:I27) -> #DIV/0! | ... M28: =+SUM(M14:M27) -> #DIV/0! | N28: =sum(B28:M28) -> #DIV/0! | O28: =N28/$N$13 -> #DIV/0!
A29: Store Level EBITDA | B29: =B13-B28 -> 516320.58 | C29: =C13-C28 -> 557643.36 | D29: =D13-D28 -> 432948.63 | E29: =E13-E28 -> 451229.18 | F29: =F13-F28 -> 682874.79 | G29: =G13-G28 -> 518269.06 | H29: =H13-H28 -> #DIV/0! | I29: =I13-I28 -> #DIV/0! | ... M29: =M13-M28 -> #DIV/0! | N29: =sum(B29:M29) -> #DIV/0! | O29: =N29/$N$13 -> #DIV/0!
A30: Food Cost | B30: =(B14/B13) -> 0.2387311 | C30: =(C14/C13) -> 0.23640632 | D30: =(D14/D13) -> 0.24210403 | E30: =(E14/E13) -> 0.23495881 | F30: =(F14/F13) -> 0.23659297 | G30: =(G14/G13) -> 0.23571956 | H30: =(H14/H13) -> #DIV/0! | I30: =(I14/I13) -> #DIV/0! | ... M30: =(M14/M13) -> #DIV/0!

Sheet Forum Mall
A1: Dosa Coffee - Forum Mall | B1: =Summary!C1 -> 46113 | C1: =Summary!D1 -> 46143 | D1: =Summary!E1 -> 46174 | E1: =Summary!F1 -> 46204 | F1: =Summary!G1 -> 46235 | G1: =Summary!H1 -> 46266 | H1: =Summary!I1 -> 46296 | I1: =Summary!J1 -> 46327 | ... M1: =Summary!N1 -> 46447 | N1: FY 2025-26
A2: Food Cost Calculation
A3: Opening Stock | B3: 19397 | C3: =B7 -> 24657.25 | D3: =C7 -> 26834.46 | E3: =D7 -> 28638 | F3: =E7 -> 21575.79 | G3: =F7 -> 20884.91 | H3: =G7 -> 22345.43 | I3: =H7 | J3: =I7 | ... M3: =L7 | N3: =B3 -> 19397
A4: Purchases Food (Less Purchase Return) | B4: 137018.48 | C4: 145617 | D4: 164453 | E4: =153507-156.75 -> 153350.25 | F4: 165482.82 | G4: 164119.5 | N4: =sum(B4:M4) -> 930041.05
A5: Transferred Out | B5: 1623.62 | C5: 92.49 | D5: 2159 | E5: 1353 | F5: 733.96 | G5: 139.5 | N5: =+SUM(J5:L5) -> 0
A6: Wastage & Date Expired | B6: 4149.1 | C6: 4016.42 | D6: 4305 | E6: 5587 | F6: 8583.73 | G6: 13065.03 | N6: =+SUM(J6:L6) -> 0
A7: Closing Stock | B7: 24657.25 | C7: 26834.46 | D7: 28638 | E7: 21575.79 | F7: 20884.91 | G7: 22345.43 | N7: =sum(B7:M7) -> 144935.84
A9: Gross Revenue | B9: =646989.41*1.05 -> 679338.88 | C9: =714949.64*1.05 -> 750697.12 | D9: =805796.68*1.05 -> 846086.51 | E9: =719156.82*1.05 -> 755114.66 | F9: =690888.59*1.05 -> 725433.02 | G9: =738345.92*1.05 -> 775263.22 | N9: =+SUM(B9:M9) -> 4531933.4
A10: Catering & Fairs | N10: =+SUM(B10:M10) -> 0
A11: Less Tax | B11: =(B9+B10)/1.05*0.05 -> 32349.47 | C11: =(C9+C10)/1.05*0.05 -> 35747.482 | D11: =(D9+D10)/1.05*0.05 -> 40289.834 | E11: =(E9+E10)/1.05*0.05 -> 35957.841 | F11: =(F9+F10)/1.05*0.05 -> 34544.429 | G11: =(G9+G10)/1.05*0.05 -> 36917.296 | H11: =(H9+H10)/1.05*0.05 -> 0 | I11: =(I9+I10)/1.05*0.05 -> 0 | ... M11: =(M9+M10)/1.05*0.05 -> 0 | N11: =+SUM(B11:M11) -> 215806.35
A12: Less Commission | N12: =+SUM(B12:M12) -> 0
A13: Net Revenues from F&B Sales | B13: =B9+B10-B11-B12 -> 646989.41 | C13: =C9+C10-C11-C12 -> 714949.64 | D13: =D9+D10-D11-D12 -> 805796.68 | E13: =E9+E10-E11-E12 -> 719156.82 | F13: =F9+F10-F11-F12 -> 690888.59 | G13: =G9+G10-G11-G12 -> 738345.92 | H13: =H9+H10-H11-H12 -> 0 | I13: =I9+I10-I11-I12 -> 0 | ... M13: =M9+M10-M11-M12 -> 0 | N13: =sum(B13:M13) -> 4316127.1 | O13: =N13/$N$7 -> 29.77957
A14: F&B Cost | B14: =+B3+B4-B5-B7 -> 130134.61 | C14: =+C3+C4-C5-C7 -> 143347.3 | D14: =+D3+D4-D5-D7 -> 160490.46 | E14: =+E3+E4-E5-E7 -> 159059.46 | F14: =+F3+F4-F5-F7 -> 165439.74 | G14: =+G3+G4-G5-G7 -> 162519.48 | H14: =+H3+H4-H5-H7 -> 22345.43 | I14: =+I3+I4-I5-I7 -> 0 | ... M14: =+M3+M4-M5-M7 -> 0 | N14: =sum(B14:M14) -> 943336.48 | O14: =N14/$N$13 -> 0.21856087
A15: Electricity | B15: =3965+30161 -> 34126 | C15: =3965+32605 -> 36570 | D15: =3965+33043 -> 37008 | E15: =3965+33079 -> 37044 | F15: =3965+31777 -> 35742 | G15: =3965+30508 -> 34473 | N15: =sum(B15:M15) -> 214963 | O15: =N15/$N$13 -> 0.049804604
A16: Telephone/Internet | B16: =588.82 -> 588.82 | C16: =588.82 -> 588.82 | D16: =588.82 -> 588.82 | E16: =588.82 -> 588.82 | F16: =588.82 -> 588.82 | G16: =588.82 -> 588.82 | N16: =sum(B16:M16) -> 3532.92 | O16: =N16/$N$13 -> 0.00081853939
A17: Gas | B17: 3163 | C17: 4631 | D17: 4897 | E17: 4283 | F17: 4011 | G17: 4000 | N17: =sum(B17:M17) -> 24985 | O17: =N17/$N$13 -> 0.0057887545
A18: Rent & Revenue Share | B18: =62599+51938 -> 114537 | C18: =51098+75460 -> 126558 | D18: =64521+78089 -> 142610 | E18: =69572+57540 -> 127112 | F18: =63078+59195 -> 122273 | G18: =64867+65643 -> 130510 | N18: =sum(B18:M18) -> 763600 | O18: =N18/$N$13 -> 0.17691787
A19: Software | B19: 3343 | C19: 3343 | D19: 3343 | E19: 3343 | F19: 3343 | G19: 3343 | N19: =sum(B19:M19) -> 20058 | O19: =N19/$N$13 -> 0.0046472219
A20: Staff Salary & Bonus | B20: =90766 -> 90766 | C20: =109369 -> 109369 | D20: =125562.82 -> 125562.82 | E20: =121232.68 -> 121232.68 | F20: =121884 -> 121884 | G20: =133334 -> 133334 | N20: =sum(B20:M20) -> 702148.5 | O20: =N20/$N$13 -> 0.16268022
A21: AMC | B21: =3457+2478 -> 5935 | C21: =3457+2478 -> 5935 | D21: =3457+2478 -> 5935 | E21: =3457+2726 -> 6183 | F21: =2726+3457 -> 6183 | G21: =2726+3457 -> 6183 | N21: =sum(B21:M21) -> 36354 | O21: =N21/$N$13 -> 0.008422829
A22: Subscription | B22: =2516.16/3+9813/12+7080/12 -> 2246.47 | C22: =2516.16/3+9813/12+7080/12 -> 2246.47 | D22: =2516.16/3+9813/12+7080/12 -> 2246.47 | E22: =2516.16/3+9813/12+7080/12 -> 2246.47 | F22: =2516.16/3+9813/12+7080/12 -> 2246.47 | G22: =2516.16/3+9813/12+7080/12 -> 2246.47 | H22: =9813/12 -> 817.75 | I22: =9813/12 -> 817.75 | J22: =9813/12 -> 817.75 | K22: =9813/12 -> 817.75 | L22: =9813/12 -> 817.75 | M22: =9813/12 -> 817.75 | N22: =sum(B22:M22) -> 18385.32 | O22: =N22/$N$13 -> 0.00425968
A23: Insurance Premium | B23: 805.42 | C23: =1698 -> 1698 | D23: =1698 -> 1698 | E23: =1698 -> 1698 | F23: =1698 -> 1698 | G23: =1698 -> 1698 | H23: =1698 -> 1698 | I23: =1698 -> 1698 | J23: =1698 -> 1698 | ... M23: =1698 -> 1698 | N23: =sum(B23:M23) -> 19483.42 | O23: =N23/$N$13 -> 0.0045140979
A24: Repairs & Maintenance | B24: 0 | C24: 180 | D24: 0 | E24: ='Misc Exp'!P133 -> 0 | F24: ='Misc Exp'!K90 -> 10132 | G24: ='Misc Exp'!P43 -> 600 | N24: =sum(B24:M24) -> 10912 | O24: =N24/$N$13 -> 0.0025281925
A25: Miscellaneous Expenses | B25: =15602/12+4331 -> 5631.1667 | C25: =15602/12+7544 -> 8844.1667 | D25: =15602/12 -> 1300.1667 | E25: =15602/12+'Misc Exp'!P126 -> 4798.5 | F25: =15602/12+'Misc Exp'!K84 -> 6922.0767 | G25: =15602/12+'Misc Exp'!P38 -> 8721.1667 | H25: =15602/12 -> 1300.1667 | I25: =15602/12 -> 1300.1667 | J25: =15602/12 -> 1300.1667 | K25: =15602/12 -> 1300.1667 | L25: =15602/12 -> 1300.1667 | M25: =15602/12 -> 1300.1667 | N25: =sum(B25:M25) -> 44018.243 | O25: =N25/$N$13 -> 0.010198551
A26: CAM | B26: =54280 -> 54280 | C26: 54280 | D26: 54280 | E26: 54280 | F26: 54280 | G26: 54280 | N26: =sum(B26:M26) -> 325680 | O26: =N26/$N$13 -> 0.075456537
A27: HO+CK Cost | B27: =HO!D27 -> 143649.66 | C27: =HO!H27 -> 150201.25 | D27: =HO!L27 -> 176557.97 | E27: =HO!P27 -> 157310.14 | F27: =HO!D46 -> 137169.3 | G27: =HO!H46 -> 165424.92 | H27: =HO!L46 -> #DIV/0! | I27: =HO!P46 -> #DIV/0! | J27: =HO!D65 -> #DIV/0! | K27: =HO!H65 -> #DIV/0! | L27: =HO!L65 -> #DIV/0! | M27: =HO!P65 -> #DIV/0! | N27: =sum(B27:M27) -> #DIV/0! | O27: =N27/$N$13 -> #DIV/0!
A28: Operating Expenses | B28: =+SUM(B14:B27) -> 589206.15 | C28: =+SUM(C14:C27) -> 647792.01 | D28: =+SUM(D14:D27) -> 716517.7 | E28: =+SUM(E14:E27) -> 679179.07 | F28: =+SUM(F14:F27) -> 671912.41 | G28: =+SUM(G14:G27) -> 707921.86 | H28: =+SUM(H14:H27) -> #DIV/0! | I28: =+SUM(I14:I27) -> #DIV/0! | ... M28: =+SUM(M14:M27) -> #DIV/0! | N28: =sum(B28:M28) -> #DIV/0! | O28: =N28/$N$13 -> #DIV/0!
A29: Store Level EBITDA | B29: =B13-B28 -> 57783.259 | C29: =C13-C28 -> 67157.634 | D29: =D13-D28 -> 89278.977 | E29: =E13-E28 -> 39977.747 | F29: =F13-F28 -> 18976.181 | G29: =G13-G28 -> 30424.061 | H29: =H13-H28 -> #DIV/0! | I29: =I13-I28 -> #DIV/0! | ... M29: =M13-M28 -> #DIV/0! | N29: =sum(B29:M29) -> #DIV/0! | O29: =N29/$N$13 -> #DIV/0!
A30: Food Cost | B30: =(B14/B13) -> 0.2011387 | C30: =(C14/C13) -> 0.20049986 | D30: =(D14/D13) -> 0.19916992 | E30: =(E14/E13) -> 0.22117493 | F30: =(F14/F13) -> 0.23945936 | G30: =(G14/G13) -> 0.22011292 | H30: =(H14/H13) -> #DIV/0! | I30: =(I14/I13) -> #DIV/0! | ... M30: =(M14/M13) -> #DIV/0!

Sheet Mani Square Mall
A1: Dosa Coffee - Mani Square Mall | B1: =Summary!C1 -> 46113 | C1: =Summary!D1 -> 46143 | D1: =Summary!E1 -> 46174 | E1: =Summary!F1 -> 46204 | F1: =Summary!G1 -> 46235 | G1: =Summary!H1 -> 46266 | H1: =Summary!I1 -> 46296 | I1: =Summary!J1 -> 46327 | ... M1: =Summary!N1 -> 46447 | N1: FY 2025-26
A2: Food Cost Calculation
A3: Opening Stock | B3: 18285 | C3: =B7 -> 25668.79 | D3: =C7 -> 20001.56 | E3: =D7 -> 20509.75 | F3: =E7 -> 19370 | G3: =F7 -> 18641.87 | H3: =G7 -> 20006.16 | I3: =H7 | J3: =I7 | ... M3: =L7 | N3: =+SUM(J3:L3) -> 0
A4: Purchases Food (Less Purchase Return) | B4: 251524.39 | C4: 268950.22 | D4: =290717-57.29 -> 290659.71 | E4: 311713 | F4: 352194.31 | G4: 349739 | N4: =sum(B4:M4) -> 1824780.6
A5: Transferred Out | B5: 582.5 | C5: 460.27 | D5: 81.4 | E5: 46.3 | F5: 637.97 | G5: 0 | N5: =+SUM(J5:L5) -> 0
A6: Wastage & Date Expired | B6: 12180.79 | C6: 13023.42 | D6: 11971.21 | E6: 11893 | F6: 14696 | G6: 14821.58 | N6: =+SUM(J6:L6) -> 0
A7: Closing Stock | B7: 25668.79 | C7: 20001.56 | D7: 20509.75 | E7: 19370 | F7: 18641.87 | G7: 20006.16 | N7: =sum(B7:M7) -> 124198.13
A9: Gross Revenue | B9: =1176638.95*1.05+6608.96*1.05 -> 1242410.3 | C9: =1389551.23*1.05+7034.1*1.05 -> 1466414.6 | D9: =1344489.71*1.05+7109.98*1.05 -> 1419179.7 | E9: =1470109.32*1.05+6345.83*1.05 -> 1550277.9 | F9: =1658457.59*1.05 -> 1741380.5 | G9: =1645010.54*1.05+6786*1.05 -> 1734386.4 | N9: =+SUM(B9:M9) -> 9154049.3
A10: Catering & Fairs | N10: =+SUM(B10:M10) -> 0
A11: Less Tax | B11: =(B9+B10)/1.05*0.05 -> 59162.395 | C11: =(C9+C10)/1.05*0.05 -> 69829.266 | D11: =(D9+D10)/1.05*0.05 -> 67579.985 | E11: =(E9+E10)/1.05*0.05 -> 73822.758 | F11: =(F9+F10)/1.05*0.05 -> 82922.879 | G11: =(G9+G10)/1.05*0.05 -> 82589.827 | H11: =(H9+H10)/1.05*0.05 -> 0 | I11: =(I9+I10)/1.05*0.05 -> 0 | ... M11: =(M9+M10)/1.05*0.05 -> 0 | N11: =+SUM(B11:M11) -> 435907.11
A12: Less Commission | B12: =15000.11*1.18+9819.82*1.18+2303.48*1.18 -> 32005.624 | C12: =15991.73*1.18+10830.3*1.18+3430.24*1.18 -> 35697.679 | D12: =16587.95*1.18+15439.74*1.18 -> 37792.674 | E12: =14403.46*1.18+11363.54*1.18+13524.76*1.18 -> 46364.277 | F12: =17198.41*1.18+16278.7*1.18 -> 39502.99 | G12: =15759.83*1.18+14942.13*1.18 -> 36228.313 | N12: =+SUM(B12:M12) -> 227591.56
A13: Net Revenues from F&B Sales | B13: =B9+B10-B11-B12 -> 1151242.3 | C13: =C9+C10-C11-C12 -> 1360887.7 | D13: =D9+D10-D11-D12 -> 1313807 | E13: =E9+E10-E11-E12 -> 1430090.9 | F13: =F9+F10-F11-F12 -> 1618954.6 | G13: =G9+G10-G11-G12 -> 1615568.2 | H13: =H9+H10-H11-H12 -> 0 | I13: =I9+I10-I11-I12 -> 0 | ... M13: =M9+M10-M11-M12 -> 0 | N13: =sum(B13:M13) -> 8490550.7
A14: F&B Cost | B14: =+B3+B4-B5-B7 -> 243558.1 | C14: =+C3+C4-C5-C7 -> 274157.18 | D14: =+D3+D4-D5-D7 -> 290070.12 | E14: =+E3+E4-E5-E7 -> 312806.45 | F14: =+F3+F4-F5-F7 -> 352284.47 | G14: =+G3+G4-G5-G7 -> 348374.71 | H14: =+H3+H4-H5-H7 -> 20006.16 | I14: =+I3+I4-I5-I7 -> 0 | ... M14: =+M3+M4-M5-M7 -> 0 | N14: =sum(B14:M14) -> 1841257.2 | O14: =N14/$N$13 -> 0.21685957
A15: Electricity | B15: =15000+2000 -> 17000 | C15: =15000+1000+15000 -> 31000 | D15: 10000 | E15: 17000 | F15: 16000 | G15: 17000 | N15: =sum(B15:M15) -> 108000 | O15: =N15/$N$13 -> 0.012720023
A16: Telephone/Internet | B16: =352.82 -> 352.82 | C16: =1500/3+352.82 -> 852.82 | D16: =1500/3+352.82 -> 852.82 | E16: =1500/3+352.82 -> 852.82 | F16: =500 -> 500 | G16: =588 -> 588 | N16: =sum(B16:M16) -> 3999.28 | O16: =N16/$N$13 -> 0.00047102716
A17: Gas | B17: =25898 -> 25898 | C17: 35000 | D17: 37945 | E17: 43035 | F17: =39259 -> 39259 | G17: =41073 -> 41073 | N17: =sum(B17:M17) -> 222210 | O17: =N17/$N$13 -> 0.026171447
A18: Rent & Revenue Share | B18: =186273 -> 186273 | C18: 221256 | D18: 222952 | E18: 237599 | F18: 265413 | G18: =266481 -> 266481 | N18: =sum(B18:M18) -> 1399974 | O18: =N18/$N$13 -> 0.16488613
A19: Software | B19: 3343.33 | C19: 3343.33 | D19: 3343.33 | E19: 3343.33 | F19: 3343.33 | G19: 3343.33 | N19: =sum(B19:M19) -> 20059.98 | O19: =N19/$N$13 -> 0.0023626241
A20: Staff Salary & Bonus | B20: =123232 -> 123232 | C20: =133811 -> 133811 | D20: =142416 -> 142416 | E20: =132299 -> 132299 | F20: =125987 -> 125987 | G20: =121365.45 -> 121365.45 | N20: =sum(B20:M20) -> 779110.45 | O20: =N20/$N$13 -> 0.091762064
A21: AMC | B21: =1500+2478 -> 3978 | C21: =1500+2478 -> 3978 | D21: =2726+6410 -> 9136 | E21: =2726+1200+2596 -> 6522 | F21: =2726 -> 2726 | G21: =2726 -> 2726 | N21: =sum(B21:M21) -> 29066 | O21: =N21/$N$13 -> 0.0034233351
A22: Subscription | B22: =2516.16/3+9813/12+7080/12 -> 2246.47 | C22: =2516.16/3+9813/12+7080/12 -> 2246.47 | D22: =2516.16/3+9813/12+7080/12 -> 2246.47 | E22: =2516.16/3+9813/12+7080/12 -> 2246.47 | F22: =2516.16/3+9813/12+7080/12 -> 2246.47 | G22: =2516.16/3+9813/12+7080/12 -> 2246.47 | H22: =2516.16/3+9813/12 -> 1656.47 | I22: =2516.16/3+9813/12 -> 1656.47 | J22: =2516.16/3+9813/12 -> 1656.47 | K22: =2516.16/3+9813/12 -> 1656.47 | L22: =2516.16/3+9813/12 -> 1656.47 | M22: =2516.16/3+9813/12 -> 1656.47 | N22: =sum(B22:M22) -> 23417.64 | O22: =N22/$N$13 -> 0.0027580826
A23: Insurance Premium | B23: 526.68 | C23: =1698 -> 1698 | D23: =1698 -> 1698 | E23: =1698 -> 1698 | F23: =1698 -> 1698 | G23: =1698 -> 1698 | H23: =1698 -> 1698 | I23: =1698 -> 1698 | J23: =1698 -> 1698 | ... M23: =1698 -> 1698 | N23: =sum(B23:M23) -> 19204.68 | O23: =N23/$N$13 -> 0.0022618886
A24: Repairs & Maintenance | B24: 1782.88 | C24: 0 | D24: 5900 | E24: ='Misc Exp'!K133 -> 12500 | F24: ='Misc Exp'!K90 -> 10132 | G24: ='Misc Exp'!K43 -> 0 | N24: =sum(B24:M24) -> 30314.88 | O24: =N24/$N$13 -> 0.0035704257
A25: Miscellaneous Expenses | B25: =7596/12 -> 633 | C25: =7596/12+5132 -> 5765 | D25: =7596/12+3346 -> 3979 | E25: =7596/12+'Misc Exp'!K126 -> 10079.333 | F25: =7596/12+'Misc Exp'!K84 -> 6254.91 | G25: =7596/12+'Misc Exp'!K38 -> 10888 | H25: =7596/12 -> 633 | I25: =7596/12 -> 633 | J25: =7596/12 -> 633 | K25: =7596/12 -> 633 | L25: =7596/12 -> 633 | M25: =7596/12 -> 633 | N25: =sum(B25:M25) -> 41397.243 | O25: =N25/$N$13 -> 0.0048756842
A26: CAM | B26: =38884 -> 38884 | C26: 38884 | D26: 40440 | E26: 40440 | F26: 40440 | G26: 40440 | N26: =sum(B26:M26) -> 239528 | O26: =N26/$N$13 -> 0.028211127
A27: HO+CK Cost | B27: =HO!D31 -> 255607.84 | C27: =HO!H31 -> 285904.09 | D27: =HO!L31 -> 287868.02 | E27: =HO!P31 -> 312821.62 | F27: =HO!D50 -> 321427.91 | G27: =HO!H50 -> 361964.82 | H27: =HO!L50 -> #DIV/0! | I27: =HO!P50 -> #DIV/0! | J27: =HO!D69 -> #DIV/0! | K27: =HO!H69 -> #DIV/0! | L27: =HO!L69 -> #DIV/0! | M27: =HO!P69 -> #DIV/0! | N27: =sum(B27:M27) -> #DIV/0! | O27: =N27/$N$13 -> #DIV/0!
A28: Operating Expenses | B28: =+SUM(B14:B27) -> 903316.12 | C28: =+SUM(C14:C27) -> 1037895.9 | D28: =+SUM(D14:D27) -> 1058846.8 | E28: =+SUM(E14:E27) -> 1133243 | F28: =+SUM(F14:F27) -> 1187712.1 | G28: =+SUM(G14:G27) -> 1218188.8 | H28: =+SUM(H14:H27) -> #DIV/0! | I28: =+SUM(I14:I27) -> #DIV/0! | ... M28: =+SUM(M14:M27) -> #DIV/0! | N28: =sum(B28:M28) -> #DIV/0! | O28: =N28/$N$13 -> #DIV/0!
A29: Store Level EBITDA | B29: =B13-B28 -> 247926.16 | C29: =C13-C28 -> 322991.76 | D29: =D13-D28 -> 254960.26 | E29: =E13-E28 -> 296847.85 | F29: =F13-F28 -> 431242.51 | G29: =G13-G28 -> 397379.45 | H29: =H13-H28 -> #DIV/0! | I29: =I13-I28 -> #DIV/0! | ... M29: =M13-M28 -> #DIV/0! | N29: =sum(B29:M29) -> #DIV/0! | O29: =N29/$N$13 -> #DIV/0!
A30: Food Cost | B30: =(B14/B13) -> 0.21156111 | C30: =(C14/C13) -> 0.20145468 | D30: =(D14/D13) -> 0.22078594 | E30: =(E14/E13) -> 0.21873187 | F30: =(F14/F13) -> 0.21759997 | G30: =(G14/G13) -> 0.21563602 | H30: =(H14/H13) -> #DIV/0! | I30: =(I14/I13) -> #DIV/0! | ... M30: =(M14/M13) -> #DIV/0!

Sheet Lake Town
A1: Dosa Coffee - Lake Town | B1: =Summary!C1 -> 46113 | C1: =Summary!D1 -> 46143 | D1: =Summary!E1 -> 46174 | E1: =Summary!F1 -> 46204 | F1: =Summary!G1 -> 46235 | G1: =Summary!H1 -> 46266 | H1: =Summary!I1 -> 46296 | I1: =Summary!J1 -> 46327 | ... M1: =Summary!N1 -> 46447 | N1: FY 2025-26
A2: Food Cost Calculation
A3: Opening Stock | B3: 26043 | C3: =B7 -> 31057.31 | D3: =C7 -> 22917.19 | E3: =D7 -> 27033 | F3: =E7 -> 20479 | G3: =F7 -> 27380 | H3: =G7 -> 23670.33 | I3: =H7 | J3: =I7 | ... M3: =L7 | N3: =+SUM(J3:L3) -> 0
A4: Purchases Food (Less Purchase Return) | B4: =343088.7 -> 343088.7 | C4: 361531.99 | D4: 371332 | E4: 367107 | F4: 396283.79 | G4: 356068 | N4: =sum(B4:M4) -> 2195411.5
A5: Transferred Out | B5: 580.92 | C5: 136.61 | D5: 792 | E5: 608 | F5: 158 | G5: 204 | N5: =+SUM(J5:L5) -> 0
A6: Wastage & Date Expired | B6: 11009.92 | C6: 13042.83 | D6: 12619 | E6: 12589 | F6: 12362 | G6: 11130.88 | N6: =+SUM(J6:L6) -> 0
A7: Closing Stock | B7: 31057.31 | C7: 22917.19 | D7: 27033 | E7: 20479 | F7: 27380 | G7: 23670.33 | N7: =sum(B7:M7) -> 152536.83
A9: Gross Revenue | B9: =1319042.48*1.05+39392.47*1.05 -> 1426356.7 | C9: =1431803.7*1.05+33099.49*1.05 -> 1538148.4 | D9: =1358214.2*1.05+35094.86*1.05 -> 1462974.5 | E9: =1369101.89*1.05+35917.68*1.05 -> 1475270.5 | F9: =1484305.75*1.05 -> 1558521 | G9: =1391367.48*1.05+37457.03*1.05 -> 1500265.7 | N9: =+SUM(B9:M9) -> 8961536.9
A10: Catering & Fairs | B10: 0 | C10: 0 | D10: 0 | E10: 0 | F10: 0 | G10: 0 | H10: 0 | I10: 0 | J10: 0 | K10: 0 | L10: 0 | M10: 0 | N10: =+SUM(B10:M10) -> 0
A11: Less Tax | B11: =(B9+B10)/1.05*0.05 -> 67921.747 | C11: =(C9+C10)/1.05*0.05 -> 73245.159 | D11: =(D9+D10)/1.05*0.05 -> 69665.453 | E11: =(E9+E10)/1.05*0.05 -> 70250.978 | F11: =(F9+F10)/1.05*0.05 -> 74215.288 | G11: =(G9+G10)/1.05*0.05 -> 71441.226 | H11: =(H9+H10)/1.05*0.05 -> 0 | I11: =(I9+I10)/1.05*0.05 -> 0 | ... M11: =(M9+M10)/1.05*0.05 -> 0 | N11: =+SUM(B11:M11) -> 426739.85
A12: Less Commission | B12: =91382.87*1.18+51928.99*1.18+10556.43*1.18+704.13*1.18+73.84*1.18 -> 182482.59 | C12: =77254.74*1.18+61694.44*1.18+195.54*1.18+1228.54*1.18+20647.38*1.18 -> 190004.36 | D12: =82056.06*1.18+72144.24*1.18+838.89*1.18 -> 182946.24 | E12: =83739.65*1.18+936.27*1.18+79500*1.18 -> 193727.59 | F12: =83343.77*1.18+70741.67*1.18+84.97*1.18 -> 181921.08 | G12: =82131.45*1.18+87131.22*1.18+1091.4*1.18+18.28*1.18 -> 201039.37 | N12: =+SUM(B12:M12) -> 1132121.2
A13: Net Revenues from F&B Sales | B13: =B9+B10-B11-B12 -> 1175952.4 | C13: =C9+C10-C11-C12 -> 1274898.8 | D13: =D9+D10-D11-D12 -> 1210362.8 | E13: =E9+E10-E11-E12 -> 1211292 | F13: =F9+F10-F11-F12 -> 1302384.7 | G13: =G9+G10-G11-G12 -> 1227785.1 | H13: =H9+H10-H11-H12 -> 0 | I13: =I9+I10-I11-I12 -> 0 | ... M13: =M9+M10-M11-M12 -> 0 | N13: =sum(B13:M13) -> 7402675.8
A14: F&B Cost | B14: =+B3+B4-B5-B7 -> 337493.47 | C14: =+C3+C4-C5-C7 -> 369535.5 | D14: =+D3+D4-D5-D7 -> 366424.19 | E14: =+E3+E4-E5-E7 -> 373053 | F14: =+F3+F4-F5-F7 -> 389224.79 | G14: =+G3+G4-G5-G7 -> 359573.67 | H14: =+H3+H4-H5-H7 -> 23670.33 | I14: =+I3+I4-I5-I7 -> 0 | ... M14: =+M3+M4-M5-M7 -> 0 | N14: =sum(B14:M14) -> 2218975 | O14: =N14/$N$13 -> 0.29975309
A15: Electricity | B15: 50880 | C15: 48510 | D15: 53490 | E15: 50670 | F15: =55650 -> 55650 | G15: 55000 | N15: =sum(B15:M15) -> 314200 | O15: =N15/$N$13 -> 0.042444112
A16: Telephone/Internet | B16: =942.82+352.82 -> 1295.64 | C16: =942.82+352.82 -> 1295.64 | D16: =942.82+352.82 -> 1295.64 | E16: =352.82+942.82 -> 1295.64 | F16: =352.82+942.82 -> 1295.64 | G16: =352.82+942.82 -> 1295.64 | N16: =sum(B16:M16) -> 7773.84 | O16: =N16/$N$13 -> 0.0010501392
A17: Gas | B17: =6624+8832 -> 15456 | C17: =22414+22414+9606 -> 54434 | D17: 48832 | E17: 61630 | F17: 41963 | G17: 53371 | N17: =sum(B17:M17) -> 275686 | O17: =N17/$N$13 -> 0.037241399
A18: Rent & Revenue Share | B18: =56994 -> 56994 | C18: 56994 | D18: 56994 | E18: 56994 | F18: 56994 | G18: 56994 | N18: =sum(B18:M18) -> 341964 | O18: =N18/$N$13 -> 0.046194648
A19: Software | B19: 3761.25 | C19: 3761.25 | D19: 3761.25 | E19: 3761.25 | F19: 3761.25 | G19: 3761.25 | N19: =sum(B19:M19) -> 22567.5 | O19: =N19/$N$13 -> 0.0030485598
A20: Staff Salary & Bonus | B20: =170687 -> 170687 | C20: =197474 -> 197474 | D20: =200285+8077 -> 208362 | E20: =9231+183518.74 -> 192749.74 | F20: =168653.2+9808 -> 178461.2 | G20: =25962+165059 -> 191021 | N20: =sum(B20:M20) -> 1138754.9 | O20: =N20/$N$13 -> 0.15383018
A21: AMC | B21: =2950+2478+2478 -> 7906 | C21: =2950+2478+2478 -> 7906 | D21: =2726+2726+2950 -> 8402 | E21: =2950+2726+2726+1200 -> 9602 | F21: =2726+2726+2950 -> 8402 | G21: =2726+2726+2950 -> 8402 | N21: =sum(B21:M21) -> 50620 | O21: =N21/$N$13 -> 0.0068380679
A22: Subscription | B22: =2516.16/3+9813/12+7080/12 -> 2246.47 | C22: =2516.16/3+9813/12+7080/12 -> 2246.47 | D22: =2516.16/3+9813/12+7080/12 -> 2246.47 | E22: =2516.16/3+9813/12+7080/12 -> 2246.47 | F22: =2516.16/3+9813/12+7080/12 -> 2246.47 | G22: =2516.16/3+9813/12+7080/12 -> 2246.47 | H22: =9813/12 -> 817.75 | I22: =9813/12 -> 817.75 | J22: =9813/12 -> 817.75 | K22: =9813/12 -> 817.75 | L22: =9813/12 -> 817.75 | M22: =9813/12 -> 817.75 | N22: =sum(B22:M22) -> 18385.32 | O22: =N22/$N$13 -> 0.0024836046
A23: Insurance Premium | B23: =973.34 -> 973.34 | C23: =1698 -> 1698 | D23: =1698 -> 1698 | E23: =1698 -> 1698 | F23: =1698 -> 1698 | G23: =1698 -> 1698 | H23: =1698 -> 1698 | I23: =1698 -> 1698 | J23: =1698 -> 1698 | ... M23: =1698 -> 1698 | N23: =sum(B23:M23) -> 19651.34 | O23: =N23/$N$13 -> 0.0026546266
A24: Repairs & Maintenance | B24: 1200 | C24: 3560 | D24: 11630 | E24: ='Misc Exp'!L133 -> 5750 | F24: ='Misc Exp'!L90 -> 26620 | G24: ='Misc Exp'!L43 -> 2600 | N24: =sum(B24:M24) -> 51360 | O24: =N24/$N$13 -> 0.0069380318
A25: Miscellaneous Expenses | B25: 6885.42 | C25: 23029.72 | D25: 6484.7 | E25: ='Misc Exp'!L126 -> 23267.753 | F25: ='Misc Exp'!L84 -> 5099.11 | G25: ='Misc Exp'!L38 -> 11904.29 | N25: =sum(B25:M25) -> 76670.993 | O25: =N25/$N$13 -> 0.0103572
A26: CAM | B26: 0 | C26: 0 | D26: 0 | E26: 0 | F26: 0 | G26: 0 | N26: =sum(B26:M26) -> 0 | O26: =N26/$N$13 -> 0
A27: HO+CK Cost | B27: =HO!D28 -> 261094.17 | C27: =HO!H28 -> 267839 | D27: =HO!L28 -> 265202.38 | E27: =HO!P28 -> 264961.01 | F27: =HO!D47 -> 258575.98 | G27: =HO!H47 -> 275082.8 | H27: =HO!L47 -> #DIV/0! | I27: =HO!P47 -> #DIV/0! | J27: =HO!D66 -> #DIV/0! | K27: =HO!H66 -> #DIV/0! | L27: =HO!L66 -> #DIV/0! | M27: =HO!P66 -> #DIV/0! | N27: =sum(B27:M27) -> #DIV/0! | O27: =N27/$N$13 -> #DIV/0!
A28: Operating Expenses | B28: =+SUM(B14:B27) -> 916872.76 | C28: =+SUM(C14:C27) -> 1038283.6 | D28: =+SUM(D14:D27) -> 1034822.6 | E28: =+SUM(E14:E27) -> 1047678.9 | F28: =+SUM(F14:F27) -> 1029991.4 | G28: =+SUM(G14:G27) -> 1022950.1 | H28: =+SUM(H14:H27) -> #DIV/0! | I28: =+SUM(I14:I27) -> #DIV/0! | ... M28: =+SUM(M14:M27) -> #DIV/0! | N28: =sum(B28:M28) -> #DIV/0! | O28: =N28/$N$13 -> #DIV/0!
A29: Store Level EBITDA | B29: =B13-B28 -> 259079.61 | C29: =C13-C28 -> 236615.25 | D29: =D13-D28 -> 175540.19 | E29: =E13-E28 -> 163613.12 | F29: =F13-F28 -> 272393.22 | G29: =G13-G28 -> 204835.02 | H29: =H13-H28 -> #DIV/0! | I29: =I13-I28 -> #DIV/0! | ... M29: =M13-M28 -> #DIV/0! | N29: =sum(B29:M29) -> #DIV/0! | O29: =N29/$N$13 -> #DIV/0!
A30: Food Cost | B30: =(B14/B13) -> 0.28699587 | C30: =(C14/C13) -> 0.28985476 | D30: =(D14/D13) -> 0.30273913 | E30: =(E14/E13) -> 0.30797942 | F30: =(F14/F13) -> 0.29885548 | G30: =(G14/G13) -> 0.29286368 | H30: =(H14/H13) -> #DIV/0! | I30: =(I14/I13) -> #DIV/0! | ... M30: =(M14/M13) -> #DIV/0!

Sheet Rosedale Plaza
A1: Dosa Coffee - Rosedale Plaza | B1: =Summary!C1 -> 46113 | C1: =Summary!D1 -> 46143 | D1: =Summary!E1 -> 46174 | E1: =Summary!F1 -> 46204 | F1: =Summary!G1 -> 46235 | G1: =Summary!H1 -> 46266 | H1: =Summary!I1 -> 46296 | I1: =Summary!J1 -> 46327 | ... M1: =Summary!N1 -> 46447 | N1: FY 2025-26
A2: Food Cost Calculation
A3: Opening Stock | B3: 29064 | C3: =B7 -> 36474.1 | D3: =C7 -> 30896.92 | E3: =D7 -> 33094 | F3: =E7 -> 22177 | G3: =F7 -> 29999.95 | H3: =G7 -> 27012.18 | I3: =H7 | J3: =I7 | ... M3: =L7 | N3: =+SUM(J3:L3) -> 0
A4: Purchases Food (Less Purchase Return) | B4: 496389.17 | C4: 515675.19 | D4: 532402 | E4: 521135 | F4: 590814.52 | G4: 506223.45 | N4: =sum(B4:M4) -> 3162639.3
A5: Transferred Out | B5: 1314.93 | C5: 920.64 | D5: 515 | E5: 1599 | F5: 1758 | G5: 4868.94 | N5: =+SUM(J5:L5) -> 0
A6: Wastage & Date Expired | B6: 17684.9 | C6: 20557.78 | D6: 16809 | E6: 16407 | F6: 14324 | G6: 15023.07 | N6: =+SUM(J6:L6) -> 0
A7: Closing Stock | B7: 36474.1 | C7: 30896.92 | D7: 33094 | E7: 22177 | F7: 29999.95 | G7: 27012.18 | N7: =sum(B7:M7) -> 179654.15
A9: Gross Revenue | B9: =2000756.54*1.05+44980.36*1.05 -> 2148023.7 | C9: =2156375.71*1.05+50459.35*1.05 -> 2317176.8 | D9: =2052903.86*1.05+44650.95*1.05 -> 2202432.6 | E9: =2122630.2*1.05+46700.77*1.05 -> 2277797.5 | F9: =2374200.41*1.05 -> 2492910.4 | G9: =2023925.25*1.05+50866.96*1.05 -> 2178531.8 | N9: =+SUM(B9:M9) -> 13616873
A10: Catering & Fairs | B10: 0 | C10: 0 | D10: 0 | N10: =+SUM(B10:M10) -> 0
A11: Less Tax | B11: =(B9+B10)/1.05*0.05 -> 102286.85 | C11: =(C9+C10)/1.05*0.05 -> 110341.75 | D11: =(D9+D10)/1.05*0.05 -> 104877.74 | E11: =(E9+E10)/1.05*0.05 -> 108466.55 | F11: =(F9+F10)/1.05*0.05 -> 118710.02 | G11: =(G9+G10)/1.05*0.05 -> 103739.61 | H11: =(H9+H10)/1.05*0.05 -> 0 | I11: =(I9+I10)/1.05*0.05 -> 0 | ... M11: =(M9+M10)/1.05*0.05 -> 0 | N11: =+SUM(B11:M11) -> 648422.52
A12: Less Commission | B12: =103460.6*1.18+74495.57*1.18+19883.29*1.18+590.77*1.18 -> 234147.67 | C12: =116493.89*1.18+76866.38*1.18+58.02*1.18+523.57*1.18+58.23*1.18+25472.95*1.18 -> 258978.19 | D12: =103322.77*1.18+105970.99*1.18+714.89*1.18 -> 247810.21 | E12: =107902.52*1.18+629.43*1.18+117156.63*1.18 -> 266312.52 | F12: =121996.88*1.18+124835.33*1.18+618.89*1.18 -> 291992.3 | G12: =117920.19*1.18+106157.46*1.18+447.88*1.18+54.5*1.18 -> 265004.44 | N12: =+SUM(B12:M12) -> 1564245.3
A13: Net Revenues from F&B Sales | B13: =B9+B10-B11-B12 -> 1811589.2 | C13: =C9+C10-C11-C12 -> 1947856.9 | D13: =D9+D10-D11-D12 -> 1849744.6 | E13: =E9+E10-E11-E12 -> 1903018.4 | F13: =F9+F10-F11-F12 -> 2082208.1 | G13: =G9+G10-G11-G12 -> 1809787.8 | H13: =H9+H10-H11-H12 -> 0 | I13: =I9+I10-I11-I12 -> 0 | ... M13: =M9+M10-M11-M12 -> 0 | N13: =sum(B13:M13) -> 11404205 | O13: =N13/$N$7 -> 63.478662
A14: F&B Cost | B14: =+B3+B4-B5-B7 -> 487664.14 | C14: =+C3+C4-C5-C7 -> 520331.73 | D14: =+D3+D4-D5-D7 -> 529689.92 | E14: =+E3+E4-E5-E7 -> 530453 | F14: =+F3+F4-F5-F7 -> 581233.57 | G14: =+G3+G4-G5-G7 -> 504342.28 | H14: =+H3+H4-H5-H7 -> 27012.18 | I14: =+I3+I4-I5-I7 -> 0 | ... M14: =+M3+M4-M5-M7 -> 0 | N14: =sum(B14:M14) -> 3180726.8 | O14: =N14/$N$7 -> 17.704722
A15: Electricity | B15: =35215.8+13629+0.2 -> 48845 | C15: =36660.91+15399.63 -> 52060.54 | D15: =33939.05+16284+0.95 -> 50224 | E15: =32522+14337 -> 46859 | F15: =33981+15222 -> 49203 | G15: =31427.64+14337 -> 45764.64 | N15: =sum(B15:M15) -> 292956.18 | O15: =N15/$N$7 -> 1.6306675
A16: Telephone/Internet | B16: =352.82 -> 352.82 | C16: =352.82 -> 352.82 | D16: =352.82 -> 352.82 | E16: =352.82 -> 352.82 | F16: =352.82 -> 352.82 | G16: =352.82 -> 352.82 | N16: =sum(B16:M16) -> 2116.92 | O16: =N16/$N$7 -> 0.011783307
A17: Gas | B17: =4416+26496 -> 30912 | C17: =38424+32020+38424 -> 108868 | D17: 97664 | E17: 110934 | F17: =97912 -> 97912 | G17: =78652 -> 78652 | N17: =sum(B17:M17) -> 524942 | O17: =N17/$N$7 -> 2.9219587
A18: Rent & Revenue Share | B18: =310263.47 -> 310263.47 | C18: =333437 -> 333437 | D18: 316313.81 | E18: 326015 | F18: =356294 -> 356294 | G18: =308801 -> 308801 | N18: =sum(B18:M18) -> 1951124.3 | O18: =N18/$N$7 -> 10.860446
A19: Software | B19: 3761.25 | C19: 3761.25 | D19: 3761.25 | E19: 3761.25 | F19: 3761.25 | G19: 3761.25 | N19: =sum(B19:M19) -> 22567.5 | O19: =N19/$N$7 -> 0.12561636
A20: Staff Salary | B20: =4500+275653 -> 280153 | C20: =4500+286103 -> 290603 | D20: =4500+280040.63 -> 284540.63 | E20: =4500+250082 -> 254582 | F20: =262717+4500 -> 267217 | G20: =4500+262717 -> 267217 | N20: =sum(B20:M20) -> 1644312.6 | O20: =N20/$N$7 -> 9.152656
A21: AMC | B21: =2440+2850+2478 -> 7768 | C21: =2440+2850+2478+9185 -> 16953 | D21: =2726+1850+2400 -> 6976 | E21: =2726+3250 -> 5976 | F21: =3200+3300+2726 -> 9226 | G21: =3200+3300+2726 -> 9226 | N21: =sum(B21:M21) -> 56125 | O21: =N21/$N$7 -> 0.31240581
A22: Subscription | B22: =2516.16/3+9813/12+7080/12 -> 2246.47 | C22: =2516.16/3+9813/12+7080/12 -> 2246.47 | D22: =2516.16/3+9813/12+7080/12 -> 2246.47 | E22: =2516.16/3+9813/12+7080/12 -> 2246.47 | F22: =2516.16/3+9813/12+7080/12 -> 2246.47 | G22: =2516.16/3+9813/12+7080/12 -> 2246.47 | H22: =2516.16/3+9813/12+7080/12 -> 2246.47 | I22: =9813/12 -> 817.75 | J22: =9813/12 -> 817.75 | K22: =9813/12 -> 817.75 | L22: =9813/12 -> 817.75 | M22: =9813/12 -> 817.75 | N22: =sum(B22:M22) -> 19814.04
A23: Insurance Premium | B23: =590 -> 590 | C23: =1698 -> 1698 | D23: =1698 -> 1698 | E23: =1698 -> 1698 | F23: =1698 -> 1698 | G23: =1698 -> 1698 | H23: =1698 -> 1698 | I23: =1698 -> 1698 | J23: =1698 -> 1698 | ... M23: =1698 -> 1698 | N23: =sum(B23:M23) -> 19268 | O23: =N23/$N$7 -> 0.10725051
A24: Repairs & Maintenance | B24: 580 | C24: 20326 | D24: 6665 | E24: ='Misc Exp'!D133 -> 2144 | F24: ='Misc Exp'!D90 -> 16210 | G24: ='Misc Exp'!D43 -> 5720 | N24: =sum(B24:M24) -> 51645 | O24: =N24/$N$7 -> 0.28746901
A25: Miscellaneous Expenses | B25: 20073.29 | C25: 23647.52 | D25: 18161.5 | E25: ='Misc Exp'!D126 -> 33841.283 | F25: ='Misc Exp'!D84 -> 15891.72 | G25: ='Misc Exp'!D38 -> 23424.94 | N25: =sum(B25:M25) -> 135040.25 | O25: =N25/$N$7 -> 0.75166788
A26: CAM | B26: =13570 -> 13570 | C26: 13570 | D26: 13570 | E26: 13570 | F26: 13570 | G26: 13570 | N26: =sum(B26:M26) -> 81420 | O26: =N26/$N$7 -> 0.45320411
A27: HO+CK Cost | B27: =HO!D30 -> 402223.25 | C27: =HO!H30 -> 409218.38 | D27: =HO!L30 -> 405297.21 | E27: =HO!P30 -> 416270.97 | F27: =HO!D49 -> 413402.45 | G27: =HO!H49 -> 405479.32 | H27: =HO!L49 -> #DIV/0! | I27: =HO!P49 -> #DIV/0! | J27: =HO!D68 -> #DIV/0! | K27: =HO!H68 -> #DIV/0! | L27: =HO!L68 -> #DIV/0! | M27: =HO!P68 -> #DIV/0! | N27: =sum(B27:M27) -> #DIV/0! | O27: =N27/$N$7 -> #DIV/0!
A28: Operating Expenses | B28: =+SUM(B14:B27) -> 1609002.7 | C28: =+SUM(C14:C27) -> 1797073.7 | D28: =+SUM(D14:D27) -> 1737160.6 | E28: =+SUM(E14:E27) -> 1748703.8 | F28: =+SUM(F14:F27) -> 1828218.3 | G28: =+SUM(G14:G27) -> 1670255.7 | H28: =+SUM(H14:H27) -> #DIV/0! | I28: =+SUM(I14:I27) -> #DIV/0! | ... M28: =+SUM(M14:M27) -> #DIV/0! | N28: =sum(B28:M28) -> #DIV/0! | O28: =N28/$N$7 -> #DIV/0!
A29: Store Level EBITDA | B29: =B13-B28 -> 202586.54 | C29: =C13-C28 -> 150783.16 | D29: =D13-D28 -> 112583.99 | E29: =E13-E28 -> 154314.66 | F29: =F13-F28 -> 253989.84 | G29: =G13-G28 -> 139532.05 | H29: =H13-H28 -> #DIV/0! | I29: =I13-I28 -> #DIV/0! | ... M29: =M13-M28 -> #DIV/0! | N29: =sum(B29:M29) -> #DIV/0! | O29: =N29/$N$7 -> #DIV/0!
A30: Food Cost | B30: =(B14/B13) -> 0.26919134 | C30: =(C14/C13) -> 0.26713037 | D30: =(D14/D13) -> 0.28635841 | E30: =(E14/E13) -> 0.27874296 | F30: =(F14/F13) -> 0.27914288 | G30: =(G14/G13) -> 0.27867482 | H30: =(H14/H13) -> #DIV/0! | I30: =(I14/I13) -> #DIV/0! | ... M30: =(M14/M13) -> #DIV/0!

Sheet CSC
A1: Dosa Coffee - CSC | B1: =Summary!C1 -> 46113 | C1: =Summary!D1 -> 46143 | D1: =Summary!E1 -> 46174 | E1: =Summary!F1 -> 46204 | F1: =Summary!G1 -> 46235 | G1: =Summary!H1 -> 46266 | H1: =Summary!I1 -> 46296 | I1: =Summary!J1 -> 46327 | ... M1: =Summary!N1 -> 46447 | N1: FY 2025-26
A2: Food Cost Calculation
A3: Opening Stock | B3: 6073 | C3: =B7 -> 5816.17 | D3: =C7 -> 8416.17 | E3: =D7 -> 7154 | F3: =E7 -> 6599 | G3: =F7 -> 6174.65 | H3: =G7 -> 7033.7 | I3: =H7 | J3: =I7 | ... M3: =L7 | N3: =+SUM(J3:L3) -> 0
A4: Purchases Food (Less Purchase Return) | B4: 32309.34 | C4: 43513.82 | D4: 44125 | E4: 38814 | F4: 42941.73 | G4: 38347.91 | N4: =sum(B4:M4) -> 240051.8
A5: Transferred Out | B5: 0 | C5: 71.7 | D5: 150 | E5: 0 | F5: 0 | G5: 80.89 | N5: =+SUM(J5:L5) -> 0
A6: Wastage & Date Expired | B6: 969.51 | C6: 1038.04 | D6: 1166 | E6: 395.7 | F6: 1369.66 | G6: 1673 | N6: =+SUM(J6:L6) -> 0
A7: Closing Stock | B7: 5816.17 | C7: 8416.17 | D7: 7154 | E7: 6599 | F7: 6174.65 | G7: 7033.7 | N7: =sum(B7:M7) -> 41193.69
A9: Gross Revenue | B9: =100225.27*1.05 -> 105236.53 | C9: =125499.4*1.05 -> 131774.37 | D9: =169953 -> 169953 | E9: =129663.74*1.05 -> 136146.93 | F9: =151447.67*1.05 -> 159020.05 | G9: =126050.93*1.05 -> 132353.48 | N9: =+SUM(B9:M9) -> 834484.36
A10: Catering & Fairs | N10: =+SUM(B10:M10) -> 0
A11: Less Tax | B11: =(B9+B10)/1.05*0.05 -> 5011.2635 | C11: =(C9+C10)/1.05*0.05 -> 6274.97 | D11: =(D9+D10)/1.05*0.05 -> 8093 | E11: =(E9+E10)/1.05*0.05 -> 6483.187 | F11: =(F9+F10)/1.05*0.05 -> 7572.3835 | G11: =(G9+G10)/1.05*0.05 -> 6302.5465 | H11: =(H9+H10)/1.05*0.05 -> 0 | I11: =(I9+I10)/1.05*0.05 -> 0 | ... M11: =(M9+M10)/1.05*0.05 -> 0 | N11: =+SUM(B11:M11) -> 39737.351
A12: Less Commission | N12: =+SUM(B12:M12) -> 0
A13: Net Revenues from F&B Sales | B13: =B9+B10-B11-B12 -> 100225.27 | C13: =C9+C10-C11-C12 -> 125499.4 | D13: =D9+D10-D11-D12 -> 161860 | E13: =E9+E10-E11-E12 -> 129663.74 | F13: =F9+F10-F11-F12 -> 151447.67 | G13: =G9+G10-G11-G12 -> 126050.93 | H13: =H9+H10-H11-H12 -> 0 | I13: =I9+I10-I11-I12 -> 0 | ... M13: =M9+M10-M11-M12 -> 0 | N13: =sum(B13:M13) -> 794747.01
A14: F&B Cost | B14: =+B3+B4-B5-B7 -> 32566.17 | C14: =+C3+C4-C5-C7 -> 40842.12 | D14: =+D3+D4-D5-D7 -> 45237.17 | E14: =+E3+E4-E5-E7 -> 39369 | F14: =+F3+F4-F5-F7 -> 43366.08 | G14: =+G3+G4-G5-G7 -> 37407.97 | H14: =+H3+H4-H5-H7 -> 7033.7 | I14: =+I3+I4-I5-I7 -> 0 | ... M14: =+M3+M4-M5-M7 -> 0 | N14: =sum(B14:M14) -> 245822.21 | O14: =N14/$N$13 -> 0.30930876
A15: Electricity | B15: 0 | C15: 0 | D15: 0 | E15: 0 | F15: 0 | G15: 0 | N15: =sum(B15:M15) -> 0 | O15: =N15/$N$13 -> 0
A16: Telephone/Internet | B16: =588.82 -> 588.82 | C16: =588.82 -> 588.82 | D16: =588.82 -> 588.82 | E16: =588.82 -> 588.82 | F16: =588.82 -> 588.82 | G16: =588.82 -> 588.82 | N16: =sum(B16:M16) -> 3532.92 | O16: =N16/$N$13 -> 0.0044453392
A17: Gas | B17: =6496 -> 6496 | C17: 13013 | D17: 14448 | E17: 15974 | F17: 10500 | G17: 12768 | N17: =sum(B17:M17) -> 73199 | O17: =N17/$N$13 -> 0.092103524
A18: Rent & Revenue Share | B18: 0 | C18: 0 | D18: 0 | E18: 0 | F18: 0 | G18: 0 | N18: =sum(B18:M18) -> 0 | O18: =N18/$N$13 -> 0
A19: Software | B19: 3343.33 | C19: 3343.33 | D19: 3343.33 | E19: 3343.33 | F19: 3343.33 | G19: 3343.33 | N19: =sum(B19:M19) -> 20059.98 | O19: =N19/$N$13 -> 0.025240712
A20: Staff Salary & Bonus | B20: =37960 -> 37960 | C20: =29064 -> 29064 | D20: =34460 -> 34460 | E20: =34460.53 -> 34460.53 | F20: =34460.53 -> 34460.53 | G20: 34461 | N20: =sum(B20:M20) -> 204866.06 | O20: =N20/$N$13 -> 0.25777519
A21: AMC | B21: 0 | C21: 0 | D21: 0 | E21: 1200 | F21: 1650 | G21: 1650 | N21: =sum(B21:M21) -> 4500 | O21: =N21/$N$13 -> 0.0056621792
A22: Subscription | B22: 0 | C22: 0 | D22: 0 | E22: 0 | F22: 0 | G22: 0 | N22: =sum(B22:M22) -> 0 | O22: =N22/$N$13 -> 0
A23: Insurance Premium | B23: 353 | C23: =1698 -> 1698 | D23: =1698 -> 1698 | E23: =1698 -> 1698 | F23: =1698 -> 1698 | G23: =1698 -> 1698 | H23: =1698 -> 1698 | I23: =1698 -> 1698 | J23: =1698 -> 1698 | ... M23: =1698 -> 1698 | N23: =sum(B23:M23) -> 19031 | O23: =N23/$N$13 -> 0.023945985
A24: Repairs & Maintenance | B24: 0 | C24: 0 | D24: 0 | E24: ='Misc Exp'!C133 -> 0 | F24: ='Misc Exp'!C90 -> 3410 | G24: ='Misc Exp'!C43 -> 120 | N24: =sum(B24:M24) -> 3530 | O24: =N24/$N$13 -> 0.004441665
A25: Miscellaneous Expenses | B25: =5104/12+1392 -> 1817.3333 | C25: =5104/12+7968 -> 8393.3333 | D25: =5104/12+6256 -> 6681.3333 | E25: =5104/12+'Misc Exp'!C126 -> 5767.6667 | F25: =5104/12+'Misc Exp'!C90 -> 3835.3333 | G25: =5104/12+'Misc Exp'!C38 -> 8193.3333 | H25: =5104/12 -> 425.33333 | I25: =5104/12 -> 425.33333 | J25: =5104/12 -> 425.33333 | K25: =5104/12 -> 425.33333 | L25: =5104/12 -> 425.33333 | M25: =5104/12 -> 425.33333 | N25: =sum(B25:M25) -> 37240.333 | O25: =N25/$N$13 -> 0.046858098
A26: CAM | B26: 0 | C26: 0 | D26: 0 | E26: 0 | F26: 0 | G26: 0 | N26: =sum(B26:M26) -> 0 | O26: =N26/$N$13 -> 0
A27: HO+CK Cost | B27: =HO!D33 -> 22252.801 | C27: =HO!H33 -> 26365.726 | D27: =HO!L33 -> 35465.116 | E27: =HO!P33 -> 28362.967 | F27: =HO!D52 -> 30068.482 | G27: =HO!H52 -> 28241.458 | H27: =HO!L52 -> #DIV/0! | I27: =HO!P52 -> #DIV/0! | J27: =HO!D71 -> #DIV/0! | K27: =HO!H71 -> #DIV/0! | L27: =HO!L71 -> #DIV/0! | M27: =HO!P71 -> #DIV/0! | N27: =sum(B27:M27) -> #DIV/0! | O27: =N27/$N$13 -> #DIV/0!
A28: Operating Expenses | B28: =+SUM(B14:B27) -> 105377.45 | C28: =+SUM(C14:C27) -> 123308.33 | D28: =+SUM(D14:D27) -> 141921.77 | E28: =+SUM(E14:E27) -> 130764.31 | F28: =+SUM(F14:F27) -> 132920.58 | G28: =+SUM(G14:G27) -> 128471.91 | H28: =+SUM(H14:H27) -> #DIV/0! | I28: =+SUM(I14:I27) -> #DIV/0! | ... M28: =+SUM(M14:M27) -> #DIV/0! | N28: =sum(B28:M28) -> #DIV/0! | O28: =N28/$N$13 -> #DIV/0!
A29: Store Level EBITDA | B29: =B13-B28 -> -5152.184 | C29: =C13-C28 -> 2191.0702 | D29: =D13-D28 -> 19938.231 | E29: =E13-E28 -> -1100.5741 | F29: =F13-F28 -> 18527.095 | G29: =G13-G28 -> -2420.9814 | H29: =H13-H28 -> #DIV/0! | I29: =I13-I28 -> #DIV/0! | ... M29: =M13-M28 -> #DIV/0! | N29: =sum(B29:M29) -> #DIV/0! | O29: =N29/$N$13 -> #DIV/0!
A30: Food Cost | B30: =(B14/B13) -> 0.32492973 | C30: =(C14/C13) -> 0.32543678 | D30: =(D14/D13) -> 0.27948332 | E30: =(E14/E13) -> 0.30362382 | F30: =(F14/F13) -> 0.28634366 | G30: =(G14/G13) -> 0.2967687 | H30: =(H14/H13) -> #DIV/0! | I30: =(I14/I13) -> #DIV/0! | ... M30: =(M14/M13) -> #DIV/0!

Sheet Technopolis
A1: Dosa Coffee - Technopolis | B1: =Summary!C1 -> 46113 | C1: =Summary!D1 -> 46143 | D1: =Summary!E1 -> 46174 | E1: =Summary!F1 -> 46204 | F1: =Summary!G1 -> 46235 | G1: =Summary!H1 -> 46266 | H1: =Summary!I1 -> 46296 | I1: =Summary!J1 -> 46327 | ... M1: =Summary!N1 -> 46447 | N1: FY 2025-26
A2: Food Cost Calculation
A3: Opening Stock | B3: 1603 | C3: =B7 -> 2918.59 | D3: =C7 -> 1713.61 | E3: =D7 -> 1683 | F3: =E7 -> 1357.94 | G3: =F7 -> 1999.5 | H3: =G7 -> 6463 | I3: =H7 | J3: =I7 | ... M3: =L7 | N3: =+SUM(J3:L3) -> 0
A4: Purchases Food (Less Purchase Return) | B4: 22984.18 | C4: 22113.42 | D4: 24161 | E4: 26674.83 | F4: 24641.22 | G4: 28684 | N4: =sum(B4:M4) -> 149258.65
A5: Transferred Out | B5: 0 | C5: 0 | D5: 0 | E5: 124.76 | F5: 0 | G5: 0 | N5: =+SUM(J5:L5) -> 0
A6: Wastage & Date Expired | B6: 251.24 | C6: 1893.67 | D6: 674.55 | E6: 891 | F6: 504.96 | G6: 889 | N6: =+SUM(J6:L6) -> 0
A7: Closing Stock | B7: 2918.59 | C7: 1713.61 | D7: 1683 | E7: 1357.94 | F7: 1999.5 | G7: 6463 | N7: =sum(B7:M7) -> 16135.64
A9: Gross Revenue | B9: =66928.33*1.05 -> 70274.746 | C9: =60107.25*1.05 -> 63112.613 | D9: =71847.78*1.05 -> 75440.169 | E9: =84255.87*1.05 -> 88468.663 | F9: =85698*1.05 -> 89982.9 | G9: =92109.77*1.05 -> 96715.258 | N9: =+SUM(B9:M9) -> 483994.35
A10: Catering & Fairs | N10: =+SUM(B10:M10) -> 0
A11: Less Tax | B11: =(B9+B10)/1.05*0.05 -> 3346.4165 | C11: =(C9+C10)/1.05*0.05 -> 3005.3625 | D11: =(D9+D10)/1.05*0.05 -> 3592.389 | E11: =(E9+E10)/1.05*0.05 -> 4212.7935 | F11: =(F9+F10)/1.05*0.05 -> 4284.9 | G11: =(G9+G10)/1.05*0.05 -> 4605.4885 | H11: =(H9+H10)/1.05*0.05 -> 0 | I11: =(I9+I10)/1.05*0.05 -> 0 | ... M11: =(M9+M10)/1.05*0.05 -> 0 | N11: =+SUM(B11:M11) -> 23047.35
A12: Less Commission | B12: 0 | C12: 0 | N12: =+SUM(B12:M12) -> 0
A13: Net Revenues from F&B Sales | B13: =B9+B10-B11-B12 -> 66928.33 | C13: =C9+C10-C11-C12 -> 60107.25 | D13: =D9+D10-D11-D12 -> 71847.78 | E13: =E9+E10-E11-E12 -> 84255.87 | F13: =F9+F10-F11-F12 -> 85698 | G13: =G9+G10-G11-G12 -> 92109.77 | H13: =H9+H10-H11-H12 -> 0 | I13: =I9+I10-I11-I12 -> 0 | ... M13: =M9+M10-M11-M12 -> 0 | N13: =sum(B13:M13) -> 460947 | O13: =N13/$N$7 -> 28.567011
A14: F&B Cost | B14: =+B3+B4-B5-B7 -> 21668.59 | C14: =+C3+C4-C5-C7 -> 23318.4 | D14: =+D3+D4-D5-D7 -> 24191.61 | E14: =+E3+E4-E5-E7 -> 26875.13 | F14: =+F3+F4-F5-F7 -> 23999.66 | G14: =+G3+G4-G5-G7 -> 24220.5 | H14: =+H3+H4-H5-H7 -> 6463 | I14: =+I3+I4-I5-I7 -> 0 | ... M14: =+M3+M4-M5-M7 -> 0 | N14: =sum(B14:M14) -> 150736.89 | O14: =N14/$N$7 -> 9.34186
A15: Electricity | B15: =4726 -> 4726 | C15: =5351.66 -> 5351.66 | D15: 5253.63 | E15: 4845.77 | F15: =4860.02 -> 4860.02 | G15: 5000 | N15: =sum(B15:M15) -> 30037.08 | O15: =N15/$N$7 -> 1.8615363
A16: Telephone/Internet | B16: =588.82 -> 588.82 | C16: =588.82 -> 588.82 | D16: =588.82 -> 588.82 | E16: =588.82 -> 588.82 | F16: =588.82 -> 588.82 | G16: =588.82 -> 588.82 | N16: =sum(B16:M16) -> 3532.92 | O16: =N16/$N$7 -> 0.21895134
A17: Gas | B17: 939 | C17: 939 | D17: 3255 | E17: 1936 | F17: =968 -> 968 | G17: =2904 -> 2904 | N17: =sum(B17:M17) -> 10941 | O17: =N17/$N$7 -> 0.67806421
A18: Rent & Revenue Share | B18: =11846 -> 11846 | C18: 10639 | D18: =D13*0.177 -> 12717.057 | E18: 15090 | F18: 15090 | G18: =(F18/F13)*G13 -> 16219.007 | N18: =sum(B18:M18) -> 81601.064 | O18: =N18/$N$7 -> 5.0571941
A19: Software | B19: 3343.33 | C19: 3343.33 | D19: 3343.33 | E19: 3343.33 | F19: 3343.33 | G19: 3343.33 | N19: =sum(B19:M19) -> 20059.98 | O19: =N19/$N$7 -> 1.2432094
A20: Staff Salary | B20: =19313 -> 19313 | C20: =19899 -> 19899 | D20: =19899 -> 19899 | E20: =19899.24 -> 19899.24 | F20: =19899 -> 19899 | G20: =19899 -> 19899 | N20: =sum(B20:M20) -> 118808.24 | O20: =N20/$N$7 -> 7.3630944
A21: AMC | B21: 0 | C21: 0 | D21: 0 | E21: 0 | F21: 0 | G21: 0 | N21: =sum(B21:M21) -> 0 | O21: =N21/$N$7 -> 0
A22: Subscription | B22: 0 | C22: 0 | D22: 0 | E22: 0 | F22: 0 | G22: 0
A23: Insurance Premium | B23: =(4900+18306)/12 -> 1933.8333 | C23: =(4900+18306)/12 -> 1933.8333 | D23: =(4900+18306)/12 -> 1933.8333 | E23: =(4900+18306)/12 -> 1933.8333 | F23: =(4900+18306)/12 -> 1933.8333 | G23: =(4900+18306)/12 -> 1933.8333 | H23: =(4900+18306)/12 -> 1933.8333 | I23: =(4900+18306)/12 -> 1933.8333 | ... M23: =(4900+18306)/12 -> 1933.8333
A24: Repairs & Maintenance | B24: 0 | C24: 0 | D24: 0 | E24: ='Misc Exp'!R133 -> 0 | F24: ='Misc Exp'!R90 -> 32080 | G24: ='Misc Exp'!R43 -> 0 | N24: =sum(B24:M24) -> 32080 | O24: =N24/$N$7 -> 1.9881455
A25: Miscellaneous Expenses | B25: =1550/12+159.56 -> 288.72667 | C25: =1550/12+6962.26 -> 7091.4267 | D25: =1550/12+196 -> 325.16667 | E25: =1550/12+'Misc Exp'!R126 -> 532.06 | F25: =1550/12+'Misc Exp'!R84 -> 3520.5267 | G25: =1550/12+'Misc Exp'!R38 -> 6607.6467 | H25: =1550/12 -> 129.16667 | I25: =1550/12 -> 129.16667 | J25: =1550/12 -> 129.16667 | K25: =1550/12 -> 129.16667 | L25: =1550/12 -> 129.16667 | M25: =1550/12 -> 129.16667 | N25: =sum(B25:M25) -> 19140.553 | O25: =N25/$N$7 -> 1.1862283
A26: CAM | B26: 0 | C26: 0 | D26: 0 | E26: 0 | F26: 0 | G26: 0 | H26: 0 | I26: 0 | J26: 0 | K26: 0 | L26: 0 | M26: 0 | N26: =sum(B26:M26) -> 0 | O26: =N26/$N$7 -> 0
A27: HO+CK Cost | B27: =HO!D35 -> 14859.953 | C27: =HO!H35 -> 12627.72 | D27: =HO!L35 -> 15742.554 | E27: =HO!P35 -> 18430.338 | F27: =HO!D54 -> 17014.516 | G27: =HO!H54 -> 20637.009 | H27: =HO!L54 -> #DIV/0! | I27: =HO!P54 -> #DIV/0! | J27: =HO!D73 -> #DIV/0! | K27: =HO!H73 -> #DIV/0! | L27: =HO!L73 -> #DIV/0! | M27: =HO!P73 -> #DIV/0! | N27: =sum(B27:M27) -> #DIV/0! | O27: =N27/$N$7 -> #DIV/0!
A28: Operating Expenses | B28: =+SUM(B14:B27) -> 79507.253 | C28: =+SUM(C14:C27) -> 85732.19 | D28: =+SUM(D14:D27) -> 87250.001 | E28: =+SUM(E14:E27) -> 93474.521 | F28: =+SUM(F14:F27) -> 123297.71 | G28: =+SUM(G14:G27) -> 101353.15 | H28: =+SUM(H14:H27) -> #DIV/0! | I28: =+SUM(I14:I27) -> #DIV/0! | ... M28: =+SUM(M14:M27) -> #DIV/0! | N28: =sum(B28:M28) -> #DIV/0! | O28: =N28/$N$7 -> #DIV/0!
A29: Store Level EBITDA | B29: =B13-B28 -> -12578.923 | C29: =C13-C28 -> -25624.94 | D29: =D13-D28 -> -15402.221 | E29: =E13-E28 -> -9218.6509 | F29: =F13-F28 -> -37599.706 | G29: =G13-G28 -> -9243.3758 | H29: =H13-H28 -> #DIV/0! | I29: =I13-I28 -> #DIV/0! | ... M29: =M13-M28 -> #DIV/0! | N29: =sum(B29:M29) -> #DIV/0! | O29: =N29/$N$7 -> #DIV/0!
A30: Food Cost | B30: =(B14/B13) -> 0.32375812 | C30: =(C14/C13) -> 0.38794655 | D30: =(D14/D13) -> 0.33670644 | E30: =(E14/E13) -> 0.31897042 | F30: =(F14/F13) -> 0.28004924 | G30: =(G14/G13) -> 0.26295256 | H30: =(H14/H13) -> #DIV/0! | I30: =(I14/I13) -> #DIV/0! | ... M30: =(M14/M13) -> #DIV/0!

Sheet Forum Rangoli
A1: Dosa Coffee - Forum Rangoli | B1: =Summary!C1 -> 46113 | C1: =Summary!D1 -> 46143 | D1: =Summary!E1 -> 46174 | E1: =Summary!F1 -> 46204 | F1: =Summary!G1 -> 46235 | G1: =Summary!H1 -> 46266 | H1: =Summary!I1 -> 46296 | I1: =Summary!J1 -> 46327 | ... M1: =Summary!N1 -> 46447 | N1: FY 2025-26
A2: Food Cost Calculation
A3: Opening Stock | B3: 47968 | C3: =B7 -> 45542.3 | D3: =C7 -> 60523.93 | E3: =D7 -> 44301 | F3: =E7 -> 38073 | G3: =F7 -> 39365.18 | H3: =G7 -> 43465.95 | I3: =H7 | J3: =I7 | ... M3: =L7 | N3: =+SUM(J3:L3) -> 0
A4: Purchases Food (Less Purchase Return) | B4: 286806.81 | C4: 358998.03 | D4: 312072.88 | E4: 311177 | F4: 372050.15 | G4: 329652 | N4: =sum(B4:M4) -> 1970756.9
A5: Transferred Out | B5: 178.26 | C5: 0 | D5: 0 | E5: 0 | F5: 0 | G5: 0 | N5: =+SUM(J5:L5) -> 0
A6: Wastage & Date Expired | B6: 10792.82 | C6: 12591.71 | D6: 11895 | E6: 9557 | F6: 15854.91 | G6: 19467.56 | N6: =+SUM(J6:L6) -> 0
A7: Closing Stock | B7: 45542.3 | C7: 60523.93 | D7: 44301 | E7: 38073 | F7: 39365.18 | G7: 43465.95 | N7: =sum(B7:M7) -> 271271.36
A9: Gross Revenue | B9: =1109095.63*1.05+19177.88*1.05 -> 1184687.2 | C9: =1399774.46*1.05+21006.81*1.05 -> 1491820.3 | D9: =1221152.63*1.05+19944.37*1.05 -> 1303151.9 | E9: =1145504*1.05+19902.7*1.05 -> 1223677 | F9: =1409544.58*1.05 -> 1480021.8 | G9: =1255530.46*1.05+16550.7*1.05 -> 1335685.2 | N9: =+SUM(B9:M9) -> 8019043.4
A10: Catering & Fairs | N10: =+SUM(B10:M10) -> 0
A11: Less Tax | B11: =(B9+B10)/1.05*0.05 -> 56413.675 | C11: =(C9+C10)/1.05*0.05 -> 71039.064 | D11: =(D9+D10)/1.05*0.05 -> 62054.85 | E11: =(E9+E10)/1.05*0.05 -> 58270.335 | F11: =(F9+F10)/1.05*0.05 -> 70477.229 | G11: =(G9+G10)/1.05*0.05 -> 63604.058 | H11: =(H9+H10)/1.05*0.05 -> 0 | I11: =(I9+I10)/1.05*0.05 -> 0 | ... M11: =(M9+M10)/1.05*0.05 -> 0 | N11: =+SUM(B11:M11) -> 381859.21
A12: Less Commission | B12: =44354.67*1.18+12858.68*1.18+3251.57*1.18+55.19*1.18+41.53*1.18 -> 71462.735 | C12: =48814.67*1.18+14377.75*1.18+138.93*1.18+4059.94*1.18 -> 79521.722 | D12: =46830.06*1.18+16034.79*1.18+20.68*1.18+33.12*1.18 -> 74244.007 | E12: =46350.99*1.18+14613.69*1.18 -> 71938.322 | F12: =49001.44*1.18+16132*1.18+47.11*1.18 -> 76913.049 | G12: =38415.57*1.18+17031.53*1.18+101.43*1.18 -> 65547.265 | N12: =+SUM(B12:M12) -> 439627.1
A13: Net Revenues from F&B Sales | B13: =B9+B10-B11-B12 -> 1056810.8 | C13: =C9+C10-C11-C12 -> 1341259.5 | D13: =D9+D10-D11-D12 -> 1166853 | E13: =E9+E10-E11-E12 -> 1093468.4 | F13: =F9+F10-F11-F12 -> 1332631.5 | G13: =G9+G10-G11-G12 -> 1206533.9 | H13: =H9+H10-H11-H12 -> 0 | I13: =I9+I10-I11-I12 -> 0 | ... M13: =M9+M10-M11-M12 -> 0 | N13: =sum(B13:M13) -> 7197557.1
A14: F&B Cost | B14: =+B3+B4-B5-B7 -> 289054.25 | C14: =+C3+C4-C5-C7 -> 344016.4 | D14: =+D3+D4-D5-D7 -> 328295.81 | E14: =+E3+E4-E5-E7 -> 317405 | F14: =+F3+F4-F5-F7 -> 370757.97 | G14: =+G3+G4-G5-G7 -> 325551.23 | H14: =+H3+H4-H5-H7 -> 43465.95 | I14: =+I3+I4-I5-I7 -> 0 | ... M14: =+M3+M4-M5-M7 -> 0 | N14: =sum(B14:M14) -> 2018546.6 | O14: =N14/$N$13 -> 0.28044885
A15: Electricity | B15: =55085 -> 55085 | C15: 66149 | D15: 60573 | E15: 61311 | F15: =63957 -> 63957 | G15: 62000 | N15: =sum(B15:M15) -> 369075 | O15: =N15/$N$13 -> 0.051277815
A16: Telephone/Internet | B16: =800+352.82 -> 1152.82 | C16: =800+352.82 -> 1152.82 | D16: =800+352.82 -> 1152.82 | E16: =352.82+800 -> 1152.82 | F16: =352.82+800 -> 1152.82 | G16: =352.82+800 -> 1152.82 | N16: =sum(B16:M16) -> 6916.92 | O16: =N16/$N$13 -> 0.00096100939
A17: Gas | B17: 0 | C17: 0 | D17: 0 | E17: 0 | F17: 0 | G17: 0 | N17: =sum(B17:M17) -> 0 | O17: =N17/$N$13 -> 0
A18: Rent & Revenue Share | B18: =153393 -> 153393 | C18: 195957 | D18: 169670 | E18: 158470 | F18: =194528 -> 194528 | G18: =(F18/F13)*G13 -> 176121.17 | N18: =sum(B18:M18) -> 1048139.2 | O18: =N18/$N$13 -> 0.14562429
A19: Software | B19: =5767 -> 5767 | C19: =5767 -> 5767 | D19: =5767 -> 5767 | E19: =5767 -> 5767 | F19: =69207/12 -> 5767.25 | G19: =69207/12 -> 5767.25 | H19: =69207/12 -> 5767.25 | I19: =69207/12 -> 5767.25 | J19: =69207/12 -> 5767.25 | K19: =69207/12 -> 5767.25 | L19: =69207/12 -> 5767.25 | M19: =69207/12 -> 5767.25 | N19: =sum(B19:M19) -> 69206 | O19: =N19/$N$13 -> 0.0096152068
A20: Staff Salary & Bonus | B20: =3864+198355 -> 202219 | C20: =3500+835+220079 -> 224414 | D20: =3500+236180 -> 239680 | E20: =3300+222140.54 -> 225440.54 | F20: =210429+3300 -> 213729 | G20: =3300+216097.88 -> 219397.88 | N20: =sum(B20:M20) -> 1324880.4 | O20: =N20/$N$13 -> 0.18407362
A21: AMC | B21: =3457+3115 -> 6572 | C21: =3457+3115 -> 6572 | D21: =3457+3115 -> 6572 | E21: =3457+3115 -> 6572 | F21: =3115+3457 -> 6572 | G21: =3115+3457 -> 6572 | N21: =sum(B21:M21) -> 39432 | O21: =N21/$N$13 -> 0.0054785255
A22: Subscription | B22: =2516.16/3+9813/12+7080/12 -> 2246.47 | C22: =2516.16/3+9813/12+7080/12 -> 2246.47 | D22: =2516.16/3+9813/12+7080/12 -> 2246.47 | E22: =2516.16/3+9813/12+7080/12 -> 2246.47 | F22: =2516.16/3+9813/12+7080/12 -> 2246.47 | G22: =2516.16/3+9813/12+7080/12 -> 2246.47 | H22: =9813/12 -> 817.75 | I22: =9813/12 -> 817.75 | J22: =9813/12 -> 817.75 | K22: =9813/12 -> 817.75 | L22: =9813/12 -> 817.75 | M22: =9813/12 -> 817.75 | N22: =sum(B22:M22) -> 18385.32 | O22: =N22/$N$13 -> 0.0025543833
A23: Insurance Premium | B23: =991 -> 991 | C23: =1698 -> 1698 | D23: =1698 -> 1698 | E23: =1698 -> 1698 | F23: =1698 -> 1698 | G23: =1698 -> 1698 | H23: =1698 -> 1698 | I23: =1698 -> 1698 | J23: =1698 -> 1698 | ... M23: =1698 -> 1698 | N23: =sum(B23:M23) -> 19669 | O23: =N23/$N$13 -> 0.0027327327
A24: Repairs & Maintenance | B24: 2000 | C24: 1700 | D24: 800 | E24: ='Misc Exp'!I133 -> 800 | F24: ='Misc Exp'!I90 -> 255391 | G24: ='Misc Exp'!I43 -> 915 | N24: =sum(B24:M24) -> 261606 | O24: =N24/$N$13 -> 0.036346499
A25: Miscellaneous Expenses | B25: 6956.71 | C25: 22647.94 | D25: 7546 | E25: ='Misc Exp'!I126 -> 50446.813 | F25: ='Misc Exp'!I84 -> 6669.46 | G25: ='Misc Exp'!I38 -> 19826.66 | N25: =sum(B25:M25) -> 114093.58 | O25: =N25/$N$13 -> 0.015851709
A26: CAM | B26: 84370 | C26: 84370 | D26: 84370 | E26: 96617 | F26: 97026 | G26: 97026 | N26: =sum(B26:M26) -> 543779 | O26: =N26/$N$13 -> 0.075550495
A27: HO+CK Cost | B27: =HO!D32 -> 234641.42 | C27: =HO!H32 -> 281780.49 | D27: =HO!L32 -> 255668.95 | E27: =HO!P32 -> 239187.98 | F27: =HO!D51 -> 264581.21 | G27: =HO!H51 -> 270321.5 | H27: =HO!L51 -> #DIV/0! | I27: =HO!P51 -> #DIV/0! | J27: =HO!D70 -> #DIV/0! | K27: =HO!H70 -> #DIV/0! | L27: =HO!L70 -> #DIV/0! | M27: =HO!P70 -> #DIV/0! | N27: =sum(B27:M27) -> #DIV/0! | O27: =N27/$N$13 -> #DIV/0!
A28: Operating Expenses | B28: =+SUM(B14:B27) -> 1044448.7 | C28: =+SUM(C14:C27) -> 1238471.1 | D28: =+SUM(D14:D27) -> 1164040.1 | E28: =+SUM(E14:E27) -> 1167114.6 | F28: =+SUM(F14:F27) -> 1484076.2 | G28: =+SUM(G14:G27) -> 1188596 | H28: =+SUM(H14:H27) -> #DIV/0! | I28: =+SUM(I14:I27) -> #DIV/0! | ... M28: =+SUM(M14:M27) -> #DIV/0! | N28: =sum(B28:M28) -> #DIV/0! | O28: =N28/$N$13 -> #DIV/0!
A29: Store Level EBITDA | B29: =B13-B28 -> 12362.107 | C29: =C13-C28 -> 102788.43 | D29: =D13-D28 -> 2812.9421 | E29: =E13-E28 -> -73646.245 | F29: =F13-F28 -> -151444.65 | G29: =G13-G28 -> 17937.915 | H29: =H13-H28 -> #DIV/0! | I29: =I13-I28 -> #DIV/0! | ... M29: =M13-M28 -> #DIV/0! | N29: =sum(B29:M29) -> #DIV/0! | O29: =N29/$N$13 -> #DIV/0!
A30: Food Cost | B30: =(B14/B13) -> 0.27351562 | C30: =(C14/C13) -> 0.25648757 | D30: =(D14/D13) -> 0.28135147 | E30: =(E14/E13) -> 0.2902736 | F30: =(F14/F13) -> 0.27821492 | G30: =(G14/G13) -> 0.26982353 | H30: =(H14/H13) -> #DIV/0! | I30: =(I14/I13) -> #DIV/0! | ... M30: =(M14/M13) -> #DIV/0!

Sheet Jameslong
A1: Dosa Coffee - Jameslong Sarani | B1: =Summary!C1 -> 46113 | C1: =Summary!D1 -> 46143 | D1: =Summary!E1 -> 46174 | E1: =Summary!F1 -> 46204 | F1: =Summary!G1 -> 46235 | G1: =Summary!H1 -> 46266 | H1: =Summary!I1 -> 46296 | I1: =Summary!J1 -> 46327 | ... M1: =Summary!N1 -> 46447 | N1: FY 2025-26
A2: Food Cost Calculation
A3: Opening Stock | B3: 34826 | C3: =B7 -> 40407.74 | D3: =C7 -> 41084.72 | E3: =D7 -> 44677.69 | F3: =E7 -> 35601 | G3: =F7 -> 29069.5 | H3: =G7 -> 29112 | I3: =H7 | J3: =I7 | ... M3: =L7 | N3: =+SUM(J3:L3) -> 0
A4: Purchases Food (Less Purchase Return) | B4: 358980.56 | C4: 403701 | D4: 398780 | E4: 431006 | F4: 452253.79 | G4: 436470.58 | N4: =sum(B4:M4) -> 2481191.9
A5: Transferred Out | B5: 305.14 | C5: -232.42 | D5: 0 | E5: 617 | F5: 127.66 | G5: 1840.43 | N5: =+SUM(J5:L5) -> 0
A6: Wastage & Date Expired | B6: 13917.07 | C6: 15769.19 | D6: 16562 | E6: 15466 | F6: 28717.49 | G6: 30067 | N6: =+SUM(J6:L6) -> 0
A7: Closing Stock | B7: 40407.74 | C7: 41084.72 | D7: 44677.69 | E7: 35601 | F7: 29069.5 | G7: 29112 | N7: =sum(B7:M7) -> 219952.65
A9: Gross Revenue | B9: =1334894.42*1.05+35530.65*1.05 -> 1438946.3 | C9: =1530373.97*1.05+36488.76*1.05 -> 1645205.9 | D9: =1479924.29*1.05+36035.99*1.05 -> 1591758.3 | E9: =1592393.33*1.05+39546.44*1.05 -> 1713536.8 | F9: =1811478.97*1.05 -> 1902052.9 | G9: =1653240.94*1.05+45232.07*1.05 -> 1783396.7 | N9: =+SUM(B9:M9) -> 10074897
A10: Catering & Fairs | N10: =+SUM(B10:M10) -> 0
A11: Less Tax | B11: =(B9+B10)/1.05*0.05 -> 68521.254 | C11: =(C9+C10)/1.05*0.05 -> 78343.136 | D11: =(D9+D10)/1.05*0.05 -> 75798.014 | E11: =(E9+E10)/1.05*0.05 -> 81596.989 | F11: =(F9+F10)/1.05*0.05 -> 90573.948 | G11: =(G9+G10)/1.05*0.05 -> 84923.651 | H11: =(H9+H10)/1.05*0.05 -> 0 | I11: =(I9+I10)/1.05*0.05 -> 0 | ... M11: =(M9+M10)/1.05*0.05 -> 0 | N11: =+SUM(B11:M11) -> 479756.99
A12: Less Commission | B12: =82836.46*1.18+44469.12*1.18+9617.35*1.18+1608.62*1.18+98.86*1.18 -> 163583.88 | C12: =84885.15*1.18+52884.98*1.18+99.54*1.18+1317.38*1.18+21476.38*1.18 -> 189582.85 | D12: =1874.42*1.18+66764.41*1.05+713.6*1.18+21.15*1.18+5.67*1.18+84678.35*1.18 -> 173108.59 | E12: =91896.72*1.18+913.55*1.18+79263*1.18 -> 203046.46 | F12: =101776.34*1.18+88147.52*1.18+2030.85*1.18 -> 226506.56 | G12: =105047.39*1.18+83113.41*1.18+403.12*1.18+10.35*1.18 -> 222517.64 | N12: =+SUM(B12:M12) -> 1178346
A13: Net Revenues from F&B Sales | B13: =B9+B10-B11-B12 -> 1206841.2 | C13: =C9+C10-C11-C12 -> 1377279.9 | D13: =D9+D10-D11-D12 -> 1342851.7 | E13: =E9+E10-E11-E12 -> 1428893.3 | F13: =F9+F10-F11-F12 -> 1584972.4 | G13: =G9+G10-G11-G12 -> 1475955.4 | H13: =H9+H10-H11-H12 -> 0 | I13: =I9+I10-I11-I12 -> 0 | ... M13: =M9+M10-M11-M12 -> 0 | N13: =sum(B13:M13) -> 8416793.8
A14: F&B Cost | B14: =+B3+B4-B5-B7 -> 353093.68 | C14: =+C3+C4-C5-C7 -> 403256.44 | D14: =+D3+D4-D5-D7 -> 395187.03 | E14: =+E3+E4-E5-E7 -> 439465.69 | F14: =+F3+F4-F5-F7 -> 458657.63 | G14: =+G3+G4-G5-G7 -> 434587.65 | H14: =+H3+H4-H5-H7 -> 29112 | I14: =+I3+I4-I5-I7 -> 0 | ... M14: =+M3+M4-M5-M7 -> 0 | N14: =sum(B14:M14) -> 2513360.1 | O14: =N14/$N$13 -> 0.29861253
A15: Electricity | B15: 59120 | C15: 70800 | D15: 70820 | E15: 68740 | F15: =69480 -> 69480 | G15: 69000 | N15: =sum(B15:M15) -> 407960 | O15: =N15/$N$13 -> 0.048469763
A16: Telephone/Internet | B16: =352.82 -> 352.82 | C16: =352.82 -> 352.82 | D16: =352.82 -> 352.82 | E16: =352.82 -> 352.82 | F16: =352.82 -> 352.82 | G16: =352.82 -> 352.82 | N16: =sum(B16:M16) -> 2116.92 | O16: =N16/$N$13 -> 0.00025151145
A17: Gas | B17: =8832+15456 -> 24288 | C17: =22414+22414+25616 -> 70444 | D17: 68365 | E17: 70875 | F17: =67141 -> 67141 | G17: =61798 -> 61798 | N17: =sum(B17:M17) -> 362911 | O17: =N17/$N$13 -> 0.043117487
A18: Rent & Revenue Share | B18: =159536 -> 159536 | C18: =159536 -> 159536 | D18: =159536 -> 159536 | E18: =159536 -> 159536 | F18: =159536 -> 159536 | G18: 165917 | N18: =sum(B18:M18) -> 963597 | O18: =N18/$N$13 -> 0.11448504
A19: Software | B19: 6352 | C19: 6352 | D19: 6352 | E19: 6352 | F19: 6352 | G19: 6352 | N19: =sum(B19:M19) -> 38112 | O19: =N19/$N$13 -> 0.00452809
A20: Staff Salary | B20: =3100+170797 -> 173897 | C20: =3100+600+187387 -> 191087 | D20: =3100+200860.85 -> 203960.85 | E20: =3300+202123.84 -> 205423.84 | F20: =185779+3300 -> 189079 | G20: =3300+211917 -> 215217 | N20: =sum(B20:M20) -> 1178664.7 | O20: =N20/$N$13 -> 0.14003725
A21: AMC | B21: =2360+2560+2478 -> 7398 | C21: =2360+2560+2478 -> 7398 | D21: =1200+2596+2726+1200 -> 7722 | E21: =2360+2596+2726+3000 -> 10682 | F21: =2100+2596+2726+2360 -> 9782 | G21: =2100+2596+2726+2360 -> 9782 | N21: =sum(B21:M21) -> 52764 | O21: =N21/$N$13 -> 0.0062688954
A22: Subscription | B22: =2516.16/3+9000/3+9813/12+7080/12 -> 5246.47 | C22: =2516.16/3+9000/3+9813/12+7080/12 -> 5246.47 | D22: =2516.16/3+9000/3+9813/12+7080/12 -> 5246.47 | E22: =2516.16/3+9000/3+9813/12+7080/12 -> 5246.47 | F22: =2516.16/3+9000/3+9813/12+7080/12 -> 5246.47 | G22: =2516.16/3+9000/3+9813/12+7080/12 -> 5246.47 | H22: =9813/12 -> 817.75 | I22: =9813/12 -> 817.75 | J22: =9813/12 -> 817.75 | K22: =9813/12 -> 817.75 | L22: =9813/12 -> 817.75 | M22: =9813/12 -> 817.75 | N22: =sum(B22:M22) -> 36385.32 | O22: =N22/$N$13 -> 0.004322943
A23: Insurance Premium | B23: 1078 | C23: =1698 -> 1698 | D23: =1698 -> 1698 | E23: =1698 -> 1698 | F23: =1698 -> 1698 | G23: =1698 -> 1698 | H23: =1698 -> 1698 | I23: =1698 -> 1698 | J23: =1698 -> 1698 | ... M23: =1698 -> 1698 | N23: =sum(B23:M23) -> 19756 | O23: =N23/$N$13 -> 0.0023472121
A24: Repairs & Maintenance | B24: 1046 | C24: 983 | D24: 10416 | E24: ='Misc Exp'!J133 -> 29651 | F24: ='Misc Exp'!J90 -> 17949 | G24: ='Misc Exp'!J43 -> 4112 | N24: =sum(B24:M24) -> 64157 | O24: =N24/$N$13 -> 0.0076224987
A25: Miscellaneous Expenses | B25: 11363.71 | C25: =29914.19 -> 29914.19 | D25: 9923.9 | E25: ='Misc Exp'!J126 -> 24999.183 | F25: ='Misc Exp'!J84 -> 27372.4 | G25: ='Misc Exp'!J38 -> 22200.07 | N25: =sum(B25:M25) -> 125773.45 | O25: =N25/$N$13 -> 0.014943155
A26: CAM | B26: 0 | C26: 0 | D26: 0 | E26: 0 | F26: 0 | G26: 0 | N26: =sum(B26:M26) -> 0 | O26: =N26/$N$13 -> 0
A27: HO+CK Cost | B27: =HO!D34 -> 267952.35 | C27: =HO!H34 -> 289347.87 | D27: =HO!L34 -> 294231.99 | E27: =HO!P34 -> 312559.66 | F27: =HO!D53 -> 314681.07 | G27: =HO!H53 -> 330684.84 | H27: =HO!L53 -> #DIV/0! | I27: =HO!P53 -> #DIV/0! | J27: =HO!D72 -> #DIV/0! | K27: =HO!H72 -> #DIV/0! | L27: =HO!L72 -> #DIV/0! | M27: =HO!P72 -> #DIV/0! | N27: =sum(B27:M27) -> #DIV/0! | O27: =N27/$N$13 -> #DIV/0!
A28: Operating Expenses | B28: =+SUM(B14:B27) -> 1070724 | C28: =+SUM(C14:C27) -> 1236415.8 | D28: =+SUM(D14:D27) -> 1233812.1 | E28: =+SUM(E14:E27) -> 1335581.7 | F28: =+SUM(F14:F27) -> 1327327.4 | G28: =+SUM(G14:G27) -> 1326947.9 | H28: =+SUM(H14:H27) -> #DIV/0! | I28: =+SUM(I14:I27) -> #DIV/0! | ... M28: =+SUM(M14:M27) -> #DIV/0! | N28: =sum(B28:M28) -> #DIV/0! | O28: =N28/$N$13 -> #DIV/0!
A29: Store Level EBITDA | B29: =B13-B28 -> 136117.16 | C29: =C13-C28 -> 140864.09 | D29: =D13-D28 -> 109039.62 | E29: =E13-E28 -> 93311.648 | F29: =F13-F28 -> 257645.02 | G29: =G13-G28 -> 149007.52 | H29: =H13-H28 -> #DIV/0! | I29: =I13-I28 -> #DIV/0! | ... M29: =M13-M28 -> #DIV/0! | N29: =sum(B29:M29) -> #DIV/0! | O29: =N29/$N$13 -> #DIV/0!
A30: Food Cost | B30: =(B14/B13) -> 0.29257676 | C30: =(C14/C13) -> 0.29279193 | D30: =(D14/D13) -> 0.29428941 | E30: =(E14/E13) -> 0.30755668 | F30: =(F14/F13) -> 0.28937894 | G30: =(G14/G13) -> 0.29444498 | H30: =(H14/H13) -> #DIV/0! | I30: =(I14/I13) -> #DIV/0! | ... M30: =(M14/M13) -> #DIV/0!

Sheet Sector 1
A1: Dosa Coffee - Sector 1 | B1: =Summary!C1 -> 46113 | C1: =Summary!D1 -> 46143 | D1: =Summary!E1 -> 46174 | E1: =Summary!F1 -> 46204 | F1: =Summary!G1 -> 46235 | G1: =Summary!H1 -> 46266 | H1: =Summary!I1 -> 46296 | I1: =Summary!J1 -> 46327 | ... M1: =Summary!N1 -> 46447 | N1: FY 2025-26
A2: Food Cost Calculation
A3: Opening Stock | B3: 42775 | C3: =B7 -> 49260.08 | D3: =C7 -> 45210.94 | E3: =D7 -> 44903 | F3: =E7 -> 32962 | G3: =F7 -> 41371 | H3: =G7 -> 41268 | I3: =H7 | J3: =I7 | ... M3: =L7 | N3: =+SUM(J3:L3) -> 0
A4: Purchases Food (Less Purchase Return) | B4: 576251.31 | C4: 620133.58 | D4: 605345 | E4: 611396 | F4: 674094.52 | G4: 591238.98 | N4: =sum(B4:M4) -> 3678459.4
A5: Transferred Out | B5: 2905.24 | C5: 1347.91 | D5: 98.75 | E5: 649 | F5: 1158 | G5: 2160.4 | N5: =+SUM(J5:L5) -> 0
A6: Wastage & Date Expired | B6: 22698.2 | C6: 23405.85 | D6: 23805 | E6: 25975 | F6: 26507 | G6: 27194 | N6: =+SUM(J6:L6) -> 0
A7: Closing Stock | B7: 49260.08 | C7: 45210.94 | D7: 44903 | E7: 32962 | F7: 41371 | G7: 41268 | N7: =sum(B7:M7) -> 254975.02
A9: Gross Revenue | B9: =2470922.82*1.05+34561.38*1.05 -> 2630758.4 | C9: =2688845.21*1.05+31444.11*1.05 -> 2856303.8 | D9: =2506372.74*1.05+30138.86*1.05 -> 2663337.2 | E9: =2577742.46*1.05+32051.15*1.05 -> 2740283.3 | F9: =2864382.33*1.05 -> 3007601.4 | G9: =2441866.4*1.05+31897*1.105 -> 2599205.9 | N9: =+SUM(B9:M9) -> 16497490
A10: Catering & Fairs | N10: =+SUM(B10:M10) -> 0
A11: Less Tax | B11: =(B9+B10)/1.05*0.05 -> 125274.21 | C11: =(C9+C10)/1.05*0.05 -> 136014.47 | D11: =(D9+D10)/1.05*0.05 -> 126825.58 | E11: =(E9+E10)/1.05*0.05 -> 130489.68 | F11: =(F9+F10)/1.05*0.05 -> 143219.12 | G11: =(G9+G10)/1.05*0.05 -> 123771.71 | H11: =(H9+H10)/1.05*0.05 -> 0 | I11: =(I9+I10)/1.05*0.05 -> 0 | ... M11: =(M9+M10)/1.05*0.05 -> 0 | N11: =+SUM(B11:M11) -> 785594.76
A12: Less Commission | B12: =82426.71*1.18+60223.11*1.18+9374.77*1.18+3920.75*1.18+5.67*1.18 -> 184022.19 | C12: =76130.54*1.18+48673.52*1.18+678.75*1.18+7154.4*1.18+18079.63*1.18 -> 177845.87 | D12: =72075.26*1.18+63122.23*1.18+2795.69*1.18 -> 162831.95 | E12: =77597*1.18+4423.92*1.18+22.95*1.18+66867*1.18 -> 175714.83 | F12: =81126.94*1.18+66426.52*1.18+5020.23*1.18 -> 180036.95 | G12: =76824.82*1.18+66124.5*1.18+2.92*1.18 -> 168683.64 | N12: =+SUM(B12:M12) -> 1049135.4
A13: Net Revenues from F&B Sales | B13: =B9+B10-B11-B12 -> 2321462 | C13: =C9+C10-C11-C12 -> 2542443.4 | D13: =D9+D10-D11-D12 -> 2373679.6 | E13: =E9+E10-E11-E12 -> 2434078.8 | F13: =F9+F10-F11-F12 -> 2684345.4 | G13: =G9+G10-G11-G12 -> 2306750.6 | H13: =H9+H10-H11-H12 -> 0 | I13: =I9+I10-I11-I12 -> 0 | ... M13: =M9+M10-M11-M12 -> 0 | N13: =sum(B13:M13) -> 14662760
A14: F&B Cost | B14: =+B3+B4-B5-B7 -> 566860.99 | C14: =+C3+C4-C5-C7 -> 622834.81 | D14: =+D3+D4-D5-D7 -> 605554.19 | E14: =+E3+E4-E5-E7 -> 622688 | F14: =+F3+F4-F5-F7 -> 664527.52 | G14: =+G3+G4-G5-G7 -> 589181.58 | H14: =+H3+H4-H5-H7 -> 41268 | I14: =+I3+I4-I5-I7 -> 0 | ... M14: =+M3+M4-M5-M7 -> 0 | N14: =sum(B14:M14) -> 3712915.1 | O14: =N14/$N$13 -> 0.25322075
A15: Electricity | B15: 79068.55 | C15: 79793.18 | D15: =76311 -> 76311 | E15: 70952 | F15: 69341 | G15: 68580 | N15: =sum(B15:M15) -> 444045.73 | O15: =N15/$N$13 -> 0.030283912
A16: Telephone/Internet | B16: =291+352.82 -> 643.82 | C16: =291+352.82 -> 643.82 | D16: =291+352.82 -> 643.82 | E16: =352.82+291 -> 643.82 | F16: =291+3540/12+352.82 -> 938.82 | G16: =3540/12+352.82 -> 647.82 | H16: =3540/12 -> 295 | I16: =3540/12 -> 295 | J16: =3540/12 -> 295 | K16: =3540/12 -> 295 | L16: =3540/12 -> 295 | M16: =3540/12 -> 295 | N16: =sum(B16:M16) -> 5931.92 | O16: =N16/$N$13 -> 0.00040455686
A17: Gas | B17: =4416+26496 -> 30912 | C17: =32020+32020+38424 -> 102464 | D17: 104176 | E17: 92445 | F17: =89520 -> 89520 | G17: =28090+36517+28090 -> 92697 | N17: =sum(B17:M17) -> 512214 | O17: =N17/$N$13 -> 0.034932987
A18: Rent & Revenue Share | B18: =257830 -> 257830 | C18: =257830 -> 257830 | D18: =257830 -> 257830 | E18: =257830 -> 257830 | F18: =257830 -> 257830 | G18: =257830 -> 257830 | N18: =sum(B18:M18) -> 1546980 | O18: =N18/$N$13 -> 0.10550401
A19: Software | B19: 5726 | C19: 5726 | D19: 5726 | E19: 5726 | F19: =69207/12 -> 5767.25 | G19: =69207/12 -> 5767.25 | H19: =69207/12 -> 5767.25 | I19: =69207/12 -> 5767.25 | J19: =69207/12 -> 5767.25 | K19: =69207/12 -> 5767.25 | L19: =69207/12 -> 5767.25 | M19: =69207/12 -> 5767.25 | N19: =sum(B19:M19) -> 69042 | O19: =N19/$N$13 -> 0.0047086634
A20: Staff Salary & Bonus | B20: =23364+319810 -> 343174 | C20: =23364+328574+36923 -> 388861 | D20: =41250+348148.15 -> 389398.15 | E20: =37500+24229+343233.76+25123 -> 430085.76 | F20: =346325+25960+37500+41538 -> 451323 | G20: =25960+37500+45000+366199.35 -> 474659.35 | N20: =sum(B20:M20) -> 2477501.3 | O20: =N20/$N$13 -> 0.16896555
A21: AMC | B21: =2400+2950+2850+2596+2478 -> 13274 | C21: =4460+2596+2796+2400+2950 -> 15202 | D21: =4460+2596+2796+2400+2950 -> 15202 | E21: =2950+5322+2440+2596+2726 -> 16034 | F21: =2400+2596+2726+2950 -> 10672 | G21: =2400+2596+2726+2950 -> 10672 | N21: =sum(B21:M21) -> 81056 | O21: =N21/$N$13 -> 0.005528018
A22: Subscription | B22: =2516.16/3+9813/12+7080/12 -> 2246.47 | C22: =2516.16/3+9813/12+7080/12 -> 2246.47 | D22: =2516.16/3+9813/12+7080/12 -> 2246.47 | E22: =2516.16/3+9813/12+7080/12 -> 2246.47 | F22: =2516.16/3+9813/12+7080/12 -> 2246.47 | G22: =2516.16/3+9813/12+7080/12 -> 2246.47 | H22: =9813/12 -> 817.75 | I22: =9813/12 -> 817.75 | J22: =9813/12 -> 817.75 | K22: =9813/12 -> 817.75 | L22: =9813/12 -> 817.75 | M22: =9813/12 -> 817.75 | N22: =sum(B22:M22) -> 18385.32 | O22: =N22/$N$13 -> 0.0012538785
A23: Insurance Premium | B23: 879 | C23: =1698 -> 1698 | D23: =1698 -> 1698 | E23: =1698 -> 1698 | F23: =1698 -> 1698 | G23: =1698 -> 1698 | H23: =1698 -> 1698 | I23: =1698 -> 1698 | J23: =1698 -> 1698 | ... M23: =1698 -> 1698 | N23: =sum(B23:M23) -> 19557 | O23: =N23/$N$13 -> 0.0013337871
A24: Repairs & Maintenance | B24: 3315 | C24: 5400 | D24: 22207 | E24: ='Misc Exp'!G133 -> 8491 | F24: ='Misc Exp'!G90 -> 41904 | G24: ='Misc Exp'!G43 -> 25633 | N24: =sum(B24:M24) -> 106950 | O24: =N24/$N$13 -> 0.0072939884
A25: Miscellaneous Expenses | B25: 17491.34 | C25: =27091.6 -> 27091.6 | D25: 23140.25 | E25: ='Misc Exp'!G126 -> 28679.523 | F25: ='Misc Exp'!G84 -> 13655.5 | G25: ='Misc Exp'!G38 -> 27117.72 | N25: =sum(B25:M25) -> 137175.93 | O25: =N25/$N$13 -> 0.0093553966
A26: CAM | B26: 0 | C26: 0 | D26: 0 | E26: 0 | F26: 0 | G26: 0 | N26: =sum(B26:M26) -> 0 | O26: =N26/$N$13 -> 0
A27: HO+CK Cost | B27: =HO!D38 -> 515429.21 | C27: =HO!H38 -> 534132.98 | D27: =HO!L38 -> 520096.52 | E27: =HO!P38 -> 532436.42 | F27: =HO!D57 -> 532951.02 | G27: =HO!H57 -> 516822.83 | H27: =HO!L57 -> #DIV/0! | I27: =HO!P57 -> #DIV/0! | J27: =HO!D76 -> #DIV/0! | K27: =HO!H76 -> #DIV/0! | L27: =HO!L76 -> #DIV/0! | M27: =HO!P76 -> #DIV/0! | N27: =sum(B27:M27) -> #DIV/0! | O27: =N27/$N$13 -> #DIV/0!
A28: Operating Expenses | B28: =+SUM(B14:B27) -> 1836850.4 | C28: =+SUM(C14:C27) -> 2043923.9 | D28: =+SUM(D14:D27) -> 2024229.4 | E28: =+SUM(E14:E27) -> 2069956 | F28: =+SUM(F14:F27) -> 2142374.6 | G28: =+SUM(G14:G27) -> 2073553 | H28: =+SUM(H14:H27) -> #DIV/0! | I28: =+SUM(I14:I27) -> #DIV/0! | ... M28: =+SUM(M14:M27) -> #DIV/0! | N28: =sum(B28:M28) -> #DIV/0! | O28: =N28/$N$13 -> #DIV/0!
A29: Store Level EBITDA | B29: =B13-B28 -> 484611.63 | C29: =C13-C28 -> 498519.59 | D29: =D13-D28 -> 349450.24 | E29: =E13-E28 -> 364122.79 | F29: =F13-F28 -> 541970.79 | G29: =G13-G28 -> 233197.53 | H29: =H13-H28 -> #DIV/0! | I29: =I13-I28 -> #DIV/0! | ... M29: =M13-M28 -> #DIV/0! | N29: =sum(B29:M29) -> #DIV/0! | O29: =N29/$N$13 -> #DIV/0!
A30: Food Cost | B30: =(B14/B13) -> 0.24418276 | C30: =(C14/C13) -> 0.24497489 | D30: =(D14/D13) -> 0.25511201 | E30: =(E14/E13) -> 0.25582081 | F30: =(F14/F13) -> 0.24755664 | G30: =(G14/G13) -> 0.25541625 | H30: =(H14/H13) -> #DIV/0! | I30: =(I14/I13) -> #DIV/0! | ... M30: =(M14/M13) -> #DIV/0!

Sheet Chinar Park
A1: Dosa Coffee - Chinar Park | B1: =Summary!C1 -> 46113 | C1: =Summary!D1 -> 46143 | D1: =Summary!E1 -> 46174 | E1: =Summary!F1 -> 46204 | F1: =Summary!G1 -> 46235 | G1: =Summary!H1 -> 46266 | H1: =Summary!I1 -> 46296 | I1: =Summary!J1 -> 46327 | ... M1: =Summary!N1 -> 46447 | N1: FY 2025-26
A2: Food Cost Calculation
A3: Opening Stock | B3: 19436 | C3: =B7 -> 21020.61 | D3: =C7 -> 21614.93 | E3: =D7 -> 22425 | F3: =E7 -> 18629 | G3: =F7 -> 20114 | H3: =G7 -> 22463.08 | I3: =H7 | J3: =I7 | ... M3: =L7 | N3: =+SUM(J3:L3) -> 0
A4: Purchases Food (Less Purchase Return) | B4: 209773.31 | C4: 244982.15 | D4: =237813-457 -> 237356 | E4: 251214 | F4: 267151 | G4: 229930 | N4: =sum(B4:M4) -> 1440406.5
A5: Transferred Out | B5: 717.04 | C5: 1998.13 | D5: 42.68 | E5: 696 | F5: 455 | G5: 4218 | N5: =+SUM(J5:L5) -> 0
A6: Wastage & Date Expired | B6: 5630.17 | C6: 7688.64 | D6: 7215 | E6: 8380 | F6: 11904 | G6: 15090.99 | N6: =+SUM(J6:L6) -> 0
A7: Closing Stock | B7: 21020.61 | C7: 21614.93 | D7: 22425 | E7: 18629 | F7: 20114 | G7: 22463.08 | N7: =sum(B7:M7) -> 126266.62
A9: Gross Revenue | B9: =769688.55*1.05+37355.18*1.05 -> 847395.92 | C9: =844376.03*1.05+42017.77*1.05 -> 930713.49 | D9: =800254.2*1.05+41061.23*1.05 -> 883381.2 | E9: =828279.37*1.05+42186*1.05 -> 913988.64 | F9: =896749.33*1.05 -> 941586.8 | G9: =725488.9*1.05+37587.25*1.05 -> 801229.96 | N9: =+SUM(B9:M9) -> 5318296
A10: Catering & Fairs | N10: =+SUM(B10:M10) -> 0
A11: Less Tax | B11: =(B9+B10)/1.05*0.05 -> 40352.187 | C11: =(C9+C10)/1.05*0.05 -> 44319.69 | D11: =(D9+D10)/1.05*0.05 -> 42065.772 | E11: =(E9+E10)/1.05*0.05 -> 43523.268 | F11: =(F9+F10)/1.05*0.05 -> 44837.467 | G11: =(G9+G10)/1.05*0.05 -> 38153.808 | H11: =(H9+H10)/1.05*0.05 -> 0 | I11: =(I9+I10)/1.05*0.05 -> 0 | ... M11: =(M9+M10)/1.05*0.05 -> 0 | N11: =+SUM(B11:M11) -> 253252.19
A12: Less Commission | B12: =86055.82*1.18+57752.8*1.18+15268.27*1.18+5.67*1.18 -> 187717.42 | C12: =96713.6*1.18+56069.04*1.18+22218.8*1.18 -> 206501.7 | D12: =94663.84*1.18+72991.91*1.18 -> 197833.79 | E12: =97006*1.18+74751*1.18 -> 202673.26 | F12: =96967.35*1.18+81686.79*1.18 -> 210811.89 | G12: =86743.5*1.18+67960.11*1.18 -> 182550.26 | N12: =+SUM(B12:M12) -> 1188088.3
A13: Net Revenues from F&B Sales | B13: =B9+B10-B11-B12 -> 619326.31 | C13: =C9+C10-C11-C12 -> 679892.1 | D13: =D9+D10-D11-D12 -> 643481.65 | E13: =E9+E10-E11-E12 -> 667792.11 | F13: =F9+F10-F11-F12 -> 685937.44 | G13: =G9+G10-G11-G12 -> 580525.89 | H13: =H9+H10-H11-H12 -> 0 | I13: =I9+I10-I11-I12 -> 0 | ... M13: =M9+M10-M11-M12 -> 0 | N13: =sum(B13:M13) -> 3876955.5
A14: F&B Cost | B14: =+B3+B4-B5-B7 -> 207471.66 | C14: =+C3+C4-C5-C7 -> 242389.7 | D14: =+D3+D4-D5-D7 -> 236503.25 | E14: =+E3+E4-E5-E7 -> 254314 | F14: =+F3+F4-F5-F7 -> 265211 | G14: =+G3+G4-G5-G7 -> 223362.92 | H14: =+H3+H4-H5-H7 -> 22463.08 | I14: =+I3+I4-I5-I7 -> 0 | ... M14: =+M3+M4-M5-M7 -> 0 | N14: =sum(B14:M14) -> 1451715.6 | O14: =N14/$N$13 -> 0.37444732
A15: Electricity | B15: =41558.4 -> 41558.4 | C15: =43508.4 -> 43508.4 | D15: =41636 -> 41636 | E15: 44896 | F15: 45396 | G15: =40981 -> 40981 | N15: =sum(B15:M15) -> 257975.8 | O15: =N15/$N$13 -> 0.066540821
A16: Telephone/Internet | B16: =1003+352.82 -> 1355.82 | C16: =1003+352.82 -> 1355.82 | D16: =1003+352.82 -> 1355.82 | E16: =352.82+1003 -> 1355.82 | F16: =352.82+1003 -> 1355.82 | G16: =352.82+1003 -> 1355.82 | N16: =sum(B16:M16) -> 8134.92 | O16: =N16/$N$13 -> 0.0020982753
A17: Gas | B17: 0 | C17: 0 | D17: 0 | E17: 0 | F17: 0 | G17: 0 | N17: =sum(B17:M17) -> 0 | O17: =N17/$N$13 -> 0
A18: Rent & Revenue Share | B18: =18880 -> 18880 | C18: 18880 | D18: 18880 | E18: 18880 | F18: 18880 | G18: 18880 | N18: =sum(B18:M18) -> 113280 | O18: =N18/$N$13 -> 0.029218803
A19: Software | B19: 3761 | C19: 3761 | D19: 3761 | E19: 3761 | F19: 3761 | G19: 3761 | N19: =sum(B19:M19) -> 22566 | O19: =N19/$N$13 -> 0.0058205466
A20: Staff Salary & Bonus | B20: =97962 -> 97962 | C20: =100611 -> 100611 | D20: =100611 -> 100611 | E20: =102890.56 -> 102890.56 | F20: 102891 | G20: 102891 | N20: =sum(B20:M20) -> 607856.56 | O20: =N20/$N$13 -> 0.15678709
A21: AMC | B21: =1200+2360+1239 -> 4799 | C21: =1200+2360+1239 -> 4799 | D21: =1363+2360 -> 3723 | E21: =2360+1363 -> 3723 | F21: =1363+2360 -> 3723 | G21: =1363+2360 -> 3723 | N21: =sum(B21:M21) -> 24490 | O21: =N21/$N$13 -> 0.0063168123
A22: Subscription | B22: =2516.16/3 -> 838.72 | C22: =2516.16/3 -> 838.72 | D22: =2516.16/3 -> 838.72 | E22: =2516.16/3 -> 838.72 | F22: =2516.16/3 -> 838.72 | G22: =2516.16/3 -> 838.72 | N22: =sum(B22:M22) -> 5032.32 | O22: =N22/$N$13 -> 0.0012980082
A23: Insurance Premium | B23: 805 | C23: =1698 -> 1698 | D23: =1698 -> 1698 | E23: =1698 -> 1698 | F23: =1698 -> 1698 | G23: =1698 -> 1698 | H23: =1698 -> 1698 | I23: =1698 -> 1698 | J23: =1698 -> 1698 | ... M23: =1698 -> 1698 | N23: =sum(B23:M23) -> 19483 | O23: =N23/$N$13 -> 0.005025335
A24: Repairs & Maintenance | B24: 5605.83 | C24: 0 | D24: 0 | E24: ='Misc Exp'!N133 -> 297 | F24: ='Misc Exp'!N90 -> 8850 | G24: ='Misc Exp'!N43 -> 0 | N24: =sum(B24:M24) -> 14752.83 | O24: =N24/$N$13 -> 0.0038052616
A25: Miscellaneous Expenses | B25: =22334/12 -> 1861.1667 | C25: =22334/12+34158.86 -> 36020.027 | D25: =22334/12 -> 1861.1667 | E25: =22334/12+'Misc Exp'!N126 -> 35171.18 | F25: =22334/12+'Misc Exp'!N84 -> 7373.7067 | G25: =22334/12+'Misc Exp'!N38 -> 11338.957 | H25: =22334/12 -> 1861.1667 | I25: =22334/12 -> 1861.1667 | J25: =22334/12 -> 1861.1667 | K25: =22334/12 -> 1861.1667 | L25: =22334/12 -> 1861.1667 | M25: =22334/12 -> 1861.1667 | N25: =sum(B25:M25) -> 104793.2 | O25: =N25/$N$13 -> 0.027029767
A26: CAM | B26: 0 | C26: 0 | D26: 0 | E26: 0 | F26: 0 | G26: 0 | N26: =sum(B26:M26) -> 0 | O26: =N26/$N$13 -> 0
A27: HO+CK Cost | B27: =HO!D37 -> 137507.69 | C27: =HO!H37 -> 142836.13 | D27: =HO!L37 -> 140993.15 | E27: =HO!P37 -> 146074.5 | F27: =HO!D56 -> 136186.3 | G27: =HO!H56 -> 130065.66 | H27: =HO!L56 -> #DIV/0! | I27: =HO!P56 -> #DIV/0! | J27: =HO!D75 -> #DIV/0! | K27: =HO!H75 -> #DIV/0! | L27: =HO!L75 -> #DIV/0! | M27: =HO!P75 -> #DIV/0! | N27: =sum(B27:M27) -> #DIV/0! | O27: =N27/$N$13 -> #DIV/0!
A28: Operating Expenses | B28: =+SUM(B14:B27) -> 522406.28 | C28: =+SUM(C14:C27) -> 596697.8 | D28: =+SUM(D14:D27) -> 551861.1 | E28: =+SUM(E14:E27) -> 613899.78 | F28: =+SUM(F14:F27) -> 596164.55 | G28: =+SUM(G14:G27) -> 538896.08 | H28: =+SUM(H14:H27) -> #DIV/0! | I28: =+SUM(I14:I27) -> #DIV/0! | ... M28: =+SUM(M14:M27) -> #DIV/0! | N28: =sum(B28:M28) -> #DIV/0! | O28: =N28/N13 -> #DIV/0!
A29: Store Level EBITDA | B29: =B13-B28 -> 96920.027 | C29: =C13-C28 -> 83194.3 | D29: =D13-D28 -> 91620.54 | E29: =E13-E28 -> 53892.331 | F29: =F13-F28 -> 89772.898 | G29: =G13-G28 -> 41629.812 | H29: =H13-H28 -> #DIV/0! | I29: =I13-I28 -> #DIV/0! | ... M29: =M13-M28 -> #DIV/0! | N29: =sum(B29:M29) -> #DIV/0! | O29: =N29/N13 -> #DIV/0!
A30: Food Cost | B30: =(B14/B13) -> 0.33499572 | C30: =(C14/C13) -> 0.35651201 | D30: =(D14/D13) -> 0.3675369 | E30: =(E14/E13) -> 0.3808281 | F30: =(F14/F13) -> 0.38664021 | G30: =(G14/G13) -> 0.38475962 | H30: =(H14/H13) -> #DIV/0! | I30: =(I14/I13) -> #DIV/0! | ... M30: =(M14/M13) -> #DIV/0!

Sheet Santoshpur
A1: Dosa Coffee - Santoshpur | B1: =Summary!C1 -> 46113 | C1: =Summary!D1 -> 46143 | D1: =Summary!E1 -> 46174 | E1: =Summary!F1 -> 46204 | F1: =Summary!G1 -> 46235 | G1: =Summary!H1 -> 46266 | H1: =Summary!I1 -> 46296 | I1: =Summary!J1 -> 46327 | ... M1: =Summary!N1 -> 46447 | N1: FY 2025-26
A2: Food Cost Calculation
A3: Opening Stock | B3: 27910 | C3: =B7 -> 40786.52 | D3: =C7 -> 39038.96 | E3: =D7 -> 49439 | F3: =E7 -> 36808 | G3: =F7 -> 42108 | H3: =G7 -> 27220 | I3: =H7 | J3: =I7 | ... M3: =L7 | N3: =+SUM(J3:L3) -> 0
A4: Purchases Food (Less Purchase Return) | B4: 322224.42 | C4: 327727.76 | D4: =316922-374 -> 316548 | E4: 309819 | F4: 396749.93 | G4: 325187.15 | N4: =sum(B4:M4) -> 1998256.3
A5: Transferred Out | B5: 527.4 | C5: 1039.8 | D5: 1155 | E5: 2451 | F5: 1513 | G5: 898.71 | N5: =+SUM(J5:L5) -> 0
A6: Wastage & Date Expired | B6: 11145.91 | C6: 12011.2 | D6: 12346 | E6: 11727 | F6: 15937 | G6: 15517.54 | N6: =+SUM(J6:L6) -> 0
A7: Closing Stock | B7: 40786.52 | C7: 39038.96 | D7: 49439 | E7: 36808 | F7: 42108 | G7: 27220 | N7: =sum(B7:M7) -> 235400.48
A9: Gross Revenue | B9: =1216198.46*1.05+30585.5*1.05 -> 1309123.2 | C9: =1254552.57*1.05+31713.83*1.05 -> 1350579.7 | D9: =1219484.47*1.05+32807.81*1.05 -> 1314906.9 | E9: =1272990.14*1.05+33869*1.05 -> 1372202.1 | F9: =1453073.39*1.05 -> 1525727.1 | G9: =1248887.67*1.05+32102.47*1.05 -> 1345039.6 | N9: =+SUM(B9:M9) -> 8217578.6
A10: Catering & Fairs | N10: =+SUM(B10:M10) -> 0
A11: Less Tax | B11: =(B9+B10)/1.05*0.05 -> 62339.198 | C11: =(C9+C10)/1.05*0.05 -> 64313.32 | D11: =(D9+D10)/1.05*0.05 -> 62614.614 | E11: =(E9+E10)/1.05*0.05 -> 65342.957 | F11: =(F9+F10)/1.05*0.05 -> 72653.67 | G11: =(G9+G10)/1.05*0.05 -> 64049.507 | H11: =(H9+H10)/1.05*0.05 -> 0 | I11: =(I9+I10)/1.05*0.05 -> 0 | ... M11: =(M9+M10)/1.05*0.05 -> 0 | N11: =+SUM(B11:M11) -> 391313.27
A12: Less Commission | B12: =71144.64*1.18+53263.03*1.18+11161.37*1.18+337.04*1.18 -> 160369.17 | C12: =73401.17*1.18+43615.84*1.18+47.49*1.18+176.93*1.18+17958.42*1.18 -> 159535.82 | D12: =341.13*1.18+67901.55*1.18+426.48*1.18+76039.2*1.18 -> 170755.86 | E12: =78804.9*1.18+163.58*1.18+72843.53*1.18 -> 179138.17 | F12: =86663.08*1.18+78505.67*1.18+85.55*1.18 -> 195000.07 | G12: =74446.03*1.18+73875.21*1.18+152.09*1.18+36.99*1.18 -> 175242.18 | N12: =+SUM(B12:M12) -> 1040041.3
A13: Net Revenues from F&B Sales | B13: =B9+B10-B11-B12 -> 1086414.8 | C13: =C9+C10-C11-C12 -> 1126730.6 | D13: =D9+D10-D11-D12 -> 1081536.4 | E13: =E9+E10-E11-E12 -> 1127721 | F13: =F9+F10-F11-F12 -> 1258073.3 | G13: =G9+G10-G11-G12 -> 1105748 | H13: =H9+H10-H11-H12 -> 0 | I13: =I9+I10-I11-I12 -> 0 | ... M13: =M9+M10-M11-M12 -> 0 | N13: =sum(B13:M13) -> 6786224
A14: F&B Cost | B14: =+B3+B4-B5-B7 -> 308820.5 | C14: =+C3+C4-C5-C7 -> 328435.52 | D14: =+D3+D4-D5-D7 -> 304992.96 | E14: =+E3+E4-E5-E7 -> 319999 | F14: =+F3+F4-F5-F7 -> 389936.93 | G14: =+G3+G4-G5-G7 -> 339176.44 | H14: =+H3+H4-H5-H7 -> 27220 | I14: =+I3+I4-I5-I7 -> 0 | ... M14: =+M3+M4-M5-M7 -> 0 | N14: =sum(B14:M14) -> 2018581.4 | O14: =N14/$N$13 -> 0.2974528
A15: Electricity | B15: =54730+2970 -> 57700 | C15: =60590+7800 -> 68390 | D15: =57630+8390 -> 66020 | E15: =57480+9190 -> 66670 | F15: =55540+8580 -> 64120 | G15: 65000 | N15: =sum(B15:M15) -> 387900 | O15: =N15/$N$13 -> 0.057159917
A16: Telephone/Internet | B16: =352.82 -> 352.82 | C16: =352.82 -> 352.82 | D16: =352.82 -> 352.82 | E16: =352.82+4300/12 -> 711.15333 | F16: =4300/12+352.82 -> 711.15333 | G16: =4300/12+352.82 -> 711.15333 | H16: =4300/12 -> 358.33333 | I16: =4300/12 -> 358.33333 | J16: =4300/12 -> 358.33333 | K16: =4300/12 -> 358.33333 | L16: =4300/12 -> 358.33333 | M16: =4300/12 -> 358.33333 | N16: =sum(B16:M16) -> 5341.92 | O16: =N16/$N$13 -> 0.00078717118
A17: Gas | B17: =11040+6624 -> 17664 | C17: =19212+22414+19212 -> 60838 | D17: 52088 | E17: 58549 | F17: =50355.5 -> 50355.5 | G17: =53371 -> 53371 | N17: =sum(B17:M17) -> 292865.5 | O17: =N17/$N$13 -> 0.043155884
A18: Rent & Revenue Share | B18: =42280.58+42280.58 -> 84561.16 | C18: =42280.58+42280.58 -> 84561.16 | D18: =42280.58+42280.58 -> 84561.16 | E18: =42280.58+42280.58 -> 84561.16 | F18: =42280.58+42280.58 -> 84561.16 | G18: =42280.58+42280.58 -> 84561.16 | N18: =sum(B18:M18) -> 507366.96 | O18: =N18/$N$13 -> 0.074764252
A19: Software | B19: 5767 | C19: 5767 | D19: 5767 | E19: 5767 | F19: 5767 | G19: 5767 | N19: =sum(B19:M19) -> 34602 | O19: =N19/$N$13 -> 0.0050988591
A20: Staff Salary & Bonus | B20: =197466 -> 197466 | C20: =204020 -> 204020 | D20: =187306 -> 187306 | E20: =188837.35 -> 188837.35 | F20: =196060 -> 196060 | G20: =188234 -> 188234 | N20: =sum(B20:M20) -> 1161923.4 | O20: =N20/$N$13 -> 0.17121795
A21: AMC | B21: =3100+5145+3717+2956+450 -> 15368 | C21: =3100+5145+3717+2956+450 -> 15368 | D21: =2596+4089+5145 -> 11830 | E21: =5145+2596+4089+2400 -> 14230 | F21: =2596+4089+5145 -> 11830 | G21: =2596+4089+5145 -> 11830 | N21: =sum(B21:M21) -> 80456 | O21: =N21/$N$13 -> 0.011855783
A22: Subscription | B22: =2516.16/3+9813/12+7080/12 -> 2246.47 | C22: =2516.16/3+9813/12+7080/12 -> 2246.47 | D22: =2516.16/3+9813/12+7080/12 -> 2246.47 | E22: =2516.16/3+9813/12+7080/12 -> 2246.47 | F22: =2516.16/3+9813/12+7080/12 -> 2246.47 | G22: =2516.16/3+9813/12+7080/12 -> 2246.47 | H22: =9813/12 -> 817.75 | I22: =9813/12 -> 817.75 | J22: =9813/12 -> 817.75 | K22: =9813/12 -> 817.75 | L22: =9813/12 -> 817.75 | M22: =9813/12 -> 817.75 | N22: =sum(B22:M22) -> 18385.32 | O22: =N22/$N$13 -> 0.0027092121
A23: Insurance Premium | B23: =7885/12+1083/12 -> 747.33333 | C23: =7885/12+1083/12 -> 747.33333 | D23: =7885/12+1083/12 -> 747.33333 | E23: =7885/12+1083/12 -> 747.33333 | F23: =7885/12+1083/12 -> 747.33333 | G23: =7885/12+1083/12 -> 747.33333 | H23: =7885/12+1083/12 -> 747.33333 | I23: =7885/12+1083/12 -> 747.33333 | ... M23: =7885/12+1083/12 -> 747.33333 | N23: =sum(B23:M23) -> 8968 | O23: =N23/$N$13 -> 0.0013215007
A24: Repairs & Maintenance | B24: =1680 -> 1680 | C24: 6933 | D24: 27230 | E24: ='Misc Exp'!E133 -> 7680 | F24: ='Misc Exp'!E90 -> 16857 | G24: ='Misc Exp'!E43 -> 1950 | N24: =sum(B24:M24) -> 62330 | O24: =N24/$N$13 -> 0.0091847837
A25: Miscellaneous Expenses | B25: =21934/12+8743.66 -> 10571.493 | C25: =21934/12+19715 -> 21542.833 | D25: =21934/12+7823.6 -> 9651.4333 | E25: =21934/12+'Misc Exp'!E126 -> 22414.117 | F25: =21934/12+'Misc Exp'!E84 -> 9254.7033 | G25: =21934/12+'Misc Exp'!E38 -> 17706.863 | H25: =21934/12 -> 1827.8333 | I25: =21934/12 -> 1827.8333 | J25: =21934/12 -> 1827.8333 | K25: =21934/12 -> 1827.8333 | L25: =21934/12 -> 1827.8333 | M25: =21934/12 -> 1827.8333 | N25: =sum(B25:M25) -> 102108.44 | O25: =N25/$N$13 -> 0.01504643
A26: CAM | B26: 0 | C26: 0 | D26: 0 | E26: 0 | F26: 0 | G26: 0 | N26: =sum(B26:M26) -> 0 | O26: =N26/$N$13 -> 0
A27: HO+CK Cost | B27: =HO!D36 -> 241214.33 | C27: =HO!H36 -> 236710.85 | D27: =HO!L36 -> 236975.25 | E27: =HO!P36 -> 246680.48 | F27: =HO!D55 -> 249778.39 | G27: =HO!H55 -> 247740.61 | H27: =HO!L55 -> #DIV/0! | I27: =HO!P55 -> #DIV/0! | J27: =HO!D74 -> #DIV/0! | K27: =HO!H74 -> #DIV/0! | L27: =HO!L74 -> #DIV/0! | M27: =HO!P74 -> #DIV/0! | N27: =sum(B27:M27) -> #DIV/0! | O27: =N27/$N$13 -> #DIV/0!
A28: Operating Expenses | B28: =+SUM(B14:B27) -> 944159.11 | C28: =+SUM(C14:C27) -> 1035913 | D28: =+SUM(D14:D27) -> 989768.43 | E28: =+SUM(E14:E27) -> 1019093.1 | F28: =+SUM(F14:F27) -> 1082225.6 | G28: =+SUM(G14:G27) -> 1019042 | H28: =+SUM(H14:H27) -> #DIV/0! | I28: =+SUM(I14:I27) -> #DIV/0! | ... M28: =+SUM(M14:M27) -> #DIV/0! | N28: =sum(B28:M28) -> #DIV/0! | O28: =N28/N13 -> #DIV/0!
A29: Store Level EBITDA | B29: =B13-B28 -> 142255.68 | C29: =C13-C28 -> 90817.586 | D29: =D13-D28 -> 91767.988 | E29: =E13-E28 -> 108627.91 | F29: =F13-F28 -> 175847.68 | G29: =G13-G28 -> 86705.929 | H29: =H13-H28 -> #DIV/0! | I29: =I13-I28 -> #DIV/0! | ... M29: =M13-M28 -> #DIV/0! | N29: =sum(B29:M29) -> #DIV/0! | O29: =N29/N13 -> #DIV/0!
A30: Food Cost | B30: =(B14/B13) -> 0.28425653 | C30: =(C14/C13) -> 0.29149428 | D30: =(D14/D13) -> 0.28199971 | E30: =(E14/E13) -> 0.28375725 | F30: =(F14/F13) -> 0.3099477 | G30: =(G14/G13) -> 0.30673938 | H30: =(H14/H13) -> #DIV/0! | I30: =(I14/I13) -> #DIV/0! | ... M30: =(M14/M13) -> #DIV/0!

Sheet Kalikapur
A1: Dosa Coffee - Kalikapur | B1: =Summary!C1 -> 46113 | C1: =Summary!D1 -> 46143 | D1: =Summary!E1 -> 46174 | E1: =Summary!F1 -> 46204 | F1: =Summary!G1 -> 46235 | G1: =Summary!H1 -> 46266 | H1: =Summary!I1 -> 46296 | I1: =Summary!J1 -> 46327 | ... M1: =Summary!N1 -> 46447 | N1: FY 2025-26
A2: Food Cost Calculation
A3: Opening Stock | B3: 23040 | C3: =B7 -> 24932.46 | D3: =C7 -> 21614.93 | E3: =D7 -> 25343 | F3: =E7 -> 23427 | G3: =F7 -> 25030.9 | H3: =G7 -> 27434.27 | I3: =H7 | J3: =I7 | ... M3: =L7 | N3: =+SUM(J3:L3) -> 0
A4: Purchases Food (Less Purchase Return) | B4: =313579.86 -> 313579.86 | C4: 244982 | D4: 332658.81 | E4: 339375 | F4: 361798.99 | G4: 349072.71 | N4: =sum(B4:M4) -> 1941467.4
A5: Transferred Out | B5: =921.61 -> 921.61 | C5: 1998 | D5: 207.32 | E5: 51.67 | F5: 839 | G5: 694 | N5: =+SUM(J5:L5) -> 0
A6: Wastage & Date Expired | B6: 9327.27 | C6: 7688.64 | D6: 12263 | E6: 12490 | F6: 11561.52 | G6: 22913 | N6: =+SUM(J6:L6) -> 0
A7: Closing Stock | B7: 24932.46 | C7: 21614.93 | D7: 25343 | E7: 23427 | F7: 25030.9 | G7: 27434.27 | N7: =sum(B7:M7) -> 147782.56
A9: Gross Revenue | B9: =1274252.75*1.05+22870.89*1.05 -> 1361979.8 | C9: =1385703.46*1.05+26558.92*1.05 -> 1482875.5 | D9: =1296705.26*1.05+28185.39*1.05 -> 1391135.2 | E9: =1309159.77*1.05+28333.42*1.05 -> 1404367.9 | F9: =1421589.51*1.05 -> 1492669 | G9: =1389454.12*1.05+29185.64*1.05 -> 1489571.7 | N9: =+SUM(B9:M9) -> 8622599.1
A10: Catering & Fairs | N10: =+SUM(B10:M10) -> 0
A11: Less Tax | B11: =(B9+B10)/1.05*0.05 -> 64856.182 | C11: =(C9+C10)/1.05*0.05 -> 70613.119 | D11: =(D9+D10)/1.05*0.05 -> 66244.533 | E11: =(E9+E10)/1.05*0.05 -> 66874.659 | F11: =(F9+F10)/1.05*0.05 -> 71079.476 | G11: =(G9+G10)/1.05*0.05 -> 70931.988 | H11: =(H9+H10)/1.05*0.05 -> 0 | I11: =(I9+I10)/1.05*0.05 -> 0 | ... M11: =(M9+M10)/1.05*0.05 -> 0 | N11: =+SUM(B11:M11) -> 410599.96
A12: Less Commission | B12: =53221.17*1.18+41738.6*1.18+12562.02*1.18+1288.64*1.18 -> 128396.31 | C12: =62028.96*1.18+48226.45*1.18+1625.09*1.18+15699.71*1.18 -> 150544.65 | D12: =66112.99*1.18+50012.05*1.05+835.89*1.18 -> 131512.33 | E12: =66077.13*1.18+559.81*1.18+58624.99*1.18 -> 147809.08 | F12: =68241.08*1.18+65733.57*1.18+686.29*1.18 -> 158899.91 | G12: =67918.03*1.18+63726.81*1.18+783.67*1.18 -> 156265.64 | N12: =+SUM(B12:M12) -> 873427.91
A13: Net Revenues from F&B Sales | B13: =B9+B10-B11-B12 -> 1168727.3 | C13: =C9+C10-C11-C12 -> 1261717.7 | D13: =D9+D10-D11-D12 -> 1193378.3 | E13: =E9+E10-E11-E12 -> 1189684.1 | F13: =F9+F10-F11-F12 -> 1262689.6 | G13: =G9+G10-G11-G12 -> 1262374.1 | H13: =H9+H10-H11-H12 -> 0 | I13: =I9+I10-I11-I12 -> 0 | ... M13: =M9+M10-M11-M12 -> 0 | N13: =sum(B13:M13) -> 7338571.2 | O13: =N13/$N$7 -> 49.657897
A14: F&B Cost | B14: =+B3+B4-B5-B7 -> 310765.79 | C14: =+C3+C4-C5-C7 -> 246301.53 | D14: =+D3+D4-D5-D7 -> 328723.42 | E14: =+E3+E4-E5-E7 -> 341239.33 | F14: =+F3+F4-F5-F7 -> 359356.09 | G14: =+G3+G4-G5-G7 -> 345975.34 | H14: =+H3+H4-H5-H7 -> 27434.27 | I14: =+I3+I4-I5-I7 -> 0 | ... M14: =+M3+M4-M5-M7 -> 0 | N14: =sum(B14:M14) -> 1959795.8 | O14: =N14/$N$13 -> 0.26705413
A15: Electricity | B15: =72892.84 -> 72892.84 | C15: 84970 | D15: 82560 | E15: 73540 | F15: 74720 | G15: 74000 | N15: =sum(B15:M15) -> 462682.84 | O15: =N15/$N$13 -> 0.063048082
A16: Telephone/Internet | B16: 1027 | C16: 1027 | D16: 1027 | E16: 1027 | F16: 1027 | G16: 1027 | N16: =sum(B16:M16) -> 6162 | O16: =N16/$N$13 -> 0.00083967299
A17: Gas | B17: 0 | C17: 0 | D17: 0 | E17: 0 | F17: 0 | G17: 0 | N17: =sum(B17:M17) -> 0 | O17: =N17/$N$13 -> 0
A18: Rent & Revenue Share | B18: =74340 -> 74340 | C18: =74340 -> 74340 | D18: =74340 -> 74340 | E18: =74340 -> 74340 | F18: =74340 -> 74340 | G18: =74340 -> 74340 | N18: =sum(B18:M18) -> 446040 | O18: =N18/$N$13 -> 0.060780224
A19: Software | B19: 7355 | C19: 7355 | D19: 7355 | E19: 7355 | F19: 7355 | G19: 7355 | N19: =sum(B19:M19) -> 44130 | O19: =N19/$N$13 -> 0.0060134321
A20: Staff Salary & Bonus | B20: =196229 -> 196229 | C20: =207253 -> 207253 | D20: =210582.91 -> 210582.91 | E20: =202550.91 -> 202550.91 | F20: 212010 | G20: =200596 -> 200596 | N20: =sum(B20:M20) -> 1229221.8 | O20: =N20/$N$13 -> 0.16750152
A21: AMC | B21: =2360+3717+2478 -> 8555 | C21: =2360+3717+2478 -> 8555 | D21: =6815+2360 -> 9175 | E21: =2360+2726+4089 -> 9175 | F21: =2726+4089+2360 -> 9175 | G21: =2726+4089+2360 -> 9175 | N21: =sum(B21:M21) -> 53810 | O21: =N21/$N$13 -> 0.00733249
A22: Subscription | B22: =2516.16/3+9813/12+7080/12 -> 2246.47 | C22: =2516.16/3+9813/12+7080/12 -> 2246.47 | D22: =2516.16/3+9813/12+7080/12 -> 2246.47 | E22: =2516.16/3+9813/12+7080/12 -> 2246.47 | F22: =2516.16/3+9813/12+7080/12 -> 2246.47 | G22: =2516.16/3+9813/12+7080/12 -> 2246.47 | H22: =9813/12 -> 817.75 | I22: =9813/12 -> 817.75 | J22: =9813/12 -> 817.75 | K22: =9813/12 -> 817.75 | L22: =9813/12 -> 817.75 | M22: =9813/12 -> 817.75 | N22: =sum(B22:M22) -> 18385.32 | O22: =N22/$N$13 -> 0.0025052997
A23: Insurance Premium | B23: 1160.3 | C23: =1698 -> 1698 | D23: =1698 -> 1698 | E23: =1698 -> 1698 | F23: =1698 -> 1698 | G23: =1698 -> 1698 | H23: =1698 -> 1698 | I23: =1698 -> 1698 | J23: =1698 -> 1698 | ... M23: =1698 -> 1698 | N23: =sum(B23:M23) -> 19838.3 | O23: =N23/$N$13 -> 0.0027032919
A24: Repairs & Maintenance | B24: =2846 -> 2846 | C24: 0 | D24: 39658 | E24: ='Misc Exp'!F133 -> 3719 | F24: ='Misc Exp'!F90 -> 23478 | G24: ='Misc Exp'!F43 -> 782 | N24: =sum(B24:M24) -> 70483 | O24: =N24/$N$13 -> 0.0096044581
A25: Miscellaneous Expenses | B25: =21934/12+10841 -> 12668.833 | C25: =21934/12+33899.75 -> 35727.583 | D25: =21934/12+7627 -> 9454.8333 | E25: =21934/12+'Misc Exp'!F126 -> 17031.227 | F25: =21934/12+'Misc Exp'!F84 -> 11549.053 | G25: =21934/12+'Misc Exp'!F38 -> 17171.983 | H25: =21934/12 -> 1827.8333 | I25: =21934/12 -> 1827.8333 | J25: =21934/12 -> 1827.8333 | K25: =21934/12 -> 1827.8333 | L25: =21934/12 -> 1827.8333 | M25: =21934/12 -> 1827.8333 | N25: =sum(B25:M25) -> 114570.51 | O25: =N25/$N$13 -> 0.015612101
A26: CAM | B26: =49560 -> 49560 | C26: 49560 | D26: 49560 | E26: 49560 | F26: 49560 | G26: 49560 | N26: =sum(B26:M26) -> 297360 | O26: =N26/$N$13 -> 0.040520149
A27: HO+CK Cost | B27: =HO!D40 -> 259490.01 | C27: =HO!H40 -> 265069.83 | D27: =HO!L40 -> 261480.91 | E27: =HO!P40 -> 260234.45 | F27: =HO!D59 -> 250694.91 | G27: =HO!H59 -> 282832.39 | H27: =HO!L59 -> #DIV/0! | I27: =HO!P59 -> #DIV/0! | J27: =HO!D78 -> #DIV/0! | K27: =HO!H78 -> #DIV/0! | L27: =HO!L78 -> #DIV/0! | M27: =HO!P78 -> #DIV/0! | N27: =sum(B27:M27) -> #DIV/0! | O27: =N27/$N$13 -> #DIV/0!
A28: Operating Expenses | B28: =+SUM(B14:B27) -> 999136.24 | C28: =+SUM(C14:C27) -> 984103.41 | D28: =+SUM(D14:D27) -> 1077861.5 | E28: =+SUM(E14:E27) -> 1043716.4 | F28: =+SUM(F14:F27) -> 1077209.5 | G28: =+SUM(G14:G27) -> 1066759.2 | H28: =+SUM(H14:H27) -> #DIV/0! | I28: =+SUM(I14:I27) -> #DIV/0! | ... M28: =+SUM(M14:M27) -> #DIV/0! | N28: =sum(B28:M28) -> #DIV/0! | O28: =N28/N13 -> #DIV/0!
A29: Store Level EBITDA | B29: =B13-B28 -> 169591.09 | C29: =C13-C28 -> 277614.32 | D29: =D13-D28 -> 115516.78 | E29: =E13-E28 -> 145967.73 | F29: =F13-F28 -> 185480.08 | G29: =G13-G28 -> 195614.94 | H29: =H13-H28 -> #DIV/0! | I29: =I13-I28 -> #DIV/0! | ... M29: =M13-M28 -> #DIV/0! | N29: =sum(B29:M29) -> #DIV/0! | O29: =N29/N13 -> #DIV/0!
A30: Food Cost | B30: =(B14/B13) -> 0.26590102 | C30: =(C14/C13) -> 0.19521128 | D30: =(D14/D13) -> 0.27545617 | E30: =(E14/E13) -> 0.28683188 | F30: =(F14/F13) -> 0.28459575 | G30: =(G14/G13) -> 0.2740672 | H30: =(H14/H13) -> #DIV/0! | I30: =(I14/I13) -> #DIV/0! | ... M30: =(M14/M13) -> #DIV/0!

Sheet Lake Road
A1: Dosa Coffee - Lake Road | B1: =Summary!C1 -> 46113 | C1: =Summary!D1 -> 46143 | D1: =Summary!E1 -> 46174 | E1: =Summary!F1 -> 46204 | F1: =Summary!G1 -> 46235 | G1: =Summary!H1 -> 46266 | H1: =Summary!I1 -> 46296 | I1: =Summary!J1 -> 46327 | ... M1: =Summary!N1 -> 46447 | N1: FY 2025-26
A2: Food Cost Calculation
A3: Opening Stock | B3: 41653 | C3: =B7 -> 55859.11 | D3: =C7 -> 40101.87 | E3: =D7 -> 39631 | F3: =E7 -> 30712 | G3: =F7 -> 34650 | H3: =G7 -> 32579.83 | I3: =H7 | J3: =I7 | ... M3: =L7 | N3: =B3 -> 41653
A4: Purchases Food (Less Purchase Return) | B4: 570115.74 | C4: 571057.25 | D4: 618636 | E4: 614060 | F4: 724817 | G4: 634160 | N4: =sum(B4:M4) -> 3732846
A5: Transferred Out | B5: 363.49 | C5: 614.4 | D5: 472 | E5: 915 | F5: 1495 | G5: 1574 | N5: =+SUM(J5:L5) -> 0
A6: Wastage & Date Expired | B6: 12293.95 | C6: 13778.86 | D6: 18307 | E6: 19678 | F6: 46652.17 | G6: 38912 | N6: =+SUM(J6:L6) -> 0
A7: Closing Stock | B7: 55859.11 | C7: 40101.87 | D7: 39631 | E7: 30712 | F7: 34650 | G7: 32579.83 | N7: =sum(B7:M7) -> 233533.81
A9: Gross Revenue | B9: =2245373.24*1.05+80*1.05+37495.16*1.05 -> 2397095.8 | C9: =2449354.45*1.05+41112.44*1.05+70*1.05 -> 2615063.7 | D9: =2374062.99*1.05+120*1.05+37207.62*1.05 -> 2531960.1 | E9: =2326006.47*1.05+41030*1.05+60*1.05 -> 2485451.3 | F9: =2589777.65*1.05 -> 2719266.5 | G9: =2453115.87*1.05+40343.11*1.05 -> 2618131.9 | N9: =+SUM(B9:M9) -> 15366969
A10: Catering & Fairs | N10: =+SUM(B10:M10) -> 0
A11: Less Tax | B11: =(B9+B10)/1.05*0.05 -> 114147.42 | C11: =(C9+C10)/1.05*0.05 -> 124526.84 | D11: =(D9+D10)/1.05*0.05 -> 120569.53 | E11: =(E9+E10)/1.05*0.05 -> 118354.82 | F11: =(F9+F10)/1.05*0.05 -> 129488.88 | G11: =(G9+G10)/1.05*0.05 -> 124672.95 | H11: =(H9+H10)/1.05*0.05 -> 0 | I11: =(I9+I10)/1.05*0.05 -> 0 | ... M11: =(M9+M10)/1.05*0.05 -> 0 | N11: =+SUM(B11:M11) -> 731760.45
A12: Less Commission | B12: =89347.62*1.18+80815.33*1.18+12281.26*1.18+2741.39*1.18 -> 218519.01 | C12: =96500.63*1.18+68368.81*1.18+367.62*1.18+5966*1.18+28878.28*1.18 -> 236095.98 | D12: =88723.94*1.18+92553.12*1.18+3497.81*1.18 -> 218034.35 | E12: =96461.71*1.18+3153.9*1.18+102169*1.18 -> 238105.84 | F12: =107146.38*1.18+117160.82*1.18+3834.24*1.18 -> 269206.9 | G12: =99780.96*1.18+106772.17*1.18+4184.09*1.18 -> 248669.92 | N12: =+SUM(B12:M12) -> 1428632
A13: Net Revenues from F&B Sales | B13: =B9+B10-B11-B12 -> 2064429.4 | C13: =C9+C10-C11-C12 -> 2254440.9 | D13: =D9+D10-D11-D12 -> 2193356.3 | E13: =E9+E10-E11-E12 -> 2128990.6 | F13: =F9+F10-F11-F12 -> 2320570.8 | G13: =G9+G10-G11-G12 -> 2244789.1 | H13: =H9+H10-H11-H12 -> 0 | I13: =I9+I10-I11-I12 -> 0 | ... M13: =M9+M10-M11-M12 -> 0 | N13: =sum(B13:M13) -> 13206577
A14: F&B Cost | B14: =+B3+B4-B5-B7 -> 555546.14 | C14: =+C3+C4-C5-C7 -> 586200.09 | D14: =+D3+D4-D5-D7 -> 618634.87 | E14: =+E3+E4-E5-E7 -> 622064 | F14: =+F3+F4-F5-F7 -> 719384 | G14: =+G3+G4-G5-G7 -> 634656.17 | H14: =+H3+H4-H5-H7 -> 32579.83 | I14: =+I3+I4-I5-I7 -> 0 | ... M14: =+M3+M4-M5-M7 -> 0 | N14: =sum(B14:M14) -> 3769065.1 | O14: =N14/$N$13 -> 0.28539304
A15: Electricity | B15: 99920 | C15: 104367 | D15: 105142 | E15: 104740 | F15: =107020 -> 107020 | G15: 105000 | N15: =sum(B15:M15) -> 626189 | O15: =N15/$N$13 -> 0.047414936
A16: Telephone/Internet | B16: 145.67 | C16: 145.67 | D16: 145.67 | E16: 145.67 | F16: 145.67 | G16: 145.67 | N16: =sum(B16:M16) -> 874.02 | O16: =N16/$N$13 -> 6.6180661e-05
A17: Gas | B17: =15456+11040 -> 26496 | C17: =25616+25616+32020 -> 83252 | D17: 84462 | E17: 80120 | F17: =81126 -> 81126 | G17: =78652 -> 78652 | N17: =sum(B17:M17) -> 434108 | O17: =N17/$N$13 -> 0.032870592
A18: Rent & Revenue Share | B18: 180000 | C18: 180000 | D18: 180000 | E18: 180000 | F18: 180000 | G18: 180000 | N18: =sum(B18:M18) -> 1080000 | O18: =N18/$N$13 -> 0.081777436
A19: Software | B19: =5767.25 -> 5767.25 | C19: =5767.25 -> 5767.25 | D19: =5767.25 -> 5767.25 | E19: =5767.25 -> 5767.25 | F19: =5767.25 -> 5767.25 | G19: =5767.25 -> 5767.25 | N19: =sum(B19:M19) -> 34603.5 | O19: =N19/$N$13 -> 0.0026201718
A20: Staff Salary | B20: =25960+20119+10000+282526 -> 338605 | C20: =29500+10000+1456+25960+343363 -> 410279 | D20: =29500+10000+359044 -> 398544 | E20: =10800+14055+25960+330264.07+18798 -> 399877.07 | F20: =332276+25960+18798+10800 -> 387834 | G20: =25960+19521+10800+341739.29 -> 398020.29 | N20: =sum(B20:M20) -> 2333159.4 | O20: =N20/$N$13 -> 0.17666647
A21: AMC | B21: =2400+2950+2850+2596 -> 10796 | C21: =2400+2950+2850+2596 -> 10796 | D21: =2750+2596+2400+2950 -> 10696 | E21: =2950+2596 -> 5546 | F21: =5100+2596+2950 -> 10646 | G21: =5100+2596+2950 -> 10646 | N21: =sum(B21:M21) -> 59126 | O21: =N21/$N$13 -> 0.0044770117
A22: Subscription | B22: =2516.16/3+16500/3+9813/12+7080/12 -> 7746.47 | C22: =2516.16/3+16500/3+9813/12+7080/12 -> 7746.47 | D22: =2516.16/3+16500/3+9813/12+7080/12 -> 7746.47 | E22: =9813/12+2516.16/3+16500/3+7080/12 -> 7746.47 | F22: =9813/12+2516.16/3+16500/3+7080/12 -> 7746.47 | G22: =9813/12+2516.16/3+16500/3+7080/12 -> 7746.47 | H22: =9813/12 -> 817.75 | I22: =9813/12 -> 817.75 | J22: =9813/12 -> 817.75 | K22: =9813/12 -> 817.75 | L22: =9813/12 -> 817.75 | M22: =9813/12 -> 817.75 | N22: =sum(B22:M22) -> 51385.32 | O22: =N22/$N$13 -> 0.0038908886
A23: Insurance Premium | B23: 1126.85 | C23: =1698 -> 1698 | D23: =1698 -> 1698 | E23: =1698 -> 1698 | F23: =1698 -> 1698 | G23: =1698 -> 1698 | H23: =1698 -> 1698 | I23: =1698 -> 1698 | J23: =1698 -> 1698 | ... M23: =1698 -> 1698 | N23: =sum(B23:M23) -> 19804.85 | O23: =N23/$N$13 -> 0.0014996202
A24: Repairs & Maintenance | B24: =17705.93 -> 17705.93 | C24: =2207 -> 2207 | D24: 12779 | E24: ='Misc Exp'!M133 -> 10053 | F24: ='Misc Exp'!M90 -> 30041 | G24: ='Misc Exp'!M43 -> 5896 | N24: =sum(B24:M24) -> 78681.93 | O24: =N24/$N$13 -> 0.0059577838
A25: Miscellaneous Expenses | B25: =48492/12+13570 -> 17611 | C25: =48492/12+39169.22 -> 43210.22 | D25: =48492/12+20127.73 -> 24168.73 | E25: =48492/12+'Misc Exp'!M126 -> 51182.533 | F25: =48492/12+'Misc Exp'!M84 -> 21500.74 | G25: =48492/12+'Misc Exp'!M38 -> 26126.97 | H25: =48492/12 -> 4041 | I25: =48492/12 -> 4041 | J25: =48492/12 -> 4041 | K25: =48492/12 -> 4041 | L25: =48492/12 -> 4041 | M25: =48492/12 -> 4041 | N25: =sum(B25:M25) -> 208046.19 | O25: =N25/$N$13 -> 0.015753226
A26: CAM | B26: 5000 | C26: 5000 | D26: 5000 | E26: 5000 | F26: 5000 | G26: 5000 | N26: =sum(B26:M26) -> 30000 | O26: =N26/$N$13 -> 0.0022715954
A27: HO+CK Cost | B27: =HO!D39 -> 458360.81 | C27: =HO!H39 -> 473627.54 | D27: =HO!L39 -> 480585.9 | E27: =HO!P39 -> 465700.68 | F27: =HO!D58 -> 460727.06 | G27: =HO!H58 -> 502940.49 | H27: =HO!L58 -> #DIV/0! | I27: =HO!P58 -> #DIV/0! | J27: =HO!D77 -> #DIV/0! | K27: =HO!H77 -> #DIV/0! | L27: =HO!L77 -> #DIV/0! | M27: =HO!P77 -> #DIV/0! | N27: =sum(B27:M27) -> #DIV/0! | O27: =N27/$N$13 -> #DIV/0!
A28: Operating Expenses | B28: =+SUM(B14:B27) -> 1724827.1 | C28: =+SUM(C14:C27) -> 1914296.2 | D28: =+SUM(D14:D27) -> 1935369.9 | E28: =+SUM(E14:E27) -> 1939640.7 | F28: =+SUM(F14:F27) -> 2018636.2 | G28: =+SUM(G14:G27) -> 1962295.3 | H28: =+SUM(H14:H27) -> #DIV/0! | I28: =+SUM(I14:I27) -> #DIV/0! | ... M28: =+SUM(M14:M27) -> #DIV/0! | N28: =sum(B28:M28) -> #DIV/0! | O28: =N28/N13 -> #DIV/0!
A29: Store Level EBITDA | B29: =B13-B28 -> 339602.27 | C29: =C13-C28 -> 340144.67 | D29: =D13-D28 -> 257986.37 | E29: =E13-E28 -> 189349.96 | F29: =F13-F28 -> 301934.56 | G29: =G13-G28 -> 282493.75 | H29: =H13-H28 -> #DIV/0! | I29: =I13-I28 -> #DIV/0! | ... M29: =M13-M28 -> #DIV/0! | N29: =sum(B29:M29) -> #DIV/0! | O29: =N29/N13 -> #DIV/0!
A30: Food Cost | B30: =(B14/B13) -> 0.26910397 | C30: =(C14/C13) -> 0.26002016 | D30: =(D14/D13) -> 0.28204942 | E30: =(E14/E13) -> 0.29218729 | F30: =(F14/F13) -> 0.31000305 | G30: =(G14/G13) -> 0.28272419 | H30: =(H14/H13) -> #DIV/0! | I30: =(I14/I13) -> #DIV/0! | ... M30: =(M14/M13) -> #DIV/0!

Sheet Quest Mall
A1: Dosa Coffee - Quest Mall | B1: =Summary!C1 -> 46113 | C1: =Summary!D1 -> 46143 | D1: =Summary!E1 -> 46174 | E1: =Summary!F1 -> 46204 | F1: =Summary!G1 -> 46235 | G1: =Summary!H1 -> 46266 | H1: =Summary!I1 -> 46296 | I1: =Summary!J1 -> 46327 | ... M1: =Summary!N1 -> 46447 | N1: FY 2025-26
A2: Food Cost Calculation
A3: Opening Stock | B3: 26431 | C3: =B7 -> 26476.9 | D3: =C7 -> 26517.6 | E3: =D7 -> 28972 | F3: =E7 -> 35628 | G3: =F7 -> 31301.72 | H3: =G7 -> 31115.79 | I3: =H7 | J3: =I7 | ... M3: =L7 | N3: =+SUM(J3:L3) -> 0
A4: Purchases Food (Less Purchase Return) | B4: =202555.22 -> 202555.22 | C4: 230206.84 | D4: =258617-371 -> 258246 | E4: 297086 | F4: 328617.5 | G4: 294770.41 | N4: =sum(B4:M4) -> 1611482
A5: Transferred Out | B5: =581.61 -> 581.61 | C5: 232.05 | D5: 0 | E5: 50 | F5: 0 | G5: 175.66 | N5: =+SUM(J5:L5) -> 0
A6: Wastage & Date Expired | B6: 10885.49 | C6: 6071.62 | D6: 8400 | E6: 14904 | F6: 20972.76 | G6: 29838.28 | N6: =+SUM(J6:L6) -> 0
A7: Closing Stock | B7: 26476.9 | C7: 26517.6 | D7: 28972 | E7: 35628 | F7: 31301.72 | G7: 31115.79 | N7: =sum(B7:M7) -> 180012.01
A9: Gross Revenue | B9: =812876.2*1.05 -> 853520.01 | C9: =886185.85*1.05 -> 930495.14 | D9: =1031212.73*1.05 -> 1082773.4 | E9: =1119835.82*1.05 -> 1175827.6 | F9: =1230446.98*1.05 -> 1291969.3 | G9: =1014168.4*1.05 -> 1064876.8 | N9: =+SUM(B9:M9) -> 6399462.3
A10: Catering & Fairs | B10: 0 | N10: =+SUM(B10:M10) -> 0
A11: Less Tax | B11: =(B9+B10)/1.05*0.05 -> 40643.81 | C11: =(C9+C10)/1.05*0.05 -> 44309.293 | D11: =(D9+D10)/1.05*0.05 -> 51560.637 | E11: =(E9+E10)/1.05*0.05 -> 55991.791 | F11: =(F9+F10)/1.05*0.05 -> 61522.349 | G11: =(G9+G10)/1.05*0.05 -> 50708.42 | H11: =(H9+H10)/1.05*0.05 -> 0 | I11: =(I9+I10)/1.05*0.05 -> 0 | ... M11: =(M9+M10)/1.05*0.05 -> 0 | N11: =+SUM(B11:M11) -> 304736.3
A12: Less Commission | B12: 0 | C12: 0 | D12: 0 | E12: 0 | F12: 0 | G12: 0 | H12: 0 | I12: 0 | J12: 0 | K12: 0 | L12: 0 | M12: 0 | N12: =+SUM(B12:M12) -> 0
A13: Net Revenues from F&B Sales | B13: =B9+B10-B11-B12 -> 812876.2 | C13: =C9+C10-C11-C12 -> 886185.85 | D13: =D9+D10-D11-D12 -> 1031212.7 | E13: =E9+E10-E11-E12 -> 1119835.8 | F13: =F9+F10-F11-F12 -> 1230447 | G13: =G9+G10-G11-G12 -> 1014168.4 | H13: =H9+H10-H11-H12 -> 0 | I13: =I9+I10-I11-I12 -> 0 | ... M13: =M9+M10-M11-M12 -> 0 | N13: =sum(B13:M13) -> 6094726
A14: F&B Cost | B14: =+B3+B4-B5-B7 -> 201927.71 | C14: =+C3+C4-C5-C7 -> 229934.09 | D14: =+D3+D4-D5-D7 -> 255791.6 | E14: =+E3+E4-E5-E7 -> 290380 | F14: =+F3+F4-F5-F7 -> 332943.78 | G14: =+G3+G4-G5-G7 -> 294780.68 | H14: =+H3+H4-H5-H7 -> 31115.79 | I14: =+I3+I4-I5-I7 -> 0 | ... M14: =+M3+M4-M5-M7 -> 0 | N14: =sum(B14:M14) -> 1636873.6 | O14: =N14/$N$13 -> 0.26857215
A15: Electricity | B15: 30554.25 | C15: 32890.76 | D15: =31045 -> 31045 | E15: 31610.35 | F15: =32951.24 -> 32951.24 | G15: 30000 | N15: =sum(B15:M15) -> 189051.6 | O15: =N15/$N$13 -> 0.031018884
A16: Telephone/Internet | B16: 801.42 | C16: 801.42 | D16: 801.42 | E16: 801.42 | F16: 801.42 | G16: 801.42 | N16: =sum(B16:M16) -> 4808.52 | O16: =N16/$N$13 -> 0.0007889641
A17: Gas | B17: =47511 -> 47511 | C17: 75306.84 | D17: 78110.78 | E17: 78519 | F17: 75786 | G17: 73145 | N17: =sum(B17:M17) -> 428378.62 | O17: =N17/$N$13 -> 0.070286773
A18: Rent & Revenue Share | B18: =B13*0.14*1.18 -> 134287.15 | C18: =C13*0.14*1.18 -> 146397.9 | D18: 170351 | E18: =E13*0.14*1.18 -> 184996.88 | F18: =F13*0.14*1.18 -> 203269.84 | G18: =G13*0.14*1.18 -> 167540.62 | N18: =sum(B18:M18) -> 1006843.4 | O18: =N18/$N$13 -> 0.16519912
A19: Software | B19: 4080.83 | C19: 4080.83 | D19: 4080.83 | E19: 4080.83 | F19: 4080.83 | G19: 4080.83 | N19: =sum(B19:M19) -> 24484.98 | O19: =N19/$N$13 -> 0.0040174046
A20: Staff Salary | B20: =169898 -> 169898 | C20: =175464 -> 175464 | D20: 174567 | E20: =174568.26 -> 174568.26 | F20: 161637 | G20: =152589.03 -> 152589.03 | N20: =sum(B20:M20) -> 1008723.3 | O20: =N20/$N$13 -> 0.16550757
A21: AMC | B21: =2400+2950+2850+2360 -> 10560 | C21: =2400+2950+2850+2360 -> 10560 | D21: =2400+2950+2850+2360 -> 10560 | E21: =2950+2596+2400 -> 7946 | F21: =5880+2596+2950 -> 11426 | G21: =5880+2596+2950 -> 11426 | N21: =sum(B21:M21) -> 62478 | O21: =N21/$N$13 -> 0.010251158
A22: Subscription | B22: 0 | C22: 0 | D22: 0 | E22: 0 | F22: 0 | G22: 0 | N22: =sum(B22:M22) -> 0 | O22: =N22/$N$13 -> 0
A23: Insurance Premium | B23: 868.94 | C23: =1698 -> 1698 | D23: =1698 -> 1698 | E23: =1698 -> 1698 | F23: =1698 -> 1698 | G23: =1698 -> 1698 | H23: =1698 -> 1698 | I23: =1698 -> 1698 | J23: =1698 -> 1698 | ... M23: =1698 -> 1698 | N23: =sum(B23:M23) -> 19546.94 | O23: =N23/$N$13 -> 0.0032071893
A24: Repairs & Maintenance | B24: 1218 | C24: 0 | D24: 3200 | E24: ='Misc Exp'!O133 -> 5900 | F24: ='Misc Exp'!O90 -> 150 | G24: ='Misc Exp'!O43 -> 0 | N24: =sum(B24:M24) -> 10468 | O24: =N24/$N$13 -> 0.0017175506
A25: Miscellaneous Expenses | B25: =50492/12+3797.34+124271/12 -> 18360.923 | C25: =50492/12+11879.35+124271/12 -> 26442.933 | D25: =50492/12+3827.57+124271/12 -> 18391.153 | E25: =50492/12+'Misc Exp'!O126+124271/12 -> 19365.707 | F25: =50492/12+124271/12+'Misc Exp'!O84 -> 19474.483 | G25: =50492/12+124271/12+'Misc Exp'!O38 -> 24642.963 | H25: =50492/12+124271/12 -> 14563.583 | I25: =50492/12+124271/12 -> 14563.583 | J25: =50492/12+124271/12 -> 14563.583 | K25: =50492/12+124271/12 -> 14563.583 | L25: =50492/12+124271/12 -> 14563.583 | M25: =50492/12+124271/12 -> 14563.583 | N25: =sum(B25:M25) -> 214059.66 | O25: =N25/$N$13 -> 0.035122114
A26: CAM | B26: =107702.14 -> 107702.14 | C26: 107702.14 | D26: 107702.14 | E26: 107702.14 | F26: 107702.14 | G26: 107702.14 | N26: =sum(B26:M26) -> 646212.84 | O26: =N26/$N$13 -> 0.1060282
A27: HO+CK Cost | B27: =HO!D29 -> 180481.15 | C27: =HO!H29 -> 186175.66 | D27: =HO!L29 -> 225948.84 | E27: =HO!P29 -> 244955.66 | F27: =HO!D48 -> 244293.44 | G27: =HO!H48 -> 227222.4 | H27: =HO!L48 -> #DIV/0! | I27: =HO!P48 -> #DIV/0! | J27: =HO!D67 -> #DIV/0! | K27: =HO!H67 -> #DIV/0! | L27: =HO!L67 -> #DIV/0! | M27: =HO!P67 -> #DIV/0! | N27: =sum(B27:M27) -> #DIV/0! | O27: =N27/$N$13 -> #DIV/0!
A28: Operating Expenses | B28: =+SUM(B14:B27) -> 908251.51 | C28: =+SUM(C14:C27) -> 997454.58 | D28: =+SUM(D14:D27) -> 1082247.8 | E28: =+SUM(E14:E27) -> 1152524.2 | F28: =+SUM(F14:F27) -> 1196214.2 | G28: =+SUM(G14:G27) -> 1095629.1 | H28: =+SUM(H14:H27) -> #DIV/0! | I28: =+SUM(I14:I27) -> #DIV/0! | ... M28: =+SUM(M14:M27) -> #DIV/0! | N28: =sum(B28:M28) -> #DIV/0! | O28: =N28/$N$13 -> #DIV/0!
A29: Store Level EBITDA | B29: =B13-B28 -> -95375.312 | C29: =C13-C28 -> -111268.73 | D29: =D13-D28 -> -51035.03 | E29: =E13-E28 -> -32688.423 | F29: =F13-F28 -> 34232.801 | G29: =G13-G28 -> -81460.679 | H29: =H13-H28 -> #DIV/0! | I29: =I13-I28 -> #DIV/0! | ... M29: =M13-M28 -> #DIV/0! | N29: =sum(B29:M29) -> #DIV/0! | O29: =N29/$N$13 -> #DIV/0!
A30: Food Cost | B30: =(B14/B13) -> 0.24841139 | C30: =(C14/C13) -> 0.25946486 | D30: =(D14/D13) -> 0.2480493 | E30: =(E14/E13) -> 0.25930587 | F30: =(F14/F13) -> 0.27058767 | G30: =(G14/G13) -> 0.29066246 | H30: =(H14/H13) -> #DIV/0! | I30: =(I14/I13) -> #DIV/0! | ... M30: =(M14/M13) -> #DIV/0!

Sheet Event Sales
A1: Dosa Coffee - Event Sales | B1: =Summary!C1 -> 46113 | C1: =Summary!D1 -> 46143 | D1: =Summary!E1 -> 46174 | E1: =Summary!F1 -> 46204 | F1: =Summary!G1 -> 46235 | G1: =Summary!H1 -> 46266 | H1: =Summary!I1 -> 46296 | I1: =Summary!J1 -> 46327 | ... M1: =Summary!N1 -> 46447 | N1: FY 2025-26
A2: Food Cost Calculation
A3: Opening Stock | B3: 0 | C3: =B7 -> 0 | D3: =C7 -> 0 | E3: =D7 -> 0 | F3: =E7 -> 0 | G3: 0 | H3: 0 | I3: =H7 | J3: =I7 | K3: =J7 | L3: =K7 | M3: =L7 | N3: =+SUM(J3:L3) -> 0
A4: Purchases Food (Less Purchase Return) | B4: 5276.62 | C4: 18323.01 | D4: =67552-14726 -> 52826 | E4: 75127 | F4: =15600-8452 -> 7148 | G4: 0 | N4: =sum(B4:M4) -> 158700.63
A5: Transferred Out | B5: 0 | C5: 830.49 | D5: 0 | E5: 1007 | F5: 730 | G5: 0 | N5: =+SUM(J5:L5) -> 0
A6: Wastage & Date Expired | B6: 0 | C6: 0 | D6: 0 | E6: 5026 | F6: 0 | G6: 0 | N6: =+SUM(J6:L6) -> 0
A7: Closing Stock | B7: 0 | C7: 0 | D7: 0 | E7: 0 | F7: 0 | G7: 0 | N7: =sum(B7:M7) -> 0
A9: Gross Revenue | B9: =49999.25*1.05 -> 52499.213 | C9: =33600*1.05 -> 35280 | D9: =126940*1.05 -> 133287 | E9: =136542.7*1.05 -> 143369.83 | F9: =5410*1.05 -> 5680.5 | N9: =+SUM(B9:M9) -> 370116.55
A10: Catering & Fairs | N10: =+SUM(B10:M10) -> 0
A11: Less Tax | B11: =(B9+B10)/1.05*0.05 -> 2499.9625 | C11: =(C9+C10)/1.05*0.05 -> 1680 | D11: =(D9+D10)/1.05*0.05 -> 6347 | E11: =(E9+E10)/1.05*0.05 -> 6827.135 | F11: =(F9+F10)/1.05*0.05 -> 270.5 | G11: =(G9+G10)/1.05*0.05 -> 0 | H11: =(H9+H10)/1.05*0.05 -> 0 | I11: =(I9+I10)/1.05*0.05 -> 0 | ... M11: =(M9+M10)/1.05*0.05 -> 0 | N11: =+SUM(B11:M11) -> 17624.597
A12: Less Commission | B12: 0 | C12: 0 | D12: 0 | N12: =+SUM(B12:M12) -> 0
A13: Net Revenues from F&B Sales | B13: =B9+B10-B11-B12 -> 49999.25 | C13: =C9+C10-C11-C12 -> 33600 | D13: =D9+D10-D11-D12 -> 126940 | E13: =E9+E10-E11-E12 -> 136542.7 | F13: =F9+F10-F11-F12 -> 5410 | G13: =G9+G10-G11-G12 -> 0 | H13: =H9+H10-H11-H12 -> 0 | I13: =I9+I10-I11-I12 -> 0 | ... M13: =M9+M10-M11-M12 -> 0 | N13: =sum(B13:M13) -> 352491.95 | O13: =N13/$N$7 -> #DIV/0!
A14: F&B Cost | B14: =+B3+B4-B5-B7 -> 5276.62 | C14: =+C3+C4-C5-C7 -> 17492.52 | D14: =+D3+D4-D5-D7 -> 52826 | E14: =+E3+E4-E5-E7 -> 74120 | F14: =+F3+F4-F5-F7 -> 6418 | G14: =+G3+G4-G5-G7 -> 0 | H14: =+H3+H4-H5-H7 -> 0 | I14: =+I3+I4-I5-I7 -> 0 | ... M14: =+M3+M4-M5-M7 -> 0 | N14: =sum(B14:M14) -> 156133.14 | O14: =N14/$N$7 -> #DIV/0!
A15: Electricity | B15: 0 | C15: 0 | D15: 0 | E15: 0 | F15: 0 | N15: =sum(B15:M15) -> 0 | O15: =N15/$N$7 -> #DIV/0!
A16: Telephone/Internet | B16: 0 | C16: 0 | D16: 0 | E16: 0 | F16: 0 | N16: =sum(B16:M16) -> 0 | O16: =N16/$N$7 -> #DIV/0!
A17: Gas | B17: 0 | C17: 6404 | D17: 0 | E17: 9245 | F17: 2798 | M17: 0 | N17: =sum(B17:M17) -> 18447 | O17: =N17/$N$7 -> #DIV/0!
A18: Rent & Revenue Share | B18: 0 | C18: 0 | D18: 0 | E18: 20000 | F18: 0 | N18: =sum(B18:M18) -> 20000 | O18: =N18/$N$7 -> #DIV/0!
A19: Software | B19: 0 | C19: 0 | D19: 0 | E19: 0 | F19: 0 | N19: =sum(B19:M19) -> 0 | O19: =N19/$N$7 -> #DIV/0!
A20: Staff Salary | B20: 0 | C20: 0 | D20: 0 | E20: 0 | F20: 0 | N20: =sum(B20:M20) -> 0 | O20: =N20/$N$7 -> #DIV/0!
A21: AMC | B21: 0 | C21: 0 | D21: 0 | E21: 0 | F21: 0 | N21: =sum(B21:M21) -> 0 | O21: =N21/$N$7 -> #DIV/0!
A22: Staff Incentives | B22: 0 | C22: 0 | D22: 0 | E22: 0 | F22: 0 | N22: =sum(B22:M22) -> 0 | O22: =N22/$N$7 -> #DIV/0!
A23: Insurance Premium | B23: 0 | C23: 0 | D23: 0 | E23: 0 | F23: 0
A24: Repairs & Maintenance | B24: 0 | C24: 0 | D24: 4774 | E24: 0 | F24: 0 | G24: ='Misc Exp'!Q43 -> 0 | N24: =sum(B24:M24) -> 4774 | O24: =N24/$N$7 -> #DIV/0!
A25: Miscellaneous Expenses | B25: 10104 | C25: 7309 | D25: 0 | E25: ='Misc Exp'!Q126 -> 29973.333 | F25: ='Misc Exp'!Q84 -> 1937 | G25: ='Misc Exp'!Q38 -> 25131 | N25: =sum(B25:M25) -> 74454.333 | O25: =N25/$N$7 -> #DIV/0!
A26: CAM | B26: 0 | C26: 0 | D26: 0 | E26: 0 | F26: 0 | N26: =sum(B26:M26) -> 0 | O26: =N26/$N$7 -> #DIV/0!
A27: HO+CK Cost | B27: =HO!D41 -> 11101.226 | C27: =HO!H41 -> 7058.9055 | D27: =HO!L41 -> 27813.801 | E27: =HO!P41 -> 29867.688 | F27: =HO!D60 -> 1074.1036 | G27: =HO!H60 -> 0 | H27: =HO!L60 -> #DIV/0! | I27: =HO!P60 -> #DIV/0! | J27: =HO!D79 -> #DIV/0! | K27: =HO!H79 -> #DIV/0! | L27: =HO!L79 -> #DIV/0! | M27: =HO!P79 -> #DIV/0! | N27: =sum(B27:M27) -> #DIV/0! | O27: =N27/$N$7 -> #DIV/0!
A28: Operating Expenses | B28: =+SUM(B14:B27) -> 26481.846 | C28: =+SUM(C14:C27) -> 38264.426 | D28: =+SUM(D14:D27) -> 85413.801 | E28: =+SUM(E14:E27) -> 163206.02 | F28: =+SUM(F14:F27) -> 12227.104 | G28: =+SUM(G14:G27) -> 25131 | H28: =+SUM(H14:H27) -> #DIV/0! | I28: =+SUM(I14:I27) -> #DIV/0! | ... M28: =+SUM(M14:M27) -> #DIV/0! | N28: =sum(B28:M28) -> #DIV/0! | O28: =N28/$N$7 -> #DIV/0!
A29: Store Level EBITDA | B29: =B13-B28 -> 23517.404 | C29: =C13-C28 -> -4664.4255 | D29: =D13-D28 -> 41526.199 | E29: =E13-E28 -> -26663.321 | F29: =F13-F28 -> -6817.1036 | G29: =G13-G28 -> -25131 | H29: =H13-H28 -> #DIV/0! | I29: =I13-I28 -> #DIV/0! | ... M29: =M13-M28 -> #DIV/0! | N29: =sum(B29:M29) -> #DIV/0! | O29: =N29/$N$7 -> #DIV/0!
A30: Food Cost | B30: =(B14/B13) -> 0.10553398 | C30: =(C14/C13) -> 0.52061071 | D30: =(D14/D13) -> 0.41614936 | E30: =(E14/E13) -> 0.54283385 | F30: =(F14/F13) -> 1.1863216 | G30: =(G14/G13) -> #DIV/0! | H30: =(H14/H13) -> #DIV/0! | I30: =(I14/I13) -> #DIV/0! | ... M30: =(M14/M13) -> #DIV/0!
A31: Depriciation (2%) + Interest (1%)
A32: P/L | B32: =B29-B31 -> 23517.404 | C32: =C29-C31 -> -4664.4255 | D32: =D29-D31 -> 41526.199 | E32: =E29-E31 -> -26663.321 | F32: =F29-F31 -> -6817.1036 | G32: =G29-G31 -> -25131 | H32: =H29-H31 -> #DIV/0! | I32: =I29-I31 -> #DIV/0! | ... M32: =M29-M31 -> #DIV/0! | N32: =sum(B32:J32) -> #DIV/0!

Sheet Central Kitchen - Kolkata
A1: Capital Deployed
B2: =Summary!C1 -> 46113 | C2: =Summary!D1 -> 46143 | D2: =Summary!E1 -> 46174 | E2: =Summary!F1 -> 46204 | F2: =Summary!G1 -> 46235 | G2: =Summary!H1 -> 46266 | H2: =Summary!I1 -> 46296 | I2: =Summary!J1 -> 46327 | ... M2: =Summary!N1 -> 46447 | N2: FY 2024-25
A3: Food Cost Calculation
A4: Opening Stock | B4: =1407577.72 -> 1407577.7 | C4: =B7 -> 1556076.4 | D4: =C7 -> 1160094.1 | E4: =D7 -> 1297940 | F4: =E7 -> 1375782 | G4: =F7 -> 1248156.8 | H4: =G7 -> 1346378.4 | I4: =H7 | J4: =I7 | ... M4: =L7
A5: Purchases Food (Less Purchase Return) | B5: =5917527.79 -> 5917527.8 | C5: =5769642.08 -> 5769642.1 | D5: =6297331.45-423 -> 6296908.5 | E5: =6305757 -> 6305757 | F5: =6808957.72 -> 6808957.7 | G5: =6935964 -> 6935964 | N5: =SUM(B5:M5) -> 38034757
A6: Transferred Out | B6: 5641542.2 | C6: 6117758.7 | D6: =6056092.58 -> 6056092.6 | E6: 6259971 | F6: =8398712-1491404 -> 6907308 | G6: =6135736 -> 6135736 | N6: =SUM(B6:M6) -> 37118408 | P6: =M6
A7: Closing Stock | B7: =1369686.41+186390 -> 1556076.4 | C7: =983166.68+176927.4 -> 1160094.1 | D7: =1128815+169125 -> 1297940 | E7: =197059+1178723 -> 1375782 | F7: =1032765.76+215391 -> 1248156.8 | G7: =1169931.67+176446.72 -> 1346378.4 | P7: =Summary!N4 -> 0
P8: =P6-P7 -> 0
A9: Consumption | B9: =B4+B5-B6-B7 -> 127486.89 | C9: =C4+C5-C6-C7 -> 47865.7 | D9: =D4+D5-D6-D7 -> 102969.95 | E9: =E4+E5-E6-E7 -> -32056 | F9: =F4+F5-F6-F7 -> 29274.96 | G9: =G4+G5-G6-G7 -> 702006.37 | H9: =H4+H5-H6-H7 -> 1346378.4 | I9: =I4+I5-I6-I7 -> 0 | ... M9: =M4+M5-M6-M7 -> 0 | N9: =sum(B9:M9) -> 2323926.3 | P9: -49525
A10: Wastage | B10: =1903.54+25271.35 -> 27174.89 | C10: =13677.25+29835.47 -> 43512.72 | D10: =1424+24510 -> 25934 | E10: =29271+4153.47 -> 33424.47 | F10: =4072+41271 -> 45343 | G10: =6544+46727.93 -> 53271.93 | N10: =SUM(D10:M10) -> 157973.4
A11: Electricity | B11: 201560 | C11: 226640 | D11: 226580 | E11: =205110-13950 -> 191160 | F11: =228630 -> 228630 | G11: 223740 | N11: =sum(B11:M11) -> 1298310
A12: Telephone/Internet | B12: =4718.82+142.12+1500 -> 6360.94 | C12: =4718.82 -> 4718.82 | D12: =4718.82 -> 4718.82 | E12: =4718.82 -> 4718.82 | F12: =4718.82 -> 4718.82 | G12: =4718.82 -> 4718.82 | N12: =sum(B12:M12) -> 29955.04
A13: Gas | B13: =52992+99360+39744+119232 -> 311328 | C13: =115272+99262+89656 -> 304190 | D13: 325549 | E13: 326640 | F13: =318914 -> 318914 | G13: =323035 -> 323035 | N13: =sum(B13:M13) -> 1909656
A14: Rent & CAM | B14: =162840+108560 -> 271400 | C14: =162840+108560 -> 271400 | D14: =162840+108560 -> 271400 | E14: =162840+108560 -> 271400 | F14: =162840+108560 -> 271400 | G14: =162840+108560 -> 271400 | N14: =sum(B14:M14) -> 1628400
A15: Software | B15: =8358.33 -> 8358.33 | C15: =8358.33 -> 8358.33 | D15: =8358.33 -> 8358.33 | E15: =8358.33 -> 8358.33 | F15: =8358.33 -> 8358.33 | G15: =8358.33 -> 8358.33 | N15: =sum(B15:M15) -> 50149.98
A16: Staff Salary | B16: =18480+11548+3000+523310+114184+75709+13000+14976 -> 774207 | C16: =5800+3000+18480+11548+20279+30376+13000+146042+75709+547670 -> 871904 | D16: =30544+72286+117969+23653+13000+18648+556264 -> 832364 | E16: =30196+139418+13000+15000+81851+543824 -> 823289 | F16: =548226+81680+100000+146988+13000+10962+30196 -> 931052 | G16: =81680+146988+30196+546288 -> 805152 | N16: =sum(B16:M16) -> 5037968
A17: Insurance Premium | B17: =4165.39 -> 4165.39 | C17: =1698 -> 1698 | D17: =1698 -> 1698 | E17: =1698 -> 1698 | F17: =1698 -> 1698 | G17: =1698 -> 1698 | H17: =1698 -> 1698 | I17: =1698 -> 1698 | J17: =1698 -> 1698 | ... M17: =1698 -> 1698 | N17: =sum(B17:M17) -> 22843.39
A18: Repairs & Maintenance | B18: =60614+39394 -> 100008 | C18: =101626+39394 -> 141020 | D18: 215575 | E18: ='Misc Exp'!S133 -> 187437 | F18: ='Misc Exp'!S90 -> 126466 | G18: ='Misc Exp'!S43 -> 90690 | N18: =sum(B18:M18) -> 861196
A19: Membership & Subscription | B19: 0 | C19: 0 | D19: 0 | N19: =sum(B19:M19) -> 0
A20: AMC | B20: =2720+9440+2850+8437 -> 23447 | C20: =2720+9440+2850+8437 -> 23447 | D20: =4180+9440+2780+8437 -> 24837 | E20: =9440+8437+7500+1200 -> 26577 | F20: =5270+8437+9440 -> 23147 | G20: =5270+8437+9440 -> 23147 | N20: =sum(B20:M20) -> 144602
A21: Subscription | B21: 0 | C21: 0 | D21: 0 | E21: 0 | F21: 0
A22: Miscellaneous Expenses | B22: =18760/12+38737.22+34235/12 -> 43153.47 | C22: =18760/12+186065.22+34235/12 -> 190481.47 | D22: =18760/12+205434+34235/12 -> 209850.25 | E22: =18760/12+'Misc Exp'!S126+34235/12 -> 286720.58 | F22: =18760/12+34235/12+'Misc Exp'!S84 -> 215758.42 | G22: =18760/12+34235/12+'Misc Exp'!S38 -> 259824.58 | H22: =18760/12+34235/12 -> 4416.25 | I22: =18760/12+34235/12 -> 4416.25 | J22: =18760/12+34235/12 -> 4416.25 | K22: =18760/12+34235/12 -> 4416.25 | L22: =18760/12+34235/12 -> 4416.25 | M22: =18760/12+34235/12 -> 4416.25 | N22: =sum(B22:M22) -> 1232286.3
A23: Conveyance | B23: 0 | C23: 0 | D23: 0 | E23: 0 | F23: 0 | G23: 0 | N23: =sum(B23:M23) -> 0
A24: Transport Charges | B24: =66529 -> 66529 | C24: =34743+30480 -> 65223 | D24: =35893 -> 35893 | E24: 24223 | F24: 36279 | G24: 369512 | N24: =sum(B24:M24) -> 597659
A25: Operating Expenses | B25: =SUM(B10:B24) -> 1837692 | C25: =SUM(C10:C24) -> 2152593.3 | D25: =SUM(D10:D24) -> 2182757.4 | E25: =SUM(E10:E24) -> 2185646.2 | F25: =SUM(F10:F24) -> 2211764.6 | G25: =SUM(G11:G24) -> 2381275.7 | H25: =SUM(H11:H24) -> 6114.25 | I25: =SUM(I11:I24) -> 6114.25 | J25: =SUM(J11:J24) -> 6114.25 | K25: =SUM(K11:K24) -> 6114.25 | L25: =SUM(L11:L24) -> 6114.25 | M25: =SUM(M11:M24) -> 6114.25 | N25: =sum(B25:M25) -> 12988415

Sheet Ads Account
A1: Dosa Coffee - Kolkata | B1: =Summary!C1 -> 46113 | C1: =Summary!D1 -> 46143 | D1: =Summary!E1 -> 46174 | E1: =Summary!F1 -> 46204 | F1: =Summary!G1 -> 46235 | G1: =Summary!H1 -> 46266 | H1: =Summary!I1 -> 46296 | I1: =Summary!J1 -> 46327 | ... M1: =Summary!N1 -> 46447 | N1: FY 25-26
A2: Advertisement & Promotion | N2: =+SUM(B2:M2) -> 0
A3: - Team
A4: - Social Media/Digital Media | B4: =35400+62663.68 -> 98063.68 | C4: =35400+65255 -> 100655 | D4: =35400 -> 35400 | E4: =35400+88297 -> 123697 | F4: =35400+36506 -> 71906 | G4: =35400 -> 35400
A5: - Print Media | C5: =30713 -> 30713
A6: - Radio
A7: - Public Relations
A8: - Influencers | C8: 45000 | D8: =(4000+45400+26000+40000+78000)/2 -> 96700 | E8: 15000 | F8: 10000 | G8: 71000
A9: - POP Materials
A10: - Photo and Video Shoot | B10: =47702 -> 47702 | C10: 25000 | D10: 0 | E10: 10620 | F10: =17700 -> 17700 | G10: =23600+17287+20000 -> 60887
A11: - Website | N11: =+SUM(B11:M11) -> 0
A12: - Competitions and Give Aways | N12: =+SUM(B12:M12) -> 0
