Workbook

Sheet Summary
A1: Dosa Coffee - Kolkata | B1: Department | C1: 45748 | D1: 45778 | E1: 45809 | F1: 45839 | G1: 45870 | H1: 45901 | I1: 45931 | J1: 45962 | K1: 45992 | L1: 46023 | M1: 46054 | N1: 46082 | O1: FY 2025-26
A2: Food Cost Calculation
A3: Opening Stock | B3: Procurement | C3: ='Ideal Plaza'!B3+'Salt Lake JC -21'!B3+'Forum Mall'!B3+'Lake Town'!B3+'Quest Mall'!B3+'Rosedale Plaza'!B3+'Mani Square Mall'!B3+'Forum Rangoli'!B3+CSC!B3+Jameslong!B3+Technopolis!B3+Santoshpur!B3+'Chinar Park'!B3+'Lake Road'!B3+Kalikapur!B3+'Event Sales'!B3+'Sector 1'!B3 -> 481976.41 | D3: ='Ideal Plaza'!C3+'Salt Lake JC -21'!C3+'Forum Mall'!C3+'Lake Town'!C3+'Quest Mall'!C3+'Rosedale Plaza'!C3+'Mani Square Mall'!C3+'Forum Rangoli'!C3+CSC!C3+Jameslong!C3+Technopolis!C3+Santoshpur!C3+'Chinar Park'!C3+'Lake Road'!C3+Kalikapur!C3+'Event Sales'!C3+'Sector 1'!C3 -> 511140.61 | E3: ='Ideal Plaza'!D3+'Salt Lake JC -21'!D3+'Forum Mall'!D3+'Lake Town'!D3+'Quest Mall'!D3+'Rosedale Plaza'!D3+'Mani Square Mall'!D3+'Forum Rangoli'!D3+CSC!D3+Jameslong!D3+Technopolis!D3+Santoshpur!D3+'Chinar Park'!D3+'Lake Road'!D3+Kalikapur!D3+'Event Sales'!D3+'Sector 1'!D3 -> 503059.99 | F3: ='Ideal Plaza'!E3+'Salt Lake JC -21'!E3+'Forum Mall'!E3+'Lake Town'!E3+'Quest Mall'!E3+'Rosedale Plaza'!E3+'Mani Square Mall'!E3+'Forum Rangoli'!E3+CSC!E3+Jameslong!E3+Technopolis!E3+Santoshpur!E3+'Chinar Park'!E3+'Lake Road'!E3+Kalikapur!E3+'Event Sales'!E3+'Sector 1'!E3 -> 509757.55 | G3: ='Ideal Plaza'!F3+'Salt Lake JC -21'!F3+'Forum Mall'!F3+'Lake Town'!F3+'Quest Mall'!F3+'Rosedale Plaza'!F3+'Mani Square Mall'!F3+'Forum Rangoli'!F3+CSC!F3+Jameslong!F3+Technopolis!F3+Santoshpur!F3+'Chinar Park'!F3+'Lake Road'!F3+Kalikapur!F3+'Event Sales'!F3+'Sector 1'!F3 -> 535959.05 | H3: ='Ideal Plaza'!G3+'Salt Lake JC -21'!G3+'Forum Mall'!G3+'Lake Town'!G3+'Quest Mall'!G3+'Rosedale Plaza'!G3+'Mani Square Mall'!G3+'Forum Rangoli'!G3+CSC!G3+Jameslong!G3+Technopolis!G3+Santoshpur!G3+'Chinar Park'!G3+'Lake Road'!G3+Kalikapur!G3+'Event Sales'!G3+'Sector 1'!G3 -> 475720.3 | I3: ='Ideal Plaza'!H3+'Salt Lake JC -21'!H3+'Forum Mall'!H3+'Lake Town'!H3+'Quest Mall'!H3+'Rosedale Plaza'!H3+'Mani Square Mall'!H3+'Forum Rangoli'!H3+CSC!H3+Jameslong!H3+Technopolis!H3+Santoshpur!H3+'Chinar Park'!H3+'Lake Road'!H3+Kalikapur!H3+'Event Sales'!H3+'Sector 1'!H3 -> 580618.48 | J3: ='Ideal Plaza'!I3+'Salt Lake JC -21'!I3+'Forum Mall'!I3+'Lake Town'!I3+'Quest Mall'!I3+'Rosedale Plaza'!I3+'Mani Square Mall'!I3+'Forum Rangoli'!I3+CSC!I3+Jameslong!I3+Technopolis!I3+Santoshpur!I3+'Chinar Park'!I3+'Lake Road'!I3+Kalikapur!I3+'Event Sales'!I3+'Sector 1'!I3 -> 528450.61 | ... N3: ='Ideal Plaza'!M3+'Salt Lake JC -21'!M3+'Forum Mall'!M3+'Lake Town'!M3+'Quest Mall'!M3+'Rosedale Plaza'!M3+'Mani Square Mall'!M3+'Forum Rangoli'!M3+CSC!M3+Jameslong!M3+Technopolis!M3+Santoshpur!M3+'Chinar Park'!M3+'Lake Road'!M3+Kalikapur!M3+'Event Sales'!M3+'Sector 1'!M3 -> 429071.62
A4: Purchases Food (Less Purchase Return) | B4: Procurement | C4: ='Ideal Plaza'!B4+'Salt Lake JC -21'!B4+'Forum Mall'!B4+'Lake Town'!B4+'Quest Mall'!B4+'Rosedale Plaza'!B4+'Mani Square Mall'!B4+'Forum Rangoli'!B4+CSC!B4+Jameslong!B4+Technopolis!B4+Santoshpur!B4+'Chinar Park'!B4+'Lake Road'!B4+Kalikapur!B4+'Event Sales'!B4+'Sector 1'!B4+23882 -> 4234148 | D4: ='Ideal Plaza'!C4+'Salt Lake JC -21'!C4+'Forum Mall'!C4+'Lake Town'!C4+'Quest Mall'!C4+'Rosedale Plaza'!C4+'Mani Square Mall'!C4+'Forum Rangoli'!C4+CSC!C4+Jameslong!C4+Technopolis!C4+Santoshpur!C4+'Chinar Park'!C4+'Lake Road'!C4+Kalikapur!C4+'Event Sales'!C4+'Sector 1'!C4+121780 -> 4730248.5 | E4: ='Ideal Plaza'!D4+'Salt Lake JC -21'!D4+'Forum Mall'!D4+'Lake Town'!D4+'Quest Mall'!D4+'Rosedale Plaza'!D4+'Mani Square Mall'!D4+'Forum Rangoli'!D4+CSC!D4+Jameslong!D4+Technopolis!D4+Santoshpur!D4+'Chinar Park'!D4+'Lake Road'!D4+Kalikapur!D4+'Event Sales'!D4+'Sector 1'!D4+19791 -> 4509359 | F4: ='Ideal Plaza'!E4+'Salt Lake JC -21'!E4+'Forum Mall'!E4+'Lake Town'!E4+'Quest Mall'!E4+'Rosedale Plaza'!E4+'Mani Square Mall'!E4+'Forum Rangoli'!E4+CSC!E4+Jameslong!E4+Technopolis!E4+Santoshpur!E4+'Chinar Park'!E4+'Lake Road'!E4+Kalikapur!E4+'Event Sales'!E4+'Sector 1'!E4+173336 -> 5001231.9 | G4: ='Ideal Plaza'!F4+'Salt Lake JC -21'!F4+'Forum Mall'!F4+'Lake Town'!F4+'Quest Mall'!F4+'Rosedale Plaza'!F4+'Mani Square Mall'!F4+'Forum Rangoli'!F4+CSC!F4+Jameslong!F4+Technopolis!F4+Santoshpur!F4+'Chinar Park'!F4+'Lake Road'!F4+Kalikapur!F4+'Event Sales'!F4+'Sector 1'!F4+46932 -> 4933701.7 | H4: ='Ideal Plaza'!G4+'Salt Lake JC -21'!G4+'Forum Mall'!G4+'Lake Town'!G4+'Quest Mall'!G4+'Rosedale Plaza'!G4+'Mani Square Mall'!G4+'Forum Rangoli'!G4+CSC!G4+Jameslong!G4+Technopolis!G4+Santoshpur!G4+'Chinar Park'!G4+'Lake Road'!G4+Kalikapur!G4+'Event Sales'!G4+'Sector 1'!G4+398499 -> 5209917.8 | I4: ='Ideal Plaza'!H4+'Salt Lake JC -21'!H4+'Forum Mall'!H4+'Lake Town'!H4+'Quest Mall'!H4+'Rosedale Plaza'!H4+'Mani Square Mall'!H4+'Forum Rangoli'!H4+CSC!H4+Jameslong!H4+Technopolis!H4+Santoshpur!H4+'Chinar Park'!H4+'Lake Road'!H4+Kalikapur!H4+'Event Sales'!H4+'Sector 1'!H4+168591 -> 4961053.3 | J4: ='Ideal Plaza'!I4+'Salt Lake JC -21'!I4+'Forum Mall'!I4+'Lake Town'!I4+'Quest Mall'!I4+'Rosedale Plaza'!I4+'Mani Square Mall'!I4+'Forum Rangoli'!I4+CSC!I4+Jameslong!I4+Technopolis!I4+Santoshpur!I4+'Chinar Park'!I4+'Lake Road'!I4+Kalikapur!I4+'Event Sales'!I4+'Sector 1'!I4+145899 -> 4685135 | K4: ='Ideal Plaza'!J4+'Salt Lake JC -21'!J4+'Forum Mall'!J4+'Lake Town'!J4+'Quest Mall'!J4+'Rosedale Plaza'!J4+'Mani Square Mall'!J4+'Forum Rangoli'!J4+CSC!J4+Jameslong!J4+Technopolis!J4+Santoshpur!J4+'Chinar Park'!J4+'Lake Road'!J4+Kalikapur!J4+'Event Sales'!J4+'Sector 1'!J4+128494 -> 4955138.7 | L4: ='Ideal Plaza'!K4+'Salt Lake JC -21'!K4+'Forum Mall'!K4+'Lake Town'!K4+'Quest Mall'!K4+'Rosedale Plaza'!K4+'Mani Square Mall'!K4+'Forum Rangoli'!K4+CSC!K4+Jameslong!K4+Technopolis!K4+Santoshpur!K4+'Chinar Park'!K4+'Lake Road'!K4+Kalikapur!K4+'Event Sales'!K4+'Sector 1'!K4+29018 -> 4958819.2 | M4: ='Ideal Plaza'!L4+'Salt Lake JC -21'!L4+'Forum Mall'!L4+'Lake Town'!L4+'Quest Mall'!L4+'Rosedale Plaza'!L4+'Mani Square Mall'!L4+'Forum Rangoli'!L4+CSC!L4+Jameslong!L4+Technopolis!L4+Santoshpur!L4+'Chinar Park'!L4+'Lake Road'!L4+Kalikapur!L4+'Event Sales'!L4+'Sector 1'!L4+200000 -> 4678972.7 | N4: ='Ideal Plaza'!M4+'Salt Lake JC -21'!M4+'Forum Mall'!M4+'Lake Town'!M4+'Quest Mall'!M4+'Rosedale Plaza'!M4+'Mani Square Mall'!M4+'Forum Rangoli'!M4+CSC!M4+Jameslong!M4+Technopolis!M4+Santoshpur!M4+'Chinar Park'!M4+'Lake Road'!M4+Kalikapur!M4+'Event Sales'!M4+'Sector 1'!M4+188921 -> 5687723.8 | O4: =sum(C4:N4) -> 58545450
A5: Transferred Out | B5: Procurement | C5: ='Ideal Plaza'!B5+'Salt Lake JC -21'!B5+'Forum Mall'!B5+'Lake Town'!B5+'Quest Mall'!B5+'Rosedale Plaza'!B5+'Mani Square Mall'!B5+'Forum Rangoli'!B5+CSC!B5+Jameslong!B5+Technopolis!B5+Santoshpur!B5+'Chinar Park'!B5+'Lake Road'!B5+Kalikapur!B5+'Event Sales'!B5+'Sector 1'!B5 -> 9164.38 | D5: ='Ideal Plaza'!C5+'Salt Lake JC -21'!C5+'Forum Mall'!C5+'Lake Town'!C5+'Quest Mall'!C5+'Rosedale Plaza'!C5+'Mani Square Mall'!C5+'Forum Rangoli'!C5+CSC!C5+Jameslong!C5+Technopolis!C5+Santoshpur!C5+'Chinar Park'!C5+'Lake Road'!C5+Kalikapur!C5+'Event Sales'!C5+'Sector 1'!C5 -> 19210.5 | E5: ='Ideal Plaza'!D5+'Salt Lake JC -21'!D5+'Forum Mall'!D5+'Lake Town'!D5+'Quest Mall'!D5+'Rosedale Plaza'!D5+'Mani Square Mall'!D5+'Forum Rangoli'!D5+CSC!D5+Jameslong!D5+Technopolis!D5+Santoshpur!D5+'Chinar Park'!D5+'Lake Road'!D5+Kalikapur!D5+'Event Sales'!D5+'Sector 1'!D5 -> 9349.45 | F5: ='Ideal Plaza'!E5+'Salt Lake JC -21'!E5+'Forum Mall'!E5+'Lake Town'!E5+'Quest Mall'!E5+'Rosedale Plaza'!E5+'Mani Square Mall'!E5+'Forum Rangoli'!E5+CSC!E5+Jameslong!E5+Technopolis!E5+Santoshpur!E5+'Chinar Park'!E5+'Lake Road'!E5+Kalikapur!E5+'Event Sales'!E5+'Sector 1'!E5 -> 14961.98 | G5: ='Ideal Plaza'!F5+'Salt Lake JC -21'!F5+'Forum Mall'!F5+'Lake Town'!F5+'Quest Mall'!F5+'Rosedale Plaza'!F5+'Mani Square Mall'!F5+'Forum Rangoli'!F5+CSC!F5+Jameslong!F5+Technopolis!F5+Santoshpur!F5+'Chinar Park'!F5+'Lake Road'!F5+Kalikapur!F5+'Event Sales'!F5+'Sector 1'!F5 -> 5568.7 | H5: ='Ideal Plaza'!G5+'Salt Lake JC -21'!G5+'Forum Mall'!G5+'Lake Town'!G5+'Quest Mall'!G5+'Rosedale Plaza'!G5+'Mani Square Mall'!G5+'Forum Rangoli'!G5+CSC!G5+Jameslong!G5+Technopolis!G5+Santoshpur!G5+'Chinar Park'!G5+'Lake Road'!G5+Kalikapur!G5+'Event Sales'!G5+'Sector 1'!G5 -> 11717.04 | I5: ='Ideal Plaza'!H5+'Salt Lake JC -21'!H5+'Forum Mall'!H5+'Lake Town'!H5+'Quest Mall'!H5+'Rosedale Plaza'!H5+'Mani Square Mall'!H5+'Forum Rangoli'!H5+CSC!H5+Jameslong!H5+Technopolis!H5+Santoshpur!H5+'Chinar Park'!H5+'Lake Road'!H5+Kalikapur!H5+'Event Sales'!H5+'Sector 1'!H5 -> 10777.79 | J5: ='Ideal Plaza'!I5+'Salt Lake JC -21'!I5+'Forum Mall'!I5+'Lake Town'!I5+'Quest Mall'!I5+'Rosedale Plaza'!I5+'Mani Square Mall'!I5+'Forum Rangoli'!I5+CSC!I5+Jameslong!I5+Technopolis!I5+Santoshpur!I5+'Chinar Park'!I5+'Lake Road'!I5+Kalikapur!I5+'Event Sales'!I5+'Sector 1'!I5 -> 9860.07 | ... N5: ='Ideal Plaza'!M5+'Salt Lake JC -21'!M5+'Forum Mall'!M5+'Lake Town'!M5+'Quest Mall'!M5+'Rosedale Plaza'!M5+'Mani Square Mall'!M5+'Forum Rangoli'!M5+CSC!M5+Jameslong!M5+Technopolis!M5+Santoshpur!M5+'Chinar Park'!M5+'Lake Road'!M5+Kalikapur!M5+'Event Sales'!M5+'Sector 1'!M5 -> 9274.74 | O5: =sum(C5:N5) -> 163812.49
A6: Wastage & Date Expired | B6: Procurement | C6: ='Ideal Plaza'!B6+'Salt Lake JC -21'!B6+'Forum Mall'!B6+'Lake Town'!B6+'Quest Mall'!B6+'Rosedale Plaza'!B6+'Mani Square Mall'!B6+'Forum Rangoli'!B6+CSC!B6+Jameslong!B6+Technopolis!B6+Santoshpur!B6+'Chinar Park'!B6+'Lake Road'!B6+Kalikapur!B6+'Event Sales'!B6+'Sector 1'!B6 -> 169576.18 | D6: ='Ideal Plaza'!C6+'Salt Lake JC -21'!C6+'Forum Mall'!C6+'Lake Town'!C6+'Quest Mall'!C6+'Rosedale Plaza'!C6+'Mani Square Mall'!C6+'Forum Rangoli'!C6+CSC!C6+Jameslong!C6+Technopolis!C6+Santoshpur!C6+'Chinar Park'!C6+'Lake Road'!C6+Kalikapur!C6+'Event Sales'!C6+'Sector 1'!C6 -> 159755.04 | E6: ='Ideal Plaza'!D6+'Salt Lake JC -21'!D6+'Forum Mall'!D6+'Lake Town'!D6+'Quest Mall'!D6+'Rosedale Plaza'!D6+'Mani Square Mall'!D6+'Forum Rangoli'!D6+CSC!D6+Jameslong!D6+Technopolis!D6+Santoshpur!D6+'Chinar Park'!D6+'Lake Road'!D6+Kalikapur!D6+'Event Sales'!D6+'Sector 1'!D6 -> 155713.59 | F6: ='Ideal Plaza'!E6+'Salt Lake JC -21'!E6+'Forum Mall'!E6+'Lake Town'!E6+'Quest Mall'!E6+'Rosedale Plaza'!E6+'Mani Square Mall'!E6+'Forum Rangoli'!E6+CSC!E6+Jameslong!E6+Technopolis!E6+Santoshpur!E6+'Chinar Park'!E6+'Lake Road'!E6+Kalikapur!E6+'Event Sales'!E6+'Sector 1'!E6 -> 168665.32 | G6: ='Ideal Plaza'!F6+'Salt Lake JC -21'!F6+'Forum Mall'!F6+'Lake Town'!F6+'Quest Mall'!F6+'Rosedale Plaza'!F6+'Mani Square Mall'!F6+'Forum Rangoli'!F6+CSC!F6+Jameslong!F6+Technopolis!F6+Santoshpur!F6+'Chinar Park'!F6+'Lake Road'!F6+Kalikapur!F6+'Event Sales'!F6+'Sector 1'!F6 -> 154617.53 | H6: ='Ideal Plaza'!G6+'Salt Lake JC -21'!G6+'Forum Mall'!G6+'Lake Town'!G6+'Quest Mall'!G6+'Rosedale Plaza'!G6+'Mani Square Mall'!G6+'Forum Rangoli'!G6+CSC!G6+Jameslong!G6+Technopolis!G6+Santoshpur!G6+'Chinar Park'!G6+'Lake Road'!G6+Kalikapur!G6+'Event Sales'!G6+'Sector 1'!G6 -> 158807.8 | I6: ='Ideal Plaza'!H6+'Salt Lake JC -21'!H6+'Forum Mall'!H6+'Lake Town'!H6+'Quest Mall'!H6+'Rosedale Plaza'!H6+'Mani Square Mall'!H6+'Forum Rangoli'!H6+CSC!H6+Jameslong!H6+Technopolis!H6+Santoshpur!H6+'Chinar Park'!H6+'Lake Road'!H6+Kalikapur!H6+'Event Sales'!H6+'Sector 1'!H6 -> 164011.6 | J6: ='Ideal Plaza'!I6+'Salt Lake JC -21'!I6+'Forum Mall'!I6+'Lake Town'!I6+'Quest Mall'!I6+'Rosedale Plaza'!I6+'Mani Square Mall'!I6+'Forum Rangoli'!I6+CSC!I6+Jameslong!I6+Technopolis!I6+Santoshpur!I6+'Chinar Park'!I6+'Lake Road'!I6+Kalikapur!I6+'Event Sales'!I6+'Sector 1'!I6 -> 187550.4 | ... N6: ='Ideal Plaza'!M6+'Salt Lake JC -21'!M6+'Forum Mall'!M6+'Lake Town'!M6+'Quest Mall'!M6+'Rosedale Plaza'!M6+'Mani Square Mall'!M6+'Forum Rangoli'!M6+CSC!M6+Jameslong!M6+Technopolis!M6+Santoshpur!M6+'Chinar Park'!M6+'Lake Road'!M6+Kalikapur!M6+'Event Sales'!M6+'Sector 1'!M6 -> 193727.21 | O6: =sum(C6:N6) -> 2057897.8
A7: Closing Stock | B7: Procurement | C7: ='Ideal Plaza'!B7+'Salt Lake JC -21'!B7+'Forum Mall'!B7+'Lake Town'!B7+'Quest Mall'!B7+'Rosedale Plaza'!B7+'Mani Square Mall'!B7+'Forum Rangoli'!B7+CSC!B7+Jameslong!B7+Technopolis!B7+Santoshpur!B7+'Chinar Park'!B7+'Lake Road'!B7+Kalikapur!B7+'Event Sales'!B7+'Sector 1'!B7 -> 511140.61 | D7: ='Ideal Plaza'!C7+'Salt Lake JC -21'!C7+'Forum Mall'!C7+'Lake Town'!C7+'Quest Mall'!C7+'Rosedale Plaza'!C7+'Mani Square Mall'!C7+'Forum Rangoli'!C7+CSC!C7+Jameslong!C7+Technopolis!C7+Santoshpur!C7+'Chinar Park'!C7+'Lake Road'!C7+Kalikapur!C7+'Event Sales'!C7+'Sector 1'!C7 -> 503059.99 | E7: ='Ideal Plaza'!D7+'Salt Lake JC -21'!D7+'Forum Mall'!D7+'Lake Town'!D7+'Quest Mall'!D7+'Rosedale Plaza'!D7+'Mani Square Mall'!D7+'Forum Rangoli'!D7+CSC!D7+Jameslong!D7+Technopolis!D7+Santoshpur!D7+'Chinar Park'!D7+'Lake Road'!D7+Kalikapur!D7+'Event Sales'!D7+'Sector 1'!D7 -> 509757.55 | F7: ='Ideal Plaza'!E7+'Salt Lake JC -21'!E7+'Forum Mall'!E7+'Lake Town'!E7+'Quest Mall'!E7+'Rosedale Plaza'!E7+'Mani Square Mall'!E7+'Forum Rangoli'!E7+CSC!E7+Jameslong!E7+Technopolis!E7+Santoshpur!E7+'Chinar Park'!E7+'Lake Road'!E7+Kalikapur!E7+'Event Sales'!E7+'Sector 1'!E7 -> 535959.05 | G7: ='Ideal Plaza'!F7+'Salt Lake JC -21'!F7+'Forum Mall'!F7+'Lake Town'!F7+'Quest Mall'!F7+'Rosedale Plaza'!F7+'Mani Square Mall'!F7+'Forum Rangoli'!F7+CSC!F7+Jameslong!F7+Technopolis!F7+Santoshpur!F7+'Chinar Park'!F7+'Lake Road'!F7+Kalikapur!F7+'Event Sales'!F7+'Sector 1'!F7 -> 475720.3 | H7: ='Ideal Plaza'!G7+'Salt Lake JC -21'!G7+'Forum Mall'!G7+'Lake Town'!G7+'Quest Mall'!G7+'Rosedale Plaza'!G7+'Mani Square Mall'!G7+'Forum Rangoli'!G7+CSC!G7+Jameslong!G7+Technopolis!G7+Santoshpur!G7+'Chinar Park'!G7+'Lake Road'!G7+Kalikapur!G7+'Event Sales'!G7+'Sector 1'!G7 -> 580618.48 | I7: ='Ideal Plaza'!H7+'Salt Lake JC -21'!H7+'Forum Mall'!H7+'Lake Town'!H7+'Quest Mall'!H7+'Rosedale Plaza'!H7+'Mani Square Mall'!H7+'Forum Rangoli'!H7+CSC!H7+Jameslong!H7+Technopolis!H7+Santoshpur!H7+'Chinar Park'!H7+'Lake Road'!H7+Kalikapur!H7+'Event Sales'!H7+'Sector 1'!H7 -> 528450.61 | J7: ='Ideal Plaza'!I7+'Salt Lake JC -21'!I7+'Forum Mall'!I7+'Lake Town'!I7+'Quest Mall'!I7+'Rosedale Plaza'!I7+'Mani Square Mall'!I7+'Forum Rangoli'!I7+CSC!I7+Jameslong!I7+Technopolis!I7+Santoshpur!I7+'Chinar Park'!I7+'Lake Road'!I7+Kalikapur!I7+'Event Sales'!I7+'Sector 1'!I7 -> 489106.08 | ... N7: ='Ideal Plaza'!M7+'Salt Lake JC -21'!M7+'Forum Mall'!M7+'Lake Town'!M7+'Quest Mall'!M7+'Rosedale Plaza'!M7+'Mani Square Mall'!M7+'Forum Rangoli'!M7+CSC!M7+Jameslong!M7+Technopolis!M7+Santoshpur!M7+'Chinar Park'!M7+'Lake Road'!M7+Kalikapur!M7+'Event Sales'!M7+'Sector 1'!M7 -> 447327.4 | O7: =sum(C7:N7) -> 6049833.5
A9: Gross Revenue | B9: Operation | C9: ='Ideal Plaza'!B9+'Salt Lake JC -21'!B9+'Forum Mall'!B9+'Lake Town'!B9+'Quest Mall'!B9+'Rosedale Plaza'!B9+'Mani Square Mall'!B9+'Forum Rangoli'!B9+CSC!B9+Jameslong!B9+Technopolis!B9+Santoshpur!B9+'Chinar Park'!B9+'Lake Road'!B9+Kalikapur!B9+'Event Sales'!B9+'Sector 1'!B9 -> 19139166 | D9: ='Ideal Plaza'!C9+'Salt Lake JC -21'!C9+'Forum Mall'!C9+'Lake Town'!C9+'Quest Mall'!C9+'Rosedale Plaza'!C9+'Mani Square Mall'!C9+'Forum Rangoli'!C9+CSC!C9+Jameslong!C9+Technopolis!C9+Santoshpur!C9+'Chinar Park'!C9+'Lake Road'!C9+Kalikapur!C9+'Event Sales'!C9+'Sector 1'!C9 -> 21117889 | E9: ='Ideal Plaza'!D9+'Salt Lake JC -21'!D9+'Forum Mall'!D9+'Lake Town'!D9+'Quest Mall'!D9+'Rosedale Plaza'!D9+'Mani Square Mall'!D9+'Forum Rangoli'!D9+CSC!D9+Jameslong!D9+Technopolis!D9+Santoshpur!D9+'Chinar Park'!D9+'Lake Road'!D9+Kalikapur!D9+'Event Sales'!D9+'Sector 1'!D9 -> 20900296 | F9: ='Ideal Plaza'!E9+'Salt Lake JC -21'!E9+'Forum Mall'!E9+'Lake Town'!E9+'Quest Mall'!E9+'Rosedale Plaza'!E9+'Mani Square Mall'!E9+'Forum Rangoli'!E9+CSC!E9+Jameslong!E9+Technopolis!E9+Santoshpur!E9+'Chinar Park'!E9+'Lake Road'!E9+Kalikapur!E9+'Event Sales'!E9+'Sector 1'!E9 -> 21852255 | G9: ='Ideal Plaza'!F9+'Salt Lake JC -21'!F9+'Forum Mall'!F9+'Lake Town'!F9+'Quest Mall'!F9+'Rosedale Plaza'!F9+'Mani Square Mall'!F9+'Forum Rangoli'!F9+CSC!F9+Jameslong!F9+Technopolis!F9+Santoshpur!F9+'Chinar Park'!F9+'Lake Road'!F9+Kalikapur!F9+'Event Sales'!F9+'Sector 1'!F9 -> 22073888 | H9: ='Ideal Plaza'!G9+'Salt Lake JC -21'!G9+'Forum Mall'!G9+'Lake Town'!G9+'Quest Mall'!G9+'Rosedale Plaza'!G9+'Mani Square Mall'!G9+'Forum Rangoli'!G9+CSC!G9+Jameslong!G9+Technopolis!G9+Santoshpur!G9+'Chinar Park'!G9+'Lake Road'!G9+Kalikapur!G9+'Event Sales'!G9+'Sector 1'!G9 -> 22114565 | I9: ='Ideal Plaza'!H9+'Salt Lake JC -21'!H9+'Forum Mall'!H9+'Lake Town'!H9+'Quest Mall'!H9+'Rosedale Plaza'!H9+'Mani Square Mall'!H9+'Forum Rangoli'!H9+CSC!H9+Jameslong!H9+Technopolis!H9+Santoshpur!H9+'Chinar Park'!H9+'Lake Road'!H9+Kalikapur!H9+'Event Sales'!H9+'Sector 1'!H9 -> 21781995 | J9: ='Ideal Plaza'!I9+'Salt Lake JC -21'!I9+'Forum Mall'!I9+'Lake Town'!I9+'Quest Mall'!I9+'Rosedale Plaza'!I9+'Mani Square Mall'!I9+'Forum Rangoli'!I9+CSC!I9+Jameslong!I9+Technopolis!I9+Santoshpur!I9+'Chinar Park'!I9+'Lake Road'!I9+Kalikapur!I9+'Event Sales'!I9+'Sector 1'!I9 -> 20044349 | ... N9: ='Ideal Plaza'!M9+'Salt Lake JC -21'!M9+'Forum Mall'!M9+'Lake Town'!M9+'Quest Mall'!M9+'Rosedale Plaza'!M9+'Mani Square Mall'!M9+'Forum Rangoli'!M9+CSC!M9+Jameslong!M9+Technopolis!M9+Santoshpur!M9+'Chinar Park'!M9+'Lake Road'!M9+Kalikapur!M9+'Event Sales'!M9+'Sector 1'!M9 -> 23883535 | O9: =+SUM(C9:N9) -> 2.5443848e+08
A10: Catering & Fairs | B10: Operation | C10: ='Ideal Plaza'!B10+'Salt Lake JC -21'!B10+'Forum Mall'!B10+'Lake Town'!B10+'Quest Mall'!B10+'Rosedale Plaza'!B10+'Mani Square Mall'!B10+'Forum Rangoli'!B10+CSC!B10+Jameslong!B10+Technopolis!B10+Santoshpur!B10+'Chinar Park'!B10+'Lake Road'!B10+Kalikapur!B10+'Event Sales'!B10+'Sector 1'!B10 -> 0 | D10: ='Ideal Plaza'!C10+'Salt Lake JC -21'!C10+'Forum Mall'!C10+'Lake Town'!C10+'Quest Mall'!C10+'Rosedale Plaza'!C10+'Mani Square Mall'!C10+'Forum Rangoli'!C10+CSC!C10+Jameslong!C10+Technopolis!C10+Santoshpur!C10+'Chinar Park'!C10+'Lake Road'!C10+Kalikapur!C10+'Event Sales'!C10+'Sector 1'!C10 -> 0 | E10: ='Ideal Plaza'!D10+'Salt Lake JC -21'!D10+'Forum Mall'!D10+'Lake Town'!D10+'Quest Mall'!D10+'Rosedale Plaza'!D10+'Mani Square Mall'!D10+'Forum Rangoli'!D10+CSC!D10+Jameslong!D10+Technopolis!D10+Santoshpur!D10+'Chinar Park'!D10+'Lake Road'!D10+Kalikapur!D10+'Event Sales'!D10+'Sector 1'!D10 -> 0 | F10: ='Ideal Plaza'!E10+'Salt Lake JC -21'!E10+'Forum Mall'!E10+'Lake Town'!E10+'Quest Mall'!E10+'Rosedale Plaza'!E10+'Mani Square Mall'!E10+'Forum Rangoli'!E10+CSC!E10+Jameslong!E10+Technopolis!E10+Santoshpur!E10+'Chinar Park'!E10+'Lake Road'!E10+Kalikapur!E10+'Event Sales'!E10+'Sector 1'!E10 -> 0 | G10: ='Ideal Plaza'!F10+'Salt Lake JC -21'!F10+'Forum Mall'!F10+'Lake Town'!F10+'Quest Mall'!F10+'Rosedale Plaza'!F10+'Mani Square Mall'!F10+'Forum Rangoli'!F10+CSC!F10+Jameslong!F10+Technopolis!F10+Santoshpur!F10+'Chinar Park'!F10+'Lake Road'!F10+Kalikapur!F10+'Event Sales'!F10+'Sector 1'!F10 -> 0 | H10: ='Ideal Plaza'!G10+'Salt Lake JC -21'!G10+'Forum Mall'!G10+'Lake Town'!G10+'Quest Mall'!G10+'Rosedale Plaza'!G10+'Mani Square Mall'!G10+'Forum Rangoli'!G10+CSC!G10+Jameslong!G10+Technopolis!G10+Santoshpur!G10+'Chinar Park'!G10+'Lake Road'!G10+Kalikapur!G10+'Event Sales'!G10+'Sector 1'!G10 -> 0 | I10: ='Ideal Plaza'!H10+'Salt Lake JC -21'!H10+'Forum Mall'!H10+'Lake Town'!H10+'Quest Mall'!H10+'Rosedale Plaza'!H10+'Mani Square Mall'!H10+'Forum Rangoli'!H10+CSC!H10+Jameslong!H10+Technopolis!H10+Santoshpur!H10+'Chinar Park'!H10+'Lake Road'!H10+Kalikapur!H10+'Event Sales'!H10+'Sector 1'!H10 -> 0 | J10: ='Ideal Plaza'!I10+'Salt Lake JC -21'!I10+'Forum Mall'!I10+'Lake Town'!I10+'Quest Mall'!I10+'Rosedale Plaza'!I10+'Mani Square Mall'!I10+'Forum Rangoli'!I10+CSC!I10+Jameslong!I10+Technopolis!I10+Santoshpur!I10+'Chinar Park'!I10+'Lake Road'!I10+Kalikapur!I10+'Event Sales'!I10+'Sector 1'!I10 -> 0 | ... N10: ='Ideal Plaza'!M10+'Salt Lake JC -21'!M10+'Forum Mall'!M10+'Lake Town'!M10+'Quest Mall'!M10+'Rosedale Plaza'!M10+'Mani Square Mall'!M10+'Forum Rangoli'!M10+CSC!M10+Jameslong!M10+Technopolis!M10+Santoshpur!M10+'Chinar Park'!M10+'Lake Road'!M10+Kalikapur!M10+'Event Sales'!M10+'Sector 1'!M10 -> 0 | O10: =+SUM(C10:N10) -> 0
A11: Less Tax | B11: Operation | C11: ='Ideal Plaza'!B11+'Salt Lake JC -21'!B11+'Forum Mall'!B11+'Lake Town'!B11+'Quest Mall'!B11+'Rosedale Plaza'!B11+'Mani Square Mall'!B11+'Forum Rangoli'!B11+CSC!B11+Jameslong!B11+Technopolis!B11+Santoshpur!B11+'Chinar Park'!B11+'Lake Road'!B11+Kalikapur!B11+'Event Sales'!B11+'Sector 1'!B11 -> 911388.87 | D11: ='Ideal Plaza'!C11+'Salt Lake JC -21'!C11+'Forum Mall'!C11+'Lake Town'!C11+'Quest Mall'!C11+'Rosedale Plaza'!C11+'Mani Square Mall'!C11+'Forum Rangoli'!C11+CSC!C11+Jameslong!C11+Technopolis!C11+Santoshpur!C11+'Chinar Park'!C11+'Lake Road'!C11+Kalikapur!C11+'Event Sales'!C11+'Sector 1'!C11 -> 1005613.8 | E11: ='Ideal Plaza'!D11+'Salt Lake JC -21'!D11+'Forum Mall'!D11+'Lake Town'!D11+'Quest Mall'!D11+'Rosedale Plaza'!D11+'Mani Square Mall'!D11+'Forum Rangoli'!D11+CSC!D11+Jameslong!D11+Technopolis!D11+Santoshpur!D11+'Chinar Park'!D11+'Lake Road'!D11+Kalikapur!D11+'Event Sales'!D11+'Sector 1'!D11 -> 995252.17 | F11: ='Ideal Plaza'!E11+'Salt Lake JC -21'!E11+'Forum Mall'!E11+'Lake Town'!E11+'Quest Mall'!E11+'Rosedale Plaza'!E11+'Mani Square Mall'!E11+'Forum Rangoli'!E11+CSC!E11+Jameslong!E11+Technopolis!E11+Santoshpur!E11+'Chinar Park'!E11+'Lake Road'!E11+Kalikapur!E11+'Event Sales'!E11+'Sector 1'!E11 -> 1040583.6 | G11: ='Ideal Plaza'!F11+'Salt Lake JC -21'!F11+'Forum Mall'!F11+'Lake Town'!F11+'Quest Mall'!F11+'Rosedale Plaza'!F11+'Mani Square Mall'!F11+'Forum Rangoli'!F11+CSC!F11+Jameslong!F11+Technopolis!F11+Santoshpur!F11+'Chinar Park'!F11+'Lake Road'!F11+Kalikapur!F11+'Event Sales'!F11+'Sector 1'!F11 -> 1051137.5 | H11: ='Ideal Plaza'!G11+'Salt Lake JC -21'!G11+'Forum Mall'!G11+'Lake Town'!G11+'Quest Mall'!G11+'Rosedale Plaza'!G11+'Mani Square Mall'!G11+'Forum Rangoli'!G11+CSC!G11+Jameslong!G11+Technopolis!G11+Santoshpur!G11+'Chinar Park'!G11+'Lake Road'!G11+Kalikapur!G11+'Event Sales'!G11+'Sector 1'!G11 -> 1053074.5 | I11: ='Ideal Plaza'!H11+'Salt Lake JC -21'!H11+'Forum Mall'!H11+'Lake Town'!H11+'Quest Mall'!H11+'Rosedale Plaza'!H11+'Mani Square Mall'!H11+'Forum Rangoli'!H11+CSC!H11+Jameslong!H11+Technopolis!H11+Santoshpur!H11+'Chinar Park'!H11+'Lake Road'!H11+Kalikapur!H11+'Event Sales'!H11+'Sector 1'!H11 -> 1037237.9 | J11: ='Ideal Plaza'!I11+'Salt Lake JC -21'!I11+'Forum Mall'!I11+'Lake Town'!I11+'Quest Mall'!I11+'Rosedale Plaza'!I11+'Mani Square Mall'!I11+'Forum Rangoli'!I11+CSC!I11+Jameslong!I11+Technopolis!I11+Santoshpur!I11+'Chinar Park'!I11+'Lake Road'!I11+Kalikapur!I11+'Event Sales'!I11+'Sector 1'!I11 -> 954492.82 | ... N11: ='Ideal Plaza'!M11+'Salt Lake JC -21'!M11+'Forum Mall'!M11+'Lake Town'!M11+'Quest Mall'!M11+'Rosedale Plaza'!M11+'Mani Square Mall'!M11+'Forum Rangoli'!M11+CSC!M11+Jameslong!M11+Technopolis!M11+Santoshpur!M11+'Chinar Park'!M11+'Lake Road'!M11+Kalikapur!M11+'Event Sales'!M11+'Sector 1'!M11 -> 1137311.2 | O11: =+SUM(C11:N11) -> 12116118 | R11: =O9-O11 -> 2.4232237e+08
A12: Less Commission | B12: Operation | C12: ='Ideal Plaza'!B12+'Salt Lake JC -21'!B12+'Forum Mall'!B12+'Lake Town'!B12+'Quest Mall'!B12+'Rosedale Plaza'!B12+'Mani Square Mall'!B12+'Forum Rangoli'!B12+CSC!B12+Jameslong!B12+Technopolis!B12+Santoshpur!B12+'Chinar Park'!B12+'Lake Road'!B12+Kalikapur!B12+'Event Sales'!B12+'Sector 1'!B12 -> 1472425 | D12: ='Ideal Plaza'!C12+'Salt Lake JC -21'!C12+'Forum Mall'!C12+'Lake Town'!C12+'Quest Mall'!C12+'Rosedale Plaza'!C12+'Mani Square Mall'!C12+'Forum Rangoli'!C12+CSC!C12+Jameslong!C12+Technopolis!C12+Santoshpur!C12+'Chinar Park'!C12+'Lake Road'!C12+Kalikapur!C12+'Event Sales'!C12+'Sector 1'!C12 -> 1754242.9 | E12: ='Ideal Plaza'!D12+'Salt Lake JC -21'!D12+'Forum Mall'!D12+'Lake Town'!D12+'Quest Mall'!D12+'Rosedale Plaza'!D12+'Mani Square Mall'!D12+'Forum Rangoli'!D12+CSC!D12+Jameslong!D12+Technopolis!D12+Santoshpur!D12+'Chinar Park'!D12+'Lake Road'!D12+Kalikapur!D12+'Event Sales'!D12+'Sector 1'!D12 -> 1807217.1 | F12: ='Ideal Plaza'!E12+'Salt Lake JC -21'!E12+'Forum Mall'!E12+'Lake Town'!E12+'Quest Mall'!E12+'Rosedale Plaza'!E12+'Mani Square Mall'!E12+'Forum Rangoli'!E12+CSC!E12+Jameslong!E12+Technopolis!E12+Santoshpur!E12+'Chinar Park'!E12+'Lake Road'!E12+Kalikapur!E12+'Event Sales'!E12+'Sector 1'!E12 -> 1894214.6 | G12: ='Ideal Plaza'!F12+'Salt Lake JC -21'!F12+'Forum Mall'!F12+'Lake Town'!F12+'Quest Mall'!F12+'Rosedale Plaza'!F12+'Mani Square Mall'!F12+'Forum Rangoli'!F12+CSC!F12+Jameslong!F12+Technopolis!F12+Santoshpur!F12+'Chinar Park'!F12+'Lake Road'!F12+Kalikapur!F12+'Event Sales'!F12+'Sector 1'!F12 -> 1928717.8 | H12: ='Ideal Plaza'!G12+'Salt Lake JC -21'!G12+'Forum Mall'!G12+'Lake Town'!G12+'Quest Mall'!G12+'Rosedale Plaza'!G12+'Mani Square Mall'!G12+'Forum Rangoli'!G12+CSC!G12+Jameslong!G12+Technopolis!G12+Santoshpur!G12+'Chinar Park'!G12+'Lake Road'!G12+Kalikapur!G12+'Event Sales'!G12+'Sector 1'!G12 -> 1812909.7 | I12: ='Ideal Plaza'!H12+'Salt Lake JC -21'!H12+'Forum Mall'!H12+'Lake Town'!H12+'Quest Mall'!H12+'Rosedale Plaza'!H12+'Mani Square Mall'!H12+'Forum Rangoli'!H12+CSC!H12+Jameslong!H12+Technopolis!H12+Santoshpur!H12+'Chinar Park'!H12+'Lake Road'!H12+Kalikapur!H12+'Event Sales'!H12+'Sector 1'!H12 -> 1975471.1 | J12: ='Ideal Plaza'!I12+'Salt Lake JC -21'!I12+'Forum Mall'!I12+'Lake Town'!I12+'Quest Mall'!I12+'Rosedale Plaza'!I12+'Mani Square Mall'!I12+'Forum Rangoli'!I12+CSC!I12+Jameslong!I12+Technopolis!I12+Santoshpur!I12+'Chinar Park'!I12+'Lake Road'!I12+Kalikapur!I12+'Event Sales'!I12+'Sector 1'!I12 -> 1751596.1 | ... N12: ='Ideal Plaza'!M12+'Salt Lake JC -21'!M12+'Forum Mall'!M12+'Lake Town'!M12+'Quest Mall'!M12+'Rosedale Plaza'!M12+'Mani Square Mall'!M12+'Forum Rangoli'!M12+CSC!M12+Jameslong!M12+Technopolis!M12+Santoshpur!M12+'Chinar Park'!M12+'Lake Road'!M12+Kalikapur!M12+'Event Sales'!M12+'Sector 1'!M12 -> 2081410.1 | O12: =+SUM(C12:N12) -> 21504524
A13: Commission % | C13: =C12/C9 -> 0.076932556 | D13: =D12/D9 -> 0.083069045 | E13: =E12/E9 -> 0.086468497 | F13: =F12/F9 -> 0.086682796 | G13: =G12/G9 -> 0.087375537 | H13: =H12/H9 -> 0.081978087 | I13: =I12/I9 -> 0.090692847 | J13: =J12/J9 -> 0.087386031 | ... N13: =N12/N9 -> 0.087148325
A14: Net Revenues from F&B Sales | C14: =C9+C10-C11-C12 -> 16755353 | D14: =D9+D10-D11-D12 -> 18358032 | E14: =E9+E10-E11-E12 -> 18097826 | F14: =F9+F10-F11-F12 -> 18917457 | G14: =G9+G10-G11-G12 -> 19094032 | H14: =H9+H10-H11-H12 -> 19248580 | I14: =I9+I10-I11-I12 -> 18769286 | J14: =J9+J10-J11-J12 -> 17338260 | ... N14: =N9+N10-N11-N12 -> 20664814 | O14: =sum(C14:N14) -> 2.2081784e+08 | P14: =O14/$O$14 -> 1 | Q14: Average
A15: F&B Cost | B15: Operation | C15: =C3+C4-C5-C7 -> 4195819.5 | D15: =D3+D4-D5-D7 -> 4719118.6 | E15: =E3+E4-E5-E7 -> 4493312 | F15: =F3+F4-F5-F7 -> 4960068.4 | G15: =G3+G4-G5-G7 -> 4988371.7 | H15: =H3+H4-H5-H7 -> 5093302.5 | I15: =I3+I4-I5-I7 -> 5002443.4 | J15: =J3+J4-J5-J7 -> 4714619.5 | ... N15: =N3+N4-N5-N7 -> 5660193.2 | O15: =sum(C15:N15) -> 58416286 | P15: =O15/$O$14 -> 0.26454514 | Q15: =AVERAGE(C15:N15)/14 -> 347715.99
A16: Electricity | B16: Operation | C16: ='Ideal Plaza'!B15+'Salt Lake JC -21'!B15+'Forum Mall'!B15+'Lake Town'!B15+'Quest Mall'!B15+'Rosedale Plaza'!B15+'Mani Square Mall'!B15+'Forum Rangoli'!B15+CSC!B17+Jameslong!B15+Technopolis!B15+Santoshpur!B15+'Chinar Park'!B15+'Lake Road'!B15+Kalikapur!B15+'Event Sales'!B15+'Sector 1'!B15 -> 820496.63 | D16: ='Ideal Plaza'!C15+'Salt Lake JC -21'!C15+'Forum Mall'!C15+'Lake Town'!C15+'Quest Mall'!C15+'Rosedale Plaza'!C15+'Mani Square Mall'!C15+'Forum Rangoli'!C15+CSC!C15+Jameslong!C15+Technopolis!C15+Santoshpur!C15+'Chinar Park'!C15+'Lake Road'!C15+Kalikapur!C15+'Event Sales'!C15+'Sector 1'!C15 -> 921345.56 | E16: ='Ideal Plaza'!D15+'Salt Lake JC -21'!D15+'Forum Mall'!D15+'Lake Town'!D15+'Quest Mall'!D15+'Rosedale Plaza'!D15+'Mani Square Mall'!D15+'Forum Rangoli'!D15+CSC!D15+Jameslong!D15+Technopolis!D15+Santoshpur!D15+'Chinar Park'!D15+'Lake Road'!D15+Kalikapur!D15+'Event Sales'!D15+'Sector 1'!D15 -> 877451.53 | F16: ='Ideal Plaza'!E15+'Salt Lake JC -21'!E15+'Forum Mall'!E15+'Lake Town'!E15+'Quest Mall'!E15+'Rosedale Plaza'!E15+'Mani Square Mall'!E15+'Forum Rangoli'!E15+CSC!E15+Jameslong!E15+Technopolis!E15+Santoshpur!E15+'Chinar Park'!E15+'Lake Road'!E15+Kalikapur!E15+'Event Sales'!E15+'Sector 1'!E15 -> 868000.52 | G16: ='Ideal Plaza'!F15+'Salt Lake JC -21'!F15+'Forum Mall'!F15+'Lake Town'!F15+'Quest Mall'!F15+'Rosedale Plaza'!F15+'Mani Square Mall'!F15+'Forum Rangoli'!F15+CSC!F15+Jameslong!F15+Technopolis!F15+Santoshpur!F15+'Chinar Park'!F15+'Lake Road'!F15+Kalikapur!F15+'Event Sales'!F15+'Sector 1'!F15 -> 864909.84 | H16: ='Ideal Plaza'!G15+'Salt Lake JC -21'!G15+'Forum Mall'!G15+'Lake Town'!G15+'Quest Mall'!G15+'Rosedale Plaza'!G15+'Mani Square Mall'!G15+'Forum Rangoli'!G15+CSC!G15+Jameslong!G15+Technopolis!G15+Santoshpur!G15+'Chinar Park'!G15+'Lake Road'!G15+Kalikapur!G15+'Event Sales'!G15+'Sector 1'!G15 -> 896155.49 | I16: ='Ideal Plaza'!H15+'Salt Lake JC -21'!H15+'Forum Mall'!H15+'Lake Town'!H15+'Quest Mall'!H15+'Rosedale Plaza'!H15+'Mani Square Mall'!H15+'Forum Rangoli'!H15+CSC!H15+Jameslong!H15+Technopolis!H15+Santoshpur!H15+'Chinar Park'!H15+'Lake Road'!H15+Kalikapur!H15+'Event Sales'!H15+'Sector 1'!H15 -> 832346.38 | J16: ='Ideal Plaza'!I15+'Salt Lake JC -21'!I15+'Forum Mall'!I15+'Lake Town'!I15+'Quest Mall'!I15+'Rosedale Plaza'!I15+'Mani Square Mall'!I15+'Forum Rangoli'!I15+CSC!I15+Jameslong!I15+Technopolis!I15+Santoshpur!I15+'Chinar Park'!I15+'Lake Road'!I15+Kalikapur!I15+'Event Sales'!I15+'Sector 1'!I15 -> 689788.13 | K16: ='Ideal Plaza'!J15+'Salt Lake JC -21'!J15+'Forum Mall'!J15+'Lake Town'!J15+'Quest Mall'!J15+'Rosedale Plaza'!J15+'Mani Square Mall'!J15+'Forum Rangoli'!J15+CSC!J15+Jameslong!J15+Technopolis!J15+Santoshpur!J15+'Chinar Park'!J15+'Lake Road'!J15+Kalikapur!J15+'Event Sales'!J15+'Sector 1'!J15 -> 638203.51 | ... N16: ='Ideal Plaza'!M15+'Salt Lake JC -21'!M15+'Forum Mall'!M15+'Lake Town'!M15+'Quest Mall'!M15+'Rosedale Plaza'!M15+'Mani Square Mall'!M15+'Forum Rangoli'!M15+CSC!M15+Jameslong!M15+Technopolis!M15+Santoshpur!M15+'Chinar Park'!M15+'Lake Road'!M15+Kalikapur!M15+'Event Sales'!M15+'Sector 1'!M15 -> 814985.13 | O16: =sum(C16:N16) -> 9499418.1 | P16: =O16/$O$14 -> 0.043019251 | Q16: =AVERAGE(C16:N16)/14 -> 56544.155
A17: Telephone/Internet | B17: Operation | C17: ='Ideal Plaza'!B16+'Salt Lake JC -21'!B16+'Forum Mall'!B16+'Lake Town'!B16+'Quest Mall'!B16+'Rosedale Plaza'!B16+'Mani Square Mall'!B16+'Forum Rangoli'!B16+CSC!B16+Jameslong!B16+Technopolis!B16+Santoshpur!B16+'Chinar Park'!B16+'Lake Road'!B16+Kalikapur!B16+'Event Sales'!B16+'Sector 1'!B16 -> 11088.827 | D17: ='Ideal Plaza'!C16+'Salt Lake JC -21'!C16+'Forum Mall'!C16+'Lake Town'!C16+'Quest Mall'!C16+'Rosedale Plaza'!C16+'Mani Square Mall'!C16+'Forum Rangoli'!C16+CSC!C16+Jameslong!C16+Technopolis!C16+Santoshpur!C16+'Chinar Park'!C16+'Lake Road'!C16+Kalikapur!C16+'Event Sales'!C16+'Sector 1'!C16 -> 12130.827 | E17: ='Ideal Plaza'!D16+'Salt Lake JC -21'!D16+'Forum Mall'!D16+'Lake Town'!D16+'Quest Mall'!D16+'Rosedale Plaza'!D16+'Mani Square Mall'!D16+'Forum Rangoli'!D16+CSC!D16+Jameslong!D16+Technopolis!D16+Santoshpur!D16+'Chinar Park'!D16+'Lake Road'!D16+Kalikapur!D16+'Event Sales'!D16+'Sector 1'!D16 -> 13758.41 | F17: ='Ideal Plaza'!E16+'Salt Lake JC -21'!E16+'Forum Mall'!E16+'Lake Town'!E16+'Quest Mall'!E16+'Rosedale Plaza'!E16+'Mani Square Mall'!E16+'Forum Rangoli'!E16+CSC!E16+Jameslong!E16+Technopolis!E16+Santoshpur!E16+'Chinar Park'!E16+'Lake Road'!E16+Kalikapur!E16+'Event Sales'!E16+'Sector 1'!E16 -> 13883.117 | G17: ='Ideal Plaza'!F16+'Salt Lake JC -21'!F16+'Forum Mall'!F16+'Lake Town'!F16+'Quest Mall'!F16+'Rosedale Plaza'!F16+'Mani Square Mall'!F16+'Forum Rangoli'!F16+CSC!F16+Jameslong!F16+Technopolis!F16+Santoshpur!F16+'Chinar Park'!F16+'Lake Road'!F16+Kalikapur!F16+'Event Sales'!F16+'Sector 1'!F16 -> 15377.207 | H17: ='Ideal Plaza'!G16+'Salt Lake JC -21'!G16+'Forum Mall'!G16+'Lake Town'!G16+'Quest Mall'!G16+'Rosedale Plaza'!G16+'Mani Square Mall'!G16+'Forum Rangoli'!G16+CSC!G16+Jameslong!G16+Technopolis!G16+Santoshpur!G16+'Chinar Park'!G16+'Lake Road'!G16+Kalikapur!G16+'Event Sales'!G16+'Sector 1'!G16 -> 16381.387 | I17: ='Ideal Plaza'!H16+'Salt Lake JC -21'!H16+'Forum Mall'!H16+'Lake Town'!H16+'Quest Mall'!H16+'Rosedale Plaza'!H16+'Mani Square Mall'!H16+'Forum Rangoli'!H16+CSC!H16+Jameslong!H16+Technopolis!H16+Santoshpur!H16+'Chinar Park'!H16+'Lake Road'!H16+Kalikapur!H16+'Event Sales'!H16+'Sector 1'!H16 -> 15803.72 | J17: ='Ideal Plaza'!I16+'Salt Lake JC -21'!I16+'Forum Mall'!I16+'Lake Town'!I16+'Quest Mall'!I16+'Rosedale Plaza'!I16+'Mani Square Mall'!I16+'Forum Rangoli'!I16+CSC!I16+Jameslong!I16+Technopolis!I16+Santoshpur!I16+'Chinar Park'!H16+'Lake Road'!I16+Kalikapur!I16+'Event Sales'!I16+'Sector 1'!I16 -> 14614.72 | K17: ='Ideal Plaza'!J16+'Salt Lake JC -21'!J16+'Forum Mall'!J16+'Lake Town'!J16+'Quest Mall'!J16+'Rosedale Plaza'!J16+'Mani Square Mall'!J16+'Forum Rangoli'!J16+CSC!J16+Jameslong!J16+Technopolis!J16+Santoshpur!J16+'Chinar Park'!J16+'Lake Road'!J16+Kalikapur!J16+'Event Sales'!J16+'Sector 1'!J16 -> 15670.887 | L17: ='Ideal Plaza'!K16+'Salt Lake JC -21'!K16+'Forum Mall'!K16+'Lake Town'!K16+'Quest Mall'!K16+'Rosedale Plaza'!K16+'Mani Square Mall'!K16+'Forum Rangoli'!K16+CSC!K16+Jameslong!K16+Technopolis!K16+Santoshpur!K16+'Chinar Park'!K16+'Lake Road'!K16+Kalikapur!K16+'Event Sales'!K16+'Sector 1'!K16 -> 16485.553 | M17: ='Ideal Plaza'!L16+'Salt Lake JC -21'!L16+'Forum Mall'!L16+'Lake Town'!L16+'Quest Mall'!L16+'Rosedale Plaza'!L16+'Mani Square Mall'!L16+'Forum Rangoli'!L16+CSC!L16+Jameslong!L16+Technopolis!L16+Santoshpur!L16+'Chinar Park'!L16+'Lake Road'!L16+Kalikapur!L16+'Event Sales'!L16+'Sector 1'!L16 -> 17592.177 | N17: ='Ideal Plaza'!M16+'Salt Lake JC -21'!M16+'Forum Mall'!M16+'Lake Town'!M16+'Quest Mall'!M16+'Rosedale Plaza'!M16+'Mani Square Mall'!M16+'Forum Rangoli'!M16+CSC!M16+Jameslong!M16+Technopolis!M16+Santoshpur!M16+'Chinar Park'!M16+'Lake Road'!M16+Kalikapur!M16+'Event Sales'!M16+'Sector 1'!M16 -> 17592.177 | O17: =sum(C17:N17) -> 180379.01 | P17: =O17/$O$14 -> 0.0008168679 | Q17: =AVERAGE(C17:N17)/14 -> 1073.6846
A18: Gas | B18: Operation | C18: ='Ideal Plaza'!B17+'Salt Lake JC -21'!B17+'Forum Mall'!B17+'Lake Town'!B17+'Quest Mall'!B17+'Rosedale Plaza'!B17+'Mani Square Mall'!B17+'Forum Rangoli'!B17+CSC!B17+Jameslong!B17+Technopolis!B17+Santoshpur!B17+'Chinar Park'!B17+'Lake Road'!B17+Kalikapur!B17+'Event Sales'!B17+'Sector 1'!B17 -> 259532.3 | D18: ='Ideal Plaza'!C17+'Salt Lake JC -21'!C17+'Forum Mall'!C17+'Lake Town'!C17+'Quest Mall'!C17+'Rosedale Plaza'!C17+'Mani Square Mall'!C17+'Forum Rangoli'!C17+CSC!C17+Jameslong!C17+Technopolis!C17+Santoshpur!C17+'Chinar Park'!C17+'Lake Road'!C17+Kalikapur!C17+'Event Sales'!C17+'Sector 1'!C17 -> 263345.22 | E18: ='Ideal Plaza'!D17+'Salt Lake JC -21'!D17+'Forum Mall'!D17+'Lake Town'!D17+'Quest Mall'!D17+'Rosedale Plaza'!D17+'Mani Square Mall'!D17+'Forum Rangoli'!D17+CSC!D17+Jameslong!D17+Technopolis!D17+Santoshpur!D17+'Chinar Park'!D17+'Lake Road'!D17+Kalikapur!D17+'Event Sales'!D17+'Sector 1'!D17 -> 257091 | F18: ='Ideal Plaza'!E17+'Salt Lake JC -21'!E17+'Forum Mall'!E17+'Lake Town'!E17+'Quest Mall'!E17+'Rosedale Plaza'!E17+'Mani Square Mall'!E17+'Forum Rangoli'!E17+CSC!E17+Jameslong!E17+Technopolis!E17+Santoshpur!E17+'Chinar Park'!E17+'Lake Road'!E17+Kalikapur!E17+'Event Sales'!E17+'Sector 1'!E17 -> 287704 | G18: ='Ideal Plaza'!F17+'Salt Lake JC -21'!F17+'Forum Mall'!F17+'Lake Town'!F17+'Quest Mall'!F17+'Rosedale Plaza'!F17+'Mani Square Mall'!F17+'Forum Rangoli'!F17+CSC!F17+Jameslong!F17+Technopolis!F17+Santoshpur!F17+'Chinar Park'!F17+'Lake Road'!F17+Kalikapur!F17+'Event Sales'!F17+'Sector 1'!F17 -> 263086.42 | H18: ='Ideal Plaza'!G17+'Salt Lake JC -21'!G17+'Forum Mall'!G17+'Lake Town'!G17+'Quest Mall'!G17+'Rosedale Plaza'!G17+'Mani Square Mall'!G17+'Forum Rangoli'!G17+CSC!G17+Jameslong!G17+Technopolis!G17+Santoshpur!G17+'Chinar Park'!G17+'Lake Road'!G17+Kalikapur!G17+'Event Sales'!G17+'Sector 1'!G17 -> 280706 | I18: ='Ideal Plaza'!H17+'Salt Lake JC -21'!H17+'Forum Mall'!H17+'Lake Town'!H17+'Quest Mall'!H17+'Rosedale Plaza'!H17+'Mani Square Mall'!H17+'Forum Rangoli'!H17+CSC!H17+Jameslong!H17+Technopolis!H17+Santoshpur!H17+'Chinar Park'!H17+'Lake Road'!H17+Kalikapur!H17+'Event Sales'!H17+'Sector 1'!H17 -> 264253 | J18: ='Ideal Plaza'!I17+'Salt Lake JC -21'!I17+'Forum Mall'!I17+'Lake Town'!I17+'Quest Mall'!I17+'Rosedale Plaza'!I17+'Mani Square Mall'!I17+'Forum Rangoli'!I17+CSC!I17+Jameslong!I17+Technopolis!I17+Santoshpur!I17+'Chinar Park'!I17+'Lake Road'!I17+Kalikapur!I17+'Event Sales'!I17+'Sector 1'!I17 -> 273603 | ... N18: ='Ideal Plaza'!M17+'Salt Lake JC -21'!M17+'Forum Mall'!M17+'Lake Town'!M17+'Quest Mall'!M17+'Rosedale Plaza'!M17+'Mani Square Mall'!M17+'Forum Rangoli'!M17+CSC!M17+Jameslong!M17+Technopolis!M17+Santoshpur!M17+'Chinar Park'!M17+'Lake Road'!M17+Kalikapur!M17+'Event Sales'!M17+'Sector 1'!M17 -> 470434 | O18: =sum(C18:N18) -> 3508416.9 | P18: =O18/$O$14 -> 0.015888286 | Q18: =AVERAGE(C18:N18)/7 -> 41766.868
A19: Rent & Revenue Share | B19: Accounts | C19: ='Ideal Plaza'!B18+'Salt Lake JC -21'!B18+'Forum Mall'!B18+'Lake Town'!B18+'Quest Mall'!B18+'Rosedale Plaza'!B18+'Mani Square Mall'!B18+'Forum Rangoli'!B18+CSC!B18+Jameslong!B18+Technopolis!B18+Santoshpur!B18+'Chinar Park'!B18+'Lake Road'!B18+Kalikapur!B18+'Event Sales'!B18+'Sector 1'!B18 -> 1714474.5 | D19: ='Ideal Plaza'!C18+'Salt Lake JC -21'!C18+'Forum Mall'!C18+'Lake Town'!C18+'Quest Mall'!C18+'Rosedale Plaza'!C18+'Mani Square Mall'!C18+'Forum Rangoli'!C18+CSC!C18+Jameslong!C18+Technopolis!C18+Santoshpur!C18+'Chinar Park'!C18+'Lake Road'!C18+Kalikapur!C18+'Event Sales'!C18+'Sector 1'!C18 -> 1829647.9 | E19: ='Ideal Plaza'!D18+'Salt Lake JC -21'!D18+'Forum Mall'!D18+'Lake Town'!D18+'Quest Mall'!D18+'Rosedale Plaza'!D18+'Mani Square Mall'!D18+'Forum Rangoli'!D18+CSC!D18+Jameslong!D18+Technopolis!D18+Santoshpur!D18+'Chinar Park'!D18+'Lake Road'!D18+Kalikapur!D18+'Event Sales'!D18+'Sector 1'!D18 -> 1849680 | F19: ='Ideal Plaza'!E18+'Salt Lake JC -21'!E18+'Forum Mall'!E18+'Lake Town'!E18+'Quest Mall'!E18+'Rosedale Plaza'!E18+'Mani Square Mall'!E18+'Forum Rangoli'!E18+CSC!E18+Jameslong!E18+Technopolis!E18+Santoshpur!E18+'Chinar Park'!E18+'Lake Road'!E18+Kalikapur!E18+'Event Sales'!E18+'Sector 1'!E18 -> 2097753.2 | G19: ='Ideal Plaza'!F18+'Salt Lake JC -21'!F18+'Forum Mall'!F18+'Lake Town'!F18+'Quest Mall'!F18+'Rosedale Plaza'!F18+'Mani Square Mall'!F18+'Forum Rangoli'!F18+CSC!F18+Jameslong!F18+Technopolis!F18+Santoshpur!F18+'Chinar Park'!F18+'Lake Road'!F18+Kalikapur!F18+'Event Sales'!F18+'Sector 1'!F18 -> 2100565.7 | H19: ='Ideal Plaza'!G18+'Salt Lake JC -21'!G18+'Forum Mall'!G18+'Lake Town'!G18+'Quest Mall'!G18+'Rosedale Plaza'!G18+'Mani Square Mall'!G18+'Forum Rangoli'!G18+CSC!G18+Jameslong!G18+Technopolis!G18+Santoshpur!G18+'Chinar Park'!G18+'Lake Road'!G18+Kalikapur!G18+'Event Sales'!G18+'Sector 1'!G18 -> 2189167.2 | I19: ='Ideal Plaza'!H18+'Salt Lake JC -21'!H18+'Forum Mall'!H18+'Lake Town'!H18+'Quest Mall'!H18+'Rosedale Plaza'!H18+'Mani Square Mall'!H18+'Forum Rangoli'!H18+CSC!H18+Jameslong!H18+Technopolis!H18+Santoshpur!H18+'Chinar Park'!H18+'Lake Road'!H18+Kalikapur!H18+'Event Sales'!H18+'Sector 1'!H18 -> 2092027.9 | J19: ='Ideal Plaza'!I18+'Salt Lake JC -21'!I18+'Forum Mall'!I18+'Lake Town'!I18+'Quest Mall'!I18+'Rosedale Plaza'!I18+'Mani Square Mall'!I18+'Forum Rangoli'!I18+CSC!I18+Jameslong!I18+Technopolis!I18+Santoshpur!I18+'Chinar Park'!I18+'Lake Road'!I18+Kalikapur!I18+'Event Sales'!I18+'Sector 1'!I18 -> 2057423.5 | ... N19: ='Ideal Plaza'!M18+'Salt Lake JC -21'!M18+'Forum Mall'!M18+'Lake Town'!M18+'Quest Mall'!M18+'Rosedale Plaza'!M18+'Mani Square Mall'!M18+'Forum Rangoli'!M18+CSC!M18+Jameslong!M18+Technopolis!M18+Santoshpur!M18+'Chinar Park'!M18+'Lake Road'!M18+Kalikapur!M18+'Event Sales'!M18+'Sector 1'!M18 -> 2202285.9 | O19: =sum(C19:N19) -> 24397629 | P19: =O19/$O$14 -> 0.11048758 | Q19: =AVERAGE(C19:N19)/14 -> 145223.98
A20: Software | B20: Operation | C20: ='Ideal Plaza'!B19+'Salt Lake JC -21'!B19+'Forum Mall'!B19+'Lake Town'!B19+'Quest Mall'!B19+'Rosedale Plaza'!B19+'Mani Square Mall'!B19+'Forum Rangoli'!B19+CSC!B19+Jameslong!B19+Technopolis!B19+Santoshpur!B19+'Chinar Park'!B19+'Lake Road'!B19+Kalikapur!B19+'Event Sales'!B19+'Sector 1'!B19 -> 82801 | D20: ='Ideal Plaza'!C19+'Salt Lake JC -21'!C19+'Forum Mall'!C19+'Lake Town'!C19+'Quest Mall'!C19+'Rosedale Plaza'!C19+'Mani Square Mall'!C19+'Forum Rangoli'!C19+CSC!C19+Jameslong!C19+Technopolis!C19+Santoshpur!C19+'Chinar Park'!C19+'Lake Road'!C19+Kalikapur!C19+'Event Sales'!C19+'Sector 1'!C19 -> 82801.5 | E20: ='Ideal Plaza'!D19+'Salt Lake JC -21'!D19+'Forum Mall'!D19+'Lake Town'!D19+'Quest Mall'!D19+'Rosedale Plaza'!D19+'Mani Square Mall'!D19+'Forum Rangoli'!D19+CSC!D19+Jameslong!D19+Technopolis!D19+Santoshpur!D19+'Chinar Park'!D19+'Lake Road'!D19+Kalikapur!D19+'Event Sales'!D19+'Sector 1'!D19 -> 83539.25 | F20: ='Ideal Plaza'!E19+'Salt Lake JC -21'!E19+'Forum Mall'!E19+'Lake Town'!E19+'Quest Mall'!E19+'Rosedale Plaza'!E19+'Mani Square Mall'!E19+'Forum Rangoli'!E19+CSC!E19+Jameslong!E19+Technopolis!E19+Santoshpur!E19+'Chinar Park'!E19+'Lake Road'!E19+Kalikapur!E19+'Event Sales'!E19+'Sector 1'!E19 -> 83539.25 | G20: ='Ideal Plaza'!F19+'Salt Lake JC -21'!F19+'Forum Mall'!F19+'Lake Town'!F19+'Quest Mall'!F19+'Rosedale Plaza'!F19+'Mani Square Mall'!F19+'Forum Rangoli'!F19+CSC!F19+Jameslong!F19+Technopolis!F19+Santoshpur!F19+'Chinar Park'!F19+'Lake Road'!F19+Kalikapur!F19+'Event Sales'!F19+'Sector 1'!F19 -> 83539.25 | H20: ='Ideal Plaza'!G19+'Salt Lake JC -21'!G19+'Forum Mall'!G19+'Lake Town'!G19+'Quest Mall'!G19+'Rosedale Plaza'!G19+'Mani Square Mall'!G19+'Forum Rangoli'!G19+CSC!G19+Jameslong!G19+Technopolis!G19+Santoshpur!G19+'Chinar Park'!G19+'Lake Road'!G19+Kalikapur!G19+'Event Sales'!G19+'Sector 1'!G19 -> 75666.833 | I20: ='Ideal Plaza'!H19+'Salt Lake JC -21'!H19+'Forum Mall'!H19+'Lake Town'!H19+'Quest Mall'!H19+'Rosedale Plaza'!H19+'Mani Square Mall'!H19+'Forum Rangoli'!H19+CSC!H19+Jameslong!H19+Technopolis!H19+Santoshpur!H19+'Chinar Park'!H19+'Lake Road'!H19+Kalikapur!H19+'Event Sales'!H19+'Sector 1'!H19 -> 76085.083 | J20: ='Ideal Plaza'!I19+'Salt Lake JC -21'!I19+'Forum Mall'!I19+'Lake Town'!I19+'Quest Mall'!I19+'Rosedale Plaza'!I19+'Mani Square Mall'!I19+'Forum Rangoli'!I19+CSC!I19+Jameslong!I19+Technopolis!I19+Santoshpur!I19+'Chinar Park'!I19+'Lake Road'!I19+Kalikapur!I19+'Event Sales'!I19+'Sector 1'!I19 -> 76503.25 | ... N20: ='Ideal Plaza'!M19+'Salt Lake JC -21'!M19+'Forum Mall'!M19+'Lake Town'!M19+'Quest Mall'!M19+'Rosedale Plaza'!M19+'Mani Square Mall'!M19+'Forum Rangoli'!M19+CSC!M19+Jameslong!M19+Technopolis!M19+Santoshpur!M19+'Chinar Park'!M19+'Lake Road'!M19+Kalikapur!M19+'Event Sales'!M19+'Sector 1'!M19 -> 72994.75 | O20: =sum(C20:N20) -> 939962.33 | P20: =O20/$O$14 -> 0.0042567318 | Q20: =AVERAGE(C20:N20)/14 -> 5595.0139
A21: Staff Salary | B21: HR | C21: ='Ideal Plaza'!B20+'Salt Lake JC -21'!B20+'Forum Mall'!B20+'Lake Town'!B20+'Quest Mall'!B20+'Rosedale Plaza'!B20+'Mani Square Mall'!B20+'Forum Rangoli'!B20+CSC!B20+Jameslong!B20+Technopolis!B20+Santoshpur!B20+'Chinar Park'!B20+'Lake Road'!B20+Kalikapur!B20+'Event Sales'!B20+'Sector 1'!B20 -> 2891988 | D21: ='Ideal Plaza'!C20+'Salt Lake JC -21'!C20+'Forum Mall'!C20+'Lake Town'!C20+'Quest Mall'!C20+'Rosedale Plaza'!C20+'Mani Square Mall'!C20+'Forum Rangoli'!C20+CSC!C20+Jameslong!C20+Technopolis!C20+Santoshpur!C20+'Chinar Park'!C20+'Lake Road'!C20+Kalikapur!C20+'Event Sales'!C20+'Sector 1'!C20 -> 2933580 | E21: ='Ideal Plaza'!D20+'Salt Lake JC -21'!D20+'Forum Mall'!D20+'Lake Town'!D20+'Quest Mall'!D20+'Rosedale Plaza'!D20+'Mani Square Mall'!D20+'Forum Rangoli'!D20+CSC!D20+Jameslong!D20+Technopolis!D20+Santoshpur!D20+'Chinar Park'!D20+'Lake Road'!D20+Kalikapur!D20+'Event Sales'!D20+'Sector 1'!D20 -> 2926089.7 | F21: ='Ideal Plaza'!E20+'Salt Lake JC -21'!E20+'Forum Mall'!E20+'Lake Town'!E20+'Quest Mall'!E20+'Rosedale Plaza'!E20+'Mani Square Mall'!E20+'Forum Rangoli'!E20+CSC!E20+Jameslong!E20+Technopolis!E20+Santoshpur!E20+'Chinar Park'!E20+'Lake Road'!E20+Kalikapur!E20+'Event Sales'!E20+'Sector 1'!E20 -> 2954189.4 | G21: ='Ideal Plaza'!F20+'Salt Lake JC -21'!F20+'Forum Mall'!F20+'Lake Town'!F20+'Quest Mall'!F20+'Rosedale Plaza'!F20+'Mani Square Mall'!F20+'Forum Rangoli'!F20+CSC!F20+Jameslong!F20+Technopolis!F20+Santoshpur!F20+'Chinar Park'!F20+'Lake Road'!F20+Kalikapur!F20+'Event Sales'!F20+'Sector 1'!F20 -> 3050210.3 | H21: ='Ideal Plaza'!G20+'Salt Lake JC -21'!G20+'Forum Mall'!G20+'Lake Town'!G20+'Quest Mall'!G20+'Rosedale Plaza'!G20+'Mani Square Mall'!G20+'Forum Rangoli'!G20+CSC!G20+Jameslong!G20+Technopolis!G20+Santoshpur!G20+'Chinar Park'!G20+'Lake Road'!G20+Kalikapur!G20+'Event Sales'!G20+'Sector 1'!G20 -> 3055416.8 | I21: ='Ideal Plaza'!H20+'Salt Lake JC -21'!H20+'Forum Mall'!H20+'Lake Town'!H20+'Quest Mall'!H20+'Rosedale Plaza'!H20+'Mani Square Mall'!H20+'Forum Rangoli'!H20+CSC!H20+Jameslong!H20+Technopolis!H20+Santoshpur!H20+'Chinar Park'!H20+'Lake Road'!H20+Kalikapur!H20+'Event Sales'!H20+'Sector 1'!H20 -> 2923769.1 | J21: ='Ideal Plaza'!I20+'Salt Lake JC -21'!I20+'Forum Mall'!I20+'Lake Town'!I20+'Quest Mall'!I20+'Rosedale Plaza'!I20+'Mani Square Mall'!I20+'Forum Rangoli'!I20+CSC!I20+Jameslong!I20+Technopolis!I20+Santoshpur!I20+'Chinar Park'!I20+'Lake Road'!I20+Kalikapur!I20+'Event Sales'!I20+'Sector 1'!I20 -> 3025177.2 | ... N21: ='Ideal Plaza'!M20+'Salt Lake JC -21'!M20+'Forum Mall'!M20+'Lake Town'!M20+'Quest Mall'!M20+'Rosedale Plaza'!M20+'Mani Square Mall'!M20+'Forum Rangoli'!M20+CSC!M20+Jameslong!M20+Technopolis!M20+Santoshpur!M20+'Chinar Park'!M20+'Lake Road'!M20+Kalikapur!M20+'Event Sales'!M20+'Sector 1'!M20 -> 3081995.2 | O21: =sum(C21:N21) -> 36004883 | P21: =O21/$O$14 -> 0.16305242 | Q21: =AVERAGE(C21:N21)/14 -> 214314.78
A22: AMC | B22: Operation | C22: ='Ideal Plaza'!B21+'Salt Lake JC -21'!B21+'Forum Mall'!B21+'Lake Town'!B21+'Quest Mall'!B21+'Rosedale Plaza'!B21+'Mani Square Mall'!B21+'Forum Rangoli'!B21+CSC!B21+Jameslong!B21+Technopolis!B21+Santoshpur!B21+'Chinar Park'!B21+'Lake Road'!B21+Kalikapur!B21+'Event Sales'!B21+'Sector 1'!B21 -> 116012.42 | D22: ='Ideal Plaza'!C21+'Salt Lake JC -21'!C21+'Forum Mall'!C21+'Lake Town'!C21+'Quest Mall'!C21+'Rosedale Plaza'!C21+'Mani Square Mall'!C21+'Forum Rangoli'!C21+CSC!C21+Jameslong!C21+Technopolis!C21+Santoshpur!C21+'Chinar Park'!C21+'Lake Road'!C21+Kalikapur!C21+'Event Sales'!C21+'Sector 1'!C21 -> 130825.42 | E22: ='Ideal Plaza'!D21+'Salt Lake JC -21'!D21+'Forum Mall'!D21+'Lake Town'!D21+'Quest Mall'!D21+'Rosedale Plaza'!D21+'Mani Square Mall'!D21+'Forum Rangoli'!D21+CSC!D21+Jameslong!D21+Technopolis!D21+Santoshpur!D21+'Chinar Park'!D21+'Lake Road'!D21+Kalikapur!D21+'Event Sales'!D21+'Sector 1'!D21 -> 121291.42 | F22: ='Ideal Plaza'!E21+'Salt Lake JC -21'!E21+'Forum Mall'!E21+'Lake Town'!E21+'Quest Mall'!E21+'Rosedale Plaza'!E21+'Mani Square Mall'!E21+'Forum Rangoli'!E21+CSC!E21+Jameslong!E21+Technopolis!E21+Santoshpur!E21+'Chinar Park'!E21+'Lake Road'!E21+Kalikapur!E21+'Event Sales'!E21+'Sector 1'!E21 -> 131765.42 | G22: ='Ideal Plaza'!F21+'Salt Lake JC -21'!F21+'Forum Mall'!F21+'Lake Town'!F21+'Quest Mall'!F21+'Rosedale Plaza'!F21+'Mani Square Mall'!F21+'Forum Rangoli'!F21+CSC!F21+Jameslong!F21+Technopolis!F21+Santoshpur!F21+'Chinar Park'!F21+'Lake Road'!F21+Kalikapur!F21+'Event Sales'!F21+'Sector 1'!F21 -> 127315.42 | H22: ='Ideal Plaza'!G21+'Salt Lake JC -21'!G21+'Forum Mall'!G21+'Lake Town'!G21+'Quest Mall'!G21+'Rosedale Plaza'!G21+'Mani Square Mall'!G21+'Forum Rangoli'!G21+CSC!G21+Jameslong!G21+Technopolis!G21+Santoshpur!G21+'Chinar Park'!G21+'Lake Road'!G21+Kalikapur!G21+'Event Sales'!G21+'Sector 1'!G21 -> 132425.42 | I22: ='Ideal Plaza'!H21+'Salt Lake JC -21'!H21+'Forum Mall'!H21+'Lake Town'!H21+'Quest Mall'!H21+'Rosedale Plaza'!H21+'Mani Square Mall'!H21+'Forum Rangoli'!H21+CSC!H21+Jameslong!H21+Technopolis!H21+Santoshpur!H21+'Chinar Park'!H21+'Lake Road'!H21+Kalikapur!H21+'Event Sales'!H21+'Sector 1'!H21 -> 125035.42 | J22: ='Ideal Plaza'!I21+'Salt Lake JC -21'!I21+'Forum Mall'!I21+'Lake Town'!I21+'Quest Mall'!I21+'Rosedale Plaza'!I21+'Mani Square Mall'!I21+'Forum Rangoli'!I21+CSC!I21+Jameslong!I21+Technopolis!I21+Santoshpur!I21+'Chinar Park'!I21+'Lake Road'!I21+Kalikapur!I21+'Event Sales'!I21+'Sector 1'!I21 -> 126285.42 | ... N22: ='Ideal Plaza'!M21+'Salt Lake JC -21'!M21+'Forum Mall'!M21+'Lake Town'!M21+'Quest Mall'!M21+'Rosedale Plaza'!M21+'Mani Square Mall'!M21+'Forum Rangoli'!M21+CSC!M21+Jameslong!M21+Technopolis!M21+Santoshpur!M21+'Chinar Park'!M21+'Lake Road'!M21+Kalikapur!M21+'Event Sales'!M21+'Sector 1'!M21 -> 132352.42 | O22: =sum(C22:N22) -> 1543440 | P22: =O22/$O$14 -> 0.0069896526 | Q22: =AVERAGE(C22:N22)/14 -> 9187.1429
A23: Subscription | B23: Operation | C23: ='Ideal Plaza'!B22+'Salt Lake JC -21'!B22+'Forum Mall'!B22+'Lake Town'!B22+'Quest Mall'!B22+'Rosedale Plaza'!B22+'Mani Square Mall'!B22+'Forum Rangoli'!B22+CSC!B22+Jameslong!B22+Technopolis!B22+Santoshpur!B22+'Chinar Park'!B22+'Lake Road'!B22+Kalikapur!B22+'Event Sales'!B22+'Sector 1'!B22 -> 57927.667 | D23: ='Ideal Plaza'!C22+'Salt Lake JC -21'!C22+'Forum Mall'!C22+'Lake Town'!C22+'Quest Mall'!C22+'Rosedale Plaza'!C22+'Mani Square Mall'!C22+'Forum Rangoli'!C22+CSC!C22+Jameslong!C22+Technopolis!C22+Santoshpur!C22+'Chinar Park'!C22+'Lake Road'!C22+Kalikapur!C22+'Event Sales'!C22+'Sector 1'!C22 -> 57927.667 | E23: ='Ideal Plaza'!D22+'Salt Lake JC -21'!D22+'Forum Mall'!D22+'Lake Town'!D22+'Quest Mall'!D22+'Rosedale Plaza'!D22+'Mani Square Mall'!D22+'Forum Rangoli'!D22+CSC!D22+Jameslong!D22+Technopolis!D22+Santoshpur!D22+'Chinar Park'!D22+'Lake Road'!D22+Kalikapur!D22+'Event Sales'!D22+'Sector 1'!D22 -> 55470.667 | F23: ='Ideal Plaza'!E22+'Salt Lake JC -21'!E22+'Forum Mall'!E22+'Lake Town'!E22+'Quest Mall'!E22+'Rosedale Plaza'!E22+'Mani Square Mall'!E22+'Forum Rangoli'!E22+CSC!E22+Jameslong!E22+Technopolis!E22+Santoshpur!E22+'Chinar Park'!E22+'Lake Road'!E22+Kalikapur!E22+'Event Sales'!E22+'Sector 1'!E22 -> 57470.667 | G23: ='Ideal Plaza'!F22+'Salt Lake JC -21'!F22+'Forum Mall'!F22+'Lake Town'!F22+'Quest Mall'!F22+'Rosedale Plaza'!F22+'Mani Square Mall'!F22+'Forum Rangoli'!F22+CSC!F22+Jameslong!F22+Technopolis!F22+Santoshpur!F22+'Chinar Park'!F22+'Lake Road'!F22+Kalikapur!F22+'Event Sales'!F22+'Sector 1'!F22 -> 38470.667 | H23: ='Ideal Plaza'!G22+'Salt Lake JC -21'!G22+'Forum Mall'!G22+'Lake Town'!G22+'Quest Mall'!G22+'Rosedale Plaza'!G22+'Mani Square Mall'!G22+'Forum Rangoli'!G22+CSC!G22+Jameslong!G22+Technopolis!G22+Santoshpur!G22+'Chinar Park'!G22+'Lake Road'!G22+Kalikapur!G22+'Event Sales'!G22+'Sector 1'!G22 -> 38470.667 | I23: ='Ideal Plaza'!H22+'Salt Lake JC -21'!H22+'Forum Mall'!H22+'Lake Town'!H22+'Quest Mall'!H22+'Rosedale Plaza'!H22+'Mani Square Mall'!H22+'Forum Rangoli'!H22+CSC!H22+Jameslong!H22+Technopolis!H22+Santoshpur!H22+'Chinar Park'!H22+'Lake Road'!H22+Kalikapur!H22+'Event Sales'!H22+'Sector 1'!H22 -> 48970.667 | J23: ='Ideal Plaza'!I22+'Salt Lake JC -21'!I22+'Forum Mall'!I22+'Lake Town'!I22+'Quest Mall'!I22+'Rosedale Plaza'!I22+'Mani Square Mall'!I22+'Forum Rangoli'!I22+CSC!I22+Jameslong!I22+Technopolis!I22+Santoshpur!I22+'Chinar Park'!I22+'Lake Road'!I22+Kalikapur!I22+'Event Sales'!I22+'Sector 1'!I22 -> 48970.667 | ... N23: ='Ideal Plaza'!M22+'Salt Lake JC -21'!M22+'Forum Mall'!M22+'Lake Town'!M22+'Quest Mall'!M22+'Rosedale Plaza'!M22+'Mani Square Mall'!M22+'Forum Rangoli'!M22+CSC!M22+Jameslong!M22+Technopolis!M22+Santoshpur!M22+'Chinar Park'!M22+'Lake Road'!M22+Kalikapur!M22+'Event Sales'!M22+'Sector 1'!M22 -> 53942.387 | O23: =sum(C23:N23) -> 614477.16 | P23: =O23/$O$14 -> 0.0027827333 | Q23: =AVERAGE(C23:N23)/14 -> 3657.6021
A24: Insurance | B24: Development | C24: ='Ideal Plaza'!B23+'Salt Lake JC -21'!B23+'Forum Mall'!B23+'Lake Town'!B23+'Quest Mall'!B23+'Rosedale Plaza'!B23+'Mani Square Mall'!B23+'Forum Rangoli'!B23+CSC!B23+Jameslong!B23+Technopolis!B23+Santoshpur!B23+'Chinar Park'!B23+'Lake Road'!B23+Kalikapur!B23+'Event Sales'!B23+'Sector 1'!B23 -> 0 | D24: ='Ideal Plaza'!C23+'Salt Lake JC -21'!C23+'Forum Mall'!C23+'Lake Town'!C23+'Quest Mall'!C23+'Rosedale Plaza'!C23+'Mani Square Mall'!C23+'Forum Rangoli'!C23+CSC!C23+Jameslong!C23+Technopolis!C23+Santoshpur!C23+'Chinar Park'!C23+'Lake Road'!C23+Kalikapur!C23+'Event Sales'!C23+'Sector 1'!C23 -> 11536.813 | E24: ='Ideal Plaza'!D23+'Salt Lake JC -21'!D23+'Forum Mall'!D23+'Lake Town'!D23+'Quest Mall'!D23+'Rosedale Plaza'!D23+'Mani Square Mall'!D23+'Forum Rangoli'!D23+CSC!D23+Jameslong!D23+Technopolis!D23+Santoshpur!D23+'Chinar Park'!D23+'Lake Road'!D23+Kalikapur!D23+'Event Sales'!D23+'Sector 1'!D23 -> 11536.813 | F24: ='Ideal Plaza'!E23+'Salt Lake JC -21'!E23+'Forum Mall'!E23+'Lake Town'!E23+'Quest Mall'!E23+'Rosedale Plaza'!E23+'Mani Square Mall'!E23+'Forum Rangoli'!E23+CSC!E23+Jameslong!E23+Technopolis!E23+Santoshpur!E23+'Chinar Park'!E23+'Lake Road'!E23+Kalikapur!E23+'Event Sales'!E23+'Sector 1'!E23 -> 11536.813 | G24: ='Ideal Plaza'!F23+'Salt Lake JC -21'!F23+'Forum Mall'!F23+'Lake Town'!F23+'Quest Mall'!F23+'Rosedale Plaza'!F23+'Mani Square Mall'!F23+'Forum Rangoli'!F23+CSC!F23+Jameslong!F23+Technopolis!F23+Santoshpur!F23+'Chinar Park'!F23+'Lake Road'!F23+Kalikapur!F23+'Event Sales'!F23+'Sector 1'!F23 -> 11536.813 | H24: ='Ideal Plaza'!G23+'Salt Lake JC -21'!G23+'Forum Mall'!G23+'Lake Town'!G23+'Quest Mall'!G23+'Rosedale Plaza'!G23+'Mani Square Mall'!G23+'Forum Rangoli'!G23+CSC!G23+Jameslong!G23+Technopolis!G23+Santoshpur!G23+'Chinar Park'!G23+'Lake Road'!G23+Kalikapur!G23+'Event Sales'!G23+'Sector 1'!G23 -> 11536.813 | I24: ='Ideal Plaza'!H23+'Salt Lake JC -21'!H23+'Forum Mall'!H23+'Lake Town'!H23+'Quest Mall'!H23+'Rosedale Plaza'!H23+'Mani Square Mall'!H23+'Forum Rangoli'!H23+CSC!H23+Jameslong!H23+Technopolis!H23+Santoshpur!H23+'Chinar Park'!H23+'Lake Road'!H23+Kalikapur!H23+'Event Sales'!H23+'Sector 1'!H23 -> 11536.813 | J24: ='Ideal Plaza'!I23+'Salt Lake JC -21'!I23+'Forum Mall'!I23+'Lake Town'!I23+'Quest Mall'!I23+'Rosedale Plaza'!I23+'Mani Square Mall'!I23+'Forum Rangoli'!I23+CSC!I23+Jameslong!I23+Technopolis!I23+Santoshpur!I23+'Chinar Park'!I23+'Lake Road'!I23+Kalikapur!I23+'Event Sales'!I23+'Sector 1'!I23 -> 11536.813 | ... N24: ='Ideal Plaza'!M23+'Salt Lake JC -21'!M23+'Forum Mall'!M23+'Lake Town'!M23+'Quest Mall'!M23+'Rosedale Plaza'!M23+'Mani Square Mall'!M23+'Forum Rangoli'!M23+CSC!M23+Jameslong!M23+Technopolis!M23+Santoshpur!M23+'Chinar Park'!M23+'Lake Road'!M23+Kalikapur!M23+'Event Sales'!M23+'Sector 1'!M23 -> 11536.813 | O24: =sum(C24:N24) -> 126904.95 | P24: =O24/$O$14 -> 0.00057470423 | Q24: =AVERAGE(C24:N24)/14 -> 755.38659
A25: Repairs & Maintenance | B25: Operation | C25: ='Ideal Plaza'!B24+'Salt Lake JC -21'!B24+'Forum Mall'!B24+'Lake Town'!B24+'Quest Mall'!B24+'Rosedale Plaza'!B24+'Mani Square Mall'!B24+'Forum Rangoli'!B24+CSC!B24+Jameslong!B24+Technopolis!B24+Santoshpur!B24+'Chinar Park'!B24+'Lake Road'!B24+Kalikapur!B24+'Event Sales'!B24+'Sector 1'!B24 -> 11261 | D25: ='Ideal Plaza'!C24+'Salt Lake JC -21'!C24+'Forum Mall'!C24+'Lake Town'!C24+'Quest Mall'!C24+'Rosedale Plaza'!C24+'Mani Square Mall'!C24+'Forum Rangoli'!C24+CSC!C24+Jameslong!C24+Technopolis!C24+Santoshpur!C24+'Chinar Park'!C24+'Lake Road'!C24+Kalikapur!C24+'Event Sales'!C24+'Sector 1'!C24 -> 46220 | E25: ='Ideal Plaza'!D24+'Salt Lake JC -21'!D24+'Forum Mall'!D24+'Lake Town'!D24+'Quest Mall'!D24+'Rosedale Plaza'!D24+'Mani Square Mall'!D24+'Forum Rangoli'!D24+CSC!D24+Jameslong!D24+Technopolis!D24+Santoshpur!D24+'Chinar Park'!D24+'Lake Road'!D24+Kalikapur!D24+'Event Sales'!D24+'Sector 1'!D24 -> 77624.38 | F25: ='Ideal Plaza'!E24+'Salt Lake JC -21'!E24+'Forum Mall'!E24+'Lake Town'!E24+'Quest Mall'!E24+'Rosedale Plaza'!E24+'Mani Square Mall'!E24+'Forum Rangoli'!E24+CSC!E24+Jameslong!E24+Technopolis!E24+Santoshpur!E24+'Chinar Park'!E24+'Lake Road'!E24+Kalikapur!E24+'Event Sales'!E24+'Sector 1'!E24 -> 105499 | G25: ='Ideal Plaza'!F24+'Salt Lake JC -21'!F24+'Forum Mall'!F24+'Lake Town'!F24+'Quest Mall'!F24+'Rosedale Plaza'!F24+'Mani Square Mall'!F24+'Forum Rangoli'!F24+CSC!F24+Jameslong!F24+Technopolis!F24+Santoshpur!F24+'Chinar Park'!F24+'Lake Road'!F24+Kalikapur!F24+'Event Sales'!F24+'Sector 1'!F24 -> 102556 | H25: ='Ideal Plaza'!G24+'Salt Lake JC -21'!G24+'Forum Mall'!G24+'Lake Town'!G24+'Quest Mall'!G24+'Rosedale Plaza'!G24+'Mani Square Mall'!G24+'Forum Rangoli'!G24+CSC!G24+Jameslong!G24+Technopolis!G24+Santoshpur!G24+'Chinar Park'!G24+'Lake Road'!G24+Kalikapur!G24+'Event Sales'!G24+'Sector 1'!G24 -> 114010 | I25: ='Ideal Plaza'!H24+'Salt Lake JC -21'!H24+'Forum Mall'!H24+'Lake Town'!H24+'Quest Mall'!H24+'Rosedale Plaza'!H24+'Mani Square Mall'!H24+'Forum Rangoli'!H24+CSC!H24+Jameslong!H24+Technopolis!H24+Santoshpur!H24+'Chinar Park'!H24+'Lake Road'!H24+Kalikapur!H24+'Event Sales'!H24+'Sector 1'!H24 -> 92296 | J25: ='Ideal Plaza'!I24+'Salt Lake JC -21'!I24+'Forum Mall'!I24+'Lake Town'!I24+'Quest Mall'!I24+'Rosedale Plaza'!I24+'Mani Square Mall'!I24+'Forum Rangoli'!I24+CSC!I24+Jameslong!I24+Technopolis!I24+Santoshpur!I24+'Chinar Park'!I24+'Lake Road'!I24+Kalikapur!I24+'Event Sales'!I24+'Sector 1'!I24 -> 98069 | ... N25: ='Ideal Plaza'!M24+'Salt Lake JC -21'!M24+'Forum Mall'!M24+'Lake Town'!M24+'Quest Mall'!M24+'Rosedale Plaza'!M24+'Mani Square Mall'!M24+'Forum Rangoli'!M24+CSC!M24+Jameslong!M24+Technopolis!M24+Santoshpur!M24+'Chinar Park'!M24+'Lake Road'!M24+Kalikapur!M24+'Event Sales'!M24+'Sector 1'!M24 -> 179908 | O25: =sum(C25:N25) -> 1258615.9 | P25: =O25/$O$14 -> 0.0056997926 | Q25: =AVERAGE(C25:N25)/14 -> 7491.7613
A26: Miscellaneous Expenses | B26: Accounts | C26: ='Ideal Plaza'!B25+'Salt Lake JC -21'!B25+'Forum Mall'!B25+'Lake Town'!B25+'Quest Mall'!B25+'Rosedale Plaza'!B25+'Mani Square Mall'!B25+'Forum Rangoli'!B25+CSC!B25+Jameslong!B25+Technopolis!B25+Santoshpur!B25+'Chinar Park'!B25+'Lake Road'!B25+Kalikapur!B25+'Event Sales'!B25+'Sector 1'!B25 -> 135902.35 | D26: ='Ideal Plaza'!C25+'Salt Lake JC -21'!C25+'Forum Mall'!C25+'Lake Town'!C25+'Quest Mall'!C25+'Rosedale Plaza'!C25+'Mani Square Mall'!C25+'Forum Rangoli'!C25+CSC!C25+Jameslong!C25+Technopolis!C25+Santoshpur!C25+'Chinar Park'!C25+'Lake Road'!C25+Kalikapur!C25+'Event Sales'!C25+'Sector 1'!C25 -> 216210.09 | E26: ='Ideal Plaza'!D25+'Salt Lake JC -21'!D25+'Forum Mall'!D25+'Lake Town'!D25+'Quest Mall'!D25+'Rosedale Plaza'!D25+'Mani Square Mall'!D25+'Forum Rangoli'!D25+CSC!D25+Jameslong!D25+Technopolis!D25+Santoshpur!D25+'Chinar Park'!D25+'Lake Road'!D25+Kalikapur!D25+'Event Sales'!D25+'Sector 1'!D25 -> 165486.47 | F26: ='Ideal Plaza'!E25+'Salt Lake JC -21'!E25+'Forum Mall'!E25+'Lake Town'!E25+'Quest Mall'!E25+'Rosedale Plaza'!E25+'Mani Square Mall'!E25+'Forum Rangoli'!E25+CSC!E25+Jameslong!E25+Technopolis!E25+Santoshpur!E25+'Chinar Park'!E25+'Lake Road'!E25+Kalikapur!E25+'Event Sales'!E25+'Sector 1'!E25 -> 230564.32 | G26: ='Ideal Plaza'!F25+'Salt Lake JC -21'!F25+'Forum Mall'!F25+'Lake Town'!F25+'Quest Mall'!F25+'Rosedale Plaza'!F25+'Mani Square Mall'!F25+'Forum Rangoli'!F25+CSC!F25+Jameslong!F25+Technopolis!F25+Santoshpur!F25+'Chinar Park'!F24+'Lake Road'!F25+Kalikapur!F25+'Event Sales'!F25+'Sector 1'!F25 -> 201540.31 | H26: ='Ideal Plaza'!G25+'Salt Lake JC -21'!G25+'Forum Mall'!G25+'Lake Town'!G25+'Quest Mall'!G25+'Rosedale Plaza'!G25+'Mani Square Mall'!G25+'Forum Rangoli'!G25+CSC!G25+Jameslong!G25+Technopolis!G25+Santoshpur!G25+'Chinar Park'!G25+'Lake Road'!G25+Kalikapur!G25+'Event Sales'!G25+'Sector 1'!G25 -> 203928.02 | I26: ='Ideal Plaza'!H25+'Salt Lake JC -21'!H25+'Forum Mall'!H25+'Lake Town'!H25+'Quest Mall'!H25+'Rosedale Plaza'!H25+'Mani Square Mall'!H25+'Forum Rangoli'!H25+CSC!H25+Jameslong!H25+Technopolis!H25+Santoshpur!H25+'Chinar Park'!H25+'Lake Road'!H25+Kalikapur!H25+'Event Sales'!H25+'Sector 1'!H25 -> 212709.14 | J26: ='Ideal Plaza'!I25+'Salt Lake JC -21'!I25+'Forum Mall'!I25+'Lake Town'!I25+'Quest Mall'!I25+'Rosedale Plaza'!I25+'Mani Square Mall'!I25+'Forum Rangoli'!I25+CSC!I25+Jameslong!I25+Technopolis!I25+Santoshpur!I25+'Chinar Park'!I25+'Lake Road'!I25+Kalikapur!I25+'Event Sales'!I25+'Sector 1'!I25 -> 180612.72 | K26: ='Ideal Plaza'!J25+'Salt Lake JC -21'!J25+'Forum Mall'!J25+'Lake Town'!J25+'Quest Mall'!J25+'Rosedale Plaza'!J25+'Mani Square Mall'!J25+'Forum Rangoli'!J25+CSC!J25+Jameslong!J25+Technopolis!J25+Santoshpur!J25+'Chinar Park'!J25+'Lake Road'!J25+Kalikapur!J25+'Event Sales'!J25+'Sector 1'!J25 -> 248932.48 | L26: ='Ideal Plaza'!K25+'Salt Lake JC -21'!K25+'Forum Mall'!K25+'Lake Town'!K25+'Quest Mall'!K25+'Rosedale Plaza'!K25+'Mani Square Mall'!K25+'Forum Rangoli'!K25+CSC!K25+Jameslong!K25+Technopolis!K25+Santoshpur!K25+'Chinar Park'!K25+'Lake Road'!K25+Kalikapur!K25+'Event Sales'!K25+'Sector 1'!K25 -> 217041.3 | M26: ='Ideal Plaza'!L25+'Salt Lake JC -21'!L25+'Forum Mall'!L25+'Lake Town'!L25+'Quest Mall'!L25+'Rosedale Plaza'!L25+'Mani Square Mall'!L25+'Forum Rangoli'!L25+CSC!L25+Jameslong!L25+Technopolis!L25+Santoshpur!L25+'Chinar Park'!L25+'Lake Road'!L25+Kalikapur!L25+'Event Sales'!L25+'Sector 1'!L25 -> 200181.79 | N26: ='Ideal Plaza'!M25+'Salt Lake JC -21'!M25+'Forum Mall'!M25+'Lake Town'!M25+'Quest Mall'!M25+'Rosedale Plaza'!M25+'Mani Square Mall'!M25+'Forum Rangoli'!M25+CSC!M25+Jameslong!M25+Technopolis!M25+Santoshpur!M25+'Chinar Park'!M25+'Lake Road'!M25+Kalikapur!M25+'Event Sales'!M25+'Sector 1'!M25 -> 298730.61 | O26: =sum(C26:N26) -> 2511839.6 | P26: =O26/$O$14 -> 0.011375166 | Q26: =AVERAGE(C26:N26)/14 -> 14951.426
A27: CAM | B27: Accounts | C27: ='Ideal Plaza'!B26+'Salt Lake JC -21'!B26+'Forum Mall'!B26+'Lake Town'!B26+'Quest Mall'!B26+'Rosedale Plaza'!B26+'Mani Square Mall'!B26+'Forum Rangoli'!B26+CSC!B26+Jameslong!B26+Technopolis!B26+Santoshpur!B26+'Chinar Park'!B26+'Lake Road'!B26+Kalikapur!B26+'Event Sales'!B26+'Sector 1'!B26 -> 368505 | D27: ='Ideal Plaza'!C26+'Salt Lake JC -21'!C26+'Forum Mall'!C26+'Lake Town'!C26+'Quest Mall'!C26+'Rosedale Plaza'!C26+'Mani Square Mall'!C26+'Forum Rangoli'!C26+CSC!C26+Jameslong!C26+Technopolis!C26+Santoshpur!C26+'Chinar Park'!C26+'Lake Road'!C26+Kalikapur!C26+'Event Sales'!C26+'Sector 1'!C26 -> 368505 | E27: ='Ideal Plaza'!D26+'Salt Lake JC -21'!D26+'Forum Mall'!D26+'Lake Town'!D26+'Quest Mall'!D26+'Rosedale Plaza'!D26+'Mani Square Mall'!D26+'Forum Rangoli'!D26+CSC!D26+Jameslong!D26+Technopolis!D26+Santoshpur!D26+'Chinar Park'!D26+'Lake Road'!D26+Kalikapur!D26+'Event Sales'!D26+'Sector 1'!D26 -> 370275 | F27: ='Ideal Plaza'!E26+'Salt Lake JC -21'!E26+'Forum Mall'!E26+'Lake Town'!E26+'Quest Mall'!E26+'Rosedale Plaza'!E26+'Mani Square Mall'!E26+'Forum Rangoli'!E26+CSC!E26+Jameslong!E26+Technopolis!E26+Santoshpur!E26+'Chinar Park'!E26+'Lake Road'!E26+Kalikapur!E26+'Event Sales'!E26+'Sector 1'!E26 -> 374919 | G27: ='Ideal Plaza'!F26+'Salt Lake JC -21'!F26+'Forum Mall'!F26+'Lake Town'!F26+'Quest Mall'!F26+'Rosedale Plaza'!F26+'Mani Square Mall'!F26+'Forum Rangoli'!F26+CSC!F26+Jameslong!F26+Technopolis!F26+Santoshpur!F26+'Chinar Park'!F26+'Lake Road'!F26+Kalikapur!F26+'Event Sales'!F26+'Sector 1'!F26 -> 375508 | H27: ='Ideal Plaza'!G26+'Salt Lake JC -21'!G26+'Forum Mall'!G26+'Lake Town'!G26+'Quest Mall'!G26+'Rosedale Plaza'!G26+'Mani Square Mall'!G26+'Forum Rangoli'!G26+CSC!G26+Jameslong!G26+Technopolis!G26+Santoshpur!G26+'Chinar Park'!G26+'Lake Road'!G26+Kalikapur!G26+'Event Sales'!G26+'Sector 1'!G26 -> 375326 | I27: ='Ideal Plaza'!H26+'Salt Lake JC -21'!H26+'Forum Mall'!H26+'Lake Town'!H26+'Quest Mall'!H26+'Rosedale Plaza'!H26+'Mani Square Mall'!H26+'Forum Rangoli'!H26+CSC!H26+Jameslong!H26+Technopolis!H26+Santoshpur!H26+'Chinar Park'!H26+'Lake Road'!H26+Kalikapur!H26+'Event Sales'!H26+'Sector 1'!H26 -> 379717.98 | J27: ='Ideal Plaza'!I26+'Salt Lake JC -21'!I26+'Forum Mall'!I26+'Lake Town'!I26+'Quest Mall'!I26+'Rosedale Plaza'!I26+'Mani Square Mall'!I26+'Forum Rangoli'!I26+CSC!I26+Jameslong!I26+Technopolis!I26+Santoshpur!I26+'Chinar Park'!I26+'Lake Road'!I26+Kalikapur!I26+'Event Sales'!I26+'Sector 1'!I26 -> 379758 | ... N27: ='Ideal Plaza'!M26+'Salt Lake JC -21'!M26+'Forum Mall'!M26+'Lake Town'!M26+'Quest Mall'!M26+'Rosedale Plaza'!M26+'Mani Square Mall'!M26+'Forum Rangoli'!M26+CSC!M26+Jameslong!M26+Technopolis!M26+Santoshpur!M26+'Chinar Park'!M26+'Lake Road'!M26+Kalikapur!M26+'Event Sales'!M26+'Sector 1'!M26 -> 379326 | O27: =sum(C27:N27) -> 4509984 | P27: =O27/$O$14 -> 0.020424002 | Q27: =AVERAGE(C27:N27)/14 -> 26845.143
A28: ADs Account | B28: Accounts | C28: ='Ads Account'!B12 -> 618589 | D28: ='Ads Account'!C12 -> 644882.61 | E28: ='Ads Account'!D12 -> 804890.4 | F28: ='Ads Account'!E12 -> 405466 | G28: ='Ads Account'!F12 -> 532635.83 | H28: ='Ads Account'!G12 -> 593071.02 | I28: ='Ads Account'!H12 -> 570206.14 | J28: ='Ads Account'!I12 -> 619813.96 | ... N28: ='Ads Account'!M12 -> 859544.64 | O28: =sum(C28:N28) -> 7888066 | P28: =O28/$O$14 -> 0.03572205 | Q28: =AVERAGE(C28:N28)/14 -> 46952.774
A29: HO+CK Cost | B29: Accounts | C29: ='Ideal Plaza'!B27+'Salt Lake JC -21'!B27+'Forum Mall'!B27+'Lake Town'!B27+'Quest Mall'!B27+'Rosedale Plaza'!B27+'Mani Square Mall'!B27+'Forum Rangoli'!B27+CSC!B27+Jameslong!B27+Technopolis!B27+Santoshpur!B27+'Chinar Park'!B27+'Lake Road'!B27+Kalikapur!B27+'Event Sales'!B27+'Sector 1'!B27 -> 3398453.8 | D29: ='Ideal Plaza'!C27+'Salt Lake JC -21'!C27+'Forum Mall'!C27+'Lake Town'!C27+'Quest Mall'!C27+'Rosedale Plaza'!C27+'Mani Square Mall'!C27+'Forum Rangoli'!C27+CSC!C27+Jameslong!C27+Technopolis!C27+Santoshpur!C27+'Chinar Park'!C27+'Lake Road'!C27+Kalikapur!C27+'Event Sales'!C27+'Sector 1'!C27 -> 3689032.8 | E29: ='Ideal Plaza'!D27+'Salt Lake JC -21'!D27+'Forum Mall'!D27+'Lake Town'!D27+'Quest Mall'!D27+'Rosedale Plaza'!D27+'Mani Square Mall'!D27+'Forum Rangoli'!D27+CSC!D27+Jameslong!D27+Technopolis!D27+Santoshpur!D27+'Chinar Park'!D27+'Lake Road'!D27+Kalikapur!D27+'Event Sales'!D27+'Sector 1'!D27 -> 3599598.3 | F29: ='Ideal Plaza'!E27+'Salt Lake JC -21'!E27+'Forum Mall'!E27+'Lake Town'!E27+'Quest Mall'!E27+'Rosedale Plaza'!E27+'Mani Square Mall'!E27+'Forum Rangoli'!E27+CSC!E27+Jameslong!E27+Technopolis!E27+Santoshpur!E27+'Chinar Park'!E27+'Lake Road'!E27+Kalikapur!E27+'Event Sales'!E27+'Sector 1'!E27 -> 4046350.4 | G29: ='Ideal Plaza'!F27+'Salt Lake JC -21'!F27+'Forum Mall'!F27+'Lake Town'!F27+'Quest Mall'!F27+'Rosedale Plaza'!F27+'Mani Square Mall'!F27+'Forum Rangoli'!F27+CSC!F27+Jameslong!F27+Technopolis!F27+Santoshpur!F27+'Chinar Park'!F27+'Lake Road'!F27+Kalikapur!F27+'Event Sales'!F27+'Sector 1'!F27 -> 3745587.7 | H29: ='Ideal Plaza'!G27+'Salt Lake JC -21'!G27+'Forum Mall'!G27+'Lake Town'!G27+'Quest Mall'!G27+'Rosedale Plaza'!G27+'Mani Square Mall'!G27+'Forum Rangoli'!G27+CSC!G27+Jameslong!G27+Technopolis!G27+Santoshpur!G27+'Chinar Park'!G27+'Lake Road'!G27+Kalikapur!G27+'Event Sales'!G27+'Sector 1'!G27 -> 4139909.9 | I29: ='Ideal Plaza'!H27+'Salt Lake JC -21'!H27+'Forum Mall'!H27+'Lake Town'!H27+'Quest Mall'!H27+'Rosedale Plaza'!H27+'Mani Square Mall'!H27+'Forum Rangoli'!H27+CSC!H27+Jameslong!H27+Technopolis!H27+Santoshpur!H27+'Chinar Park'!H27+'Lake Road'!H27+Kalikapur!H27+'Event Sales'!H27+'Sector 1'!H27 -> 3617032.3 | J29: ='Ideal Plaza'!I27+'Salt Lake JC -21'!I27+'Forum Mall'!I27+'Lake Town'!I27+'Quest Mall'!I27+'Rosedale Plaza'!I27+'Mani Square Mall'!I27+'Forum Rangoli'!I27+CSC!I27+Jameslong!I27+Technopolis!I27+Santoshpur!I27+'Chinar Park'!I27+'Lake Road'!I27+Kalikapur!I27+'Event Sales'!I27+'Sector 1'!I27 -> 3740668.7 | ... N29: ='Ideal Plaza'!M27+'Salt Lake JC -21'!M27+'Forum Mall'!M27+'Lake Town'!M27+'Quest Mall'!M27+'Rosedale Plaza'!M27+'Mani Square Mall'!M27+'Forum Rangoli'!M27+CSC!M27+Jameslong!M27+Technopolis!M27+Santoshpur!M27+'Chinar Park'!M27+'Lake Road'!M27+Kalikapur!M27+'Event Sales'!M27+'Sector 1'!M27 -> 3805833.6 | O29: =sum(C29:N29) -> 44338551 | P29: =O29/$O$14 -> 0.20079243 | Q29: =AVERAGE(C29:N29)/14 -> 263919.94
A30: Operating Expenses | C30: =+SUM(C15:C29) -> 14682852 | D30: =+SUM(D15:D29) -> 15927110 | E30: =+SUM(E15:E29) -> 15707095 | F30: =+SUM(F15:F29) -> 16628710 | G30: =+SUM(G15:G29) -> 16501211 | H30: =+SUM(H15:H29) -> 17215474 | I30: =+SUM(I15:I29) -> 16264233 | J30: =+SUM(J15:J29) -> 16057445 | ... N30: =+SUM(N15:N29) -> 18041655 | O30: =sum(C30:N30) -> 1.9573885e+08 | P30: =O30/$O$14 -> 0.8864268 | Q30: =AVERAGE(C30:N30) -> 16311571
A31: Store Level EBITDA | C31: =C14-C30 -> 2072500.6 | D31: =D14-D30 -> 2430922.4 | E31: =E14-E30 -> 2390730.9 | F31: =F14-F30 -> 2288747.4 | G31: =G14-G30 -> 2592821.1 | H31: =H14-H30 -> 2033106.3 | I31: =I14-I30 -> 2505053.1 | J31: =J14-J30 -> 1280815.6 | ... N31: =N14-N30 -> 2623158.9 | O31: =sum(C31:N31) -> 25078989 | P31: =O31/$O$14 -> 0.1135732 | Q31: =AVERAGE(C31:N31) -> 2089915.7
A32: EBIDTA Margin % | C32: =C31/C14 -> 0.12369185 | D32: =D31/D14 -> 0.13241737 | E32: =E31/E14 -> 0.13210045 | F32: =F31/F14 -> 0.120986 | G32: =G31/G14 -> 0.13579222 | H32: =H31/H14 -> 0.1056237 | I32: =I31/I14 -> 0.13346555 | J32: =J31/J14 -> 0.073872212 | ... N32: =N31/N14 -> 0.12693843 | P32: =AVERAGE(C32:N32) -> 0.11262789
A33: Food Cost | C33: =C15/C14 -> 0.25041666 | D33: =D15/D14 -> 0.25706015 | E33: =E15/E14 -> 0.2482791 | F33: =(F15/F14) -> 0.26219531 | G33: =(G15/G14) -> 0.26125292 | H33: =(H15/H14) -> 0.26460666 | I33: =(I15/I14) -> 0.26652284 | J33: =(J15/J14) -> 0.27191999 | K33: =(K15/K14) -> 0.26560374 | L33: =(L15/L14) -> 0.26536026 | M33: =(M15/M14) -> 0.2877126 | N33: =(N15/N14) -> 0.27390487 | P33: =AVERAGE(C33:N33) -> 0.26456959

Sheet Ideal Plaza
A1: F | B1: 45748 | C1: 45778 | D1: 45809 | E1: 45839 | F1: 45870 | G1: 45901 | H1: 45931 | I1: 45962 | J1: 45992 | K1: 46023 | L1: 46054 | M1: 46082 | N1: FY 2025-26
A2: Food Cost Calculation
A3: Opening Stock | B3: =44945.58 -> 44945.58 | C3: =B7 -> 51724 | D3: =C7 -> 37108.77 | E3: =D7 -> 41568.44 | F3: =E7 -> 47446.62 | G3: =F7 -> 52793.17 | H3: =G7 -> 45183 | I3: =H7 -> 45811 | J3: =I7 -> 47804.9 | ... M3: =L7 -> 38156.51 | N3: =+SUM(J3:L3) -> 147448.69
A4: Purchases Food (Less Purchase Return) | B4: 594373 | C4: 632127 | D4: 598614 | E4: 657733 | F4: 655137 | G4: 570053.89 | H4: 612354 | I4: 647580 | J4: =621640.68-3964.58 -> 617676.1 | K4: 631870.43 | L4: 609497 | M4: =771030.48 -> 771030.48 | N4: =sum(B4:M4) -> 7598045.9
A5: Transferred Out | B5: 469.6 | C5: 1268.71 | D5: 370.66 | E5: 940.68 | F5: 766.52 | G5: 3604 | H5: 814.74 | I5: 1207.37 | J5: 2892.98 | K5: 3581 | L5: 2440 | M5: 1907.31 | N5: =+SUM(J5:L5) -> 8913.98
A6: Wastage & Date Expired | B6: 17556 | C6: 18684.39 | D6: 17946.17 | E6: 18861.99 | F6: 17219 | G6: 18324.91 | H6: 19738.05 | I6: 28022.38 | J6: 24657 | K6: 23890 | L6: 26090 | M6: 24764.48 | N6: =+SUM(J6:L6) -> 74637
A7: Closing Stock | B7: 51724 | C7: 37108.77 | D7: 41568.44 | E7: 47446.62 | F7: 52793.17 | G7: 45183 | H7: 45811 | I7: 47804.9 | J7: 52068 | K7: 47575.79 | L7: 38156.51 | M7: 47397.02 | N7: =sum(B7:M7) -> 554637.22
A9: Gross Revenue | B9: =2548637.87*1.05+43218.97*1.05 -> 2721449.7 | C9: =2631268.94*1.05+54041.72*1.05 -> 2819576.2 | D9: =2522016.1*1.05+54999.89*1.05 -> 2705866.8 | E9: =2729685.55*1.05+63869.62*1.05 -> 2933232.9 | F9: =2582413.9*1.05+61635.2*1.05 -> 2776251.6 | G9: =2369906.82*1.05 -> 2488402.2 | H9: =2545706*1.05+63761.9*1.05 -> 2739941.3 | I9: =2461573.74*1.05+63094.22*1.05 -> 2650901.4 | J9: =2411532.51*1.05+55354.97*1.05 -> 2590231.9 | K9: =2356461.41*1.05+56374*1.05 -> 2533477.2 | L9: =2221953.22*1.05+57799.79*1.05 -> 2393740.7 | M9: =2953762.56*1.05+72309.59*1.05 -> 3177375.8 | N9: =+SUM(B9:M9) -> 32530447
A10: Catering & Fairs | B10: 0 | C10: 0 | D10: 0 | E10: 0 | F10: 0 | G10: 0 | H10: 0 | I10: 0 | J10: 0 | K10: 0 | L10: 0 | M10: 0 | N10: =+SUM(B10:M10) -> 0
A11: Less: Tax | B11: =(B9+B10)/1.05*0.05 -> 129592.84 | C11: =(C9+C10)/1.05*0.05 -> 134265.53 | D11: =(D9+D10)/1.05*0.05 -> 128850.8 | E11: =(E9+E10)/1.05*0.05 -> 139677.76 | F11: =(F9+F10)/1.05*0.05 -> 132202.45 | G11: =(G9+G10)/1.05*0.05 -> 118495.34 | H11: =(H9+H10)/1.05*0.05 -> 130473.4 | I11: =(I9+I10)/1.05*0.05 -> 126233.4 | ... M11: =(M9+M10)/1.05*0.05 -> 151303.61 | N11: =+SUM(B11:M11) -> 1549068.9
A12: Less: Commission | B12: =99165.02+427.02+17849.7+76.86+117459.26+21142.66+836.72+16899 -> 273856.24 | C12: =22458.52+124769.56+107754.48+19395.79+376.65+246.01+16.7+32239.33+5803+4234.46 -> 317294.5 | D12: =125624.92+22612.49+89532.89+16115.91+2159.08+41967.19+7554.08 -> 305566.56 | E12: =146856+26434.08+119885.8+21606.39+2125.94+1631+179.65+25239+4543 -> 348500.86 | F12: =91613.42+16490.42+142331.2+25619.92+1129.44*1.18+37197.72+6695.56 -> 321280.98 | G12: =118786.34*1.18+2568.04*1.18+103927.14*1.18-1759.7 -> 264072.49 | H12: =146933.25*1.18+85454.55*1.18+2932.62*1.18+20821.39*1.18 -> 302247.34 | I12: =145277.32*1.18+99684.31*1.18+2856.24*1.18 -> 292425.09 | J12: =(127476.88+911.08)*1.18+114582.43*1.18+1461.48*1.18 -> 288429.61 | K12: =131298.23*1.18+1734.5*1.18+102732.86*1.18 -> 278203.4 | L12: =157004+47110.75+52609.25+138.05+8479.94+24.84+1959.63*1.18+95.41*1.18 -> 267791.78 | M12: =166993.16*1.18+85169.45*1.18+4521.44*1.18+78.8*1.18+42102.25*1.18 -> 352660.82 | N12: =+SUM(B12:M12) -> 3612329.7
A13: Net Revenues from F&B Sales | B13: =B9+B10-B11-B12 -> 2318000.6 | C13: =C9+C10-C11-C12 -> 2368016.2 | D13: =D9+D10-D11-D12 -> 2271449.4 | E13: =E9+E10-E11-E12 -> 2445054.3 | F13: =F9+F10-F11-F12 -> 2322768.1 | G13: =G9+G10-G11-G12 -> 2105834.3 | H13: =H9+H10-H11-H12 -> 2307220.6 | I13: =I9+I10-I11-I12 -> 2232242.9 | ... M13: =M9+M10-M11-M12 -> 2673411.3 | N13: =sum(B13:M13) -> 27369049
A14: F&B Cost | B14: =+B3+B4-B5-B7 -> 587124.98 | C14: =+C3+C4-C5-C7 -> 645473.52 | D14: =+D3+D4-D5-D7 -> 593783.67 | E14: =+E3+E4-E5-E7 -> 650914.14 | F14: =+F3+F4-F5-F7 -> 649023.93 | G14: =+G3+G4-G5-G7 -> 574060.06 | H14: =+H3+H4-H5-H7 -> 610911.26 | I14: =+I3+I4-I5-I7 -> 644378.73 | ... M14: =+M3+M4-M5-M7 -> 759882.66 | N14: =sum(B14:M14) -> 7575330.9 | O14: =N14/$N$13 -> 0.27678459
A15: Electricity | B15: 134637 | C15: 149275 | D15: 149302 | E15: =151934 -> 151934 | F15: 152776 | G15: =141963 -> 141963 | H15: =156151 -> 156151 | I15: 131662 | J15: =106908 -> 106908 | K15: =98249 -> 98249 | L15: =96497 -> 96497 | M15: 125000 | N15: =sum(B15:M15) -> 1594354 | O15: =N15/$N$13 -> 0.058253906
A16: Telephone/Internet | B16: 1100 | C16: =1060.82+182 -> 1242.82 | D16: =1060.82+182 -> 1242.82 | E16: =2600/3 -> 866.66667 | F16: =2600/3 -> 866.66667 | G16: =2600/3+1003 -> 1869.6667 | H16: =6018/3 -> 2006 | I16: =6018/3 -> 2006 | J16: =6018/3 -> 2006 | K16: =6018/3 -> 2006 | L16: 2475 | M16: 2475 | N16: =sum(B16:M16) -> 20162.64 | O16: =N16/$N$13 -> 0.00073669495
A17: Gas | B17: 0 | C17: 0 | D17: 0 | E17: 0 | F17: 0 | G17: 0 | H17: 0 | I17: 0 | J17: 0 | K17: 0 | L17: =10107 -> 10107 | M17: =15462+2*3556 -> 22574 | N17: =sum(B17:M17) -> 32681 | O17: =N17/$N$13 -> 0.0011940861
A18: Rent & Revenue Share | B18: 177000 | C18: 177000 | D18: =177000+7500*1.18 -> 185850 | E18: =177000+7500*1.18 -> 185850 | F18: =177000+7500*1.18 -> 185850 | G18: =177000+7500*1.18 -> 185850 | H18: =177000+7500*1.18 -> 185850 | I18: =177000+7500*1.18 -> 185850 | J18: =177000+7500*1.18 -> 185850 | K18: =177000+7500*1.18 -> 185850 | ... M18: =177000+7500*1.18 -> 185850 | N18: =sum(B18:M18) -> 2212500 | O18: =N18/$N$13 -> 0.080839492
A19: Software | B19: 6770 | C19: 6770 | D19: 6770 | E19: 6770 | F19: 6770 | G19: 6770 | H19: 6770 | I19: 6770 | J19: 6770 | K19: =34000*1.18/12+4250*1.18/12 -> 3761.25 | L19: =34000*1.18/12+4250*1.18/12 -> 3761.25 | M19: =34000*1.18/12+4250*1.18/12 -> 3761.25 | N19: =sum(B19:M19) -> 72213.75 | O19: =N19/$N$13 -> 0.0026385188
A20: Staff Salary & Bonus | B20: =400358+168169/12 -> 414372.08 | C20: =389046+168169/12 -> 403060.08 | D20: =270369.22+107604.47+12274.8+168169/12 -> 404262.57 | E20: =387694.01+168169/12 -> 401708.09 | F20: =391990.49+168169/12 -> 406004.57 | G20: =376223+168169/12 -> 390237.08 | H20: =168169/12+367160.98 -> 381175.06 | I20: =168169/12+385078 -> 399092.08 | J20: =168169/12+386585 -> 400599.08 | K20: =168169/12+368580 -> 382594.08 | L20: =168169/12+396205+8344.29 -> 418563.37 | M20: =168169/12+9000+361801 -> 384815.08 | N20: =sum(B20:M20) -> 4786483.3 | O20: =N20/$N$13 -> 0.17488672
A21: AMC | B21: =1200+2360+2974+5145+69284/12+38645/12 -> 20673.083 | C21: =2478+2974+5145+69284/12+38645/12 -> 19591.083 | D21: =2478+2974+5145+69284/12+38645/12 -> 19591.083 | E21: =5145+1200+2974+2478+69284/12+38645/12 -> 20791.083 | F21: =5145+1200+2974+2478+69284/12+38645/12 -> 20791.083 | G21: =69284/12+38645/12+5145+2974+2478 -> 19591.083 | H21: =69284/12+38645/12+5145+2478+2974 -> 19591.083 | I21: =69284/12+38645/12+5145+2974+2478 -> 19591.083 | J21: =69284/12+38645/12+5452+5145 -> 19591.083 | K21: =69284/12+38645/12+5145+2974+2478 -> 19591.083 | L21: =69284/12+38645/12+1500+2974+2478+5145 -> 21091.083 | M21: =69284/12+38645/12+5145+2850+2974+2478 -> 22441.083 | N21: =sum(B21:M21) -> 242925 | O21: =N21/$N$13 -> 0.0088759022
A22: Subscription | B22: =18000/3+2124/3+9813/12+6372/12 -> 8056.75 | C22: =18000/3+2124/3+9813/12+6372/12 -> 8056.75 | D22: =18000/3+2124/3+9813/12+6372/12 -> 8056.75 | E22: =9813/12+6372/12+2124/3+18000/3 -> 8056.75 | F22: =9813/12+6372/12+2124/3+18000/3 -> 8056.75 | G22: =9813/12+6372/12+2124/3+18000/3 -> 8056.75 | H22: =9813/12+6372/12+2124/3+18000/3 -> 8056.75 | I22: =9813/12+6372/12+2124/3+18000/3 -> 8056.75 | J22: =9813/12+6372/12+2124/3+18000/3 -> 8056.75 | K22: =9813/12+6372/12+3271.32/3+18000/3 -> 8439.19 | L22: =9813/12+6372/12+3271.32/3+18000/3 -> 8439.19 | M22: =9813/12+6372/12+3271.32/3+18000/3 -> 8439.19 | N22: =sum(B22:M22) -> 97828.32 | O22: =N22/$N$13 -> 0.0035744143
A23: Insurance Premium | B23: 0 | C23: 1380.47 | D23: 1380.47 | E23: 1380.47 | F23: 1380.47 | G23: 1380.47 | H23: 1380.47 | I23: 1380.47 | J23: 1380.47 | K23: 1380.47 | L23: 1380.47 | M23: 1380.47 | N23: =sum(B23:M23) -> 15185.17 | O23: =N23/$N$13 -> 0.00055483002
A24: Repairs & Maintenance | B24: 4650 | C24: 24860 | D24: 5940 | E24: 5800 | F24: 16816 | G24: 13150 | H24: 13725 | I24: 20190 | J24: 20840 | K24: 126010 | L24: 10869 | M24: 35061 | N24: =sum(B24:M24) -> 297911 | O24: =N24/$N$13 -> 0.01088496
A25: Miscellaneous Expenses | B25: 9542.35 | C25: 74498.15 | D25: =27823 -> 27823 | E25: 59290 | F25: =24890.54 -> 24890.54 | G25: 15445.67 | H25: 10370 | I25: 26121.27 | J25: 11861 | K25: 11624.27 | L25: 15045 | M25: =23926.72 -> 23926.72 | N25: =sum(B25:M25) -> 310437.97 | O25: =N25/$N$13 -> 0.011342666
A26: CAM | B26: 12614 | C26: 12614 | D26: 12614 | E26: 11535 | F26: 12124 | G26: 11942 | H26: 12191 | I26: 12232 | J26: 11975 | K26: 11765 | L26: =11826 -> 11826 | M26: 11800 | N26: =sum(B26:M26) -> 145232 | O26: =N26/$N$13 -> 0.0053064321
A27: HO+CK Cost | B27: =HO!D25 -> 470155.31 | C27: =HO!H25 -> 475851.06 | D27: =HO!L25 -> 451783.84 | E27: =HO!P25 -> 522985.02 | F27: =HO!D44 -> 455646.65 | G27: =HO!H44 -> 452914.66 | H27: =HO!L44 -> 444624.86 | I27: =HO!P44 -> 481598.55 | J27: =HO!D63 -> 410208.66 | K27: =HO!H63 -> 416043.78 | L27: =HO!L63 -> 420938.15 | M27: =HO!P63 -> 492361.5 | N27: =sum(B27:M27) -> 5495112 | O27: =N27/$N$13 -> 0.20077833
A28: Operating Expenses | B28: =+SUM(B14:B27) -> 1846695.6 | C28: =+SUM(C14:C27) -> 1999672.9 | D28: =+SUM(D14:D27) -> 1868400.2 | E28: =+SUM(E14:E27) -> 2027881.2 | F28: =+SUM(F14:F27) -> 1940996.7 | G28: =+SUM(G14:G27) -> 1823230.4 | H28: =+SUM(H14:H27) -> 1852802.5 | I28: =+SUM(I14:I27) -> 1938928.9 | ... M28: =+SUM(M14:M27) -> 2079768 | N28: =sum(B28:M28) -> 22898357 | O28: =N28/$N$13 -> 0.83665155
A29: Store Level EBITDA | B29: =B13-B28 -> 471305.05 | C29: =C13-C28 -> 368343.22 | D29: =D13-D28 -> 403049.22 | E29: =E13-E28 -> 417173.09 | F29: =F13-F28 -> 381771.46 | G29: =G13-G28 -> 282603.88 | H29: =H13-H28 -> 454418.08 | I29: =I13-I28 -> 293313.93 | ... M29: =M13-M28 -> 593643.38 | N29: =sum(B29:M29) -> 4470691.8 | O29: =N29/$N$13 -> 0.16334845
A30: Food Cost | B30: =(B14/B13) -> 0.2532894 | C30: =(C14/C13) -> 0.27257986 | D30: =(D14/D13) -> 0.26141179 | E30: =(E14/E13) -> 0.26621664 | F30: =(F14/F13) -> 0.2794183 | G30: =(G14/G13) -> 0.27260457 | H30: =(H14/H13) -> 0.26478234 | I30: =(I14/I13) -> 0.28866874 | ... M30: =(M14/M13) -> 0.28423709
B32: =B29+B27 -> 941460.35 | C32: =C29+C27 -> 844194.28 | D32: =D29+D27 -> 854833.06 | E32: =E29+E27 -> 940158.11 | F32: =F29+F27 -> 837418.11 | G32: =G29+G27 -> 735518.54 | H32: =H29+H27 -> 899042.94 | I32: =I29+I27 -> 774912.49 | ... M32: =M29+M27 -> 1086004.9
B33: =B32/B13 -> 0.4061519 | C33: =C32/C13 -> 0.35649853 | D33: =D32/D13 -> 0.37633814 | E33: =E32/E13 -> 0.3845142 | F33: =F32/F13 -> 0.36052592 | G33: =G32/G13 -> 0.34927655 | H33: =H32/H13 -> 0.38966493 | I33: =I32/I13 -> 0.34714524 | ... M33: =M32/M13 -> 0.40622439

Sheet Salt Lake JC -21
A1: Dosa Coffee - Salt Lake JC 21 | B1: 45748 | C1: 45778 | D1: 45809 | E1: 45839 | F1: 45870 | G1: 45901 | H1: 45931 | I1: 45962 | J1: 45992 | K1: 46023 | L1: 46054 | M1: 46082 | N1: FY 2025-26
A2: Food Cost Calculation
A3: Opening Stock | B3: 28853.64 | C3: =B7 -> 27870.05 | D3: =C7 -> 30897.09 | E3: =D7 -> 25613.86 | F3: =E7 -> 34797 | G3: =F7 -> 29046 | H3: =G7 -> 34437.17 | I3: =H7 -> 35238.95 | J3: =I7 -> 30377.92 | ... M3: =L7 -> 27487.28 | N3: =+SUM(J3:L3) -> 94641.44
A4: Purchases Food (Less Purchase Return) | B4: 412929.15 | C4: 454226.11 | D4: 457480.9 | E4: 504849.47 | F4: 503759.38 | G4: 487853.37 | H4: 484824.47 | I4: 474597.35 | J4: 477515 | K4: 533474.51 | L4: 459966.98 | M4: =573365 -> 573365 | N4: =sum(B4:M4) -> 5824841.7
A5: Transferred Out | B5: 569 | C5: 1199.23 | D5: 0 | E5: 0 | F5: 437.54 | G5: 1357.9 | H5: 1300.1 | I5: 520.41 | J5: 165 | K5: 379.42 | L5: 734.8 | M5: 782.37 | N5: =+SUM(J5:L5) -> 1279.22
A6: Wastage & Date Expired | B6: 19567.36 | C6: 21686.37 | D6: 22389.7 | E6: 24346 | F6: 24160 | G6: 23754 | H6: 22285.52 | I6: 21987.71 | J6: 23991 | K6: 23450 | L6: 19167.53 | M6: 25393 | N6: =+SUM(J6:L6) -> 66608.53
A7: Closing Stock | B7: 27870.05 | C7: 30897.09 | D7: 25613.86 | E7: 34797 | F7: 29046 | G7: 34437.17 | H7: =35238.95 -> 35238.95 | I7: 30377.92 | J7: 32918 | K7: 31345.52 | L7: 27487.28 | M7: 35427.58 | N7: =sum(B7:M7) -> 375456.42
A9: Gross Revenue | B9: =2055773.56*1.05+15222.14*1.05 -> 2174545.5 | C9: =2222764.92*1.05+18363.66*1.05 -> 2353185 | D9: =2173493.93*1.05+16289.61*1.05 -> 2299272.7 | E9: =2428106.25*1.05+17673.6*1.05 -> 2568068.8 | F9: =2350844.78*1.05+18922.31*1.05 -> 2488255.4 | G9: =2333997.27*1.05 -> 2450697.1 | H9: =2253685.32*1.05+24245.55*1.05 -> 2391827.4 | I9: =2199380.1*1.05+22203.68*1.05 -> 2332663 | J9: =2179487.16*1.05+17329.25*1.05 -> 2306657.2 | K9: =2420087.75*1.05+18893.18*1.05 -> 2560930 | L9: =2125094.86*1.05+15321.13*1.05 -> 2247436.8 | M9: =2573967.17*1.05 -> 2702665.5 | N9: =+SUM(B9:M9) -> 28876205
A10: Catering & Fairs | B10: 0 | C10: 0 | D10: 0 | E10: 0 | F10: 0 | G10: 0 | H10: 0 | I10: 0 | J10: 0 | K10: 0 | L10: 0 | M10: 0 | N10: =+SUM(B10:M10) -> 0
A11: Less Tax | B11: =(B9+B10)/1.05*0.05 -> 103549.79 | C11: =(C9+C10)/1.05*0.05 -> 112056.43 | D11: =(D9+D10)/1.05*0.05 -> 109489.18 | E11: =(E9+E10)/1.05*0.05 -> 122288.99 | F11: =(F9+F10)/1.05*0.05 -> 118488.35 | G11: =(G9+G10)/1.05*0.05 -> 116699.86 | H11: =(H9+H10)/1.05*0.05 -> 113896.54 | I11: =(I9+I10)/1.05*0.05 -> 111079.19 | ... M11: =(M9+M10)/1.05*0.05 -> 128698.36 | N11: =+SUM(B11:M11) -> 1375057.4
A12: Less Commission | B12: =35080.59+526.5+6314.5+94.72+50247.26+9044.53+9150 -> 110458.1 | C12: =7597.18+42206.52+56185.98+10113.45+65.88+14144+2545.94 -> 132858.95 | D12: =37612.75+6770.29+48344.69+8702+18079.23+3254.27 -> 122763.23 | E12: =366.24+40778.46+16083.39+7406.04+56223.16+10120.2+1788.28+13363+2405 -> 148533.77 | F12: =55260.33+8053.33+44193.64+7954+1396.83+22322.89+4018.31 -> 143199.33 | G12: =44848.24*1.18+1828.72*1.18+64092.76*1.18 -> 130708.27 | H12: =56178.46*1.18+58872.03*1.18+842.5*1.18+11765.87*1.18 -> 150637.45 | I12: =52116.71*1.18+55610.67*1.18+2788.64*1.18 -> 130408.9 | J12: =(40030+780.36)*1.18+58904.98*1.18+1753.22*1.18 -> 119732.9 | K12: =44878.17*1.18+2581.98*1.18+60807*1.18 -> 127755.24 | L12: =41762.09+25279.76+30155+152.19+4550.33+27.37+1625.53*1.18+30.75*1.18 -> 103881.15 | M12: =51295.94*1.18+44390.78*1.18+2605.82*1.18+30.35*1.18+24010.66*1.18 -> 144353.59 | N12: =+SUM(B12:M12) -> 1565290.9
A13: Net Revenues from F&B Sales | B13: =B9+B10-B11-B12 -> 1960537.6 | C13: =C9+C10-C11-C12 -> 2108269.6 | D13: =D9+D10-D11-D12 -> 2067020.3 | E13: =E9+E10-E11-E12 -> 2297246.1 | F13: =F9+F10-F11-F12 -> 2226567.8 | G13: =G9+G10-G11-G12 -> 2203289 | H13: =H9+H10-H11-H12 -> 2127293.4 | I13: =I9+I10-I11-I12 -> 2091174.9 | ... M13: =M9+M10-M11-M12 -> 2429613.6 | N13: =sum(B13:M13) -> 25935856
A14: F&B Cost | B14: =+B3+B4-B5-B7 -> 413343.74 | C14: =+C3+C4-C5-C7 -> 449999.84 | D14: =+D3+D4-D5-D7 -> 462764.13 | E14: =+E3+E4-E5-E7 -> 495666.33 | F14: =+F3+F4-F5-F7 -> 509072.84 | G14: =+G3+G4-G5-G7 -> 481104.3 | H14: =+H3+H4-H5-H7 -> 482722.59 | I14: =+I3+I4-I5-I7 -> 478937.97 | ... M14: =+M3+M4-M5-M7 -> 564642.33 | N14: =sum(B14:M14) -> 5810822 | O14: =N14/$N$13 -> 0.22404589
A15: Electricity | B15: =81743 -> 81743 | C15: 85077 | D15: =79803 -> 79803 | E15: 78743 | F15: 85879 | G15: 77576 | H15: 77448 | I15: 63656 | J15: 61194 | K15: 55639 | L15: 63555 | M15: 72310 | N15: =sum(B15:M15) -> 882623 | O15: =N15/$N$13 -> 0.034030995
A16: Telephone/Internet | B16: 1357 | C16: =1357 -> 1357 | D16: =1357 -> 1357 | E16: =1357 -> 1357 | F16: 1357 | G16: 1357 | H16: 1357 | I16: 1357 | J16: 1357 | K16: 1357 | L16: 1357 | M16: =1357 -> 1357 | N16: =sum(B16:M16) -> 16284 | O16: =N16/$N$13 -> 0.00062785666
A17: Gas | N17: =sum(B17:M17) -> 0 | O17: =N17/$N$13 -> 0
A18: Rent & Revenue Share | B18: =109740+105782 -> 215522 | C18: =109740+123019 -> 232759 | D18: =109740+117992 -> 227732 | E18: =109740+144816 -> 254556 | F18: =109740+136278 -> 246018 | G18: =109740+133004 -> 242744 | H18: =109740+126106 -> 235846 | I18: =109740+120976 -> 230716 | J18: =109740+118456 -> 228196 | K18: =109740+143840 -> 253580 | L18: =109740+112739 -> 222479 | M18: =109740+159479 -> 269219 | N18: =sum(B18:M18) -> 2859367 | O18: =N18/$N$13 -> 0.11024764
A19: Software | B19: 5767 | C19: 5767 | D19: 5767 | E19: 5767 | F19: 5767 | G19: 5767 | H19: 5767 | I19: 5767 | J19: 5767 | K19: =34000*1.18/12+4250*1.18/12 -> 3761.25 | L19: =34000*1.18/12+4250*1.18/12 -> 3761.25 | M19: =34000*1.18/12+4250*1.18/12 -> 3761.25 | N19: =sum(B19:M19) -> 63186.75 | O19: =N19/$N$13 -> 0.0024362701
A20: Staff Salary & Bonus | B20: =258126+9800+16520+136352/12 -> 295808.67 | C20: =252065.16+9800+136352/12 -> 273227.83 | D20: =190896.66+64998.15+4035.15+9800+16520+136352/12 -> 297612.63 | E20: =259788.06+9800+16520+136352/12 -> 297470.73 | F20: =16520+269723.55+136352/12+9800 -> 307406.22 | G20: =296525.01+136352/12+9800+16520 -> 334207.68 | H20: =136352/12+299612.59+9800+12790 -> 333565.26 | I20: =136352/12+304902+9800+551 -> 326615.67 | J20: =136352/12+285156+9800+551 -> 306869.67 | K20: =136352/12+9800+298717 -> 319879.67 | L20: =136352/12+9800+308488 -> 329650.67 | M20: =136352/12+11000+304706 -> 327068.67 | N20: =sum(B20:M20) -> 3749383.3 | O20: =N20/$N$13 -> 0.1445637
A21: AMC | B21: =2360+2478+2950 -> 7788 | C21: =2478+2478+2950 -> 7906 | D21: =2478+1859+2950 -> 7287 | E21: =2950+2478+2478 -> 7906 | F21: =2950+2478+2478 -> 7906 | G21: =2950+2478+2478 -> 7906 | H21: =2950+2478+2478 -> 7906 | I21: =2950+2478+2478 -> 7906 | J21: =2478+2478+2950+2478 -> 10384 | K21: =2950+4500+2478+2478 -> 12406 | L21: =2478+2478+2950 -> 7906 | M21: =2950+2478+2478 -> 7906 | N21: =sum(B21:M21) -> 101113 | O21: =N21/$N$13 -> 0.0038985796
A22: Subscription | B22: =24000/3+2124/3+9813/12+6372/12 -> 10056.75 | C22: =24000/3+2124/3+9813/12+6372/12 -> 10056.75 | D22: =24000/3+2124/3+9813/12+6372/12+1000 -> 11056.75 | E22: =9813/12+6372/12+2124/3+24000/3 -> 10056.75 | F22: =9813/12+6372/12+2124/3 -> 2056.75 | G22: =9813/12+6372/12+2124/3 -> 2056.75 | H22: =9813/12+6372/12+2124/3+24000/3 -> 10056.75 | I22: =9813/12+6372/12+2124/3+24000/3 -> 10056.75 | J22: =9813/12+6372/12+2124/3+24000/3 -> 10056.75 | K22: =9813/12+6372/12+3271.32/3+24000/3 -> 10439.19 | L22: =9813/12+6372/12+3271.32/3+24000/3 -> 10439.19 | M22: =9813/12+6372/12+3271.32/3+24000/3 -> 10439.19 | N22: =sum(B22:M22) -> 106828.32 | O22: =N22/$N$13 -> 0.0041189432
A23: Insurance Premium | N23: =sum(B23:M23) -> 0 | O23: =N23/$N$13 -> 0
A24: Repairs & Maintenance | B24: 100 | C24: 0 | D24: =40120/12+200 -> 3543.3333 | E24: =40120/12+30318 -> 33661.333 | F24: =40120/12+11250 -> 14593.333 | G24: =40120/12+1150 -> 4493.3333 | H24: =40120/12 -> 3343.3333 | I24: =40120/12+20500 -> 23843.333 | J24: =40120/12+23270 -> 26613.333 | K24: =40120/12+700 -> 4043.3333 | L24: =40120/12+593 -> 3936.3333 | M24: =40120/12+12810 -> 16153.333 | N24: =sum(B24:M24) -> 134324.33 | O24: =N24/$N$13 -> 0.0051790977
A25: Miscellaneous Expenses | B25: =11736.67+5310/3 -> 13506.67 | C25: =8966.98+5310/3 -> 10736.98 | D25: =6211+5310/3 -> 7981 | E25: =24056+4500/3 -> 25556 | F25: =32705+4500/3 -> 34205 | G25: =20849.19+4500/3 -> 22349.19 | H25: 23216 | I25: 27974.32 | J25: 32933 | K25: =20500.88 -> 20500.88 | L25: 33557 | M25: 35347 | N25: =sum(B25:M25) -> 287863.04 | O25: =N25/$N$13 -> 0.011099037
A26: CAM | B26: 14160 | C26: 14160 | D26: 14160 | E26: 14160 | F26: 14160 | G26: 14160 | H26: 14160 | I26: 14160 | J26: 14160 | K26: 14160 | L26: 14160 | M26: 14160 | N26: =sum(B26:M26) -> 169920 | O26: =N26/$N$13 -> 0.0065515477
A27: HO+CK Cost | B27: =HO!D26 -> 397651.82 | C27: =HO!H26 -> 423655.19 | D27: =HO!L26 -> 411123.56 | E27: =HO!P26 -> 491369.57 | F27: =HO!D45 -> 436775.47 | G27: =HO!H45 -> 473874.84 | H27: =HO!L45 -> 409951.07 | I27: =HO!P45 -> 451163.63 | J27: =HO!D64 -> 391119.63 | K27: =HO!H64 -> 450462.22 | L27: =HO!L64 -> 426079.39 | M27: =HO!P64 -> 447461.33 | N27: =sum(B27:M27) -> 5210687.7 | O27: =N27/$N$13 -> 0.20090672
A28: Operating Expenses | B28: =+SUM(B14:B27) -> 1456804.6 | C28: =+SUM(C14:C27) -> 1514702.6 | D28: =+SUM(D14:D27) -> 1530187.4 | E28: =+SUM(E14:E27) -> 1716269.7 | F28: =+SUM(F14:F27) -> 1665196.6 | G28: =+SUM(G14:G27) -> 1667596.1 | H28: =+SUM(H14:H27) -> 1605339 | I28: =+SUM(I14:I27) -> 1642153.7 | ... M28: =+SUM(M14:M27) -> 1769825.1 | N28: =sum(B28:M28) -> 19392402 | O28: =N28/$N$13 -> 0.74770627
A29: Store Level EBITDA | B29: =B13-B28 -> 503732.95 | C29: =C13-C28 -> 593567.04 | D29: =D13-D28 -> 536832.91 | E29: =E13-E28 -> 580976.37 | F29: =F13-F28 -> 561371.15 | G29: =G13-G28 -> 535692.91 | H29: =H13-H28 -> 521954.42 | I29: =I13-I28 -> 449021.21 | ... M29: =M13-M28 -> 659788.48 | N29: =sum(B29:M29) -> 6543453.8 | O29: =N29/$N$13 -> 0.25229373
A30: Food Cost | B30: =(B14/B13) -> 0.21083184 | C30: =(C14/C13) -> 0.21344511 | D30: =(D14/D13) -> 0.22387982 | E30: =(E14/E13) -> 0.21576545 | F30: =(F14/F13) -> 0.22863568 | G30: =(G14/G13) -> 0.21835733 | H30: =(H14/H13) -> 0.22691867 | I30: =(I14/I13) -> 0.22902818 | ... M30: =(M14/M13) -> 0.23240006
B32: =B29+B27 -> 901384.77 | C32: =C29+C27 -> 1017222.2 | D32: =D29+D27 -> 947956.47 | E32: =E29+E27 -> 1072345.9 | F32: =F29+F27 -> 998146.62 | G32: =G29+G27 -> 1009567.8 | H32: =H29+H27 -> 931905.49 | I32: =I29+I27 -> 900184.84 | ... M32: =M29+M27 -> 1107249.8
B33: =B32/B13 -> 0.45976408 | C33: =C32/C13 -> 0.48249153 | D33: =D32/D13 -> 0.45861014 | E33: =E32/E13 -> 0.46679629 | F33: =F32/F13 -> 0.44828935 | G33: =G32/G13 -> 0.45820941 | H33: =H32/H13 -> 0.43807097 | I33: =I32/I13 -> 0.43046846 | ... M33: =M32/M13 -> 0.45573083

Sheet Forum Mall
A1: Dosa Coffee - Forum Mall | B1: 45748 | C1: 45778 | D1: 45809 | E1: 45839 | F1: 45870 | G1: 45901 | H1: 45931 | I1: 45962 | J1: 45992 | K1: 46023 | L1: 46054 | M1: 46082 | N1: FY 2025-26
A2: Food Cost Calculation
A3: Opening Stock | B3: 31212.63 | C3: =B7 -> 32154.48 | D3: =C7 -> 29729.9 | E3: =D7 -> 42360.03 | F3: =E7 -> 39466.8 | G3: =F7 -> 27409.41 | H3: =G7 -> 25428 | I3: =H7 -> 26072 | J3: =I7 -> 17790.41 | ... M3: =L7 -> 16996 | N3: =B3 -> 31212.63
A4: Purchases Food (Less Purchase Return) | B4: 138244 | C4: 151022 | D4: 148054 | E4: 148260 | F4: 125671 | G4: 130553 | H4: 127326.39 | I4: 113539.22 | J4: 148785 | K4: 133628 | L4: =115163-5040.78 -> 110122.22 | M4: 140671.29 | N4: =sum(B4:M4) -> 1615876.1
A5: Transferred Out | B5: 1136.97 | C5: 2006.09 | D5: 1302.59 | E5: 2571.86 | F5: 377.52 | G5: 133.48 | H5: 315 | I5: 992.33 | J5: 76 | K5: 1398 | L5: =4854.37 -> 4854.37 | M5: 855.01 | N5: =+SUM(J5:L5) -> 6328.37
A6: Wastage & Date Expired | B6: 4271.44 | C6: 3150.74 | D6: 3864 | E6: 7104.68 | F6: 3404.91 | G6: 2860 | H6: 3805.07 | I6: 3304 | J6: 3935 | K6: 4897.67 | L6: 13315 | M6: 5686 | N6: =+SUM(J6:L6) -> 22147.67
A7: Closing Stock | B7: 32154.48 | C7: 29729.9 | D7: 42360.03 | E7: 39466.8 | F7: 27409.41 | G7: 25428 | H7: 26072 | I7: 17790.41 | J7: 21846 | K7: 24890.98 | L7: 16996 | M7: 19397.33 | N7: =sum(B7:M7) -> 323541.34
A9: Gross Revenue | B9: =632245.42*1.05 -> 663857.69 | C9: =733415.89*1.05 -> 770086.68 | D9: =660849.43*1.05 -> 693891.9 | E9: =772036.5*1.05 -> 810638.32 | F9: =665954.87*1.05 -> 699252.61 | G9: =686650.07*1.05 -> 720982.57 | H9: =620318.57*1.05 -> 651334.5 | I9: =627585.92*1.05 -> 658965.22 | J9: =734697.69*1.05 -> 771432.57 | K9: =625240*1.05 -> 656502 | L9: =350349.47*1.05 -> 367866.94 | M9: =631692.74*1.05 -> 663277.38 | N9: =+SUM(B9:M9) -> 8128088.4
A10: Catering & Fairs | B10: 0 | C10: 0 | D10: 0 | E10: 0 | F10: 0 | G10: 0 | H10: 0 | I10: 0 | J10: 0 | K10: 0 | L10: 0 | M10: 0 | N10: =+SUM(B10:M10) -> 0
A11: Less Tax | B11: =(B9+B10)/1.05*0.05 -> 31612.271 | C11: =(C9+C10)/1.05*0.05 -> 36670.795 | D11: =(D9+D10)/1.05*0.05 -> 33042.471 | E11: =(E9+E10)/1.05*0.05 -> 38601.825 | F11: =(F9+F10)/1.05*0.05 -> 33297.743 | G11: =(G9+G10)/1.05*0.05 -> 34332.503 | H11: =(H9+H10)/1.05*0.05 -> 31015.929 | I11: =(I9+I10)/1.05*0.05 -> 31379.296 | ... M11: =(M9+M10)/1.05*0.05 -> 31584.637 | N11: =+SUM(B11:M11) -> 387051.83
A12: Less Commission | N12: =+SUM(B12:M12) -> 0
A13: Net Revenues from F&B Sales | B13: =B9+B10-B11-B12 -> 632245.42 | C13: =C9+C10-C11-C12 -> 733415.89 | D13: =D9+D10-D11-D12 -> 660849.43 | E13: =E9+E10-E11-E12 -> 772036.5 | F13: =F9+F10-F11-F12 -> 665954.87 | G13: =G9+G10-G11-G12 -> 686650.07 | H13: =H9+H10-H11-H12 -> 620318.57 | I13: =I9+I10-I11-I12 -> 627585.92 | ... M13: =M9+M10-M11-M12 -> 631692.74 | N13: =sum(B13:M13) -> 7741036.6 | O13: =N13/$N$7 -> 23.925958
A14: F&B Cost | B14: =+B3+B4-B5-B7 -> 136165.18 | C14: =+C3+C4-C5-C7 -> 151440.49 | D14: =+D3+D4-D5-D7 -> 134121.28 | E14: =+E3+E4-E5-E7 -> 148581.37 | F14: =+F3+F4-F5-F7 -> 137350.87 | G14: =+G3+G4-G5-G7 -> 132400.93 | H14: =+H3+H4-H5-H7 -> 126367.39 | I14: =+I3+I4-I5-I7 -> 120828.48 | ... M14: =+M3+M4-M5-M7 -> 137414.95 | N14: =sum(B14:M14) -> 1611672.2 | O14: =N14/$N$13 -> 0.2081985
A15: Electricity | B15: =3965+47011 -> 50976 | C15: =3965+48049 -> 52014 | D15: =3965+42320 -> 46285 | E15: =3965+46546 -> 50511 | F15: =3965+43524 -> 47489 | G15: =43196+3965 -> 47161 | H15: =3965+45032 -> 48997 | I15: =41325+3965 -> 45290 | J15: =3965+44282 -> 48247 | K15: =3965+43832 -> 47797 | L15: =3965+34082 -> 38047 | M15: =44759+1026 -> 45785 | N15: =sum(B15:M15) -> 568599 | O15: =N15/$N$13 -> 0.073452566
A16: Telephone/Internet | B16: =588.82 -> 588.82 | C16: =588.82 -> 588.82 | D16: =588.82 -> 588.82 | E16: =588.82 -> 588.82 | F16: =588.82 -> 588.82 | G16: =588.82 -> 588.82 | H16: =588.82 -> 588.82 | I16: =588.82 -> 588.82 | ... K16: =588.82 -> 588.82 | L16: 588.52 | M16: 588.52 | N16: =sum(B16:M16) -> 7065.24 | O16: =N16/$N$13 -> 0.00091269947
A17: Gas | B17: 0 | C17: 0 | D17: 0 | E17: 0 | F17: 0 | G17: 0 | H17: 0 | I17: 0 | J17: 0 | K17: 0 | L17: =1576 -> 1576 | M17: 4239 | N17: =sum(B17:M17) -> 5815 | O17: =N17/$N$13 -> 0.00075119139
A18: Rent & Revenue Share | B18: =52881+59162 -> 112043 | C18: =66959+63301 -> 130260 | D18: =55823+61683 -> 117506 | E18: =63424+73282 -> 136706 | F18: =58968+58907 -> 117875 | G18: =59568+59568 -> 119136 | H18: =61286+47687 -> 108973 | I18: =56198+54890 -> 111088 | J18: =56816+73217 -> 130033 | K18: =56764+53917 -> 110681 | L18: =35778+26235 -> 62013 | M18: =44114+67649 -> 111763 | N18: =sum(B18:M18) -> 1368077 | O18: =N18/$N$13 -> 0.17673047
A19: Software | B19: 3343 | C19: 3343 | D19: 3343 | E19: 3343 | F19: 3343 | G19: 3343 | H19: 3343 | I19: 3343 | J19: 3343 | K19: =34000*1.18/12 -> 3343.3333 | L19: =34000*1.18/12 -> 3343.3333 | M19: =34000*1.18/12 -> 3343.3333 | N19: =sum(B19:M19) -> 40117 | O19: =N19/$N$13 -> 0.0051823809
A20: Staff Salary & Bonus | B20: =79451+37286/12 -> 82558.167 | C20: =76271+37286/12 -> 79378.167 | D20: =66367+26325+1808.59+37286/12 -> 97607.757 | E20: =97964+37286/12 -> 101071.17 | F20: =96964+37286/12 -> 100071.17 | G20: =96964+37286/12 -> 100071.17 | H20: =37286/12+96964 -> 100071.17 | I20: =37286/12+100214 -> 103321.17 | J20: =37286/12+94408 -> 97515.167 | K20: =37286/12+103931 -> 107038.17 | L20: =37286/12+102093 -> 105200.17 | M20: =37286/12+92182 -> 95289.167 | N20: =sum(B20:M20) -> 1169192.6 | O20: =N20/$N$13 -> 0.15103825
A21: AMC | B21: =2478+2478+3457+14455/12 -> 9617.5833 | C21: =2478+3457+14455/12 -> 7139.5833 | D21: =2478+3457+14455/12 -> 7139.5833 | E21: =2478+3457+14455/12 -> 7139.5833 | F21: =2478+3457+14455/12 -> 7139.5833 | G21: =14455/12+3457+2478 -> 7139.5833 | H21: =14455/12+3457+2478 -> 7139.5833 | I21: =14455/12+3457+2478 -> 7139.5833 | J21: =14455/12+2478+3457 -> 7139.5833 | K21: =14455/12+3457+2478 -> 7139.5833 | L21: =14455/12+2478+3457+6250 -> 13389.583 | M21: =14455/12+2457+2478 -> 6139.5833 | N21: =sum(B21:M21) -> 93403 | O21: =N21/$N$13 -> 0.012065955
A22: Subscription | B22: =2124/3+9813/12+6372/12 -> 2056.75 | C22: =2124/3+9813/12+6372/12 -> 2056.75 | D22: =2124/3+9813/12+6372/12 -> 2056.75 | E22: =9813/12+6372/12+2124/3 -> 2056.75 | F22: =9813/12+6372/12+2124/3 -> 2056.75 | G22: =9813/12+6372/12+2124/3 -> 2056.75 | H22: =9813/12+6372/12+2124/3 -> 2056.75 | I22: =9813/12+6372/12+2124/3 -> 2056.75 | J22: =9813/12+6372/12+2124/3 -> 2056.75 | K22: =9813/12+6372/12+3271.32/3 -> 2439.19 | L22: =9813/12+6372/12+3271.32/3 -> 2439.19 | M22: =9813/12+6372/12+3271.32/3 -> 2439.19 | N22: =sum(B22:M22) -> 25828.32 | O22: =N22/$N$13 -> 0.0033365454
A23: Insurance Premium | B23: 0 | C23: 805.42 | D23: 805.42 | E23: 805.42 | F23: 805.42 | G23: 805.42 | H23: 805.42 | I23: 805.42 | J23: 805.42 | K23: 805.42 | L23: 805.42 | M23: 805.42 | N23: =sum(B23:M23) -> 8859.62 | O23: =N23/$N$13 -> 0.0011445005
A24: Repairs & Maintenance | B24: 0 | C24: 0 | D24: =7392 -> 7392 | E24: 0 | F24: =7900 -> 7900 | G24: 0 | H24: 2155 | I24: 0 | J24: 2000 | K24: 2506.82 | L24: =7978 -> 7978 | M24: 1000 | N24: =sum(B24:M24) -> 30931.82 | O24: =N24/$N$13 -> 0.003995824
A25: Miscellaneous Expenses | B25: 2420 | C25: 280 | D25: =1040 -> 1040 | E25: 2545 | F25: =11311 -> 11311 | G25: 2312 | H25: 21147 | I25: 1255 | J25: 0 | K25: 0 | L25: 1933 | M25: 11480 | N25: =sum(B25:M25) -> 55723 | O25: =N25/$N$13 -> 0.00719839
A26: CAM | B26: =54280 -> 54280 | C26: =54280 -> 54280 | D26: =54280 -> 54280 | E26: =54280 -> 54280 | F26: =54280 -> 54280 | G26: =54280 -> 54280 | H26: =54280 -> 54280 | I26: =54280 -> 54280 | ... K26: =54280 -> 54280 | L26: 54280 | M26: 54280 | N26: =sum(B26:M26) -> 651360 | O26: =N26/$N$13 -> 0.08414377
A27: HO+CK Cost | B27: =HO!D27 -> 128237.04 | C27: =HO!H27 -> 147379.37 | D27: =HO!L27 -> 131440.78 | E27: =HO!P27 -> 165134.79 | F27: =HO!D46 -> 130637.28 | G27: =HO!H46 -> 147682.03 | H27: =HO!L46 -> 119541.7 | I27: =HO!P46 -> 135399.46 | J27: =HO!D65 -> 138345.28 | K27: =HO!H65 -> 121860.45 | L27: =HO!L65 -> 73299.354 | M27: =HO!P65 -> 116338.69 | N27: =sum(B27:M27) -> 1555296.2 | O27: =N27/$N$13 -> 0.20091576
A28: Operating Expenses | B28: =+SUM(B14:B27) -> 582285.54 | C28: =+SUM(C14:C27) -> 628965.6 | D28: =+SUM(D14:D27) -> 603606.39 | E28: =+SUM(E14:E27) -> 672762.9 | F28: =+SUM(F14:F27) -> 620847.89 | G28: =+SUM(G14:G27) -> 616976.7 | H28: =+SUM(H14:H27) -> 595465.83 | I28: =+SUM(I14:I27) -> 585395.68 | ... M28: =+SUM(M14:M27) -> 590905.86 | N28: =sum(B28:M28) -> 7191940 | O28: =N28/$N$13 -> 0.92906679
A29: Store Level EBITDA | B29: =B13-B28 -> 49959.878 | C29: =C13-C28 -> 104450.29 | D29: =D13-D28 -> 57243.036 | E29: =E13-E28 -> 99273.603 | F29: =F13-F28 -> 45106.983 | G29: =G13-G28 -> 69673.371 | H29: =H13-H28 -> 24852.745 | I29: =I13-I28 -> 42190.244 | ... M29: =M13-M28 -> 40786.882 | N29: =sum(B29:M29) -> 549096.57 | O29: =N29/$N$13 -> 0.070933209
A30: Food Cost | B30: =(B14/B13) -> 0.2153676 | C30: =(C14/C13) -> 0.20648651 | D30: =(D14/D13) -> 0.20295286 | E30: =(E14/E13) -> 0.19245382 | F30: =(F14/F13) -> 0.20624651 | G30: =(G14/G13) -> 0.19282155 | H30: =(H14/H13) -> 0.2037137 | I30: =(I14/I13) -> 0.19252898 | ... M30: =(M14/M13) -> 0.21753448
B32: =B29+B27 -> 178196.92 | C32: =C29+C27 -> 251829.66 | D32: =D29+D27 -> 188683.82 | E32: =E29+E27 -> 264408.39 | F32: =F29+F27 -> 175744.26 | G32: =G29+G27 -> 217355.4 | H32: =H29+H27 -> 144394.44 | I32: =I29+I27 -> 177589.7 | ... M32: =M29+M27 -> 157125.58
B33: =B32/B13 -> 0.2818477 | C33: =C32/C13 -> 0.34336543 | D33: =D32/D13 -> 0.28551711 | E33: =E32/E13 -> 0.34248172 | F33: =F32/F13 -> 0.26389815 | G33: =G32/G13 -> 0.31654464 | H33: =H32/H13 -> 0.23277465 | I33: =I32/I13 -> 0.28297273 | ... M33: =M32/M13 -> 0.24873735

Sheet Mani Square Mall
A1: Dosa Coffee - Mani Square Mall | B1: 45748 | C1: 45778 | D1: 45809 | E1: 45839 | F1: 45870 | G1: 45901 | H1: 45931 | I1: 45962 | J1: 45992 | K1: 46023 | L1: 46054 | M1: 46082 | N1: FY 2025-26
A2: Food Cost Calculation
A3: Opening Stock | B3: 14541.53 | C3: =B7 -> 20148 | D3: =C7 -> 21129.86 | E3: =D7 -> 21048 | F3: =E7 -> 19868.5 | G3: =F7 -> 18431 | H3: =G7 -> 32940.33 | I3: =H7 -> 19943 | J3: =I7 -> 19476.86 | ... M3: =L7 -> 18292.91 | N3: =+SUM(J3:L3) -> 61982.36
A4: Purchases Food (Less Purchase Return) | B4: 183554.03 | C4: 196478.17 | D4: 198378.76 | E4: 196653.19 | F4: 220579.13 | G4: 211797.97 | H4: 199039.54 | I4: =200241.02 -> 200241.02 | J4: 239529 | K4: 224268.94 | L4: 209295 | M4: 254180 | N4: =sum(B4:M4) -> 2533994.8
A5: Transferred Out | B5: 891 | C5: 236.6 | D5: 187.5 | E5: 220.77 | F5: 143.59 | G5: 114.86 | H5: 58 | I5: 77.5 | J5: 0 | K5: 0 | L5: 0 | M5: 38 | N5: =+SUM(J5:L5) -> 0
A6: Wastage & Date Expired | B6: 5864 | C6: 6074.97 | D6: 4986 | E6: 5539.73 | F6: 4481.36 | G6: 4310 | H6: 4810 | I6: 9135.96 | J6: 8819 | K6: 8047.3 | L6: 8163.52 | M6: 11178.24 | N6: =+SUM(J6:L6) -> 25029.82
A7: Closing Stock | B7: 20148 | C7: 21129.86 | D7: 21048 | E7: 19868.5 | F7: 18431 | G7: 32940.33 | H7: 19943 | I7: 19476.86 | J7: 22461 | K7: 20044.5 | L7: 18292.91 | M7: 18285 | N7: =sum(B7:M7) -> 252068.96
A9: Gross Revenue | B9: =935573.97*1.05+4557.36*1.05 -> 987137.9 | C9: =1053137*1.05+5057.08*1.05 -> 1111103.8 | D9: =1054582.18*1.05+420.06*1.05+5446.7*1.05 -> 1113471.4 | E9: =1106268.72*1.05+4612.67*1.05 -> 1166425.5 | F9: =1200880.04*1.05+5693.81*1.05 -> 1266902.5 | G9: =1194807.26*1.05 -> 1254547.6 | H9: =993949.88*1.05+5982.88*1.05 -> 1049929.4 | I9: =977605.67*1.05+4674.62*1.05 -> 1031394.3 | J9: =1167402.33*1.05+4424.77*1.05 -> 1230418.5 | K9: =1132008*1.05+4651.04*1.05 -> 1193492 | L9: =924356.35*1.05+4589.99*1.05 -> 975393.66 | M9: =1224267.01*1.05+5672.85*1.05 -> 1291436.9 | N9: =+SUM(B9:M9) -> 13671653
A10: Catering & Fairs | B10: 0 | C10: 0 | D10: 0 | E10: 0 | F10: 0 | G10: 0 | N10: =+SUM(B10:M10) -> 0
A11: Less Tax | B11: =(B9+B10)/1.05*0.05 -> 47006.567 | C11: =(C9+C10)/1.05*0.05 -> 52909.704 | D11: =(D9+D10)/1.05*0.05 -> 53022.447 | E11: =(E9+E10)/1.05*0.05 -> 55544.069 | F11: =(F9+F10)/1.05*0.05 -> 60328.692 | G11: =(G9+G10)/1.05*0.05 -> 59740.363 | H11: =(H9+H10)/1.05*0.05 -> 49996.638 | I11: =(I9+I10)/1.05*0.05 -> 49114.014 | ... M11: =(M9+M10)/1.05*0.05 -> 61496.993 | N11: =+SUM(B11:M11) -> 651031.11
A12: Less Commission | B12: =10527.27+1894.9+13015.25+2342.74+1343 -> 29123.16 | C12: =2096.64+11648+14259.32+2566.69+4038+726.89 -> 35335.54 | D12: =12503.02+2250.54+11654.87+2097.87+7333.56+1320.04 -> 37159.9 | E12: =10604.04+1908.73+16792.91+3022.73+3416+614 -> 36358.41 | F12: =12716.82+2289.03+13092.13+2356.58+5020.36+903.74 -> 36378.66 | G12: =13851.2*1.18+12173.86*1.18 -> 30709.571 | H12: =13820.16*1.18+11267.58*1.18+1317.34*1.18 -> 31157.994 | I12: =10788.11*1.18+7750.47*1.18 -> 21875.524 | J12: =10221.16*1.18+9237.56*1.18 -> 22961.29 | K12: =10639.73*1.18+8683*1.18 -> 22800.821 | L12: =12269.53+5281.09+5615.92+950.6 -> 24117.14 | M12: =12551.36*1.18+8240.21*1.18+4717.04*1.18 -> 30100.16 | N12: =+SUM(B12:M12) -> 358078.17
A13: Net Revenues from F&B Sales | B13: =B9+B10-B11-B12 -> 911008.17 | C13: =C9+C10-C11-C12 -> 1022858.5 | D13: =D9+D10-D11-D12 -> 1023289 | E13: =E9+E10-E11-E12 -> 1074523 | F13: =F9+F10-F11-F12 -> 1170195.2 | G13: =G9+G10-G11-G12 -> 1164097.7 | H13: =H9+H10-H11-H12 -> 968774.77 | I13: =I9+I10-I11-I12 -> 960404.77 | ... M13: =M9+M10-M11-M12 -> 1199839.7 | N13: =sum(B13:M13) -> 12662544
A14: F&B Cost | B14: =+B3+B4-B5-B7 -> 177056.56 | C14: =+C3+C4-C5-C7 -> 195259.71 | D14: =+D3+D4-D5-D7 -> 198273.12 | E14: =+E3+E4-E5-E7 -> 197611.92 | F14: =+F3+F4-F5-F7 -> 221873.04 | G14: =+G3+G4-G5-G7 -> 197173.78 | H14: =+H3+H4-H5-H7 -> 211978.87 | I14: =+I3+I4-I5-I7 -> 200629.66 | ... M14: =+M3+M4-M5-M7 -> 254149.91 | N14: =sum(B14:M14) -> 2528283.5 | O14: =N14/$N$13 -> 0.19966631
A15: Electricity | B15: 14000 | C15: 15000 | D15: 15000 | E15: 15000 | F15: 15000 | G15: =10000+1000 -> 11000 | H15: 15000 | I15: 15000 | J15: 15000 | K15: 15000 | L15: =10000+5000+500+500 -> 16000 | M15: =868+15000 -> 15868 | N15: =sum(B15:M15) -> 176868 | O15: =N15/$N$13 -> 0.013967809
A16: Telephone/Internet | B16: =942.82+352.82 -> 1295.64 | C16: =942.82+352.82 -> 1295.64 | D16: =942.82+352.82 -> 1295.64 | E16: =942.82+352.82 -> 1295.64 | F16: =942.82+352.82 -> 1295.64 | G16: 352.82 | H16: 352.82 | I16: 352.82 | J16: 352.82 | K16: 352.82 | L16: 352.82 | M16: =352.82 -> 352.82 | N16: =sum(B16:M16) -> 8947.94 | O16: =N16/$N$13 -> 0.00070664631
A17: Gas | B17: 11766.64 | C17: 10376.4 | D17: 7400 | E17: 8168 | F17: 10346 | G17: 9726 | H17: 11576 | I17: =9078 -> 9078 | J17: 12163 | K17: 14521 | L17: =18215 -> 18215 | M17: 25000 | N17: =sum(B17:M17) -> 148336.04 | O17: =N17/$N$13 -> 0.011714553
A18: Rent & Revenue Share | B18: 152611 | C18: 162045 | D18: 160955 | E18: 170530 | F18: =187638 -> 187638 | G18: 189620 | H18: 154769 | I18: 158086 | J18: =191186 -> 191186 | K18: 184826 | L18: 148550 | M18: =195155 -> 195155 | N18: =sum(B18:M18) -> 2055971 | O18: =N18/$N$13 -> 0.16236635
A19: Software | B19: 3761 | C19: 3761 | D19: 3761 | E19: 3761 | F19: 3761 | G19: 3761 | H19: 3761 | I19: =3761+5015/12 -> 4178.9167 | J19: =3761+5015/12 -> 4178.9167 | K19: =34000*1.18/12 -> 3343.3333 | L19: =34000*1.18/12 -> 3343.3333 | M19: =34000*1.18/12 -> 3343.3333 | N19: =sum(B19:M19) -> 44714.833 | O19: =N19/$N$13 -> 0.0035312677
A20: Staff Salary & Bonus | B20: =96151+37331/12 -> 99261.917 | C20: =105528.42+37331/12 -> 108639.34 | D20: =72908+27404+1977+13429+37331/12 -> 118828.92 | E20: =99574+37331/12 -> 102684.92 | F20: =114775.29+37331/12 -> 117886.21 | G20: =95868+37331/12 -> 98978.917 | H20: =37331/12+98013 -> 101123.92 | I20: =37331/12+103549 -> 106659.92 | J20: =37331/12+111458 -> 114568.92 | K20: =37331/12+134434 -> 137544.92 | L20: =37331/12+134512 -> 137622.92 | M20: =37331/12+130267 -> 133377.92 | N20: =sum(B20:M20) -> 1377178.7 | O20: =N20/$N$13 -> 0.10876003
A21: AMC | B21: =2478+8555/12 -> 3190.9167 | C21: =2478+8555/12 -> 3190.9167 | D21: =2478+1200+8555/12 -> 4390.9167 | E21: =2170+1200+2478+8555/12 -> 6560.9167 | F21: =2478+8555/12 -> 3190.9167 | G21: =8555/12+2478 -> 3190.9167 | H21: =8555/12+2478 -> 3190.9167 | I21: =8555/12+2478 -> 3190.9167 | J21: =8555/12+1200+2478 -> 4390.9167 | K21: =8555/12+1200+2478 -> 4390.9167 | L21: =8555/12+2478+1930 -> 5120.9167 | M21: =8555/12+2478 -> 3190.9167 | N21: =sum(B21:M21) -> 47191 | O21: =N21/$N$13 -> 0.0037268182
A22: Subscription | B22: =2124/3+9813/12+6372/12 -> 2056.75 | C22: =2124/3+9813/12+6372/12 -> 2056.75 | D22: =2124/3+9813/12+6372/12 -> 2056.75 | E22: =9813/12+6372/12+2124/3 -> 2056.75 | F22: =9813/12+6372/12+2124/3 -> 2056.75 | G22: =9813/12+6372/12+2124/3 -> 2056.75 | H22: =9813/12+6372/12+2124/3 -> 2056.75 | I22: =9813/12+6372/12+2124/3 -> 2056.75 | J22: =9813/12+6372/12+2124/3 -> 2056.75 | K22: =9813/12+6372/12+3271.32/3 -> 2439.19 | L22: =9813/12+6372/12+3271.32/3 -> 2439.19 | M22: =9813/12+6372/12+3271.32/3 -> 2439.19 | N22: =sum(B22:M22) -> 25828.32 | O22: =N22/$N$13 -> 0.0020397418
A23: Insurance Premium | B23: 0 | C23: 526.68 | D23: 526.68 | E23: 526.68 | F23: 526.68 | G23: 526.68 | H23: 526.68 | I23: 526.68 | J23: 526.68 | K23: 526.68 | L23: 526.68 | M23: 526.68 | N23: =sum(B23:M23) -> 5793.48 | O23: =N23/$N$13 -> 0.00045752891
A24: Repairs & Maintenance | B24: 0 | C24: 3600 | D24: 2284 | E24: 0 | F24: 540 | G24: 5900 | H24: 0 | I24: 0 | J24: 4130 | K24: 240 | L24: 4194 | M24: 40 | N24: =sum(B24:M24) -> 20928 | O24: =N24/$N$13 -> 0.0016527484
A25: Miscellaneous Expenses | B25: =3480 -> 3480 | C25: 1840.67 | D25: =2176.81 -> 2176.81 | E25: 5292 | F25: 5901 | G25: 22698 | H25: 710 | I25: 794.56 | J25: 430 | K25: 2765 | L25: 5152 | M25: 9817 | N25: =sum(B25:M25) -> 61057.04 | O25: =N25/$N$13 -> 0.004821862
A26: CAM | B26: =38161 -> 38161 | C26: =38161 -> 38161 | D26: =38161 -> 38161 | E26: 38884 | F26: 38884 | G26: 38884 | H26: 38884 | I26: 38884 | J26: 38884 | K26: 38884 | L26: 38884 | M26: 38884 | N26: =sum(B26:M26) -> 464439 | O26: =N26/$N$13 -> 0.036678174
A27: HO+CK Cost | B27: =HO!D31 -> 184777.92 | C27: =HO!H31 -> 205542.65 | D27: =HO!L31 -> 203528.83 | E27: =HO!P31 -> 229835.15 | F27: =HO!D50 -> 229551.76 | G27: =HO!H50 -> 250369.61 | H27: =HO!L50 -> 186692.75 | I27: =HO!P50 -> 207203.95 | J27: =HO!D69 -> 216334.09 | K27: =HO!H69 -> 217093.05 | L27: =HO!L69 -> 189306.4 | M27: =HO!P69 -> 220974.18 | N27: =sum(B27:M27) -> 2541210.3 | O27: =N27/$N$13 -> 0.20068719
A28: Operating Expenses | B28: =+SUM(B14:B27) -> 691419.34 | C28: =+SUM(C14:C27) -> 751295.76 | D28: =+SUM(D14:D27) -> 758638.67 | E28: =+SUM(E14:E27) -> 782206.97 | F28: =+SUM(F14:F27) -> 838450.99 | G28: =+SUM(G14:G27) -> 834238.47 | H28: =+SUM(H14:H27) -> 730622.7 | I28: =+SUM(I14:I27) -> 746642.17 | ... M28: =+SUM(M14:M27) -> 903118.95 | N28: =sum(B28:M28) -> 9506747.2 | O28: =N28/$N$13 -> 0.75077702
A29: Store Level EBITDA | B29: =B13-B28 -> 219588.83 | C29: =C13-C28 -> 271562.78 | D29: =D13-D28 -> 264650.37 | E29: =E13-E28 -> 292316.01 | F29: =F13-F28 -> 331744.2 | G29: =G13-G28 -> 329859.22 | H29: =H13-H28 -> 238152.07 | I29: =I13-I28 -> 213762.59 | ... M29: =M13-M28 -> 296720.75 | N29: =sum(B29:M29) -> 3155796.9 | O29: =N29/$N$13 -> 0.24922298
A30: Food Cost | B30: =(B14/B13) -> 0.19435233 | C30: =(C14/C13) -> 0.1908961 | D30: =(D14/D13) -> 0.19376062 | E30: =(E14/E13) -> 0.18390665 | F30: =(F14/F13) -> 0.18960345 | G30: =(G14/G13) -> 0.16937907 | H30: =(H14/H13) -> 0.2188113 | I30: =(I14/I13) -> 0.20890115 | ... M30: =(M14/M13) -> 0.21181989
B32: =B29+B27 -> 404366.75 | C32: =C29+C27 -> 477105.44 | D32: =D29+D27 -> 468179.21 | E32: =E29+E27 -> 522151.16 | F32: =F29+F27 -> 561295.96 | G32: =G29+G27 -> 580228.83 | H32: =H29+H27 -> 424844.81 | I32: =I29+I27 -> 420966.55 | ... M32: =M29+M27 -> 517694.93
B33: =B32/B13 -> 0.44386731 | C33: =C32/C13 -> 0.46644323 | D33: =D32/D13 -> 0.45752391 | E33: =E32/E13 -> 0.48593764 | F33: =F32/F13 -> 0.47966011 | G33: =G32/G13 -> 0.49843654 | H33: =H32/H13 -> 0.43853827 | I33: =I32/I13 -> 0.43832201 | ... M33: =M32/M13 -> 0.43147008

Sheet Lake Town
A1: Dosa Coffee - Lake Town | B1: 45748 | C1: 45778 | D1: 45809 | E1: 45839 | F1: 45870 | G1: 45901 | H1: 45931 | I1: 45962 | J1: 45992 | K1: 46023 | L1: 46054 | M1: 46082 | N1: FY 2025-26
A2: Food Cost Calculation
A3: Opening Stock | B3: 38819.35 | C3: =B7 -> 25881 | D3: =C7 -> 31727.17 | E3: =D7 -> 28718 | F3: =E7 -> 34065.77 | G3: =F7 -> 33590 | H3: =G7 -> 36469.93 | I3: =H7 -> 25880.53 | J3: =I7 -> 32224.05 | ... M3: =L7 -> 24432.3 | N3: =+SUM(J3:L3) -> 102626.05
A4: Purchases Food (Less Purchase Return) | B4: 212521.04 | C4: 244166.7 | D4: 223375.53 | E4: 264442.95 | F4: 270401.81 | G4: 272673.67 | H4: 272620.42 | I4: 255616.3 | J4: 239051 | K4: 279528.57 | L4: 262212 | M4: 335291.85 | N4: =sum(B4:M4) -> 3131901.8
A5: Transferred Out | B5: 306.04 | C5: 444.62 | D5: 176.93 | E5: 385.3 | F5: 0 | G5: 397.28 | H5: 877 | I5: 506.78 | J5: 285 | K5: 539.27 | L5: 85.76 | M5: 926.45 | N5: =+SUM(J5:L5) -> 910.03
A6: Wastage & Date Expired | B6: 5521.73 | C6: 5677.35 | D6: 6363 | E6: 9065.29 | F6: 8750 | G6: 7370.63 | H6: 8506 | I6: 7949.81 | J6: 7606 | K6: 7430.61 | L6: 7167.83 | M6: 9082.81 | N6: =+SUM(J6:L6) -> 22204.44
A7: Closing Stock | B7: 25881 | C7: 31727.17 | D7: 28718 | E7: 34065.77 | F7: 33590 | G7: 36469.93 | H7: 25880.53 | I7: 32224.05 | J7: 42889 | K7: 27513 | L7: 24432.3 | M7: 26042.56 | N7: =sum(B7:M7) -> 369433.31
A9: Gross Revenue | B9: =926387.29*1.05+278*1.05+20193.12*1.05 -> 994201.33 | C9: =988606.08*1.05+22790.38*1.05 -> 1061966.3 | D9: =985391.49*1.05+24865.58*1.05 -> 1060769.9 | E9: =1048238.36*1.05+25443.63*1.05 -> 1127366.1 | F9: =1064391.36*1.05+25722.67*1.05 -> 1144619.7 | G9: =1128167.28*1.05 -> 1184575.6 | H9: =1153667.79*1.05+29797.6*1.05 -> 1242638.7 | I9: =1029646.39*1.05+27662.96*1.05 -> 1110174.8 | J9: =960051.15*1.05+23270.78*1.05 -> 1032488 | K9: =1146000.72*1.05+26840.5*1.05 -> 1231483.3 | L9: =1050622.44*1.05+30772.33*1.05 -> 1135464.5 | M9: =1304860.9*1.05+35584.44*1.05 -> 1407467.6 | N9: =+SUM(B9:M9) -> 13733216
A10: Catering & Fairs | B10: 0 | C10: 0 | D10: 0 | E10: 0 | F10: 0 | G10: 0 | H10: 0 | I10: 0 | J10: 0 | K10: 0 | L10: 0 | M10: 0 | N10: =+SUM(B10:M10) -> 0
A11: Less Tax | B11: =(B9+B10)/1.05*0.05 -> 47342.921 | C11: =(C9+C10)/1.05*0.05 -> 50569.823 | D11: =(D9+D10)/1.05*0.05 -> 50512.853 | E11: =(E9+E10)/1.05*0.05 -> 53684.099 | F11: =(F9+F10)/1.05*0.05 -> 54505.702 | G11: =(G9+G10)/1.05*0.05 -> 56408.364 | H11: =(H9+H10)/1.05*0.05 -> 59173.27 | I11: =(I9+I10)/1.05*0.05 -> 52865.467 | ... M11: =(M9+M10)/1.05*0.05 -> 67022.267 | N11: =+SUM(B11:M11) -> 653962.66
A12: Less Commission | B12: =46111.25+101.31+8300.02+18.24+40150.19+7227.01+37.5+6709 -> 108654.52 | C12: =35.4+52718.38+9453.9+43285.74+7791.43+5.11+11076.73+1993.81 -> 126360.5 | D12: =57558.73+10360.58+41462.84+7462+14345.76+2582.23 -> 133772.14 | E12: =58878.37+10598.11+49132.02+7604.4+525.64+7817+1407 -> 135962.54 | F12: =44150.72+7947.12+59565.66+10721.82+1258.92*1.18+14345.4+2582.16 -> 140798.41 | G12: =56322.46*1.18+422.01*1.18+54944.82*1.18 -> 131793.36 | H12: =69028*1.18+47620.78*1.18+1268.59*1.18+12356.91*1.18 -> 153723.65 | I12: =64344.75*1.18+44991.1*1.18+347.61*1.18 -> 129426.48 | J12: =(53712.61+447.06)*1.18+46757.98*1.18+422.95*1.18 -> 119581.91 | K12: =62817.69*1.18+1320.73*1.18+54396.11*1.18 -> 139870.75 | L12: =83866.75+22358.89+27382.74+111.09+4024.64+20.02+312.85*1.18+20.28*1.18 -> 138157.22 | M12: =82804.87*1.18+42479.59*1.18+897.71*1.18+26.06*1.18+23679.15*1.18 -> 176867.11 | N12: =+SUM(B12:M12) -> 1634968.6
A13: Net Revenues from F&B Sales | B13: =B9+B10-B11-B12 -> 838203.89 | C13: =C9+C10-C11-C12 -> 885035.96 | D13: =D9+D10-D11-D12 -> 876484.93 | E13: =E9+E10-E11-E12 -> 937719.45 | F13: =F9+F10-F11-F12 -> 949315.62 | G13: =G9+G10-G11-G12 -> 996373.92 | H13: =H9+H10-H11-H12 -> 1029741.7 | I13: =I9+I10-I11-I12 -> 927882.87 | ... M13: =M9+M10-M11-M12 -> 1163578.2 | N13: =sum(B13:M13) -> 11444285
A14: F&B Cost | B14: =+B3+B4-B5-B7 -> 225153.35 | C14: =+C3+C4-C5-C7 -> 237875.91 | D14: =+D3+D4-D5-D7 -> 226207.77 | E14: =+E3+E4-E5-E7 -> 258709.88 | F14: =+F3+F4-F5-F7 -> 270877.58 | G14: =+G3+G4-G5-G7 -> 269396.46 | H14: =+H3+H4-H5-H7 -> 282332.82 | I14: =+I3+I4-I5-I7 -> 248766 | ... M14: =+M3+M4-M5-M7 -> 332755.14 | N14: =sum(B14:M14) -> 3139748.2 | O14: =N14/$N$13 -> 0.27435076
A15: Electricity | B15: 35350 | C15: 68820 | D15: 48630 | E15: =47350 -> 47350 | F15: 43720 | G15: 49020 | H15: 41270 | I15: 33670 | J15: 28950 | K15: 28870 | L15: 37450 | M15: =48130 -> 48130 | N15: =sum(B15:M15) -> 511230 | O15: =N15/$N$13 -> 0.044671206
A16: Telephone/Internet | B16: =942.82+352.82 -> 1295.64 | C16: =942.82+352.82 -> 1295.64 | D16: =2478/3+352.82+942.82 -> 2121.64 | E16: =2478/3+352.82+942.82 -> 2121.64 | F16: =2478/3+942.82+352.82 -> 2121.64 | G16: =942.82+767+352.82 -> 2062.64 | H16: =942.82+767+352.82 -> 2062.64 | I16: =352.82+942.82 -> 1295.64 | J16: =352.82+942.82 -> 1295.64 | K16: =767+942.82+352.82 -> 2062.64 | L16: =767+942.82+85.22+352.82 -> 2147.86 | M16: =767+942.82+85.22+352.82 -> 2147.86 | N16: =sum(B16:M16) -> 22031.12 | O16: =N16/$N$13 -> 0.0019250762
A17: Gas | B17: =23919 -> 23919 | C17: 23681 | D17: =18326 -> 18326 | E17: 22526 | F17: 20468 | G17: 22860 | H17: 21567 | I17: 21476 | J17: 21336 | K17: 24525 | L17: =25268 -> 25268 | M17: =11597+9*3556 -> 43601 | N17: =sum(B17:M17) -> 289553 | O17: =N17/$N$13 -> 0.025301101
A18: Rent & Revenue Share | B18: 48300 | C18: =48300*1.18 -> 56994 | D18: =56994 -> 56994 | E18: =56994 -> 56994 | F18: =56994 -> 56994 | G18: =56994 -> 56994 | H18: =56994 -> 56994 | I18: =56994 -> 56994 | J18: =56994 -> 56994 | K18: =56994 -> 56994 | ... M18: =56994 -> 56994 | N18: =sum(B18:M18) -> 675234 | O18: =N18/$N$13 -> 0.059001853
A19: Software | B19: 3761 | C19: 3761 | D19: 3761 | E19: 3761 | F19: 3761 | G19: 3761 | H19: 3761 | I19: 3761 | J19: 3761 | K19: =34000*1.18/12+4250*1.18/12 -> 3761.25 | L19: =34000*1.18/12+4250*1.18/12 -> 3761.25 | M19: =34000*1.18/12+4250*1.18/12 -> 3761.25 | N19: =sum(B19:M19) -> 45132.75 | O19: =N19/$N$13 -> 0.0039436934
A20: Staff Salary & Bonus | B20: =157249+56014/12 -> 161916.83 | C20: =136460+56014/12 -> 141127.83 | D20: =103286.25+47543.13+3145.63+56014/12 -> 158642.84 | E20: =160298+56014/12 -> 164965.83 | F20: =160775+56014/12 -> 165442.83 | G20: =161150+56014/12 -> 165817.83 | H20: =56014/12+126822.58 -> 131490.41 | I20: =56014/12+157880 -> 162547.83 | J20: =56014/12+159884 -> 164551.83 | K20: =56014/12+157884 -> 162551.83 | L20: =56014/12+160134 -> 164801.83 | M20: =56014/12+160384 -> 165051.83 | N20: =sum(B20:M20) -> 1908909.6 | O20: =N20/$N$13 -> 0.16680025
A21: AMC | B21: =2360+2478+2950+19175/12 -> 9385.9167 | C21: =2478+2478+2950+19175/12 -> 9503.9167 | D21: =2478+2478+2950+19175/12 -> 9503.9167 | E21: =2950+2478+2478+19175/12 -> 9503.9167 | F21: =2478+2478+2950+19175/12 -> 9503.9167 | G21: =19175/12+2950+2478+2478 -> 9503.9167 | H21: =19175/12+2950+2478+2478 -> 9503.9167 | I21: =19175/12+2950+2478+2478 -> 9503.9167 | J21: =19175/12+2478+2478+2950 -> 9503.9167 | K21: =19175/12+2950+2478+2478 -> 9503.9167 | L21: =19175/12+2478+2478+2950 -> 9503.9167 | M21: =19175/12+2950+2478+2478 -> 9503.9167 | N21: =sum(B21:M21) -> 113929 | O21: =N21/$N$13 -> 0.0099551002
A22: Subscription | B22: =2124/3+9813/12+6372/12 -> 2056.75 | C22: =2124/3+9813/12+6372/12 -> 2056.75 | D22: =2124/3+9813/12+6372/12 -> 2056.75 | E22: =9813/12+6372/12+2124/3 -> 2056.75 | F22: =9813/12+6372/12+2124/3 -> 2056.75 | G22: =9813/12+6372/12+2124/3 -> 2056.75 | H22: =9813/12+6372/12+2124/3 -> 2056.75 | I22: =9813/12+6372/12+2124/3 -> 2056.75 | J22: =9813/12+6372/12+2124/3 -> 2056.75 | K22: =9813/12+6372/12+3271.32/3 -> 2439.19 | L22: =9813/12+6372/12+3271.32/3 -> 2439.19 | M22: =9813/12+6372/12+3271.32/3 -> 2439.19 | N22: =sum(B22:M22) -> 25828.32 | O22: =N22/$N$13 -> 0.002256875
A23: Insurance Premium | B23: 0 | C23: 973.34 | D23: 973.34 | E23: 973.34 | F23: 973.34 | G23: 973.34 | H23: 973.34 | I23: 973.34 | J23: 973.34 | K23: 973.34 | L23: 973.34 | M23: 973.34 | N23: =sum(B23:M23) -> 10706.74 | O23: =N23/$N$13 -> 0.00093555345
A24: Repairs & Maintenance | B24: 1000 | C24: 4000 | D24: =20060/12+6161 -> 7832.6667 | E24: =20060/12+1000 -> 2671.6667 | F24: =20060/12+6900 -> 8571.6667 | G24: =20060/12+1000 -> 2671.6667 | H24: =20060/12+1560 -> 3231.6667 | I24: =20060/12+1000 -> 2671.6667 | J24: =20060/12 -> 1671.6667 | K24: =20060/12+7570.7 -> 9242.3667 | L24: =20060/12+14293 -> 15964.667 | M24: =20060/12+10876 -> 12547.667 | N24: =sum(B24:M24) -> 72077.367 | O24: =N24/$N$13 -> 0.0062981103
A25: Miscellaneous Expenses | B25: 2087 | C25: 1955.76 | D25: =3119.54 -> 3119.54 | E25: =11017 -> 11017 | F25: =14417.89 -> 14417.89 | G25: 5900.8 | H25: 8846 | I25: 7255.82 | J25: 7253.73 | K25: 7490 | L25: 7142.91 | M25: =13255.44 -> 13255.44 | N25: =sum(B25:M25) -> 89741.89 | O25: =N25/$N$13 -> 0.0078416339
A26: CAM | N26: =sum(B26:M26) -> 0 | O26: =N26/$N$13 -> 0
A27: HO+CK Cost | B27: =HO!D28 -> 170011.18 | C27: =HO!H28 -> 177847.31 | D27: =HO!L28 -> 174329.98 | E27: =HO!P28 -> 200573.55 | F27: =HO!D47 -> 186222.84 | G27: =HO!H47 -> 214296.23 | H27: =HO!L47 -> 198441.7 | I27: =HO!P47 -> 200187.47 | J27: =HO!D66 -> 162644.25 | K27: =HO!H66 -> 201327.88 | L27: =HO!L66 -> 197342.11 | M27: =HO!P66 -> 214295.91 | N27: =sum(B27:M27) -> 2297520.4 | O27: =N27/$N$13 -> 0.20075701
A28: Operating Expenses | B28: =+SUM(B14:B27) -> 684236.67 | C28: =+SUM(C14:C27) -> 729892.46 | D28: =+SUM(D14:D27) -> 712499.44 | E28: =+SUM(E14:E27) -> 783224.58 | F28: =+SUM(F14:F27) -> 785131.46 | G28: =+SUM(G14:G27) -> 805314.64 | H28: =+SUM(H14:H27) -> 762531.25 | I28: =+SUM(I14:I27) -> 751159.43 | ... M28: =+SUM(M14:M27) -> 905456.55 | N28: =sum(B28:M28) -> 9201642.4 | O28: =N28/$N$13 -> 0.80403823
A29: Store Level EBITDA | B29: =B13-B28 -> 153967.22 | C29: =C13-C28 -> 155143.5 | D29: =D13-D28 -> 163985.49 | E29: =E13-E28 -> 154494.87 | F29: =F13-F28 -> 164184.17 | G29: =G13-G28 -> 191059.28 | H29: =H13-H28 -> 267210.49 | I29: =I13-I28 -> 176723.43 | ... M29: =M13-M28 -> 258121.68 | N29: =sum(B29:M29) -> 2242642.3 | O29: =N29/$N$13 -> 0.19596177
A30: Food Cost | B30: =(B14/B13) -> 0.26861406 | C30: =(C14/C13) -> 0.26877542 | D30: =(D14/D13) -> 0.25808518 | E30: =(E14/E13) -> 0.27589262 | F30: =(F14/F13) -> 0.28533985 | G30: =(G14/G13) -> 0.27037687 | H30: =(H14/H13) -> 0.27417828 | I30: =(I14/I13) -> 0.26810065 | ... M30: =(M14/M13) -> 0.28597574
B32: =B29+B27 -> 323978.4 | C32: =C29+C27 -> 332990.81 | D32: =D29+D27 -> 338315.46 | E32: =E29+E27 -> 355068.42 | F32: =F29+F27 -> 350407.01 | G32: =G29+G27 -> 405355.51 | H32: =H29+H27 -> 465652.19 | I32: =I29+I27 -> 376910.9 | ... M32: =M29+M27 -> 472417.59
B33: =B32/B13 -> 0.38651503 | C33: =C32/C13 -> 0.37624551 | D33: =D32/D13 -> 0.38599119 | E33: =E32/E13 -> 0.37865102 | F33: =F32/F13 -> 0.36911539 | G33: =G32/G13 -> 0.40683071 | H33: =H32/H13 -> 0.45220289 | I33: =I32/I13 -> 0.40620526 | ... M33: =M32/M13 -> 0.40600415

Sheet Rosedale Plaza
A1: Dosa Coffee - Rosedale Plaza | B1: 45748 | C1: 45778 | D1: 45809 | E1: 45839 | F1: 45870 | G1: 45901 | H1: 45931 | I1: 45962 | J1: 45992 | K1: 46023 | L1: 46054 | M1: 46082 | N1: FY 2025-26
A2: Food Cost Calculation
A3: Opening Stock | B3: 32680.43 | C3: =B7 -> 29379 | D3: =C7 -> 29592.26 | E3: =D7 -> 28982 | F3: =E7 -> 32793.74 | G3: =F7 -> 29689.76 | H3: =G7 -> 33909.81 | I3: =H7 -> 34062.04 | J3: =I7 -> 22015.85 | ... M3: =L7 -> 28822.5 | N3: =+SUM(J3:L3) -> 83021.85
A4: Purchases Food (Less Purchase Return) | B4: 390608.89 | C4: 407880.03 | D4: 456682.78 | E4: 476176.6 | F4: 480515.81 | G4: 453478.08 | H4: 440092.72 | I4: 400814.44 | J4: 432955 | K4: 430978.46 | L4: 418813.38 | M4: 486947.6 | N4: =sum(B4:M4) -> 5275943.8
A5: Transferred Out | B5: 854 | C5: 451.97 | D5: 2859 | E5: 1020 | F5: 1049.57 | G5: 1386 | H5: 368.26 | I5: 271.99 | J5: 935 | K5: 252.96 | L5: 454.42 | M5: 358.73 | N5: =+SUM(J5:L5) -> 1642.38
A6: Wastage & Date Expired | B6: 14772.76 | C6: 16787.36 | D6: 15425 | E6: 14951 | F6: 15906.7 | G6: 15804 | H6: 14474.62 | I6: 11909.58 | J6: 12140 | K6: 12476.72 | L6: 11569 | M6: 16852.2 | N6: =+SUM(J6:L6) -> 36185.72
A7: Closing Stock | B7: 29379 | C7: 29592.26 | D7: 28982 | E7: 32793.74 | F7: 29689.76 | G7: 33909.81 | H7: 34062.04 | I7: 22015.85 | J7: 33790 | K7: 27216 | L7: 28822.5 | M7: 29064 | N7: =sum(B7:M7) -> 359316.96
A9: Gross Revenue | B9: =1654226.13*1.05+32752.55*1.05 -> 1771327.6 | C9: =1693394.06*1.05+37852.52*1.05 -> 1817808.9 | D9: =1910175.75*1.05+44366.76*1.05 -> 2052269.6 | E9: =1930557.68*1.05+45953.88*1.05 -> 2075337.1 | F9: =1956062.5*1.05+45349.39*1.05 -> 2101482.5 | G9: =1936006.97*1.05 -> 2032807.3 | H9: =1862224.52*1.05+43405.28*1.05 -> 2000911.3 | I9: =1781786.68*1.05+43955.13*1.05 -> 1917028.9 | J9: =1805508.38*1.05+38896.56*1.05 -> 1936625.2 | K9: =1832872.13*1.05+36570.33*1.05 -> 1962914.6 | L9: =1686686.45*1.05+39024.85*1.05 -> 1811996.9 | M9: =1952418.34*1.05+47307.1*1.05 -> 2099711.7 | N9: =+SUM(B9:M9) -> 23580222
A10: Catering & Fairs | B10: 0 | C10: 0 | D10: 0 | E10: 0 | F10: 0 | G10: 0 | H10: 0 | I10: 0 | J10: 0 | K10: 0 | L10: 0 | M10: 0 | N10: =+SUM(B10:M10) -> 0
A11: Less Tax | B11: =(B9+B10)/1.05*0.05 -> 84348.934 | C11: =(C9+C10)/1.05*0.05 -> 86562.329 | D11: =(D9+D10)/1.05*0.05 -> 97727.125 | E11: =(E9+E10)/1.05*0.05 -> 98825.578 | F11: =(F9+F10)/1.05*0.05 -> 100070.59 | G11: =(G9+G10)/1.05*0.05 -> 96800.348 | H11: =(H9+H10)/1.05*0.05 -> 95281.49 | I11: =(I9+I10)/1.05*0.05 -> 91287.091 | ... M11: =(M9+M10)/1.05*0.05 -> 99986.272 | N11: =+SUM(B11:M11) -> 1122867.7
A12: Less Commission | B12: =74777.47+81.27+13459.94+14.62+75491.77+13588.55+8936 -> 186349.62 | C12: =15723.86+87354.78+76474.32+13765.38+10.51+17552.51+3159 -> 214040.36 | D12: =102072.69+18373.08+73011.95+13142.19+33220.07+5979.61 -> 245799.59 | E12: =102083.85+18375.09+91226.64+16420.79+222.7+15852+2853 -> 247034.07 | F12: =78982.91+14216.9+104985.72+18897.43+425.06*1.18+31473.13+5665.16 -> 254722.82 | G12: =101805.27*1.18+255.3*1.18+92753.76*1.18 -> 229880.91 | H12: =100238.43*1.18+84483.25*1.18+195.61*1.18+52.98+14988.57*1.18 -> 235941.89 | I12: =102734.31*1.18+82613.38*1.18+621.42*1.18 -> 219443.55 | J12: =(90121+475.02)*1.18+84619.72*1.18+1125.48*1.18 -> 208082.64 | K12: =84607.34*1.18+669.3*1.18+84131*1.18 -> 199901.02 | L12: =105957.01+39933.45+50587.89+61.56+7187.99+11.08+209.47*1.18+9.37*1.18 -> 203997.21 | M12: =109163.03*1.18+60275.52*1.18+656.65*1.18+8.1*1.18+26068.42*1.18 -> 231482.63 | N12: =+SUM(B12:M12) -> 2676676.3
A13: Net Revenues from F&B Sales | B13: =B9+B10-B11-B12 -> 1500629.1 | C13: =C9+C10-C11-C12 -> 1517206.2 | D13: =D9+D10-D11-D12 -> 1708742.9 | E13: =E9+E10-E11-E12 -> 1729477.5 | F13: =F9+F10-F11-F12 -> 1746689.1 | G13: =G9+G10-G11-G12 -> 1706126.1 | H13: =H9+H10-H11-H12 -> 1669687.9 | I13: =I9+I10-I11-I12 -> 1606298.3 | ... M13: =M9+M10-M11-M12 -> 1768242.8 | N13: =sum(B13:M13) -> 19780678
A14: F&B Cost | B14: =+B3+B4-B5-B7 -> 393056.32 | C14: =+C3+C4-C5-C7 -> 407214.8 | D14: =+D3+D4-D5-D7 -> 454434.04 | E14: =+E3+E4-E5-E7 -> 471344.86 | F14: =+F3+F4-F5-F7 -> 482570.22 | G14: =+G3+G4-G5-G7 -> 447872.03 | H14: =+H3+H4-H5-H7 -> 439572.23 | I14: =+I3+I4-I5-I7 -> 412588.64 | ... M14: =+M3+M4-M5-M7 -> 486347.37 | N14: =sum(B14:M14) -> 5269298.3 | O14: =N14/$N$13 -> 0.26638614
A15: Electricity | B15: =25703.32+11328 -> 37031.32 | C15: =26432.9+11859 -> 38291.9 | D15: =27064+13452 -> 40516 | E15: =25394+12036 -> 37430 | F15: =26671.41+14691+0.59 -> 41363 | G15: =26643.35+12390+4060 -> 43093.35 | H15: =27499+12390 -> 39889 | I15: =24314.33+11328 -> 35642.33 | J15: =23234+12390 -> 35624 | K15: =22883+11505 -> 34388 | L15: =22434.29+4602+0.71 -> 27037 | M15: =29056.56+11328 -> 40384.56 | N15: =sum(B15:M15) -> 450690.46 | O15: =N15/$N$13 -> 0.022784379
A16: Telephone/Internet | B16: =352.82 -> 352.82 | C16: 353 | D16: 353 | E16: 353 | F16: =5246.28/6+352.82 -> 1227.2 | G16: =5246.28/6+352.82 -> 1227.2 | H16: =5246.28/6+352.82 -> 1227.2 | I16: =5246.28/6+352.82 -> 1227.2 | J16: =5246.28/6+352.82 -> 1227.2 | K16: =5246.28/6+352.82+2700/3 -> 2127.2 | L16: =5246.28/6+2700/3+352.82 -> 2127.2 | M16: =5246.28/6+2700/3+352.82 -> 2127.2 | N16: =sum(B16:M16) -> 13929.42 | O16: =N16/$N$13 -> 0.00070419327
A17: Gas | B17: =44421 -> 44421 | C17: 45671 | D17: =48314 -> 48314 | E17: 57924 | F17: 48809 | G17: 53340 | H17: 53917 | I17: 53690 | J17: 53340 | K17: 57225 | L17: =55589 -> 55589 | M17: =31500+12000+22964+12*3556 -> 109136 | N17: =sum(B17:M17) -> 681376 | O17: =N17/$N$13 -> 0.034446545
A18: Rent & Revenue Share | B18: 257211 | C18: =260414 -> 260414 | D18: 292761 | E18: =295744 -> 295744 | F18: 298888.58 | G18: 292054.55 | H18: =285338.4 -> 285338.4 | I18: 274779 | J18: 281658.63 | K18: 286931 | L18: =260307.42 -> 260307.42 | M18: =303032.91 -> 303032.91 | N18: =sum(B18:M18) -> 3389120.5 | O18: =N18/$N$13 -> 0.1713349
A19: Software | B19: 4764 | C19: 4764 | D19: 4764 | E19: 4764 | F19: 4764 | G19: 4764 | H19: 4764 | I19: 4764 | J19: 4764 | K19: =34000*1.18/12+4250*1.18/12 -> 3761.25 | L19: =34000*1.18/12+4250*1.18/12 -> 3761.25 | M19: =34000*1.18/12+4250*1.18/12 -> 3761.25 | N19: =sum(B19:M19) -> 54159.75 | O19: =N19/$N$13 -> 0.0027380129
A20: Staff Salary | B20: =210518.026+4000+104897/12 -> 223259.44 | C20: =234615+4000+104897/12 -> 247356.42 | D20: =165048+63283+14285+4000+104897/12 -> 255357.42 | E20: =244908+4000+104897/12 -> 257649.42 | F20: =4000+233985.42+104897/12 -> 246726.84 | G20: =239858+104897/12+4000 -> 252599.42 | H20: =104897/12+242358+4000 -> 255099.42 | I20: =104897/12+236586+4000 -> 249327.42 | J20: =104897/12+252023+4000 -> 264764.42 | K20: =104897/12+249794 -> 258535.42 | L20: =104897/12+4500+263286 -> 276527.42 | M20: =104897/12+4500+261095 -> 274336.42 | N20: =sum(B20:M20) -> 3061539.4 | O20: =N20/$N$13 -> 0.15477425
A21: AMC | B21: =2400+2478+22406/12 -> 6745.1667 | C21: =2400+2478+22406/12 -> 6745.1667 | D21: =2400+2478+22406/12 -> 6745.1667 | E21: =3070+2478+22406/12 -> 7415.1667 | F21: =22406/12+2478+2400 -> 6745.1667 | G21: =22406/12+6550+2478 -> 10895.167 | H21: =22406/12+2720+2478 -> 7065.1667 | I21: =22406/12+2720+2478 -> 7065.1667 | J21: =22406/12+2400+2478 -> 6745.1667 | K21: =22406/12+2400+2478 -> 6745.1667 | L21: =22406/12+1200+2478+5900 -> 11445.167 | M21: =22406/12+2850+2478 -> 7195.1667 | N21: =sum(B21:M21) -> 91552 | O21: =N21/$N$13 -> 0.0046283551
A22: Subscription | B22: =2124/3+9813/12+6372/12 -> 2056.75 | C22: =2124/3+9813/12+6372/12 -> 2056.75 | D22: =2124/3+9813/12+6372/12 -> 2056.75 | E22: =9813/12+6372/12+2124/3 -> 2056.75 | F22: =9813/12+6372/12+2124/3 -> 2056.75 | G22: =9813/12+6372/12+2124/3 -> 2056.75 | H22: =9813/12+6372/12+2124/3 -> 2056.75 | I22: =9813/12+6372/12+2124/3 -> 2056.75 | J22: =9813/12+6372/12+2124/3 -> 2056.75 | K22: =9813/12+6372/12+3271.32/3 -> 2439.19 | L22: =9813/12+6372/12+3271.32/3 -> 2439.19 | M22: =9813/12+6372/12+3271.32/3 -> 2439.19 | N22: =sum(B22:M22) -> 25828.32 | O22: =N22/$N$13 -> 0.0013057348
A23: Insurance Premium | B23: 0 | C23: =7081.71/12 -> 590.1425 | D23: =7081.71/12 -> 590.1425 | E23: =7081.71/12 -> 590.1425 | F23: =7081.71/12 -> 590.1425 | G23: =7081.71/12 -> 590.1425 | H23: =7081.71/12 -> 590.1425 | I23: =7081.71/12 -> 590.1425 | J23: =7081.71/12 -> 590.1425 | ... M23: =7081.71/12 -> 590.1425 | N23: =sum(B23:M23) -> 6491.5675 | O23: =N23/$N$13 -> 0.00032817721
A24: Repairs & Maintenance | B24: 240 | C24: 400 | D24: 12583 | E24: 280 | F24: 0 | G24: 6100 | H24: 18200 | I24: 16284 | J24: 0 | K24: 1641 | L24: 370 | M24: =1641+27399 -> 29040 | N24: =sum(B24:M24) -> 85138 | O24: =N24/$N$13 -> 0.0043040993
A25: Miscellaneous Expenses | B25: 11886.93 | C25: 19185.33 | D25: 13553 | E25: =26538.67 -> 26538.67 | F25: 4232.15 | G25: 10630.98 | H25: =16625 -> 16625 | I25: 13290.34 | J25: =28844-12390 -> 16454 | K25: 15749 | L25: 25926 | M25: =26746.39 -> 26746.39 | N25: =sum(B25:M25) -> 200817.79 | O25: =N25/$N$13 -> 0.01015222
A26: CAM | B26: =11800 -> 11800 | C26: =11800 -> 11800 | D26: 13570 | E26: 13570 | F26: 13570 | G26: 13570 | H26: 13570 | I26: 13570 | J26: 13570 | K26: 13570 | L26: 13570 | M26: 13570 | N26: =sum(B26:M26) -> 159300 | O26: =N26/$N$13 -> 0.0080533136
A27: HO+CK Cost | B27: =HO!D30 -> 304369.52 | C27: =HO!H30 -> 304881.45 | D27: =HO!L30 -> 339863.36 | E27: =HO!P30 -> 369926.68 | F27: =HO!D49 -> 342639.89 | G27: =HO!H49 -> 366946.96 | H27: =HO!L49 -> 321765.84 | I27: =HO!P49 -> 346553.2 | J27: =HO!D68 -> 308123.28 | K27: =HO!H68 -> 325396.75 | L27: =HO!L68 -> 318369.71 | M27: =HO!P68 -> 325656.84 | N27: =sum(B27:M27) -> 3974493.5 | O27: =N27/$N$13 -> 0.20092807
A28: Operating Expenses | B28: =+SUM(B14:B27) -> 1297194.3 | C28: =+SUM(C14:C27) -> 1349724 | D28: =+SUM(D14:D27) -> 1485460.9 | E28: =+SUM(E14:E27) -> 1545586.7 | F28: =+SUM(F14:F27) -> 1494182.9 | G28: =+SUM(G14:G27) -> 1505740.6 | H28: =+SUM(H14:H27) -> 1459680.1 | I28: =+SUM(I14:I27) -> 1431428.2 | ... M28: =+SUM(M14:M27) -> 1624363.4 | N28: =sum(B28:M28) -> 17463735 | O28: =N28/$N$7 -> 48.60259
A29: Store Level EBITDA | B29: =B13-B28 -> 203434.8 | C29: =C13-C28 -> 167482.27 | D29: =D13-D28 -> 223282.04 | E29: =E13-E28 -> 183890.81 | F29: =F13-F28 -> 252506.13 | G29: =G13-G28 -> 200385.51 | H29: =H13-H28 -> 210007.76 | I29: =I13-I28 -> 174870.07 | ... M29: =M13-M28 -> 143879.38 | N29: =sum(B29:M29) -> 2316942.6 | O29: =N29/$N$7 -> 6.448186
A30: Food Cost | B30: =(B14/B13) -> 0.2619277 | C30: =(C14/C13) -> 0.26839779 | D30: =(D14/D13) -> 0.26594641 | E30: =(E14/E13) -> 0.27253599 | F30: =(F14/F13) -> 0.27627712 | G30: =(G14/G13) -> 0.26250817 | H30: =(H14/H13) -> 0.2632661 | I30: =(I14/I13) -> 0.25685681 | ... M30: =(M14/M13) -> 0.27504558
B32: =B29+B27 -> 507804.31 | C32: =C29+C27 -> 472363.71 | D32: =D29+D27 -> 563145.4 | E32: =E29+E27 -> 553817.48 | F32: =F29+F27 -> 595146.02 | G32: =G29+G27 -> 567332.47 | H32: =H29+H27 -> 531773.6 | I32: =I29+I27 -> 521423.27 | ... M32: =M29+M27 -> 469536.21
B33: =B32/B13 -> 0.33839429 | C33: =C32/C13 -> 0.31133784 | D33: =D32/D13 -> 0.32956707 | E33: =E32/E13 -> 0.32022243 | F33: =F32/F13 -> 0.34072809 | G33: =G32/G13 -> 0.3325267 | H33: =H32/H13 -> 0.31848682 | I33: =I32/I13 -> 0.32461174 | ... M33: =M32/M13 -> 0.26553831

Sheet CSC
A1: Dosa Coffee - CSC | B1: 45748 | C1: 45778 | D1: 45809 | E1: 45839 | F1: 45870 | G1: 45901 | H1: 45931 | I1: 45962 | J1: 45992 | K1: 46023 | L1: 46054 | M1: 46082 | N1: FY 2025-26
A2: Food Cost Calculation
A3: Opening Stock | B3: 6692.81 | C3: =B7 -> 6009.21 | D3: =C7 -> 5755.48 | E3: =D7 -> 6864 | F3: =E7 -> 6390 | G3: =F7 -> 7428.76 | H3: =G7 -> 6649 | I3: =H7 -> 5443.36 | J3: =I7 -> 6083.05 | ... M3: =L7 -> 6841 | N3: =+SUM(J3:L3) -> 19781.97
A4: Purchases Food (Less Purchase Return) | B4: 46372 | C4: 50742 | D4: 46664 | E4: 47047 | F4: 42786 | G4: 31837.98 | H4: =34642.61 -> 34642.61 | I4: 38316.95 | J4: 32929 | K4: 31744 | L4: 25980 | M4: 29281.66 | N4: =sum(B4:M4) -> 458343.2
A5: Transferred Out | B5: 0 | C5: 0 | D5: 0 | E5: 0 | F5: 57 | G5: 95.54 | H5: 0 | I5: 0 | J5: 0 | K5: 0 | L5: 0 | M5: 0 | N5: =+SUM(J5:L5) -> 0
A6: Wastage & Date Expired | B6: 641.69 | C6: 758.1 | D6: 1213 | E6: 1152 | F6: 1405 | G6: 1565.78 | H6: 841.82 | I6: 112.3 | J6: 71 | K6: 859.06 | L6: 862 | M6: 695.24 | N6: =+SUM(J6:L6) -> 1792.06
A7: Closing Stock | B7: 6009.21 | C7: 5755.48 | D7: 6864 | E7: 6390 | F7: 7428.76 | G7: 6649 | H7: 5443.36 | I7: 6083.05 | J7: 6859 | K7: 6839.92 | L7: 6841 | M7: 6072.78 | N7: =sum(B7:M7) -> 77235.56
A9: Gross Revenue | B9: =145250.1*1.05 -> 152512.61 | C9: =161332.56*1.05 -> 169399.19 | D9: =163406.09*1.05 -> 171576.39 | E9: =138523.22*1.05 -> 145449.38 | F9: =127893.63*1.05 -> 134288.31 | G9: =97950.63*1.05 -> 102848.16 | H9: =114069.27*1.05 -> 119772.73 | I9: =116002.28*1.05 -> 121802.39 | J9: =106235.94*1.05 -> 111547.74 | K9: =96184.67*1.05 -> 100993.9 | L9: =80747.04*1.05 -> 84784.392 | M9: =87604*1.05 -> 91984.2 | N9: =+SUM(B9:M9) -> 1506959.4
A10: Catering & Fairs | B10: 0 | C10: 0 | N10: =+SUM(B10:M10) -> 0
A11: Less Tax | B11: =(B9+B10)/1.05*0.05 -> 7262.505 | C11: =(C9+C10)/1.05*0.05 -> 8066.628 | D11: =(D9+D10)/1.05*0.05 -> 8170.3045 | E11: =(E9+E10)/1.05*0.05 -> 6926.161 | F11: =(F9+F10)/1.05*0.05 -> 6394.6815 | G11: =(G9+G10)/1.05*0.05 -> 4897.5315 | H11: =(H9+H10)/1.05*0.05 -> 5703.4635 | I11: =(I9+I10)/1.05*0.05 -> 5800.114 | ... M11: =(M9+M10)/1.05*0.05 -> 4380.2 | N11: =+SUM(B11:M11) -> 71759.971
A12: Less Commission | N12: =+SUM(B12:M12) -> 0
A13: Net Revenues from F&B Sales | B13: =B9+B10-B11-B12 -> 145250.1 | C13: =C9+C10-C11-C12 -> 161332.56 | D13: =D9+D10-D11-D12 -> 163406.09 | E13: =E9+E10-E11-E12 -> 138523.22 | F13: =F9+F10-F11-F12 -> 127893.63 | G13: =G9+G10-G11-G12 -> 97950.63 | H13: =H9+H10-H11-H12 -> 114069.27 | I13: =I9+I10-I11-I12 -> 116002.28 | ... M13: =M9+M10-M11-M12 -> 87604 | N13: =sum(B13:M13) -> 1435199.4
A14: F&B Cost | B14: =+B3+B4-B5-B7 -> 47055.6 | C14: =+C3+C4-C5-C7 -> 50995.73 | D14: =+D3+D4-D5-D7 -> 45555.48 | E14: =+E3+E4-E5-E7 -> 47521 | F14: =+F3+F4-F5-F7 -> 41690.24 | G14: =+G3+G4-G5-G7 -> 32522.2 | H14: =+H3+H4-H5-H7 -> 35848.25 | I14: =+I3+I4-I5-I7 -> 37677.26 | ... M14: =+M3+M4-M5-M7 -> 30049.88 | N14: =sum(B14:M14) -> 458810.69 | O14: =N14/$N$13 -> 0.31968428
A15: Electricity | B15: 0 | C15: 0 | D15: 0 | E15: 0 | F15: 0 | G15: 0 | H15: 0 | I15: 0 | J15: 0 | K15: 0 | L15: 0 | M15: 0 | N15: =sum(B15:M15) -> 0 | O15: =N15/$N$13 -> 0
A16: Telephone/Internet | B16: =588.82 -> 588.82 | C16: =588.82 -> 588.82 | D16: 588.82 | E16: 588.82 | F16: 588.82 | G16: 588.82 | H16: 588.82 | I16: 588.82 | J16: 588.82 | K16: 588.82 | L16: 588.52 | M16: =588.52 -> 588.52 | N16: =sum(B16:M16) -> 7065.24 | O16: =N16/$N$13 -> 0.004922828
A17: Gas | B17: =3417+3417 -> 6834 | C17: =3383 -> 3383 | D17: 8243 | E17: 7049 | F17: 8020 | G17: 6476 | H17: 5670 | I17: 6300 | J17: 6930 | K17: 5985 | L17: 5432 | M17: =10000 -> 10000 | N17: =sum(B17:M17) -> 80322 | O17: =N17/$N$13 -> 0.055965741
A18: Rent & Revenue Share | N18: =sum(B18:M18) -> 0 | O18: =N18/$N$13 -> 0
A19: Software | B19: 3343 | C19: 3343 | D19: =3343 -> 3343 | E19: 3343 | F19: 3343 | G19: 3343 | H19: 3343 | I19: 3343 | J19: 3343 | K19: =34000*1.18/12 -> 3343.3333 | L19: =34000*1.18/12 -> 3343.3333 | M19: =34000*1.18/12 -> 3343.3333 | N19: =sum(B19:M19) -> 40117 | O19: =N19/$N$13 -> 0.027952213
A20: Staff Salary & Bonus | B20: =33098+19289/12 -> 34705.417 | C20: =33098+19289/12 -> 34705.417 | D20: =21513.67+10756.83+827.5+19289/12 -> 34705.417 | E20: =33098+19289/12 -> 34705.417 | F20: =33098+19289/12 -> 34705.417 | G20: =33098+19289/12 -> 34705.417 | H20: =19289/12+33098 -> 34705.417 | I20: =19289/12+33098 -> 34705.417 | J20: =19289/12+33099 -> 34706.417 | K20: =19289/12+33099 -> 34706.417 | L20: =19289/12+33099 -> 34706.417 | M20: =19289/12+33099 -> 34706.417 | N20: =sum(B20:M20) -> 416469 | O20: =N20/$N$13 -> 0.29018197
A21: AMC | B21: =4720/12 -> 393.33333 | C21: =4720/12 -> 393.33333 | D21: =4720/12 -> 393.33333 | E21: =4720/12 -> 393.33333 | F21: =4720/12 -> 393.33333 | G21: =4720/12 -> 393.33333 | H21: =4720/12 -> 393.33333 | I21: =4720/12 -> 393.33333 | ... M21: =4720/12 -> 393.33333 | N21: =sum(B21:M21) -> 4720 | O21: =N21/$N$13 -> 0.0032887416
A22: Subscription | N22: =sum(B22:M22) -> 0 | O22: =N22/$N$13 -> 0
A23: Insurance Premium | B23: 0 | C23: 352.81 | D23: 352.81 | E23: 352.81 | F23: 352.81 | G23: 352.81 | H23: 352.81 | I23: 352.81 | J23: 352.81 | K23: 352.81 | L23: 352.81 | M23: 352.81 | N23: =sum(B23:M23) -> 3880.91 | O23: =N23/$N$13 -> 0.0027040911
A24: Repairs & Maintenance | B24: 0 | C24: 0 | D24: 200 | E24: 10000 | F24: 0 | G24: 0 | H24: 0 | I24: 460 | J24: 0 | K24: 0 | L24: 0 | M24: 0 | N24: =sum(B24:M24) -> 10660 | O24: =N24/$N$13 -> 0.0074275392
A25: Miscellaneous Expenses | B25: 2884 | C25: 490 | D25: 490 | E25: 6051 | F25: 720 | G25: 8330 | H25: 530 | I25: 1650 | J25: 5450 | K25: 0 | L25: 0 | M25: 7206 | N25: =sum(B25:M25) -> 33801 | O25: =N25/$N$13 -> 0.023551431
A26: CAM | N26: =sum(B26:M26) -> 0 | O26: =N26/$N$13 -> 0
A27: HO+CK Cost | B27: =HO!D33 -> 29460.78 | C27: =HO!H33 -> 32419.656 | D27: =HO!L33 -> 32500.935 | E27: =HO!P33 -> 29629.431 | F27: =HO!D52 -> 25088.3 | G27: =HO!H52 -> 21066.841 | H27: =HO!L52 -> 21982.308 | I27: =HO!P52 -> 25027.084 | J27: =HO!D71 -> 20004.473 | K27: =HO!H71 -> 18746.572 | L27: =HO!L71 -> 16893.72 | M27: =HO!P71 -> 16134.007 | N27: =sum(B27:M27) -> 288954.11 | O27: =N27/$N$13 -> 0.20133377
A28: Operating Expenses | B28: =+SUM(B14:B27) -> 125264.95 | C28: =+SUM(C14:C27) -> 126671.77 | D28: =+SUM(D14:D27) -> 126372.8 | E28: =+SUM(E14:E27) -> 139633.81 | F28: =+SUM(F14:F27) -> 114901.92 | G28: =+SUM(G14:G27) -> 107778.42 | H28: =+SUM(H14:H27) -> 103413.94 | I28: =+SUM(I14:I27) -> 110497.72 | ... M28: =+SUM(M14:M27) -> 102774.3 | N28: =sum(B28:M28) -> 1344799.9 | O28: =N28/$N$13 -> 0.9370126
A29: Store Level EBITDA | B29: =B13-B28 -> 19985.15 | C29: =C13-C28 -> 34660.794 | D29: =D13-D28 -> 37033.295 | E29: =E13-E28 -> -1110.5913 | F29: =F13-F28 -> 12991.71 | G29: =G13-G28 -> -9827.7909 | H29: =H13-H28 -> 10655.332 | I29: =I13-I28 -> 5504.5559 | ... M29: =M13-M28 -> -15170.3 | N29: =sum(B29:M29) -> 90399.481 | O29: =N29/$N$13 -> 0.062987401
A30: Food Cost | B30: =(B14/B13) -> 0.3239626 | C30: =(C14/C13) -> 0.31609075 | D30: =(D14/D13) -> 0.27878692 | E30: =(E14/E13) -> 0.3430544 | F30: =(F14/F13) -> 0.32597589 | G30: =(G14/G13) -> 0.33202645 | H30: =(H14/H13) -> 0.31426737 | I30: =(I14/I13) -> 0.32479758 | ... M30: =(M14/M13) -> 0.3430195
B32: =B29+B27 -> 49445.93 | C32: =C29+C27 -> 67080.45 | D32: =D29+D27 -> 69534.23 | E32: =E29+E27 -> 28518.84 | F32: =F29+F27 -> 38080.01 | G32: =G29+G27 -> 11239.05 | H32: =H29+H27 -> 32637.64 | I32: =I29+I27 -> 30531.64 | ... M32: =M29+M27 -> 963.70667
B33: =B32/B13 -> 0.34041925 | C33: =C32/C13 -> 0.41578991 | D33: =D32/D13 -> 0.42553022 | E33: =E32/E13 -> 0.20587769 | F33: =F32/F13 -> 0.29774751 | G33: =G32/G13 -> 0.11474199 | H33: =H32/H13 -> 0.28612123 | I33: =I32/I13 -> 0.26319862 | ... M33: =M32/M13 -> 0.011000715

Sheet Technopolis
A1: Dosa Coffee - Technopolis | B1: 45748 | C1: 45778 | D1: 45809 | E1: 45839 | F1: 45870 | G1: 45901 | H1: 45931 | I1: 45962 | J1: 45992 | K1: 46023 | L1: 46054 | M1: 46082 | N1: FY 2025-26
A2: Food Cost Calculation
A3: Opening Stock | B3: 1971.69 | C3: =B7 -> 1699.02 | D3: =C7 -> 1426.26 | E3: =D7 -> 2406 | F3: =E7 -> 3088 | G3: =F7 -> 2849 | H3: =G7 -> 2437 | I3: =H7 -> 2546.3 | J3: =I7 -> 2564.97 | ... M3: =L7 -> 1914.49 | N3: =+SUM(J3:L3) -> 6703.24
A4: Purchases Food (Less Purchase Return) | B4: 24304 | C4: 22731 | D4: 22465 | E4: 22659 | F4: 22044 | G4: 18016 | H4: =22101.19 -> 22101.19 | I4: 24235.9 | J4: 17246 | K4: 24612 | L4: 26812.58 | M4: 25350.58 | N4: =sum(B4:M4) -> 272577.25
A5: Transferred Out | B5: 0 | C5: 0 | D5: 0 | E5: 0 | F5: 0 | G5: 0 | H5: 149.53 | I5: 0 | J5: 0 | K5: 0 | L5: 0 | M5: 0 | N5: =+SUM(J5:L5) -> 0
A6: Wastage & Date Expired | B6: 3772.86 | C6: 4382.8 | D6: 3785 | E6: 2432.51 | F6: 645 | G6: 332.11 | H6: 759.63 | I6: 456.81 | J6: 2667 | K6: 912.8 | L6: 636.29 | M6: 552.79 | N6: =+SUM(J6:L6) -> 4216.09
A7: Closing Stock | B7: 1699.02 | C7: 1426.26 | D7: 2406 | E7: 3088 | F7: 2849 | G7: 2437 | H7: 2546.3 | I7: 2564.97 | J7: 1930 | K7: 2208.27 | L7: 1914.49 | M7: 1603.29 | N7: =sum(B7:M7) -> 26672.6
A9: Gross Revenue | B9: =42175.85*1.05 -> 44284.643 | C9: =43678.77*1.05 -> 45862.709 | D9: =34095.21*1.05 -> 35799.971 | E9: =55783.63*1.05 -> 58572.812 | F9: =70880.7*1.05 -> 74424.735 | G9: =58299.89*1.05 -> 61214.885 | H9: =76295.29*1.05 -> 80110.054 | I9: =79590.38*1.05 -> 83569.899 | J9: =52847.5*1.05 -> 55489.875 | K9: =76912.53*1.05 -> 80758.156 | L9: =90761*1.05 -> 95299.05 | M9: =81446.28*1.05 -> 85518.594 | N9: =+SUM(B9:M9) -> 800905.38
A10: Catering & Fairs | B10: 0 | C10: 0 | D10: 0 | E10: 0 | F10: 0 | G10: 0 | N10: =+SUM(B10:M10) -> 0
A11: Less Tax | B11: =(B9+B10)/1.05*0.05 -> 2108.7925 | C11: =(C9+C10)/1.05*0.05 -> 2183.9385 | D11: =(D9+D10)/1.05*0.05 -> 1704.7605 | E11: =(E9+E10)/1.05*0.05 -> 2789.1815 | F11: =(F9+F10)/1.05*0.05 -> 3544.035 | G11: =(G9+G10)/1.05*0.05 -> 2914.9945 | H11: =(H9+H10)/1.05*0.05 -> 3814.7645 | I11: =(I9+I10)/1.05*0.05 -> 3979.519 | ... M11: =(M9+M10)/1.05*0.05 -> 4072.314 | N11: =+SUM(B11:M11) -> 38138.351
A12: Less Commission | B12: 0 | C12: 0 | N12: =+SUM(B12:M12) -> 0
A13: Net Revenues from F&B Sales | B13: =B9+B10-B11-B12 -> 42175.85 | C13: =C9+C10-C11-C12 -> 43678.77 | D13: =D9+D10-D11-D12 -> 34095.21 | E13: =E9+E10-E11-E12 -> 55783.63 | F13: =F9+F10-F11-F12 -> 70880.7 | G13: =G9+G10-G11-G12 -> 58299.89 | H13: =H9+H10-H11-H12 -> 76295.29 | I13: =I9+I10-I11-I12 -> 79590.38 | ... M13: =M9+M10-M11-M12 -> 81446.28 | N13: =sum(B13:M13) -> 762767.03 | O13: =N13/$N$7 -> 28.597401
A14: F&B Cost | B14: =+B3+B4-B5-B7 -> 24576.67 | C14: =+C3+C4-C5-C7 -> 23003.76 | D14: =+D3+D4-D5-D7 -> 21485.26 | E14: =+E3+E4-E5-E7 -> 21977 | F14: =+F3+F4-F5-F7 -> 22283 | G14: =+G3+G4-G5-G7 -> 18428 | H14: =+H3+H4-H5-H7 -> 21842.36 | I14: =+I3+I4-I5-I7 -> 24217.23 | ... M14: =+M3+M4-M5-M7 -> 25661.78 | N14: =sum(B14:M14) -> 272796.12 | O14: =N14/$N$7 -> 10.227579
A15: Electricity | B15: =3383.54 -> 3383.54 | C15: 3711 | D15: 3418 | E15: 3862 | F15: 4489.84 | G15: 4931 | H15: 4923.5 | I15: 4601 | J15: 4500 | K15: 2873 | L15: 4172.87 | M15: 4500 | N15: =sum(B15:M15) -> 49365.75 | O15: =N15/$N$7 -> 1.8508038
A16: Telephone/Internet | B16: =588.82 -> 588.82 | C16: =588.82 -> 588.82 | D16: =588.82 -> 588.82 | E16: =588.82 -> 588.82 | F16: =588.82 -> 588.82 | G16: =588.82 -> 588.82 | H16: =588.82 -> 588.82 | I16: =588.82 -> 588.82 | ... K16: =588.82 -> 588.82 | L16: 588.52 | M16: 588.52 | N16: =sum(B16:M16) -> 7065.24 | O16: =N16/$N$7 -> 0.26488756
A17: Gas | B17: 879 | C17: 879 | D17: 879 | E17: =879+879+879 -> 2637 | F17: 879 | G17: 879 | H17: 879 | I17: 879 | J17: =879+879 -> 1758 | K17: 879 | L17: 879 | M17: 879 | N17: =sum(B17:M17) -> 13185 | O17: =N17/$N$7 -> 0.49432751
A18: Rent & Revenue Share | B18: 7465 | C18: =7683.94 -> 7683.94 | D18: 6034.86 | E18: 9870.33 | F18: 12545.89 | G18: 10319.08 | H18: 13504 | I18: 14087.5 | J18: 9354 | K18: =13613.52 -> 13613.52 | L18: =16064.89 -> 16064.89 | M18: 14450 | N18: =sum(B18:M18) -> 134993.01 | O18: =N18/$N$7 -> 5.0611118
A19: Software | B19: 3343 | C19: 3343 | D19: 3343 | E19: 3343 | F19: 3343 | G19: 3343 | H19: =3343 -> 3343 | I19: =3343 -> 3343 | J19: =3343 -> 3343 | K19: =3343 -> 3343 | L19: =34000*1.18/12 -> 3343.3333 | M19: =34000*1.18/12 -> 3343.3333 | N19: =sum(B19:M19) -> 40116.667 | O19: =N19/$N$7 -> 1.5040404
A20: Staff Salary | B20: =16000 -> 16000 | C20: 16000 | D20: =10400+5200+400 -> 16000 | E20: 0 | F20: =16330.65 -> 16330.65 | G20: 18750 | H20: 18750 | I20: =18750 -> 18750 | J20: =19557 -> 19557 | K20: 18751 | L20: =18751 -> 18751 | M20: =18751 -> 18751 | N20: =sum(B20:M20) -> 196390.65 | O20: =N20/$N$7 -> 7.3630111
A21: AMC | B21: =7080/12 -> 590 | C21: =7080/12 -> 590 | D21: =7080/12 -> 590 | E21: =7080/12 -> 590 | F21: =7080/12 -> 590 | G21: =7080/12 -> 590 | H21: =7080/12 -> 590 | I21: =7080/12 -> 590 | ... M21: =7080/12 -> 590 | N21: =sum(B21:M21) -> 7080 | O21: =N21/$N$7 -> 0.26544094
A22: Subscription | B22: 0 | C22: 0 | D22: 0
A23: Insurance Premium | B23: 0 | C23: 0 | D23: 0
A24: Repairs & Maintenance | B24: 0 | C24: 0 | D24: 0 | F24: 0 | G24: 0 | H24: 0 | I24: 0 | J24: 0 | K24: 0 | L24: 0 | M24: 0 | N24: =sum(B24:M24) -> 0 | O24: =N24/$N$7 -> 0
A25: Miscellaneous Expenses | B25: 6.3 | C25: 46.8 | D25: 63.32 | E25: 83 | F25: 88 | G25: 1550 | H25: 98.43 | I25: 107.2 | J25: 879 | K25: 1466.67 | L25: 1376.4 | M25: =6410 -> 6410 | N25: =sum(B25:M25) -> 12175.12 | O25: =N25/$N$7 -> 0.45646544
A26: CAM | B26: 0 | C26: 0 | D26: 0 | E26: 0 | F26: 0 | G26: 0 | H26: 0 | I26: 0 | J26: 0 | K26: 0 | L26: 0 | M26: 0 | N26: =sum(B26:M26) -> 0 | O26: =N26/$N$7 -> 0
A27: HO+CK Cost | B27: =HO!D35 -> 8554.4412 | C27: =HO!H35 -> 8777.2159 | D27: =HO!L35 -> 6781.4254 | E27: =HO!P35 -> 11931.842 | F27: =HO!D54 -> 13904.338 | G27: =HO!H54 -> 12538.914 | H27: =HO!L54 -> 14702.878 | I27: =HO!P54 -> 17171.345 | J27: =HO!D73 -> 9951.3066 | K27: =HO!H73 -> 14990.396 | L27: =HO!L73 -> 18988.819 | M27: =HO!P73 -> 14999.941 | N27: =sum(B27:M27) -> 153292.86 | O27: =N27/$N$7 -> 5.7472036
A28: Operating Expenses | B28: =+SUM(B14:B27) -> 65386.771 | C28: =+SUM(C14:C27) -> 64623.536 | D28: =+SUM(D14:D27) -> 59183.685 | E28: =+SUM(E14:E27) -> 54882.992 | F28: =+SUM(F14:F27) -> 75042.538 | G28: =+SUM(G14:G27) -> 71917.814 | H28: =+SUM(H14:H27) -> 79221.988 | I28: =+SUM(I14:I27) -> 84335.095 | ... M28: =+SUM(M14:M27) -> 90173.574 | N28: =sum(B28:M28) -> 886460.42 | O28: =N28/$N$7 -> 33.234871
A29: Store Level EBITDA | B29: =B13-B28 -> -23210.921 | C29: =C13-C28 -> -20944.766 | D29: =D13-D28 -> -25088.475 | E29: =E13-E28 -> 900.63759 | F29: =F13-F28 -> -4161.8381 | G29: =G13-G28 -> -13617.924 | H29: =H13-H28 -> -2926.6981 | I29: =I13-I28 -> -4744.7147 | ... M29: =M13-M28 -> -8727.2945 | N29: =sum(B29:M29) -> -123693.39 | O29: =N29/$N$7 -> -4.6374703
A30: Food Cost | B30: =(B14/B13) -> 0.58271902 | C30: =(C14/C13) -> 0.52665769 | D30: =(D14/D13) -> 0.63015479 | E30: =(E14/E13) -> 0.39396862 | F30: =(F14/F13) -> 0.31437331 | G30: =(G14/G13) -> 0.31608979 | H30: =(H14/H13) -> 0.28628714 | I30: =(I14/I13) -> 0.30427333 | ... M30: =(M14/M13) -> 0.31507615
B32: =B29+B27 -> -14656.48 | C32: =C29+C27 -> -12167.55 | D32: =D29+D27 -> -18307.05 | E32: =E29+E27 -> 12832.48 | F32: =F29+F27 -> 9742.5 | G32: =G29+G27 -> -1079.01 | H32: =H29+H27 -> 11776.18 | I32: =I29+I27 -> 12426.63 | ... M32: =M29+M27 -> 6272.6467
B33: =B32/B13 -> -0.34750882 | C33: =C32/C13 -> -0.27856897 | D33: =D32/D13 -> -0.53693906 | E33: =E32/E13 -> 0.23004025 | F33: =F32/F13 -> 0.13744926 | G33: =G32/G13 -> -0.018507925 | H33: =H32/H13 -> 0.15435003 | I33: =I32/I13 -> 0.15613231 | ... M33: =M32/M13 -> 0.077015754

Sheet Forum Rangoli
A1: Dosa Coffee - Forum Rangoli | B1: 45748 | C1: 45778 | D1: 45809 | E1: 45839 | F1: 45870 | G1: 45901 | H1: 45931 | I1: 45962 | J1: 45992 | K1: 46023 | L1: 46054 | M1: 46082 | N1: FY 2025-26
A2: Food Cost Calculation
A3: Opening Stock | B3: 24583.34 | C3: =B7 -> 37490.05 | D3: =C7 -> 36305.88 | E3: =D7 -> 41022 | F3: =E7 -> 42739 | G3: =F7 -> 39413.25 | H3: =G7 -> 45539 | I3: =H7 -> 44702.52 | J3: =I7 -> 34880.19 | ... M3: =L7 -> 39477.37 | N3: =+SUM(J3:L3) -> 125008.19
A4: Purchases Food (Less Purchase Return) | B4: 229481.45 | C4: 249563.5 | D4: 234649.01 | E4: 272404.76 | F4: 282590 | G4: =310944.01 -> 310944.01 | H4: 276970.91 | I4: 251370.94 | J4: 284488 | K4: 270863 | L4: 244541.63 | M4: 338863.45 | N4: =sum(B4:M4) -> 3246730.7
A5: Transferred Out | B5: 196.1 | C5: 74.74 | D5: 76.33 | E5: 269 | F5: 0 | G5: 0 | H5: 77.19 | I5: 31.49 | J5: 0 | K5: 1230 | L5: 156.72 | M5: 0 | N5: =+SUM(J5:L5) -> 1386.72
A6: Wastage & Date Expired | B6: 8809.58 | C6: 8805.22 | D6: 8946 | E6: 7132 | F6: 8262.17 | G6: 8810 | H6: 8240.9 | I6: 8700.84 | J6: 11035 | K6: 11090.11 | L6: 9163.72 | M6: 12419.99 | N6: =+SUM(J6:L6) -> 31288.83
A7: Closing Stock | B7: 37490.05 | C7: 36305.88 | D7: 41022 | E7: 42739 | F7: 39413.25 | G7: 45539 | H7: 44702.52 | I7: 34880.19 | J7: 48588 | K7: 41540 | L7: 39477.37 | M7: 47968.29 | N7: =sum(B7:M7) -> 499665.55
A9: Gross Revenue | B9: =980237.72*1.05+11477.56*1.05 -> 1041301 | C9: =1171261.08*1.05+12535.57*1.05 -> 1242986.5 | D9: =1079116.95*1.05+15056.56*1.05 -> 1148882.2 | E9: =1075676.2*1.05+14044.69*1.05 -> 1144206.9 | F9: =14667.21*1.05+1191600.952*1.05 -> 1266581.6 | G9: =1306926.76*1.05 -> 1372273.1 | H9: =1083845.96*1.05+16540.36*1.05 -> 1155405.6 | I9: =974763.81*1.05+14969.16*1.05 -> 1039219.6 | J9: =1077287.23*1.05+13276.35*1.05 -> 1145091.8 | K9: =1048867.26*1.05+12227.29*1.05 -> 1114149.3 | L9: =907389.02*1.05+15211.92*1.05 -> 968730.99 | M9: =1311260.04*1.05+20674.47*1.05 -> 1398531.2 | N9: =+SUM(B9:M9) -> 14037360
A10: Catering & Fairs | B10: 0 | C10: 0 | D10: 0 | E10: 0 | F10: 0 | G10: 0 | H10: 0 | I10: 0 | J10: 0 | K10: 0 | L10: 0 | M10: 0 | N10: =+SUM(B10:M10) -> 0
A11: Less Tax | B11: =(B9+B10)/1.05*0.05 -> 49585.764 | C11: =(C9+C10)/1.05*0.05 -> 59189.832 | D11: =(D9+D10)/1.05*0.05 -> 54708.675 | E11: =(E9+E10)/1.05*0.05 -> 54486.045 | F11: =(F9+F10)/1.05*0.05 -> 60313.408 | G11: =(G9+G10)/1.05*0.05 -> 65346.338 | H11: =(H9+H10)/1.05*0.05 -> 55019.316 | I11: =(I9+I10)/1.05*0.05 -> 49486.649 | ... M11: =(M9+M10)/1.05*0.05 -> 66596.726 | N11: =+SUM(B11:M11) -> 668445.71
A12: Less Commission | B12: =26018.21+182.91+4683.28+32.92+13532.05+2435.8+1183 -> 48068.17 | C12: =5186.7+28815.01+10329.2+1859.24+14.08+2659.02+478.62 -> 49341.87 | D12: =34544.96+6218.09+9398.62+1691.78+3679.79+662.38 -> 56195.62 | E12: =32489.29+5848.07+13693.91+2464.93+31.97+2949+530.93 -> 58008.1 | F12: =8697.72+1565.6+34297.06+6173.47+92.11+3928.12+707.06 -> 55461.14 | G12: =33028.64*1.18+9799.67*1.18 -> 50537.406 | H12: =38406*1.18+9557.74*1.18+49.34*1.18+3295.59*1.18 -> 60544.231 | I12: =34964.27*1.18+7353.96*1.18+121.3*1.18 -> 50078.645 | J12: =(30508.52+584.19)*1.18+10398.13*1.18+49.18*1.18 -> 49017.224 | K12: =28591.75*1.18+30.29*1.18+9333.36*1.18 -> 44787.372 | L12: =41452.81+4518.09+6116.22+813.24+52.07*1.18 -> 52961.803 | M12: =48429.34*1.18+9218.24*1.18+50.55*1.18+81.25*1.18+6217.69*1.18 -> 75516.543 | N12: =+SUM(B12:M12) -> 650518.12
A13: Net Revenues from F&B Sales | B13: =B9+B10-B11-B12 -> 943647.11 | C13: =C9+C10-C11-C12 -> 1134454.8 | D13: =D9+D10-D11-D12 -> 1037977.9 | E13: =E9+E10-E11-E12 -> 1031712.8 | F13: =F9+F10-F11-F12 -> 1150807 | G13: =G9+G10-G11-G12 -> 1256389.4 | H13: =H9+H10-H11-H12 -> 1039842.1 | I13: =I9+I10-I11-I12 -> 939654.32 | ... M13: =M9+M10-M11-M12 -> 1256418 | N13: =sum(B13:M13) -> 12718396
A14: F&B Cost | B14: =+B3+B4-B5-B7 -> 216378.64 | C14: =+C3+C4-C5-C7 -> 250672.93 | D14: =+D3+D4-D5-D7 -> 229856.56 | E14: =+E3+E4-E5-E7 -> 270418.76 | F14: =+F3+F4-F5-F7 -> 285915.75 | G14: =+G3+G4-G5-G7 -> 304818.26 | H14: =+H3+H4-H5-H7 -> 277730.2 | I14: =+I3+I4-I5-I7 -> 261161.78 | ... M14: =+M3+M4-M5-M7 -> 330372.53 | N14: =sum(B14:M14) -> 3221234.1 | O14: =N14/$N$13 -> 0.25327362
A15: Electricity | B15: 53641 | C15: 52715 | D15: 50548 | E15: 55148 | F15: 60856 | G15: 62886 | H15: 57288 | I15: 53691 | J15: =57093 -> 57093 | K15: =54827 -> 54827 | L15: =47209 -> 47209 | M15: =60000 -> 60000 | N15: =sum(B15:M15) -> 665902 | O15: =N15/$N$13 -> 0.052357388
A16: Telephone/Internet | B16: =800+352.82 -> 1152.82 | C16: =800+352.82 -> 1152.82 | D16: =800+352.82 -> 1152.82 | E16: =800+352.82 -> 1152.82 | F16: =800+352.82 -> 1152.82 | G16: =800+352.82 -> 1152.82 | H16: =800+352.82 -> 1152.82 | I16: =352.82+800 -> 1152.82 | J16: =800+352.82 -> 1152.82 | K16: =800+352.82 -> 1152.82 | L16: =800+352.82 -> 1152.82 | M16: =800+352.82 -> 1152.82 | N16: =sum(B16:M16) -> 13833.84 | O16: =N16/$N$13 -> 0.0010877032
A17: Gas | N17: =sum(B17:M17) -> 0 | O17: =N17/$N$13 -> 0
A18: Rent & Revenue Share | B18: 138636 | C18: 167965 | D18: 152324 | E18: =151195 -> 151195 | F18: 169761 | G18: =186432 -> 186432 | H18: =152183 -> 152183 | I18: =138048 -> 138048 | J18: 153569 | K18: =150291 -> 150291 | L18: =126666 -> 126666 | M18: =M13*0.1478 -> 185698.58 | N18: =sum(B18:M18) -> 1872768.6 | O18: =N18/$N$13 -> 0.1472488
A19: Software | B19: 5767 | C19: 5767 | D19: =69207/12 -> 5767.25 | E19: =69207/12 -> 5767.25 | F19: =69207/12 -> 5767.25 | G19: =69207/12 -> 5767.25 | H19: =69207/12 -> 5767.25 | I19: =69207/12 -> 5767.25 | J19: =69207/12 -> 5767.25 | K19: =69207/12 -> 5767.25 | ... M19: =69207/12 -> 5767.25 | N19: =sum(B19:M19) -> 69206.5 | O19: =N19/$N$13 -> 0.0054414487
A20: Staff Salary & Bonus | B20: =198014.35+87602/12 -> 205314.52 | C20: =187742+87602/12 -> 195042.17 | D20: =117024.5+53412+3674+87602/12 -> 181410.67 | E20: =182290.07+87602/12 -> 189590.24 | F20: =192497.49++87602/12 -> 199797.66 | G20: =191585.34+87602/12 -> 198885.51 | H20: =87602/12+186033+4500 -> 197833.17 | I20: =87602/12+170127+3672 -> 181099.17 | J20: =87602/12+192885+3588 -> 203773.17 | K20: =87602/12+3540+208277 -> 219117.17 | L20: =87602/12+3700+199785 -> 210785.17 | M20: =87602/12+3700+200573 -> 211573.17 | N20: =sum(B20:M20) -> 2394221.8 | O20: =N20/$N$13 -> 0.18824872
A21: AMC | B21: =2832+13400/12 -> 3948.6667 | C21: =2832+3457+13400/12 -> 7405.6667 | D21: =2832+3457+13400/12 -> 7405.6667 | E21: =2832+3457+13400/12 -> 7405.6667 | F21: =2832+3457+13400/12 -> 7405.6667 | G21: =13400/12+3457+2832 -> 7405.6667 | H21: =13400/12+3457+2832 -> 7405.6667 | I21: =13400/12+3457+2832 -> 7405.6667 | J21: =13400/12+2832+3457 -> 7405.6667 | K21: =13400/12+3457+2832 -> 7405.6667 | L21: =13400/12+3115+3457 -> 7688.6667 | M21: =13400/12+3457+3115 -> 7688.6667 | N21: =sum(B21:M21) -> 85977 | O21: =N21/$N$13 -> 0.0067600506
A22: Subscription | B22: =2124/3+9813/12+6372/12+3457 -> 5513.75 | C22: =2124/3+9813/12+6372/12+3457 -> 5513.75 | D22: =2124/3+9813/12+6372/12 -> 2056.75 | E22: =9813/12+6372/12+2124/3 -> 2056.75 | F22: =9813/12+6372/12+2124/3 -> 2056.75 | G22: =9813/12+6372/12+2124/3 -> 2056.75 | H22: =9813/12+6372/12+2124/3 -> 2056.75 | I22: =9813/12+6372/12+2124/3 -> 2056.75 | J22: =9813/12+6372/12+2124/3 -> 2056.75 | K22: =9813/12+6372/12+3271.32/3 -> 2439.19 | L22: =9813/12+6372/12+3271.32/3 -> 2439.19 | M22: =9813/12+6372/12+3271.32/3 -> 2439.19 | N22: =sum(B22:M22) -> 32742.32 | O22: =N22/$N$13 -> 0.0025744064
A23: Insurance Premium | B23: 0 | C23: =11895.27/12 -> 991.2725 | D23: =11895.27/12 -> 991.2725 | E23: =11895.27/12 -> 991.2725 | F23: =11895.27/12 -> 991.2725 | G23: =11895.27/12 -> 991.2725 | H23: =11895.27/12 -> 991.2725 | I23: =11895.27/12 -> 991.2725 | J23: =11895.27/12 -> 991.2725 | ... M23: =11895.27/12 -> 991.2725 | N23: =sum(B23:M23) -> 10903.997 | O23: =N23/$N$13 -> 0.00085734062
A24: Repairs & Maintenance | B24: =219 -> 219 | C24: 4000 | D24: =2325 -> 2325 | E24: =15000+20000 -> 35000 | F24: 7945 | G24: 35640 | H24: =1270 -> 1270 | I24: 0 | J24: 15100 | K24: 550 | L24: 0 | M24: =19634 -> 19634 | N24: =sum(B24:M24) -> 121683 | O24: =N24/$N$13 -> 0.0095674801
A25: Miscellaneous Expenses | B25: =2489.46 -> 2489.46 | C25: 4246.18 | D25: =17259 -> 17259 | E25: 12666 | F25: 20735.97 | G25: 14422.8 | H25: 13899.76 | I25: 7681.28 | J25: 34504 | K25: 7878.67 | L25: 12666 | M25: =13171 -> 13171 | N25: =sum(B25:M25) -> 161620.12 | O25: =N25/$N$13 -> 0.012707587
A26: CAM | B26: =84370 -> 84370 | C26: =84370 -> 84370 | D26: =84370 -> 84370 | E26: =84370 -> 84370 | F26: 84370 | G26: =84370 -> 84370 | H26: =84370 -> 84370 | I26: 84370 | J26: 84370 | K26: 84370 | L26: 84370 | M26: 84370 | N26: =sum(B26:M26) -> 1012440 | O26: =N26/$N$13 -> 0.079604378
A27: HO+CK Cost | B27: =HO!D32 -> 191398.01 | C27: =HO!H32 -> 227967.83 | D27: =HO!L32 -> 206450.4 | E27: =HO!P32 -> 220678.26 | F27: =HO!D51 -> 225748.47 | G27: =HO!H51 -> 270219.34 | H27: =HO!L51 -> 200388.14 | I27: =HO!P51 -> 202727.12 | J27: =HO!D70 -> 196125.59 | K27: =HO!H70 -> 198080.17 | L27: =HO!L70 -> 181944.01 | M27: =HO!P70 -> 231394.18 | N27: =sum(B27:M27) -> 2553121.5 | O27: =N27/$N$13 -> 0.20074242
A28: Operating Expenses | B28: =+SUM(B14:B27) -> 908828.86 | C28: =+SUM(C14:C27) -> 1007809.6 | D28: =+SUM(D14:D27) -> 941917.38 | E28: =+SUM(E14:E27) -> 1036440 | F28: =+SUM(F14:F27) -> 1072503.6 | G28: =+SUM(G14:G27) -> 1175047.7 | H28: =+SUM(H14:H27) -> 1002336 | I28: =+SUM(I14:I27) -> 946152.1 | ... M28: =+SUM(M14:M27) -> 1154252.7 | N28: =sum(B28:M28) -> 12215655 | O28: =N28/$N$13 -> 0.96047133
A29: Store Level EBITDA | B29: =B13-B28 -> 34818.248 | C29: =C13-C28 -> 126645.16 | D29: =D13-D28 -> 96060.507 | E29: =E13-E28 -> -4727.2262 | F29: =F13-F28 -> 78303.412 | G29: =G13-G28 -> 81341.688 | H29: =H13-H28 -> 37506.061 | I29: =I13-I28 -> -6497.7787 | ... M29: =M13-M28 -> 102165.31 | N29: =sum(B29:M29) -> 502741.23 | O29: =N29/$N$13 -> 0.039528666
A30: Food Cost | B30: =(B14/B13) -> 0.22930038 | C30: =(C14/C13) -> 0.22096335 | D30: =(D14/D13) -> 0.22144649 | E30: =(E14/E13) -> 0.26210663 | F30: =(F14/F13) -> 0.24844804 | G30: =(G14/G13) -> 0.24261449 | H30: =(H14/H13) -> 0.26708882 | I30: =(I14/I13) -> 0.27793389 | ... M30: =(M14/M13) -> 0.26294795
B32: =B29+B27 -> 226216.26 | C32: =C29+C27 -> 354612.99 | D32: =D29+D27 -> 302510.9 | E32: =E29+E27 -> 215951.03 | F32: =F29+F27 -> 304051.89 | G32: =G29+G27 -> 351561.03 | H32: =H29+H27 -> 237894.2 | I32: =I29+I27 -> 196229.34 | ... M32: =M29+M27 -> 333559.5
B33: =B32/B13 -> 0.23972548 | C33: =C32/C13 -> 0.31258451 | D33: =D32/D13 -> 0.29144253 | E33: =E32/E13 -> 0.20931313 | F33: =F32/F13 -> 0.26420753 | G33: =G32/G13 -> 0.27981853 | H33: =H32/H13 -> 0.22877916 | I33: =I32/I13 -> 0.20883141 | ... M33: =M32/M13 -> 0.2654845

Sheet Jameslong
A1: Dosa Coffee - Jameslong Sarani | B1: 45748 | C1: 45778 | D1: 45809 | E1: 45839 | F1: 45870 | G1: 45901 | H1: 45931 | I1: 45962 | J1: 45992 | K1: 46023 | L1: 46054 | M1: 46082 | N1: FY 2025-26
A2: Food Cost Calculation
A3: Opening Stock | B3: 36440.58 | C3: =B7 -> 49415 | D3: =C7 -> 40894.4 | E3: =D7 -> 42081 | F3: =E7 -> 51469.27 | G3: =F7 -> 33321.05 | H3: =G7 -> 54739 | I3: =H7 -> 47750.07 | J3: =I7 -> 42671.01 | ... M3: =L7 -> 31857.94 | N3: =+SUM(J3:L3) -> 124117.01
A4: Purchases Food (Less Purchase Return) | B4: 308394.42 | C4: 295315.3 | D4: 321515.25 | E4: 336278.42 | F4: 337683 | G4: 383106.07 | H4: =331066.51 -> 331066.51 | I4: 277556.23 | J4: 290604 | K4: =536818.18-223052.95 -> 313765.23 | L4: 316636.84 | M4: 387548.22 | N4: =sum(B4:M4) -> 3899469.5
A5: Transferred Out | B5: 131.1 | C5: 1424.03 | D5: 594.78 | E5: 0 | F5: 75.43 | G5: 164.54 | H5: 0 | I5: 184.73 | J5: 0 | K5: 100.61 | L5: 342.65 | M5: 40.42 | N5: =+SUM(J5:L5) -> 443.26
A6: Wastage & Date Expired | B6: 12170.41 | C6: 10003.02 | D6: 9402.75 | E6: 10940 | F6: 13602 | G6: 13310.96 | H6: 11634.49 | I6: 13128 | J6: 12489.6 | K6: 13026 | L6: 12641.68 | M6: 16962.73 | N6: =+SUM(J6:L6) -> 38157.28
A7: Closing Stock | B7: 49415 | C7: 40894.4 | D7: 42081 | E7: 51469.27 | F7: 33321.05 | G7: 54739 | H7: 47750.07 | I7: 42671.01 | J7: 43985 | K7: 37461 | L7: 31857.94 | M7: 34825.91 | N7: =sum(B7:M7) -> 510470.65
A9: Gross Revenue | B9: =1270719.95*1.05+22353.25*1.05 -> 1357726.9 | C9: =1244511.96*1.05+23630.1*1.05 -> 1331549.2 | D9: =1307750.68*1.05+27958.39*1.05 -> 1402494.5 | E9: =1302085.47*1.05+25893.55*1.05 -> 1394378 | F9: =1346577.17*1.05+30977.61*1.05 -> 1446432.5 | G9: =1621687.54*1.05 -> 1702771.9 | H9: =1390378.98*1.05+34379.15*1.05 -> 1495996 | I9: =1145895.82*1.05+27855.51*1.05 -> 1232438.9 | J9: =1182232.01*1.05+22743.06*1.05 -> 1265223.8 | K9: =1280269.71*1.05+27583.42*1.05 -> 1373245.8 | L9: =1217226.46*1.05+29997.05*1.05 -> 1309584.7 | M9: =1466810.85*1.05+36183.74*1.05 -> 1578144.3 | N9: =+SUM(B9:M9) -> 16889986
A10: Catering & Fairs | B10: 0 | C10: 0 | D10: 0 | E10: 0 | F10: 0 | G10: 0 | H10: 0 | I10: 0 | J10: 0 | K10: 0 | L10: 0 | M10: 0 | N10: =+SUM(B10:M10) -> 0
A11: Less Tax | B11: =(B9+B10)/1.05*0.05 -> 64653.66 | C11: =(C9+C10)/1.05*0.05 -> 63407.103 | D11: =(D9+D10)/1.05*0.05 -> 66785.454 | E11: =(E9+E10)/1.05*0.05 -> 66398.951 | F11: =(F9+F10)/1.05*0.05 -> 68877.739 | G11: =(G9+G10)/1.05*0.05 -> 81084.377 | H11: =(H9+H10)/1.05*0.05 -> 71237.906 | I11: =(I9+I10)/1.05*0.05 -> 58687.567 | ... M11: =(M9+M10)/1.05*0.05 -> 75149.73 | N11: =+SUM(B11:M11) -> 804285.07
A12: Less Commission | B12: =479.58+51367.71+86.32+9246.18+55269.02+9948.44+9048.76 -> 135446.01 | C12: =9871.66+54842.53+43084.1+7755.1+190.83+12164.37+11895+2189.59 -> 141993.18 | D12: =64694.81+11645.07+44509.21+6559.24+20443.33+3679.81 -> 151531.47 | E12: =59988.85+10798+59059.59+10630.77+581.3+9609+2.6+1727 -> 152397.11 | F12: =47382.18+8528.8+72145+12986.1+18591.98 -> 159634.06 | G12: =78306.73*1.18+754.85*1.18+63908.06*1.18 -> 168704.18 | H12: =79302.24*1.18+55153.36*1.18+281.38*1.18+11011.05*1.18 -> 171982.68 | I12: =64821.17*1.18+46755.46*1.18+1264*1.18 -> 133151.94 | J12: =(52490.73+588.93)*1.18+56023.17*1.18+1443.92*1.18 -> 130445.16 | K12: =63705.75*1.18+1438.62*1.18+58417.73*1.18 -> 145803.28 | L12: =81583.94+24880.78+30837.25+101.22+4448.64+18.2 -> 141870.03 | M12: =84283.41*1.18+46278.27*1.18+950.17*1.18+146.83*1.18+22928.16*1.18 -> 182412.47 | N12: =+SUM(B12:M12) -> 1815371.6
A13: Net Revenues from F&B Sales | B13: =B9+B10-B11-B12 -> 1157627.2 | C13: =C9+C10-C11-C12 -> 1126148.9 | D13: =D9+D10-D11-D12 -> 1184177.6 | E13: =E9+E10-E11-E12 -> 1175581.9 | F13: =F9+F10-F11-F12 -> 1217920.7 | G13: =G9+G10-G11-G12 -> 1452983.4 | H13: =H9+H10-H11-H12 -> 1252775.5 | I13: =I9+I10-I11-I12 -> 1040599.4 | ... M13: =M9+M10-M11-M12 -> 1320582.1 | N13: =sum(B13:M13) -> 14270330
A14: F&B Cost | B14: =+B3+B4-B5-B7 -> 295288.9 | C14: =+C3+C4-C5-C7 -> 302411.87 | D14: =+D3+D4-D5-D7 -> 319733.87 | E14: =+E3+E4-E5-E7 -> 326890.15 | F14: =+F3+F4-F5-F7 -> 355755.79 | G14: =+G3+G4-G5-G7 -> 361523.58 | H14: =+H3+H4-H5-H7 -> 338055.44 | I14: =+I3+I4-I5-I7 -> 282450.56 | ... M14: =+M3+M4-M5-M7 -> 384539.83 | N14: =sum(B14:M14) -> 3898025.9 | O14: =N14/$N$13 -> 0.27315598
A15: Electricity | B15: 51330.24 | C15: 63439.76 | D15: 61760 | E15: 66750 | F15: 58410 | G15: 73620 | H15: 51020 | I15: 40220 | J15: 37450 | K15: =41380 -> 41380 | L15: 62640 | M15: =60290 -> 60290 | N15: =sum(B15:M15) -> 668310 | O15: =N15/$N$13 -> 0.046832134
A16: Telephone/Internet | B16: =352.82+4250/12 -> 706.98667 | C16: =352.82+4250/12 -> 706.98667 | D16: =4250/12+352.82 -> 706.98667 | E16: =4250/12+353 -> 707.16667 | F16: =4250/12+2478/4+352.82 -> 1326.4867 | G16: =4250/12+2478/4+352.82 -> 1326.4867 | H16: =4250/12+2478/4+352.82 -> 1326.4867 | I16: =4250/12+352.82 -> 706.98667 | J16: =4250/12+352.82 -> 706.98667 | K16: =4250/12+352.82 -> 706.98667 | L16: =4250/12+352.82 -> 706.98667 | M16: =4250/12+352.82 -> 706.98667 | N16: =sum(B16:M16) -> 10342.52 | O16: =N16/$N$13 -> 0.0007247569
A17: Gas | B17: =29044 -> 29044 | C17: 28756 | D17: 28322 | E17: 33789 | F17: =28341 -> 28341 | G17: 33528 | H17: 30810 | I17: 29146 | J17: 33528 | K17: 35970 | L17: =35375 -> 35375 | M17: =11368+9*3556 -> 43372 | N17: =sum(B17:M17) -> 389981 | O17: =N17/$N$13 -> 0.0273281
A18: Rent & Revenue Share | B18: =153400 -> 153400 | C18: =153400 -> 153400 | D18: =153400 -> 153400 | E18: =153400 -> 153400 | F18: =153400 -> 153400 | G18: =153400+12272/2 -> 159536 | H18: =153400+12272/2 -> 159536 | I18: 159536 | J18: 159536 | K18: 159536 | L18: 159536 | M18: 159536 | N18: =sum(B18:M18) -> 1883752 | O18: =N18/$N$13 -> 0.1320048
A19: Software | B19: 5767 | C19: 5767 | D19: 5767 | E19: 5767 | F19: 5767 | G19: =76228/12 -> 6352.3333 | H19: =76228/12 -> 6352.3333 | I19: =76228/12 -> 6352.3333 | J19: =76228/12 -> 6352.3333 | K19: =76228/12 -> 6352.3333 | L19: =76228/12 -> 6352.3333 | M19: =76228/12 -> 6352.3333 | N19: =sum(B19:M19) -> 73301.333 | O19: =N19/$N$13 -> 0.005136625
A20: Staff Salary | B20: =181879.05+3100+86142/12 -> 192157.55 | C20: =195123+3100+580+86142/12 -> 205981.5 | D20: =115638.89+48039.32+3621.2+3100+86142/12 -> 177577.91 | E20: =188303+3100+86142/12 -> 198581.5 | F20: =3100+550+176634.84+86142/12 -> 187463.34 | G20: =203262+86142/12+3100 -> 213540.5 | H20: =86142/12+162254.59+3100+540 -> 173073.09 | I20: =86142/12+180584+3530 -> 191292.5 | J20: =86142/12+173716+3100 -> 183994.5 | K20: =86142/12+3100+152293 -> 162571.5 | L20: =86142/12+3100+161450 -> 171728.5 | M20: =86142/12+3100+153008 -> 163286.5 | N20: =sum(B20:M20) -> 2221248.9 | O20: =N20/$N$13 -> 0.15565505
A21: AMC | B21: =1200+2360+2360+18032/12 -> 7422.6667 | C21: =9840+2360+2478+18032/12 -> 16180.667 | D21: =2478+2360+2360+1200+18032/12 -> 9900.6667 | E21: =2360+1200+2478+2360+18032/12 -> 9900.6667 | F21: =1200+2478+2360+2360+18032/12 -> 9900.6667 | G21: =18032/12+2360+2360+2478+1200 -> 9900.6667 | H21: =18032/12+2360+2478+2360 -> 8700.6667 | I21: =18032/12+2360+2360+2478 -> 8700.6667 | J21: =18032/12+1200+4838+2360 -> 9900.6667 | K21: =18032/12+2360+1200+2360+2478 -> 9900.6667 | L21: =18032/12+1200+2596+2478+2360 -> 10136.667 | M21: =18032/12+2360+1650+2596+2478 -> 10586.667 | N21: =sum(B21:M21) -> 121132 | O21: =N21/$N$13 -> 0.0084883812
A22: Subscription | B22: =2124/3+9813/12+6372/12 -> 2056.75 | C22: =2124/3+9813/12+6372/12 -> 2056.75 | D22: =2124/3+9813/12+6372/12 -> 2056.75 | E22: =9813/12+6372/12+2124/3+9000/3 -> 5056.75 | F22: =9813/12+6372/12+2124/3 -> 2056.75 | G22: =9813/12+6372/12+2124/3 -> 2056.75 | H22: =9813/12+6372/12+2124/3 -> 2056.75 | I22: =9813/12+6372/12+2124/3 -> 2056.75 | J22: =9813/12+6372/12+2124/3 -> 2056.75 | K22: =9813/12+6372/12+3271.32/3+9000/3 -> 5439.19 | L22: =9813/12+6372/12+3271.32/3+9000/3 -> 5439.19 | M22: =9813/12+6372/12+3271.32/3+9000/3 -> 5439.19 | N22: =sum(B22:M22) -> 37828.32 | O22: =N22/$N$13 -> 0.0026508371
A23: Insurance Premium | B23: 0 | C23: =12930.58/12 -> 1077.5483 | D23: =12930.58/12 -> 1077.5483 | E23: =12930.58/12 -> 1077.5483 | F23: =12930.58/12 -> 1077.5483 | G23: =12930.58/12 -> 1077.5483 | H23: =12930.58/12 -> 1077.5483 | I23: =12930.58/12 -> 1077.5483 | J23: =12930.58/12 -> 1077.5483 | ... M23: =12930.58/12 -> 1077.5483 | N23: =sum(B23:M23) -> 11853.032 | O23: =N23/$N$13 -> 0.00083060671
A24: Repairs & Maintenance | B24: 680 | C24: 660 | D24: =25960/12+8258.38 -> 10421.713 | E24: =25960/12 -> 2163.3333 | F24: =25960/12+700 -> 2863.3333 | G24: =25960/12+6400 -> 8563.3333 | H24: =25960/12+11760 -> 13923.333 | I24: =25960/12+11682 -> 13845.333 | J24: =25960/12 -> 2163.3333 | K24: =25960/12+1050 -> 3213.3333 | L24: =25960/12+4558 -> 6721.3333 | M24: =25960/12+7313 -> 9476.3333 | N24: =sum(B24:M24) -> 74694.713 | O24: =N24/$N$13 -> 0.0052342668
A25: Miscellaneous Expenses | B25: =5777.39 -> 5777.39 | C25: 42009.75 | D25: 13918 | E25: 16483 | F25: =8309.86 -> 8309.86 | G25: 34914.49 | H25: 31975.55 | I25: 33725.27 | J25: =30083.5 -> 30083.5 | K25: 26820 | L25: 10041 | M25: =16575 -> 16575 | N25: =sum(B25:M25) -> 270632.81 | O25: =N25/$N$13 -> 0.01896472
A26: CAM | N26: =sum(B26:M26) -> 0 | O26: =N26/$N$13 -> 0
A27: HO+CK Cost | B27: =HO!D34 -> 234799.15 | C27: =HO!H34 -> 226298.77 | D27: =HO!L34 -> 235529.04 | E27: =HO!P34 -> 251451.15 | F27: =HO!D53 -> 238913.86 | G27: =HO!H53 -> 312502.02 | H27: =HO!L53 -> 241422.57 | I27: =HO!P53 -> 224505.66 | J27: =HO!D72 -> 202336.47 | K27: =HO!H72 -> 226485.69 | L27: =HO!L72 -> 231259.65 | M27: =HO!P72 -> 243211.28 | N27: =sum(B27:M27) -> 2868715.3 | O27: =N27/$N$13 -> 0.20102656
A28: Operating Expenses | B28: =+SUM(B14:B27) -> 978430.63 | C28: =+SUM(C14:C27) -> 1048746.6 | D28: =+SUM(D14:D27) -> 1020171.5 | E28: =+SUM(E14:E27) -> 1072017.3 | F28: =+SUM(F14:F27) -> 1053585.6 | G28: =+SUM(G14:G27) -> 1218441.7 | H28: =+SUM(H14:H27) -> 1059329.8 | I28: =+SUM(I14:I27) -> 993615.61 | ... M28: =+SUM(M14:M27) -> 1104449.7 | N28: =sum(B28:M28) -> 12529818 | O28: =N28/$N$13 -> 0.87803281
A29: Store Level EBITDA | B29: =B13-B28 -> 179196.56 | C29: =C13-C28 -> 77402.281 | D29: =D13-D28 -> 164006.11 | E29: =E13-E28 -> 103564.64 | F29: =F13-F28 -> 164335.09 | G29: =G13-G28 -> 234541.66 | H29: =H13-H28 -> 193445.69 | I29: =I13-I28 -> 46983.778 | ... M29: =M13-M28 -> 216132.45 | N29: =sum(B29:M29) -> 1740512.1 | O29: =N29/$N$13 -> 0.12196719
A30: Food Cost | B30: =(B14/B13) -> 0.25508117 | C30: =(C14/C13) -> 0.26853631 | D30: =(D14/D13) -> 0.270005 | E30: =(E14/E13) -> 0.27806667 | F30: =(F14/F13) -> 0.29210094 | G30: =(G14/G13) -> 0.24881467 | H30: =(H14/H13) -> 0.2698452 | I30: =(I14/I13) -> 0.27143064 | ... M30: =(M14/M13) -> 0.29118964
B32: =B29+B27 -> 413995.71 | C32: =C29+C27 -> 303701.05 | D32: =D29+D27 -> 399535.16 | E32: =E29+E27 -> 355015.79 | F32: =F29+F27 -> 403248.95 | G32: =G29+G27 -> 547043.68 | H32: =H29+H27 -> 434868.26 | I32: =I29+I27 -> 271489.44 | ... M32: =M29+M27 -> 459343.73
B33: =B32/B13 -> 0.35762438 | C33: =C32/C13 -> 0.26968108 | D33: =D32/D13 -> 0.33739462 | E33: =E32/E13 -> 0.30199154 | F33: =F32/F13 -> 0.33109622 | G33: =G32/G13 -> 0.37649686 | H33: =H32/H13 -> 0.34712386 | I33: =I32/I13 -> 0.26089717 | ... M33: =M32/M13 -> 0.34783428

Sheet Sector 1
A1: Dosa Coffee - Sector 1 | B1: 45748 | C1: 45778 | D1: 45809 | E1: 45839 | F1: 45870 | G1: 45901 | H1: 45931 | I1: 45962 | J1: 45992 | K1: 46023 | L1: 46054 | M1: 46082 | N1: FY 2025-26
A2: Food Cost Calculation
A3: Opening Stock | B3: 36973.5 | C3: =B7 -> 44220.46 | D3: =C7 -> 49031.88 | E3: =D7 -> 44276.99 | F3: =E7 -> 50255.2 | G3: =F7 -> 51137 | H3: =G7 -> 72934 | I3: =H7 -> 53953.04 | J3: =I7 -> 47832 | ... M3: =L7 -> 47420 | N3: =+SUM(J3:L3) -> 151116.96
A4: Purchases Food (Less Purchase Return) | B4: 446235.91 | C4: 502976.96 | D4: 466449.26 | E4: 489417.49 | F4: 506977.7 | G4: 482187.6 | H4: 501251.98 | I4: 461743.19 | J4: 476528 | K4: 482819 | L4: 455132.39 | M4: 553945.51 | N4: =sum(B4:M4) -> 5825665
A5: Transferred Out | B5: 692.32 | C5: 2206.36 | D5: =1303.62 -> 1303.62 | E5: 1073 | F5: 256.53 | G5: 1958 | H5: 528.83 | I5: 124 | J5: 1228 | K5: 1360 | L5: 815.11 | M5: 1264.79 | N5: =+SUM(J5:L5) -> 3403.11
A6: Wastage & Date Expired | B6: 19656.58 | C6: 20162.07 | D6: 21036.4 | E6: 24674.89 | F6: 23193.84 | G6: 21362 | H6: 18273.34 | I6: 19352 | J6: 20045 | K6: 18565 | L6: 18143.59 | M6: 22907.3 | N6: =+SUM(J6:L6) -> 56753.59
A7: Closing Stock | B7: 44220.46 | C7: 49031.88 | D7: 44276.99 | E7: 50255.2 | F7: 51137 | G7: 72934 | H7: 53953.04 | I7: 47832 | J7: 55399 | K7: 47885.96 | L7: 47420 | M7: 42774.58 | N7: =sum(B7:M7) -> 607120.11
A9: Gross Revenue | B9: =1978916.02*1.05+30336.45*1.05 -> 2109715.1 | C9: =2187819.17*1.05+42348.06*1.05 -> 2341675.6 | D9: =2022684.26*1.05+36700.5*1.05 -> 2162354 | E9: =2078229.43*1.05+38733.6*1.05 -> 2222811.2 | F9: =35921.64*1.05+2086017.9*1.05 -> 2228036.5 | G9: =2170253.74*1.05 -> 2278766.4 | H9: =2249040.63*1.05+39707.18*1.05 -> 2403185.2 | I9: =2006908.1*1.05+38117.06*1.05 -> 2147276.4 | J9: =1950245.73*1.05+31534.79*1.05 -> 2080869.5 | K9: =2071379*1.05+32239.46*1.05 -> 2208799.4 | L9: =1850270.17*1.05+32154.24*1.05 -> 1976545.6 | M9: =2445470.71*1.05+34878.19*1.05 -> 2604366.3 | N9: =+SUM(B9:M9) -> 26764401
A10: Catering & Fairs | B10: 0 | C10: 0 | D10: 0 | E10: 0 | F10: 0 | G10: 0 | H10: 0 | I10: 0 | J10: 0 | K10: 0 | L10: 0 | M10: 0 | N10: =+SUM(B10:M10) -> 0
A11: Less Tax | B11: =(B9+B10)/1.05*0.05 -> 100462.62 | C11: =(C9+C10)/1.05*0.05 -> 111508.36 | D11: =(D9+D10)/1.05*0.05 -> 102969.24 | E11: =(E9+E10)/1.05*0.05 -> 105848.15 | F11: =(F9+F10)/1.05*0.05 -> 106096.98 | G11: =(G9+G10)/1.05*0.05 -> 108512.69 | H11: =(H9+H10)/1.05*0.05 -> 114437.39 | I11: =(I9+I10)/1.05*0.05 -> 102251.26 | ... M11: =(M9+M10)/1.05*0.05 -> 124017.45 | N11: =+SUM(B11:M11) -> 1274495.3
A12: Less Commission | B12: =69904.08+942.27+12582.74+169.62+74066.58+13332.06+12620 -> 183617.35 | C12: =17583.94+97688.56+75896.57+13661.34+344.46+23524.74 -> 228699.61 | D12: =84962.78+15293.3+68295.72+12293+28966+5213.96 -> 215024.76 | E12: =89352.18+78452.72+14121.47+1289.21+13691+2465 -> 199371.58 | F12: =66251.17+11925.18+83180.93+14972.56+2458.75*1.18+22878.34+4118.08 -> 206227.58 | G12: =77250.5*1.18+1446.04*1.18+78476.92*1.18 -> 185464.68 | H12: =92478*1.18+70437.69*1.18+3690.35*1.18+16107.23*1.18 -> 215601.66 | I12: =89313.97*1.18+71989.57*1.18+2581.61*1.18 -> 193384.48 | J12: =(72834.87+1354.05)*1.18+72238.71*1.18+3720.88*1.18 -> 177175.24 | K12: =76323*1.18+3614.04*1.18+70858.81*1.18 -> 177939.1 | L12: =87696.55+30496.69+39143.18+67.68+5489.43+12.18+3636.35*1.18+8.1*1.18 -> 167206.16 | M12: =81951.39*1.18+51183.01*1.18+4067.21*1.18+46.17*1.18+20480.12*1.18 -> 186118.92 | N12: =+SUM(B12:M12) -> 2335831.1
A13: Net Revenues from F&B Sales | B13: =B9+B10-B11-B12 -> 1825635.1 | C13: =C9+C10-C11-C12 -> 2001467.6 | D13: =D9+D10-D11-D12 -> 1844360 | E13: =E9+E10-E11-E12 -> 1917591.4 | F13: =F9+F10-F11-F12 -> 1915712 | G13: =G9+G10-G11-G12 -> 1984789.1 | H13: =H9+H10-H11-H12 -> 2073146.2 | I13: =I9+I10-I11-I12 -> 1851640.7 | ... M13: =M9+M10-M11-M12 -> 2294230 | N13: =sum(B13:M13) -> 23154075
A14: F&B Cost | B14: =+B3+B4-B5-B7 -> 438296.63 | C14: =+C3+C4-C5-C7 -> 495959.18 | D14: =+D3+D4-D5-D7 -> 469900.53 | E14: =+E3+E4-E5-E7 -> 482366.28 | F14: =+F3+F4-F5-F7 -> 505839.37 | G14: =+G3+G4-G5-G7 -> 458432.6 | H14: =+H3+H4-H5-H7 -> 519704.11 | I14: =+I3+I4-I5-I7 -> 467740.23 | ... M14: =+M3+M4-M5-M7 -> 557326.14 | N14: =sum(B14:M14) -> 5807053.3 | O14: =N14/$N$13 -> 0.25080049
A15: Electricity | B15: =89171 -> 89171 | C15: =89358 -> 89358 | D15: =92741 -> 92741 | E15: 81325 | F15: 73971 | G15: 79350 | H15: 63628 | I15: =47160 -> 47160 | J15: =44844 -> 44844 | K15: =44579 -> 44579 | L15: =44037 -> 44037 | M15: =60740.77 -> 60740.77 | N15: =sum(B15:M15) -> 810904.77 | O15: =N15/$N$13 -> 0.035022119
A16: Telephone/Internet | B16: =352.82 -> 352.82 | C16: =352.82 -> 352.82 | D16: =352.82 -> 352.82 | E16: =352.82 -> 352.82 | F16: =352.82 -> 352.82 | G16: =352.82+1003 -> 1355.82 | H16: =289+352.82 -> 641.82 | I16: =352.82+8142/12 -> 1031.32 | J16: =8142/12+1294+352.82 -> 2325.32 | K16: =8142/12+352.82 -> 1031.32 | L16: =8142/12+291+352.82 -> 1322.32 | M16: =8142/12+291+352.82 -> 1322.32 | N16: =sum(B16:M16) -> 10794.34 | O16: =N16/$N$13 -> 0.00046619613
A17: Gas | B17: =49546 -> 49546 | C17: 52437 | D17: 51646 | E17: 56315 | F17: =50384 -> 50384 | G17: 48768 | H17: 50836 | I17: =53690 -> 53690 | J17: 45720 | K17: 57225 | L17: =52220 -> 52220 | M17: =19213+16*3556 -> 76109 | N17: =sum(B17:M17) -> 644896 | O17: =N17/$N$13 -> 0.027852376
A18: Rent & Revenue Share | B18: =134520 -> 134520 | C18: =134520 -> 134520 | D18: =134520 -> 134520 | E18: =134520 -> 134520 | F18: =134520 -> 134520 | G18: 224200 | H18: 224200 | I18: 224200 | J18: 224200 | K18: 224200 | L18: 224200 | M18: 224200 | N18: =sum(B18:M18) -> 2242000 | O18: =N18/$N$13 -> 0.096829608
A19: Software | B19: 5725 | C19: =68706/12 -> 5725.5 | D19: =68706/12 -> 5725.5 | E19: =68706/12 -> 5725.5 | F19: =68706/12 -> 5725.5 | G19: =68706/12 -> 5725.5 | H19: =68706/12 -> 5725.5 | I19: =68706/12 -> 5725.5 | J19: =68706/12 -> 5725.5 | ... M19: =68706/12 -> 5725.5 | N19: =sum(B19:M19) -> 68705.5 | O19: =N19/$N$13 -> 0.0029673179
A20: Staff Salary & Bonus | B20: =279018.01+163837/12 -> 292671.09 | C20: =281415+163837/12 -> 295068.08 | D20: =215647+74254+4986.72++163837/12 -> 308540.8 | E20: =290113++163837/12 -> 303766.08 | F20: =301615.68+163837/12 -> 315268.76 | G20: =287787.21+163837/12 -> 301440.29 | H20: =163837/12+291293.75 -> 304946.83 | I20: =163837/12+299468 -> 313121.08 | J20: =163837/12+285280 -> 298933.08 | K20: =163837/12+284171+4796 -> 302620.08 | L20: =163837/12+292669+7417 -> 313739.08 | M20: =163837/12+8500+314919 -> 337072.08 | N20: =sum(B20:M20) -> 3687187.4 | O20: =N20/$N$13 -> 0.15924572
A21: AMC | B21: =2850+2360+2950+21362/12 -> 9940.1667 | C21: =2400+2360+2478+2950+21362/12 -> 11968.167 | D21: =2400+2360+2950+21362/12 -> 9490.1667 | E21: =2400+2360+2478+2950+21362/12 -> 11968.167 | F21: =21362/12+2950+2478+2360+2400 -> 11968.167 | G21: =21362/12+2950+3750+2360+2478 -> 13318.167 | H21: =21362/12+2950+3750+2360+2478 -> 13318.167 | I21: =21362/12+2950+2400+2478+2360 -> 11968.167 | J21: =21362/12+2400+4838+2950 -> 11968.167 | K21: =21362/12+2950+2400+2360+2478 -> 11968.167 | L21: =21362/12+3000+2478+2596+2950 -> 12804.167 | M21: =21362/12+2950+2850+2596+2478 -> 12654.167 | N21: =sum(B21:M21) -> 143334 | O21: =N21/$N$13 -> 0.0061904438
A22: Subscription | B22: =9000/3+2124/3+9813/12+6372/12 -> 5056.75 | C22: =9000/3+2124/3+9813/12+6372/12 -> 5056.75 | D22: =9000/3+2124/3+9813/12+6372/12 -> 5056.75 | E22: =9813/12+6372/12+2124/3+9000/3 -> 5056.75 | F22: =9813/12+6372/12+2124/3+9000/3 -> 5056.75 | G22: =9813/12+6372/12+2124/3+9000/3 -> 5056.75 | H22: =9813/12+6372/12+2124/3 -> 2056.75 | I22: =9813/12+6372/12+2124/3 -> 2056.75 | J22: =9813/12+6372/12+2124/3 -> 2056.75 | K22: =9813/12+6372/12+3271.32/3 -> 2439.19 | L22: =9813/12+6372/12+3271.32/3 -> 2439.19 | M22: =9813/12+6372/12+3271.32/3 -> 2439.19 | N22: =sum(B22:M22) -> 43828.32 | O22: =N22/$N$13 -> 0.0018928988
A23: Insurance Premium | B23: 0 | C23: 878.51 | D23: 878.51 | E23: 878.51 | F23: 878.51 | G23: 878.51 | H23: 878.51 | I23: 878.51 | J23: 878.51 | K23: 878.51 | L23: 878.51 | M23: 878.51 | N23: =sum(B23:M23) -> 9663.61 | O23: =N23/$N$13 -> 0.00041736109
A24: Repairs & Maintenance | B24: 2000 | C24: 2000 | D24: =35400/12+6478 -> 9428 | E24: =35400/12+2500 -> 5450 | F24: =35400/12+10575 -> 13525 | G24: =35400/12+11471 -> 14421 | H24: =35400/12+5910 -> 8860 | I24: =35400/12+2900 -> 5850 | J24: =35400/12+7310 -> 10260 | K24: =35400/12+7861 -> 10811 | L24: =35400/12+6660 -> 9610 | M24: =35400/12+10638 -> 13588 | N24: =sum(B24:M24) -> 105803 | O24: =N24/$N$13 -> 0.0045695196
A25: Miscellaneous Expenses | B25: 9044 | C25: 29855.81 | D25: 27732.55 | E25: =22125 -> 22125 | F25: 18047 | G25: 18239.5 | H25: 21364.15 | I25: 11737.73 | J25: 17291 | K25: 15854 | L25: 5856 | M25: =43240 -> 43240 | N25: =sum(B25:M25) -> 240386.74 | O25: =N25/$N$13 -> 0.010382049
A26: CAM | N26: =sum(B26:M26) -> 0 | O26: =N26/$N$13 -> 0
A27: HO+CK Cost | B27: =HO!D38 -> 370289.83 | C27: =HO!H38 -> 402193.41 | D27: =HO!L38 -> 366837.15 | E27: =HO!P38 -> 410163.32 | F27: =HO!D57 -> 375796.33 | G27: =HO!H57 -> 426880.72 | H27: =HO!L57 -> 399516.34 | I27: =HO!P57 -> 399484.97 | J27: =HO!D76 -> 339811.35 | K27: =HO!H76 -> 375318.51 | L27: =HO!L76 -> 358854.23 | M27: =HO!P76 -> 422527.76 | N27: =sum(B27:M27) -> 4647673.9 | O27: =N27/$N$13 -> 0.20072812
A28: Operating Expenses | B28: =+SUM(B14:B27) -> 1406613.3 | C28: =+SUM(C14:C27) -> 1525373.2 | D28: =+SUM(D14:D27) -> 1482849.8 | E28: =+SUM(E14:E27) -> 1520012.4 | F28: =+SUM(F14:F27) -> 1511333.2 | G28: =+SUM(G14:G27) -> 1598066.9 | H28: =+SUM(H14:H27) -> 1615676.2 | I28: =+SUM(I14:I27) -> 1544644.3 | ... M28: =+SUM(M14:M27) -> 1757823.4 | N28: =sum(B28:M28) -> 18462231 | O28: =N28/$N$13 -> 0.79736422
A29: Store Level EBITDA | B29: =B13-B28 -> 419021.83 | C29: =C13-C28 -> 476094.39 | D29: =D13-D28 -> 361510.22 | E29: =E13-E28 -> 397579.02 | F29: =F13-F28 -> 404378.75 | G29: =G13-G28 -> 386722.2 | H29: =H13-H28 -> 457469.97 | I29: =I13-I28 -> 306996.42 | ... M29: =M13-M28 -> 536406.53 | N29: =sum(B29:M29) -> 4691844 | O29: =N29/$N$13 -> 0.20263578
A30: Food Cost | B30: =(B14/B13) -> 0.24007899 | C30: =(C14/C13) -> 0.24779775 | D30: =(D14/D13) -> 0.25477701 | E30: =(E14/E13) -> 0.25154799 | F30: =(F14/F13) -> 0.26404772 | G30: =(G14/G13) -> 0.23097296 | H30: =(H14/H13) -> 0.25068378 | I30: =(I14/I13) -> 0.25260853 | ... M30: =(M14/M13) -> 0.24292514
B32: =B29+B27 -> 789311.66 | C32: =C29+C27 -> 878287.8 | D32: =D29+D27 -> 728347.37 | E32: =E29+E27 -> 807742.34 | F32: =F29+F27 -> 780175.07 | G32: =G29+G27 -> 813602.92 | H32: =H29+H27 -> 856986.31 | I32: =I29+I27 -> 706481.39 | ... M32: =M29+M27 -> 958934.3
B33: =B32/B13 -> 0.43234908 | C33: =C32/C13 -> 0.43882189 | D33: =D32/D13 -> 0.39490521 | E33: =E32/E13 -> 0.42122755 | F33: =F32/F13 -> 0.40725072 | G33: =G32/G13 -> 0.40991909 | H33: =H32/H13 -> 0.41337477 | I33: =I32/I13 -> 0.38154346 | ... M33: =M32/M13 -> 0.41797654

Sheet Santoshpur
A1: Dosa Coffee - Santoshpur | B1: 45748 | C1: 45778 | D1: 45809 | E1: 45839 | F1: 45870 | G1: 45901 | H1: 45931 | I1: 45962 | J1: 45992 | K1: 46023 | L1: 46054 | M1: 46082 | N1: FY 2025-26
A2: Food Cost Calculation
A3: Opening Stock | B3: 35790.75 | C3: =B7 -> 35819.27 | D3: =C7 -> 42257.23 | E3: =D7 -> 40083.86 | F3: =E7 -> 44361 | G3: =F7 -> 34807.62 | H3: =G7 -> 36647.52 | I3: =H7 -> 45512 | J3: =I7 -> 35369.11 | ... M3: =L7 -> 33144 | N3: =+SUM(J3:L3) -> 103748.11
A4: Purchases Food (Less Purchase Return) | B4: 221851.81 | C4: 270594.55 | D4: 257666.86 | E4: 266556.77 | F4: 265528.46 | G4: 283795 | H4: 272178 | I4: 258151 | J4: 254793 | K4: 285193.78 | L4: 258537.36 | M4: 295202.51 | N4: =sum(B4:M4) -> 3190049.1
A5: Transferred Out | B5: 815.76 | C5: 654.29 | D5: 926.78 | E5: 30.62 | F5: 121 | G5: 873.06 | H5: 2102 | I5: 2516.83 | J5: 1020 | K5: 858.75 | L5: 200 | M5: 581.06 | N5: =+SUM(J5:L5) -> 2078.75
A6: Wastage & Date Expired | B6: 5497.6 | C6: 5973.96 | D6: 6915 | E6: 9045 | F6: 11579 | G6: 10278 | H6: 14177.54 | I6: 16394.17 | J6: 19699 | K6: 10684 | L6: 7844.65 | M6: 9355.78 | N6: =+SUM(J6:L6) -> 38227.65
A7: Closing Stock | B7: 35819.27 | C7: 42257.23 | D7: =40083.86 -> 40083.86 | E7: 44361 | F7: 34807.62 | G7: 36647.52 | H7: 45512 | I7: 35369.11 | J7: 29636 | K7: 38743 | L7: 33144 | M7: 27909.5 | N7: =sum(B7:M7) -> 444290.11
A9: Gross Revenue | B9: =965878.32*1.05+14744.43*1.05 -> 1029653.9 | C9: =1156845.24*1.05+23631.36*1.05 -> 1239500.4 | D9: =1128986.75*1.05+23635.4*1.05 -> 1210253.3 | E9: =1077244.62*1.05+21918.89*1.05 -> 1154121.7 | F9: =1126367.91*1.05+23745.13*1.05 -> 1207618.7 | G9: =1193024.76*1.05 -> 1252676 | H9: =1096294.12*1.05+28499.55*1.05 -> 1181033.4 | I9: =1013886.59*1.05+27330.08*1.05 -> 1093277.5 | J9: =985351.84*1.05+25585.47*1.05 -> 1061484.2 | K9: =1042741.12*1.05+25389.68*1.05 -> 1121537.3 | L9: =955199*1.05+25864.26*1.05 -> 1030116.4 | M9: =1175673.48*1.05+29694.96*1.05 -> 1265636.9 | N9: =+SUM(B9:M9) -> 13846910
A10: Catering & Fairs | B10: 0 | C10: 0 | D10: 0 | E10: 0 | F10: 0 | G10: 0 | H10: 0 | I10: 0 | J10: 0 | K10: 0 | L10: 0 | M10: 0 | N10: =+SUM(B10:M10) -> 0
A11: Less Tax | B11: =(B9+B10)/1.05*0.05 -> 49031.137 | C11: =(C9+C10)/1.05*0.05 -> 59023.83 | D11: =(D9+D10)/1.05*0.05 -> 57631.107 | E11: =(E9+E10)/1.05*0.05 -> 54958.175 | F11: =(F9+F10)/1.05*0.05 -> 57505.652 | G11: =(G9+G10)/1.05*0.05 -> 59651.238 | H11: =(H9+H10)/1.05*0.05 -> 56239.683 | I11: =(I9+I10)/1.05*0.05 -> 52060.834 | ... M11: =(M9+M10)/1.05*0.05 -> 60268.422 | N11: =+SUM(B11:M11) -> 659376.65
A12: Less Commission | B12: =34058.87+112.5+6130.6+20.24+52233.57+9402.03+9068.53 -> 111026.34 | C12: =9807.72+54487.3+57800.45+10404.13+37.66+11333.48+2040.03 -> 145910.77 | D12: =54676.98+9841.86+49006.48+8821+19758.96+3556.61 -> 145661.89 | E12: =50812.64+9146.28+59025.58+10624.6+243.76+9731+1751 -> 141334.86 | F12: =50684.24+9123.17+54932.07+9887.77+243.22*1.18+19390.07+3490.19 -> 147794.51 | G12: =60066.17*1.18+314.93*1.18+62761.94*1.18 -> 145308.79 | H12: =65738.57*1.18+49043.28*1.18+163.39*1.18+8364.01*1.18 -> 145504.92 | I12: =63077.27*1.18+51249.11*1.18+90.93*1.18 -> 135012.43 | J12: =(59115.65+423.48)*1.18+53043.34*1.18+339.89*1.18 -> 133248.38 | K12: =58862.39*1.18+842.14*1.18+56083.59*1.18 -> 136629.98 | L12: =70224+23801.88+33901+29.58+4284.38+5.32+322.1*1.18 -> 132626.24 | M12: =68614.82*1.18+43705.76*1.18+396.87*1.18+14.6*1.18+24288.66*1.18 -> 161684.44 | N12: =+SUM(B12:M12) -> 1681743.5
A13: Net Revenues from F&B Sales | B13: =B9+B10-B11-B12 -> 869596.41 | C13: =C9+C10-C11-C12 -> 1034565.8 | D13: =D9+D10-D11-D12 -> 1006960.3 | E13: =E9+E10-E11-E12 -> 957828.65 | F13: =F9+F10-F11-F12 -> 1002318.5 | G13: =G9+G10-G11-G12 -> 1047716 | H13: =H9+H10-H11-H12 -> 979288.76 | I13: =I9+I10-I11-I12 -> 906204.24 | ... M13: =M9+M10-M11-M12 -> 1043684 | N13: =sum(B13:M13) -> 11505789
A14: F&B Cost | B14: =+B3+B4-B5-B7 -> 221007.53 | C14: =+C3+C4-C5-C7 -> 263502.3 | D14: =+D3+D4-D5-D7 -> 258913.45 | E14: =+E3+E4-E5-E7 -> 262249.01 | F14: =+F3+F4-F5-F7 -> 274960.84 | G14: =+G3+G4-G5-G7 -> 281082.04 | H14: =+H3+H4-H5-H7 -> 261211.52 | I14: =+I3+I4-I5-I7 -> 265777.06 | ... M14: =+M3+M4-M5-M7 -> 299855.95 | N14: =sum(B14:M14) -> 3187230.2 | O14: =N14/$N$13 -> 0.277011
A15: Electricity | B15: =49609+1557 -> 51166 | C15: =47160.79+6512.11 -> 53672.9 | D15: =40820+6260 -> 47080 | E15: =7300+44100 -> 51400 | F15: 47440 | G15: =53770+7730 -> 61500 | H15: =47170+7140 -> 54310 | I15: =31660+7110 -> 38770 | J15: =26190+7160 -> 33350 | K15: =25710+7210 -> 32920 | L15: =31530+6930 -> 38460 | M15: =50240+7910 -> 58150 | N15: =sum(B15:M15) -> 568218.9 | O15: =N15/$N$13 -> 0.049385477
A16: Telephone/Internet | B16: =352.82 -> 352.82 | C16: =352.82 -> 352.82 | D16: =352.82 -> 352.82 | E16: =6018/12+352 -> 853.5 | F16: =6018/12+352.82 -> 854.32 | G16: =6018/12+352.82 -> 854.32 | H16: =6018/12+352.82 -> 854.32 | I16: =6018/12+352.82 -> 854.32 | J16: =6018/12+352.82 -> 854.32 | K16: =6018/12+352.82 -> 854.32 | L16: =6018/12+352.82 -> 854.32 | M16: =6018/12+352.82 -> 854.32 | N16: =sum(B16:M16) -> 8746.52 | O16: =N16/$N$13 -> 0.00076018426
A17: Gas | B17: =17085 -> 17085 | C17: 21990 | D17: 19992 | E17: =25744 -> 25744 | F17: 20468 | G17: 30480 | H17: 20026 | I17: =27612 -> 27612 | J17: 27432 | K17: 31065 | L17: =25268 -> 25268 | M17: =9378+12*3556 -> 52050 | N17: =sum(B17:M17) -> 319212 | O17: =N17/$N$13 -> 0.027743598
A18: Rent & Revenue Share | B18: =34125+34125 -> 68250 | C18: =(34125+34125)*1.18 -> 80535 | D18: =40268+40268 -> 80536 | E18: =40268+40268 -> 80536 | F18: =40268+40268 -> 80536 | G18: =40268+40268 -> 80536 | H18: =42280.58+42280.5 -> 84561.08 | I18: =42280.58+42280.5 -> 84561.08 | J18: =42280.58+42280.5 -> 84561.08 | K18: =42280.58+42280.5 -> 84561.08 | L18: =42280.58+42280.5 -> 84561.08 | M18: =42280.58+42280.5 -> 84561.08 | N18: =sum(B18:M18) -> 978295.48 | O18: =N18/$N$13 -> 0.085026368
A19: Software | B19: 5767 | C19: 5767 | D19: 5767 | E19: 5767 | F19: 5767 | G19: 5767 | H19: 5767 | I19: =69207/12 -> 5767.25 | J19: 5767 | K19: 5767 | L19: 5767 | M19: 5767 | N19: =sum(B19:M19) -> 69204.25 | O19: =N19/$N$13 -> 0.0060147329
A20: Staff Salary & Bonus | B20: =187946+55972/12 -> 192610.33 | C20: =198594.19+55972/12 -> 203258.52 | D20: =131993.71+54755.82+3422.99+55972/12 -> 194836.85 | E20: =187261+55972/12 -> 191925.33 | F20: =188860.65+55972/12 -> 193524.98 | G20: =187437+55972/12 -> 192101.33 | H20: =55972/12+167684.48 -> 172348.81 | I20: =55972/12+208239 -> 212903.33 | J20: =55972/12+195399 -> 200063.33 | K20: =55972/12+207275 -> 211939.33 | L20: =55972/12+190084 -> 194748.33 | M20: =55972/12+179345 -> 184009.33 | N20: =sum(B20:M20) -> 2344269.8 | O20: =N20/$N$13 -> 0.20374698
A21: AMC | B21: =3540+2360+5145+18032/12 -> 12547.667 | C21: =3717+2360+5145+18032/12 -> 12724.667 | D21: =3717+2360+5145+18032/12 -> 12724.667 | E21: =5145+2360+3717+18032/12 -> 12724.667 | F21: =3717+2360+5145+18032/12 -> 12724.667 | G21: =18032/12+5145+2360+3717+1160 -> 13884.667 | H21: =18032/12+5145+3717+2360 -> 12724.667 | I21: =18032/12+5145+1400+2360+3717 -> 14124.667 | J21: =18032/12+6077+5145 -> 12724.667 | K21: =18032/12+5145+2360+3717 -> 12724.667 | L21: =18032/12+2596+3717+5145 -> 12960.667 | M21: =18032/12+5145+3717+2956+450 -> 13770.667 | N21: =sum(B21:M21) -> 156361 | O21: =N21/$N$13 -> 0.013589767
A22: Subscription | B22: =9000/3+2124/3+9813/12+6372/12 -> 5056.75 | C22: =9000/3+2124/3+9813/12+6372/12 -> 5056.75 | D22: =9000/3+2124/3+9813/12+6372/12 -> 5056.75 | E22: =9813/12+6372/12+2124/3+9000/3 -> 5056.75 | F22: =9813/12+6372/12+2124/3+9000/3 -> 5056.75 | G22: =9813/12+6372/12+2124/3+9000/3 -> 5056.75 | H22: =9813/12+6372/12+2124/3+9000/3 -> 5056.75 | I22: =9813/12+6372/12+2124/3+9000/3 -> 5056.75 | J22: =9813/12+6372/12+2124/3+9000/3 -> 5056.75 | K22: =9813/12+6372/12+3271.32/3 -> 2439.19 | L22: =9813/12+6372/12+3271.32/3 -> 2439.19 | M22: =9813/12+6372/12+3271.32/3 -> 2439.19 | N22: =sum(B22:M22) -> 52828.32 | O22: =N22/$N$13 -> 0.0045914555
A23: Insurance Premium | N23: =sum(B23:M23) -> 0 | O23: =N23/$N$13 -> 0
A24: Repairs & Maintenance | B24: 1300 | C24: =4600 -> 4600 | D24: =43660/12+6915 -> 10553.333 | E24: =43660/12+1610 -> 5248.3333 | F24: =43660/12+8750 -> 12388.333 | G24: =43660/12+5685 -> 9323.3333 | H24: =43660/12+6586 -> 10224.333 | I24: =43660/12+8185 -> 11823.333 | J24: =43660/12+16130 -> 19768.333 | K24: =43660/12+14110 -> 17748.333 | L24: =43660/12+28190 -> 31828.333 | M24: =43660/12+3400 -> 7038.3333 | N24: =sum(B24:M24) -> 141844.33 | O24: =N24/$N$13 -> 0.012328084
A25: Miscellaneous Expenses | B25: 18964 | C25: 4873.43 | D25: 5088 | E25: =7185 -> 7185 | F25: =3037.53 -> 3037.53 | G25: 13594.75 | H25: 13008.91 | I25: =12615.7 -> 12615.7 | J25: =4031 -> 4031 | K25: 10615 | L25: 5954.88 | M25: 22287 | N25: =sum(B25:M25) -> 121255.2 | O25: =N25/$N$13 -> 0.010538625
A26: CAM | N26: =sum(B26:M26) -> 0 | O26: =N26/$N$13 -> 0
A27: HO+CK Cost | B27: =HO!D36 -> 176378.46 | C27: =HO!H36 -> 207895.22 | D27: =HO!L36 -> 200281.09 | E27: =HO!P36 -> 204874.81 | F27: =HO!D55 -> 196620.18 | G27: =HO!H55 -> 225338.68 | H27: =HO!L55 -> 188718.9 | I27: =HO!P55 -> 195510.38 | J27: =HO!D74 -> 165270.86 | K27: =HO!H74 -> 181551.25 | L27: =HO!L74 -> 177508.15 | M27: =HO!P74 -> 192215.02 | N27: =sum(B27:M27) -> 2312163 | O27: =N27/$N$13 -> 0.20095648
A28: Operating Expenses | B28: =+SUM(B14:B27) -> 770485.56 | C28: =+SUM(C14:C27) -> 864228.61 | D28: =+SUM(D14:D27) -> 841181.97 | E28: =+SUM(E14:E27) -> 853564.4 | F28: =+SUM(F14:F27) -> 853378.6 | G28: =+SUM(G14:G27) -> 919518.87 | H28: =+SUM(H14:H27) -> 828812.29 | I28: =+SUM(I14:I27) -> 875375.87 | ... M28: =+SUM(M14:M27) -> 922997.9 | N28: =sum(B28:M28) -> 10259629 | O28: =N28/N13 -> 0.89169275
A29: Store Level EBITDA | B29: =B13-B28 -> 99110.853 | C29: =C13-C28 -> 170337.22 | D29: =D13-D28 -> 165778.29 | E29: =E13-E28 -> 104264.25 | F29: =F13-F28 -> 148939.93 | G29: =G13-G28 -> 128197.1 | H29: =H13-H28 -> 150476.46 | I29: =I13-I28 -> 30828.371 | ... M29: =M13-M28 -> 120686.11 | N29: =sum(B29:M29) -> 1246160.4 | O29: =N29/N13 -> 0.10830725
A30: Food Cost | B30: =(B14/B13) -> 0.25414954 | C30: =(C14/C13) -> 0.25469844 | D30: =(D14/D13) -> 0.2571238 | E30: =(E14/E13) -> 0.27379533 | F30: =(F14/F13) -> 0.27432481 | G30: =(G14/G13) -> 0.26828076 | H30: =(H14/H13) -> 0.26673595 | I30: =(I14/I13) -> 0.29328605 | ... M30: =(M14/M13) -> 0.2873053
B32: =B29+B27 -> 275489.31 | C32: =C29+C27 -> 378232.44 | D32: =D29+D27 -> 366059.39 | E32: =E29+E27 -> 309139.06 | F32: =F29+F27 -> 345560.11 | G32: =G29+G27 -> 353535.78 | H32: =H29+H27 -> 339195.36 | I32: =I29+I27 -> 226338.75 | ... M32: =M29+M27 -> 312901.13
B33: =B32/B13 -> 0.31680134 | C33: =C32/C13 -> 0.36559533 | D33: =D32/D13 -> 0.36352913 | E33: =E32/E13 -> 0.32274985 | F33: =F32/F13 -> 0.34476077 | G33: =G32/G13 -> 0.33743475 | H33: =H32/H13 -> 0.3463691 | I33: =I32/I13 -> 0.24976571 | ... M33: =M32/M13 -> 0.29980447

Sheet Chinar Park
A1: Dosa Coffee - Chinar Park | B1: 45748 | C1: 45778 | D1: 45809 | E1: 45839 | F1: 45870 | G1: 45901 | H1: 45931 | I1: 45962 | J1: 45992 | K1: 46023 | L1: 46054 | M1: 46082 | N1: FY 2025-26
A2: Food Cost Calculation
A3: Opening Stock | B3: 21194.92 | C3: =B7 -> 21050 | D3: =C7 -> 20124.19 | E3: =D7 -> 20673 | F3: =E7 -> 20106 | G3: =F7 -> 18750.26 | H3: =G7 -> 26751.92 | I3: =H7 -> 26621.51 | J3: =I7 -> 19499.95 | ... M3: =L7 -> 17507.71 | N3: =+SUM(J3:L3) -> 65124.86
A4: Purchases Food (Less Purchase Return) | B4: 125825.06 | C4: 154923.55 | D4: 144937.6 | E4: 164200.72 | F4: 159612 | G4: 183936 | H4: =187759.26 -> 187759.26 | I4: 162872.58 | J4: 181868.83 | K4: 162489 | L4: =169946.16 -> 169946.16 | M4: 226082.33 | N4: =sum(B4:M4) -> 2024453.1
A5: Transferred Out | B5: 368.17 | C5: 548.1 | D5: 635.58 | E5: 578 | F5: 297 | G5: 309.33 | H5: 606.6 | I5: 843.62 | J5: 848 | K5: 59 | L5: 31.13 | M5: 0 | N5: =+SUM(J5:L5) -> 938.13
A6: Wastage & Date Expired | B6: 6637.47 | C6: 6124.53 | D6: 6901.46 | E6: 5118.28 | F6: 5208 | G6: 5073.82 | H6: 5293.62 | I6: 4818.84 | J6: 4708 | K6: 4687 | L6: 3450.55 | M6: 5412.21 | N6: =+SUM(J6:L6) -> 12845.55
A7: Closing Stock | B7: 21050 | C7: 20124.19 | D7: 20673 | E7: 20106 | F7: 18750.26 | G7: 26751.92 | H7: 26621.51 | I7: 19499.95 | J7: 24585 | K7: 21039.91 | L7: =17507.71 -> 17507.71 | M7: 19436.14 | N7: =sum(B7:M7) -> 256145.59
A9: Gross Revenue | B9: =441871.49*1.05+19714.69*1.05 -> 484665.49 | C9: =500069.72*1.05+21974.12*1.05+50*1.05 -> 548198.53 | D9: =537670*1.05+25815.55*1.05 -> 591659.83 | E9: =553869.55*1.05+24114*1.05 -> 606882.73 | F9: =562265.38*1.05+26957*1.05 -> 618683.5 | G9: =670058.61*1.05 -> 703561.54 | H9: =669654.65*1.05+33287.61*1.05+20*1.05 -> 738110.37 | I9: =604108.71*1.05+34205.39*1.05 -> 670229.81 | J9: =642876.88*1.05+32078.13*1.05 -> 708702.76 | K9: =577898.61*1.05+28161.08*1.05 -> 636362.67 | L9: =595497.01*1.05+32204*1.05 -> 659086.06 | M9: =785753.56*1.05+40292.38*1.05 -> 867348.24 | N9: =+SUM(B9:M9) -> 7833491.5
A10: Catering & Fairs | B10: 0 | C10: 0 | D10: 0 | E10: 0 | F10: 0 | G10: 0 | H10: 0 | I10: 0 | J10: 0 | K10: 0 | L10: 0 | M10: 0 | N10: =+SUM(B10:M10) -> 0
A11: Less Tax | B11: =(B9+B10)/1.05*0.05 -> 23079.309 | C11: =(C9+C10)/1.05*0.05 -> 26104.692 | D11: =(D9+D10)/1.05*0.05 -> 28174.278 | E11: =(E9+E10)/1.05*0.05 -> 28899.178 | F11: =(F9+F10)/1.05*0.05 -> 29461.119 | G11: =(G9+G10)/1.05*0.05 -> 33502.931 | H11: =(H9+H10)/1.05*0.05 -> 35148.113 | I11: =(I9+I10)/1.05*0.05 -> 31915.705 | ... M11: =(M9+M10)/1.05*0.05 -> 41302.297 | N11: =+SUM(B11:M11) -> 373023.41
A12: Less Commission | B12: =45473.44+8185.22+38976.97+7015.86+6951 -> 106602.49 | C12: =9123.24+50684.68+44101.49+7938.27+2141.16 -> 113988.84 | D12: =59427.36+10696+36440.27+8700.4+19009.83+3421.77 -> 137695.63 | E12: =55325.06+9958.51+49294.52+8873.02+10117+1821 -> 135389.11 | F12: =42396.87+7631.43+61859.29+11134.67+16534.39+3346.56+2976.19 -> 145879.4 | G12: =72869.69*1.18+61895.6*1.18 -> 159023.04 | H12: =76344.11*1.18+54219.99*1.18+11312.78*1.18 -> 167414.72 | I12: =78477.63*1.18+49415.82*1.18 -> 150914.27 | J12: =73737.51*1.18+59909.74*1.18 -> 157703.76 | K12: =64927.89*1.18+52944*1.18 -> 139088.83 | L12: =86725+24148.35+26689.84+4346.71+1269.72*1.18 -> 143408.17 | M12: =92825.42*1.18+43815.96*1.18+23945.05*1.18 -> 189491.99 | N12: =+SUM(B12:M12) -> 1746600.2
A13: Net Revenues from F&B Sales | B13: =B9+B10-B11-B12 -> 354983.69 | C13: =C9+C10-C11-C12 -> 408105 | D13: =D9+D10-D11-D12 -> 425789.92 | E13: =E9+E10-E11-E12 -> 442594.44 | F13: =F9+F10-F11-F12 -> 443342.98 | G13: =G9+G10-G11-G12 -> 511035.57 | H13: =H9+H10-H11-H12 -> 535547.54 | I13: =I9+I10-I11-I12 -> 487399.83 | ... M13: =M9+M10-M11-M12 -> 636553.95 | N13: =sum(B13:M13) -> 5713867.9
A14: F&B Cost | B14: =+B3+B4-B5-B7 -> 125601.81 | C14: =+C3+C4-C5-C7 -> 155301.26 | D14: =+D3+D4-D5-D7 -> 143753.21 | E14: =+E3+E4-E5-E7 -> 164189.72 | F14: =+F3+F4-F5-F7 -> 160670.74 | G14: =+G3+G4-G5-G7 -> 175625.01 | H14: =+H3+H4-H5-H7 -> 187283.07 | I14: =+I3+I4-I5-I7 -> 169150.52 | ... M14: =+M3+M4-M5-M7 -> 224153.9 | N14: =sum(B14:M14) -> 2021087.3 | O14: =N14/$N$13 -> 0.35371615
A15: Electricity | B15: 31605 | C15: 33618 | D15: =33281 -> 33281 | E15: 34991 | F15: =34258 -> 34258 | G15: 39546 | H15: 38298 | I15: 33976.8 | J15: 32494 | K15: =31777 -> 31777 | L15: 31340 | M15: 41776.8 | N15: =sum(B15:M15) -> 416961.6 | O15: =N15/$N$13 -> 0.072973616
A16: Telephone/Internet | B16: =1003+352.82 -> 1355.82 | C16: =1003+352.82 -> 1355.82 | D16: =1003.25+352.82 -> 1356.07 | E16: =1003.25+352.82 -> 1356.07 | F16: =1003+352.82 -> 1355.82 | G16: =1003+352.82 -> 1355.82 | H16: =1003+352.82 -> 1355.82 | I16: =352.82 -> 352.82 | J16: =352.82 -> 352.82 | K16: =1003+352.82 -> 1355.82 | L16: =1003+352.82 -> 1355.82 | M16: =1003+352.82 -> 1355.82 | N16: =sum(B16:M16) -> 14264.34 | O16: =N16/$N$13 -> 0.002496442
A17: Gas | N17: =sum(B17:M17) -> 0 | O17: =N17/$N$13 -> 0
A18: Rent & Revenue Share | B18: 16000 | C18: =16000*1.18 -> 18880 | D18: =16000*1.18 -> 18880 | E18: =16000*1.18 -> 18880 | F18: =16000*1.18 -> 18880 | G18: =16000*1.18 -> 18880 | H18: =16000*1.18 -> 18880 | I18: =16000*1.18 -> 18880 | J18: =16000*1.18 -> 18880 | ... M18: =16000*1.18 -> 18880 | N18: =sum(B18:M18) -> 223680 | O18: =N18/$N$13 -> 0.039146862
A19: Software | B19: =3343 -> 3343 | C19: =3343 -> 3343 | D19: =3343 -> 3343 | E19: =3343 -> 3343 | F19: =3343 -> 3343 | G19: =3343 -> 3343 | H19: =45135/12 -> 3761.25 | I19: =45135/12 -> 3761.25 | J19: =45135/12 -> 3761.25 | K19: =45135/12 -> 3761.25 | L19: =45135/12 -> 3761.25 | M19: =45135/12 -> 3761.25 | N19: =sum(B19:M19) -> 42625.5 | O19: =N19/$N$13 -> 0.007460008
A20: Staff Salary & Bonus | B20: =90230+55386/12 -> 94845.5 | C20: =91630+55386/12 -> 96245.5 | D20: =64117.08+23938.42+1639.51+55386/12 -> 94310.51 | E20: =89945.01+55386/12 -> 94560.51 | F20: =109545.01+55386/12 -> 114160.51 | G20: =109545+55386/12 -> 114160.5 | H20: =55386/12+95635.98 -> 100251.48 | I20: =55386/12+89040 -> 93655.5 | J20: =55386/12+88541 -> 93156.5 | K20: =55386/12+88541 -> 93156.5 | L20: =55386/12+88541 -> 93156.5 | M20: =55386/12+88541 -> 93156.5 | N20: =sum(B20:M20) -> 1174816 | O20: =N20/$N$13 -> 0.20560784
A21: AMC | B21: =1239+2360+13587/12 -> 4731.25 | C21: =1239+2360+13587/12 -> 4731.25 | D21: =1239+2360+13587/12 -> 4731.25 | E21: =1239+2360+13587/12 -> 4731.25 | F21: =1239+2360+13587/12 -> 4731.25 | G21: =13587/12+2360+1239 -> 4731.25 | H21: =13587/12+2360+1239 -> 4731.25 | I21: =13587/12+2360+1239 -> 4731.25 | J21: =13587/12+1239+2360 -> 4731.25 | K21: =13587/12+2360+1239 -> 4731.25 | L21: =13587/12+1239+2360 -> 4731.25 | M21: =13587/12+2360+1239 -> 4731.25 | N21: =sum(B21:M21) -> 56775 | O21: =N21/$N$13 -> 0.0099363516
A22: Subscription | B22: =2124/3 -> 708 | C22: =2124/3 -> 708 | D22: =2124/3 -> 708 | E22: =2124/3 -> 708 | F22: =2124/3 -> 708 | G22: =2124/3 -> 708 | H22: =2124/3 -> 708 | I22: =2124/3 -> 708 | J22: =2124/3 -> 708 | K22: =3271.32/3 -> 1090.44 | L22: =3271.32/3 -> 1090.44 | M22: =3271.32/3 -> 1090.44 | N22: =sum(B22:M22) -> 9643.32 | O22: =N22/$N$13 -> 0.0016877044
