Workbook

Sheet Summary
A2: Dosa Coffee - NCR | B2: Department | C2: 45748 | D2: 45778 | E2: 45809 | F2: 45839 | G2: 45870 | H2: 45901 | I2: 45931 | J2: 45962 | K2: 45992 | L2: 46023 | M2: 46054 | N2: 46082 | O2: FY 2025-26
A3: Food Cost Calculation
A4: Opening Stock | B4: Procurement | C4: ='Noida Sec - 18'!B3+'Noida Sec -143'!B3+DLF!B3+'Faridabad Sec15'!B3+'Gurgaon Sec-15'!B3+'Gurgaon Sec - 10'!B3+'Paschim Vihar'!B3+Kalkaji!B3+CP!B3+Rohini!B3+'Model Town'!B3+'Pacific Mall'!B3+'Shalimar Bagh'!B3 -> 871359 | D4: ='Noida Sec - 18'!C3+'Noida Sec -143'!C3+DLF!C3+'Faridabad Sec15'!C3+'Gurgaon Sec-15'!C3+'Gurgaon Sec - 10'!C3+'Paschim Vihar'!C3+Kalkaji!C3+CP!C3+Rohini!C3+'Model Town'!C3+'Pacific Mall'!C3 -> 871581.38 | E4: ='Noida Sec - 18'!D3+'Noida Sec -143'!D3+DLF!D3+'Faridabad Sec15'!D3+'Gurgaon Sec-15'!D3+'Gurgaon Sec - 10'!D3+'Gurgaon Sector 31'!D3+'Paschim Vihar'!D3+Kalkaji!D3+CP!D3+Rohini!D3+'Model Town'!D3+'Pacific Mall'!D3+'Shalimar Bagh'!D3 -> 901128.86 | F4: ='Noida Sec - 18'!E3+'Noida Sec -143'!E3+DLF!E3+'Faridabad Sec15'!E3+'Gurgaon Sec-15'!E3+'Gurgaon Sec - 10'!E3+'Gurgaon Sector 31'!E3+'Paschim Vihar'!E3+Kalkaji!E3+CP!E3+Rohini!E3+'Model Town'!E3+'Pacific Mall'!E3+'Shalimar Bagh'!E3 -> 843369.96 | G4: ='Noida Sec - 18'!F3+'Noida Sec -143'!F3+DLF!F3+'Faridabad Sec15'!F3+'Gurgaon Sec-15'!F3+'Gurgaon Sec - 10'!F3+'Gurgaon Sector 31'!F3+'Paschim Vihar'!F3+Kalkaji!F3+CP!F3+Rohini!F3+'Model Town'!F3+'Pacific Mall'!F3+'Shalimar Bagh'!F3 -> 778147.1 | H4: ='Noida Sec - 18'!G3+'Noida Sec -143'!G3+DLF!G3+'Faridabad Sec15'!G3+'Gurgaon Sec-15'!G3+'Gurgaon Sec - 10'!G3+'Gurgaon Sector 31'!G3+'Paschim Vihar'!G3+Kalkaji!G3+CP!G3+Rohini!G3+'Model Town'!G3+'Pacific Mall'!G3+'Shalimar Bagh'!G3 -> 746317.86 | I4: ='Noida Sec - 18'!H3+'Noida Sec -143'!H3+DLF!H3+'Faridabad Sec15'!H3+'Gurgaon Sec-15'!H3+'Gurgaon Sec - 10'!H3+'Gurgaon Sector 31'!H3+'Paschim Vihar'!H3+Kalkaji!H3+CP!H3+Rohini!H3+'Model Town'!H3+'Pacific Mall'!H3+'Shalimar Bagh'!H3 -> 300476.16 | J4: ='Noida Sec - 18'!I3+'Noida Sec -143'!I3+DLF!I3+'Faridabad Sec15'!I3+'Gurgaon Sec-15'!I3+'Gurgaon Sec - 10'!I3+'Paschim Vihar'!I3+Kalkaji!I3+CP!I3+Rohini!I3+'Model Town'!I3+'Pacific Mall'!I3 -> 0 | K4: ='Noida Sec - 18'!J3+'Noida Sec -143'!J3+DLF!J3+'Faridabad Sec15'!J3+'Gurgaon Sec-15'!J3+'Gurgaon Sec - 10'!J3+'Paschim Vihar'!J3+Kalkaji!J3+CP!J3+Rohini!J3+'Model Town'!J3+'Pacific Mall'!J3 -> 0 | L4: ='Noida Sec - 18'!K3+'Noida Sec -143'!K3+DLF!K3+'Faridabad Sec15'!K3+'Gurgaon Sec-15'!K3+'Gurgaon Sec - 10'!K3+'Paschim Vihar'!K3+Kalkaji!K3+CP!K3+Rohini!K3+'Model Town'!K3+'Pacific Mall'!K3 -> 0 | M4: ='Noida Sec - 18'!L3+'Noida Sec -143'!L3+DLF!L3+'Faridabad Sec15'!L3+'Gurgaon Sec-15'!L3+'Gurgaon Sec - 10'!L3+'Paschim Vihar'!L3+Kalkaji!L3+CP!L3+Rohini!L3+'Model Town'!L3+'Pacific Mall'!L3 -> 0 | N4: ='Noida Sec - 18'!M3+'Noida Sec -143'!M3+DLF!M3+'Faridabad Sec15'!M3+'Gurgaon Sec-15'!M3+'Gurgaon Sec - 10'!M3+'Paschim Vihar'!M3+Kalkaji!M3+CP!M3+Rohini!M3+'Model Town'!M3+'Pacific Mall'!M3+'Shalimar Bagh'!M3 -> 0 | R4: 850672 | S4: =C4-R4 -> 20687 | U4: =6736750.78-186270-304531 -> 6245949.8 | V4: 6406016
A5: Purchases Food (Less Purchase Return) | B5: Procurement | C5: ='Noida Sec - 18'!B4+'Noida Sec -143'!B4+DLF!B4+'Faridabad Sec15'!B4+'Gurgaon Sec-15'!B4+'Gurgaon Sec - 10'!B4+'Paschim Vihar'!B4+Kalkaji!B4+CP!B4+Rohini!B4+'Model Town'!B4+'Pacific Mall'!B4+'Shalimar Bagh'!B4+285196 -> 6018343.5 | D5: ='Noida Sec - 18'!C4+'Noida Sec -143'!C4+DLF!C4+'Faridabad Sec15'!C4+'Gurgaon Sec-15'!C4+'Gurgaon Sec - 10'!C4+'Paschim Vihar'!C4+Kalkaji!C4+CP!C4+Rohini!C4+'Model Town'!C4+'Pacific Mall'!C4+'Shalimar Bagh'!C4+'Gurgaon Sector 31'!C4+150525 -> 6203393.9 | E5: ='Noida Sec - 18'!D4+'Noida Sec -143'!D4+DLF!D4+'Faridabad Sec15'!D4+'Gurgaon Sec-15'!D4+'Gurgaon Sec - 10'!D4+'Gurgaon Sector 31'!D4+'Paschim Vihar'!D4+Kalkaji!D4+CP!D4+Rohini!D4+'Model Town'!D4+'Pacific Mall'!D4+'Shalimar Bagh'!D4+314521 -> 6404315.8 | F5: ='Noida Sec - 18'!E4+'Noida Sec -143'!E4+DLF!E4+'Faridabad Sec15'!E4+'Gurgaon Sec-15'!E4+'Gurgaon Sec - 10'!E4+'Gurgaon Sector 31'!E4+'Paschim Vihar'!E4+Kalkaji!E4+CP!E4+Rohini!E4+'Model Town'!E4+'Pacific Mall'!E4+'Shalimar Bagh'!E4 -> 5892054.8 | G5: ='Noida Sec - 18'!F4+'Noida Sec -143'!F4+'Faridabad Sec15'!F4+DLF!F4+'Gurgaon Sec-15'!F4+'Paschim Vihar'!F4+Kalkaji!F4+CP!F4+Rohini!F4+'Model Town'!F4+'Pacific Mall'!F4 -> 5592889.2 | H5: ='Noida Sec - 18'!G4+'Noida Sec -143'!G4+'Faridabad Sec15'!G4+DLF!G4+'Gurgaon Sec-15'!G4+'Paschim Vihar'!G4+Kalkaji!G4+CP!G4+Rohini!G4+'Model Town'!G4+'Pacific Mall'!G4 -> 1809423.1 | I5: ='Noida Sec - 18'!H4+'Noida Sec -143'!H4+'Faridabad Sec15'!H4+DLF!H4+'Gurgaon Sec-15'!H4+'Paschim Vihar'!H4+Kalkaji!H4+CP!H4+Rohini!H4+'Model Town'!H4+'Pacific Mall'!H4 -> 0 | J5: ='Noida Sec - 18'!I4+'Noida Sec -143'!I4+'Faridabad Sec15'!I4+DLF!I4+'Gurgaon Sec-15'!I4+'Paschim Vihar'!I4+Kalkaji!I4+CP!I4+Rohini!I4+'Model Town'!I4+'Pacific Mall'!I4 -> 0 | K5: ='Noida Sec - 18'!J4+'Noida Sec -143'!J4+'Faridabad Sec15'!J4+DLF!J4+'Gurgaon Sec-15'!J4+'Paschim Vihar'!J4+Kalkaji!J4+CP!J4+Rohini!J4+'Model Town'!J4+'Pacific Mall'!J4+'Gurgaon Sec - 10'!J4 -> 0 | L5: ='Noida Sec - 18'!K4+'Noida Sec -143'!K4+'Faridabad Sec15'!K4+DLF!K4+'Gurgaon Sec-15'!K4+'Paschim Vihar'!K4+Kalkaji!K4+CP!K4+Rohini!K4+'Model Town'!K4+'Pacific Mall'!K4+'Gurgaon Sec - 10'!K4 -> 0 | M5: ='Noida Sec - 18'!L4+'Noida Sec -143'!L4+DLF!L4+'Faridabad Sec15'!L4+'Gurgaon Sec-15'!L4+'Gurgaon Sec - 10'!L4+'Paschim Vihar'!L4+Kalkaji!L4+CP!L4+Rohini!L4+'Model Town'!L4+'Pacific Mall'!L4 -> 0 | N5: ='Noida Sec - 18'!M4+'Noida Sec -143'!M4+DLF!M4+'Faridabad Sec15'!M4+'Gurgaon Sec-15'!M4+'Gurgaon Sec - 10'!M4+'Paschim Vihar'!M4+Kalkaji!M4+CP!M4+Rohini!M4+'Model Town'!M4+'Pacific Mall'!M4+'Shalimar Bagh'!M4 -> 0 | R5: 5694719 | S5: =C5-R5 -> 323624.5 | U5: -42555 | V5: =E5 -> 6404315.8
A6: Transferred Out | B6: Procurement | C6: ='Noida Sec - 18'!B5+'Noida Sec -143'!B5+DLF!B5+'Faridabad Sec15'!B5+'Gurgaon Sec-15'!B5+'Gurgaon Sec - 10'!B5+'Paschim Vihar'!B5+Kalkaji!B5+CP!B5+Rohini!B5+'Model Town'!B5+'Pacific Mall'!B5+'Shalimar Bagh'!B5 -> 2618 | D6: ='Noida Sec - 18'!C5+'Noida Sec -143'!C5+DLF!C5+'Faridabad Sec15'!C5+'Gurgaon Sec-15'!C5+'Gurgaon Sec - 10'!C5+'Paschim Vihar'!C5+Kalkaji!C5+CP!C5+Rohini!C5+'Model Town'!C5+'Pacific Mall'!C5+'Shalimar Bagh'!C5 -> 255.24 | E6: ='Noida Sec - 18'!D5+'Noida Sec -143'!D5+DLF!D5+'Faridabad Sec15'!D5+'Gurgaon Sec-15'!D5+'Gurgaon Sec - 10'!D5+'Paschim Vihar'!D5+Kalkaji!D5+CP!D5+Rohini!D5+'Model Town'!D5+'Pacific Mall'!D5+'Shalimar Bagh'!D5 -> 58857.92 | F6: ='Noida Sec - 18'!E5+'Noida Sec -143'!E5+DLF!E5+'Faridabad Sec15'!E5+'Gurgaon Sec-15'!E5+'Gurgaon Sec - 10'!E5+'Paschim Vihar'!E5+Kalkaji!E5+CP!E5+Rohini!E5+'Model Town'!E5+'Pacific Mall'!E5+'Shalimar Bagh'!E5 -> 0 | G6: ='Noida Sec - 18'!F5+'Noida Sec -143'!F5+'Faridabad Sec15'!F5+DLF!F5+'Gurgaon Sec-15'!F5+'Paschim Vihar'!F5+Kalkaji!F5+CP!F5+Rohini!F5+'Model Town'!F5+'Pacific Mall'!F5 -> 0 | H6: ='Noida Sec - 18'!G5+'Noida Sec -143'!G5+'Faridabad Sec15'!G5+DLF!G5+'Gurgaon Sec-15'!G5+'Paschim Vihar'!G5+Kalkaji!G5+CP!G5+Rohini!G5+'Model Town'!G5+'Pacific Mall'!G5 -> 0 | I6: ='Noida Sec - 18'!H5+'Noida Sec -143'!H5+'Faridabad Sec15'!H5+DLF!H5+'Gurgaon Sec-15'!H5+'Paschim Vihar'!H5+Kalkaji!H5+CP!H5+Rohini!H5+'Model Town'!H5+'Pacific Mall'!H5 -> 0 | J6: ='Noida Sec - 18'!I5+'Noida Sec -143'!I5+'Faridabad Sec15'!I5+DLF!I5+'Gurgaon Sec-15'!I5+'Paschim Vihar'!I5+Kalkaji!I5+CP!I5+Rohini!I5+'Model Town'!I5+'Pacific Mall'!I5 -> 0 | K6: ='Noida Sec - 18'!J5+'Noida Sec -143'!J5+'Faridabad Sec15'!J5+DLF!J5+'Gurgaon Sec-15'!J5+'Paschim Vihar'!J5+Kalkaji!J5+CP!J5+Rohini!J5+'Model Town'!J5+'Pacific Mall'!J5+'Gurgaon Sec - 10'!J5 -> 0 | L6: ='Noida Sec - 18'!K5+'Noida Sec -143'!K5+'Faridabad Sec15'!K5+DLF!K5+'Gurgaon Sec-15'!K5+'Paschim Vihar'!K5+Kalkaji!K5+CP!K5+Rohini!K5+'Model Town'!K5+'Pacific Mall'!K5+'Gurgaon Sec - 10'!K5 -> 0 | M6: ='Noida Sec - 18'!L5+'Noida Sec -143'!L5+DLF!L5+'Faridabad Sec15'!L5+'Gurgaon Sec-15'!L5+'Gurgaon Sec - 10'!L5+'Paschim Vihar'!L5+Kalkaji!L5+CP!L5+Rohini!L5+'Model Town'!L5+'Pacific Mall'!L5 -> 0 | N6: ='Noida Sec - 18'!M5+'Noida Sec -143'!M5+DLF!M5+'Faridabad Sec15'!M5+'Gurgaon Sec-15'!M5+'Gurgaon Sec - 10'!M5+'Paschim Vihar'!M5+Kalkaji!M5+CP!M5+Rohini!M5+'Model Town'!M5+'Pacific Mall'!M5+'Shalimar Bagh'!M5 -> 0 | R6: 3115 | S6: =C6-R6 -> -497 | U6: =U4+U5 -> 6203394.8 | V6: =V4-V5 -> 1700.25
A7: Wastage & Date Expired | B7: Procurement | C7: ='Noida Sec - 18'!B6+'Noida Sec -143'!B6+DLF!B6+'Faridabad Sec15'!B6+'Gurgaon Sec-15'!B6+'Gurgaon Sec - 10'!B6+'Paschim Vihar'!B6+Kalkaji!B6+CP!B6+Rohini!B6+'Model Town'!B6+'Pacific Mall'!B6+'Shalimar Bagh'!B6 -> 332697.6 | D7: ='Noida Sec - 18'!C6+'Noida Sec -143'!C6+DLF!C6+'Faridabad Sec15'!C6+'Gurgaon Sec-15'!C6+'Gurgaon Sec - 10'!C6+'Paschim Vihar'!C6+Kalkaji!C6+CP!C6+Rohini!C6+'Model Town'!C6+'Pacific Mall'!C6+'Shalimar Bagh'!C6 -> 371280.15 | E7: ='Noida Sec - 18'!D6+'Noida Sec -143'!D6+DLF!D6+'Faridabad Sec15'!D6+'Gurgaon Sec-15'!D6+'Gurgaon Sec - 10'!D6+'Gurgaon Sector 31'!D6+'Paschim Vihar'!D6+Kalkaji!D6+CP!D6+Rohini!D6+'Model Town'!D6+'Pacific Mall'!D6+'Shalimar Bagh'!D6 -> 359511.46 | F7: ='Noida Sec - 18'!E6+'Noida Sec -143'!E6+DLF!E6+'Faridabad Sec15'!E6+'Gurgaon Sec-15'!E6+'Gurgaon Sec - 10'!E6+'Gurgaon Sector 31'!E6+'Paschim Vihar'!E6+Kalkaji!E6+CP!E6+Rohini!E6+'Model Town'!E6+'Pacific Mall'!E6+'Shalimar Bagh'!E6 -> 330564.45 | G7: ='Noida Sec - 18'!F6+'Noida Sec -143'!F6+'Faridabad Sec15'!F6+DLF!F6+'Gurgaon Sec-15'!F6+'Paschim Vihar'!F6+Kalkaji!F6+CP!F6+Rohini!F6+'Model Town'!F6+'Pacific Mall'!F6 -> 299777.48 | H7: ='Noida Sec - 18'!G6+'Noida Sec -143'!G6+'Faridabad Sec15'!G6+DLF!G6+'Gurgaon Sec-15'!G6+'Paschim Vihar'!G6+Kalkaji!G6+CP!G6+Rohini!G6+'Model Town'!G6+'Pacific Mall'!G6 -> 88417 | I7: ='Noida Sec - 18'!H6+'Noida Sec -143'!H6+'Faridabad Sec15'!H6+DLF!H6+'Gurgaon Sec-15'!H6+'Paschim Vihar'!H6+Kalkaji!H6+CP!H6+Rohini!H6+'Model Town'!H6+'Pacific Mall'!H6 -> 0 | J7: ='Noida Sec - 18'!I6+'Noida Sec -143'!I6+'Faridabad Sec15'!I6+DLF!I6+'Gurgaon Sec-15'!I6+'Paschim Vihar'!I6+Kalkaji!I6+CP!I6+Rohini!I6+'Model Town'!I6+'Pacific Mall'!I6 -> 0 | K7: ='Noida Sec - 18'!J6+'Noida Sec -143'!J6+'Faridabad Sec15'!J6+DLF!J6+'Gurgaon Sec-15'!J6+'Paschim Vihar'!J6+Kalkaji!J6+CP!J6+Rohini!J6+'Model Town'!J6+'Pacific Mall'!J6+'Gurgaon Sec - 10'!J6 -> 0 | L7: ='Noida Sec - 18'!K6+'Noida Sec -143'!K6+'Faridabad Sec15'!K6+DLF!K6+'Gurgaon Sec-15'!K6+'Paschim Vihar'!K6+Kalkaji!K6+CP!K6+Rohini!K6+'Model Town'!K6+'Pacific Mall'!K6+'Gurgaon Sec - 10'!K6 -> 0 | M7: ='Noida Sec - 18'!L6+'Noida Sec -143'!L6+DLF!L6+'Faridabad Sec15'!L6+'Gurgaon Sec-15'!L6+'Gurgaon Sec - 10'!L6+'Paschim Vihar'!L6+Kalkaji!L6+CP!L6+Rohini!L6+'Model Town'!L6+'Pacific Mall'!L6 -> 0 | N7: ='Noida Sec - 18'!M6+'Noida Sec -143'!M6+DLF!M6+'Faridabad Sec15'!M6+'Gurgaon Sec-15'!M6+'Gurgaon Sec - 10'!M6+'Paschim Vihar'!M6+Kalkaji!M6+CP!M6+Rohini!M6+'Model Town'!M6+'Pacific Mall'!M6+'Shalimar Bagh'!M6 -> 0 | R7: 344801 | S7: =C7-R7 -> -12103.4 | U7: =U6-D5 -> 0.88 | V7: -1700
A8: Closing Stock | B8: Procurement | C8: ='Noida Sec - 18'!B7+'Noida Sec -143'!B7+DLF!B7+'Faridabad Sec15'!B7+'Gurgaon Sec-15'!B7+'Gurgaon Sec - 10'!B7+'Paschim Vihar'!B7+Kalkaji!B7+CP!B7+Rohini!B7+'Model Town'!B7+'Pacific Mall'!B7+'Shalimar Bagh'!B7 -> 890504.38 | D8: ='Noida Sec - 18'!C7+'Noida Sec -143'!C7+DLF!C7+'Faridabad Sec15'!C7+'Gurgaon Sec-15'!C7+'Gurgaon Sec - 10'!C7+'Paschim Vihar'!C7+Kalkaji!C7+CP!C7+Rohini!C7+'Model Town'!C7+'Pacific Mall'!C7+'Shalimar Bagh'!C7 -> 875056.86 | E8: ='Noida Sec - 18'!D7+'Noida Sec -143'!D7+DLF!D7+'Faridabad Sec15'!D7+'Gurgaon Sec-15'!D7+'Gurgaon Sec - 10'!D7+'Gurgaon Sector 31'!D7+'Paschim Vihar'!D7+Kalkaji!D7+CP!D7+Rohini!D7+'Model Town'!D7+'Pacific Mall'!D7+'Shalimar Bagh'!D7 -> 843369.96 | F8: ='Noida Sec - 18'!E7+'Noida Sec -143'!E7+DLF!E7+'Faridabad Sec15'!E7+'Gurgaon Sec-15'!E7+'Gurgaon Sec - 10'!E7+'Gurgaon Sector 31'!E7+'Paschim Vihar'!E7+Kalkaji!E7+CP!E7+Rohini!E7+'Model Town'!E7+'Pacific Mall'!E7+'Shalimar Bagh'!E7 -> 778147.1 | G8: ='Noida Sec - 18'!F7+'Noida Sec -143'!F7+DLF!F7+'Faridabad Sec15'!F7+'Gurgaon Sec-15'!F7+'Gurgaon Sec - 10'!F7+'Paschim Vihar'!F7+Kalkaji!F7+CP!F7+Rohini!F7+'Model Town'!F7+'Pacific Mall'!F7 -> 685286.86 | H8: ='Noida Sec - 18'!G7+'Noida Sec -143'!G7+DLF!G7+'Faridabad Sec15'!G7+'Gurgaon Sec-15'!G7+'Gurgaon Sec - 10'!G7+'Paschim Vihar'!G7+Kalkaji!G7+CP!G7+Rohini!G7+'Model Town'!G7+'Pacific Mall'!G7 -> 281082.93 | I8: ='Noida Sec - 18'!H7+'Noida Sec -143'!H7+DLF!H7+'Faridabad Sec15'!H7+'Gurgaon Sec-15'!H7+'Gurgaon Sec - 10'!H7+'Paschim Vihar'!H7+Kalkaji!H7+CP!H7+Rohini!H7+'Model Town'!H7+'Pacific Mall'!H7 -> 0 | J8: ='Noida Sec - 18'!I7+'Noida Sec -143'!I7+DLF!I7+'Faridabad Sec15'!I7+'Gurgaon Sec-15'!I7+'Gurgaon Sec - 10'!I7+'Paschim Vihar'!I7+Kalkaji!I7+CP!I7+Rohini!I7+'Model Town'!I7+'Pacific Mall'!I7 -> 0 | K8: ='Noida Sec - 18'!J7+'Noida Sec -143'!J7+DLF!J7+'Faridabad Sec15'!J7+'Gurgaon Sec-15'!J7+'Gurgaon Sec - 10'!J7+'Paschim Vihar'!J7+Kalkaji!J7+CP!J7+Rohini!J7+'Model Town'!J7+'Pacific Mall'!J7 -> 0 | L8: ='Noida Sec - 18'!K7+'Noida Sec -143'!K7+DLF!K7+'Faridabad Sec15'!K7+'Gurgaon Sec-15'!K7+'Gurgaon Sec - 10'!K7+'Paschim Vihar'!K7+Kalkaji!K7+CP!K7+Rohini!K7+'Model Town'!K7+'Pacific Mall'!K7 -> 0 | M8: ='Noida Sec - 18'!L7+'Noida Sec -143'!L7+DLF!L7+'Faridabad Sec15'!L7+'Gurgaon Sec-15'!L7+'Gurgaon Sec - 10'!L7+'Paschim Vihar'!L7+Kalkaji!L7+CP!L7+Rohini!L7+'Model Town'!L7+'Pacific Mall'!L7 -> 0 | N8: ='Noida Sec - 18'!M7+'Noida Sec -143'!M7+DLF!M7+'Faridabad Sec15'!M7+'Gurgaon Sec-15'!M7+'Gurgaon Sec - 10'!M7+'Paschim Vihar'!M7+Kalkaji!M7+CP!M7+Rohini!M7+'Model Town'!M7+'Pacific Mall'!M7+'Shalimar Bagh'!M7 -> 0 | R8: 865957 | S8: =C8-R8 -> 24547.38
A10: Gross Revenue | B10: Operation | C10: ='Noida Sec - 18'!B9+'Noida Sec -143'!B9+DLF!B9+'Faridabad Sec15'!B9+'Gurgaon Sec-15'!B9+'Gurgaon Sec - 10'!B9+'Paschim Vihar'!B9+Kalkaji!B9+CP!B9+Rohini!B9+'Model Town'!B9+'Pacific Mall'!B9+'Shalimar Bagh'!B9 -> 24583139 | D10: ='Noida Sec - 18'!C9+'Noida Sec -143'!C9+DLF!C9+'Faridabad Sec15'!C9+'Gurgaon Sec-15'!C9+'Gurgaon Sec - 10'!C9+'Paschim Vihar'!C9+Kalkaji!C9+CP!C9+Rohini!C9+'Model Town'!C9+'Pacific Mall'!C9+'Shalimar Bagh'!C9+'Gurgaon Sector 31'!C9 -> 26193866 | E10: ='Noida Sec - 18'!D9+'Noida Sec -143'!D9+DLF!D9+'Faridabad Sec15'!D9+'Gurgaon Sec-15'!D9+'Gurgaon Sec - 10'!D9+'Gurgaon Sector 31'!D9+'Paschim Vihar'!D9+Kalkaji!D9+CP!D9+Rohini!D9+'Model Town'!D9+'Pacific Mall'!D9+'Shalimar Bagh'!D9 -> 25442386 | F10: ='Noida Sec - 18'!E9+'Noida Sec -143'!E9+DLF!E9+'Faridabad Sec15'!E9+'Gurgaon Sec-15'!E9+'Gurgaon Sec - 10'!E9+'Gurgaon Sector 31'!E9+'Paschim Vihar'!E9+Kalkaji!E9+CP!E9+Rohini!E9+'Model Town'!E9+'Pacific Mall'!E9+'Shalimar Bagh'!E9 -> 24553889 | G10: ='Noida Sec - 18'!F9+'Noida Sec -143'!F9+'Faridabad Sec15'!F9+DLF!F9+'Gurgaon Sec-15'!F9+'Paschim Vihar'!F9+Kalkaji!F9+CP!F9+Rohini!F9+'Model Town'!F9+'Pacific Mall'!F9 -> 0 | H10: ='Noida Sec - 18'!G9+'Noida Sec -143'!G9+'Faridabad Sec15'!G9+DLF!G9+'Gurgaon Sec-15'!G9+'Paschim Vihar'!G9+Kalkaji!G9+CP!G9+Rohini!G9+'Model Town'!G9+'Pacific Mall'!G9 -> 0 | I10: ='Noida Sec - 18'!H9+'Noida Sec -143'!H9+'Faridabad Sec15'!H9+DLF!H9+'Gurgaon Sec-15'!H9+'Paschim Vihar'!H9+Kalkaji!H9+CP!H9+Rohini!H9+'Model Town'!H9+'Pacific Mall'!H9 -> 0 | J10: ='Noida Sec - 18'!I9+'Noida Sec -143'!I9+'Faridabad Sec15'!I9+DLF!I9+'Gurgaon Sec-15'!I9+'Paschim Vihar'!I9+Kalkaji!I9+CP!I9+Rohini!I9+'Model Town'!I9+'Pacific Mall'!I9 -> 0 | K10: ='Noida Sec - 18'!J9+'Noida Sec -143'!J9+'Faridabad Sec15'!J9+DLF!J9+'Gurgaon Sec-15'!J9+'Paschim Vihar'!J9+Kalkaji!J9+CP!J9+Rohini!J9+'Model Town'!J9+'Pacific Mall'!J9+'Gurgaon Sec - 10'!J9 -> 0 | L10: ='Noida Sec - 18'!K9+'Noida Sec -143'!K9+'Faridabad Sec15'!K9+DLF!K9+'Gurgaon Sec-15'!K9+'Paschim Vihar'!K9+Kalkaji!K9+CP!K9+Rohini!K9+'Model Town'!K9+'Pacific Mall'!K9+'Gurgaon Sec - 10'!K9 -> 0 | M10: ='Noida Sec - 18'!L9+'Noida Sec -143'!L9+'Faridabad Sec15'!L9+DLF!L9+'Gurgaon Sec-15'!L9+'Paschim Vihar'!L9+Kalkaji!L9+CP!L9+Rohini!L9+'Model Town'!L9+'Pacific Mall'!L9+'Gurgaon Sec - 10'!L9 -> 0 | N10: ='Noida Sec - 18'!M9+'Noida Sec -143'!M9+'Faridabad Sec15'!M9+DLF!M9+'Gurgaon Sec-15'!M9+'Paschim Vihar'!M9+Kalkaji!M9+CP!M9+Rohini!M9+'Model Town'!M9+'Pacific Mall'!M9+'Gurgaon Sec - 10'!M9+'Shalimar Bagh'!M9 -> 0 | O10: =+SUM(C10:N10) -> 1.0077328e+08 | R10: 23420696 | S10: =C10-R10 -> 1162443.1
A11: Catering & Fairs | B11: Operation | C11: ='Noida Sec - 18'!B10+'Noida Sec -143'!B10+DLF!B10+'Faridabad Sec15'!B10+'Gurgaon Sec-15'!B10+'Gurgaon Sec - 10'!B10+'Paschim Vihar'!B10+Kalkaji!B10+CP!B10+Rohini!B10+'Model Town'!B10+'Pacific Mall'!B10+'Shalimar Bagh'!B10 -> 0 | D11: ='Noida Sec - 18'!C10+'Noida Sec -143'!C10+DLF!C10+'Faridabad Sec15'!C10+'Gurgaon Sec-15'!C10+'Gurgaon Sec - 10'!C10+'Paschim Vihar'!C10+Kalkaji!C10+CP!C10+Rohini!C10+'Model Town'!C10+'Pacific Mall'!C10+'Shalimar Bagh'!C10+'Gurgaon Sector 31'!C10 -> 0 | E11: ='Noida Sec - 18'!D10+'Noida Sec -143'!D10+DLF!D10+'Faridabad Sec15'!D10+'Gurgaon Sec-15'!D10+'Gurgaon Sec - 10'!D10+'Gurgaon Sector 31'!D10+'Paschim Vihar'!D10+Kalkaji!D10+CP!D10+Rohini!D10+'Model Town'!D10+'Pacific Mall'!D10+'Shalimar Bagh'!D10 -> 0 | F11: ='Noida Sec - 18'!E10+'Noida Sec -143'!E10+DLF!E10+'Faridabad Sec15'!E10+'Gurgaon Sec-15'!E10+'Gurgaon Sec - 10'!E10+'Gurgaon Sector 31'!E10+'Paschim Vihar'!E10+Kalkaji!E10+CP!E10+Rohini!E10+'Model Town'!E10+'Pacific Mall'!E10+'Shalimar Bagh'!E10 -> 0 | G11: ='Noida Sec - 18'!F10+'Noida Sec -143'!F10+'Faridabad Sec15'!F10+DLF!F10+'Gurgaon Sec-15'!F10+'Paschim Vihar'!F10+Kalkaji!F10+CP!F10+Rohini!F10+'Model Town'!F10+'Pacific Mall'!F10 -> 0 | H11: ='Noida Sec - 18'!G10+'Noida Sec -143'!G10+'Faridabad Sec15'!G10+DLF!G10+'Gurgaon Sec-15'!G10+'Paschim Vihar'!G10+Kalkaji!G10+CP!G10+Rohini!G10+'Model Town'!G10+'Pacific Mall'!G10 -> 0 | I11: ='Noida Sec - 18'!H10+'Noida Sec -143'!H10+'Faridabad Sec15'!H10+DLF!H10+'Gurgaon Sec-15'!H10+'Paschim Vihar'!H10+Kalkaji!H10+CP!H10+Rohini!H10+'Model Town'!H10+'Pacific Mall'!H10 -> 0 | J11: ='Noida Sec - 18'!I10+'Noida Sec -143'!I10+'Faridabad Sec15'!I10+DLF!I10+'Gurgaon Sec-15'!I10+'Paschim Vihar'!I10+Kalkaji!I10+CP!I10+Rohini!I10+'Model Town'!I10+'Pacific Mall'!I10 -> 0 | K11: ='Noida Sec - 18'!J10+'Noida Sec -143'!J10+'Faridabad Sec15'!J10+DLF!J10+'Gurgaon Sec-15'!J10+'Paschim Vihar'!J10+Kalkaji!J10+CP!J10+Rohini!J10+'Model Town'!J10+'Pacific Mall'!J10+'Gurgaon Sec - 10'!J10 -> 0 | L11: ='Noida Sec - 18'!K10+'Noida Sec -143'!K10+'Faridabad Sec15'!K10+DLF!K10+'Gurgaon Sec-15'!K10+'Paschim Vihar'!K10+Kalkaji!K10+CP!K10+Rohini!K10+'Model Town'!K10+'Pacific Mall'!K10 -> 0 | M11: ='Noida Sec - 18'!L10+'Noida Sec -143'!L10+'Faridabad Sec15'!L10+DLF!L10+'Gurgaon Sec-15'!L10+'Paschim Vihar'!L10+Kalkaji!L10+CP!L10+Rohini!L10+'Model Town'!L10+'Pacific Mall'!L10 -> 0 | N11: ='Noida Sec - 18'!M10+'Noida Sec -143'!M10+'Faridabad Sec15'!M10+DLF!M10+'Gurgaon Sec-15'!M10+'Paschim Vihar'!M10+Kalkaji!M10+CP!M10+Rohini!M10+'Model Town'!M10+'Pacific Mall'!M10+'Gurgaon Sec - 10'!M10+'Shalimar Bagh'!M10 -> 0 | O11: =+SUM(C11:N11) -> 0 | R11: 0 | S11: =C11-R11 -> 0
A12: Less Tax | B12: Operation | C12: ='Noida Sec - 18'!B11+'Noida Sec -143'!B11+DLF!B11+'Faridabad Sec15'!B11+'Gurgaon Sec-15'!B11+'Gurgaon Sec - 10'!B11+'Paschim Vihar'!B11+Kalkaji!B11+CP!B11+Rohini!B11+'Model Town'!B11+'Pacific Mall'!B11+'Shalimar Bagh'!B11 -> 1170625.7 | D12: ='Noida Sec - 18'!C11+'Noida Sec -143'!C11+DLF!C11+'Faridabad Sec15'!C11+'Gurgaon Sec-15'!C11+'Gurgaon Sec - 10'!C11+'Paschim Vihar'!C11+Kalkaji!C11+CP!C11+Rohini!C11+'Model Town'!C11+'Pacific Mall'!C11+'Shalimar Bagh'!C11+'Gurgaon Sector 31'!C11 -> 1247326.9 | E12: ='Noida Sec - 18'!D11+'Noida Sec -143'!D11+DLF!D11+'Faridabad Sec15'!D11+'Gurgaon Sec-15'!D11+'Gurgaon Sec - 10'!D11+'Gurgaon Sector 31'!D11+'Paschim Vihar'!D11+Kalkaji!D11+CP!D11+Rohini!D11+'Model Town'!D11+'Pacific Mall'!D11+'Shalimar Bagh'!D11 -> 1211542.2 | F12: ='Noida Sec - 18'!E11+'Noida Sec -143'!E11+DLF!E11+'Faridabad Sec15'!E11+'Gurgaon Sec-15'!E11+'Gurgaon Sec - 10'!E11+'Gurgaon Sector 31'!E11+'Paschim Vihar'!E11+Kalkaji!E11+CP!E11+Rohini!E11+'Model Town'!E11+'Pacific Mall'!E11+'Shalimar Bagh'!E11 -> 1169232.8 | G12: ='Noida Sec - 18'!F11+'Noida Sec -143'!F11+'Faridabad Sec15'!F11+DLF!F11+'Gurgaon Sec-15'!F11+'Paschim Vihar'!F11+Kalkaji!F11+CP!F11+Rohini!F11+'Model Town'!F11+'Pacific Mall'!F11 -> 0 | H12: ='Noida Sec - 18'!G11+'Noida Sec -143'!G11+'Faridabad Sec15'!G11+DLF!G11+'Gurgaon Sec-15'!G11+'Paschim Vihar'!G11+Kalkaji!G11+CP!G11+Rohini!G11+'Model Town'!G11+'Pacific Mall'!G11 -> 0 | I12: ='Noida Sec - 18'!H11+'Noida Sec -143'!H11+'Faridabad Sec15'!H11+DLF!H11+'Gurgaon Sec-15'!H11+'Paschim Vihar'!H11+Kalkaji!H11+CP!H11+Rohini!H11+'Model Town'!H11+'Pacific Mall'!H11 -> 0 | J12: ='Noida Sec - 18'!I11+'Noida Sec -143'!I11+'Faridabad Sec15'!I11+DLF!I11+'Gurgaon Sec-15'!I11+'Paschim Vihar'!I11+Kalkaji!I11+CP!I11+Rohini!I11+'Model Town'!I11+'Pacific Mall'!I11 -> 0 | K12: ='Noida Sec - 18'!J11+'Noida Sec -143'!J11+'Faridabad Sec15'!J11+DLF!J11+'Gurgaon Sec-15'!J11+'Paschim Vihar'!J11+Kalkaji!J11+CP!J11+Rohini!J11+'Model Town'!J11+'Pacific Mall'!J11+'Gurgaon Sec - 10'!J11 -> 0 | L12: ='Noida Sec - 18'!K11+'Noida Sec -143'!K11+'Faridabad Sec15'!K11+DLF!K11+'Gurgaon Sec-15'!K11+'Paschim Vihar'!K11+Kalkaji!K11+CP!K11+Rohini!K11+'Model Town'!K11+'Pacific Mall'!K11+'Gurgaon Sec - 10'!K11 -> 0 | M12: ='Noida Sec - 18'!L11+'Noida Sec -143'!L11+'Faridabad Sec15'!L11+DLF!L11+'Gurgaon Sec-15'!L11+'Paschim Vihar'!L11+Kalkaji!L11+CP!L11+Rohini!L11+'Model Town'!L11+'Pacific Mall'!L11+'Gurgaon Sec - 10'!L11 -> 0 | N12: ='Noida Sec - 18'!M11+'Noida Sec -143'!M11+'Faridabad Sec15'!M11+DLF!M11+'Gurgaon Sec-15'!M11+'Paschim Vihar'!M11+Kalkaji!M11+CP!M11+Rohini!M11+'Model Town'!M11+'Pacific Mall'!M11+'Gurgaon Sec - 10'!M11+'Shalimar Bagh'!M11 -> 0 | O12: =+SUM(C12:N12) -> 4798727.6 | R12: 1115271 | S12: =C12-R12 -> 55354.673
A13: Less Commission | B13: Operation | C13: ='Noida Sec - 18'!B12+'Noida Sec -143'!B12+DLF!B12+'Faridabad Sec15'!B12+'Gurgaon Sec-15'!B12+'Gurgaon Sec - 10'!B12+'Paschim Vihar'!B12+Kalkaji!B12+CP!B12+Rohini!B12+'Model Town'!B12+'Pacific Mall'!B12+'Shalimar Bagh'!B12 -> 2005043.4 | D13: ='Noida Sec - 18'!C12+'Noida Sec -143'!C12+DLF!C12+'Faridabad Sec15'!C12+'Gurgaon Sec-15'!C12+'Gurgaon Sec - 10'!C12+'Paschim Vihar'!C12+Kalkaji!C12+CP!C12+Rohini!C12+'Model Town'!C12+'Pacific Mall'!C12+'Shalimar Bagh'!C12+'Gurgaon Sector 31'!C12 -> 2238242.3 | E13: ='Noida Sec - 18'!D12+'Noida Sec -143'!D12+DLF!D12+'Faridabad Sec15'!D12+'Gurgaon Sec-15'!D12+'Gurgaon Sec - 10'!D12+'Gurgaon Sector 31'!D12+'Paschim Vihar'!D12+Kalkaji!D12+CP!D12+Rohini!D12+'Model Town'!D12+'Pacific Mall'!D12+'Shalimar Bagh'!D12 -> 2276412.2 | F13: ='Noida Sec - 18'!E12+'Noida Sec -143'!E12+DLF!E12+'Faridabad Sec15'!E12+'Gurgaon Sec-15'!E12+'Gurgaon Sec - 10'!E12+'Gurgaon Sector 31'!E12+'Paschim Vihar'!E12+Kalkaji!E12+CP!E12+Rohini!E12+'Model Town'!E12+'Pacific Mall'!E12+'Shalimar Bagh'!E12 -> 2037896.3 | G13: ='Noida Sec - 18'!F12+'Noida Sec -143'!F12+'Faridabad Sec15'!F12+DLF!F12+'Gurgaon Sec-15'!F12+'Paschim Vihar'!F12+Kalkaji!F12+CP!F12+Rohini!F12+'Model Town'!F12+'Pacific Mall'!F12 -> 0 | H13: ='Noida Sec - 18'!G12+'Noida Sec -143'!G12+'Faridabad Sec15'!G12+DLF!G12+'Gurgaon Sec-15'!G12+'Paschim Vihar'!G12+Kalkaji!G12+CP!G12+Rohini!G12+'Model Town'!G12+'Pacific Mall'!G12 -> 0 | I13: ='Noida Sec - 18'!H12+'Noida Sec -143'!H12+'Faridabad Sec15'!H12+DLF!H12+'Gurgaon Sec-15'!H12+'Paschim Vihar'!H12+Kalkaji!H12+CP!H12+Rohini!H12+'Model Town'!H12+'Pacific Mall'!H12 -> 0 | J13: ='Noida Sec - 18'!I12+'Noida Sec -143'!I12+'Faridabad Sec15'!I12+DLF!I12+'Gurgaon Sec-15'!I12+'Paschim Vihar'!I12+Kalkaji!I12+CP!I12+Rohini!I12+'Model Town'!I12+'Pacific Mall'!I12 -> 0 | K13: ='Noida Sec - 18'!J12+'Noida Sec -143'!J12+'Faridabad Sec15'!J12+DLF!J12+'Gurgaon Sec-15'!J12+'Paschim Vihar'!J12+Kalkaji!J12+CP!J12+Rohini!J12+'Model Town'!J12+'Pacific Mall'!J12+'Gurgaon Sec - 10'!J12 -> 0 | L13: ='Noida Sec - 18'!K12+'Noida Sec -143'!K12+DLF!K12+'Faridabad Sec15'!K12+'Gurgaon Sec-15'!K12+'Gurgaon Sec - 10'!K12+'Paschim Vihar'!K12+Kalkaji!K12+CP!K12+Rohini!K12+'Model Town'!K12+'Pacific Mall'!K12 -> 0 | M13: ='Noida Sec - 18'!L12+'Noida Sec -143'!L12+DLF!L12+'Faridabad Sec15'!L12+'Gurgaon Sec-15'!L12+'Gurgaon Sec - 10'!L12+'Paschim Vihar'!L12+Kalkaji!L12+CP!L12+Rohini!L12+'Model Town'!L12+'Pacific Mall'!L12 -> 0 | N13: ='Noida Sec - 18'!M12+'Noida Sec -143'!M12+'Faridabad Sec15'!M12+DLF!M12+'Gurgaon Sec-15'!M12+'Paschim Vihar'!M12+Kalkaji!M12+CP!M12+Rohini!M12+'Model Town'!M12+'Pacific Mall'!M12+'Gurgaon Sec - 10'!M12+'Shalimar Bagh'!M12 -> 0 | O13: =+SUM(C13:N13) -> 8557594.2 | R13: 1826332 | S13: =C13-R13 -> 178711.37
A14: Commission % | C14: =C13/C10 -> 0.081561731 | D14: =D13/D10 -> 0.085449101 | E14: =E13/E10 -> 0.08947322 | F14: =F13/F10 -> 0.082996886 | G14: =G13/G10 -> #DIV/0! | H14: =H13/H10 -> #DIV/0! | I14: =I13/I10 -> #DIV/0! | J14: =J13/J10 -> #DIV/0! | ... N14: =N13/N10 -> #DIV/0! | R14: 0.0819 | S14: =C14-R14 -> -0.00033826949
A15: Net Revenues from F&B Sales | C15: =C10+C11-C12-C13 -> 21407470 | D15: =D10+D11-D12-D13 -> 22708297 | E15: =E10+E11-E12-E13 -> 21954431 | F15: =F10+F11-F12-F13 -> 21346760 | G15: =G10+G11-G12-G13 -> 0 | H15: =H10+H11-H12-H13 -> 0 | I15: =I10+I11-I12-I13 -> 0 | J15: =J10+J11-J12-J13 -> 0 | ... N15: =N10+N11-N12-N13 -> 0 | O15: =sum(C15:N15) -> 87416958 | P15: =O15/$O$15 -> 1 | R15: 20479092 | S15: =C15-R15 -> 928378.1
A16: F&B Cost | B16: Operation | C16: =C4+C5-C6-C8 -> 5996580.1 | D16: =D4+D5-D6-D8 -> 6199663.2 | E16: =E4+E5-E6-E8 -> 6403216.7 | F16: =F4+F5-F6-F8 -> 5957277.6 | G16: =G4+G5-G6-G8 -> 5685749.4 | H16: =H4+H5-H6-H8 -> 2274658 | I16: =I4+I5-I6-I8 -> 300476.16 | J16: =J4+J5-J6-J8 -> 0 | ... N16: =N4+N5-N6-N8 -> 0 | O16: =sum(C16:N16) -> 32817621 | P16: =O16/$O$15 -> 0.37541482 | R16: 5676318 | S16: =C16-R16 -> 320262.12
A17: Electricity | B17: Operation | C17: ='Noida Sec - 18'!B15+'Noida Sec -143'!B15+DLF!B15+'Faridabad Sec15'!B15+'Gurgaon Sec-15'!B15+'Gurgaon Sec - 10'!B15+'Paschim Vihar'!B15+Kalkaji!B15+CP!B15+Rohini!B15+'Model Town'!B15+'Pacific Mall'!B15+'Shalimar Bagh'!B15 -> 1155579.2 | D17: ='Noida Sec - 18'!C15+'Noida Sec -143'!C15+DLF!C15+'Faridabad Sec15'!C15+'Gurgaon Sec-15'!C15+'Gurgaon Sec - 10'!C15+'Paschim Vihar'!C15+Kalkaji!C15+CP!C15+Rohini!C15+'Model Town'!C15+'Pacific Mall'!C15+'Shalimar Bagh'!C15+'Gurgaon Sector 31'!C15 -> 1249533.9 | E17: ='Noida Sec - 18'!D15+'Noida Sec -143'!D15+DLF!D15+'Faridabad Sec15'!D15+'Gurgaon Sec-15'!D15+'Gurgaon Sec - 10'!D15+'Gurgaon Sector 31'!D15+'Paschim Vihar'!D15+Kalkaji!D15+CP!D15+Rohini!D15+'Model Town'!D15+'Pacific Mall'!D15+'Shalimar Bagh'!D15 -> 1316244.8 | F17: ='Noida Sec - 18'!E15+'Noida Sec -143'!E15+DLF!E15+'Faridabad Sec15'!E15+'Gurgaon Sec-15'!E15+'Gurgaon Sec - 10'!E15+'Gurgaon Sector 31'!E15+'Paschim Vihar'!E15+Kalkaji!E15+CP!E15+Rohini!E15+'Model Town'!E15+'Pacific Mall'!E15+'Shalimar Bagh'!E15 -> 1500529.5 | G17: ='Noida Sec - 18'!F15+'Noida Sec -143'!F15+'Faridabad Sec15'!F15+DLF!F15+'Gurgaon Sec-15'!F15+'Paschim Vihar'!F15+Kalkaji!F15+CP!F15+Rohini!F15+'Model Town'!F15+'Pacific Mall'!F15 -> 0 | H17: ='Noida Sec - 18'!G15+'Noida Sec -143'!G15+'Faridabad Sec15'!G15+DLF!G15+'Gurgaon Sec-15'!G15+'Paschim Vihar'!G15+Kalkaji!G15+CP!G15+Rohini!G15+'Model Town'!G15+'Pacific Mall'!G15 -> 0 | I17: ='Noida Sec -143'!H15+'Noida Sec -143'!H15+'Faridabad Sec15'!H15+DLF!H15+'Gurgaon Sec-15'!H15+'Paschim Vihar'!H15+Kalkaji!H15+CP!H15+Rohini!H15+'Model Town'!H15+'Pacific Mall'!H15 -> 0 | J17: ='Noida Sec - 18'!I15+'Noida Sec -143'!I15+'Faridabad Sec15'!I15+DLF!I15+'Gurgaon Sec-15'!I15+'Paschim Vihar'!I15+Kalkaji!I15+CP!I15+Rohini!I15+'Model Town'!I15+'Pacific Mall'!I15 -> 0 | K17: ='Noida Sec - 18'!J15+'Noida Sec -143'!J15+'Faridabad Sec15'!J15+DLF!J15+'Gurgaon Sec-15'!J15+'Paschim Vihar'!J15+Kalkaji!J15+CP!J15+Rohini!J15+'Model Town'!J15+'Pacific Mall'!J15+'Gurgaon Sec - 10'!J15 -> 0 | L17: ='Noida Sec - 18'!K15+'Noida Sec -143'!K15+DLF!K15+'Faridabad Sec15'!K15+'Gurgaon Sec-15'!K15+'Gurgaon Sec - 10'!K15+'Paschim Vihar'!K15+Kalkaji!K15+CP!K15+Rohini!K15+'Model Town'!K15+'Pacific Mall'!K15 -> 0 | M17: ='Noida Sec - 18'!L15+'Noida Sec -143'!L15+DLF!L15+'Faridabad Sec15'!L15+'Gurgaon Sec-15'!L15+'Gurgaon Sec - 10'!L15+'Paschim Vihar'!L15+Kalkaji!L15+CP!L15+Rohini!L15+'Model Town'!L15+'Pacific Mall'!L15 -> 0 | N17: ='Noida Sec - 18'!M15+'Noida Sec -143'!M15+DLF!M15+'Faridabad Sec15'!M15+'Gurgaon Sec-15'!M15+'Gurgaon Sec - 10'!M15+'Paschim Vihar'!M15+Kalkaji!M15+CP!M15+Rohini!M15+'Model Town'!M15+'Pacific Mall'!M15+'Shalimar Bagh'!M15 -> 0 | O17: =sum(C17:N17) -> 5221887.4 | P17: =O17/$O$15 -> 0.059735405 | R17: 960724 | S17: =C17-R17 -> 194855.17
A18: Telephone/Internet | B18: Operation | C18: ='Noida Sec - 18'!B16+'Noida Sec -143'!B16+DLF!B16+'Faridabad Sec15'!B16+'Gurgaon Sec-15'!B16+'Gurgaon Sec - 10'!B16+'Paschim Vihar'!B16+Kalkaji!B16+CP!B16+Rohini!B16+'Model Town'!B16+'Pacific Mall'!B16+'Shalimar Bagh'!B16 -> 19069.5 | D18: ='Noida Sec - 18'!C16+'Noida Sec -143'!C16+DLF!C16+'Faridabad Sec15'!C16+'Gurgaon Sec-15'!C16+'Gurgaon Sec - 10'!C16+'Paschim Vihar'!C16+Kalkaji!C16+CP!C16+Rohini!C16+'Model Town'!C16+'Pacific Mall'!C16+'Shalimar Bagh'!C16+'Gurgaon Sector 31'!C16 -> 18608.5 | E18: ='Noida Sec - 18'!D16+'Noida Sec -143'!D16+DLF!D16+'Faridabad Sec15'!D16+'Gurgaon Sec-15'!D16+'Gurgaon Sec - 10'!D16+'Gurgaon Sector 31'!D16+'Paschim Vihar'!D16+Kalkaji!D16+CP!D16+Rohini!D16+'Model Town'!D16+'Pacific Mall'!D16+'Shalimar Bagh'!D16 -> 19011.5 | F18: ='Noida Sec - 18'!E16+'Noida Sec -143'!E16+DLF!E16+'Faridabad Sec15'!E16+'Gurgaon Sec-15'!E16+'Gurgaon Sec - 10'!E16+'Gurgaon Sector 31'!E16+'Paschim Vihar'!E16+Kalkaji!E16+CP!E16+Rohini!E16+'Model Town'!E16+'Pacific Mall'!E16+'Shalimar Bagh'!E16 -> 18644.5 | G18: ='Noida Sec - 18'!F16+'Noida Sec -143'!F16+'Faridabad Sec15'!F16+DLF!F16+'Gurgaon Sec-15'!F16+'Paschim Vihar'!F16+Kalkaji!F16+CP!F16+Rohini!F16+'Model Town'!F16+'Pacific Mall'!F16 -> 2006 | H18: ='Noida Sec - 18'!G16+'Noida Sec -143'!G16+'Faridabad Sec15'!G16+DLF!G16+'Gurgaon Sec-15'!G16+'Paschim Vihar'!G16+Kalkaji!G16+CP!G16+Rohini!G16+'Model Town'!G16+'Pacific Mall'!G16 -> 2006 | I18: ='Noida Sec - 18'!H16+'Noida Sec -143'!H16+'Faridabad Sec15'!H16+DLF!H16+'Gurgaon Sec-15'!H16+'Paschim Vihar'!H16+Kalkaji!H16+CP!H16+Rohini!H16+'Model Town'!H16+'Pacific Mall'!H16 -> 0 | J18: ='Noida Sec - 18'!I16+'Noida Sec -143'!I16+'Faridabad Sec15'!I16+DLF!I16+'Gurgaon Sec-15'!I16+'Paschim Vihar'!I16+Kalkaji!I16+CP!I16+Rohini!I16+'Model Town'!I16+'Pacific Mall'!I16 -> 0 | K18: ='Noida Sec - 18'!J16+'Noida Sec -143'!J16+'Faridabad Sec15'!J16+DLF!J16+'Gurgaon Sec-15'!J16+'Paschim Vihar'!J16+Kalkaji!J16+CP!J16+Rohini!J16+'Model Town'!J16+'Pacific Mall'!J16+'Gurgaon Sec - 10'!J16 -> 0 | L18: ='Noida Sec - 18'!K16+'Noida Sec -143'!K16+DLF!K16+'Faridabad Sec15'!K16+'Gurgaon Sec-15'!K16+'Gurgaon Sec - 10'!K16+'Paschim Vihar'!K16+Kalkaji!K16+CP!K16+Rohini!K16+'Model Town'!K16+'Pacific Mall'!K16 -> 0 | M18: ='Noida Sec - 18'!L16+'Noida Sec -143'!L16+DLF!L16+'Faridabad Sec15'!L16+'Gurgaon Sec-15'!L16+'Gurgaon Sec - 10'!L16+'Paschim Vihar'!L16+Kalkaji!L16+CP!L16+Rohini!L16+'Model Town'!L16+'Pacific Mall'!L16 -> 0 | N18: ='Noida Sec - 18'!M16+'Noida Sec -143'!M16+DLF!M16+'Faridabad Sec15'!M16+'Gurgaon Sec-15'!M16+'Gurgaon Sec - 10'!M16+'Paschim Vihar'!M16+Kalkaji!M16+CP!M16+Rohini!M16+'Model Town'!M16+'Pacific Mall'!M16+'Shalimar Bagh'!M16 -> 0 | O18: =sum(C18:N18) -> 79346 | P18: =O18/$O$15 -> 0.00090767286 | R18: 16959 | S18: =C18-R18 -> 2110.5
A19: Gas | B19: Operation | C19: ='Noida Sec - 18'!B17+'Noida Sec -143'!B17+DLF!B17+'Faridabad Sec15'!B17+'Gurgaon Sec-15'!B17+'Gurgaon Sec - 10'!B17+'Paschim Vihar'!B17+Kalkaji!B17+CP!B17+Rohini!B17+'Model Town'!B17+'Pacific Mall'!B17+'Shalimar Bagh'!B17 -> 635379.18 | D19: ='Noida Sec - 18'!C17+'Noida Sec -143'!C17+DLF!C17+'Faridabad Sec15'!C17+'Gurgaon Sec-15'!C17+'Gurgaon Sec - 10'!C17+'Paschim Vihar'!C17+Kalkaji!C17+CP!C17+Rohini!C17+'Model Town'!C17+'Pacific Mall'!C17+'Shalimar Bagh'!C17+'Gurgaon Sector 31'!C17 -> 658801.19 | E19: ='Noida Sec - 18'!D17+'Noida Sec -143'!D17+DLF!D17+'Faridabad Sec15'!D17+'Gurgaon Sec-15'!D17+'Gurgaon Sec - 10'!D17+'Gurgaon Sector 31'!D17+'Paschim Vihar'!D17+Kalkaji!D17+CP!D17+Rohini!D17+'Model Town'!D17+'Pacific Mall'!D17+'Shalimar Bagh'!D17 -> 647709 | F19: ='Noida Sec - 18'!E17+'Noida Sec -143'!E17+DLF!E17+'Faridabad Sec15'!E17+'Gurgaon Sec-15'!E17+'Gurgaon Sec - 10'!E17+'Gurgaon Sector 31'!E17+'Paschim Vihar'!E17+Kalkaji!E17+CP!E17+Rohini!E17+'Model Town'!E17+'Pacific Mall'!E17+'Shalimar Bagh'!E17 -> 762281 | G19: ='Noida Sec - 18'!F17+'Noida Sec -143'!F17+'Faridabad Sec15'!F17+DLF!F17+'Gurgaon Sec-15'!F17+'Paschim Vihar'!F17+Kalkaji!F17+CP!F17+Rohini!F17+'Model Town'!F17+'Pacific Mall'!F17 -> 0 | H19: ='Noida Sec - 18'!G17+'Noida Sec -143'!G17+'Faridabad Sec15'!G17+DLF!G17+'Gurgaon Sec-15'!G17+'Paschim Vihar'!G17+Kalkaji!G17+CP!G17+Rohini!G17+'Model Town'!G17+'Pacific Mall'!G17 -> 0 | I19: ='Noida Sec - 18'!H17+'Noida Sec -143'!H17+'Faridabad Sec15'!H17+DLF!H17+'Gurgaon Sec-15'!H17+'Paschim Vihar'!H17+Kalkaji!H17+CP!H17+Rohini!H17+'Model Town'!H17+'Pacific Mall'!H17 -> 0 | J19: ='Noida Sec - 18'!I17+'Noida Sec -143'!I17+'Faridabad Sec15'!I17+DLF!I17+'Gurgaon Sec-15'!I17+'Paschim Vihar'!I17+Kalkaji!I17+CP!I17+Rohini!I17+'Model Town'!I17+'Pacific Mall'!I17 -> 0 | K19: ='Noida Sec - 18'!J17+'Noida Sec -143'!J17+'Faridabad Sec15'!J17+DLF!J17+'Gurgaon Sec-15'!J17+'Paschim Vihar'!J17+Kalkaji!J17+CP!J17+Rohini!J17+'Model Town'!J17+'Pacific Mall'!J17+'Gurgaon Sec - 10'!J17 -> 0 | L19: ='Noida Sec - 18'!K17+'Noida Sec -143'!K17+DLF!K17+'Faridabad Sec15'!K17+'Gurgaon Sec-15'!K17+'Gurgaon Sec - 10'!K17+'Paschim Vihar'!K17+Kalkaji!K17+CP!K17+Rohini!K17+'Model Town'!K17+'Pacific Mall'!K17 -> 0 | M19: ='Noida Sec - 18'!L17+'Noida Sec -143'!L17+DLF!L17+'Faridabad Sec15'!L17+'Gurgaon Sec-15'!L17+'Gurgaon Sec - 10'!L17+'Paschim Vihar'!L17+Kalkaji!L17+CP!L17+Rohini!L17+'Model Town'!L17+'Pacific Mall'!L17 -> 0 | N19: ='Noida Sec - 18'!M17+'Noida Sec -143'!M17+DLF!M17+'Faridabad Sec15'!M17+'Gurgaon Sec-15'!M17+'Gurgaon Sec - 10'!M17+'Paschim Vihar'!M17+Kalkaji!M17+CP!M17+Rohini!M17+'Model Town'!M17+'Pacific Mall'!M17+'Shalimar Bagh'!M17 -> 0 | O19: =sum(C19:N19) -> 2704170.4 | P19: =O19/$O$15 -> 0.030934162 | R19: 569161 | S19: =C19-R19 -> 66218.18
A20: Rent & Revenue Share | B20: Accounts | C20: ='Noida Sec - 18'!B18+'Noida Sec -143'!B18+DLF!B18+'Faridabad Sec15'!B18+'Gurgaon Sec-15'!B18+'Gurgaon Sec - 10'!B18+'Paschim Vihar'!B18+Kalkaji!B18+CP!B18+Rohini!B18+'Model Town'!B18+'Pacific Mall'!B18+'Shalimar Bagh'!B18 -> 4147999.5 | D20: ='Noida Sec - 18'!C18+'Noida Sec -143'!C18+DLF!C18+'Faridabad Sec15'!C18+'Gurgaon Sec-15'!C18+'Gurgaon Sec - 10'!C18+'Paschim Vihar'!C18+Kalkaji!C18+CP!C18+Rohini!C18+'Model Town'!C18+'Pacific Mall'!C18+'Shalimar Bagh'!C18+'Gurgaon Sector 31'!C18 -> 4174744.4 | E20: ='Noida Sec - 18'!D18+'Noida Sec -143'!D18+DLF!D18+'Faridabad Sec15'!D18+'Gurgaon Sec-15'!D18+'Gurgaon Sec - 10'!D18+'Gurgaon Sector 31'!D18+'Paschim Vihar'!D18+Kalkaji!D18+CP!D18+Rohini!D18+'Model Town'!D18+'Pacific Mall'!D18+'Shalimar Bagh'!D18 -> 4471419.7 | F20: ='Noida Sec - 18'!E18+'Noida Sec -143'!E18+DLF!E18+'Faridabad Sec15'!E18+'Gurgaon Sec-15'!E18+'Gurgaon Sec - 10'!E18+'Gurgaon Sector 31'!E18+'Paschim Vihar'!E18+Kalkaji!E18+CP!E18+Rohini!E18+'Model Town'!E18+'Pacific Mall'!E18+'Shalimar Bagh'!E18 -> 4565197.5 | G20: ='Noida Sec - 18'!F18+'Noida Sec -143'!F18+'Faridabad Sec15'!F18+DLF!F18+'Gurgaon Sec-15'!F18+'Paschim Vihar'!F18+Kalkaji!F18+CP!F18+Rohini!F18+'Model Town'!F18+'Pacific Mall'!F18 -> 0 | H20: ='Noida Sec - 18'!G18+'Noida Sec -143'!G18+'Faridabad Sec15'!G18+DLF!G18+'Gurgaon Sec-15'!G18+'Paschim Vihar'!G18+Kalkaji!G18+CP!G18+Rohini!G18+'Model Town'!G18+'Pacific Mall'!G18 -> 0 | I20: ='Noida Sec - 18'!H18+'Noida Sec -143'!H18+'Faridabad Sec15'!H18+DLF!H18+'Gurgaon Sec-15'!H18+'Paschim Vihar'!H18+Kalkaji!H18+CP!H18+Rohini!H18+'Model Town'!H18+'Pacific Mall'!H18 -> 0 | J20: ='Noida Sec - 18'!I18+'Noida Sec -143'!I18+'Faridabad Sec15'!I18+DLF!I18+'Gurgaon Sec-15'!I18+'Paschim Vihar'!I18+Kalkaji!I18+CP!I18+Rohini!I18+'Model Town'!I18+'Pacific Mall'!I18 -> 0 | K20: ='Noida Sec - 18'!J18+'Noida Sec -143'!J18+'Faridabad Sec15'!J18+DLF!J18+'Gurgaon Sec-15'!J18+'Paschim Vihar'!J18+Kalkaji!J18+CP!J18+Rohini!J18+'Model Town'!J18+'Pacific Mall'!J18+'Gurgaon Sec - 10'!J18 -> 0 | L20: ='Noida Sec - 18'!K18+'Noida Sec -143'!K18+DLF!K18+'Faridabad Sec15'!K18+'Gurgaon Sec-15'!K18+'Gurgaon Sec - 10'!K18+'Paschim Vihar'!K18+Kalkaji!K18+CP!K18+Rohini!K18+'Model Town'!K18+'Pacific Mall'!K18 -> 0 | M20: ='Noida Sec - 18'!L18+'Noida Sec -143'!L18+DLF!L18+'Faridabad Sec15'!L18+'Gurgaon Sec-15'!L18+'Gurgaon Sec - 10'!L18+'Paschim Vihar'!L18+Kalkaji!L18+CP!L18+Rohini!L18+'Model Town'!L18+'Pacific Mall'!L18 -> 0 | N20: ='Noida Sec - 18'!M18+'Noida Sec -143'!M18+DLF!M18+'Faridabad Sec15'!M18+'Gurgaon Sec-15'!M18+'Gurgaon Sec - 10'!M18+'Paschim Vihar'!M18+Kalkaji!M18+CP!M18+Rohini!M18+'Model Town'!M18+'Pacific Mall'!M18+'Shalimar Bagh'!M18 -> 0 | O20: =sum(C20:N20) -> 17359361 | P20: =O20/$O$15 -> 0.19858116 | R20: 3821495 | S20: =C20-R20 -> 326504.51
A21: Insurance | B21: Accounts | C21: ='Noida Sec - 18'!B19+'Noida Sec -143'!B19+DLF!B19+'Faridabad Sec15'!B19+'Gurgaon Sec-15'!B19+'Gurgaon Sec - 10'!B19+'Paschim Vihar'!B19+Kalkaji!B19+CP!B19+Rohini!B19+'Model Town'!B19+'Pacific Mall'!B19+'Shalimar Bagh'!B19 -> 15666 | D21: ='Noida Sec - 18'!C19+'Noida Sec -143'!C19+DLF!C19+'Faridabad Sec15'!C19+'Gurgaon Sec-15'!C19+'Gurgaon Sec - 10'!C19+'Paschim Vihar'!C19+Kalkaji!C19+CP!C19+Rohini!C19+'Model Town'!C19+'Pacific Mall'!C19+'Shalimar Bagh'!C19 -> 15296.013 | E21: ='Noida Sec - 18'!D19+'Noida Sec -143'!D19+DLF!D19+'Faridabad Sec15'!D19+'Gurgaon Sec-15'!D19+'Gurgaon Sec - 10'!D19+'Gurgaon Sector 31'!D19+'Paschim Vihar'!D19+Kalkaji!D19+CP!D19+Rohini!D19+'Model Town'!D19+'Pacific Mall'!D19+'Shalimar Bagh'!D19 -> 15296.013 | F21: ='Noida Sec - 18'!E19+'Noida Sec -143'!E19+DLF!E19+'Faridabad Sec15'!E19+'Gurgaon Sec-15'!E19+'Gurgaon Sec - 10'!E19+'Gurgaon Sector 31'!E19+'Paschim Vihar'!E19+Kalkaji!E19+CP!E19+Rohini!E19+'Model Town'!E19+'Pacific Mall'!E19+'Shalimar Bagh'!E19 -> 15296.013 | G21: ='Noida Sec - 18'!F19+'Noida Sec -143'!F19+'Faridabad Sec15'!F19+DLF!F19+'Gurgaon Sec-15'!F19+'Paschim Vihar'!F19+Kalkaji!F19+CP!F19+Rohini!F19+'Model Town'!F19+'Pacific Mall'!F19 -> 13102.05 | H21: ='Noida Sec - 18'!G19+'Noida Sec -143'!G19+'Faridabad Sec15'!G19+DLF!G19+'Gurgaon Sec-15'!G19+'Paschim Vihar'!G19+Kalkaji!G19+CP!G19+Rohini!G19+'Model Town'!G19+'Pacific Mall'!G19 -> 13102.05 | I21: ='Noida Sec - 18'!H19+'Noida Sec -143'!H19+'Faridabad Sec15'!H19+DLF!H19+'Gurgaon Sec-15'!H19+'Paschim Vihar'!H19+Kalkaji!H19+CP!H19+Rohini!H19+'Model Town'!H19+'Pacific Mall'!H19 -> 13102.05 | J21: ='Noida Sec - 18'!I19+'Noida Sec -143'!I19+'Faridabad Sec15'!I19+DLF!I19+'Gurgaon Sec-15'!I19+'Paschim Vihar'!I19+Kalkaji!I19+CP!I19+Rohini!I19+'Model Town'!I19+'Pacific Mall'!I19 -> 13102.05 | K21: ='Noida Sec - 18'!J19+'Noida Sec -143'!J19+'Faridabad Sec15'!J19+DLF!J19+'Gurgaon Sec-15'!J19+'Paschim Vihar'!J19+Kalkaji!J19+CP!J19+Rohini!J19+'Model Town'!J19+'Pacific Mall'!J19+'Gurgaon Sec - 10'!J19 -> 13871.88 | L21: ='Noida Sec - 18'!K19+'Noida Sec -143'!K19+DLF!K19+'Faridabad Sec15'!K19+'Gurgaon Sec-15'!K19+'Gurgaon Sec - 10'!K19+'Paschim Vihar'!K19+Kalkaji!K19+CP!K19+Rohini!K19+'Model Town'!K19+'Pacific Mall'!K19 -> 13871.88 | M21: ='Noida Sec - 18'!L19+'Noida Sec -143'!L19+DLF!L19+'Faridabad Sec15'!L19+'Gurgaon Sec-15'!L19+'Gurgaon Sec - 10'!L19+'Paschim Vihar'!L19+Kalkaji!L19+CP!L19+Rohini!L19+'Model Town'!L19+'Pacific Mall'!L19 -> 13871.88 | N21: ='Noida Sec - 18'!M19+'Noida Sec -143'!M19+DLF!M19+'Faridabad Sec15'!M19+'Gurgaon Sec-15'!M19+'Gurgaon Sec - 10'!M19+'Paschim Vihar'!M19+Kalkaji!M19+CP!M19+Rohini!M19+'Model Town'!M19+'Pacific Mall'!M19+'Shalimar Bagh'!M19 -> 15296.013 | O21: =sum(C21:N21) -> 170873.89 | P21: =O21/$O$15 -> 0.0019546996 | R21: 14417 | S21: =C21-R21 -> 1249
A22: Software | B22: Operation | C22: ='Noida Sec - 18'!B20+'Noida Sec -143'!B20+DLF!B20+'Faridabad Sec15'!B20+'Gurgaon Sec-15'!B20+'Gurgaon Sec - 10'!B20+'Paschim Vihar'!B20+Kalkaji!B20+CP!B20+Rohini!B20+'Model Town'!B20+'Pacific Mall'!B20+'Shalimar Bagh'!B20 -> 86713 | D22: ='Noida Sec - 18'!C20+'Noida Sec -143'!C20+DLF!C20+'Faridabad Sec15'!C20+'Gurgaon Sec-15'!C20+'Gurgaon Sec - 10'!C20+'Paschim Vihar'!C20+Kalkaji!C20+CP!C20+Rohini!C20+'Model Town'!C20+'Pacific Mall'!C20+'Shalimar Bagh'!C20+'Gurgaon Sector 31'!C20 -> 94570 | E22: ='Noida Sec - 18'!D20+'Noida Sec -143'!D20+DLF!D20+'Faridabad Sec15'!D20+'Gurgaon Sec-15'!D20+'Gurgaon Sec - 10'!D20+'Gurgaon Sector 31'!D20+'Paschim Vihar'!D20+Kalkaji!D20+CP!D20+Rohini!D20+'Model Town'!D20+'Pacific Mall'!D20+'Shalimar Bagh'!D20 -> 94570 | F22: ='Noida Sec - 18'!E20+'Noida Sec -143'!E20+DLF!E20+'Faridabad Sec15'!E20+'Gurgaon Sec-15'!E20+'Gurgaon Sec - 10'!E20+'Gurgaon Sector 31'!E20+'Paschim Vihar'!E20+Kalkaji!E20+CP!E20+Rohini!E20+'Model Town'!E20+'Pacific Mall'!E20+'Shalimar Bagh'!E20 -> 94570 | G22: ='Noida Sec - 18'!F20+'Noida Sec -143'!F20+'Faridabad Sec15'!F20+DLF!F20+'Gurgaon Sec-15'!F20+'Paschim Vihar'!F20+Kalkaji!F20+CP!F20+Rohini!F20+'Model Town'!F20+'Pacific Mall'!F20 -> 0 | H22: ='Noida Sec - 18'!G20+'Noida Sec -143'!G20+'Faridabad Sec15'!G20+DLF!G20+'Gurgaon Sec-15'!G20+'Paschim Vihar'!G20+Kalkaji!G20+CP!G20+Rohini!G20+'Model Town'!G20+'Pacific Mall'!G20 -> 0 | I22: ='Noida Sec - 18'!H20+'Noida Sec -143'!H20+'Faridabad Sec15'!H20+DLF!H20+'Gurgaon Sec-15'!H20+'Paschim Vihar'!H20+Kalkaji!H20+CP!H20+Rohini!H20+'Model Town'!H20+'Pacific Mall'!H20 -> 0 | J22: ='Noida Sec - 18'!I20+'Noida Sec -143'!I20+'Faridabad Sec15'!I20+DLF!I20+'Gurgaon Sec-15'!I20+'Paschim Vihar'!I20+Kalkaji!I20+CP!I20+Rohini!I20+'Model Town'!I20+'Pacific Mall'!I20 -> 0 | K22: ='Noida Sec - 18'!J20+'Noida Sec -143'!J20+'Faridabad Sec15'!J20+DLF!J20+'Gurgaon Sec-15'!J20+'Paschim Vihar'!J20+Kalkaji!J20+CP!J20+Rohini!J20+'Model Town'!J20+'Pacific Mall'!J20+'Gurgaon Sec - 10'!J20 -> 0 | L22: ='Noida Sec - 18'!K20+'Noida Sec -143'!K20+DLF!K20+'Faridabad Sec15'!K20+'Gurgaon Sec-15'!K20+'Gurgaon Sec - 10'!K20+'Paschim Vihar'!K20+Kalkaji!K20+CP!K20+Rohini!K20+'Model Town'!K20+'Pacific Mall'!K20 -> 0 | M22: ='Noida Sec - 18'!L20+'Noida Sec -143'!L20+DLF!L20+'Faridabad Sec15'!L20+'Gurgaon Sec-15'!L20+'Gurgaon Sec - 10'!L20+'Paschim Vihar'!L20+Kalkaji!L20+CP!L20+Rohini!L20+'Model Town'!L20+'Pacific Mall'!L20 -> 0 | N22: ='Noida Sec - 18'!M20+'Noida Sec -143'!M20+DLF!M20+'Faridabad Sec15'!M20+'Gurgaon Sec-15'!M20+'Gurgaon Sec - 10'!M20+'Paschim Vihar'!M20+Kalkaji!M20+CP!M20+Rohini!M20+'Model Town'!M20+'Pacific Mall'!M20+'Shalimar Bagh'!M20 -> 0 | O22: =sum(C22:N22) -> 370423 | P22: =O22/$O$15 -> 0.0042374273 | R22: 80948 | S22: =C22-R22 -> 5765
A23: Staff Salary | B23: HR | C23: ='Noida Sec - 18'!B21+'Noida Sec -143'!B21+DLF!B21+'Faridabad Sec15'!B21+'Gurgaon Sec-15'!B21+'Gurgaon Sec - 10'!B21+'Paschim Vihar'!B21+Kalkaji!B21+CP!B21+Rohini!B21+'Model Town'!B21+'Pacific Mall'!B21+'Shalimar Bagh'!B21 -> 4447913 | D23: ='Noida Sec - 18'!C21+'Noida Sec -143'!C21+DLF!C21+'Faridabad Sec15'!C21+'Gurgaon Sec-15'!C21+'Gurgaon Sec - 10'!C21+'Paschim Vihar'!C21+Kalkaji!C21+CP!C21+Rohini!C21+'Model Town'!C21+'Pacific Mall'!C21+'Shalimar Bagh'!C21+'Gurgaon Sector 31'!C21 -> 4540935.6 | E23: ='Noida Sec - 18'!D21+'Noida Sec -143'!D21+DLF!D21+'Faridabad Sec15'!D21+'Gurgaon Sec-15'!D21+'Gurgaon Sec - 10'!D21+'Gurgaon Sector 31'!D21+'Paschim Vihar'!D21+Kalkaji!D21+CP!D21+Rohini!D21+'Model Town'!D21+'Pacific Mall'!D21+'Shalimar Bagh'!D21 -> 4826186.5 | F23: ='Noida Sec - 18'!E21+'Noida Sec -143'!E21+DLF!E21+'Faridabad Sec15'!E21+'Gurgaon Sec-15'!E21+'Gurgaon Sec - 10'!E21+'Gurgaon Sector 31'!E21+'Paschim Vihar'!E21+Kalkaji!E21+CP!E21+Rohini!E21+'Model Town'!E21+'Pacific Mall'!E21+'Shalimar Bagh'!E21 -> 4815183.9 | G23: ='Noida Sec - 18'!F21+'Noida Sec -143'!F21+'Faridabad Sec15'!F21+DLF!F21+'Gurgaon Sec-15'!F21+'Paschim Vihar'!F21+Kalkaji!F21+CP!F21+Rohini!F21+'Model Town'!F21+'Pacific Mall'!F21 -> 0 | H23: ='Noida Sec - 18'!G21+'Noida Sec -143'!G21+'Faridabad Sec15'!G21+DLF!G21+'Gurgaon Sec-15'!G21+'Paschim Vihar'!G21+Kalkaji!G21+CP!G21+Rohini!G21+'Model Town'!G21+'Pacific Mall'!G21 -> 0 | I23: ='Noida Sec - 18'!H21+'Noida Sec -143'!H21+'Faridabad Sec15'!H21+DLF!H21+'Gurgaon Sec-15'!H21+'Paschim Vihar'!H21+Kalkaji!H21+CP!H21+Rohini!H21+'Model Town'!H21+'Pacific Mall'!H21 -> 0 | J23: ='Noida Sec - 18'!I21+'Noida Sec -143'!I21+'Faridabad Sec15'!I21+DLF!I21+'Gurgaon Sec-15'!I21+'Paschim Vihar'!I21+Kalkaji!I21+CP!I21+Rohini!I21+'Model Town'!I21+'Pacific Mall'!I21 -> 0 | K23: ='Noida Sec - 18'!J21+'Noida Sec -143'!J21+'Faridabad Sec15'!J21+DLF!J21+'Gurgaon Sec-15'!J21+'Paschim Vihar'!J21+Kalkaji!J21+CP!J21+Rohini!J21+'Model Town'!J21+'Pacific Mall'!J21+'Gurgaon Sec - 10'!J21 -> 0 | L23: ='Noida Sec - 18'!K21+'Noida Sec -143'!K21+DLF!K21+'Faridabad Sec15'!K21+'Gurgaon Sec-15'!K21+'Gurgaon Sec - 10'!K21+'Paschim Vihar'!K21+Kalkaji!K21+CP!K21+Rohini!K21+'Model Town'!K21+'Pacific Mall'!K21 -> 0 | M23: ='Noida Sec - 18'!L21+'Noida Sec -143'!L21+DLF!L21+'Faridabad Sec15'!L21+'Gurgaon Sec-15'!L21+'Gurgaon Sec - 10'!L21+'Paschim Vihar'!L21+Kalkaji!L21+CP!L21+Rohini!L21+'Model Town'!L21+'Pacific Mall'!L21 -> 0 | N23: ='Noida Sec - 18'!M21+'Noida Sec -143'!M21+DLF!M21+'Faridabad Sec15'!M21+'Gurgaon Sec-15'!M21+'Gurgaon Sec - 10'!M21+'Paschim Vihar'!M21+Kalkaji!M21+CP!M21+Rohini!M21+'Model Town'!M21+'Pacific Mall'!M21+'Shalimar Bagh'!M21 -> 0 | O23: =sum(C23:N23) -> 18630219 | P23: =O23/$O$15 -> 0.21311905 | R23: 3840779 | S23: =C23-R23 -> 607134
A24: AMC | B24: Operation | C24: ='Noida Sec - 18'!B22+'Noida Sec -143'!B22+DLF!B22+'Faridabad Sec15'!B22+'Gurgaon Sec-15'!B22+'Gurgaon Sec - 10'!B22+'Paschim Vihar'!B22+Kalkaji!B22+CP!B22+Rohini!B22+'Model Town'!B22+'Pacific Mall'!B22+'Shalimar Bagh'!B22 -> 99545 | D24: ='Noida Sec - 18'!C22+'Noida Sec -143'!C22+DLF!C22+'Faridabad Sec15'!C22+'Gurgaon Sec-15'!C22+'Gurgaon Sec - 10'!C22+'Paschim Vihar'!C22+Kalkaji!C22+CP!C22+Rohini!C22+'Model Town'!C22+'Pacific Mall'!C22+'Shalimar Bagh'!C22+'Gurgaon Sector 31'!C22 -> 99545 | E24: ='Noida Sec - 18'!D22+'Noida Sec -143'!D22+DLF!D22+'Faridabad Sec15'!D22+'Gurgaon Sec-15'!D22+'Gurgaon Sec - 10'!D22+'Gurgaon Sector 31'!D22+'Paschim Vihar'!D22+Kalkaji!D22+CP!D22+Rohini!D22+'Model Town'!D22+'Pacific Mall'!D22+'Shalimar Bagh'!D22 -> 107050 | F24: ='Noida Sec - 18'!E22+'Noida Sec -143'!E22+DLF!E22+'Faridabad Sec15'!E22+'Gurgaon Sec-15'!E22+'Gurgaon Sec - 10'!E22+'Gurgaon Sector 31'!E22+'Paschim Vihar'!E22+Kalkaji!E22+CP!E22+Rohini!E22+'Model Town'!E22+'Pacific Mall'!E22+'Shalimar Bagh'!E22 -> 107050 | G24: ='Noida Sec - 18'!F22+'Noida Sec -143'!F22+'Faridabad Sec15'!F22+DLF!F22+'Gurgaon Sec-15'!F22+'Paschim Vihar'!F22+Kalkaji!F22+CP!F22+Rohini!F22+'Model Town'!F22+'Pacific Mall'!F22 -> 0 | H24: ='Noida Sec - 18'!G22+'Noida Sec -143'!G22+'Faridabad Sec15'!G22+DLF!G22+'Gurgaon Sec-15'!G22+'Paschim Vihar'!G22+Kalkaji!G22+CP!G22+Rohini!G22+'Model Town'!G22+'Pacific Mall'!G22 -> 0 | I24: ='Noida Sec - 18'!H22+'Noida Sec -143'!H22+'Faridabad Sec15'!H22+DLF!H22+'Gurgaon Sec-15'!H22+'Paschim Vihar'!H22+Kalkaji!H22+CP!H22+Rohini!H22+'Model Town'!H22+'Pacific Mall'!H22 -> 0 | J24: ='Noida Sec - 18'!I22+'Noida Sec -143'!I22+'Faridabad Sec15'!I22+DLF!I22+'Gurgaon Sec-15'!I22+'Paschim Vihar'!I22+Kalkaji!I22+CP!I22+Rohini!I22+'Model Town'!I22+'Pacific Mall'!I22 -> 0 | K24: ='Noida Sec - 18'!J22+'Noida Sec -143'!J22+'Faridabad Sec15'!J22+DLF!J22+'Gurgaon Sec-15'!J22+'Paschim Vihar'!J22+Kalkaji!J22+CP!J22+Rohini!J22+'Model Town'!J22+'Pacific Mall'!J22+'Gurgaon Sec - 10'!J22 -> 0 | L24: ='Noida Sec - 18'!K22+'Noida Sec -143'!K22+DLF!K22+'Faridabad Sec15'!K22+'Gurgaon Sec-15'!K22+'Gurgaon Sec - 10'!K22+'Paschim Vihar'!K22+Kalkaji!K22+CP!K22+Rohini!K22+'Model Town'!K22+'Pacific Mall'!K22 -> 0 | M24: ='Noida Sec - 18'!L22+'Noida Sec -143'!L22+DLF!L22+'Faridabad Sec15'!L22+'Gurgaon Sec-15'!L22+'Gurgaon Sec - 10'!L22+'Paschim Vihar'!L22+Kalkaji!L22+CP!L22+Rohini!L22+'Model Town'!L22+'Pacific Mall'!L22 -> 0 | N24: ='Noida Sec - 18'!M22+'Noida Sec -143'!M22+DLF!M22+'Faridabad Sec15'!M22+'Gurgaon Sec-15'!M22+'Gurgaon Sec - 10'!M22+'Paschim Vihar'!M22+Kalkaji!M22+CP!M22+Rohini!M22+'Model Town'!M22+'Pacific Mall'!M22+'Shalimar Bagh'!M22 -> 0 | O24: =sum(C24:N24) -> 413190 | P24: =O24/$O$15 -> 0.0047266573 | R24: 104978 | S24: =C24-R24 -> -5433
A25: Subscription | B25: Operation | C25: ='Noida Sec - 18'!B23+'Noida Sec -143'!B23+DLF!B23+'Faridabad Sec15'!B23+'Gurgaon Sec-15'!B23+'Gurgaon Sec - 10'!B23+'Paschim Vihar'!B23+Kalkaji!B23+CP!B23+Rohini!B23+'Model Town'!B23+'Pacific Mall'!B23+'Shalimar Bagh'!B23 -> 14254.847 | D25: ='Noida Sec - 18'!C23+'Noida Sec -143'!C23+DLF!C23+'Faridabad Sec15'!C23+'Gurgaon Sec-15'!C23+'Gurgaon Sec - 10'!C23+'Paschim Vihar'!C23+Kalkaji!C23+CP!C23+Rohini!C23+'Model Town'!C23+'Pacific Mall'!C23+'Shalimar Bagh'!C23+'Gurgaon Sector 31'!C23 -> 14561.68 | E25: ='Noida Sec - 18'!D23+'Noida Sec -143'!D23+DLF!D23+'Faridabad Sec15'!D23+'Gurgaon Sec-15'!D23+'Gurgaon Sec - 10'!D23+'Gurgaon Sector 31'!D23+'Paschim Vihar'!D23+Kalkaji!D23+CP!D23+Rohini!D23+'Model Town'!D23+'Pacific Mall'!D23+'Shalimar Bagh'!D23 -> 14561.68 | F25: ='Noida Sec - 18'!E23+'Noida Sec -143'!E23+DLF!E23+'Faridabad Sec15'!E23+'Gurgaon Sec-15'!E23+'Gurgaon Sec - 10'!E23+'Gurgaon Sector 31'!E23+'Paschim Vihar'!E23+Kalkaji!E23+CP!E23+Rohini!E23+'Model Town'!E23+'Pacific Mall'!E23+'Shalimar Bagh'!E23 -> 16920.67 | G25: ='Noida Sec - 18'!F23+'Noida Sec -143'!F23+'Faridabad Sec15'!F23+DLF!F23+'Gurgaon Sec-15'!F23+'Paschim Vihar'!F23+Kalkaji!F23+CP!F23+Rohini!F23+'Model Town'!F23+'Pacific Mall'!F23 -> 13975.833 | H25: ='Noida Sec - 18'!G23+'Noida Sec -143'!G23+'Faridabad Sec15'!G23+DLF!G23+'Gurgaon Sec-15'!G23+'Paschim Vihar'!G23+Kalkaji!G23+CP!G23+Rohini!G23+'Model Town'!G23+'Pacific Mall'!G23 -> 13975.833 | I25: ='Noida Sec - 18'!H23+'Noida Sec -143'!H23+'Faridabad Sec15'!H23+DLF!H23+'Gurgaon Sec-15'!H23+'Paschim Vihar'!H23+Kalkaji!H23+CP!H23+Rohini!H23+'Model Town'!H23+'Pacific Mall'!H23 -> 4059.5 | J25: ='Noida Sec - 18'!I23+'Noida Sec -143'!I23+'Faridabad Sec15'!I23+DLF!I23+'Gurgaon Sec-15'!I23+'Paschim Vihar'!I23+Kalkaji!I23+CP!I23+Rohini!I23+'Model Town'!I23+'Pacific Mall'!I23 -> 4059.5 | K25: ='Noida Sec - 18'!J23+'Noida Sec -143'!J23+'Faridabad Sec15'!J23+DLF!J23+'Gurgaon Sec-15'!J23+'Paschim Vihar'!J23+Kalkaji!J23+CP!J23+Rohini!J23+'Model Town'!J23+'Pacific Mall'!J23+'Gurgaon Sec - 10'!J23 -> 4059.5 | L25: ='Noida Sec - 18'!K23+'Noida Sec -143'!K23+DLF!K23+'Faridabad Sec15'!K23+'Gurgaon Sec-15'!K23+'Gurgaon Sec - 10'!K23+'Paschim Vihar'!K23+Kalkaji!K23+CP!K23+Rohini!K23+'Model Town'!K23+'Pacific Mall'!K23 -> 4059.5 | M25: ='Noida Sec - 18'!L23+'Noida Sec -143'!L23+DLF!L23+'Faridabad Sec15'!L23+'Gurgaon Sec-15'!L23+'Gurgaon Sec - 10'!L23+'Paschim Vihar'!L23+Kalkaji!L23+CP!L23+Rohini!L23+'Model Town'!L23+'Pacific Mall'!L23 -> 4059.5 | N25: ='Noida Sec - 18'!M23+'Noida Sec -143'!M23+DLF!M23+'Faridabad Sec15'!M23+'Gurgaon Sec-15'!M23+'Gurgaon Sec - 10'!M23+'Paschim Vihar'!M23+Kalkaji!M23+CP!M23+Rohini!M23+'Model Town'!M23+'Pacific Mall'!M23+'Shalimar Bagh'!M23 -> 4059.5 | O25: =sum(C25:N25) -> 112607.54 | P25: =O25/$O$15 -> 0.0012881659 | R25: 14822 | S25: =C25-R25 -> -567.15333
A26: Repairs & Maintenance | B26: Operation | C26: ='Noida Sec - 18'!B24+'Noida Sec -143'!B24+DLF!B24+'Faridabad Sec15'!B24+'Gurgaon Sec-15'!B24+'Gurgaon Sec - 10'!B24+'Paschim Vihar'!B24+Kalkaji!B24+CP!B24+Rohini!B24+'Model Town'!B24+'Pacific Mall'!B24+'Shalimar Bagh'!B24 -> 13924 | D26: ='Noida Sec - 18'!C24+'Noida Sec -143'!C24+DLF!C24+'Faridabad Sec15'!C24+'Gurgaon Sec-15'!C24+'Gurgaon Sec - 10'!C24+'Paschim Vihar'!C24+Kalkaji!C24+CP!C24+Rohini!C24+'Model Town'!C24+'Pacific Mall'!C24+'Shalimar Bagh'!C24+'Gurgaon Sector 31'!C24 -> 16297 | E26: ='Noida Sec - 18'!D24+'Noida Sec -143'!D24+DLF!D24+'Faridabad Sec15'!D24+'Gurgaon Sec-15'!D24+'Gurgaon Sec - 10'!D24+'Gurgaon Sector 31'!D24+'Paschim Vihar'!D24+Kalkaji!D24+CP!D24+Rohini!D24+'Model Town'!D24+'Pacific Mall'!D24+'Shalimar Bagh'!D24 -> 137550 | F26: ='Noida Sec - 18'!E24+'Noida Sec -143'!E24+DLF!E24+'Faridabad Sec15'!E24+'Gurgaon Sec-15'!E24+'Gurgaon Sec - 10'!E24+'Gurgaon Sector 31'!E24+'Paschim Vihar'!E24+Kalkaji!E24+CP!E24+Rohini!E24+'Model Town'!E24+'Pacific Mall'!E24+'Shalimar Bagh'!E24 -> 147961 | G26: ='Noida Sec - 18'!F24+'Noida Sec -143'!F24+'Faridabad Sec15'!F24+DLF!F24+'Gurgaon Sec-15'!F24+'Paschim Vihar'!F24+Kalkaji!F24+CP!F24+Rohini!F24+'Model Town'!F24+'Pacific Mall'!F24 -> 0 | H26: ='Noida Sec - 18'!G24+'Noida Sec -143'!G24+'Faridabad Sec15'!G24+DLF!G24+'Gurgaon Sec-15'!G24+'Paschim Vihar'!G24+Kalkaji!G24+CP!G24+Rohini!G24+'Model Town'!G24+'Pacific Mall'!G24 -> 0 | I26: ='Noida Sec - 18'!H24+'Noida Sec -143'!H24+'Faridabad Sec15'!H24+DLF!H24+'Gurgaon Sec-15'!H24+'Paschim Vihar'!H24+Kalkaji!H24+CP!H24+Rohini!H24+'Model Town'!H24+'Pacific Mall'!H24 -> 0 | J26: ='Noida Sec - 18'!I24+'Noida Sec -143'!I24+'Faridabad Sec15'!I24+DLF!I24+'Gurgaon Sec-15'!I24+'Paschim Vihar'!I24+Kalkaji!I24+CP!I24+Rohini!I24+'Model Town'!I24+'Pacific Mall'!I24 -> 0 | K26: ='Noida Sec - 18'!J24+'Noida Sec -143'!J24+'Faridabad Sec15'!J24+DLF!J24+'Gurgaon Sec-15'!J24+'Paschim Vihar'!J24+Kalkaji!J24+CP!J24+Rohini!J24+'Model Town'!J24+'Pacific Mall'!J24 -> 0 | L26: ='Noida Sec - 18'!K24+'Noida Sec -143'!K24+DLF!K24+'Faridabad Sec15'!K24+'Gurgaon Sec-15'!K24+'Gurgaon Sec - 10'!K24+'Paschim Vihar'!K24+Kalkaji!K24+CP!K24+Rohini!K24+'Model Town'!K24+'Pacific Mall'!K24 -> 0 | M26: ='Noida Sec - 18'!L24+'Noida Sec -143'!L24+DLF!L24+'Faridabad Sec15'!L24+'Gurgaon Sec-15'!L24+'Gurgaon Sec - 10'!L24+'Paschim Vihar'!L24+Kalkaji!L24+CP!L24+Rohini!L24+'Model Town'!L24+'Pacific Mall'!L24 -> 0 | N26: ='Noida Sec - 18'!M24+'Noida Sec -143'!M24+DLF!M24+'Faridabad Sec15'!M24+'Gurgaon Sec-15'!M24+'Gurgaon Sec - 10'!M24+'Paschim Vihar'!M24+Kalkaji!M24+CP!M24+Rohini!M24+'Model Town'!M24+'Pacific Mall'!M24+'Shalimar Bagh'!M24 -> 0 | O26: =sum(C26:N26) -> 315732 | P26: =O26/$O$15 -> 0.0036117935 | R26: 64439 | S26: =C26-R26 -> -50515
A27: Miscellaneous Expenses | B27: Accounts | C27: ='Noida Sec - 18'!B25+'Noida Sec -143'!B25+DLF!B25+'Faridabad Sec15'!B25+'Gurgaon Sec-15'!B25+'Gurgaon Sec - 10'!B25+'Paschim Vihar'!B25+Kalkaji!B25+CP!B25+Rohini!B25+'Model Town'!B25+'Pacific Mall'!B25+'Shalimar Bagh'!B25 -> 226936.17 | D27: ='Noida Sec - 18'!C25+'Noida Sec -143'!C25+DLF!C25+'Faridabad Sec15'!C25+'Gurgaon Sec-15'!C25+'Gurgaon Sec - 10'!C25+'Paschim Vihar'!C25+Kalkaji!C25+CP!C25+Rohini!C25+'Model Town'!C25+'Pacific Mall'!C25+'Shalimar Bagh'!C25+'Gurgaon Sector 31'!C25 -> 234720.51 | E27: ='Noida Sec - 18'!D25+'Noida Sec -143'!D25+DLF!D25+'Faridabad Sec15'!D25+'Gurgaon Sec-15'!D25+'Gurgaon Sec - 10'!D25+'Gurgaon Sector 31'!D25+'Paschim Vihar'!D25+Kalkaji!D25+CP!D25+Rohini!D25+'Model Town'!D25+'Pacific Mall'!D25+'Shalimar Bagh'!D25 -> 263807.1 | F27: ='Noida Sec - 18'!E25+'Noida Sec -143'!E25+DLF!E25+'Faridabad Sec15'!E25+'Gurgaon Sec-15'!E25+'Gurgaon Sec - 10'!E25+'Gurgaon Sector 31'!E25+'Paschim Vihar'!E25+Kalkaji!E25+CP!E25+Rohini!E25+'Model Town'!E25+'Pacific Mall'!E25+'Shalimar Bagh'!E25 -> 249489.77 | G27: ='Noida Sec - 18'!F25+'Noida Sec -143'!F25+'Faridabad Sec15'!F25+DLF!F25+'Gurgaon Sec-15'!F25+'Paschim Vihar'!F25+Kalkaji!F25+CP!F25+Rohini!F25+'Model Town'!F25+'Pacific Mall'!F25 -> 0 | H27: ='Noida Sec - 18'!G25+'Noida Sec -143'!G25+'Faridabad Sec15'!G25+DLF!G25+'Gurgaon Sec-15'!G25+'Paschim Vihar'!G25+Kalkaji!G25+CP!G25+Rohini!G25+'Model Town'!G25+'Pacific Mall'!G25 -> 0 | I27: ='Noida Sec - 18'!H25+'Noida Sec -143'!H25+'Faridabad Sec15'!H25+DLF!H25+'Gurgaon Sec-15'!H25+'Paschim Vihar'!H25+Kalkaji!H25+CP!H25+Rohini!H25+'Model Town'!H25+'Pacific Mall'!H25 -> 0 | J27: ='Noida Sec - 18'!I25+'Noida Sec -143'!I25+'Faridabad Sec15'!I25+DLF!I25+'Gurgaon Sec-15'!I25+'Paschim Vihar'!I25+Kalkaji!I25+CP!I25+Rohini!I25+'Model Town'!I25+'Pacific Mall'!I25 -> 0 | K27: ='Noida Sec - 18'!J25+'Noida Sec -143'!J25+'Faridabad Sec15'!J25+DLF!J25+'Gurgaon Sec-15'!J25+'Paschim Vihar'!J25+Kalkaji!J25+CP!J25+Rohini!J25+'Model Town'!J25+'Pacific Mall'!J25 -> 0 | L27: ='Noida Sec - 18'!K25+'Noida Sec -143'!K25+DLF!K25+'Faridabad Sec15'!K25+'Gurgaon Sec-15'!K25+'Gurgaon Sec - 10'!K25+'Paschim Vihar'!K25+Kalkaji!K25+CP!K25+Rohini!K25+'Model Town'!K25+'Pacific Mall'!K25 -> 0 | M27: ='Noida Sec - 18'!L25+'Noida Sec -143'!L25+DLF!L25+'Faridabad Sec15'!L25+'Gurgaon Sec-15'!L25+'Gurgaon Sec - 10'!L25+'Paschim Vihar'!L25+Kalkaji!L25+CP!L25+Rohini!L25+'Model Town'!L25+'Pacific Mall'!L25 -> 0 | N27: ='Noida Sec - 18'!M25+'Noida Sec -143'!M25+DLF!M25+'Faridabad Sec15'!M25+'Gurgaon Sec-15'!M25+'Gurgaon Sec - 10'!M25+'Paschim Vihar'!M25+Kalkaji!M25+CP!M25+Rohini!M25+'Model Town'!M25+'Pacific Mall'!M25+'Shalimar Bagh'!M25 -> 0 | O27: =sum(C27:N27) -> 974953.54 | P27: =O27/$O$15 -> 0.011152911 | R27: 187135 | S27: =C27-R27 -> 39801.17
A28: CAM | B28: Accounts | C28: ='Noida Sec - 18'!B26+'Noida Sec -143'!B26+DLF!B26+'Faridabad Sec15'!B26+'Gurgaon Sec-15'!B26+'Gurgaon Sec - 10'!B26+'Paschim Vihar'!B26+Kalkaji!B26+CP!B26+Rohini!B26+'Model Town'!B26+'Pacific Mall'!B26+'Shalimar Bagh'!B26 -> 222667.39 | D28: ='Noida Sec - 18'!C26+'Noida Sec -143'!C26+DLF!C26+'Faridabad Sec15'!C26+'Gurgaon Sec-15'!C26+'Gurgaon Sec - 10'!C26+'Paschim Vihar'!C26+Kalkaji!C26+CP!C26+Rohini!C26+'Model Town'!C26+'Pacific Mall'!C26+'Shalimar Bagh'!C26+'Gurgaon Sector 31'!C26 -> 225937.39 | E28: ='Noida Sec - 18'!D26+'Noida Sec -143'!D26+DLF!D26+'Faridabad Sec15'!D26+'Gurgaon Sec-15'!D26+'Gurgaon Sec - 10'!D26+'Gurgaon Sector 31'!D26+'Paschim Vihar'!D26+Kalkaji!D26+CP!D26+Rohini!D26+'Model Town'!D26+'Pacific Mall'!D26+'Shalimar Bagh'!D26 -> 228043.39 | F28: ='Noida Sec - 18'!E26+'Noida Sec -143'!E26+DLF!E26+'Faridabad Sec15'!E26+'Gurgaon Sec-15'!E26+'Gurgaon Sec - 10'!E26+'Gurgaon Sector 31'!E26+'Paschim Vihar'!E26+Kalkaji!E26+CP!E26+Rohini!E26+'Model Town'!E26+'Pacific Mall'!E26+'Shalimar Bagh'!E26 -> 232843.39 | G28: ='Noida Sec - 18'!F26+'Noida Sec -143'!F26+'Faridabad Sec15'!F26+DLF!F26+'Gurgaon Sec-15'!F26+'Paschim Vihar'!F26+Kalkaji!F26+CP!F26+Rohini!F26+'Model Town'!F26+'Pacific Mall'!F26 -> 0 | H28: ='Noida Sec - 18'!G26+'Noida Sec -143'!G26+'Faridabad Sec15'!G26+DLF!G26+'Gurgaon Sec-15'!G26+'Paschim Vihar'!G26+Kalkaji!G26+CP!G26+Rohini!G26+'Model Town'!G26+'Pacific Mall'!G26 -> 0 | I28: ='Noida Sec - 18'!H26+'Noida Sec -143'!H26+'Faridabad Sec15'!H26+DLF!H26+'Gurgaon Sec-15'!H26+'Paschim Vihar'!H26+Kalkaji!H26+CP!H26+Rohini!H26+'Model Town'!H26+'Pacific Mall'!H26 -> 0 | J28: ='Noida Sec - 18'!I26+'Noida Sec -143'!I26+'Faridabad Sec15'!I26+DLF!I26+'Gurgaon Sec-15'!I26+'Paschim Vihar'!I26+Kalkaji!I26+CP!I26+Rohini!I26+'Model Town'!I26+'Pacific Mall'!I26 -> 0 | K28: ='Noida Sec - 18'!J26+'Noida Sec -143'!J26+'Faridabad Sec15'!J26+DLF!J26+'Gurgaon Sec-15'!J26+'Paschim Vihar'!J26+Kalkaji!J26+CP!J26+Rohini!J26+'Model Town'!J26+'Pacific Mall'!J26 -> 0 | L28: ='Noida Sec - 18'!K26+'Noida Sec -143'!K26+DLF!K26+'Faridabad Sec15'!K26+'Gurgaon Sec-15'!K26+'Gurgaon Sec - 10'!K26+'Paschim Vihar'!K26+Kalkaji!K26+CP!K26+Rohini!K26+'Model Town'!K26+'Pacific Mall'!K26 -> 0 | M28: ='Noida Sec - 18'!L26+'Noida Sec -143'!L26+DLF!L26+'Faridabad Sec15'!L26+'Gurgaon Sec-15'!L26+'Gurgaon Sec - 10'!L26+'Paschim Vihar'!L26+Kalkaji!L26+CP!L26+Rohini!L26+'Model Town'!L26+'Pacific Mall'!L26 -> 0 | N28: ='Noida Sec - 18'!M26+'Noida Sec -143'!M26+DLF!M26+'Faridabad Sec15'!M26+'Gurgaon Sec-15'!M26+'Gurgaon Sec - 10'!M26+'Paschim Vihar'!M26+Kalkaji!M26+CP!M26+Rohini!M26+'Model Town'!M26+'Pacific Mall'!M26+'Shalimar Bagh'!M26 -> 0 | O28: =sum(C28:N28) -> 909491.56 | P28: =O28/$O$15 -> 0.010404063 | R28: 221907 | S28: =C28-R28 -> 760.39
A29: Ads Account | B29: Accounts | C29: ='Ads Account'!B17 -> 769400.94 | D29: ='Ads Account'!C17 -> 808635.44 | E29: ='Ads Account'!D17 -> 661870.35 | F29: ='Ads Account'!E17 -> 995300.26 | G29: ='Ads Account'!F17 -> 25283.919 | H29: ='Ads Account'!G17 -> 25283.919 | I29: ='Ads Account'!H17 -> 25283.919 | J29: ='Ads Account'!I17 -> 25283.919 | ... N29: ='Ads Account'!M17 -> 25283.919 | O29: =sum(C29:N29) -> 3437478.3 | P29: =O29/$O$15 -> 0.039322786 | R29: 711696 | S29: =C29-R29 -> 57704.942
A30: HO+CK Cost | B30: Accounts | C30: ='Noida Sec - 18'!B27+'Noida Sec -143'!B27+DLF!B27+'Faridabad Sec15'!B27+'Gurgaon Sec-15'!B27+'Gurgaon Sec - 10'!B27+'Paschim Vihar'!B27+Kalkaji!B27+CP!B27+Rohini!B27+'Model Town'!B27+'Pacific Mall'!B27+'Shalimar Bagh'!B27 -> 3254735.4 | D30: ='Noida Sec - 18'!C27+'Noida Sec -143'!C27+DLF!C27+'Faridabad Sec15'!C27+'Gurgaon Sec-15'!C27+'Gurgaon Sec - 10'!C27+'Paschim Vihar'!C27+Kalkaji!C27+CP!C27+Rohini!C27+'Model Town'!C27+'Pacific Mall'!C27+'Shalimar Bagh'!C27+'Gurgaon Sector 31'!C27 -> 3298023.1 | E30: ='Noida Sec - 18'!D27+'Noida Sec -143'!D27+DLF!D27+'Faridabad Sec15'!D27+'Gurgaon Sec-15'!D27+'Gurgaon Sec - 10'!D27+'Paschim Vihar'!D27+Kalkaji!D27+CP!D27+Rohini!D27+'Model Town'!D27+'Pacific Mall'!D27+'Shalimar Bagh'!D27+'Gurgaon Sector 31'!D27 -> 3131106.7 | F30: ='Noida Sec - 18'!E27+'Noida Sec -143'!E27+DLF!E27+'Faridabad Sec15'!E27+'Gurgaon Sec-15'!E27+'Gurgaon Sec - 10'!E27+'Paschim Vihar'!E27+Kalkaji!E27+CP!E27+Rohini!E27+'Model Town'!E27+'Pacific Mall'!E27+'Shalimar Bagh'!E27+'Gurgaon Sector 31'!E27 -> 3060447 | G30: ='Noida Sec - 18'!F27+'Noida Sec -143'!F27+'Faridabad Sec15'!F27+DLF!F27+'Gurgaon Sec-15'!F27+'Paschim Vihar'!F27+Kalkaji!F27+CP!F27+Rohini!F27+'Model Town'!F27+'Pacific Mall'!F27 -> #DIV/0! | H30: ='Noida Sec - 18'!G27+'Noida Sec -143'!G27+'Faridabad Sec15'!G27+DLF!G27+'Gurgaon Sec-15'!G27+'Paschim Vihar'!G27+Kalkaji!G27+CP!G27+Rohini!G27+'Model Town'!G27+'Pacific Mall'!G27 -> #DIV/0! | I30: ='Noida Sec - 18'!H27+'Noida Sec -143'!H27+'Faridabad Sec15'!H27+DLF!H27+'Gurgaon Sec-15'!H27+'Paschim Vihar'!H27+Kalkaji!H27+CP!H27+Rohini!H27+'Model Town'!H27+'Pacific Mall'!H27 -> #DIV/0! | J30: ='Noida Sec - 18'!I27+'Noida Sec -143'!I27+'Faridabad Sec15'!I27+DLF!I27+'Gurgaon Sec-15'!I27+'Paschim Vihar'!I27+Kalkaji!I27+CP!I27+Rohini!I27+'Model Town'!I27+'Pacific Mall'!I27 -> #DIV/0! | K30: ='Noida Sec - 18'!J27+'Noida Sec -143'!J27+'Faridabad Sec15'!J27+DLF!J27+'Gurgaon Sec-15'!J27+'Paschim Vihar'!J27+Kalkaji!J27+CP!J27+Rohini!J27+'Model Town'!J27+'Pacific Mall'!J27+'Gurgaon Sec - 10'!J27 -> #DIV/0! | L30: ='Noida Sec - 18'!K27+'Noida Sec -143'!K27+DLF!K27+'Faridabad Sec15'!K27+'Gurgaon Sec-15'!K27+'Gurgaon Sec - 10'!K27+'Paschim Vihar'!K27+Kalkaji!K27+CP!K27+Rohini!K27+'Model Town'!K27+'Pacific Mall'!K27 -> #DIV/0! | M30: ='Noida Sec - 18'!L27+'Noida Sec -143'!L27+DLF!L27+'Faridabad Sec15'!L27+'Gurgaon Sec-15'!L27+'Gurgaon Sec - 10'!L27+'Paschim Vihar'!L27+Kalkaji!L27+CP!L27+Rohini!L27+'Model Town'!L27+'Pacific Mall'!L27 -> #DIV/0! | N30: ='Noida Sec - 18'!M27+'Noida Sec -143'!M27+DLF!M27+'Faridabad Sec15'!M27+'Gurgaon Sec-15'!M27+'Gurgaon Sec - 10'!M27+'Paschim Vihar'!M27+Kalkaji!M27+CP!M27+Rohini!M27+'Model Town'!M27+'Pacific Mall'!M27+'Shalimar Bagh'!M27 -> #DIV/0! | O30: =sum(C30:N30) -> #DIV/0! | P30: =O30/$O$15 -> #DIV/0! | R30: 3242872 | S30: =C30-R30 -> 11863.39
A31: Operating Expenses | C31: =+SUM(C16:C30) -> 21106363 | D31: =+SUM(D16:D30) -> 21649873 | E31: =+SUM(E16:E30) -> 22337643 | F31: =+SUM(F16:F30) -> 22538992 | G31: =+SUM(G16:G30) -> #DIV/0! | H31: =+SUM(H16:H30) -> #DIV/0! | I31: =+SUM(I16:I30) -> #DIV/0! | J31: =+SUM(J16:J30) -> #DIV/0! | ... N31: =+SUM(N16:N30) -> #DIV/0! | O31: =sum(C31:N31) -> #DIV/0! | P31: =O31/$O$15 -> #DIV/0! | R31: 19528649 | S31: =SUM(S16:S30) -> 1577713.2
A32: Store Level EBITDA | C32: =C15-C31 -> 301106.88 | D32: =D15-D31 -> 1058423.6 | E32: =E15-E31 -> -383212.03 | F32: =F15-F31 -> -1192232.3 | G32: =G15-G31 -> #DIV/0! | H32: =H15-H31 -> #DIV/0! | I32: =I15-I31 -> #DIV/0! | J32: =J15-J31 -> #DIV/0! | ... N32: =N15-N31 -> #DIV/0! | O32: =sum(C32:N32) -> #DIV/0! | P32: =O32/$O$15 -> #DIV/0! | R32: 950443.44 | S32: =C32-R32 -> -649336.56
A33: EBITDA Margin % | C33: =C32/C15 -> 0.014065505 | D33: =D32/D15 -> 0.046609556 | E33: =E32/E15 -> -0.017454883 | F33: =F32/F15 -> -0.055850739 | G33: =G32/G15 -> #DIV/0! | H33: =H32/H15 -> #DIV/0! | I33: =I32/I15 -> #DIV/0! | J33: =J32/J15 -> #DIV/0! | ... N33: =N32/N15 -> #DIV/0! | R33: 0.0464 | S33: =C33-R33 -> -0.032334495
A34: Food Cost | C34: =(C16/C15) -> 0.28011624 | D34: =(D16/D15) -> 0.27301313 | E34: =(E16/E15) -> 0.29165942 | F34: =(F16/F15) -> 0.27907175 | G34: =(G16/G15) -> #DIV/0! | H34: =(H16/H15) -> #DIV/0! | I34: =(I16/I15) -> #DIV/0! | J34: =(J16/J15) -> #DIV/0! | ... N34: =(N16/N15) -> #DIV/0! | R34: 0.2772 | S34: =C34-R34 -> 0.0029162441
C37: =C32+C30 -> 3555842.3 | D37: =D32+D30 -> 4356446.8 | E37: =E32+E30 -> 2747894.6 | F37: =F32+F30 -> 1868214.7 | H37: =H32+H30 -> #DIV/0! | I37: =I32+I30 -> #DIV/0! | J37: =J32+J30 -> #DIV/0! | K37: =K32+K30 -> #DIV/0! | L37: =L32+L30 -> #DIV/0! | M37: =M32+M30 -> #DIV/0! | N37: =N32+N30 -> #DIV/0!

Sheet Noida Sec - 18
A1: Dosa Coffee - Noida Sector 18 | B1: 46113 | C1: 46143 | D1: 46174 | E1: 46204 | F1: 46235 | G1: 46266 | H1: 46296 | I1: 46327 | J1: 46357 | K1: 46388 | L1: 46419 | M1: 46447 | N1: FY 2025-26
A2: Food Cost Calculation
A3: Opening Stock | B3: =76058 -> 76058 | C3: =B7 -> 71874.97 | D3: =C7 -> 67029.28 | E3: =D7 -> 61102 | F3: =E7 -> 65481 | G3: =F7 -> 71128.04 | H3: =G7 -> 63923 | I3: =H7 | J3: =I7 | ... M3: =L7 | N3: =+SUM(J3:L3) -> 0
A4: Purchases Food (Less Purchase Return) | B4: 445442 | C4: 537529.7 | D4: 539928 | E4: 520803 | F4: 611035 | G4: 456993 | N4: =sum(B4:M4) -> 3111730.7
A5: Transferred Out | B5: 0 | C5: 0 | D5: 0 | E5: 0 | F5: 0 | G5: 0 | N5: =+SUM(J5:L5) -> 0
A6: Wastage & Date Expired | B6: 16553.61 | C6: 21266.47 | D6: 17540 | E6: 18994 | F6: 18614 | G6: 16055 | N6: =+SUM(J6:L6) -> 0
A7: Closing Stock | B7: 71874.97 | C7: 67029.28 | D7: 61102 | E7: 65481 | F7: 71128.04 | G7: 63923 | N7: =sum(B7:M7) -> 400538.29
A9: Gross Revenue | B9: =1903407.75*1.05+68692.32*1.05 -> 2070705.1 | C9: =2204637.53*1.05+84321.4*1.05 -> 2403406.9 | D9: =2083600*1.05+70*1.05+76928.26*1.05 -> 2268628.2 | E9: =2031470*1.05+68621*1.05 -> 2205095.5 | N9: =+SUM(B9:M9) -> 8947835.7
A10: Catering & Fairs | B10: 0 | C10: 0 | D10: 0 | E10: 0 | N10: =+SUM(B10:M10) -> 0
A11: Less Tax | B11: =(B9+B10)/1.05*0.05 -> 98605.004 | C11: =(C9+C10)/1.05*0.05 -> 114447.95 | D11: =(D9+D10)/1.05*0.05 -> 108029.91 | E11: =(E9+E10)/1.05*0.05 -> 105004.55 | F11: =(F9+F10)/1.05*0.05 -> 0 | G11: =(G9+G10)/1.05*0.05 -> 0 | H11: =(H9+H10)/1.05*0.05 -> 0 | I11: =(I9+I10)/1.05*0.05 -> 0 | ... M11: =(M9+M10)/1.05*0.05 -> 0 | N11: =+SUM(B11:M11) -> 426087.41
A12: Less Commission | B12: =160729.41*1.18+47417.8*1.18+2434.86*1.18+28.196 -> 248515.04 | C12: =197927.66*1.18+53792.41*1.18+3414.39*1.18+29.48 -> 301088.14 | D12: =185158.76*1.18+72646.36*1.18+3484*1.18+74.48*1.18 -> 308409.05 | E12: =54695.54*1.18+161066.49*1.18+1835.85*1.18+35.02 -> 256800.52 | N12: =+SUM(B12:M12) -> 1114812.7
A13: Net Revenues from F&B Sales | B13: =B9+B10-B11-B12 -> 1723585 | C13: =C9+C10-C11-C12 -> 1987870.8 | D13: =D9+D10-D11-D12 -> 1852189.2 | E13: =E9+E10-E11-E12 -> 1843290.5 | F13: =F9+F10-F11-F12 -> 0 | G13: =G9+G10-G11-G12 -> 0 | H13: =H9+H10-H11-H12 -> 0 | I13: =I9+I10-I11-I12 -> 0 | ... M13: =M9+M10-M11-M12 -> 0 | N13: =sum(B13:M13) -> 7406935.5 | O13: =N13/$N$7 -> 18.492453
A14: F&B Cost | B14: =+B3+B4-B5-B7 -> 449625.03 | C14: =+C3+C4-C5-C7 -> 542375.39 | D14: =+D3+D4-D5-D7 -> 545855.28 | E14: =+E3+E4-E5-E7 -> 516424 | F14: =+F3+F4-F5-F7 -> 605387.96 | G14: =+G3+G4-G5-G7 -> 464198.04 | H14: =+H3+H4-H5-H7 -> 63923 | I14: =+I3+I4-I5-I7 -> 0 | ... M14: =+M3+M4-M5-M7 -> 0 | N14: =sum(B14:M14) -> 3187788.7 | O14: =N14/$N$13 -> 0.43037889
A15: Electricity | B15: =64840+2000 -> 66840 | C15: =76622 -> 76622 | D15: 70514 | E15: =75358 -> 75358 | N15: =sum(B15:M15) -> 289334 | O15: =N15/$N$13 -> 0.039062579
A16: Telephone/Internet | B16: =6018/3+300 -> 2306 | C16: =6018/3+300 -> 2306 | D16: =6018/3 -> 2006 | E16: =6018/3 -> 2006 | F16: =6018/3 -> 2006 | G16: =6018/3 -> 2006 | N16: =sum(B16:M16) -> 12636 | O16: =N16/$N$13 -> 0.0017059687
A17: Gas | B17: 70765.91 | C17: 86617.61 | D17: 93622 | E17: 99777 | N17: =sum(B17:M17) -> 350782.52 | O17: =N17/$N$13 -> 0.047358657
A18: Rent & Revenue Share | B18: =393530 -> 393530 | C18: =393530 -> 393530 | D18: =393530 -> 393530 | E18: =393530 -> 393530 | N18: =sum(B18:M18) -> 1574120 | O18: =N18/$N$13 -> 0.21251974
A19: Insurance | B19: =1016 -> 1016 | C19: =26973.31/2/12 -> 1123.8879 | D19: =26973.31/2/12 -> 1123.8879 | E19: =26973.31/2/12 -> 1123.8879 | F19: =26973.31/2/12 -> 1123.8879 | G19: =26973.31/2/12 -> 1123.8879 | H19: =26973.31/2/12 -> 1123.8879 | I19: =26973.31/2/12 -> 1123.8879 | J19: =26973.31/2/12 -> 1123.8879 | ... M19: =26973.31/2/12 -> 1123.8879 | N19: =sum(B19:M19) -> 13378.767 | O19: =N19/$N$13 -> 0.0018062486
A20: Software | B20: 6018 | C20: 6018 | D20: 6018 | E20: 6018 | N20: =sum(B20:M20) -> 24072 | O20: =N20/$N$13 -> 0.003249927
A21: Staff Salary | B21: =403490 -> 403490 | C21: =414264.44 -> 414264.44 | D21: =405615.36 -> 405615.36 | E21: =405467.1 -> 405467.1 | N21: =sum(B21:M21) -> 1628836.9 | O21: =N21/$N$13 -> 0.21990699
A22: AMC | B22: =4720+2950 -> 7670 | C22: =4720+2950 -> 7670 | D22: =4720+2950 -> 7670 | E22: =2950+4720 -> 7670 | N22: =sum(B22:M22) -> 30680 | O22: =N22/$N$13 -> 0.0041420639
A23: Subscription | B23: =2549/3 -> 849.66667 | C23: =2549/3 -> 849.66667 | D23: =2549/3 -> 849.66667 | E23: =2549/3 -> 849.66667 | F23: =2549/3 -> 849.66667 | G23: =2549/3 -> 849.66667 | N23: =sum(B23:M23) -> 5098 | O23: =N23/$N$13 -> 0.00068827385
A24: Repairs & Maintenance | B24: 0 | C24: 0 | D24: 21375 | E24: ='Misc Exp'!B43 -> 2950 | N24: =sum(B24:M24) -> 24325 | O24: =N24/$N$13 -> 0.0032840842
A25: Miscellaneous Expenses | B25: 7509.22 | C25: =14490.88 -> 14490.88 | D25: 15968 | E25: ='Misc Exp'!B37 -> 20941.92 | N25: =sum(B25:M25) -> 58910.02 | O25: =N25/$N$13 -> 0.0079533594
A26: CAM | B26: 0 | C26: 0 | D26: 0 | E26: 0 | F26: 0 | G26: 0 | H26: 0 | I26: 0 | J26: 0 | K26: 0 | L26: 0 | M26: 0 | N26: =sum(B26:M26) -> 0 | O26: =N26/$N$13 -> 0
A27: HO+CK Cost | B27: =HO!D29 -> 262049.33 | C27: =HO!H29 -> 288706.99 | D27: =HO!L29 -> 264156.33 | E27: =HO!P29 -> 264269.28 | F27: =HO!D45 -> #DIV/0! | G27: =HO!H45 -> #DIV/0! | H27: =HO!L45 -> #DIV/0! | I27: =HO!P45 -> #DIV/0! | J27: =HO!D60 -> #DIV/0! | K27: =HO!H60 -> #DIV/0! | L27: =HO!L60 -> #DIV/0! | M27: =HO!P60 -> #DIV/0! | N27: =sum(B27:M27) -> #DIV/0! | O27: =N27/$N$13 -> #DIV/0!
A28: Operating Expenses | B28: =+SUM(B14:B27) -> 1671669.2 | C28: =+SUM(C14:C27) -> 1834574.9 | D28: =+SUM(D14:D27) -> 1828303.5 | E28: =+SUM(E14:E27) -> 1796384.9 | F28: =+SUM(F14:F27) -> #DIV/0! | G28: =+SUM(G14:G27) -> #DIV/0! | H28: =+SUM(H14:H27) -> #DIV/0! | I28: =+SUM(I14:I27) -> #DIV/0! | ... M28: =+SUM(M14:M27) -> #DIV/0! | N28: =sum(B28:M28) -> #DIV/0! | O28: =N28/$N$13 -> #DIV/0!
A29: Store Level EBITDA | B29: =B13-B28 -> 51915.875 | C29: =C13-C28 -> 153295.93 | D29: =D13-D28 -> 23885.689 | E29: =E13-E28 -> 46905.631 | F29: =F13-F28 -> #DIV/0! | G29: =G13-G28 -> #DIV/0! | H29: =H13-H28 -> #DIV/0! | I29: =I13-I28 -> #DIV/0! | ... M29: =M13-M28 -> #DIV/0! | N29: =sum(B29:M29) -> #DIV/0! | O29: =N29/$N$13 -> #DIV/0!
A30: Food Cost | B30: =(B14/B13) -> 0.26086617 | C30: =(C14/C13) -> 0.27284238 | D30: =(D14/D13) -> 0.29470816 | E30: =(E14/E13) -> 0.2801642 | F30: =(F14/F13) -> #DIV/0! | G30: =(G14/G13) -> #DIV/0! | H30: =(H14/H13) -> #DIV/0! | I30: =(I14/I13) -> #DIV/0! | ... M30: =(M14/M13) -> #DIV/0!
B32: =B29+B27 -> 313965.2 | C32: =C29+C27 -> 442002.91 | D32: =D29+D27 -> 288042.02 | E32: =E29+E27 -> 311174.91 | F32: =F29+F27 -> #DIV/0! | G32: =G29+G27 -> #DIV/0! | H32: =H29+H27 -> #DIV/0! | I32: =I29+I27 -> #DIV/0! | ... M32: =M29+M27 -> #DIV/0!
B33: =B32/B13 -> 0.18215823 | C33: =C32/C13 -> 0.22234992 | D33: =D32/D13 -> 0.15551436 | E33: =E32/E13 -> 0.1688149 | F33: =F32/F13 -> #DIV/0! | G33: =G32/G13 -> #DIV/0! | H33: =H32/H13 -> #DIV/0! | I33: =I32/I13 -> #DIV/0! | ... M33: =M32/M13 -> #DIV/0!

Sheet Noida Sec -143
A1: Dosa Coffee - Noida Sector 143 | B1: 46113 | C1: 46143 | D1: 46174 | E1: 46204 | F1: 46235 | G1: 46266 | H1: 46296 | I1: 46327 | J1: 46357 | K1: 46388 | L1: 46419 | M1: 46447 | N1: FY 2025-26
A2: Food Cost Calculation
A3: Opening Stock | B3: 103840 | C3: =B7 -> 93450 | D3: =C7 -> 74574.48 | E3: =D7 -> 81819 | F3: =E7 -> 59490 | G3: =F7 -> 55544 | H3: =G7 -> 58058 | I3: =H7 | J3: =I7 | ... M3: =L7 | N3: =+SUM(J3:L3) -> 0
A4: Purchases Food (Less Purchase Return) | B4: 276138 | C4: 277682.85 | D4: 278086 | E4: 281157 | F4: 287760.71 | G4: 276762.4 | N4: =sum(B4:M4) -> 1677587
A5: Transferred Out | B5: 0 | C5: 0 | D5: 0 | E5: 0 | F5: 0 | G5: 0 | N5: =+SUM(J5:L5) -> 0
A6: Wastage & Date Expired | B6: 29115 | C6: 35849.65 | D6: 20052 | E6: 28593 | F6: 26455 | G6: 25345 | N6: =+SUM(J6:L6) -> 0
A7: Closing Stock | B7: 93450 | C7: =74574.48 -> 74574.48 | D7: 81819 | E7: 59490 | F7: 55544 | G7: 58058 | N7: =sum(B7:M7) -> 422935.48
A9: Gross Revenue | B9: =1060925.74*1.05+41547.61*1.05 -> 1157597 | C9: =1170213.72*1.05+47396.07*1.05 -> 1278490.3 | D9: =954766.85*1.05+36910.57*1.05 -> 1041261.3 | E9: =1008779*1.05+34966*1.05 -> 1095932.2 | N9: =+SUM(B9:M9) -> 4573280.8
A10: Catering & Fairs | B10: 0 | N10: =+SUM(B10:M10) -> 0
A11: Less Tax | B11: =(B9+B10)/1.05*0.05 -> 55123.668 | C11: =(C9+C10)/1.05*0.05 -> 60880.49 | D11: =(D9+D10)/1.05*0.05 -> 49583.871 | E11: =(E9+E10)/1.05*0.05 -> 52187.25 | F11: =(F9+F10)/1.05*0.05 -> 0 | G11: =(G9+G10)/1.05*0.05 -> 0 | H11: =(H9+H10)/1.05*0.05 -> 0 | I11: =(I9+I10)/1.05*0.05 -> 0 | ... M11: =(M9+M10)/1.05*0.05 -> 0 | N11: =+SUM(B11:M11) -> 217775.28
A12: Less Commission | B12: =96459.46*1.18+28973.35*1.18+4709.26*1.18+1438.19*1.18+89.39 -> 155354.1 | C12: =110291.55*1.18+34303.75*1.18+900.79*1.18+99.1 -> 171784.49 | D12: =80955.57*1.18+41528.7*1.18+1288.96*1.18+149.94*1.18 -> 146229.34 | E12: =30386.73*1.18+81836.12*1.18+1305.9*1.18+51.25 -> 134015.17 | N12: =+SUM(B12:M12) -> 607383.1
A13: Net Revenues from F&B Sales | B13: =B9+B10-B11-B12 -> 947119.25 | C13: =C9+C10-C11-C12 -> 1045825.3 | D13: =D9+D10-D11-D12 -> 845448.08 | E13: =E9+E10-E11-E12 -> 909729.82 | F13: =F9+F10-F11-F12 -> 0 | G13: =G9+G10-G11-G12 -> 0 | H13: =H9+H10-H11-H12 -> 0 | I13: =I9+I10-I11-I12 -> 0 | ... M13: =M9+M10-M11-M12 -> 0 | N13: =sum(B13:M13) -> 3748122.5 | O13: =N13/$N$7 -> 8.8621613
A14: F&B Cost | B14: =+B3+B4-B5-B7 -> 286528 | C14: =+C3+C4-C5-C7 -> 296558.37 | D14: =+D3+D4-D5-D7 -> 270841.48 | E14: =+E3+E4-E5-E7 -> 303486 | F14: =+F3+F4-F5-F7 -> 291706.71 | G14: =+G3+G4-G5-G7 -> 274248.4 | H14: =+H3+H4-H5-H7 -> 58058 | I14: =+I3+I4-I5-I7 -> 0 | ... M14: =+M3+M4-M5-M7 -> 0 | N14: =sum(B14:M14) -> 1781427 | O14: =N14/$N$7 -> 4.2120537
A15: Electricity | B15: =40056 -> 40056 | C15: 45395 | D15: 49107 | E15: 45163 | N15: =sum(B15:M15) -> 179721 | O15: =N15/$N$7 -> 0.42493716
A16: Telephone/Internet | B16: =1060+489 -> 1549 | C16: =1060+489 -> 1549 | D16: =1060+489 -> 1549 | E16: =1060+489 -> 1549 | N16: =sum(B16:M16) -> 6196 | O16: =N16/$N$7 -> 0.014649989
A17: Gas | B17: 0 | C17: 0 | D17: 0 | E17: 0 | N17: =sum(B17:M17) -> 0 | O17: =N17/$N$7 -> 0
A18: Rent & Revenue Share | B18: =166416.25 -> 166416.25 | C18: =183645 -> 183645 | D18: 149486 | E18: 150692 | N18: =sum(B18:M18) -> 650239.25 | O18: =N18/$N$7 -> 1.5374431
A19: Insurance | B19: 809 | C19: =26973/2/12 -> 1123.875 | D19: =26973/2/12 -> 1123.875 | E19: =26973/2/12 -> 1123.875 | F19: =26973/2/12 -> 1123.875 | G19: =26973/2/12 -> 1123.875 | H19: =26973/2/12 -> 1123.875 | I19: =26973/2/12 -> 1123.875 | J19: =26973/2/12 -> 1123.875 | ... M19: =26973/2/12 -> 1123.875 | N19: =sum(B19:M19) -> 13171.625
A20: Software | B20: 5767 | C20: 5767 | D20: 5767 | E20: 5767 | N20: =sum(B20:M20) -> 23068 | O20: =N20/$N$7 -> 0.054542598
A21: Staff Salary | B21: =232681+8000 -> 240681 | C21: =8000+2000+238491.56 -> 248491.56 | D21: =10000+232247.56 -> 242247.56 | E21: =240401.22+10000 -> 250401.22 | N21: =sum(B21:M21) -> 981821.34 | O21: =N21/$N$7 -> 2.3214447
A22: AMC | B22: =4720+2950 -> 7670 | C22: =4720+2950 -> 7670 | D22: =4720+2950 -> 7670 | E22: =2950+4720 -> 7670 | N22: =sum(B22:M22) -> 30680 | O22: =N22/$N$7 -> 0.072540615
A23: Subscription | B23: =2549/3 -> 849.66667 | C23: =2549/3 -> 849.66667 | D23: =2549/3 -> 849.66667 | E23: =2549/3 -> 849.66667 | F23: =2549/3 -> 849.66667 | G23: =2549/3 -> 849.66667 | N23: =sum(B23:M23) -> 5098 | O23: =N23/$N$7 -> 0.012053848
A24: Repairs & Maintenance | B24: 6608 | C24: 0 | D24: 0 | E24: ='Misc Exp'!C43 -> 8056 | N24: =sum(B24:M24) -> 14664 | O24: =N24/$N$7 -> 0.034671955
A25: Miscellaneous Expenses | B25: 3138.71 | C25: =8526.63 -> 8526.63 | D25: 5463 | E25: ='Misc Exp'!C37 -> 11888 | N25: =sum(B25:M25) -> 29016.34 | O25: =N25/$N$7 -> 0.068607013
A26: CAM | B26: =22732 -> 22732 | C26: 26002 | D26: 28108 | E26: 32908 | N26: =sum(B26:M26) -> 109750 | O26: =N26/$N$7 -> 0.25949585
A27: HO+CK Cost | B27: =HO!D30 -> 143997.52 | C27: =HO!H30 -> 151889.69 | D27: =HO!L30 -> 120576.48 | E27: =HO!P30 -> 130426.35 | F27: =HO!D46 -> #DIV/0! | G27: =HO!H46 -> #DIV/0! | H27: =HO!L46 -> #DIV/0! | I27: =HO!P46 -> #DIV/0! | J27: =HO!D61 -> #DIV/0! | K27: =HO!H61 -> #DIV/0! | L27: =HO!L61 -> #DIV/0! | M27: =HO!P61 -> #DIV/0! | N27: =sum(B27:M27) -> #DIV/0! | O27: =N27/$N$7 -> #DIV/0!
A28: Operating Expenses | B28: =+SUM(B14:B27) -> 926802.14 | C28: =+SUM(C14:C27) -> 977467.79 | D28: =+SUM(D14:D27) -> 882789.06 | E28: =+SUM(E14:E27) -> 949980.11 | F28: =+SUM(F14:F27) -> #DIV/0! | G28: =+SUM(G14:G27) -> #DIV/0! | H28: =+SUM(H14:H27) -> #DIV/0! | I28: =+SUM(I14:I27) -> #DIV/0! | ... M28: =+SUM(M14:M27) -> #DIV/0! | N28: =sum(B28:M28) -> #DIV/0! | O28: =N28/$N$7 -> #DIV/0!
A29: Store Level EBITDA | B29: =B13-B28 -> 20317.109 | C29: =C13-C28 -> 68357.515 | D29: =D13-D28 -> -37340.985 | E29: =E13-E28 -> -40250.283 | F29: =F13-F28 -> #DIV/0! | G29: =G13-G28 -> #DIV/0! | H29: =H13-H28 -> #DIV/0! | I29: =I13-I28 -> #DIV/0! | ... M29: =M13-M28 -> #DIV/0! | N29: =sum(B29:M29) -> #DIV/0! | O29: =N29/$N$7 -> #DIV/0!
A30: Food Cost | B30: =(B14/B13) -> 0.30252579 | C30: =(C14/C13) -> 0.28356397 | D30: =(D14/D13) -> 0.32035259 | E30: =(E14/E13) -> 0.33360014 | F30: =(F14/F13) -> #DIV/0! | G30: =(G14/G13) -> #DIV/0! | H30: =(H14/H13) -> #DIV/0! | I30: =(I14/I13) -> #DIV/0! | ... M30: =(M14/M13) -> #DIV/0!
B32: =B29+B27 -> 164314.63 | C32: =C29+C27 -> 220247.2 | D32: =D29+D27 -> 83235.498 | E32: =E29+E27 -> 90176.063 | F32: =F29+F27 -> #DIV/0! | G32: =G29+G27 -> #DIV/0! | H32: =H29+H27 -> #DIV/0! | I32: =I29+I27 -> #DIV/0! | ... M32: =M29+M27 -> #DIV/0!
B33: =B32/B13 -> 0.17348885 | C33: =C32/C13 -> 0.21059655 | D33: =D32/D13 -> 0.098451342 | E33: =E32/E13 -> 0.099124005 | F33: =F32/F13 -> #DIV/0! | G33: =G32/G13 -> #DIV/0! | H33: =H32/H13 -> #DIV/0! | I33: =I32/I13 -> #DIV/0! | ... M33: =M32/M13 -> #DIV/0!

Sheet DLF
A1: Dosa Coffee - DLF | B1: 46113 | C1: 46143 | D1: 46174 | E1: 46204 | F1: 46235 | G1: 46266 | H1: 46296 | I1: 46327 | J1: 46357 | K1: 46388 | L1: 46419 | M1: 46447 | N1: FY 2025-26
A2: Food Cost Calculation
A3: Opening Stock | B3: 53663 | C3: =B7 -> 69458.96 | D3: =C7 -> 67234.11 | E3: =D7 -> 70784 | F3: =E7 -> 59607.8 | G3: =F7 -> 52984 | H3: =G7 -> 51744 | I3: =H7 | J3: =I7 | ... M3: =L7 | N3: =+SUM(J3:L3) -> 0
A4: Purchases Food (Less Purchase Return) | B4: =401116.14 -> 401116.14 | C4: 410387.41 | D4: =420420+947 -> 421367 | E4: 419823 | F4: =426942 -> 426942 | G4: 439629 | N4: =sum(B4:M4) -> 2519264.5
A5: Transferred Out | B5: 1412 | C5: 255.24 | D5: 0 | E5: 0 | F5: 0 | G5: 0 | N5: =+SUM(J5:L5) -> 0
A6: Wastage & Date Expired | B6: 15060 | C6: 36497.57 | D6: 11792 | E6: 17340.96 | F6: 16120 | G6: 17661 | N6: =+SUM(J6:L6) -> 0
A7: Closing Stock | B7: 69458.96 | C7: 67234.11 | D7: 70784 | E7: 59607.8 | F7: 52984 | G7: 51744 | N7: =sum(B7:M7) -> 371812.87
A9: Gross Revenue | B9: =1873928.31*1.05+58447.08*1.05 -> 2028994.2 | C9: =1816551.76*1.05+62979.41*1.05 -> 1973507.7 | D9: =1761995*1.05+61948.72*1.05 -> 1915140.9 | E9: =1845676.89*1.05+58122*1.05 -> 1998988.8 | N9: =+SUM(B9:M9) -> 7916631.6
A10: Catering & Fairs | B10: 0 | N10: =+SUM(B10:M10) -> 0
A11: Less Tax | B11: =(B9+B10)/1.05*0.05 -> 96618.769 | C11: =(C9+C10)/1.05*0.05 -> 93976.558 | D11: =(D9+D10)/1.05*0.05 -> 91197.186 | E11: =(E9+E10)/1.05*0.05 -> 95189.944 | F11: =(F9+F10)/1.05*0.05 -> 0 | G11: =(G9+G10)/1.05*0.05 -> 0 | H11: =(H9+H10)/1.05*0.05 -> 0 | I11: =(I9+I10)/1.05*0.05 -> 0 | ... M11: =(M9+M10)/1.05*0.05 -> 0 | N11: =+SUM(B11:M11) -> 376982.46
A12: Less Commission | B12: =135807.74*1.18+42649.53*1.18+1003.8*1.18 -> 211764.06 | C12: =145580.42*1.18+49289.16*1.18+944.15*1.18 -> 231060.2 | D12: =143525.37*1.18+47978.4*1.18+1022.85*1.18 -> 227181.41 | E12: =135121.61*1.18+50307.67*1.18+1014.38*1.18 -> 220003.52 | N12: =+SUM(B12:M12) -> 890009.19
A13: Net Revenues from F&B Sales | B13: =B9+B10-B11-B12 -> 1720611.3 | C13: =C9+C10-C11-C12 -> 1648471 | D13: =D9+D10-D11-D12 -> 1596762.3 | E13: =E9+E10-E11-E12 -> 1683795.4 | F13: =F9+F10-F11-F12 -> 0 | G13: =G9+G10-G11-G12 -> 0 | H13: =H9+H10-H11-H12 -> 0 | I13: =I9+I10-I11-I12 -> 0 | ... M13: =M9+M10-M11-M12 -> 0 | N13: =sum(B13:M13) -> 6649640 | O13: =N13/$N$7 -> 17.884373
A14: F&B Cost | B14: =+B3+B4-B5-B7 -> 383908.18 | C14: =+C3+C4-C5-C7 -> 412357.02 | D14: =+D3+D4-D5-D7 -> 417817.11 | E14: =+E3+E4-E5-E7 -> 430999.2 | F14: =+F3+F4-F5-F7 -> 433565.8 | G14: =+G3+G4-G5-G7 -> 440869 | H14: =+H3+H4-H5-H7 -> 51744 | I14: =+I3+I4-I5-I7 -> 0 | ... M14: =+M3+M4-M5-M7 -> 0 | N14: =sum(B14:M14) -> 2571260.3 | O14: =N14/$N$7 -> 6.9154688
A15: Electricity | B15: =12169 -> 12169 | C15: =52002 -> 52002 | D15: 57418.95 | E15: =113704 -> 113704 | N15: =sum(B15:M15) -> 235293.95 | O15: =N15/$N$7 -> 0.63282896
A16: Telephone/Internet | B16: 943 | C16: 943 | D16: 943 | E16: 943 | N16: =sum(B16:M16) -> 3772 | O16: =N16/$N$7 -> 0.010144888
A17: Gas | B17: 0 | C17: 0 | D17: 0 | E17: 0 | N17: =sum(B17:M17) -> 0 | O17: =N17/$N$7 -> 0
A18: Rent & Revenue Share | B18: =139240 -> 139240 | C18: =139240 -> 139240 | D18: =139240 -> 139240 | E18: =139240 -> 139240 | N18: =sum(B18:M18) -> 556960 | O18: =N18/$N$7 -> 1.4979578
A19: Insurance | B19: 1055 | C19: =36951.85/4/12 -> 769.83021 | D19: =36951.85/4/12 -> 769.83021 | E19: =36951.85/4/12 -> 769.83021 | F19: =36951.85/4/12 -> 769.83021 | G19: =36951.85/4/12 -> 769.83021 | H19: =36951.85/4/12 -> 769.83021 | I19: =36951.85/4/12 -> 769.83021 | J19: =36951.85/4/12 -> 769.83021 | ... M19: =36951.85/4/12 -> 769.83021 | N19: =sum(B19:M19) -> 9523.1323
A20: Software | B20: 4764 | C20: 4764 | D20: 4764 | E20: 4764 | N20: =sum(B20:M20) -> 19056 | O20: =N20/$N$7 -> 0.051251588
A21: Staff Salary | B21: =262524+9250 -> 271774 | C21: =9250+268844.15 -> 278094.15 | D21: =9250+243531.64 -> 252781.64 | E21: =277022.04+9250 -> 286272.04 | N21: =sum(B21:M21) -> 1088921.8 | O21: =N21/$N$7 -> 2.9286825
A22: AMC | B22: =4720+2950 -> 7670 | C22: =4720+2950 -> 7670 | D22: =4720+2950 -> 7670 | E22: =2950+4720 -> 7670 | N22: =sum(B22:M22) -> 30680 | O22: =N22/$N$7 -> 0.082514626
A23: Subscription | B23: =2548.75/3 -> 849.58333 | C23: =2548.75/3 -> 849.58333 | D23: =2548.75/3 -> 849.58333 | E23: =2537/3 -> 845.66667 | F23: =2537/3 -> 845.66667 | G23: =2537/3 -> 845.66667 | N23: =sum(B23:M23) -> 5085.75 | O23: =N23/$N$7 -> 0.013678252
A24: Repairs & Maintenance | B24: 0 | C24: 0 | D24: 11210 | E24: ='Misc Exp'!D43 -> 0 | N24: =sum(B24:M24) -> 11210 | O24: =N24/$N$7 -> 0.030149575
A25: Miscellaneous Expenses | B25: 7190.88 | C25: 10642.17 | D25: 9227.77 | E25: ='Misc Exp'!D37 -> 10698.94 | N25: =sum(B25:M25) -> 37759.76 | O25: =N25/$N$7 -> 0.10155582
A26: CAM | B26: =40031.5 -> 40031.5 | C26: =40031.5 -> 40031.5 | D26: =40031.5 -> 40031.5 | E26: =40031.5 -> 40031.5 | N26: =sum(B26:M26) -> 160126 | O26: =N26/$N$7 -> 0.43066288
A27: HO+CK Cost | B27: =HO!D32 -> 261597.22 | C27: =HO!H32 -> 239414.5 | D27: =HO!L32 -> 227727.74 | E27: =HO!P32 -> 241402.75 | F27: =HO!D48 -> #DIV/0! | G27: =HO!H48 -> #DIV/0! | H27: =HO!L48 -> #DIV/0! | I27: =HO!P48 -> #DIV/0! | J27: =HO!D63 -> #DIV/0! | K27: =HO!H63 -> #DIV/0! | L27: =HO!L63 -> #DIV/0! | M27: =HO!P63 -> #DIV/0! | N27: =sum(B27:M27) -> #DIV/0! | O27: =N27/$N$7 -> #DIV/0!
A28: Operating Expenses | B28: =+SUM(B14:B27) -> 1131192.4 | C28: =+SUM(C14:C27) -> 1186777.8 | D28: =+SUM(D14:D27) -> 1170451.1 | E28: =+SUM(E14:E27) -> 1277340.9 | F28: =+SUM(F14:F27) -> #DIV/0! | G28: =+SUM(G14:G27) -> #DIV/0! | H28: =+SUM(H14:H27) -> #DIV/0! | I28: =+SUM(I14:I27) -> #DIV/0! | ... M28: =+SUM(M14:M27) -> #DIV/0! | N28: =sum(B28:M28) -> #DIV/0! | O28: =N28/$N$7 -> #DIV/0!
A29: Store Level EBITDA | B29: =B13-B28 -> 589418.97 | C29: =C13-C28 -> 461693.22 | D29: =D13-D28 -> 426311.18 | E29: =E13-E28 -> 406454.45 | F29: =F13-F28 -> #DIV/0! | G29: =G13-G28 -> #DIV/0! | H29: =H13-H28 -> #DIV/0! | I29: =I13-I28 -> #DIV/0! | ... M29: =M13-M28 -> #DIV/0! | N29: =sum(B29:M29) -> #DIV/0! | O29: =N29/$N$7 -> #DIV/0!
A30: Food Cost | B30: =(B14/B13) -> 0.22312313 | C30: =(C14/C13) -> 0.25014515 | D30: =(D14/D13) -> 0.26166519 | E30: =(E14/E13) -> 0.25596887 | F30: =(F14/F13) -> #DIV/0! | G30: =(G14/G13) -> #DIV/0! | H30: =(H14/H13) -> #DIV/0! | I30: =(I14/I13) -> #DIV/0! | ... M30: =(M14/M13) -> #DIV/0!
B32: =B29+B27 -> 851016.18 | C32: =C29+C27 -> 701107.72 | D32: =D29+D27 -> 654038.92 | E32: =E29+E27 -> 647857.19 | F32: =F29+F27 -> #DIV/0! | G32: =G29+G27 -> #DIV/0! | H32: =H29+H27 -> #DIV/0! | I32: =I29+I27 -> #DIV/0! | ... M32: =M29+M27 -> #DIV/0!
B33: =B32/B13 -> 0.49460106 | C33: =C32/C13 -> 0.42530789 | D33: =D32/D13 -> 0.40960318 | E33: =E32/E13 -> 0.38476005 | F33: =F32/F13 -> #DIV/0! | G33: =G32/G13 -> #DIV/0! | H33: =H32/H13 -> #DIV/0! | I33: =I32/I13 -> #DIV/0! | ... M33: =M32/M13 -> #DIV/0!

Sheet Faridabad Sec15
A1: Dosa Coffee - Faridabad Sec 15 | B1: 46113 | C1: 46143 | D1: 46174 | E1: 46204 | F1: 46235 | G1: 46266 | H1: 46296 | I1: 46327 | J1: 46357 | K1: 46388 | L1: 46419 | M1: 46447 | N1: FY 2025-26
A2: Food Cost Calculation
A3: Opening Stock | B3: 58923 | C3: =B7 -> 48098.96 | D3: =C7 -> 45292.3 | E3: =D7 -> 61299.75 | F3: =E7 -> 51680 | G3: =F7 -> 44659.3 | H3: =G7 -> 17906 | I3: =H7 | J3: =I7 | ... M3: =L7 | N3: =+SUM(J3:L3) -> 0
A4: Purchases Food (Less Purchase Return) | B4: 271973.16 | C4: 303796 | D4: =331556+3288 -> 334844 | E4: 311448 | F4: 289536 | G4: 247318 | N4: =sum(B4:M4) -> 1758915.2
A5: Transferred Out | B5: 0 | C5: 0 | D5: 0 | E5: 0 | F5: 0 | G5: 0 | N5: =+SUM(J5:L5) -> 0
A6: Wastage & Date Expired | B6: 13013 | C6: 13477.39 | D6: 13039 | E6: 13752 | F6: 12882.77 | G6: 12878 | N6: =+SUM(J6:L6) -> 0
A7: Closing Stock | B7: 48098.96 | C7: 45292.3 | D7: 61299.75 | E7: 51680 | F7: 44659.3 | G7: 17906 | N7: =sum(B7:M7) -> 268936.31
A9: Gross Revenue | B9: =988553*1.05+42099.96*1.05 -> 1082185.6 | C9: =1110726.95*1.05+46945.07*1.05 -> 1215555.6 | D9: =1146584.06*1.05+43855.79*1.05 -> 1249961.8 | E9: =1010848.2*1.05+36201*1.05 -> 1099401.7 | N9: =+SUM(B9:M9) -> 4647104.7
A10: Catering & Fairs | B10: 0 | N10: =+SUM(B10:M10) -> 0
A11: Less Tax | B11: =(B9+B10)/1.05*0.05 -> 51532.648 | C11: =(C9+C10)/1.05*0.05 -> 57883.601 | D11: =(D9+D10)/1.05*0.05 -> 59521.993 | E11: =(E9+E10)/1.05*0.05 -> 52352.46 | F11: =(F9+F10)/1.05*0.05 -> 0 | G11: =(G9+G10)/1.05*0.05 -> 0 | H11: =(H9+H10)/1.05*0.05 -> 0 | I11: =(I9+I10)/1.05*0.05 -> 0 | ... M11: =(M9+M10)/1.05*0.05 -> 0 | N11: =+SUM(B11:M11) -> 221290.7
A12: Less Commission | B12: =97706.12*1.18+27243.84*1.18+1426.18*1.18 -> 149123.85 | C12: =109290.42*1.18+36414.29*1.18+1608.55*1.18 -> 173829.65 | D12: =101993.14*1.18+39031.76*1.18+1346.83*1.18 -> 167998.64 | E12: =84646.2*1.18+43195*1.18+427.52*1.18 -> 151357.09 | N12: =+SUM(B12:M12) -> 642309.22
A13: Net Revenues from F&B Sales | B13: =B9+B10-B11-B12 -> 881529.11 | C13: =C9+C10-C11-C12 -> 983842.37 | D13: =D9+D10-D11-D12 -> 1022441.2 | E13: =E9+E10-E11-E12 -> 895692.11 | F13: =F9+F10-F11-F12 -> 0 | G13: =G9+G10-G11-G12 -> 0 | H13: =H9+H10-H11-H12 -> 0 | I13: =I9+I10-I11-I12 -> 0 | ... M13: =M9+M10-M11-M12 -> 0 | N13: =sum(B13:M13) -> 3783504.8 | O13: =N13/$N$7 -> 14.068405
A14: F&B Cost | B14: =+B3+B4-B5-B7 -> 282797.2 | C14: =+C3+C4-C5-C7 -> 306602.66 | D14: =+D3+D4-D5-D7 -> 318836.55 | E14: =+E3+E4-E5-E7 -> 321067.75 | F14: =+F3+F4-F5-F7 -> 296556.7 | G14: =+G3+G4-G5-G7 -> 274071.3 | H14: =+H3+H4-H5-H7 -> 17906 | I14: =+I3+I4-I5-I7 -> 0 | ... M14: =+M3+M4-M5-M7 -> 0 | N14: =sum(B14:M14) -> 1817838.2 | O14: =N14/$N$7 -> 6.7593631
A15: Electricity | B15: =60228+16520+4700 -> 81448 | C15: =61718+16520+4900 -> 83138 | D15: =78536+4900+16520+7300 -> 107256 | E15: =103640+16520+8400+7400+7300 -> 143260 | N15: =sum(B15:M15) -> 415102 | O15: =N15/$N$7 -> 1.5434956
A16: Telephone/Internet | B16: 1497 | C16: =200+1296 -> 1496 | D16: =1296+200 -> 1496 | E16: =1296+200 -> 1496 | N16: =sum(B16:M16) -> 5985 | O16: =N16/$N$7 -> 0.02225434
A17: Gas | B17: 0 | C17: 0 | D17: 0 | N17: =sum(B17:M17) -> 0 | O17: =N17/$N$7 -> 0
A18: Rent & Revenue Share | B18: =62336.23+62336.23 -> 124672.46 | C18: =62336.23+62336.23 -> 124672.46 | D18: =64331.77+64331.77 -> 128663.54 | E18: =97350+97350 -> 194700 | N18: =sum(B18:M18) -> 572708.46 | O18: =N18/$N$7 -> 2.1295319
A19: Insurance | B19: 926 | C19: =36951.85/4/12 -> 769.83021 | D19: =36951.85/4/12 -> 769.83021 | E19: =36951.85/4/12 -> 769.83021 | F19: =36951.85/4/12 -> 769.83021 | G19: =36951.85/4/12 -> 769.83021 | H19: =36951.85/4/12 -> 769.83021 | I19: =36951.85/4/12 -> 769.83021 | J19: =36951.85/4/12 -> 769.83021 | ... M19: =36951.85/4/12 -> 769.83021 | N19: =sum(B19:M19) -> 9394.1323
A20: Software | B20: 5767 | C20: 5767 | D20: 5767 | E20: 5767 | N20: =sum(B20:M20) -> 23068 | O20: =N20/$N$7 -> 0.085774955
A21: Staff Salary | B21: =225287+14500 -> 239787 | C21: =14500+231504.7 -> 246004.7 | D21: =14500+269742.32 -> 284242.32 | E21: =264442.3 -> 264442.3 | N21: =sum(B21:M21) -> 1034476.3 | O21: =N21/$N$7 -> 3.8465476
A22: AMC | B22: =4720+2950 -> 7670 | C22: =4720+2950 -> 7670 | D22: =4720+2950 -> 7670 | E22: =2950+4720 -> 7670 | N22: =sum(B22:M22) -> 30680 | O22: =N22/$N$7 -> 0.11407905
A23: Subscription | B23: =2548.75/3 -> 849.58333 | C23: =2548.75/3 -> 849.58333 | D23: =2548.75/3 -> 849.58333 | E23: =2537/3 -> 845.66667 | F23: =2537/3 -> 845.66667 | G23: =2537/3 -> 845.66667 | N23: =sum(B23:M23) -> 5085.75 | O23: =N23/$N$7 -> 0.018910611
A24: Repairs & Maintenance | B24: 0 | C24: 740 | D24: 0 | E24: ='Misc Exp'!E43 -> 22426 | N24: =sum(B24:M24) -> 23166 | O24: =N24/$N$7 -> 0.086139354
A25: Miscellaneous Expenses | B25: 2362 | C25: 14386.83 | D25: 22588.19 | E25: ='Misc Exp'!E37 -> 9284.93 | N25: =sum(B25:M25) -> 48621.95 | O25: =N25/$N$7 -> 0.18079355
A26: CAM | B26: 0 | C26: 0 | D26: 0 | E26: 0 | N26: =sum(B26:M26) -> 0 | O26: =N26/$N$7 -> 0
A27: HO+CK Cost | B27: =HO!D31 -> 134025.37 | C27: =HO!H31 -> 142887.64 | D27: =HO!L31 -> 145818.97 | E27: =HO!P31 -> 128413.78 | F27: =HO!D47 -> #DIV/0! | G27: =HO!H47 -> #DIV/0! | H27: =HO!L47 -> #DIV/0! | I27: =HO!P47 -> #DIV/0! | J27: =HO!D62 -> #DIV/0! | K27: =HO!H62 -> #DIV/0! | L27: =HO!L62 -> #DIV/0! | M27: =HO!P62 -> #DIV/0! | N27: =sum(B27:M27) -> #DIV/0! | O27: =N27/$N$7 -> #DIV/0!
A28: Operating Expenses | B28: =+SUM(B14:B27) -> 881801.61 | C28: =+SUM(C14:C27) -> 934984.7 | D28: =+SUM(D14:D27) -> 1023958 | E28: =+SUM(E14:E27) -> 1100143.3 | F28: =+SUM(F14:F27) -> #DIV/0! | G28: =+SUM(G14:G27) -> #DIV/0! | H28: =+SUM(H14:H27) -> #DIV/0! | I28: =+SUM(I14:I27) -> #DIV/0! | ... M28: =+SUM(M14:M27) -> #DIV/0! | N28: =sum(B28:M28) -> #DIV/0! | O28: =N28/$N$7 -> #DIV/0!
A29: Store Level EBITDA | B29: =B13-B28 -> -272.49416 | C29: =C13-C28 -> 48857.669 | D29: =D13-D28 -> -1516.7712 | E29: =E13-E28 -> -204451.15 | F29: =F13-F28 -> #DIV/0! | G29: =G13-G28 -> #DIV/0! | H29: =H13-H28 -> #DIV/0! | I29: =I13-I28 -> #DIV/0! | ... M29: =M13-M28 -> #DIV/0! | N29: =sum(B29:M29) -> #DIV/0! | O29: =N29/$N$7 -> #DIV/0!
A30: Food Cost | B30: =(B14/B13) -> 0.32080302 | C30: =(C14/C13) -> 0.31163799 | D30: =(D14/D13) -> 0.31183852 | E30: =(E14/E13) -> 0.35845772 | F30: =(F14/F13) -> #DIV/0! | G30: =(G14/G13) -> #DIV/0! | H30: =(H14/H13) -> #DIV/0! | I30: =(I14/I13) -> #DIV/0! | ... M30: =(M14/M13) -> #DIV/0!
B32: =B29+B27 -> 133752.87 | C32: =C29+C27 -> 191745.31 | D32: =D29+D27 -> 144302.2 | E32: =E29+E27 -> -76037.366 | F32: =F29+F27 -> #DIV/0! | G32: =G29+G27 -> #DIV/0! | H32: =H29+H27 -> #DIV/0! | I32: =I29+I27 -> #DIV/0! | ... M32: =M29+M27 -> #DIV/0!
B33: =B32/B13 -> 0.15172825 | C33: =C32/C13 -> 0.19489434 | D33: =D32/D13 -> 0.14113496 | E33: =E32/E13 -> -0.084892304 | F33: =F32/F13 -> #DIV/0! | G33: =G32/G13 -> #DIV/0! | H33: =H32/H13 -> #DIV/0! | I33: =I32/I13 -> #DIV/0! | ... M33: =M32/M13 -> #DIV/0!

Sheet Gurgaon Sec-15
A1: Dosa Coffee - Huda Market | B1: 46113 | C1: 46143 | D1: 46174 | E1: 46204 | F1: 46235 | G1: 46266 | H1: 46296 | I1: 46327 | J1: 46357 | K1: 46388 | L1: 46419 | M1: 46447 | N1: FY 2025-26
A2: Food Cost Calculation
A3: Opening Stock | B3: 69049 | C3: =B7 -> 77139.91 | D3: =C7 -> 64823.23 | E3: =D7 -> 67658 | F3: =E7 -> 77230 | G3: =F7 -> 74378 | H3: =G7 -> 63965.93 | I3: =H7 | J3: =I7 | ... M3: =L7 | N3: =+SUM(J3:L3) -> 0
A4: Purchases Food (Less Purchase Return) | B4: 541517.59 | C4: 601593.16 | D4: =493572.48+3266 -> 496838.48 | E4: 477775.32 | F4: 491685 | G4: 388720.72 | N4: =sum(B4:M4) -> 2998130.3
A5: Transferred Out | B5: 1206 | C5: 0 | D5: 242.92 | E5: 0 | F5: 0 | G5: 0 | N5: =+SUM(J5:L5) -> 0
A6: Wastage & Date Expired | B6: 18484.72 | C6: 20828.93 | D6: 18211 | E6: 17324 | F6: 18272 | G6: 16478 | N6: =+SUM(J6:L6) -> 0
A7: Closing Stock | B7: 77139.91 | C7: 64823.23 | D7: 67658 | E7: 77230 | F7: 74378 | G7: 63965.93 | N7: =sum(B7:M7) -> 425195.07
A9: Gross Revenue | B9: =2047749.44*1.05+50302*1.05 -> 2202954 | C9: =2421033.2*1.05+52061.44*1.05 -> 2596749.4 | D9: =1923203.88*1.05+38192*1.05 -> 2059465.7 | E9: =1785484*1.05+31537.47*1.05 -> 1907872.5 | N9: =+SUM(B9:M9) -> 8767041.6
A10: Catering & Fairs | B10: 0 | C10: 0 | D10: 0 | N10: =+SUM(B10:M10) -> 0
A11: Less Tax | B11: =(B9+B10)/1.05*0.05 -> 104902.57 | C11: =(C9+C10)/1.05*0.05 -> 123654.73 | D11: =(D9+D10)/1.05*0.05 -> 98069.794 | E11: =(E9+E10)/1.05*0.05 -> 90851.073 | F11: =(F9+F10)/1.05*0.05 -> 0 | G11: =(G9+G10)/1.05*0.05 -> 0 | H11: =(H9+H10)/1.05*0.05 -> 0 | I11: =(I9+I10)/1.05*0.05 -> 0 | ... M11: =(M9+M10)/1.05*0.05 -> 0 | N11: =+SUM(B11:M11) -> 417478.17
A12: Less Commission | B12: =118273.79*1.18+41914.07*1.18+4216.5*1.18 -> 193997.14 | C12: =124104.37*1.18+42919.89*1.18+4863.66*1.18 -> 202827.75 | D12: =90874.44*1.18+36606.03*1.18+4592.78*1.18 -> 155846.43 | E12: =74524*1.18+32451.36*1.18+2685*1.18 -> 129399.22 | N12: =+SUM(B12:M12) -> 682070.55
A13: Net Revenues from F&B Sales | B13: =B9+B10-B11-B12 -> 1904054.3 | C13: =C9+C10-C11-C12 -> 2270266.9 | D13: =D9+D10-D11-D12 -> 1805549.4 | E13: =E9+E10-E11-E12 -> 1687622.2 | F13: =F9+F10-F11-F12 -> 0 | G13: =G9+G10-G11-G12 -> 0 | H13: =H9+H10-H11-H12 -> 0 | I13: =I9+I10-I11-I12 -> 0 | ... M13: =M9+M10-M11-M12 -> 0 | N13: =sum(B13:M13) -> 7667492.9 | O13: =N13/$N$7 -> 18.032883
A14: F&B Cost | B14: =+B3+B4-B5-B7 -> 532220.68 | C14: =+C3+C4-C5-C7 -> 613909.84 | D14: =+D3+D4-D5-D7 -> 493760.79 | E14: =+E3+E4-E5-E7 -> 468203.32 | F14: =+F3+F4-F5-F7 -> 494537 | G14: =+G3+G4-G5-G7 -> 399132.79 | H14: =+H3+H4-H5-H7 -> 63965.93 | I14: =+I3+I4-I5-I7 -> 0 | ... M14: =+M3+M4-M5-M7 -> 0 | N14: =sum(B14:M14) -> 3065730.4 | O14: =N14/$N$13 -> 0.39983478
A15: Electricity | B15: =74869+23600+2100 -> 100569 | C15: =46703+23600+6300 -> 76603 | D15: =94133+6300+23600+2100 -> 126133 | E15: =117988+23600+3800 -> 145388 | N15: =sum(B15:M15) -> 448693 | O15: =N15/$N$13 -> 0.058518868
A16: Telephone/Internet | B16: 1637 | C16: 1177 | D16: 1414 | E16: 1414 | N16: =sum(B16:M16) -> 5642 | O16: =N16/$N$13 -> 0.00073583374
A17: Gas | B17: 0 | C17: 0 | D17: 0 | E17: 0 | N17: =sum(B17:M17) -> 0 | O17: =N17/$N$13 -> 0
A18: Rent & Revenue Share | B18: =123900+123900 -> 247800 | C18: =123900+123900 -> 247800 | D18: =123900+123900 -> 247800 | E18: =123900+123900 -> 247800 | N18: =sum(B18:M18) -> 991200 | O18: =N18/$N$13 -> 0.12927303
A19: Insurance | B19: =1393 -> 1393 | C19: =36951.85/4/12 -> 769.83021 | D19: =36951.85/4/12 -> 769.83021 | E19: =36951.85/4/12 -> 769.83021 | F19: =36951.85/4/12 -> 769.83021 | G19: =36951.85/4/12 -> 769.83021 | H19: =36951.85/4/12 -> 769.83021 | I19: =36951.85/4/12 -> 769.83021 | J19: =36951.85/4/12 -> 769.83021 | ... M19: =36951.85/4/12 -> 769.83021 | N19: =sum(B19:M19) -> 9861.1323 | O19: =N19/$N$13 -> 0.001286096
A20: Software | B20: 12630 | C20: 12630 | D20: 12630 | E20: 12630 | N20: =sum(B20:M20) -> 50520 | O20: =N20/$N$13 -> 0.0065888552
A21: Staff Salary | B21: =331156+12630 -> 343786 | C21: =12630+339641.59 -> 352271.59 | D21: =12630+351254.05 -> 363884.05 | E21: =363599.07+12630 -> 376229.07 | N21: =sum(B21:M21) -> 1436170.7 | O21: =N21/$N$13 -> 0.18730643
A22: AMC | B22: =4720+2950 -> 7670 | C22: =4720+2950 -> 7670 | D22: =4720+2950 -> 7670 | E22: =2950+4720 -> 7670 | N22: =sum(B22:M22) -> 30680 | O22: =N22/$N$13 -> 0.0040013079
A23: Subscription | B23: =2548.75/3 -> 849.58333 | C23: =2548.75/3 -> 849.58333 | D23: =2548.75/3 -> 849.58333 | E23: =2537/3 -> 845.66667 | F23: =2537/3 -> 845.66667 | G23: =2537/3 -> 845.66667 | N23: =sum(B23:M23) -> 5085.75 | O23: =N23/$N$13 -> 0.00066328722
A24: Repairs & Maintenance | B24: 0 | C24: 0 | D24: 59936 | E24: ='Misc Exp'!F43 -> 10420 | N24: =sum(B24:M24) -> 70356 | O24: =N24/$N$13 -> 0.0091758807
A25: Miscellaneous Expenses | B25: 124414 | C25: 21643.15 | D25: 22126 | E25: ='Misc Exp'!F37 -> 25835.97 | N25: =sum(B25:M25) -> 194019.12 | O25: =N25/$N$13 -> 0.025304115
A26: CAM | B26: 0 | C26: 0 | D26: 0 | E26: 0 | N26: =sum(B26:M26) -> 0 | O26: =N26/$N$13 -> 0
A27: HO+CK Cost | B27: =HO!D33 -> 289487.4 | C27: =HO!H33 -> 329720.58 | D27: =HO!L33 -> 257504.64 | E27: =HO!P33 -> 241951.4 | F27: =HO!D49 -> #DIV/0! | G27: =HO!H49 -> #DIV/0! | H27: =HO!L49 -> #DIV/0! | I27: =HO!P49 -> #DIV/0! | J27: =HO!D64 -> #DIV/0! | K27: =HO!H64 -> #DIV/0! | L27: =HO!L64 -> #DIV/0! | M27: =HO!P64 -> #DIV/0! | N27: =sum(B27:M27) -> #DIV/0! | O27: =N27/$N$13 -> #DIV/0!
A28: Operating Expenses | B28: =+SUM(B14:B27) -> 1662456.7 | C28: =+SUM(C14:C27) -> 1665044.6 | D28: =+SUM(D14:D27) -> 1594477.9 | E28: =+SUM(E14:E27) -> 1539157.3 | F28: =+SUM(F14:F27) -> #DIV/0! | G28: =+SUM(G14:G27) -> #DIV/0! | H28: =+SUM(H14:H27) -> #DIV/0! | I28: =+SUM(I14:I27) -> #DIV/0! | ... M28: =+SUM(M14:M27) -> #DIV/0! | N28: =sum(B28:M28) -> #DIV/0! | O28: =N28/$N$13 -> #DIV/0!
A29: Store Level EBITDA | B29: =B13-B28 -> 241597.63 | C29: =C13-C28 -> 605222.32 | D29: =D13-D28 -> 211071.55 | E29: =E13-E28 -> 148464.99 | F29: =F13-F28 -> #DIV/0! | G29: =G13-G28 -> #DIV/0! | H29: =H13-H28 -> #DIV/0! | I29: =I13-I28 -> #DIV/0! | ... M29: =M13-M28 -> #DIV/0! | N29: =sum(B29:M29) -> #DIV/0! | O29: =N29/$N$13 -> #DIV/0!
A30: Food Cost | B30: =(B14/B13) -> 0.2795197 | C30: =(C14/C13) -> 0.27041307 | D30: =(D14/D13) -> 0.27346844 | E30: =(E14/E13) -> 0.27743372 | F30: =(F14/F13) -> #DIV/0! | G30: =(G14/G13) -> #DIV/0! | H30: =(H14/H13) -> #DIV/0! | I30: =(I14/I13) -> #DIV/0! | ... M30: =(M14/M13) -> #DIV/0!
B32: =B29+B27 -> 531085.03 | C32: =C29+C27 -> 934942.9 | D32: =D29+D27 -> 468576.19 | E32: =E29+E27 -> 390416.39 | F32: =F29+F27 -> #DIV/0! | G32: =G29+G27 -> #DIV/0! | H32: =H29+H27 -> #DIV/0! | I32: =I29+I27 -> #DIV/0! | ... M32: =M29+M27 -> #DIV/0!
B33: =B32/B13 -> 0.27892326 | C33: =C32/C13 -> 0.4118207 | D33: =D32/D13 -> 0.25952 | E33: =E32/E13 -> 0.2313411 | F33: =F32/F13 -> #DIV/0! | G33: =G32/G13 -> #DIV/0! | H33: =H32/H13 -> #DIV/0! | I33: =I32/I13 -> #DIV/0! | ... M33: =M32/M13 -> #DIV/0!

Sheet Gurgaon Sec - 10
A1: Dosa Coffee - Gurgaon Sec 10 | B1: 46113 | C1: 46143 | D1: 46174 | E1: 46204 | F1: 46235 | G1: 46266 | H1: 46296 | I1: 46327 | J1: 46357 | K1: 46388 | L1: 46419 | M1: 46447 | N1: FY 2025-26
A2: Food Cost Calculation
A3: Opening Stock | B3: 44644 | C3: =B7 -> 46808 | D3: =C7 -> 55842.74 | E3: =D7 -> 52323.51 | F3: =E7 -> 42726 | G3: =F7 -> 41972 | H3: =G7 -> 25486 | J3: 0 | K3: =J7 | L3: =K7 | M3: =L7 | N3: =+SUM(J3:L3) -> 0
A4: Purchases Food (Less Purchase Return) | B4: 197730 | C4: 242122.79 | D4: =204885+844 -> 205729 | E4: 177108 | F4: 188424 | G4: 167098.76 | N4: =sum(B4:M4) -> 1178212.6
A5: Transferred Out | B5: 0 | C5: 0 | D5: 0 | E5: 0 | F5: 0 | G5: 0 | N5: =+SUM(J5:L5) -> 0
A6: Wastage & Date Expired | B6: 4222 | C6: 5191.43 | D6: 8880.89 | E6: 5296 | F6: 3781 | G6: 4984.01 | N6: =+SUM(J6:L6) -> 0
A7: Closing Stock | B7: 46808 | C7: 55842.74 | D7: 52323.51 | E7: 42726 | F7: 41972 | G7: 25486 | N7: =sum(B7:M7) -> 265158.25
A9: Gross Revenue | B9: =722885*1.05+22878.93*1.05 -> 783052.13 | C9: =772310.07*1.05+29185.19*1.05 -> 841570.02 | D9: =702061.02*1.05+26619.61*1.05 -> 765114.66 | E9: =591826.23*1.05+23248.27*1.05 -> 645828.22 | N9: =+SUM(B9:M9) -> 3035565
A10: Catering & Fairs | B10: 0 | C10: 0 | D10: 0 | N10: =+SUM(B10:M10) -> 0
A11: Less Tax | B11: =(B9+B10)/1.05*0.05 -> 37288.196 | C11: =(C9+C10)/1.05*0.05 -> 40074.763 | D11: =(D9+D10)/1.05*0.05 -> 36434.031 | E11: =(E9+E10)/1.05*0.05 -> 30753.725 | J11: =(J9+J10)/1.05*0.05 -> 0 | K11: =(K9+K10)/1.05*0.05 -> 0 | L11: =(L9+L10)/1.05*0.05 -> 0 | M11: =(M9+M10)/1.05*0.05 -> 0 | N11: =+SUM(B11:M11) -> 144550.72
A12: Less Commission | B12: =52474.48*1.18+17261*1.18+843.22*1.18 -> 83282.866 | C12: =67596.35*1.18+16364.46*1.18+744.87*1.18 -> 99952.702 | D12: =61301.45*1.18+29695.43*1.18+490.57*1.18 -> 107955.19 | E12: =54767*1.18+12756.64*1.18+297*1.18 -> 80028.355 | N12: =+SUM(B12:M12) -> 371219.11
A13: Net Revenues from F&B Sales | B13: =B9+B10-B11-B12 -> 662481.06 | C13: =C9+C10-C11-C12 -> 701542.56 | D13: =D9+D10-D11-D12 -> 620725.44 | E13: =E9+E10-E11-E12 -> 535046.14 | F13: =F9+F10-F11-F12 -> 0 | G13: =G9+G10-G11-G12 -> 0 | H13: =H9+H10-H11-H12 -> 0 | I13: =I9+I10-I11-I12 -> 0 | ... M13: =M9+M10-M11-M12 -> 0 | N13: =sum(B13:M13) -> 2519795.2 | O13: =N13/$N$7 -> 9.5029863
A14: F&B Cost | B14: =+B3+B4-B5-B7 -> 195566 | C14: =+C3+C4-C5-C7 -> 233088.05 | D14: =+D3+D4-D5-D7 -> 209248.23 | E14: =+E3+E4-E5-E7 -> 186705.51 | J14: =+J3+J4-J5-J7 -> 0 | K14: =+K3+K4-K5-K7 -> 0 | L14: =+L3+L4-L5-L7 -> 0 | M14: =+M3+M4-M5-M7 -> 0 | N14: =sum(B14:M14) -> 824607.79 | O14: =N14/$N$13 -> 0.32725191
A15: Electricity | B15: =50000+23600+5200 -> 78800 | C15: =117037-50000+23600+3200 -> 93837 | D15: =23600+5300+173391/2 -> 115595.5 | E15: =173391/2+23600+17800 -> 128095.5 | N15: =sum(B15:M15) -> 416328 | O15: =N15/$N$13 -> 0.16522295
A16: Telephone/Internet | B16: 469 | C16: 469 | D16: 469 | E16: 349 | N16: =sum(B16:M16) -> 1756 | O16: =N16/$N$13 -> 0.00069688203
A17: Gas | B17: 0 | C17: 0 | D17: 0 | E17: 0 | N17: =sum(B17:M17) -> 0 | O17: =N17/$N$13 -> 0
A18: Rent & Revenue Share | B18: =70000+70000 -> 140000 | C18: =70000+70000 -> 140000 | D18: =70000+70000 -> 140000 | E18: =70000+70000 -> 140000 | N18: =sum(B18:M18) -> 560000 | O18: =N18/$N$13 -> 0.22224028
A19: Insurance | B19: 397 | C19: =36951.85/4/12 -> 769.83021 | D19: =36951.85/4/12 -> 769.83021 | E19: =36951.85/4/12 -> 769.83021 | F19: =36951.85/4/12 -> 769.83021 | G19: =36951.85/4/12 -> 769.83021 | H19: =36951.85/4/12 -> 769.83021 | I19: =36951.85/4/12 -> 769.83021 | J19: =36951.85/4/12 -> 769.83021 | ... M19: =36951.85/4/12 -> 769.83021 | N19: =sum(B19:M19) -> 8865.1323 | O19: =N19/$N$13 -> 0.0035181956
A20: Software | B20: 7857 | C20: 7857 | D20: 7857 | E20: 7857 | N20: =sum(B20:M20) -> 31428 | O20: =N20/$N$13 -> 0.012472442
A21: Staff Salary | B21: =209143+11000 -> 220143 | C21: =11000+214692.6 -> 225692.6 | D21: =11000+238904.25 -> 249904.25 | E21: =215191.16 -> 215191.16 | N21: =sum(B21:M21) -> 910931.01 | O21: =N21/$N$13 -> 0.36150994
A22: AMC | B22: =4720 -> 4720 | C22: =4720 -> 4720 | D22: =4720 -> 4720 | E22: =4720 -> 4720 | N22: =sum(B22:M22) -> 18880 | O22: =N22/$N$13 -> 0.0074926724
A23: Subscription | B23: =2548.75/3 -> 849.58333 | C23: =2548.75/3 -> 849.58333 | D23: =2548.75/3 -> 849.58333 | E23: =2537/3 -> 845.66667 | F23: =2537/3 -> 845.66667 | G23: =2537/3 -> 845.66667 | N23: =sum(B23:M23) -> 5085.75 | O23: =N23/$N$13 -> 0.0020183188
A24: Repairs & Maintenance | B24: 0 | C24: 0 | D24: 120 | E24: ='Misc Exp'!G43 -> 4500 | N24: =sum(B24:M24) -> 4620 | O24: =N24/$N$13 -> 0.0018334823
A25: Miscellaneous Expenses | B25: 2110 | C25: 7024.57 | D25: 6716 | E25: ='Misc Exp'!G37 -> 5531.94 | N25: =sum(B25:M25) -> 21382.51 | O25: =N25/$N$13 -> 0.0084858126
A26: CAM | B26: 0 | C26: 0 | D26: 0 | N26: =sum(B26:M26) -> 0 | O26: =N26/$N$13 -> 0
A27: HO+CK Cost | B27: =HO!D34 -> 100721.88 | C27: =HO!H34 -> 101888.03 | D27: =HO!L34 -> 88526.891 | E27: =HO!P34 -> 76708.614 | N27: =sum(B27:M27) -> 367845.41 | O27: =N27/$N$13 -> 0.14598226
A28: Operating Expenses | B28: =+SUM(B14:B27) -> 751633.46 | C28: =+SUM(C14:C27) -> 816195.66 | D28: =+SUM(D14:D27) -> 824776.28 | E28: =+SUM(E14:E27) -> 771274.22 | F28: =+SUM(F14:F27) -> 1615.4969 | G28: =+SUM(G14:G27) -> 1615.4969 | H28: =+SUM(H14:H27) -> 769.83021 | I28: =+SUM(I14:I27) -> 769.83021 | ... M28: =+SUM(M14:M27) -> 769.83021 | N28: =sum(B28:M28) -> 3171729.6 | O28: =N28/$N$13 -> 1.2587252
A29: Store Level EBITDA | B29: =B13-B28 -> -89152.396 | C29: =C13-C28 -> -114653.11 | D29: =D13-D28 -> -204050.85 | E29: =E13-E28 -> -236228.08 | F29: =F13-F28 -> -1615.4969 | G29: =G13-G28 -> -1615.4969 | H29: =H13-H28 -> -769.83021 | I29: =I13-I28 -> -769.83021 | ... M29: =M13-M28 -> -769.83021 | N29: =sum(B29:M29) -> -651934.4 | O29: =N29/$N$13 -> -0.25872515
A30: Food Cost | B30: =(B14/B13) -> 0.2952024 | C30: =(C14/C13) -> 0.33225076 | D30: =(D14/D13) -> 0.33710271 | E30: =(E14/E13) -> 0.34895216 | F30: =(F14/F13) -> #DIV/0! | G30: =(G14/G13) -> #DIV/0! | H30: =(H14/H13) -> #DIV/0! | I30: =(I14/I13) -> #DIV/0! | ... M30: =(M14/M13) -> #DIV/0!
B32: =B29+B27 -> 11569.481 | C32: =C29+C27 -> -12765.076 | D32: =D29+D27 -> -115523.95 | E32: =E29+E27 -> -159519.46 | F32: =F29+F27 -> -1615.4969 | G32: =G29+G27 -> -1615.4969 | H32: =H29+H27 -> -769.83021 | I32: =I29+I27 -> -769.83021 | ... M32: =M29+M27 -> -769.83021
B33: =B32/B13 -> 0.017463866 | C33: =C32/C13 -> -0.018195726 | D33: =D32/D13 -> -0.1861112 | E33: =E32/E13 -> -0.2981415 | F33: =F32/F13 -> #DIV/0! | G33: =G32/G13 -> #DIV/0! | H33: =H32/H13 -> #DIV/0! | I33: =I32/I13 -> #DIV/0! | ... M33: =M32/M13 -> #DIV/0!

Sheet Gurgaon Sector 31
A1: Dosa Coffee - Gurgaon Sec 31 | B1: 46113 | C1: 46143 | D1: 46174 | E1: 46204 | F1: 46235 | G1: 46266 | H1: 46296 | I1: 46327 | J1: 46357 | K1: 46388 | L1: 46419 | M1: 46447 | N1: FY 2025-26
A2: Food Cost Calculation
A3: Opening Stock | B3: 0 | C3: 503 | D3: 26072 | E3: =D7 -> 22107 | F3: =E7 -> 19249.53 | G3: =F7 -> 25610 | H3: =G7 -> 19393.23 | M3: 0 | N3: =+SUM(J3:L3) -> 0
A4: Purchases Food (Less Purchase Return) | B4: 0 | C4: =14235.82 -> 14235.82 | D4: 222391 | E4: 248102 | F4: 275497 | G4: 243241 | N4: =sum(B4:M4) -> 1003466.8
A5: Transferred Out | B5: 0 | C5: 0 | D5: 0 | E5: 0 | F5: 0 | G5: 0 | M5: 0 | N5: =+SUM(J5:L5) -> 0
A6: Wastage & Date Expired | B6: 0 | C6: 30564 | D6: 14608 | E6: 16215 | F6: 17193.82 | G6: 13886 | N6: =+SUM(J6:L6) -> 0
A7: Closing Stock | B7: 0 | D7: 22107 | E7: 19249.53 | F7: 25610 | G7: 19393.23 | N7: =sum(B7:M7) -> 86359.76
A9: Gross Revenue | B9: 0 | C9: =56963.44*1.05+92*1.05 -> 59908.212 | D9: =723645.66*1.05+15777.09*1.05 -> 776393.89 | E9: =1046684*1.05+27510.71*1.05 -> 1127904.4 | N9: =+SUM(B9:M9) -> 1964206.5
A10: Catering & Fairs | B10: 0 | C10: 0 | D10: 0 | E10: 0 | M10: 0 | N10: =+SUM(B10:M10) -> 0
A11: Less Tax | B11: =(B9+B10)/1.05*0.05 -> 0 | C11: =(C9+C10)/1.05*0.05 -> 2852.772 | D11: =(D9+D10)/1.05*0.05 -> 36971.137 | E11: =(E9+E10)/1.05*0.05 -> 53709.736 | M11: =(M9+M10)/1.05*0.05 -> 0 | N11: =+SUM(B11:M11) -> 93533.645
A12: Less Commission | B12: 0 | C12: =212.52*1.18+434.91*1.18 -> 763.9674 | D12: =35660.22*1.18 -> 42079.06 | E12: =61951.59*1.18+10569.53*1.18 -> 85574.922 | M12: 0 | N12: =+SUM(B12:M12) -> 128417.95
A13: Net Revenues from F&B Sales | B13: =B9+B10-B11-B12 -> 0 | C13: =C9+C10-C11-C12 -> 56291.473 | D13: =D9+D10-D11-D12 -> 697343.69 | E13: =E9+E10-E11-E12 -> 988619.79 | F13: =F9+F10-F11-F12 -> 0 | G13: =G9+G10-G11-G12 -> 0 | H13: =H9+H10-H11-H12 -> 0 | I13: =I9+I10-I11-I12 -> 0 | ... M13: =M9+M10-M11-M12 -> 0 | N13: =sum(B13:M13) -> 1742255 | O13: =N13/$N$7 -> 20.174384
A14: F&B Cost | B14: =+B3+B4-B5-B7 -> 0 | C14: =+C3+C4-C5-C7 -> 14738.82 | D14: =+D3+D4-D5-D7 -> 226356 | E14: =+E3+E4-E5-E7 -> 250959.47 | M14: =+M3+M4-M5-M7 -> 0 | N14: =sum(B14:M14) -> 492054.29 | O14: =N14/$N$13 -> 0.28242382
A15: Electricity | B15: =58760/75*0 -> 0 | C15: =58760/75*1 -> 783.46667 | D15: =18800+3000+9000+11891 -> 42691 | E15: =57756+18800+4534 -> 81090 | N15: =sum(B15:M15) -> 124564.47 | O15: =N15/$N$13 -> 0.071496119
A16: Telephone/Internet | B16: 0 | C16: 0 | D16: 0 | E16: 224 | N16: =sum(B16:M16) -> 224 | O16: =N16/$N$13 -> 0.00012856901
A17: Gas | B17: 0 | C17: =14438 -> 14438 | D17: 28033 | E17: 43145 | N17: =sum(B17:M17) -> 85616 | O17: =N17/$N$13 -> 0.049140914
A18: Rent & Revenue Share | B18: 0 | C18: =295000/31*1 -> 9516.129 | D18: 295000 | E18: =295000+14500 -> 309500 | N18: =sum(B18:M18) -> 614016.13 | O18: =N18/$N$13 -> 0.35242611
A19: Insurance | B19: 0 | C19: 0 | D19: 0 | E19: 0 | N19: =sum(B19:M19) -> 0 | O19: =N19/$N$13 -> 0
A20: Software | C20: 7857 | D20: 7857 | E20: 7857 | N20: =sum(B20:M20) -> 23571 | O20: =N20/$N$13 -> 0.013529019
A21: Staff Salary | B21: 0 | C21: =207773.63/31 -> 6702.3752 | D21: =13000+256462.18 -> 269462.18 | E21: =288169.74+13000 -> 301169.74 | N21: =sum(B21:M21) -> 577334.3 | O21: =N21/$N$13 -> 0.33137188
A22: AMC | B22: 0 | C22: 0 | D22: =5145+2360 -> 7505 | E22: =5145+2360 -> 7505 | N22: =sum(B22:M22) -> 15010 | O22: =N22/$N$13 -> 0.0086152718
A23: Subscription | B23: =3682/12 -> 306.83333 | C23: =3682/12 -> 306.83333 | D23: =3682/12 -> 306.83333 | E23: =3682/12+845.67 -> 1152.5033 | F23: =3682/12+845.67 -> 1152.5033 | G23: =3682/12+845.67 -> 1152.5033 | H23: =3682/12 -> 306.83333 | I23: =3682/12 -> 306.83333 | J23: =3682/12 -> 306.83333 | K23: =3682/12 -> 306.83333 | L23: =3682/12 -> 306.83333 | M23: =3682/12 -> 306.83333 | N23: =sum(B23:M23) -> 6219.01 | O23: =N23/$N$13 -> 0.0035695178
A24: Repairs & Maintenance | B24: 0 | C24: 5989 | D24: 0 | E24: ='Misc Exp'!H43 -> 39364 | N24: =sum(B24:M24) -> 45353 | O24: =N24/$N$13 -> 0.026031207
A25: Miscellaneous Expenses | B25: 0 | C25: =75992/12+278.49 -> 6611.1567 | D25: =75992/12+3087 -> 9419.6667 | E25: =75992/12+'Misc Exp'!H37 -> 12147.557 | F25: =75992/12 -> 6332.6667 | G25: =75992/12 -> 6332.6667 | H25: =75992/12 -> 6332.6667 | I25: =75992/12 -> 6332.6667 | J25: =75992/12 -> 6332.6667 | K25: =75992/12 -> 6332.6667 | L25: =75992/12 -> 6332.6667 | M25: =75992/12 -> 6332.6667 | N25: =sum(B25:M25) -> 78839.713 | O25: =N25/$N$13 -> 0.045251536
A26: CAM | B26: 0 | C26: 0 | D26: 0 | E26: 0 | N26: =sum(B26:M26) -> 0 | O26: =N26/$N$13 -> 0
A27: HO+CK Cost | B27: 0 | C27: =HO!H35 -> 8175.4516 | D27: =HO!L35 -> 99454.067 | E27: =HO!P35 -> 141736.66 | M27: =HO!P72 -> #DIV/0! | N27: =sum(B27:M27) -> #DIV/0! | O27: =N27/$N$13 -> #DIV/0!
A28: Operating Expenses | B28: =+SUM(B14:B27) -> 306.83333 | C28: =+SUM(C14:C27) -> 75118.232 | D28: =+SUM(D14:D27) -> 986084.75 | E28: =+SUM(E14:E27) -> 1195850.9 | F28: =+SUM(F14:F27) -> 7485.17 | G28: =+SUM(G14:G27) -> 7485.17 | H28: =+SUM(H14:H27) -> 6639.5 | I28: =+SUM(I14:I27) -> 6639.5 | ... M28: =+SUM(M14:M27) -> #DIV/0! | N28: =sum(B28:M28) -> #DIV/0! | O28: =N28/$N$13 -> #DIV/0!
A29: Store Level EBITDA | B29: =B13-B28 -> -306.83333 | C29: =C13-C28 -> -18826.76 | D29: =D13-D28 -> -288741.06 | E29: =E13-E28 -> -207231.14 | F29: =F13-F28 -> -7485.17 | G29: =G13-G28 -> -7485.17 | H29: =H13-H28 -> -6639.5 | I29: =I13-I28 -> -6639.5 | ... M29: =M13-M28 -> #DIV/0! | N29: =sum(B29:M29) -> #DIV/0! | O29: =N29/$N$13 -> #DIV/0!
A30: Food Cost | C30: =(C14/C13) -> 0.26183042 | D30: =(D14/D13) -> 0.32459747 | E30: =(E14/E13) -> 0.25384832 | F30: =(F14/F13) -> #DIV/0! | G30: =(G14/G13) -> #DIV/0! | H30: =(H14/H13) -> #DIV/0! | I30: =(I14/I13) -> #DIV/0! | J30: =(J14/J13) -> #DIV/0! | ... M30: =(M14/M13) -> #DIV/0!
B32: =B29+B27 -> -306.83333 | C32: =C29+C27 -> -10651.308 | D32: =D29+D27 -> -189286.99 | E32: =E29+E27 -> -65494.482 | F32: =F29+F27 -> -7485.17 | G32: =G29+G27 -> -7485.17 | H32: =H29+H27 -> -6639.5 | I32: =I29+I27 -> -6639.5 | ... L32: =L29+L27 -> -6639.5
B33: =B32/B13 -> #DIV/0! | C33: =C32/C13 -> -0.18921708 | D33: =D32/D13 -> -0.27144003 | E33: =E32/E13 -> -0.066248402 | F33: =F32/F13 -> #DIV/0! | G33: =G32/G13 -> #DIV/0! | H33: =H32/H13 -> #DIV/0! | I33: =I32/I13 -> #DIV/0! | ... L33: =L32/L13 -> #DIV/0!

Sheet Paschim Vihar
A1: Dosa Coffee - Paschim Vihar | B1: 46113 | C1: 46143 | D1: 46174 | E1: 46204 | F1: 46235 | G1: 46266 | H1: 46296 | I1: 46327 | J1: 46357 | K1: 46388 | L1: 46419 | M1: 46447 | N1: FY 2025-26
A2: Food Cost Calculation
A3: Opening Stock | B3: 78348 | C3: =B7 -> 100209.82 | D3: =C7 -> 143033.64 | E3: =D7 -> 55298 | F3: =E7 -> 57088.88 | G3: =F7 -> 57608 | H3: =G7 | I3: =H7 | J3: =I7 | ... M3: =L7 | N3: =+SUM(J3:L3) -> 0
A4: Purchases Food (Less Purchase Return) | B4: 361478.61 | C4: 363635.7 | D4: =294665 -> 294665 | E4: 285714 | F4: 325790 | N4: =sum(B4:M4) -> 1631283.3
A5: Transferred Out | B5: 0 | C5: 0 | D5: 58615 | E5: 0 | F5: 0 | N5: =+SUM(J5:L5) -> 0
A6: Wastage & Date Expired | B6: 31458.79 | C6: 36286.69 | D6: 35459 | E6: 26797.58 | F6: 23559 | N6: =+SUM(J6:L6) -> 0
A7: Closing Stock | B7: 100209.82 | C7: 143033.64 | D7: 55298 | E7: 57088.88 | F7: 57608 | N7: =sum(B7:M7) -> 413238.34
A9: Gross Revenue | B9: =1303527.71*1.05+35408.57*1.05 -> 1405883.1 | C9: =1336868.78*1.05+35334.73*1.05 -> 1440813.7 | D9: =1165780.58*1.05+20*1.05+28812.49*1.05 -> 1254343.7 | E9: =1101048.17*1.05+22786.49*1.05 -> 1180026.4 | N9: =+SUM(B9:M9) -> 5281066.9
A10: Catering & Fairs | B10: 0 | C10: 0 | D10: 0 | N10: =+SUM(B10:M10) -> 0
A11: Less Tax | B11: =(B9+B10)/1.05*0.05 -> 66946.814 | C11: =(C9+C10)/1.05*0.05 -> 68610.175 | D11: =(D9+D10)/1.05*0.05 -> 59730.654 | E11: =(E9+E10)/1.05*0.05 -> 56191.733 | F11: =(F9+F10)/1.05*0.05 -> 0 | G11: =(G9+G10)/1.05*0.05 -> 0 | H11: =(H9+H10)/1.05*0.05 -> 0 | I11: =(I9+I10)/1.05*0.05 -> 0 | ... M11: =(M9+M10)/1.05*0.05 -> 0 | N11: =+SUM(B11:M11) -> 251479.38
A12: Less Commission | B12: =83341.97*1.18+30706.72*1.18+2848.64*1.18 -> 137938.85 | C12: =82786*1.18+37443.78*1.18+2224.36*1.18+11.91 -> 144507.8 | D12: =67395.08*1.18+(6914.64/0.18)*1.18+2109.48*1.18+18.71 -> 127363.4 | E12: =53963*1.18+34229.83*1.18+1318*1.18 -> 105622.78 | N12: =+SUM(B12:M12) -> 515432.82
A13: Net Revenues from F&B Sales | B13: =B9+B10-B11-B12 -> 1200997.4 | C13: =C9+C10-C11-C12 -> 1227695.7 | D13: =D9+D10-D11-D12 -> 1067249.7 | E13: =E9+E10-E11-E12 -> 1018211.9 | F13: =F9+F10-F11-F12 -> 0 | G13: =G9+G10-G11-G12 -> 0 | H13: =H9+H10-H11-H12 -> 0 | I13: =I9+I10-I11-I12 -> 0 | ... M13: =M9+M10-M11-M12 -> 0 | N13: =sum(B13:M13) -> 4514154.7 | O13: =N13/$N$7 -> 10.923853
A14: F&B Cost | B14: =+B3+B4-B5-B7 -> 339616.79 | C14: =+C3+C4-C5-C7 -> 320811.88 | D14: =+D3+D4-D5-D7 -> 323785.64 | E14: =+E3+E4-E5-E7 -> 283923.12 | N14: =sum(B14:M14) -> 1268137.4 | O14: =N14/$N$7 -> 3.0687797
A15: Electricity | B15: 72280 | C15: =88500 -> 88500 | D15: =80270 -> 80270 | E15: =85000 -> 85000 | N15: =sum(B15:M15) -> 326050 | O15: =N15/$N$7 -> 0.78901198
A16: Telephone/Internet | B16: =1414+199 -> 1613 | C16: =1414+199 -> 1613 | D16: =1414+199 -> 1613 | E16: =1414+202 -> 1616 | N16: =sum(B16:M16) -> 6455 | O16: =N16/$N$7 -> 0.015620525
A17: Gas | B17: =53111.34 -> 53111.34 | C17: 69665 | D17: 48582 | E17: 83801 | N17: =sum(B17:M17) -> 255159.34 | O17: =N17/$N$7 -> 0.61746289 | T17: =6150*5 -> 30750
A18: Rent & Revenue Share | B18: =6490+102660+6490+102660 -> 218300 | C18: =6490+102660+6490+102660 -> 218300 | D18: =7463+118059+7463+118059 -> 251044 | E18: =7463+118059+7463+118059 -> 251044 | N18: =sum(B18:M18) -> 938688 | O18: =N18/$N$7 -> 2.2715414
A19: Insurance Premium | B19: 1133 | C19: =136716.74/8/12 -> 1424.1327 | D19: =136716.74/8/12 -> 1424.1327 | E19: =136716.74/8/12 -> 1424.1327 | F19: =136716.74/8/12 -> 1424.1327 | G19: =136716.74/8/12 -> 1424.1327 | H19: =136716.74/8/12 -> 1424.1327 | I19: =136716.74/8/12 -> 1424.1327 | J19: =136716.74/8/12 -> 1424.1327 | ... M19: =136716.74/8/12 -> 1424.1327 | N19: =sum(B19:M19) -> 16798.46
A20: Software | B20: 5767 | C20: 5767 | D20: 5767 | E20: 5767 | N20: =sum(B20:M20) -> 23068 | O20: =N20/$N$7 -> 0.055822507
A21: Staff Salary | B21: =325895+7752 -> 333647 | C21: =334452.43 -> 334452.43 | D21: =325480.51 -> 325480.51 | E21: =297740.05 -> 297740.05 | N21: =sum(B21:M21) -> 1291320 | O21: =N21/$N$7 -> 3.1248794
A22: AMC | B22: =4720+2360 -> 7080 | C22: =4720+2360 -> 7080 | D22: =4720+2360 -> 7080 | E22: =4720+2360 -> 7080 | N22: =sum(B22:M22) -> 28320 | O22: =N22/$N$7 -> 0.068531879
A23: Subscription | B23: =2548.84/3+6425/12+9813/12 -> 2202.78 | C23: =2548.84/3+6425/12+9813/12 -> 2202.78 | D23: =2548.84/3+6425/12+9813/12 -> 2202.78 | E23: =6425/12+9813/12+2840/3 -> 2299.8333 | F23: =6425/12+9813/12+2840/3 -> 2299.8333 | G23: =6425/12+9813/12+2840/3 -> 2299.8333 | H23: =6425/12+9813/12 -> 1353.1667 | I23: =6425/12+9813/12 -> 1353.1667 | J23: =6425/12+9813/12 -> 1353.1667 | K23: =6425/12+9813/12 -> 1353.1667 | L23: =6425/12+9813/12 -> 1353.1667 | M23: =6425/12+9813/12 -> 1353.1667 | N23: =sum(B23:M23) -> 21626.84 | O23: =N23/$N$7 -> 0.052335028
A24: Repairs & Maintenance | B24: 0 | C24: 404 | D24: 6800 | E24: ='Misc Exp'!I43 -> 11207 | N24: =sum(B24:M24) -> 18411 | O24: =N24/$N$7 -> 0.044552981
A25: Miscellaneous Expenses | B25: 15328 | C25: 8889.31 | D25: 26011 | E25: ='Misc Exp'!I37 -> 15464.64 | N25: =sum(B25:M25) -> 65692.95 | O25: =N25/$N$7 -> 0.15897109
A26: CAM | B26: 0 | C26: 0 | D26: 0 | E26: 0 | N26: =sum(B26:M26) -> 0 | O26: =N26/$N$7 -> 0
A27: HO+CK Cost | B27: =HO!D36 -> 182596.49 | C27: =HO!H36 -> 178303.51 | D27: =HO!L36 -> 152209.48 | E27: =HO!P36 -> 145979.23 | F27: =HO!D50 -> #DIV/0! | G27: =HO!H50 -> #DIV/0! | H27: =HO!L50 -> #DIV/0! | I27: =HO!P50 -> #DIV/0! | J27: =HO!D66 -> #DIV/0! | K27: =HO!H66 -> #DIV/0! | L27: =HO!L66 -> #DIV/0! | M27: =HO!P66 -> #DIV/0! | N27: =sum(B27:M27) -> #DIV/0! | O27: =N27/$N$7 -> #DIV/0!
A28: Operating Expenses | B28: =+SUM(B14:B27) -> 1232675.4 | C28: =+SUM(C14:C27) -> 1237413 | D28: =+SUM(D14:D27) -> 1232269.5 | E28: =+SUM(E14:E27) -> 1192346 | F28: =+SUM(F14:F27) -> #DIV/0! | G28: =+SUM(G14:G27) -> #DIV/0! | H28: =+SUM(H14:H27) -> #DIV/0! | I28: =+SUM(I14:I27) -> #DIV/0! | ... M28: =+SUM(M14:M27) -> #DIV/0! | N28: =sum(B28:M28) -> #DIV/0! | O28: =N28/$N$7 -> #DIV/0!
A29: Store Level EBITDA | B29: =B13-B28 -> -31677.967 | C29: =C13-C28 -> -9717.3231 | D29: =D13-D28 -> -165019.87 | E29: =E13-E28 -> -174134.12 | F29: =F13-F28 -> #DIV/0! | G29: =G13-G28 -> #DIV/0! | H29: =H13-H28 -> #DIV/0! | I29: =I13-I28 -> #DIV/0! | ... M29: =M13-M28 -> #DIV/0! | N29: =sum(B29:M29) -> #DIV/0! | O29: =N29/$N$7 -> #DIV/0!
A30: Food Cost | B30: =(B14/B13) -> 0.28277895 | C30: =(C14/C13) -> 0.26131221 | D30: =(D14/D13) -> 0.30338322 | E30: =(E14/E13) -> 0.27884483 | F30: =(F14/F13) -> #DIV/0! | G30: =(G14/G13) -> #DIV/0! | H30: =(H14/H13) -> #DIV/0! | I30: =(I14/I13) -> #DIV/0! | ... M30: =(M14/M13) -> #DIV/0!
B32: =B29+B27 -> 150918.52 | C32: =C29+C27 -> 168586.18
B33: =B32/B13 -> 0.12566099 | C33: =C32/C13 -> 0.13731919

Sheet Kalkaji
A1: Dosa Coffee - Kalkaji | B1: 46113 | C1: 46143 | D1: 46174 | E1: 46204 | F1: 46235 | G1: 46266 | H1: 46296 | I1: 46327 | J1: 46357 | K1: 46388 | L1: 46419 | M1: 46447 | N1: FY 2025-26
A2: Food Cost Calculation
A3: Opening Stock | B3: 64172 | C3: =B7 -> 59523 | D3: =C7 -> 62632.61 | E3: =D7 -> 67150 | F3: =E7 -> 62298 | G3: =F7 -> 63799 | H3: =G7 | I3: =H7 | J3: =I7 | ... M3: =L7 | N3: =+SUM(J3:L3) -> 0
A4: Purchases Food (Less Purchase Return) | B4: 344563 | C4: 444302 | D4: 412057 | E4: 403045.62 | F4: =452606 -> 452606 | N4: =sum(B4:M4) -> 2056573.6
A5: Transferred Out | B5: 0 | C5: 0 | D5: 0 | E5: 0 | F5: 0 | N5: =+SUM(J5:L5) -> 0
A6: Wastage & Date Expired | B6: 22818 | C6: 27175 | D6: 25578.62 | E6: 25206 | F6: 23593 | N6: =+SUM(J6:L6) -> 0
A7: Closing Stock | B7: 59523 | C7: 62632.61 | D7: 67150 | E7: 62298 | F7: 63799 | N7: =sum(B7:M7) -> 315402.61
A9: Gross Revenue | B9: =1473883.68*1.05+58146.64*1.05 -> 1608631.8 | C9: =1683163.36*1.05+66713.8*1.05 -> 1837371 | D9: =1509923.57*1.05+60943.3*1.05 -> 1649410.2 | E9: =1527493.87*1.05+63844.53*1.05 -> 1670905.3 | N9: =+SUM(B9:M9) -> 6766318.4
A10: Catering & Fairs | B10: 0 | C10: 0 | D10: 0 | N10: =+SUM(B10:M10) -> 0
A11: Less Tax | B11: =(B9+B10)/1.05*0.05 -> 76601.516 | C11: =(C9+C10)/1.05*0.05 -> 87493.858 | D11: =(D9+D10)/1.05*0.05 -> 78543.344 | E11: =(E9+E10)/1.05*0.05 -> 79566.92 | F11: =(F9+F10)/1.05*0.05 -> 0 | G11: =(G9+G10)/1.05*0.05 -> 0 | H11: =(H9+H10)/1.05*0.05 -> 0 | I11: =(I9+I10)/1.05*0.05 -> 0 | ... M11: =(M9+M10)/1.05*0.05 -> 0 | N11: =+SUM(B11:M11) -> 322205.64
A12: Less Commission | B12: =134910.56*1.18+47701.3*1.18+1466.79*1.18 -> 217212.81 | C12: =155264.77*1.18+60301.98*1.18+959.71*1.18 -> 255501.22 | D12: =141561.24*1.18+(11477.13/0.18)*1.18+1019.46*1.18+100.79 -> 243584.98 | E12: =148282.42*1.18+67904.17*1.18+505.19*1.18 -> 255696.3 | N12: =+SUM(B12:M12) -> 971995.31
A13: Net Revenues from F&B Sales | B13: =B9+B10-B11-B12 -> 1314817.5 | C13: =C9+C10-C11-C12 -> 1494375.9 | D13: =D9+D10-D11-D12 -> 1327281.9 | E13: =E9+E10-E11-E12 -> 1335642.1 | F13: =F9+F10-F11-F12 -> 0 | G13: =G9+G10-G11-G12 -> 0 | H13: =H9+H10-H11-H12 -> 0 | I13: =I9+I10-I11-I12 -> 0 | ... M13: =M9+M10-M11-M12 -> 0 | N13: =sum(B13:M13) -> 5472117.4 | O13: =N13/$N$7 -> 17.349626
A14: F&B Cost | B14: =+B3+B4-B5-B7 -> 349212 | C14: =+C3+C4-C5-C7 -> 441192.39 | D14: =+D3+D4-D5-D7 -> 407539.61 | E14: =+E3+E4-E5-E7 -> 407897.62 | F14: =+F3+F4-F5-F7 -> 451105 | G14: =+G3+G4-G5-G7 -> 63799 | H14: =+H3+H4-H5-H7 -> 0 | I14: =+I3+I4-I5-I7 -> 0 | ... M14: =+M3+M4-M5-M7 -> 0 | N14: =sum(B14:M14) -> 2120745.6 | O14: =N14/$N$7 -> 6.7239317
A15: Electricity | B15: =52670 -> 52670 | C15: =69800 -> 69800 | D15: 69190 | E15: =84730+3040 -> 87770 | N15: =sum(B15:M15) -> 279430 | O15: =N15/$N$7 -> 0.88594701
A16: Telephone/Internet | B16: =1296 -> 1296 | C16: =1296 -> 1296 | D16: =1296 -> 1296 | E16: =1296 -> 1296 | N16: =sum(B16:M16) -> 5184 | O16: =N16/$N$7 -> 0.016436135
A17: Gas | B17: 30000 | C17: 30000 | D17: 30000 | E17: 64460 | N17: =sum(B17:M17) -> 154460 | O17: =N17/$N$7 -> 0.48972328
A18: Rent & Revenue Share | B18: =162840 -> 162840 | C18: =162840 -> 162840 | D18: =162840 -> 162840 | E18: =162840 -> 162840 | N18: =sum(B18:M18) -> 651360 | O18: =N18/$N$7 -> 2.06517
A19: Insurance | B19: 866 | C19: =136716.74/8/12 -> 1424.1327 | D19: =136716.74/8/12 -> 1424.1327 | E19: =136716.74/8/12 -> 1424.1327 | F19: =136716.74/8/12 -> 1424.1327 | G19: =136716.74/8/12 -> 1424.1327 | H19: =136716.74/8/12 -> 1424.1327 | I19: =136716.74/8/12 -> 1424.1327 | J19: =136716.74/8/12 -> 1424.1327 | ... M19: =136716.74/8/12 -> 1424.1327 | N19: =sum(B19:M19) -> 16531.46
A20: Software | B20: 5767 | C20: 5767 | D20: 5767 | E20: 5767 | N20: =sum(B20:M20) -> 23068 | O20: =N20/$N$7 -> 0.073138266
A21: Staff Salary | B21: =265339 -> 265339 | C21: =271966.99 -> 271966.99 | D21: =311070.24 -> 311070.24 | E21: =303156.24 -> 303156.24 | N21: =sum(B21:M21) -> 1151532.5 | O21: =N21/$N$7 -> 3.6509922
A22: AMC | B22: =4720+2950 -> 7670 | C22: =4720+2950 -> 7670 | D22: =4720+2950 -> 7670 | E22: =4720+2950 -> 7670 | N22: =sum(B22:M22) -> 30680 | O22: =N22/$N$7 -> 0.097272499
A23: Subscription | B23: =2548.84/3+6425/12+9813/12 -> 2202.78 | C23: =2548.84/3+6425/12+9813/12 -> 2202.78 | D23: =2548.84/3+6425/12+9813/12 -> 2202.78 | E23: =6425/12+9813/12+2840/3 -> 2299.8333 | F23: =6425/12+9813/12+2840/3 -> 2299.8333 | G23: =6425/12+9813/12+2840/3 -> 2299.8333 | H23: =6425/12+9813/12 -> 1353.1667 | I23: =6425/12+9813/12 -> 1353.1667 | J23: =6425/12+9813/12 -> 1353.1667 | K23: =6425/12+9813/12 -> 1353.1667 | L23: =6425/12+9813/12 -> 1353.1667 | M23: =6425/12+9813/12 -> 1353.1667 | N23: =sum(B23:M23) -> 21626.84 | O23: =N23/$N$7 -> 0.068568995
A24: Repairs & Maintenance | B24: 0 | C24: 250 | D24: 4130 | E24: ='Misc Exp'!J43 -> 260 | N24: =sum(B24:M24) -> 4640 | O24: =N24/$N$7 -> 0.014711356
A25: Miscellaneous Expenses | B25: 7815.77 | C25: 15995 | D25: 18046 | E25: ='Misc Exp'!J37 -> 17665.98 | N25: =sum(B25:M25) -> 59522.75 | O25: =N25/$N$7 -> 0.1887199
A26: CAM | B26: 0 | C26: 0 | D26: 0 | N26: =sum(B26:M26) -> 0 | O26: =N26/$N$7 -> 0
A27: HO+CK Cost | B27: =HO!D37 -> 199901.39 | C27: =HO!H37 -> 217034.62 | D27: =HO!L37 -> 189294.87 | E27: =HO!P37 -> 191488.63 | F27: =HO!D51 -> #DIV/0! | G27: =HO!H51 -> #DIV/0! | H27: =HO!L51 -> #DIV/0! | I27: =HO!P51 -> #DIV/0! | J27: =HO!D67 -> #DIV/0! | K27: =HO!H67 -> #DIV/0! | L27: =HO!L67 -> #DIV/0! | M27: =HO!P67 -> #DIV/0! | N27: =sum(B27:M27) -> #DIV/0! | O27: =N27/$N$7 -> #DIV/0!
A28: Operating Expenses | B28: =+SUM(B14:B27) -> 1085579.9 | C28: =+SUM(C14:C27) -> 1227438.9 | D28: =+SUM(D14:D27) -> 1210470.6 | E28: =+SUM(E14:E27) -> 1253995.4 | F28: =+SUM(F14:F27) -> #DIV/0! | G28: =+SUM(G14:G27) -> #DIV/0! | H28: =+SUM(H14:H27) -> #DIV/0! | I28: =+SUM(I14:I27) -> #DIV/0! | ... M28: =+SUM(M14:M27) -> #DIV/0! | N28: =sum(B28:M28) -> #DIV/0! | O28: =N28/$N$7 -> #DIV/0!
A29: Store Level EBITDA | B29: =B13-B28 -> 229237.57 | C29: =C13-C28 -> 266937.03 | D29: =D13-D28 -> 116811.26 | E29: =E13-E28 -> 81646.663 | F29: =F13-F28 -> #DIV/0! | G29: =G13-G28 -> #DIV/0! | H29: =H13-H28 -> #DIV/0! | I29: =I13-I28 -> #DIV/0! | ... M29: =M13-M28 -> #DIV/0! | N29: =sum(B29:M29) -> #DIV/0! | O29: =N29/$N$7 -> #DIV/0!
A30: Food Cost | B30: =(B14/B13) -> 0.26559731 | C30: =(C14/C13) -> 0.29523521 | D30: =(D14/D13) -> 0.30704827 | E30: =(E14/E13) -> 0.3053944 | F30: =(F14/F13) -> #DIV/0! | G30: =(G14/G13) -> #DIV/0! | H30: =(H14/H13) -> #DIV/0! | I30: =(I14/I13) -> #DIV/0! | ... M30: =(M14/M13) -> #DIV/0!
B32: =B29+B27 -> 429138.96 | C32: =C29+C27 -> 483971.64 | D32: =D29+D27 -> 306106.13 | E32: =E29+E27 -> 273135.29 | F32: =F29+F27 -> #DIV/0! | G32: =G29+G27 -> #DIV/0! | H32: =H29+H27 -> #DIV/0! | I32: =I29+I27 -> #DIV/0! | ... M32: =M29+M27 -> #DIV/0!
B33: =B32/B13 -> 0.32638671 | C33: =C32/C13 -> 0.32386204 | D33: =D32/D13 -> 0.23062631 | E33: =E32/E13 -> 0.20449737 | F33: =F32/F13 -> #DIV/0! | G33: =G32/G13 -> #DIV/0! | H33: =H32/H13 -> #DIV/0! | I33: =I32/I13 -> #DIV/0! | ... M33: =M32/M13 -> #DIV/0!

Sheet CP
A1: Dosa Coffee - Connaught Place | B1: 46113 | C1: 46143 | D1: 46174 | E1: 46204 | F1: 46235 | G1: 46266 | H1: 46296 | I1: 46327 | J1: 46357 | K1: 46388 | L1: 46419 | M1: 46447 | N1: FY 2025-26
A2: Food Cost Calculation
A3: Opening Stock | B3: 77223 | C3: =B7 -> 80164.89 | D3: =C7 -> 79554.41 | E3: =D7 -> 84784 | F3: =E7 -> 71207.82 | G3: =F7 -> 68480 | H3: =G7 | I3: =H7 | J3: =I7 | ... M3: =L7 | N3: =+SUM(J3:L3) -> 0
A4: Purchases Food (Less Purchase Return) | B4: 993279 | C4: 866003.64 | D4: 937032 | E4: =932909.83-8429 -> 924480.83 | F4: 1002852 | N4: =sum(B4:M4) -> 4723647.5
A5: Transferred Out | B5: 0 | C5: 0 | D5: 0 | E5: 0 | F5: 0 | N5: =+SUM(J5:L5) -> 0
A6: Wastage & Date Expired | B6: 70877 | C6: 64604 | D6: 95185.98 | E6: 70739.91 | F6: 80790 | N6: =+SUM(J6:L6) -> 0
A7: Closing Stock | B7: 80164.89 | C7: 79554.41 | D7: 84784 | E7: 71207.82 | F7: 68480 | N7: =sum(B7:M7) -> 384191.12
A9: Gross Revenue | B9: =3875616.4*1.05+12531.47*1.05 -> 4082555.3 | C9: =3582116.23*1.05+11277.7*1.05 -> 3773063.6 | D9: =3916738.5*1.05+10*1.05+12699.57*1.05 -> 4125920.5 | E9: =3484375.67*1.05+8740.07*1.05 -> 3667771.5 | N9: =+SUM(B9:M9) -> 15649311
A10: Catering & Fairs | B10: 0 | C10: 0 | D10: 0 | E10: 0 | N10: =+SUM(B10:M10) -> 0
A11: Less Tax | B11: =(B9+B10)/1.05*0.05 -> 194407.39 | C11: =(C9+C10)/1.05*0.05 -> 179669.7 | D11: =(D9+D10)/1.05*0.05 -> 196472.4 | E11: =(E9+E10)/1.05*0.05 -> 174655.79 | F11: =(F9+F10)/1.05*0.05 -> 0 | G11: =(G9+G10)/1.05*0.05 -> 0 | H11: =(H9+H10)/1.05*0.05 -> 0 | I11: =(I9+I10)/1.05*0.05 -> 0 | ... M11: =(M9+M10)/1.05*0.05 -> 0 | N11: =+SUM(B11:M11) -> 745205.28
A12: Less Commission | B12: =34730.74*1.18+23770.53*1.18+(4306.58+3970.23)*1.18 -> 78798.134 | C12: =33355.67*1.18+27176.21*1.18+(3477+4585.99)*1.18 -> 80941.947 | D12: =37355.96*1.18+(5748/0.18)*1.18+44822.64*1.18 -> 134652.08 | E12: =27517*1.18+26155.42*1.18+4708*1.18 -> 68888.896 | N12: =+SUM(B12:M12) -> 363281.06
A13: Net Revenues from F&B Sales | B13: =B9+B10-B11-B12 -> 3809349.7 | C13: =C9+C10-C11-C12 -> 3512452 | D13: =D9+D10-D11-D12 -> 3794796 | E13: =E9+E10-E11-E12 -> 3424226.8 | F13: =F9+F10-F11-F12 -> 0 | G13: =G9+G10-G11-G12 -> 0 | H13: =H9+H10-H11-H12 -> 0 | I13: =I9+I10-I11-I12 -> 0 | ... M13: =M9+M10-M11-M12 -> 0 | N13: =sum(B13:M13) -> 14540825
A14: F&B Cost | B14: =+B3+B4-B5-B7 -> 990337.11 | C14: =+C3+C4-C5-C7 -> 866614.12 | D14: =+D3+D4-D5-D7 -> 931802.41 | E14: =+E3+E4-E6-E7 -> 867317.1 | F14: =+F3+F4-F5-F7 -> 1005579.8 | G14: =+G3+G4-G5-G7 -> 68480 | H14: =+H3+H4-H5-H7 -> 0 | I14: =+I3+I4-I5-I7 -> 0 | J14: =+J3+J4-J5-J7 -> 0 | K14: =+K3+K4-K5-K7 -> 0 | L14: =+L3+L4-L5-L7 -> 0 | M14: =+M3+M4-M5-M7 -> 0 | N14: =sum(B14:M14) -> 4730130.6 | O14: =N14/$N$13 -> 0.32530002
A15: Electricity | B15: =122123+45442 -> 167565 | C15: 134645 | D15: =140000+17975 -> 157975 | E15: =148995+13411 -> 162406 | N15: =sum(B15:M15) -> 622591 | O15: =N15/$N$13 -> 0.04281676
A16: Telephone/Internet | B16: =1972+202 -> 2174 | C16: =1972+202 -> 2174 | D16: =202+1972 -> 2174 | E16: =202+1972 -> 2174 | N16: =sum(B16:M16) -> 8696 | O16: =N16/$N$13 -> 0.00059804036
A17: Gas | B17: 165157 | C17: =47936+50000 -> 97936 | D17: =59600+106840 -> 166440 | E17: 116473 | N17: =sum(B17:M17) -> 546006 | O17: =N17/$N$13 -> 0.037549865
A18: Rent & Revenue Share | B18: =1180000 -> 1180000 | C18: =1180000 -> 1180000 | D18: =1180000 -> 1180000 | E18: =1180000 -> 1180000 | N18: =sum(B18:M18) -> 4720000 | O18: =N18/$N$13 -> 0.32460333
A19: Insurance | B19: =2736 -> 2736 | C19: =136716.74/8/12 -> 1424.1327 | D19: =136716.74/8/12 -> 1424.1327 | E19: =136716.74/8/12 -> 1424.1327 | F19: =136716.74/8/12 -> 1424.1327 | G19: =136716.74/8/12 -> 1424.1327 | H19: =136716.74/8/12 -> 1424.1327 | I19: =136716.74/8/12 -> 1424.1327 | J19: =136716.74/8/12 -> 1424.1327 | ... M19: =136716.74/8/12 -> 1424.1327 | N19: =sum(B19:M19) -> 18401.46 | O19: =N19/$N$13 -> 0.0012655032
A20: Software | B20: 7773 | C20: 7773 | D20: 7773 | E20: 7773 | N20: =sum(B20:M20) -> 31092 | O20: =N20/$N$13 -> 0.0021382556
A21: Staff Salary | B21: =563829+18000+38666 -> 620495 | C21: =578598.88+11612+18000+550 -> 608760.88 | D21: =586493.95+18000 -> 604493.95 | E21: =614764.53+18000 -> 632764.53 | N21: =sum(B21:M21) -> 2466514.4 | O21: =N21/$N$13 -> 0.16962686
A22: AMC | B22: =4720+7080 -> 11800 | C22: =4720+7080 -> 11800 | D22: =4720+7080 -> 11800 | E22: =4720+7080 -> 11800 | N22: =sum(B22:M22) -> 47200 | O22: =N22/$N$13 -> 0.0032460333
A23: Subscription | B23: =2548.84/3 -> 849.61333 | C23: =2548.84/3 -> 849.61333 | D23: =2548.84/3 -> 849.61333 | E23: =2840/3 -> 946.66667 | F23: =2840/3 -> 946.66667 | G23: =2840/3 -> 946.66667 | N23: =sum(B23:M23) -> 5388.84 | O23: =N23/$N$13 -> 0.00037060072
A24: Repairs & Maintenance | B24: 0 | C24: =8914 -> 8914 | D24: 18816 | E24: ='Misc Exp'!N43 -> 12632 | N24: =sum(B24:M24) -> 40362 | O24: =N24/$N$13 -> 0.0027757711
A25: Miscellaneous Expenses | B25: 24010.31 | C25: 66527 | D25: 54157 | E25: ='Misc Exp'!N37 -> 52681.66 | N25: =sum(B25:M25) -> 197375.97 | O25: =N25/$N$13 -> 0.013573919
A26: CAM | B26: 0 | C26: 0 | D26: 0 | E26: 0 | F26: 0 | N26: =sum(B26:M26) -> 0 | O26: =N26/$N$13 -> 0
A27: HO+CK Cost | B27: =HO!D38 -> 579163.5 | C27: =HO!H38 -> 510128.44 | D27: =HO!L38 -> 541207.87 | E27: =HO!P38 -> 490925.31 | F27: =HO!D52 -> #DIV/0! | G27: =HO!H52 -> #DIV/0! | H27: =HO!L52 -> #DIV/0! | I27: =HO!P52 -> #DIV/0! | J27: =HO!D68 -> #DIV/0! | K27: =HO!H68 -> #DIV/0! | L27: =HO!L68 -> #DIV/0! | M27: =HO!P68 -> #DIV/0! | N27: =sum(B27:M27) -> #DIV/0! | O27: =N27/$N$13 -> #DIV/0!
A28: Operating Expenses | B28: =+SUM(B14:B27) -> 3752060.5 | C28: =+SUM(C14:C27) -> 3497546.2 | D28: =+SUM(D14:D27) -> 3678913 | E28: =+SUM(E14:E27) -> 3539317.4 | F28: =+SUM(F14:F27) -> #DIV/0! | G28: =+SUM(G14:G27) -> #DIV/0! | H28: =+SUM(H14:H27) -> #DIV/0! | I28: =+SUM(I14:I27) -> #DIV/0! | ... M28: =+SUM(M14:M27) -> #DIV/0! | N28: =sum(B28:M28) -> #DIV/0! | O28: =N28/$N$13 -> #DIV/0!
A29: Store Level EBITDA | B29: =B13-B28 -> 57289.198 | C29: =C13-C28 -> 14905.797 | D29: =D13-D28 -> 115883.01 | E29: =E13-E28 -> -115090.55 | F29: =F13-F28 -> #DIV/0! | G29: =G13-G28 -> #DIV/0! | H29: =H13-H28 -> #DIV/0! | I29: =I13-I28 -> #DIV/0! | ... M29: =M13-M28 -> #DIV/0! | N29: =sum(B29:M29) -> #DIV/0! | O29: =N29/$N$13 -> #DIV/0!
A30: Food Cost | B30: =(B14/B13) -> 0.25997537 | C30: =(C14/C13) -> 0.24672625 | D30: =(D14/D13) -> 0.24554743 | E30: =(E14/E13) -> 0.25328845 | F30: =(F14/F13) -> #DIV/0! | G30: =(G14/G13) -> #DIV/0! | H30: =(H14/H13) -> #DIV/0! | I30: =(I14/I13) -> #DIV/0! | ... M30: =(M14/M13) -> #DIV/0!
B32: =B29+B27 -> 636452.7 | C32: =C29+C27 -> 525034.24 | D32: =D29+D27 -> 657090.88 | E32: =E29+E27 -> 375834.76 | F32: =F29+F27 -> #DIV/0! | G32: =G29+G27 -> #DIV/0! | H32: =H29+H27 -> #DIV/0! | I32: =I29+I27 -> #DIV/0! | ... M32: =M29+M27 -> #DIV/0!
B33: =B32/B13 -> 0.16707647 | C33: =C32/C13 -> 0.14947798 | D33: =D32/D13 -> 0.17315579 | E33: =E32/E13 -> 0.10975755 | F33: =F32/F13 -> #DIV/0! | G33: =G32/G13 -> #DIV/0! | H33: =H32/H13 -> #DIV/0! | I33: =I32/I13 -> #DIV/0! | ... M33: =M32/M13 -> #DIV/0!

Sheet Rohini
A1: Dosa Coffee - Rohini | B1: 46113 | C1: 46143 | D1: 46174 | E1: 46204 | F1: 46235 | G1: 46266 | H1: 46296 | I1: 46327 | J1: 46357 | K1: 46388 | L1: 46419 | M1: 46447 | N1: FY 2025-26
A2: Food Cost Calculation
A3: Opening Stock | B3: 104700 | C3: =B7 -> 122059.07 | D3: =C7 -> 92293.32 | E3: =D7 -> 95850 | F3: =E7 -> 89130.07 | G3: =F7 -> 64482 | H3: =G7 | I3: =H7 | J3: =I7 | ... M3: =L7 | N3: =+SUM(J3:L3) -> 0
A4: Purchases Food (Less Purchase Return) | B4: 526909 | C4: 526621.99 | D4: 572572.63 | E4: 524616 | F4: 577388.49 | N4: =sum(B4:M4) -> 2728108.1
A5: Transferred Out | B5: 0 | C5: 0 | D5: 0 | E5: 0 | F5: 0 | N5: =+SUM(J5:L5) -> 0
A6: Wastage & Date Expired | B6: 38401.56 | C6: 35926.17 | D6: 28888 | E6: 34131 | F6: 34625 | N6: =+SUM(J6:L6) -> 0
A7: Closing Stock | B7: 122059.07 | C7: 92293.32 | D7: 95850 | E7: 89130.07 | F7: 64482 | N7: =sum(B7:M7) -> 463814.46
A9: Gross Revenue | B9: =2051980.04*1.05+50540.57*1.05 -> 2207646.6 | C9: =2258617.27*1.05+56157.64*1.05 -> 2430513.7 | D9: =2202373*1.05+51452.11*1.05 -> 2366516.4 | E9: =2069109.32*1.05+46187.2*1.05 -> 2221061.3 | N9: =+SUM(B9:M9) -> 9225738
A10: Catering & Fairs | N10: =+SUM(B10:M10) -> 0
A11: Less Tax | B11: =(B9+B10)/1.05*0.05 -> 105126.03 | C11: =(C9+C10)/1.05*0.05 -> 115738.75 | D11: =(D9+D10)/1.05*0.05 -> 112691.26 | E11: =(E9+E10)/1.05*0.05 -> 105764.83 | F11: =(F9+F10)/1.05*0.05 -> 0 | G11: =(G9+G10)/1.05*0.05 -> 0 | H11: =(H9+H10)/1.05*0.05 -> 0 | I11: =(I9+I10)/1.05*0.05 -> 0 | ... M11: =(M9+M10)/1.05*0.05 -> 0 | N11: =+SUM(B11:M11) -> 439320.86
A12: Less Commission | B12: =119641.47*1.18+71648.19*1.18+3490.95*1.18+94.68 -> 229935.8 | C12: =+132449.28*1.18+83100.97*1.18+4244.94*1.18 -> 259358.32 | D12: =122000*1.18+(15216.95/0.18)*1.18+3892.41*1.18 -> 248308.6 | E12: =109196*1.18+82822.65*1.18+3045*1.18+55 -> 230230.11 | N12: =+SUM(B12:M12) -> 967832.84
A13: Net Revenues from F&B Sales | B13: =B9+B10-B11-B12 -> 1872584.8 | C13: =C9+C10-C11-C12 -> 2055416.6 | D13: =D9+D10-D11-D12 -> 2005516.5 | E13: =E9+E10-E11-E12 -> 1885066.4 | F13: =F9+F10-F11-F12 -> 0 | G13: =G9+G10-G11-G12 -> 0 | H13: =H9+H10-H11-H12 -> 0 | I13: =I9+I10-I11-I12 -> 0 | ... M13: =M9+M10-M11-M12 -> 0 | N13: =sum(B13:M13) -> 7818584.3 | O13: =N13/$N$7 -> 16.857138
A14: F&B Cost | B14: =+B3+B4-B5-B7 -> 509549.93 | C14: =+C3+C4-C5-C7 -> 556387.74 | D14: =+D3+D4-D5-D7 -> 569015.95 | E14: =+E3+E4-E5-E7 -> 531335.93 | F14: =+F3+F4-F5-F7 -> 602036.56 | G14: =+G3+G4-G5-G7 -> 64482 | H14: =+H3+H4-H5-H7 -> 0 | I14: =+I3+I4-I5-I7 -> 0 | ... M14: =+M3+M4-M5-M7 -> 0 | N14: =sum(B14:M14) -> 2832808.1 | O14: =N14/$N$7 -> 6.1076322
A15: Electricity | B15: =86010 -> 86010 | C15: =105990 -> 105990 | D15: =97360 -> 97360 | E15: =100090 -> 100090 | N15: =sum(B15:M15) -> 389450 | O15: =N15/$N$7 -> 0.83966765
A16: Telephone/Internet | B16: =2709/2 -> 1354.5 | C16: =2709/2 -> 1354.5 | D16: =2709/2 -> 1354.5 | E16: =2709/2 -> 1354.5 | N16: =sum(B16:M16) -> 5418 | O16: =N16/$N$7 -> 0.011681395
A17: Gas | B17: =51446.27 -> 51446.27 | C17: 57225.58 | D17: 45003 | E17: 62821 | N17: =sum(B17:M17) -> 216495.85 | O17: =N17/$N$7 -> 0.46677253
A18: Rent & Revenue Share | B18: =113832.24+113832.24 -> 227664.48 | C18: =113832.24+113832.24 -> 227664.48 | D18: =113832.24+113832.24 -> 227664.48 | E18: =113832.24+113832.24 -> 227664.48 | N18: =sum(B18:M18) -> 910657.92 | O18: =N18/$N$7 -> 1.9634099
A19: Insurance | B19: 968 | C19: =136716.74/8/12 -> 1424.1327 | D19: =136716.74/8/12 -> 1424.1327 | E19: =136716.74/8/12 -> 1424.1327 | F19: =136716.74/8/12 -> 1424.1327 | G19: =136716.74/8/12 -> 1424.1327 | H19: =136716.74/8/12 -> 1424.1327 | I19: =136716.74/8/12 -> 1424.1327 | J19: =136716.74/8/12 -> 1424.1327 | ... M19: =136716.74/8/12 -> 1424.1327 | N19: =sum(B19:M19) -> 16633.46
A20: Software | B20: 5767 | C20: 5767 | D20: 5767 | E20: 5767 | N20: =sum(B20:M20) -> 23068 | O20: =N20/$N$7 -> 0.049735405
A21: Staff Salary | B21: 378972 | C21: =389377.25 -> 389377.25 | D21: =417756.96 -> 417756.96 | E21: =388533.27 -> 388533.27 | N21: =sum(B21:M21) -> 1574639.5 | O21: =N21/$N$7 -> 3.3949771
A22: AMC | B22: =4720+2950 -> 7670 | C22: =4720+2950 -> 7670 | D22: =4720+2950 -> 7670 | E22: =4720+2950 -> 7670 | N22: =sum(B22:M22) -> 30680 | O22: =N22/$N$7 -> 0.06614714
A23: Subscription | B23: =2548.84/3+6425/12+9813/12 -> 2202.78 | C23: =2548.84/3+6425/12+9813/12 -> 2202.78 | D23: =2548.84/3+6425/12+9813/12 -> 2202.78 | E23: =6425/12+9813/12+2840/3 -> 2299.8333 | F23: =6425/12+9813/12+2840/3 -> 2299.8333 | G23: =6425/12+9813/12+2840/3 -> 2299.8333 | H23: =6425/12+9813/12 -> 1353.1667 | I23: =6425/12+9813/12 -> 1353.1667 | J23: =6425/12+9813/12 -> 1353.1667 | K23: =6425/12+9813/12 -> 1353.1667 | L23: =6425/12+9813/12 -> 1353.1667 | M23: =6425/12+9813/12 -> 1353.1667 | N23: =sum(B23:M23) -> 21626.84 | O23: =N23/$N$7 -> 0.046628214
A24: Repairs & Maintenance | B24: 0 | C24: 0 | D24: 6903 | E24: ='Misc Exp'!L43 -> 4450 | N24: =sum(B24:M24) -> 11353 | O24: =N24/$N$7 -> 0.02447746
A25: Miscellaneous Expenses | B25: 15863.25 | C25: 11970 | D25: 20071 | E25: ='Misc Exp'!L37 -> 20238.77 | N25: =sum(B25:M25) -> 68143.02 | O25: =N25/$N$7 -> 0.14691871
A26: CAM | B26: 0 | C26: 0 | D26: 0 | E26: 0 | N26: =sum(B26:M26) -> 0 | O26: =N26/$N$7 -> 0
A27: HO+CK Cost | B27: =HO!D39 -> 284702.86 | C27: =HO!H39 -> 298516.95 | D27: =HO!L39 -> 286023.63 | E27: =HO!P39 -> 270258.62 | F27: =HO!D53 -> #DIV/0! | G27: =HO!H53 -> #DIV/0! | H27: =HO!L53 -> #DIV/0! | I27: =HO!P53 -> #DIV/0! | J27: =HO!D69 -> #DIV/0! | K27: =HO!H69 -> #DIV/0! | L27: =HO!L69 -> #DIV/0! | M27: =HO!P69 -> #DIV/0! | N27: =sum(B27:M27) -> #DIV/0! | O27: =N27/$N$7 -> #DIV/0!
A28: Operating Expenses | B28: =+SUM(B14:B27) -> 1572171.1 | C28: =+SUM(C14:C27) -> 1665550.4 | D28: =+SUM(D14:D27) -> 1688216.4 | E28: =+SUM(E14:E27) -> 1623907.5 | F28: =+SUM(F14:F27) -> #DIV/0! | G28: =+SUM(G14:G27) -> #DIV/0! | H28: =+SUM(H14:H27) -> #DIV/0! | I28: =+SUM(I14:I27) -> #DIV/0! | ... M28: =+SUM(M14:M27) -> #DIV/0! | N28: =sum(B28:M28) -> #DIV/0! | O28: =N28/$N$7 -> #DIV/0!
A29: Store Level EBITDA | B29: =B13-B28 -> 300413.74 | C29: =C13-C28 -> 389866.17 | D29: =D13-D28 -> 317300.07 | E29: =E13-E28 -> 261158.88 | F29: =F13-F28 -> #DIV/0! | G29: =G13-G28 -> #DIV/0! | H29: =H13-H28 -> #DIV/0! | I29: =I13-I28 -> #DIV/0! | ... M29: =M13-M28 -> #DIV/0! | N29: =sum(B29:M29) -> #DIV/0! | O29: =N29/$N$7 -> #DIV/0!
A30: Food Cost | B30: =(B14/B13) -> 0.27211047 | C30: =(C14/C13) -> 0.27069342 | D30: =(D14/D13) -> 0.28372539 | E30: =(E14/E13) -> 0.28186589 | F30: =(F14/F13) -> #DIV/0! | G30: =(G14/G13) -> #DIV/0! | H30: =(H14/H13) -> #DIV/0! | I30: =(I14/I13) -> #DIV/0! | ... M30: =(M14/M13) -> #DIV/0!
B32: =B29+B27 -> 585116.6 | C32: =C29+C27 -> 688383.12 | D32: =D29+D27 -> 603323.7 | E32: =E29+E27 -> 531417.5 | F32: =F29+F27 -> #DIV/0! | G32: =G29+G27 -> #DIV/0! | H32: =H29+H27 -> #DIV/0! | I32: =I29+I27 -> #DIV/0! | ... M32: =M29+M27 -> #DIV/0!
B33: =B32/B13 -> 0.31246467 | C33: =C32/C13 -> 0.33491173 | D33: =D32/D13 -> 0.30083208 | E33: =E32/E13 -> 0.28190916 | F33: =F32/F13 -> #DIV/0! | G33: =G32/G13 -> #DIV/0! | H33: =H32/H13 -> #DIV/0! | I33: =I32/I13 -> #DIV/0! | ... M33: =M32/M13 -> #DIV/0!

Sheet Model Town
A1: Dosa Coffee - Model Town | B1: 46113 | C1: 46143 | D1: 46174 | E1: 46204 | F1: 46235 | G1: 46266 | H1: 46296 | I1: 46327 | J1: 46357 | K1: 46388 | L1: 46419 | M1: 46447 | N1: FY 2025-26
A2: Food Cost Calculation
A3: Opening Stock | B3: 80928 | C3: =B7 -> 75279.8 | D3: =C7 -> 65861.44 | E3: =D7 -> 60614 | F3: =E7 -> 60060 | G3: =F7 -> 64772.52 | H3: =G7 | I3: =H7 | J3: =I7 | ... M3: =L7 | N3: =+SUM(J3:L3) -> 0
A4: Purchases Food (Less Purchase Return) | B4: 591480 | C4: 586977.65 | D4: 518317 | E4: 468712 | F4: 529452 | N4: =sum(B4:M4) -> 2694938.6
A5: Transferred Out | B5: 0 | C5: 0 | D5: 0 | E5: 0 | F5: 0 | N5: =+SUM(J5:L5) -> 0
A6: Wastage & Date Expired | B6: 33396.92 | C6: 26189.06 | D6: 24713 | E6: 18719 | F6: 18555 | N6: =+SUM(J6:L6) -> 0
A7: Closing Stock | B7: 75279.8 | C7: 65861.44 | D7: 60614 | E7: 60060 | F7: 64772.52 | N7: =sum(B7:M7) -> 326587.76
A9: Gross Revenue | B9: =2253836.58*1.05+48246.93*1.05 -> 2417187.7 | C9: =2199056*1.05+47913.53*1.05 -> 2359318 | D9: =1929334.13*1.05+30*1.05+43861.65*1.05 -> 2071887.1 | E9: =1851603*1.05+39229.96*1.05 -> 1985374.6 | N9: =+SUM(B9:M9) -> 8833767.4
A10: Catering & Fairs | N10: =+SUM(B10:M10) -> 0
A11: Less Tax | B11: =(B9+B10)/1.05*0.05 -> 115104.18 | C11: =(C9+C10)/1.05*0.05 -> 112348.48 | D11: =(D9+D10)/1.05*0.05 -> 98661.289 | E11: =(E9+E10)/1.05*0.05 -> 94541.648 | F11: =(F9+F10)/1.05*0.05 -> 0 | G11: =(G9+G10)/1.05*0.05 -> 0 | H11: =(H9+H10)/1.05*0.05 -> 0 | I11: =(I9+I10)/1.05*0.05 -> 0 | ... M11: =(M9+M10)/1.05*0.05 -> 0 | N11: =+SUM(B11:M11) -> 420655.59
A12: Less Commission | B12: =113677.28*1.18+32664.31*1.18+3330.31*1.18 -> 176612.84 | C12: =113500.92*1.18+44161.46*1.18+3350.64*1.18 -> 189995.36 | D12: =103890.88*1.18+(6947/0.18)*1.18+3191.97*1.18 -> 171899.21 | E12: =93200*1.18+39209*1.18+1310*1.18 -> 157788.42 | N12: =+SUM(B12:M12) -> 696295.83 | T12: =8749.04*0.18 -> 1574.8272
A13: Net Revenues from F&B Sales | B13: =B9+B10-B11-B12 -> 2125470.7 | C13: =C9+C10-C11-C12 -> 2056974.2 | D13: =D9+D10-D11-D12 -> 1801326.6 | E13: =E9+E10-E11-E12 -> 1733044.5 | F13: =F9+F10-F11-F12 -> 0 | G13: =G9+G10-G11-G12 -> 0 | H13: =H9+H10-H11-H12 -> 0 | I13: =I9+I10-I11-I12 -> 0 | ... M13: =M9+M10-M11-M12 -> 0 | N13: =sum(B13:M13) -> 7716815.9 | O13: =N13/$N$7 -> 23.628613
A14: F&B Cost | B14: =+B3+B4-B5-B7 -> 597128.2 | C14: =+C3+C4-C5-C7 -> 596396.01 | D14: =+D3+D4-D5-D7 -> 523564.44 | E14: =+E3+E4-E5-E7 -> 469266 | F14: =+F3+F4-F5-F7 -> 524739.48 | G14: =+G3+G4-G5-G7 -> 64772.52 | H14: =+H3+H4-H5-H7 -> 0 | I14: =+I3+I4-I5-I7 -> 0 | ... M14: =+M3+M4-M5-M7 -> 0 | N14: =sum(B14:M14) -> 2775866.6 | O14: =N14/$N$7 -> 8.4996041
A15: Electricity | B15: =134910+22084/3 -> 142271.33 | C15: =167140+22084/3 -> 174501.33 | D15: =22084/3+154930 -> 162291.33 | E15: 158220 | N15: =sum(B15:M15) -> 637284 | O15: =N15/$N$7 -> 1.9513407
A16: Telephone/Internet | B16: =5310/3+219 -> 1989 | C16: =5310/3+219 -> 1989 | D16: =5310/3+219 -> 1989 | E16: =219+5310/3 -> 1989 | N16: =sum(B16:M16) -> 7956 | O16: =N16/$N$7 -> 0.024360986
A17: Gas | B17: =98881.92 -> 98881.92 | C17: 130928 | D17: 54139 | E17: 102386 | N17: =sum(B17:M17) -> 386334.92 | O17: =N17/$N$7 -> 1.1829437
A18: Rent & Revenue Share | B18: =472000 -> 472000 | C18: =472000 -> 472000 | D18: =472000 -> 472000 | E18: =472000 -> 472000 | N18: =sum(B18:M18) -> 1888000 | O18: =N18/$N$7 -> 5.7809882
A19: Insurance | B19: =1859 -> 1859 | C19: =136716.74/8/12 -> 1424.1327 | D19: =136716.74/8/12 -> 1424.1327 | E19: =136716.74/8/12 -> 1424.1327 | F19: =136716.74/8/12 -> 1424.1327 | G19: =136716.74/8/12 -> 1424.1327 | H19: =136716.74/8/12 -> 1424.1327 | I19: =136716.74/8/12 -> 1424.1327 | J19: =136716.74/8/12 -> 1424.1327 | ... M19: =136716.74/8/12 -> 1424.1327 | N19: =sum(B19:M19) -> 17524.46 | O19: =N19/$N$7 -> 0.053659267
A20: Software | B20: 7302 | C20: 7302 | D20: 7302 | E20: 7302 | N20: =sum(B20:M20) -> 29208 | O20: =N20/$N$7 -> 0.089433848
A21: Staff Salary | B21: =453973+7000 -> 460973 | C21: =466081.35+7000 -> 473081.35 | D21: =426367.08+7000 -> 433367.08 | E21: =455116.45+7000 -> 462116.45 | N21: =sum(B21:M21) -> 1829537.9 | O21: =N21/$N$7 -> 5.6019793
A22: AMC | B22: =4720+5145 -> 9865 | C22: =4720+5145 -> 9865 | D22: =4720+5145 -> 9865 | E22: =4720+5145 -> 9865 | N22: =sum(B22:M22) -> 39460 | O22: =N22/$N$7 -> 0.1208251
A23: Subscription | B23: =2548.84/3 -> 849.61333 | C23: =2548.84/3 -> 849.61333 | D23: =2548.84/3 -> 849.61333 | E23: =2840/3 -> 946.66667 | F23: =2840/3 -> 946.66667 | G23: =2840/3 -> 946.66667 | N23: =sum(B23:M23) -> 5388.84 | O23: =N23/$N$7 -> 0.016500435
A24: Repairs & Maintenance | B24: =7316 -> 7316 | C24: 0 | D24: 4130 | E24: ='Misc Exp'!K43 -> 10620 | N24: =sum(B24:M24) -> 22066 | O24: =N24/$N$7 -> 0.0675653
A25: Miscellaneous Expenses | B25: 8535.83 | C25: 9935.75 | D25: 17263.47 | E25: ='Misc Exp'!K37 -> 23598.95 | N25: =sum(B25:M25) -> 59334 | O25: =N25/$N$7 -> 0.18167858
A26: CAM | B26: 0 | C26: 0 | D26: 0 | N26: =sum(B26:M26) -> 0 | O26: =N26/$N$7 -> 0
A27: HO+CK Cost | B27: =HO!D40 -> 323150.96 | C27: =HO!H40 -> 298743.17 | D27: =HO!L40 -> 256902.38 | E27: =HO!P40 -> 248463.51 | F27: =HO!D54 -> #DIV/0! | G27: =HO!H54 -> #DIV/0! | H27: =HO!L54 -> #DIV/0! | I27: =HO!P54 -> #DIV/0! | J27: =HO!D70 -> #DIV/0! | K27: =HO!H70 -> #DIV/0! | L27: =HO!L70 -> #DIV/0! | M27: =HO!P70 -> #DIV/0! | N27: =sum(B27:M27) -> #DIV/0! | O27: =N27/$N$7 -> #DIV/0!
A28: Operating Expenses | B28: =+SUM(B14:B27) -> 2132121.9 | C28: =+SUM(C14:C27) -> 2177015.4 | D28: =+SUM(D14:D27) -> 1945087.4 | E28: =+SUM(E14:E27) -> 1968197.7 | F28: =+SUM(F14:F27) -> #DIV/0! | G28: =+SUM(G14:G27) -> #DIV/0! | H28: =+SUM(H14:H27) -> #DIV/0! | I28: =+SUM(I14:I27) -> #DIV/0! | ... M28: =+SUM(M14:M27) -> #DIV/0! | N28: =sum(B28:M28) -> #DIV/0! | O28: =N28/$N$7 -> #DIV/0!
A29: Store Level EBITDA | B29: =B13-B28 -> -6651.1928 | C29: =C13-C28 -> -120041.19 | D29: =D13-D28 -> -143760.88 | E29: =E13-E28 -> -235153.17 | F29: =F13-F28 -> #DIV/0! | G29: =G13-G28 -> #DIV/0! | H29: =H13-H28 -> #DIV/0! | I29: =I13-I28 -> #DIV/0! | ... M29: =M13-M28 -> #DIV/0! | N29: =sum(B29:M29) -> #DIV/0! | O29: =N29/$N$7 -> #DIV/0!
A30: Food Cost | B30: =(B14/B13) -> 0.28093928 | C30: =(C14/C13) -> 0.2899385 | D30: =(D14/D13) -> 0.29065493 | E30: =(E14/E13) -> 0.2707755 | F30: =(F14/F13) -> #DIV/0! | G30: =(G14/G13) -> #DIV/0! | H30: =(H14/H13) -> #DIV/0! | I30: =(I14/I13) -> #DIV/0! | ... M30: =(M14/M13) -> #DIV/0!
B32: =B29+B27 -> 316499.77 | C32: =C29+C27 -> 178701.98 | D32: =D29+D27 -> 113141.5 | E32: =E29+E27 -> 13310.341 | F32: =F29+F27 -> #DIV/0! | G32: =G29+G27 -> #DIV/0! | H32: =H29+H27 -> #DIV/0! | I32: =I29+I27 -> #DIV/0! | ... M32: =M29+M27 -> #DIV/0!
B33: =B32/B13 -> 0.14890809 | C33: =C32/C13 -> 0.086876141 | D33: =D32/D13 -> 0.062810101 | E33: =E32/E13 -> 0.0076803223 | F33: =F32/F13 -> #DIV/0! | G33: =G32/G13 -> #DIV/0! | H33: =H32/H13 -> #DIV/0! | I33: =I32/I13 -> #DIV/0! | ... M33: =M32/M13 -> #DIV/0!

Sheet Pacific Mall
A1: Dosa Coffee - Pacific Mall | B1: 46113 | C1: 46143 | D1: 46174 | E1: 46204 | F1: 46235 | G1: 46266 | H1: 46296 | I1: 46327 | J1: 46357 | K1: 46388 | L1: 46419 | M1: 46447 | N1: FY 2025-26
A2: Food Cost Calculation
A3: Opening Stock | B3: 21772 | C3: =B7 -> 27514 | D3: =C7 -> 27435.24 | E3: =D7 -> 33059 | F3: =E7 -> 25171 | G3: =F7 -> 25480 | H3: =G7 | I3: =H7 | J3: =I7 | ... M3: =L7 | N3: =+SUM(J3:L3) -> 0
A4: Purchases Food (Less Purchase Return) | B4: 505213 | C4: 533796.56 | D4: 551795 | E4: 523595 | F4: 597842 | N4: =sum(B4:M4) -> 2712241.6
A5: Transferred Out | B5: 0 | C5: 0 | D5: 0 | E5: 0 | F5: 0 | N5: =+SUM(J5:L5) -> 0
A6: Wastage & Date Expired | B6: 22006 | C6: 24242.04 | D6: 23447 | E6: 24492 | F6: 26311.71 | N6: =+SUM(J6:L6) -> 0
A7: Closing Stock | B7: 27514 | C7: 27435.24 | D7: 33059 | E7: 25171 | F7: 25480 | N7: =sum(B7:M7) -> 138659.24
A9: Gross Revenue | B9: =2155310.44*1.05+16985.87*1.05 -> 2280911.1 | C9: =2350081.58*1.05+16831.24*1.05 -> 2485258.5 | D9: =2436909.75*1.05+15012.85*1.05 -> 2574518.7 | E9: =2300624.42*1.05 -> 2415655.6 | N9: =+SUM(B9:M9) -> 9756344
A10: Catering & Fairs | N10: =+SUM(B10:M10) -> 0
A11: Less Tax | B11: =(B9+B10)/1.05*0.05 -> 108614.82 | C11: =(C9+C10)/1.05*0.05 -> 118345.64 | D11: =(D9+D10)/1.05*0.05 -> 122596.13 | E11: =(E9+E10)/1.05*0.05 -> 115031.22 | F11: =(F9+F10)/1.05*0.05 -> 0 | G11: =(G9+G10)/1.05*0.05 -> 0 | H11: =(H9+H10)/1.05*0.05 -> 0 | I11: =(I9+I10)/1.05*0.05 -> 0 | ... M11: =(M9+M10)/1.05*0.05 -> 0 | N11: =+SUM(B11:M11) -> 464587.81
A12: Less Commission | B12: =42034.5*1.18+38216.89*1.18+3438.85*1.18 -> 98754.483 | C12: =42401.9*1.18+32172.91*1.18+4242.39*1.18 -> 93004.296 | D12: =37972.85*1.18+(7495.1/0.18)*1.18+3421.24*1.18 -> 97979.571 | E12: =32074.01*1.18+40565.18*1.18+4282*1.18 -> 90767.004 | N12: =+SUM(B12:M12) -> 380505.35
A13: Net Revenues from F&B Sales | B13: =B9+B10-B11-B12 -> 2073541.8 | C13: =C9+C10-C11-C12 -> 2273908.5 | D13: =D9+D10-D11-D12 -> 2353943 | E13: =E9+E10-E11-E12 -> 2209857.4 | F13: =F9+F10-F11-F12 -> 0 | G13: =G9+G10-G11-G12 -> 0 | H13: =H9+H10-H11-H12 -> 0 | I13: =I9+I10-I11-I12 -> 0 | ... M13: =M9+M10-M11-M12 -> 0 | N13: =sum(B13:M13) -> 8911250.8 | O13: =N13/$N$7 -> 64.26727
A14: F&B Cost | B14: =+B3+B4-B5-B7 -> 499471 | C14: =+C3+C4-C5-C7 -> 533875.32 | D14: =+D3+D4-D5-D7 -> 546171.24 | E14: =+E3+E4-E5-E7 -> 531483 | F14: =+F3+F4-F5-F7 -> 597533 | G14: =+G3+G4-G5-G7 -> 25480 | H14: =+H3+H4-H5-H7 -> 0 | I14: =+I3+I4-I5-I7 -> 0 | ... M14: =+M3+M4-M5-M7 -> 0 | N14: =sum(B14:M14) -> 2734013.6 | O14: =N14/$N$13 -> 0.30680469
A15: Electricity | B15: =63414.4+11911 -> 75325.4 | C15: =65504.11+13225 -> 78729.11 | D15: =58975+14007 -> 72982 | E15: =52978+14007 -> 66985 | N15: =sum(B15:M15) -> 294021.51 | O15: =N15/$N$13 -> 0.032994415
A16: Telephone/Internet | B16: =942 -> 942 | C16: =942 -> 942 | D16: =942+474 -> 1416 | E16: =942 -> 942 | N16: =sum(B16:M16) -> 4242 | O16: =N16/$N$13 -> 0.00047602745
A17: Gas | B17: =166016.74 -> 166016.74 | C17: 171991 | D17: 181890 | E17: 189418 | N17: =sum(B17:M17) -> 709315.74 | O17: =N17/$N$13 -> 0.079597775
A18: Rent & Revenue Share | B18: =326539.52+65796.8 -> 392336.32 | C18: =326539.52+65796.8 -> 392336.32 | D18: =326539.52+65796.8+8615.36 -> 400951.68 | E18: =326539+65796+20652 -> 412987 | N18: =sum(B18:M18) -> 1598611.3 | O18: =N18/$N$13 -> 0.17939247
A19: Insurance | B19: 1258 | C19: =136716.74/8/12 -> 1424.1327 | D19: =136716.74/8/12 -> 1424.1327 | E19: =136716.74/8/12 -> 1424.1327 | F19: =136716.74/8/12 -> 1424.1327 | G19: =136716.74/8/12 -> 1424.1327 | H19: =136716.74/8/12 -> 1424.1327 | I19: =136716.74/8/12 -> 1424.1327 | J19: =136716.74/8/12 -> 1424.1327 | ... M19: =136716.74/8/12 -> 1424.1327 | N19: =sum(B19:M19) -> 16923.46 | O19: =N19/$N$13 -> 0.0018991116
A20: Software | B20: 5767 | C20: 5767 | D20: 5767 | E20: 5767 | N20: =sum(B20:M20) -> 23068 | O20: =N20/$N$13 -> 0.0025886377
A21: Staff Salary | B21: =328499+5000 -> 333499 | C21: =337285.5+5000 -> 342285.5 | D21: =363150.81+5000 -> 368150.81 | E21: =315211.15+5000 -> 320211.15 | N21: =sum(B21:M21) -> 1364146.5 | O21: =N21/$N$13 -> 0.15308137
A22: AMC | B22: =4720+2950 -> 7670 | C22: =4720+2950 -> 7670 | D22: =4720+2950 -> 7670 | E22: =4720+2950 -> 7670 | N22: =sum(B22:M22) -> 30680 | O22: =N22/$N$13 -> 0.0034428388
A23: Subscription | B23: =2548.84/3 -> 849.61333 | C23: =2548.84/3 -> 849.61333 | D23: =2548.84/3 -> 849.61333 | E23: =2840/3 -> 946.66667 | F23: =2840/3 -> 946.66667 | G23: =2840/3 -> 946.66667 | N23: =sum(B23:M23) -> 5388.84 | O23: =N23/$N$13 -> 0.00060472319
A24: Repairs & Maintenance | B24: 0 | C24: 0 | D24: 4130 | E24: ='Misc Exp'!M43 -> 0 | N24: =sum(B24:M24) -> 4130 | O24: =N24/$N$13 -> 0.00046345907
A25: Miscellaneous Expenses | B25: 6229.03 | C25: 30891.89 | D25: 24520 | E25: ='Misc Exp'!M37 -> 17135 | N25: =sum(B25:M25) -> 78775.92 | O25: =N25/$N$13 -> 0.008840052
A26: CAM | B26: =159903.89 -> 159903.89 | C26: =159903.89 -> 159903.89 | D26: =159903.89 -> 159903.89 | E26: =159903.89 -> 159903.89 | N26: =sum(B26:M26) -> 639615.56 | O26: =N26/$N$13 -> 0.071776182
A27: HO+CK Cost | B27: =HO!D41 -> 315255.84 | C27: =HO!H41 -> 330249.47 | D27: =HO!L41 -> 335715.67 | E27: =HO!P41 -> 316823.32 | F27: =HO!D55 -> #DIV/0! | G27: =HO!H55 -> #DIV/0! | H27: =HO!L55 -> #DIV/0! | I27: =HO!P55 -> #DIV/0! | J27: =HO!D71 -> #DIV/0! | K27: =HO!H71 -> #DIV/0! | L27: =HO!L71 -> #DIV/0! | M27: =HO!P71 -> #DIV/0! | N27: =sum(B27:M27) -> #DIV/0! | O27: =N27/$N$13 -> #DIV/0!
A28: Operating Expenses | B28: =+SUM(B14:B27) -> 1964523.8 | C28: =+SUM(C14:C27) -> 2056915.2 | D28: =+SUM(D14:D27) -> 2111542 | E28: =+SUM(E14:E27) -> 2031696.2 | F28: =+SUM(F14:F27) -> #DIV/0! | G28: =+SUM(G14:G27) -> #DIV/0! | H28: =+SUM(H14:H27) -> #DIV/0! | I28: =+SUM(I14:I27) -> #DIV/0! | ... M28: =+SUM(M14:M27) -> #DIV/0! | N28: =sum(B28:M28) -> #DIV/0! | O28: =N28/$N$13 -> #DIV/0!
A29: Store Level EBITDA | B29: =B13-B28 -> 109017.99 | C29: =C13-C28 -> 216993.28 | D29: =D13-D28 -> 242400.99 | E29: =E13-E28 -> 178161.25 | F29: =F13-F28 -> #DIV/0! | G29: =G13-G28 -> #DIV/0! | H29: =H13-H28 -> #DIV/0! | I29: =I13-I28 -> #DIV/0! | ... M29: =M13-M28 -> #DIV/0! | N29: =sum(B29:M29) -> #DIV/0! | O29: =N29/$N$13 -> #DIV/0!
A30: Food Cost | B30: =(B14/B13) -> 0.24087819 | C30: =(C14/C13) -> 0.23478311 | D30: =(D14/D13) -> 0.23202398 | E30: =(E14/E13) -> 0.24050556 | F30: =(F14/F13) -> #DIV/0! | G30: =(G14/G13) -> #DIV/0! | H30: =(H14/H13) -> #DIV/0! | I30: =(I14/I13) -> #DIV/0! | ... M30: =(M14/M13) -> #DIV/0!
B32: =B29+B27 -> 424273.83 | C32: =C29+C27 -> 547242.75 | D32: =D29+D27 -> 578116.66 | E32: =E29+E27 -> 494984.58 | F32: =F29+F27 -> #DIV/0! | G32: =G29+G27 -> #DIV/0! | H32: =H29+H27 -> #DIV/0! | I32: =I29+I27 -> #DIV/0! | ... M32: =M29+M27 -> #DIV/0!
B33: =B32/B13 -> 0.20461311 | C33: =C32/C13 -> 0.24066172 | D33: =D32/D13 -> 0.24559501 | E33: =E32/E13 -> 0.22398937 | F33: =F32/F13 -> #DIV/0! | G33: =G32/G13 -> #DIV/0! | H33: =H32/H13 -> #DIV/0! | I33: =I32/I13 -> #DIV/0! | ... M33: =M32/M13 -> #DIV/0!

Sheet Shalimar Bagh
A1: Dosa Coffee - Shalimar Bagh | B1: 46113 | C1: 46143 | D1: 46174 | E1: 46204 | F1: 46235 | G1: 46266 | H1: 46296 | I1: 46327 | J1: 46357 | K1: 46388 | L1: 46419 | M1: 46447 | N1: FY 2025-26
A2: Food Cost Calculation
A3: Opening Stock | B3: 38039 | C3: =B7 -> 18923 | D3: =C7 -> 29450.06 | E3: =D7 -> 29521.7 | F3: =E7 -> 37727 | G3: =F7 -> 35421 | M3: 0 | N3: =+SUM(J3:L3) -> 0
A4: Purchases Food (Less Purchase Return) | B4: 276308 | C4: 344183.63 | D4: 304172.64 | E4: 325675 | F4: 343465.46 | N4: =sum(B4:M4) -> 1593804.7
A5: Transferred Out | B5: 0 | C5: 0 | D5: 0 | E5: 0 | F5: 0 | M5: 0 | N5: =+SUM(J5:L5) -> 0
A6: Wastage & Date Expired | B6: 17291 | C6: 23745.75 | D6: 22116.97 | E6: 12964 | F6: 11508 | N6: =+SUM(J6:L6) -> 0
A7: Closing Stock | B7: 18923 | C7: 29450.06 | D7: 29521.7 | E7: 37727 | F7: 35421 | N7: =sum(B7:M7) -> 151042.76
A9: Gross Revenue | B9: =1186292.53*1.05+8788.9*1.05 -> 1254835.5 | C9: =1414654.49*1.05+12335.3*1.05 -> 1498339.3 | D9: =1249588.28*1.05+10*1.05+11185.2*1.05 -> 1323822.7 | E9: =1268638.66*1.05 -> 1332070.6 | N9: =+SUM(B9:M9) -> 5409068
A10: Catering & Fairs | M10: 0 | N10: =+SUM(B10:M10) -> 0
A11: Less Tax | B11: =(B9+B10)/1.05*0.05 -> 59754.071 | C11: =(C9+C10)/1.05*0.05 -> 71349.489 | D11: =(D9+D10)/1.05*0.05 -> 63039.174 | E11: =(E9+E10)/1.05*0.05 -> 63431.933 | F11: =(F9+F10)/1.05*0.05 -> 0 | G11: =(G9+G10)/1.05*0.05 -> 0 | H11: =(H9+H10)/1.05*0.05 -> 0 | I11: =(I9+I10)/1.05*0.05 -> 0 | ... M11: =(M9+M10)/1.05*0.05 -> 0 | N11: =+SUM(B11:M11) -> 257574.67
A12: Less Commission | B12: =20130*1.18 -> 23753.4 | C12: =28497*1.18 -> 33626.46 | D12: =25788.55*1.18+(10143.26/0.18)*1.18 -> 96925.193 | E12: =33665.06*1.18+27118*1.18 -> 71724.011 | M12: 0 | N12: =+SUM(B12:M12) -> 226029.06
A13: Net Revenues from F&B Sales | B13: =B9+B10-B11-B12 -> 1171328 | C13: =C9+C10-C11-C12 -> 1393363.3 | D13: =D9+D10-D11-D12 -> 1163858.3 | E13: =E9+E10-E11-E12 -> 1196914.6 | F13: =F9+F10-F11-F12 -> 0 | G13: =G9+G10-G11-G12 -> 0 | H13: =H9+H10-H11-H12 -> 0 | I13: =I9+I10-I11-I12 -> 0 | ... M13: =M9+M10-M11-M12 -> 0 | N13: =sum(B13:M13) -> 4925464.3 | O13: =N13/$N$7 -> 32.609734
A14: F&B Cost | B14: =+B3+B4-B5-B7 -> 295424 | C14: =+C3+C4-C5-C7 -> 333656.57 | D14: =+D3+D4-D5-D7 -> 304101 | E14: =+E3+E4-E5-E7 -> 317469.7 | M14: =+M3+M4-M5-M7 -> 0 | N14: =sum(B14:M14) -> 1250651.3 | O14: =N14/$N$13 -> 0.25391541
A15: Electricity | B15: =167575.44+12000 -> 179575.44 | C15: 168988 | D15: =107461 -> 107461 | E15: 108000 | N15: =sum(B15:M15) -> 564024.44 | O15: =N15/$N$13 -> 0.11451193
A16: Telephone/Internet | B16: 1300 | C16: 1300 | D16: =350+942 -> 1292 | E16: =350+942 -> 1292 | N16: =sum(B16:M16) -> 5184 | O16: =N16/$N$13 -> 0.0010524896
A17: Gas | B17: 0 | C17: 0 | D17: 0 | E17: 0 | N17: =sum(B17:M17) -> 0 | O17: =N17/$N$13 -> 0
A18: Rent & Revenue Share | B18: =283200 -> 283200 | C18: =283200 -> 283200 | D18: =283200 -> 283200 | E18: =283200 -> 283200 | N18: =sum(B18:M18) -> 1132800 | O18: =N18/$N$13 -> 0.22998847
A19: Insurance | B19: 1250 | C19: =136716.74/8/12 -> 1424.1327 | D19: =136716.74/8/12 -> 1424.1327 | E19: =136716.74/8/12 -> 1424.1327 | F19: =136716.74/8/12 -> 1424.1327 | G19: =136716.74/8/12 -> 1424.1327 | H19: =136716.74/8/12 -> 1424.1327 | I19: =136716.74/8/12 -> 1424.1327 | J19: =136716.74/8/12 -> 1424.1327 | ... M19: =136716.74/8/12 -> 1424.1327 | N19: =sum(B19:M19) -> 16915.46 | O19: =N19/$N$13 -> 0.0034342874
A20: Software | B20: 5767 | C20: 5767 | D20: 5767 | E20: 5767 | N20: =sum(B20:M20) -> 23068 | O20: =N20/$N$13 -> 0.0046834163
A21: Staff Salary | B21: =335327 -> 335327 | C21: =343489.82+6000 -> 349489.82 | D21: =291729.55+6000 -> 297729.55 | E21: =305489.62+6000 -> 311489.62 | N21: =sum(B21:M21) -> 1294036 | O21: =N21/$N$13 -> 0.26272366
A22: AMC | B22: =4720 -> 4720 | C22: 4720 | D22: 4720 | E22: 4720 | N22: =sum(B22:M22) -> 18880 | O22: =N22/$N$13 -> 0.0038331412
A23: Subscription | B23: 0 | C23: 0 | D23: 0 | E23: =2840/3 -> 946.66667 | F23: =2840/3 -> 946.66667 | G23: =2840/3 -> 946.66667 | N23: =sum(B23:M23) -> 2840 | O23: =N23/$N$13 -> 0.00057659539
A24: Repairs & Maintenance | B24: 0 | C24: 0 | D24: 0 | E24: ='Misc Exp'!O43 -> 21076 | N24: =sum(B24:M24) -> 21076 | O24: =N24/$N$13 -> 0.0042789875
A25: Miscellaneous Expenses | B25: 2429.17 | C25: =7186.17 -> 7186.17 | D25: 12230 | E25: ='Misc Exp'!O37 -> 6375.51 | N25: =sum(B25:M25) -> 28220.85 | O25: =N25/$N$13 -> 0.0057295817
A26: CAM | B26: 0 | C26: 0 | D26: 0 | E26: 0 | N26: =sum(B26:M26) -> 0 | O26: =N26/$N$13 -> 0
A27: HO+CK Cost | B27: =HO!D42 -> 178085.63 | C27: =HO!H42 -> 202364.12 | D27: =HO!L42 -> 165987.65 | E27: =HO!P42 -> 171599.52 | M27: =HO!P72 -> #DIV/0! | N27: =sum(B27:M27) -> #DIV/0! | O27: =N27/$N$13 -> #DIV/0!
A28: Operating Expenses | B28: =+SUM(B14:B27) -> 1287078.2 | C28: =+SUM(C14:C27) -> 1358095.8 | D28: =+SUM(D14:D27) -> 1183912.3 | E28: =+SUM(E14:E27) -> 1233360.2 | F28: =+SUM(F14:F27) -> 2370.7994 | G28: =+SUM(G14:G27) -> 2370.7994 | H28: =+SUM(H14:H27) -> 1424.1327 | I28: =+SUM(I14:I27) -> 1424.1327 | ... M28: =+SUM(M14:M27) -> #DIV/0! | N28: =sum(B28:M28) -> #DIV/0! | O28: =N28/$N$13 -> #DIV/0!
A29: Store Level EBITDA | B29: =B13-B28 -> -115750.21 | C29: =C13-C28 -> 35267.515 | D29: =D13-D28 -> -20054.045 | E29: =E13-E28 -> -36445.503 | F29: =F13-F28 -> -2370.7994 | G29: =G13-G28 -> -2370.7994 | H29: =H13-H28 -> -1424.1327 | I29: =I13-I28 -> -1424.1327 | ... M29: =M13-M28 -> #DIV/0! | N29: =sum(B29:M29) -> #DIV/0! | O29: =N29/$N$13 -> #DIV/0!
A30: Food Cost | B30: =(B14/B13) -> 0.25221287 | C30: =(C14/C13) -> 0.23946128 | D30: =(D14/D13) -> 0.26128697 | E30: =(E14/E13) -> 0.26524005 | F30: =(F14/F13) -> #DIV/0! | G30: =(G14/G13) -> #DIV/0! | H30: =(H14/H13) -> #DIV/0! | I30: =(I14/I13) -> #DIV/0! | ... M30: =(M14/M13) -> #DIV/0!
B32: =B29+B27 -> 62335.42 | C32: =C29+C27 -> 237631.64 | D32: =D29+D27 -> 145933.6 | E32: =E29+E27 -> 135154.02 | F32: =F29+F27 -> -2370.7994 | G32: =G29+G27 -> -2370.7994 | H32: =H29+H27 -> -1424.1327 | I32: =I29+I27 -> -1424.1327 | ... L32: =L29+L27 -> -1424.1327
B33: =B32/B13 -> 0.053217731 | C33: =C32/C13 -> 0.17054535 | D33: =D32/D13 -> 0.12538778 | E33: =E32/E13 -> 0.11291868 | F33: =F32/F13 -> #DIV/0! | G33: =G32/G13 -> #DIV/0! | H33: =H32/H13 -> #DIV/0! | I33: =I32/I13 -> #DIV/0! | ... L33: =L32/L13 -> #DIV/0!

Sheet Ads Account
A1: Dosa Coffee - NCR | B1: 46113 | C1: 46143 | D1: 46174 | E1: 46204 | F1: 46235 | G1: 46266 | H1: 46296 | I1: 46327 | J1: 46357 | K1: 46388 | L1: 46419 | M1: 46447 | N1: FY 25-26
A2: Advertisement & Promotion | N2: =+SUM(B2:M2) -> 0
A3: - Team
A4: - Social Media/Digital Media | B4: =20000 -> 20000 | D4: 0 | E4: =40900+35400 -> 76300
A5: - Print Media | C5: =91462 -> 91462 | E5: 37760
A6: - Radio
A7: - Public Relations
A8: - Influencers | B8: =100000+70000 -> 170000 | C8: =64940 -> 64940 | D8: =(4000+45400+26000+40000+78000)/2 -> 96700 | E8: =21000+40000+15000+77800+10000 -> 163800
A9: - POP Materials | E9: 52840
A10: - Photo and Video Shoot
A11: - Website
A12: - Competitions and Give Aways
A13: - Reelo Campaign | B13: =151653.85/12+43429/12+(21664.84+86659.34)/12 -> 25283.919 | C13: =151653.85/12+43429/12+(21664.84+86659.34)/12 -> 25283.919 | D13: =151653.85/12+43429/12+(21664.84+86659.34)/12 -> 25283.919 | E13: =151653.85/12+43429/12+(21664.84+86659.34)/12 -> 25283.919 | F13: =151653.85/12+43429/12+(21664.84+86659.34)/12 -> 25283.919 | G13: =151653.85/12+43429/12+(21664.84+86659.34)/12 -> 25283.919 | H13: =151653.85/12+43429/12+(21664.84+86659.34)/12 -> 25283.919 | I13: =151653.85/12+43429/12+(21664.84+86659.34)/12 -> 25283.919 | ... M13: =151653.85/12+43429/12+(21664.84+86659.34)/12 -> 25283.919
A14: - Misc. & Others
A15: - Zomato | B15: =33628+40414.59+120853.87*1.18+142583.32*1.18 -> 384898.47 | C15: =74450.76*1.18+137927.47*1.18+150718.92*1.18 -> 428454.64 | D15: =72661.33*1.18+150879.52*1.18+149368.31*1.18 -> 440032.81 | E15: =67716.56*1.18+141498.95*1.18+142373*1.18 -> 414874.44
A16: - Swiggy | B16: =23658.94*1.18+42996.23*1.18+76750.38*1.18 -> 169218.55 | C16: =198494.88 -> 198494.88 | D16: =18341.75*1.18+15748.96*1.18+50531*1.18 -> 99853.618 | E16: =31643*1.18+51638*1.18+106924*1.18 -> 224441.9
A17: Total | B17: =sum(B3:B16) -> 769400.94 | C17: =sum(C3:C16) -> 808635.44 | D17: =sum(D3:D16) -> 661870.35 | E17: =sum(E3:E16) -> 995300.26 | F17: =sum(F3:F16) -> 25283.919 | G17: =sum(G3:G16) -> 25283.919 | H17: =sum(H3:H16) -> 25283.919 | I17: =sum(I3:I16) -> 25283.919 | ... M17: =sum(M3:M16) -> 25283.919
C19: =71669.02*1.18+122654.94*1.18+195931.22*1.18 -> 460501.11

Sheet CK
A1: Capital Deployed
B2: 45748 | C2: 45778 | D2: 45809 | E2: 45839 | F2: 45870 | G2: 45901 | H2: 45931 | I2: 45962 | J2: 45992 | K2: 46023 | L2: 46054 | M2: 46082 | N2: FY 2024-25
A3: Food Cost Calculation
A4: Opening Stock | B4: 1311694 | C4: =B7 -> 1493885 | D4: =C7 -> 1493731.5 | E4: =D7 -> 2136551.7 | F4: =E7 -> 1770515.8 | G4: =F7 -> 1718087.3 | H4: =G7 -> 1724491.4 | I4: =H7 | J4: =I7 | ... M4: =L7
A5: Purchases Food (Less Purchase Return) | B5: =6160112 -> 6160112 | C5: =6596192.24 -> 6596192.2 | D5: =7115590.9+39776 -> 7155366.9 | E5: =6016020-38765 -> 5977255 | F5: =6865239.71 -> 6865239.7 | G5: =6345527.51 -> 6345527.5 | N5: =SUM(B5:M5) -> 39099693
A6: Transferred Out | B6: 6080124 | C6: =6736750.78-186270-304531 -> 6245949.8 | D6: 6406016 | E6: 6128496.9 | F6: 6520635.7 | G6: =6427854 -> 6427854 | N6: =SUM(B6:M6) -> 37809076
A7: Closing Stock | B7: =1294571+199314 -> 1493885 | C7: =1317687.46+176044 -> 1493731.5 | D7: =1836700.73+299850.96 -> 2136551.7 | E7: =1475927+294588.83 -> 1770515.8 | F7: =1483159.28+234928 -> 1718087.3 | G7: =1489757.43+234734 -> 1724491.4
A9: Consumption | B9: =B4+B5-B6-B7 -> -102203 | C9: =C4+C5-C6-C7 -> 350396 | D9: =D4+D5-D6-D7 -> 106530.67 | E9: =E4+E5-E6-E7 -> 214793.98 | F9: =F4+F5-F6-F7 -> 397032.58 | G9: =G4+G5-G6-G7 -> -88730.64 | H9: =H4+H5-H6-H7 -> 1724491.4 | I9: =I4+I5-I6-I7 -> 0 | ... M9: =M4+M5-M6-M7 -> 0 | N9: =sum(B9:M9) -> 2602311
A10: Wastage | B10: =16504+83736 -> 100240 | C10: =12434+53649 -> 66083 | D10: =39540+17668 -> 57208 | E10: 16125 | F10: =7433.7+25305 -> 32738.7 | G10: =2791+23092 -> 25883 | N10: =sum(B10:M10) -> 298277.7
A11: Electricity | B11: =3010+218510 -> 221520 | C11: 213600 | D11: =215000+7210 -> 222210 | E11: 241300 | N11: =sum(B11:M11) -> 898630
A12: Water Supply Charges | B12: =60000 -> 60000 | C12: 48000 | D12: 46500 | E12: 46500 | N12: =sum(B12:M12) -> 201000
A13: Telephone/Internet | B13: =198+600+600 -> 1398 | C13: 2859 | D13: =3536+600 -> 4136 | E13: =600 -> 600 | N13: =sum(B13:M13) -> 8993
A14: Gas | B14: =148024.88 -> 148024.88 | C14: 172236 | D14: 166790 | E14: 178887 | N14: =sum(B14:M14) -> 665937.88
A15: Insurance & licenses | B15: 3551.83 | C15: =136716.74/8/12 -> 1424.1327 | D15: =136716.74/8/12 -> 1424.1327 | E15: =136716.74/8/12 -> 1424.1327 | F15: =136716.74/8/12 -> 1424.1327 | G15: =136716.74/8/12 -> 1424.1327 | H15: =136716.74/8/12 -> 1424.1327 | I15: =136716.74/8/12 -> 1424.1327 | J15: =136716.74/8/12 -> 1424.1327 | ... M15: =136716.74/8/12 -> 1424.1327 | N15: =sum(B15:M15) -> 19217.29
A16: Rent & CAM | B16: =299219 -> 299219 | C16: =299219 -> 299219 | D16: =299219 -> 299219 | E16: 303555 | N16: =sum(B16:M16) -> 1201212
A17: Software | B17: 8353 | C17: 8353 | D17: 8353 | E17: 8353 | N17: =sum(B17:M17) -> 33412
A18: Staff Salary | B18: =697502+22000+3372+22420 -> 745294 | C18: =716273.43+22420+22000 -> 760693.43 | D18: =718396.31+22000+22420 -> 762816.31 | E18: =708714.66+22000+16439 -> 747153.66 | N18: =sum(B18:M18) -> 3015957.4
A19: Staff Welfare | B19: 0 | C19: 0 | D19: 0 | E19: 0 | N19: =sum(B19:M19) -> 0
A20: Repairs & Maintenance | B20: 124056 | C20: 153117.64 | D20: 74971 | E20: ='Misc Exp'!P43 -> 113838 | N20: =sum(B20:M20) -> 465982.64
A21: Membership & Subscription | B21: 0 | C21: 0 | D21: 0 | N21: =sum(B21:M21) -> 0
A22: AMC | B22: =14160+7080 -> 21240 | C22: =14160+7080 -> 21240 | D22: =14160+17700/2 -> 23010 | E22: =14160+17700/2 -> 23010 | N22: =sum(B22:M22) -> 88500
A23: Miscellaneous Expenses | B23: 163516 | C23: =246583 -> 246583 | D23: =220454 -> 220454 | E23: ='Misc Exp'!P37 -> 259111 | N23: =sum(B23:M23) -> 889664
A24: Conveyance | B24: 0 | C24: 0 | D24: 0 | N24: =sum(B24:M24) -> 0
A25: Transport Charges | B25: =133694+285946.5 -> 419640.5 | C25: =127794+185060 -> 312854 | D25: =165436+171778 -> 337214 | E25: =194582+(170488+2730) -> 367800 | N25: =sum(B25:M25) -> 1437508.5
A26: Operating Expenses | B26: =SUM(B10:B25) -> 2316053.2 | C26: =SUM(C10:C25) -> 2306262.2 | D26: =SUM(D10:D25) -> 2224305.4 | E26: =SUM(E10:E25) -> 2307656.8 | F26: =SUM(F10:F25) -> 34162.833 | G26: =SUM(G11:G25) -> 1424.1327 | H26: =SUM(H11:H25) -> 1424.1327 | I26: =SUM(I11:I25) -> 1424.1327 | J26: =SUM(J11:J25) -> 1424.1327 | K26: =SUM(K11:K25) -> 1424.1327 | L26: =SUM(L11:L25) -> 1424.1327 | M26: =SUM(M11:M25) -> 1424.1327 | N26: =sum(B26:M26) -> 9198409.4

Sheet Misc Expenses
B1: Paschim Vihar | C1: Okhla | D1: Rohini | E1: Kalkaji | F1: Pacific Mall | G1: CP | H1: Model Town | I1: Faridabad | J1: DLF | K1: Huda Market | L1: Noida Sec 18 | M1: Noida Sec 143 | N1: Head office | O1: Total
A2: Actual
A3: Travelling Expenses | B3: 0 | C3: 0 | D3: 0 | E3: 0 | F3: 0 | G3: 0 | H3: 0 | I3: 8136 | J3: 491 | K3: 5181 | L3: 0 | M3: 0 | N3: 0 | O3: =sum(B3:N3) -> 13808
A4: Motor car Expenses | B4: 0 | C4: 0 | D4: 0 | E4: 0 | F4: 0 | G4: 0 | H4: 0 | I4: 0 | J4: 0 | K4: 0 | L4: 0 | M4: 0 | N4: 0 | O4: =sum(B4:N4) -> 0
A5: Freight Charges | C5: 12634 | E5: 682 | F5: 367 | N5: 160 | O5: =sum(B5:N5) -> 13843
A6: Professional Fees | K6: 21240 | L6: 21240 | O6: =sum(B6:N6) -> 42480
A7: Parking Expenses | C7: 22750 | F7: 3150 | O7: =sum(B7:N7) -> 25900
A8: Merchant Funded Promotion | I8: 713.68 | J8: 302.4 | K8: 1029.13 | L8: 2195.37 | M8: 1907.67 | O8: =sum(B8:N8) -> 6148.25
A9: Customer Compensation | I9: 1080.71 | J9: 1715.6 | K9: 2816 | L9: 1238 | M9: 1271 | O9: =sum(B9:N9) -> 8121.31
A10: Round Up | N10: 527.23 | O10: =sum(B10:N10) -> 527.23
A11: Staff Welfare | I11: 1400 | J11: 2950 | K11: 1400 | L11: 4455 | M11: 1000 | O11: =sum(B11:N11) -> 11205
A12: Maintenance Expenses | B12: 4562 | C12: 4562 | D12: 4562 | E12: 4562 | F12: 4562 | G12: 4562 | H12: 4562 | O12: =sum(B12:N12) -> 31934
A13: Staff Electricity | K13: 800 | O13: =sum(B13:N13) -> 800
A14: DG Charges | L14: 1900 | O14: =sum(B14:N14) -> 1900
A15: Local Authority Expenses | B15: 5000 | C15: 700 | D15: 3000 | E15: 3000 | G15: 5000 | H15: 4000 | L15: 4000 | O15: =sum(B15:N15) -> 24700
A16: Travelling Expense | B16: 95 | C16: 2367 | D16: 7770 | E16: 9400 | F16: 2630 | G16: 4721 | H16: 200 | L16: 7353 | O16: =sum(B16:N16) -> 34536
A17: Staff Welfare Expenses | B17: 1014 | C17: 4840 | D17: 900 | E17: 529 | F17: 1818 | G17: 5047 | H17: 1500 | O17: =sum(B17:N17) -> 15648
A18: Swiggy Cancellation Charges | I18: 1975 | J18: 325 | K18: 3634 | L18: 1136 | M18: 1213 | O18: =sum(B18:N18) -> 8283
A19: Credit Card Settlement Charges | B19: 1494.19 | D19: 2804.19 | E19: 915.02 | F19: 3924 | G19: 167.53 | H19: 1393.4 | I19: 933.66 | J19: 2500.53 | K19: 3427.31 | L19: 9458.88 | M19: 1304 | O19: =sum(B19:N19) -> 28322.71
A20: General Expenses | B20: 70 | C20: 160 | D20: 5019 | E20: 1156 | F20: 3467 | G20: 1070 | H20: 3175 | L20: 570 | M20: 413 | O20: =sum(B20:N20) -> 15100
A21: House Keeping Charges | B21: 1000 | C21: 9000 | D21: 2300 | E21: 1400 | G21: 3609 | H21: 4000 | I21: 6986 | K21: 3300 | L21: 3963 | M21: 779 | N21: 150 | O21: =sum(B21:N21) -> 36487
A22: Printing & Stationery | B22: 515 | C22: 25550 | D22: 645 | E22: 1239 | F22: 1360 | G22: 2942 | H22: 600 | I22: 970 | J22: 870 | K22: 815 | L22: 700 | M22: 1210 | O22: =sum(B22:N22) -> 37416
A23: General Expenses | I23: 1300 | J23: 661 | K23: 3662 | O23: =sum(B23:N23) -> 5623
A24: Bank Charges | I24: 196.66 | J24: 1227.52 | K24: 1183.95 | L24: 657.33 | M24: 299.85 | O24: =sum(B24:N24) -> 3565.31
B25: =sum(B2:B24) -> 13750.19 | C25: =sum(C2:C24) -> 82563 | D25: =sum(D2:D24) -> 27000.19 | E25: =sum(E2:E24) -> 22883.02 | F25: =sum(F2:F24) -> 21278 | G25: =sum(G2:G24) -> 27118.53 | H25: =sum(H2:H24) -> 19430.4 | I25: =sum(I2:I24) -> 23691.71 | ... O25: =sum(O2:O24) -> 366347.81
A28: Repairs & Maintenance
A29: Repairs & Maintenance
A30: - Petty Cash Expenses | O30: -
A31: Repairs & Maintenance - Plant | B31: 7846 | C31: =5192+24072+225+400+5739+8354+11186+802+17708 -> 73678 | D31: 24576 | E31: 11605 | F31: 5930 | G31: 33346 | H31: 14602 | I31: 15099 | J31: 5260 | K31: 5357 | L31: 10980 | M31: 8800 | N31: 0 | O31: =sum(B31:N31) -> 217079
B32: =sum(B30:B31) -> 7846 | C32: =sum(C30:C31) -> 73678 | D32: =sum(D30:D31) -> 24576 | E32: =sum(E30:E31) -> 11605 | F32: =sum(F30:F31) -> 5930 | G32: =sum(G30:G31) -> 33346 | H32: =sum(H30:H31) -> 14602 | I32: =sum(I30:I31) -> 15099 | ... N32: =sum(N30:N31) -> 0 | O32: =sum(O31) -> 217079

Sheet HO
A1: t
A2: Head Office Expenses | B2: 46113 | C2: 46143 | D2: 46174 | E2: 46204 | F2: 46235 | G2: 46266 | H2: 46296 | I2: 46327 | J2: 46357 | K2: 46388 | L2: 46419 | M2: 46447 | N2: FY 2024-25
A3: Central Kitchen Expenses | B3: =CK!B26 -> 2316053.2 | C3: =CK!C26 -> 2306262.2 | D3: =CK!D26 -> 2224305.4 | E3: =CK!E26 -> 2307656.8 | F3: =CK!F26 -> 34162.833 | G3: =CK!G26 -> 1424.1327 | H3: =CK!H26 -> 1424.1327 | I3: =CK!I26 -> 1424.1327 | ... M3: =CK!M26 -> 1424.1327 | N3: =sum(B3:M3) -> 9198409.4
A4: Guest House Expenses | B4: =24780+24780+150+2428+3000+3834/12 -> 55457.5 | C4: =24780+24780+150+2428+3000+4050+3834/12 -> 59507.5 | D4: =24780+24780+150+2428+3000+7210+3834/12 -> 62667.5 | E4: =49560+3834/12+150+2528+3000 -> 55557.5 | F4: =3834/12 -> 319.5 | G4: =3834/12 -> 319.5 | H4: =3834/12 -> 319.5 | I4: =3834/12 -> 319.5 | J4: =3834/12 -> 319.5 | K4: =3834/12 -> 319.5 | L4: =3834/12 -> 319.5 | M4: =3834/12 -> 319.5 | N4: =sum(B4:M4) -> 235746 | R4: =961892/7 -> 137413.14
A5: Delhi Office Rent & Electricity | B5: =55755 -> 55755 | C5: =55755 -> 55755 | D5: =55755 -> 55755 | E5: =55755 -> 55755 | N5: =sum(B5:M5) -> 223020
A6: General Expenses | N6: =sum(B6:M6) -> 0
A7: Insurance Premium | N7: =sum(B7:M7) -> 0
A8: Telephone Expenses | N8: =sum(B8:M8) -> 0
A9: Head Office Salary | B9: =408176+126576+89419+144395 -> 768566 | C9: =547799.47+144395+89419 -> 781613.47 | D9: =417992.54+129806.93+30000+90000 -> 667799.47 | E9: =417992.54+144455.43 -> 562447.97 | N9: =sum(B9:M9) -> 2780426.9
A10: Leave Encashment | N10: =sum(B10:M10) -> 0
A11: Miscellaneous Expenses | B11: =33713.83 -> 33713.83 | C11: =60248.72 -> 60248.72 | D11: 92966 | E11: ='Misc Exp'!Q37 -> 52215.45 | N11: =sum(B11:M11) -> 239144
A12: Motor Car Expenses & Fuel | N12: =sum(B12:M12) -> 0
A13: Office Expenses | N13: =sum(B13:M13) -> 0
A14: Professional and Consultancy Fees | N14: =sum(B14:M14) -> 0
A15: Mystery Audit | B15: =22000 -> 22000 | C15: =22000 -> 22000 | D15: 22000 | E15: 22000
A16: Printing & Stationary | N16: =sum(B16:M16) -> 0
A17: Repair & Maintenance | N17: =sum(B17:M17) -> 0
A18: Software Charges | B18: =151635/12 -> 12636.25 | C18: =151635/12 -> 12636.25 | D18: =151635/12 -> 12636.25 | E18: =151635/12 -> 12636.25 | F18: =151635/12 -> 12636.25 | G18: =151635/12 -> 12636.25 | H18: =151635/12 -> 12636.25 | I18: =151635/12 -> 12636.25 | ... M18: =151635/12 -> 12636.25 | N18: =sum(B18:M18) -> 151635
A19: Staff Incentive | N19: =sum(B19:M19) -> 0
A20: Staff Food & Perks | N20: =sum(B20:M20) -> 0
A21: Subscription & Membership | N21: =sum(B21:M21) -> 0
A22: Transportation and Labour | N22: =sum(B22:M22) -> 0
A23: Travelling and Conveyance | N23: =sum(B23:M23) -> 0
A24: Other Sales | B24: -9446.4 | C24: 0 | D24: -7023 | E24: -7822 | N24: =sum(B24:M24) -> -24291.4
N25: =sum(B25:M25) -> 0
A26: Total HO Expenses | B26: =+SUM(B3:B24) -> 3254735.4 | C26: =+SUM(C3:C24) -> 3298023.1 | D26: =+SUM(D3:D24) -> 3131106.7 | E26: =+SUM(E3:E24) -> 3060447 | F26: =+SUM(F3:F24) -> 47118.583 | G26: =+SUM(G3:G24) -> 14379.883 | H26: =+SUM(H3:H23) -> 14379.883 | I26: =+SUM(I3:I23) -> 14379.883 | J26: =+SUM(J3:J23) -> 14379.883 | K26: =+SUM(K3:K23) -> 14379.883 | L26: =+SUM(L3:L24) -> 14379.883 | M26: =+SUM(M3:M24) -> 14379.883
B28: Apr'2026 | C28: % Sales Dist | D28: % Dist (HO) | F28: May'2026 | G28: % Sales Dist | H28: % Dist (HO) | J28: June'2025 | K28: % Sales Dist | L28: % Dist (HO) | N28: July'2025 | O28: % Sales Dist | P28: % Dist (HO)
A29: Noida Sector 18 | B29: ='Noida Sec - 18'!B13 -> 1723585 | C29: =B29/$B$43 -> 0.080513252 | D29: =$B$26*C29 -> 262049.33 | F29: ='Noida Sec - 18'!C13 -> 1987870.8 | G29: =F29/$F$43 -> 0.087539406 | H29: =G29*$C$26 -> 288706.99 | J29: ='Noida Sec - 18'!D13 -> 1852189.2 | K29: =J29/$J$43 -> 0.084365165 | L29: =$D$26*K29 -> 264156.33 | N29: ='Noida Sec - 18'!E13 -> 1843290.5 | O29: =N29/$N$43 -> 0.086349896 | P29: =O29*$E$26 -> 264269.28
A30: Noida Sector 143 | B30: ='Noida Sec -143'!B13 -> 947119.25 | C30: =B30/$B$43 -> 0.044242465 | D30: =$B$26*C30 -> 143997.52 | F30: ='Noida Sec -143'!C13 -> 1045825.3 | G30: =F30/$F$43 -> 0.046054767 | H30: =G30*$C$26 -> 151889.69 | J30: ='Noida Sec -143'!D13 -> 845448.08 | K30: =J30/$J$43 -> 0.038509222 | L30: =$D$26*K30 -> 120576.48 | N30: ='Noida Sec -143'!E13 -> 909729.82 | O30: =N30/$N$43 -> 0.042616764 | P30: =O30*$E$26 -> 130426.35
A31: Faridabad Sector 15 | B31: ='Faridabad Sec15'!B13 -> 881529.11 | C31: =B31/$B$43 -> 0.041178575 | D31: =$B$26*C31 -> 134025.37 | F31: ='Faridabad Sec15'!C13 -> 983842.37 | G31: =F31/$F$43 -> 0.043325239 | H31: =G31*$C$26 -> 142887.64 | J31: ='Faridabad Sec15'!D13 -> 1022441.2 | K31: =J31/$J$43 -> 0.046571063 | L31: =$D$26*K31 -> 145818.97 | N31: ='Faridabad Sec15'!E13 -> 895692.11 | O31: =N31/$N$43 -> 0.04195916 | P31: =O31*$E$26 -> 128413.78
A32: DLF | B32: =DLF!B13 -> 1720611.3 | C32: =B32/$B$43 -> 0.080374342 | D32: =$B$26*C32 -> 261597.22 | F32: =DLF!C13 -> 1648471 | G32: =F32/$F$43 -> 0.072593334 | H32: =G32*$C$26 -> 239414.5 | J32: =DLF!D13 -> 1596762.3 | K32: =J32/$J$43 -> 0.072730752 | L32: =$D$26*K32 -> 227727.74 | N32: =DLF!E13 -> 1683795.4 | O32: =N32/$N$43 -> 0.078878265 | P32: =O32*$E$26 -> 241402.75
A33: Huda Market | B33: ='Gurgaon Sec-15'!B13 -> 1904054.3 | C33: =B33/$B$43 -> 0.088943452 | D33: =$B$26*C33 -> 289487.4 | F33: ='Gurgaon Sec-15'!C13 -> 2270266.9 | G33: =F33/$F$43 -> 0.099975218 | H33: =G33*$C$26 -> 329720.58 | J33: ='Gurgaon Sec-15'!D13 -> 1805549.4 | K33: =J33/$J$43 -> 0.082240775 | L33: =$D$26*K33 -> 257504.64 | N33: ='Gurgaon Sec-15'!E13 -> 1687622.2 | O33: =N33/$N$43 -> 0.079057537 | P33: =O33*$E$26 -> 241951.4
A34: Sector 10 | B34: ='Gurgaon Sec - 10'!B13 -> 662481.06 | C34: =B34/$B$43 -> 0.030946257 | D34: =$B$26*C34 -> 100721.88 | F34: ='Gurgaon Sec - 10'!C13 -> 701542.56 | G34: =F34/$F$43 -> 0.030893667 | H34: =G34*$C$26 -> 101888.03 | J34: ='Gurgaon Sec - 10'!D13 -> 620725.44 | K34: =J34/$J$43 -> 0.028273355 | L34: =$D$26*K34 -> 88526.891 | N34: ='Gurgaon Sec - 10'!E13 -> 535046.14 | O34: =N34/$N$43 -> 0.025064513 | P34: =O34*$E$26 -> 76708.614
A35: Sector 31 | B35: 0 | C35: 0 | D35: =$B$26*C35 -> 0 | F35: ='Gurgaon Sector 31'!C13 -> 56291.473 | G35: =F35/$F$43 -> 0.0024788945 | H35: =G35*$C$26 -> 8175.4516 | J35: ='Gurgaon Sector 31'!D13 -> 697343.69 | K35: =J35/$J$43 -> 0.031763232 | L35: =$D$26*K35 -> 99454.067 | N35: ='Gurgaon Sector 31'!E13 -> 988619.79 | O35: =N35/$N$43 -> 0.046312405 | P35: =O35*$E$26 -> 141736.66
A36: Paschim Vihar | B36: ='Paschim Vihar'!B13 -> 1200997.4 | C36: =B36/$B$43 -> 0.056101792 | D36: =$B$26*C36 -> 182596.49 | F36: ='Paschim Vihar'!C13 -> 1227695.7 | G36: =F36/$F$43 -> 0.054063752 | H36: =G36*$C$26 -> 178303.51 | J36: ='Paschim Vihar'!D13 -> 1067249.7 | K36: =J36/$J$43 -> 0.048612039 | L36: =$D$26*K36 -> 152209.48 | N36: ='Paschim Vihar'!E13 -> 1018211.9 | O36: =N36/$N$43 -> 0.047698662 | P36: =O36*$E$26 -> 145979.23
A37: Kalkaji | B37: =Kalkaji!B13 -> 1314817.5 | C37: =B37/$B$43 -> 0.061418631 | D37: =$B$26*C37 -> 199901.39 | F37: =Kalkaji!C13 -> 1494375.9 | G37: =F37/$F$43 -> 0.065807487 | H37: =G37*$C$26 -> 217034.62 | J37: =Kalkaji!D13 -> 1327281.9 | K37: =J37/$J$43 -> 0.060456218 | L37: =$D$26*K37 -> 189294.87 | N37: =Kalkaji!E13 -> 1335642.1 | O37: =N37/$N$43 -> 0.062568845 | P37: =O37*$E$26 -> 191488.63
A38: Connaught Place | B38: =CP!B13 -> 3809349.7 | C38: =B38/$B$43 -> 0.17794488 | D38: =$B$26*C38 -> 579163.5 | F38: =CP!C13 -> 3512452 | G38: =F38/$F$43 -> 0.15467703 | H38: =G38*$C$26 -> 510128.44 | J38: =CP!D13 -> 3794796 | K38: =J38/$J$43 -> 0.17284875 | L38: =$D$26*K38 -> 541207.87 | N38: =CP!E13 -> 3424226.8 | O38: =N38/$N$43 -> 0.16040968 | P38: =O38*$E$26 -> 490925.31
A39: Rohini | B39: =Rohini!B13 -> 1872584.8 | C39: =B39/$B$43 -> 0.087473429 | D39: =$B$26*C39 -> 284702.86 | F39: =Rohini!C13 -> 2055416.6 | G39: =F39/$F$43 -> 0.090513904 | H39: =G39*$C$26 -> 298516.95 | J39: =Rohini!D13 -> 2005516.5 | K39: =J39/$J$43 -> 0.091349053 | L39: =$D$26*K39 -> 286023.63 | N39: =Rohini!E13 -> 1885066.4 | O39: =N39/$N$43 -> 0.088306911 | P39: =O39*$E$26 -> 270258.62
A40: Model Town | B40: ='Model Town'!B13 -> 2125470.7 | C40: =B40/$B$43 -> 0.099286401 | D40: =$B$26*C40 -> 323150.96 | F40: ='Model Town'!C13 -> 2056974.2 | G40: =F40/$F$43 -> 0.090582495 | H40: =G40*$C$26 -> 298743.17 | J40: ='Model Town'!D13 -> 1801326.6 | K40: =J40/$J$43 -> 0.082048428 | L40: =$D$26*K40 -> 256902.38 | N40: ='Model Town'!E13 -> 1733044.5 | O40: =N40/$N$43 -> 0.081185367 | P40: =O40*$E$26 -> 248463.51
A41: Pacific Mall | B41: ='Pacific Mall'!B13 -> 2073541.8 | C41: =B41/$B$43 -> 0.096860667 | D41: =$B$26*C41 -> 315255.84 | F41: ='Pacific Mall'!C13 -> 2273908.5 | G41: =F41/$F$43 -> 0.10013558 | H41: =G41*$C$26 -> 330249.47 | J41: ='Pacific Mall'!D13 -> 2353943 | K41: =J41/$J$43 -> 0.10721949 | L41: =$D$26*K41 -> 335715.67 | N41: ='Pacific Mall'!E13 -> 2209857.4 | O41: =N41/$N$43 -> 0.10352191 | P41: =O41*$E$26 -> 316823.32
A42: Shalimar Bagh | B42: ='Shalimar Bagh'!B13 -> 1171328 | C42: =B42/$B$43 -> 0.054715855 | D42: =$B$26*C42 -> 178085.63 | F42: ='Shalimar Bagh'!C13 -> 1393363.3 | G42: =F42/$F$43 -> 0.061359218 | H42: =G42*$C$26 -> 202364.12 | J42: ='Shalimar Bagh'!D13 -> 1163858.3 | K42: =J42/$J$43 -> 0.053012454 | L42: =$D$26*K42 -> 165987.65 | N42: ='Shalimar Bagh'!E13 -> 1196914.6 | O42: =N42/$N$43 -> 0.056070086 | P42: =O42*$E$26 -> 171599.52
B43: =sum(B29:B42) -> 21407470 | C43: =sum(C29:C41) -> 0.94528415 | D43: =sum(D29:D42) -> 3254735.4 | F43: =sum(F29:F42) -> 22708297 | G43: =sum(G29:G41) -> 0.93864078 | H43: =sum(H29:H42) -> 3298023.1 | J43: =sum(J29:J42) -> 21954431 | K43: =sum(K29:K41) -> 0.94698755 | L43: =sum(L29:L42) -> 3131106.7 | N43: =sum(N29:N42) -> 21346760 | P43: =sum(P29:P42) -> 3060447 | R43: =L43-D26 -> 4.6566129e-10
B44: Aug'2025 | C44: % Sales Dist | D44: % Dist (HO) | F44: Sep'2025 | G44: % Sales Dist | H44: % Dist (HO) | J44: Oct'2025 | K44: % Sales Dist | L44: % Dist (HO) | N44: Nov'2025 | O44: % Sales Dist | P44: % Dist (HO)
A45: Noida Sector 18 | B45: ='Noida Sec - 18'!F13 -> 0 | C45: =B45/$B$58 -> #DIV/0! | D45: =C45*$F$26 -> #DIV/0! | F45: ='Noida Sec - 18'!G13 -> 0 | G45: =F45/$F$58 -> #DIV/0! | H45: =G45*$G$26 -> #DIV/0! | J45: ='Noida Sec - 18'!H13 -> 0 | K45: =J45/$J$58 -> #DIV/0! | L45: =K45*$H$26 -> #DIV/0! | N45: ='Noida Sec - 18'!I13 -> 0 | O45: =N45/$N$58 -> #DIV/0! | P45: =O45*$I$26 -> #DIV/0!
A46: Noida Sector 143 | B46: ='Noida Sec -143'!F13 -> 0 | C46: =B46/$B$58 -> #DIV/0! | D46: =C46*$F$26 -> #DIV/0! | F46: ='Noida Sec -143'!G13 -> 0 | G46: =F46/$F$58 -> #DIV/0! | H46: =G46*$G$26 -> #DIV/0! | J46: ='Noida Sec -143'!H13 -> 0 | K46: =J46/$J$58 -> #DIV/0! | L46: =K46*$H$26 -> #DIV/0! | N46: ='Noida Sec -143'!I13 -> 0 | O46: =N46/$N$58 -> #DIV/0! | P46: =O46*$I$26 -> #DIV/0!
A47: Faridabad Sector 15 | B47: ='Faridabad Sec15'!F13 -> 0 | C47: =B47/$B$58 -> #DIV/0! | D47: =C47*$F$26 -> #DIV/0! | F47: ='Faridabad Sec15'!G13 -> 0 | G47: =F47/$F$58 -> #DIV/0! | H47: =G47*$G$26 -> #DIV/0! | J47: ='Faridabad Sec15'!H13 -> 0 | K47: =J47/$J$58 -> #DIV/0! | L47: =K47*$H$26 -> #DIV/0! | N47: ='Faridabad Sec15'!I13 -> 0 | O47: =N47/$N$58 -> #DIV/0! | P47: =O47*$I$26 -> #DIV/0!
A48: DLF | B48: =DLF!F13 -> 0 | C48: =B48/$B$58 -> #DIV/0! | D48: =C48*$F$26 -> #DIV/0! | F48: =DLF!G13 -> 0 | G48: =F48/$F$58 -> #DIV/0! | H48: =G48*$G$26 -> #DIV/0! | J48: =DLF!H13 -> 0 | K48: =J48/$J$58 -> #DIV/0! | L48: =K48*$H$26 -> #DIV/0! | N48: =DLF!I13 -> 0 | O48: =N48/$N$58 -> #DIV/0! | P48: =O48*$I$26 -> #DIV/0!
A49: Huda Market | B49: ='Gurgaon Sec-15'!F13 -> 0 | C49: =B49/$B$58 -> #DIV/0! | D49: =C49*$F$26 -> #DIV/0! | F49: ='Gurgaon Sec-15'!G13 -> 0 | G49: =F49/$F$58 -> #DIV/0! | H49: =G49*$G$26 -> #DIV/0! | J49: ='Gurgaon Sec-15'!H13 -> 0 | K49: =J49/$J$58 -> #DIV/0! | L49: =K49*$H$26 -> #DIV/0! | N49: ='Gurgaon Sec-15'!I13 -> 0 | O49: =N49/$N$58 -> #DIV/0! | P49: =O49*$I$26 -> #DIV/0!
A50: Paschim Vihar | B50: ='Paschim Vihar'!F13 -> 0 | C50: =B50/$B$58 -> #DIV/0! | D50: =C50*$F$26 -> #DIV/0! | F50: ='Paschim Vihar'!G13 -> 0 | G50: =F50/$F$58 -> #DIV/0! | H50: =G50*$G$26 -> #DIV/0! | J50: ='Paschim Vihar'!H13 -> 0 | K50: =J50/$J$58 -> #DIV/0! | L50: =K50*$H$26 -> #DIV/0! | N50: ='Paschim Vihar'!I13 -> 0 | O50: =N50/$N$58 -> #DIV/0! | P50: =O50*$I$26 -> #DIV/0!
A51: Kalkaji | B51: =Kalkaji!F13 -> 0 | C51: =B51/$B$58 -> #DIV/0! | D51: =C51*$F$26 -> #DIV/0! | F51: =Kalkaji!G13 -> 0 | G51: =F51/$F$58 -> #DIV/0! | H51: =G51*$G$26 -> #DIV/0! | J51: =Kalkaji!H13 -> 0 | K51: =J51/$J$58 -> #DIV/0! | L51: =K51*$H$26 -> #DIV/0! | N51: =Kalkaji!I13 -> 0 | O51: =N51/$N$58 -> #DIV/0! | P51: =O51*$I$26 -> #DIV/0!
A52: Connaught Place | B52: =CP!F13 -> 0 | C52: =B52/$B$58 -> #DIV/0! | D52: =C52*$F$26 -> #DIV/0! | F52: =CP!G13 -> 0 | G52: =F52/$F$58 -> #DIV/0! | H52: =G52*$G$26 -> #DIV/0! | J52: =CP!H13 -> 0 | K52: =J52/$J$58 -> #DIV/0! | L52: =K52*$H$26 -> #DIV/0! | N52: =CP!I13 -> 0 | O52: =N52/$N$58 -> #DIV/0! | P52: =O52*$I$26 -> #DIV/0!
A53: Rohini | B53: =Rohini!F13 -> 0 | C53: =B53/$B$58 -> #DIV/0! | D53: =C53*$F$26 -> #DIV/0! | F53: =Rohini!G13 -> 0 | G53: =F53/$F$58 -> #DIV/0! | H53: =G53*$G$26 -> #DIV/0! | J53: =Rohini!H13 -> 0 | K53: =J53/$J$58 -> #DIV/0! | L53: =K53*$H$26 -> #DIV/0! | N53: =Rohini!I13 -> 0 | O53: =N53/$N$58 -> #DIV/0! | P53: =O53*$I$26 -> #DIV/0!
A54: Model Town | B54: ='Model Town'!F13 -> 0 | C54: =B54/$B$58 -> #DIV/0! | D54: =C54*$F$26 -> #DIV/0! | F54: ='Model Town'!G13 -> 0 | G54: =F54/$F$58 -> #DIV/0! | H54: =G54*$G$26 -> #DIV/0! | J54: ='Model Town'!H13 -> 0 | K54: =J54/$J$58 -> #DIV/0! | L54: =K54*$H$26 -> #DIV/0! | N54: ='Model Town'!I13 -> 0 | O54: =N54/$N$58 -> #DIV/0! | P54: =O54*$I$26 -> #DIV/0!
A55: Pacific Mall | B55: ='Pacific Mall'!F13 -> 0 | C55: =B55/$B$58 -> #DIV/0! | D55: =C55*$F$26 -> #DIV/0! | F55: ='Pacific Mall'!G13 -> 0 | G55: =F55/$F$58 -> #DIV/0! | H55: =G55*$G$26 -> #DIV/0! | J55: ='Pacific Mall'!H13 -> 0 | K55: =J55/$J$58 -> #DIV/0! | L55: =K55*$H$26 -> #DIV/0! | N55: ='Pacific Mall'!I13 -> 0 | O55: =N55/$N$58 -> #DIV/0! | P55: =O55*$I$26 -> #DIV/0!
B58: =sum(B45:B55) -> 0 | D58: =sum(D45:D55) -> #DIV/0! | F58: =sum(F45:F55) -> 0 | H58: =sum(H45:H55) -> #DIV/0! | J58: =sum(J45:J55) -> 0 | L58: =sum(L45:L55) -> #DIV/0! | N58: =sum(N45:N55) -> 0 | P58: =sum(P45:P55) -> #DIV/0!
B59: Dec'2025 | C59: % Sales Dist | D59: % Dist (HO) | F59: Jan'2026 | G59: % Sales Dist | H59: % Dist (HO) | J59: Feb'2026 | K59: % Sales Dist | L59: % Dist (HO) | N59: Mar''2026 | O59: % Sales Dist | P59: % Dist (HO)
A60: Noida Sector 18 | B60: ='Noida Sec - 18'!J13 -> 0 | C60: =B60/$B$73 -> #DIV/0! | D60: =C60*$J$26 -> #DIV/0! | F60: ='Noida Sec - 18'!K13 -> 0 | G60: =F60/$F$73 -> #DIV/0! | H60: =G60*$K$26 -> #DIV/0! | J60: ='Noida Sec - 18'!L13 -> 0 | K60: =J60/$J$73 -> #DIV/0! | L60: =K60*$L$26 -> #DIV/0! | N60: ='Noida Sec - 18'!M13 -> 0 | O60: =N60/$N$73 -> #DIV/0! | P60: =O60*$M$26 -> #DIV/0!
A61: Noida Sector 143 | B61: ='Noida Sec -143'!J13 -> 0 | C61: =B61/$B$73 -> #DIV/0! | D61: =C61*$J$26 -> #DIV/0! | F61: ='Noida Sec -143'!K13 -> 0 | G61: =F61/$F$73 -> #DIV/0! | H61: =G61*$K$26 -> #DIV/0! | J61: ='Noida Sec -143'!L13 -> 0 | K61: =J61/$J$73 -> #DIV/0! | L61: =K61*$L$26 -> #DIV/0! | N61: ='Noida Sec -143'!M13 -> 0 | O61: =N61/$N$73 -> #DIV/0! | P61: =O61*$M$26 -> #DIV/0!
A62: Faridabad Sector 15 | B62: ='Faridabad Sec15'!J13 -> 0 | C62: =B62/$B$73 -> #DIV/0! | D62: =C62*$J$26 -> #DIV/0! | F62: ='Faridabad Sec15'!K13 -> 0 | G62: =F62/$F$73 -> #DIV/0! | H62: =G62*$K$26 -> #DIV/0! | J62: ='Faridabad Sec15'!L13 -> 0 | K62: =J62/$J$73 -> #DIV/0! | L62: =K62*$L$26 -> #DIV/0! | N62: ='Faridabad Sec15'!M13 -> 0 | O62: =N62/$N$73 -> #DIV/0! | P62: =O62*$M$26 -> #DIV/0!
A63: DLF | B63: =DLF!J13 -> 0 | C63: =B63/$B$73 -> #DIV/0! | D63: =C63*$J$26 -> #DIV/0! | F63: =DLF!K13 -> 0 | G63: =F63/$F$73 -> #DIV/0! | H63: =G63*$K$26 -> #DIV/0! | J63: =DLF!L13 -> 0 | K63: =J63/$J$73 -> #DIV/0! | L63: =K63*$L$26 -> #DIV/0! | N63: =DLF!M13 -> 0 | O63: =N63/$N$73 -> #DIV/0! | P63: =O63*$M$26 -> #DIV/0!
A64: Huda Market | B64: ='Gurgaon Sec-15'!J13 -> 0 | C64: =B64/$B$73 -> #DIV/0! | D64: =C64*$J$26 -> #DIV/0! | F64: ='Gurgaon Sec-15'!K13 -> 0 | G64: =F64/$F$73 -> #DIV/0! | H64: =G64*$K$26 -> #DIV/0! | J64: ='Gurgaon Sec-15'!L13 -> 0 | K64: =J64/$J$73 -> #DIV/0! | L64: =K64*$L$26 -> #DIV/0! | N64: ='Gurgaon Sec-15'!M13 -> 0 | O64: =N64/$N$73 -> #DIV/0! | P64: =O64*$M$26 -> #DIV/0!
A65: Sector 10 | B65: ='Gurgaon Sec - 10'!J13 -> 0 | C65: =B65/$B$73 -> #DIV/0! | D65: =C65*$J$26 -> #DIV/0! | F65: ='Gurgaon Sec - 10'!K13 -> 0 | G65: =F65/$F$73 -> #DIV/0! | H65: =G65*$K$26 -> #DIV/0! | J65: ='Gurgaon Sec - 10'!L13 -> 0 | K65: =J65/$J$73 -> #DIV/0! | L65: =K65*$L$26 -> #DIV/0! | N65: ='Gurgaon Sec - 10'!M13 -> 0 | O65: =N65/$N$73 -> #DIV/0! | P65: =O65*$M$26 -> #DIV/0!
A66: Paschim Vihar | B66: ='Paschim Vihar'!J13 -> 0 | C66: =B66/$B$73 -> #DIV/0! | D66: =C66*$J$26 -> #DIV/0! | F66: ='Paschim Vihar'!K13 -> 0 | G66: =F66/$F$73 -> #DIV/0! | H66: =G66*$K$26 -> #DIV/0! | J66: ='Paschim Vihar'!L13 -> 0 | K66: =J66/$J$73 -> #DIV/0! | L66: =K66*$L$26 -> #DIV/0! | N66: ='Paschim Vihar'!M13 -> 0 | O66: =N66/$N$73 -> #DIV/0! | P66: =O66*$M$26 -> #DIV/0!
A67: Kalkaji | B67: =Kalkaji!J13 -> 0 | C67: =B67/$B$73 -> #DIV/0! | D67: =C67*$J$26 -> #DIV/0! | F67: =Kalkaji!K13 -> 0 | G67: =F67/$F$73 -> #DIV/0! | H67: =G67*$K$26 -> #DIV/0! | J67: =Kalkaji!L13 -> 0 | K67: =J67/$J$73 -> #DIV/0! | L67: =K67*$L$26 -> #DIV/0! | N67: =Kalkaji!M13 -> 0 | O67: =N67/$N$73 -> #DIV/0! | P67: =O67*$M$26 -> #DIV/0!
A68: Connaught Place | B68: =CP!J13 -> 0 | C68: =B68/$B$73 -> #DIV/0! | D68: =C68*$J$26 -> #DIV/0! | F68: =CP!K13 -> 0 | G68: =F68/$F$73 -> #DIV/0! | H68: =G68*$K$26 -> #DIV/0! | J68: =CP!L13 -> 0 | K68: =J68/$J$73 -> #DIV/0! | L68: =K68*$L$26 -> #DIV/0! | N68: =CP!M13 -> 0 | O68: =N68/$N$73 -> #DIV/0! | P68: =O68*$M$26 -> #DIV/0!
A69: Rohini | B69: =Rohini!J13 -> 0 | C69: =B69/$B$73 -> #DIV/0! | D69: =C69*$J$26 -> #DIV/0! | F69: =Rohini!K13 -> 0 | G69: =F69/$F$73 -> #DIV/0! | H69: =G69*$K$26 -> #DIV/0! | J69: =Rohini!L13 -> 0 | K69: =J69/$J$73 -> #DIV/0! | L69: =K69*$L$26 -> #DIV/0! | N69: =Rohini!M13 -> 0 | O69: =N69/$N$73 -> #DIV/0! | P69: =O69*$M$26 -> #DIV/0!
A70: Model Town | B70: ='Model Town'!J13 -> 0 | C70: =B70/$B$73 -> #DIV/0! | D70: =C70*$J$26 -> #DIV/0! | F70: ='Model Town'!K13 -> 0 | G70: =F70/$F$73 -> #DIV/0! | H70: =G70*$K$26 -> #DIV/0! | J70: ='Model Town'!L13 -> 0 | K70: =J70/$J$73 -> #DIV/0! | L70: =K70*$L$26 -> #DIV/0! | N70: ='Model Town'!M13 -> 0 | O70: =N70/$N$73 -> #DIV/0! | P70: =O70*$M$26 -> #DIV/0!
A71: Pacific Mall | B71: ='Pacific Mall'!J13 -> 0 | C71: =B71/$B$73 -> #DIV/0! | D71: =C71*$J$26 -> #DIV/0! | F71: ='Pacific Mall'!K13 -> 0 | G71: =F71/$F$73 -> #DIV/0! | H71: =G71*$K$26 -> #DIV/0! | J71: ='Pacific Mall'!L13 -> 0 | K71: =J71/$J$73 -> #DIV/0! | L71: =K71*$L$26 -> #DIV/0! | N71: ='Pacific Mall'!M13 -> 0 | O71: =N71/$N$73 -> #DIV/0! | P71: =O71*$M$26 -> #DIV/0!
A72: Shalimar Bagh | N72: ='Shalimar Bagh'!M13 -> 0 | O72: =N72/$N$73 -> #DIV/0! | P72: =O72*$M$26 -> #DIV/0!
B73: =sum(B60:B71) -> 0 | D73: =sum(D60:D71) -> #DIV/0! | F73: =sum(F60:F71) -> 0 | G73: =F73/$F$73 -> #DIV/0! | H73: =sum(H60:H71) -> #DIV/0! | J73: =sum(J60:J71) -> 0 | L73: =sum(L60:L71) -> #DIV/0! | N73: =sum(N60:N72) -> 0 | P73: =sum(P60:P72) -> #DIV/0!
N74: =Summary!N15 -> 0
N75: =N73-N74 -> 0
H86: =sum(H83:H85) -> 0

Sheet Salary Reco
B3: Salary Reconciliation
D4: Kolkata | E4: Delhi NCR | F4: Total
B5: Salary As Per Grand Economics
B6: Stores | D6: =37960+97962+90766+444894+170797+196229+282526+170687+123232+198355+275653+319810+320386+197466+19313+169898 -> 3115934 | E6: 4316115 | F6: =D6+E6 -> 7432049
B7: CK | D7: =523310 -> 523310 | E7: 697502 | F7: =D7+E7 -> 1220812
B8: Head Office | D8: =362354+887749+108007 -> 1358110 | E8: 534752 | F8: =D8+E8 -> 1892862
B9: Total Salary | D9: =sum(D6:D8) -> 4997354 | E9: =sum(E6:E8) -> 5548369 | F9: =D9+E9 -> 10545723
B10: PF Employers Cont. | D10: 303660 | E10: 368635 | F10: =D10+E10 -> 672295 | G10: Added in HO Salary
B11: ESI Employers Cont. | D11: 72676 | E11: 89228 | F11: =D11+E11 -> 161904 | G11: Added in HO Salary
B12: Total Salary as reported in Grand Economics | D12: =D9+D10+D11 -> 5373690 | E12: =E9+E10+E11 -> 6006232 | F12: =D12+E12 -> 11379922
B14: Gratuity | D14: 130000 | E14: 144395 | F14: =D14+E14 -> 274395 | G14: Added in HO Salary
B16: Total CTC | D16: =D12+D14 -> 5503690 | E16: =E12+E14 -> 6150627 | F16: =D16+E16 -> 11654317

Sheet Misc Exp
A1: Particulars | B1: Noida Sec 18 | C1: Noida Sec 143 | D1: DLF | E1: Faridabad Sec 15 | F1: Huda Market | G1: Sector 10 | H1: Sector 31 | I1: Paschim Vihar | J1: Kalkaji | K1: Model Town | L1: Rohini | M1: Pacific Mall | N1: Connaught Place | O1: Shalimar Bagh | P1: Central Kitchen | Q1: Head Office | R1: Total
L2: lab
A3: Miscellaneous Expenses
A4: Local Authorities Expenses | B4: 4000 | C4: 4000 | I4: 5000 | J4: 6000 | K4: 4000 | L4: 5000 | N4: 5000 | P4: 7500 | R4: =sum(B4:Q4) -> 40500
A5: House Keeping Services | B5: 3012 | C5: 1506 | E5: 1382 | F5: 1800 | G5: 1700 | H5: 318 | I5: 500 | J5: 790 | K5: =2000+2468 -> 4468 | L5: 1000 | M5: 268 | N5: =5625+2500 -> 8125 | R5: =sum(B5:Q5) -> 24869
A6: Credit Card Settlement Charges | B6: 2748.98 | C6: 1205 | D6: 3705.94 | E6: 928.36 | F6: 2805 | G6: 385.42 | H6: 1762.15 | I6: 1217 | J6: 1464 | K6: 1565 | L6: 2234 | M6: 3990 | N6: 4401 | O6: 1673.5 | R6: =sum(B6:Q6) -> 30085.35
A7: Customer Compensation on Zomato | B7: 1121 | C7: 1298.91 | D7: 753 | E7: 667 | F7: 1230 | H7: 210 | I7: 390 | J7: 1849 | L7: 781.44 | M7: 230 | R7: =sum(B7:Q7) -> 8530.35
A8: Bank Charges | B8: 924.48 | C8: 946.93 | D8: 1662 | E8: 444.89 | F8: 1667.74 | G8: 459.92 | H8: 1598.33 | I8: 382.34 | J8: 453.6 | K8: 813.95 | L8: 1291.58 | M8: 1725 | N8: 2813 | O8: 807.91 | Q8: 141.6 | R8: =sum(B8:Q8) -> 16133.27
A9: Staff Welfare Expenses | B9: =1000+240 -> 1240 | C9: 805 | D9: 400 | I9: 1018 | J9: 2000 | L9: 600 | M9: 3500 | N9: 1830 | O9: 480 | R9: =sum(B9:Q9) -> 11873
A10: DG Charges | R10: =sum(B10:Q10) -> 0
A11: Staff Electricity | C11: 890 | F11: 990 | G11: 1260 | K11: 1850 | N11: 1585 | O11: 300 | P11: 5004 | R11: =sum(B11:Q11) -> 11879
A12: Merchant Share of Cancelled Orders | B12: 1361.94 | C12: 51.45 | I12: 136.3 | J12: 377.38 | L12: 141.75 | N12: 51.66 | O12: 170.1 | R12: =sum(B12:Q12) -> 2290.58
A13: Office Maintenance House Keeping | N13: 4810 | R13: =sum(B13:Q13) -> 4810
A14: Swiggy Cancellation Refund | B14: 2979 | C14: 565 | D14: 1002 | E14: 1765 | F14: 812 | G14: 505 | H14: 210 | I14: =1094+1960 -> 3054 | J14: 2309 | K14: 2394 | L14: 4670 | M14: 1116 | N14: 1091 | O14: 840 | R14: =sum(B14:Q14) -> 23312
A15: Merchant Funded Promotion | B15: 129.7 | C15: =514.71 -> 514.71 | E15: 961.68 | F15: 922.23 | G15: 201.6 | J15: 204 | N15: 110 | R15: =sum(B15:Q15) -> 3043.92
A16: Printing & Stationery | B16: 255 | C16: 105 | D16: 790 | E16: 180 | F16: 500 | G16: 570 | H16: 120 | I16: 244 | J16: 315 | K16: 410 | L16: 320 | M16: 250 | N16: 200 | O16: 455 | P16: 31263 | R16: =sum(B16:Q16) -> 35977
A17: Settlement Charges | B17: 57.82 | C17: 0 | R17: =sum(B17:Q17) -> 57.82
A18: Round Off | H18: -139.59 | Q18: =367.85-742 -> -374.15 | R18: =sum(B18:Q18) -> -513.74
A19: Payment Collection Charges | R19: =sum(B19:Q19) -> 0
A20: Loading & Unloading Charges | R20: =sum(B20:Q20) -> 0
A21: Travelling & Conveyance | B21: 2429 | D21: 710 | F21: 7889 | G21: 120 | H21: 100 | I21: 330 | J21: 1487 | K21: 373 | L21: 3000 | M21: 3000 | N21: 10580 | O21: 403 | P21: 12110 | Q21: 52448 | R21: =sum(B21:Q21) -> 94979
A22: Rates & Taxes | R22: =sum(B22:Q22) -> 0
A23: Subscription | R23: =sum(B23:Q23) -> 0
A24: Staff Water Charges | D24: 187 | E24: 1240 | J24: 150 | K24: 720 | N24: 6010 | P24: 400 | R24: =sum(B24:Q24) -> 8707
A25: General Expeneses | B25: 683 | D25: 1489 | E25: 720 | F25: 7220 | G25: 330 | H25: =562+290 -> 852 | I25: =771+1146 -> 1917 | K25: 1368 | L25: 500 | M25: 656 | N25: 4291 | O25: 200 | P25: 5579 | R25: =sum(B25:Q25) -> 25805
A26: Cash Pickup Charges | P26: 36674 | R26: =sum(B26:Q26) -> 36674
A27: Interest Charges | H27: 784
A28: Freight Charges | I28: 276 | J28: 267 | K28: 156 | M28: 800 | N28: 1784 | O28: 1046 | P28: 11166 | R28: =sum(B28:Q28) -> 15495
A29: Motor Car Expenses | I29: 1000 | P29: =82538+25598+20680 -> 128816 | R29: =sum(B29:Q29) -> 129816
A30: Staff Room Rent | E30: 996 | R30: =sum(B30:Q30) -> 996
A31: Kitchen Utensils | K31: 5481 | P31: 8999 | R31: =sum(B31:Q31) -> 14480
A32: Security Guard Charges | L32: 700 | R32: =sum(B32:Q32) -> 700
A33: Local Conveyance | R33: =sum(B33:Q33) -> 0
A34: Parking Charges | M34: 1600 | P34: 10000 | R34: =sum(B34:Q34) -> 11600
A35: Labor Charges | P35: 1600 | R35: =sum(B35:Q35) -> 1600
A36: Courier Charges | R36: =sum(B36:Q36) -> 0
B37: =sum(B4:B36) -> 20941.92 | C37: =sum(C4:C36) -> 11888 | D37: =sum(D4:D36) -> 10698.94 | E37: =sum(E4:E36) -> 9284.93 | F37: =sum(F4:F36) -> 25835.97 | G37: =sum(G4:G36) -> 5531.94 | H37: =sum(H4:H36) -> 5814.89 | I37: =sum(I4:I36) -> 15464.64 | ... R37: =sum(R4:R36) -> 553699.55
B39: Noida Sec 18 | C39: Noida Sec 143 | D39: DLF | E39: Faridabad Sec 15 | F39: Huda Market | G39: Sector 10 | H39: Sector 31 | I39: Paschim Vihar | J39: Kalkaji | K39: Model Town | L39: Rohini | M39: Pacific Mall | N39: Connaught Place | O39: Shalimar Bagh | P39: Central Kitchen | Q39: Head Office | R39: Total
A40: Repairs & Maintenance | B40: =32684 -> 32684 | C40: 8056 | E40: =3160+4130 -> 7290 | F40: 4130 | G40: =370+4130 -> 4500 | H40: 18360 | I40: 4130 | J40: 260 | K40: 7080 | L40: =320+4130 -> 4450 | N40: 4412 | O40: 15034 | P40: 100268 | R40: =sum(B40:Q40) -> 210654
A41: Repairs & Maintenance P&M | B41: =35400/12 -> 2950 | E41: =6050+9086 -> 15136 | F41: 6290 | H41: 21004 | I41: 7077 | K41: 3540 | N41: =4720+3500 -> 8220 | O41: 6042 | P41: 13570 | R41: =sum(B41:Q41) -> 83829
R42: =sum(B42:Q42) -> 0
B43: =sum(B41:B42) -> 2950 | C43: =sum(C40:C42) -> 8056 | D43: =sum(D40:D42) -> 0 | E43: =sum(E40:E42) -> 22426 | F43: =sum(F40:F42) -> 10420 | G43: =sum(G40:G42) -> 4500 | H43: =sum(H40:H42) -> 39364 | I43: =sum(I40:I42) -> 11207 | J43: =sum(J40:J42) -> 260 | ... R43: =sum(R40:R42) -> 294483
A47: 46199
A48: Particulars | B48: Noida Sec 18 | C48: Noida Sec 143 | D48: DLF | E48: Faridabad Sec 15 | F48: Huda Market | G48: Sector 10 | H48: Sector 31 | I48: Paschim Vihar | J48: Kalkaji | K48: Model Town | L48: Rohini | M48: Pacific Mall | N48: Connaught Place | O48: Shalimar Bagh | P48: Central Kitchen | Q48: Head Office | R48: Total
A50: Miscellaneous Expenses
A51: Local Authorities Expenses | B51: 4000 | C51: 0 | D51: 0 | E51: 0 | F51: 0 | G51: 0 | H51: 0 | I51: 12500 | J51: 6000 | K51: 4000 | L51: 5000 | N51: 5000 | P51: =7500+37500 -> 45000 | R51: =sum(B51:Q51) -> 81500
A52: House Keeping Services | B52: 595 | C52: 1133 | D52: 1873 | E52: 1345 | F52: 1500 | G52: 1500 | H52: 0 | I52: 570 | J52: 1974 | K52: 2425 | L52: 1743 | M52: 402 | N52: 2610 | O52: 2880 | P52: 4500 | R52: =sum(B52:Q52) -> 25050
A53: Credit Card Settlement Charges | B53: 2406.59 | C53: 1188.67 | D53: 2738.69 | E53: 1052.32 | F53: =2686.18 -> 2686.18 | G53: 663.88 | H53: 1498 | I53: 1050 | J53: 1065.54 | K53: 2485 | L53: 2773.4 | M53: 3713 | N53: 6422 | O53: =2256 -> 2256 | R53: =sum(B53:Q53) -> 31999.27
A54: Customer Compensation on Zomato | B54: 1556.09 | C54: 963.04 | D54: =118 -> 118 | E54: 522.68 | F54: 370.53 | G54: 120 | H54: 238.27 | I54: 1215 | J54: 580.73 | K54: 268 | L54: 495 | M54: 330 | R54: =sum(B54:Q54) -> 6777.34
A55: Bank Charges | B55: 1414.07 | C55: 625.39 | D55: 1650 | E55: 508.18 | F55: =1357.91 -> 1357.91 | G55: 687.21 | H55: 1089.18 | I55: 720.71 | J55: 486.96 | K55: 486.3 | L55: 1391.16 | M55: 1735 | N55: 2670 | O55: 863.08 | R55: =sum(B55:Q55) -> 15685.15
A56: Staff Welfare Expenses | B56: 2215 | C56: 0 | D56: 0 | E56: 850 | F56: 0 | G56: 0 | H56: 0 | I56: 1861 | J56: 1350 | K56: 2600 | L56: 500 | M56: =11750 -> 11750 | N56: 1700 | O56: 1000 | P56: 918 | R56: =sum(B56:Q56) -> 24744
A57: DG Charges | B57: 2000 | C57: 0 | D57: 0 | E57: 0 | F57: 0 | G57: 0 | H57: 0 | R57: =sum(B57:Q57) -> 2000
A58: Staff Electricity | B58: 0 | C58: 920 | D58: 0 | E58: 0 | F58: 730 | G58: 1220 | H58: 0 | O58: 830 | P58: =3044 -> 3044 | R58: =sum(B58:Q58) -> 6744
A59: Merchant Share of Cancelled Orders | B59: 670 | C59: 223 | D59: 38 | E59: 0 | F59: 43 | G59: 196 | H59: 114 | I59: 630.31 | K59: 100.17 | L59: 343.99 | M59: 168.84 | O59: 362.5 | R59: =sum(B59:Q59) -> 2889.81
A60: Swiggy Cancellation Refund | B60: 601 | C60: 0 | D60: 98.91 | E60: 0 | F60: 117.81 | G60: 0 | H60: 148 | R60: =sum(B60:Q60) -> 965.72
