Workbook

Sheet Summary
A2: Dosa Coffee - NCR | B2: Department | C2: 45748 | D2: 45778 | E2: 45809 | F2: 45839 | G2: 45870 | H2: 45901 | I2: 45931 | J2: 45962 | K2: 45992 | L2: 46023 | M2: 46054 | N2: 46082 | O2: FY 2025-26
A3: Food Cost Calculation
A4: Opening Stock | B4: Procurement | C4: ='Noida Sec - 18'!B3+'Noida Sec -143'!B3+DLF!B3+'Faridabad Sec15'!B3+'Gurgaon Sec-15'!B3+'Gurgaon Sec - 10'!B3+'Paschim Vihar'!B3+Kalkaji!B3+CP!B3+Rohini!B3+'Model Town'!B3+'Pacific Mall'!B3 -> 993716 | D4: ='Noida Sec - 18'!C3+'Noida Sec -143'!C3+DLF!C3+'Faridabad Sec15'!C3+'Gurgaon Sec-15'!C3+'Gurgaon Sec - 10'!C3+'Paschim Vihar'!C3+Kalkaji!C3+CP!C3+Rohini!C3+'Model Town'!C3+'Pacific Mall'!C3 -> 985593.38 | E4: ='Noida Sec - 18'!D3+'Noida Sec -143'!D3+DLF!D3+'Faridabad Sec15'!D3+'Gurgaon Sec-15'!D3+'Gurgaon Sec - 10'!D3+'Paschim Vihar'!D3+Kalkaji!D3+CP!D3+Rohini!D3+'Model Town'!D3+'Pacific Mall'!D3 -> 1011915 | F4: ='Noida Sec - 18'!E3+'Noida Sec -143'!E3+DLF!E3+'Faridabad Sec15'!E3+'Gurgaon Sec-15'!E3+'Gurgaon Sec - 10'!E3+'Paschim Vihar'!E3+Kalkaji!E3+CP!E3+Rohini!E3+'Model Town'!E3+'Pacific Mall'!E3 -> 1043813.5 | G4: ='Noida Sec - 18'!F3+'Noida Sec -143'!F3+DLF!F3+'Faridabad Sec15'!F3+'Gurgaon Sec-15'!F3+'Gurgaon Sec - 10'!F3+'Paschim Vihar'!F3+Kalkaji!F3+CP!F3+Rohini!F3+'Model Town'!F3+'Pacific Mall'!F3 -> 1053063.8 | H4: ='Noida Sec - 18'!G3+'Noida Sec -143'!G3+DLF!G3+'Faridabad Sec15'!G3+'Gurgaon Sec-15'!G3+'Gurgaon Sec - 10'!G3+'Paschim Vihar'!G3+Kalkaji!G3+CP!G3+Rohini!G3+'Model Town'!G3+'Pacific Mall'!G3 -> 931666.9 | I4: ='Noida Sec - 18'!H3+'Noida Sec -143'!H3+DLF!H3+'Faridabad Sec15'!H3+'Gurgaon Sec-15'!H3+'Gurgaon Sec - 10'!H3+'Paschim Vihar'!H3+Kalkaji!H3+CP!H3+Rohini!H3+'Model Town'!H3+'Pacific Mall'!H3 -> 970596.89 | J4: ='Noida Sec - 18'!I3+'Noida Sec -143'!I3+DLF!I3+'Faridabad Sec15'!I3+'Gurgaon Sec-15'!I3+'Gurgaon Sec - 10'!I3+'Paschim Vihar'!I3+Kalkaji!I3+CP!I3+Rohini!I3+'Model Town'!I3+'Pacific Mall'!I3 -> 977614.19 | ... N4: ='Noida Sec - 18'!M3+'Noida Sec -143'!M3+DLF!M3+'Faridabad Sec15'!M3+'Gurgaon Sec-15'!M3+'Gurgaon Sec - 10'!M3+'Paschim Vihar'!M3+Kalkaji!M3+CP!M3+Rohini!M3+'Model Town'!M3+'Pacific Mall'!M3 -> 850671.5
A5: Purchases Food (Less Purchase Return) | B5: Procurement | C5: ='Noida Sec - 18'!B4+'Noida Sec -143'!B4+'Faridabad Sec15'!B4+DLF!B4+'Gurgaon Sec-15'!B4+'Paschim Vihar'!B4+Kalkaji!B4+CP!B4+Rohini!B4+'Model Town'!B4+'Pacific Mall'!B4+480296 -> 4466945.2 | D5: ='Noida Sec - 18'!C4+'Noida Sec -143'!C4+'Faridabad Sec15'!C4+DLF!C4+'Gurgaon Sec-15'!C4+'Paschim Vihar'!C4+Kalkaji!C4+CP!C4+Rohini!C4+'Model Town'!C4+'Pacific Mall'!C4+238551 -> 4537965.8 | E5: ='Noida Sec - 18'!D4+'Noida Sec -143'!D4+'Faridabad Sec15'!D4+DLF!D4+'Gurgaon Sec-15'!D4+'Paschim Vihar'!D4+Kalkaji!D4+CP!D4+Rohini!D4+'Model Town'!D4+'Pacific Mall'!D4+267948 -> 4576663.5 | F5: ='Noida Sec - 18'!E4+'Noida Sec -143'!E4+'Faridabad Sec15'!E4+DLF!E4+'Gurgaon Sec-15'!E4+'Paschim Vihar'!E4+Kalkaji!E4+CP!E4+Rohini!E4+'Model Town'!E4+'Pacific Mall'!E4+113974 -> 4748672.2 | G5: ='Noida Sec - 18'!F4+'Noida Sec -143'!F4+'Faridabad Sec15'!F4+DLF!F4+'Gurgaon Sec-15'!F4+'Paschim Vihar'!F4+Kalkaji!F4+CP!F4+Rohini!F4+'Model Town'!F4+'Pacific Mall'!F4+160391 -> 4564517.1 | H5: ='Noida Sec - 18'!G4+'Noida Sec -143'!G4+'Faridabad Sec15'!G4+DLF!G4+'Gurgaon Sec-15'!G4+'Paschim Vihar'!G4+Kalkaji!G4+CP!G4+Rohini!G4+'Model Town'!G4+'Pacific Mall'!G4+515868 -> 4521500.6 | I5: ='Noida Sec - 18'!H4+'Noida Sec -143'!H4+'Faridabad Sec15'!H4+DLF!H4+'Gurgaon Sec-15'!H4+'Paschim Vihar'!H4+Kalkaji!H4+CP!H4+Rohini!H4+'Model Town'!H4+'Pacific Mall'!H4+184386 -> 3978759.1 | J5: ='Noida Sec - 18'!I4+'Noida Sec -143'!I4+'Faridabad Sec15'!I4+DLF!I4+'Gurgaon Sec-15'!I4+'Paschim Vihar'!I4+Kalkaji!I4+CP!I4+Rohini!I4+'Model Town'!I4+'Pacific Mall'!I4+283112 -> 4063531.4 | K5: ='Noida Sec - 18'!J4+'Noida Sec -143'!J4+'Faridabad Sec15'!J4+DLF!J4+'Gurgaon Sec-15'!J4+'Paschim Vihar'!J4+Kalkaji!J4+CP!J4+Rohini!J4+'Model Town'!J4+'Pacific Mall'!J4+'Gurgaon Sec - 10'!J4+105978 -> 4503673.6 | L5: ='Noida Sec - 18'!K4+'Noida Sec -143'!K4+'Faridabad Sec15'!K4+DLF!K4+'Gurgaon Sec-15'!K4+'Paschim Vihar'!K4+Kalkaji!K4+CP!K4+Rohini!K4+'Model Town'!K4+'Pacific Mall'!K4+'Gurgaon Sec - 10'!K4 -> 4550618.1 | M5: ='Noida Sec - 18'!L4+'Noida Sec -143'!L4+DLF!L4+'Faridabad Sec15'!L4+'Gurgaon Sec-15'!L4+'Gurgaon Sec - 10'!L4+'Paschim Vihar'!L4+Kalkaji!L4+CP!L4+Rohini!L4+'Model Town'!L4+'Pacific Mall'!L4+461000 -> 5135833.3 | N5: ='Noida Sec - 18'!M4+'Noida Sec -143'!M4+DLF!M4+'Faridabad Sec15'!M4+'Gurgaon Sec-15'!M4+'Gurgaon Sec - 10'!M4+'Paschim Vihar'!M4+Kalkaji!M4+CP!M4+Rohini!M4+'Model Town'!M4+'Pacific Mall'!M4+'Shalimar Bagh'!M4+114362 -> 5694719.4
A6: Transferred Out | B6: Procurement | C6: ='Noida Sec - 18'!B5+'Noida Sec -143'!B5+'Faridabad Sec15'!B5+DLF!B5+'Gurgaon Sec-15'!B5+'Paschim Vihar'!B5+Kalkaji!B5+CP!B5+Rohini!B5+'Model Town'!B5+'Pacific Mall'!B5 -> 0 | D6: ='Noida Sec - 18'!C5+'Noida Sec -143'!C5+'Faridabad Sec15'!C5+DLF!C5+'Gurgaon Sec-15'!C5+'Paschim Vihar'!C5+Kalkaji!C5+CP!C5+Rohini!C5+'Model Town'!C5+'Pacific Mall'!C5 -> 16172 | E6: ='Noida Sec - 18'!D5+'Noida Sec -143'!D5+'Faridabad Sec15'!D5+DLF!D5+'Gurgaon Sec-15'!D5+'Paschim Vihar'!D5+Kalkaji!D5+CP!D5+Rohini!D5+'Model Town'!D5+'Pacific Mall'!D5 -> 8649.27 | F6: ='Noida Sec - 18'!E5+'Noida Sec -143'!E5+'Faridabad Sec15'!E5+DLF!E5+'Gurgaon Sec-15'!E5+'Paschim Vihar'!E5+Kalkaji!E5+CP!E5+Rohini!E5+'Model Town'!E5+'Pacific Mall'!E5 -> 556 | G6: ='Noida Sec - 18'!F5+'Noida Sec -143'!F5+'Faridabad Sec15'!F5+DLF!F5+'Gurgaon Sec-15'!F5+'Paschim Vihar'!F5+Kalkaji!F5+CP!F5+Rohini!F5+'Model Town'!F5+'Pacific Mall'!F5 -> 0 | H6: ='Noida Sec - 18'!G5+'Noida Sec -143'!G5+'Faridabad Sec15'!G5+DLF!G5+'Gurgaon Sec-15'!G5+'Paschim Vihar'!G5+Kalkaji!G5+CP!G5+Rohini!G5+'Model Town'!G5+'Pacific Mall'!G5 -> 0 | I6: ='Noida Sec - 18'!H5+'Noida Sec -143'!H5+'Faridabad Sec15'!H5+DLF!H5+'Gurgaon Sec-15'!H5+'Paschim Vihar'!H5+Kalkaji!H5+CP!H5+Rohini!H5+'Model Town'!H5+'Pacific Mall'!H5 -> 0 | J6: ='Noida Sec - 18'!I5+'Noida Sec -143'!I5+'Faridabad Sec15'!I5+DLF!I5+'Gurgaon Sec-15'!I5+'Paschim Vihar'!I5+Kalkaji!I5+CP!I5+Rohini!I5+'Model Town'!I5+'Pacific Mall'!I5 -> 25336.42 | K6: ='Noida Sec - 18'!J5+'Noida Sec -143'!J5+'Faridabad Sec15'!J5+DLF!J5+'Gurgaon Sec-15'!J5+'Paschim Vihar'!J5+Kalkaji!J5+CP!J5+Rohini!J5+'Model Town'!J5+'Pacific Mall'!J5+'Gurgaon Sec - 10'!J5 -> 2081 | L6: ='Noida Sec - 18'!K5+'Noida Sec -143'!K5+'Faridabad Sec15'!K5+DLF!K5+'Gurgaon Sec-15'!K5+'Paschim Vihar'!K5+Kalkaji!K5+CP!K5+Rohini!K5+'Model Town'!K5+'Pacific Mall'!K5+'Gurgaon Sec - 10'!K5 -> 462.35 | M6: ='Noida Sec - 18'!L5+'Noida Sec -143'!L5+DLF!L5+'Faridabad Sec15'!L5+'Gurgaon Sec-15'!L5+'Gurgaon Sec - 10'!L5+'Paschim Vihar'!L5+Kalkaji!L5+CP!L5+Rohini!L5+'Model Town'!L5+'Pacific Mall'!L5 -> 43712 | N6: ='Noida Sec - 18'!M5+'Noida Sec -143'!M5+DLF!M5+'Faridabad Sec15'!M5+'Gurgaon Sec-15'!M5+'Gurgaon Sec - 10'!M5+'Paschim Vihar'!M5+Kalkaji!M5+CP!M5+Rohini!M5+'Model Town'!M5+'Pacific Mall'!M5+'Shalimar Bagh'!M5 -> 3114.98
A7: Wastage & Date Expired | B7: Procurement | C7: ='Noida Sec - 18'!B6+'Noida Sec -143'!B6+'Faridabad Sec15'!B6+DLF!B6+'Gurgaon Sec-15'!B6+'Paschim Vihar'!B6+Kalkaji!B6+CP!B6+Rohini!B6+'Model Town'!B6+'Pacific Mall'!B6 -> 257019 | D7: ='Noida Sec - 18'!C6+'Noida Sec -143'!C6+'Faridabad Sec15'!C6+DLF!C6+'Gurgaon Sec-15'!C6+'Paschim Vihar'!C6+Kalkaji!C6+CP!C6+Rohini!C6+'Model Town'!C6+'Pacific Mall'!C6 -> 272145.73 | E7: ='Noida Sec - 18'!D6+'Noida Sec -143'!D6+'Faridabad Sec15'!D6+DLF!D6+'Gurgaon Sec-15'!D6+'Paschim Vihar'!D6+Kalkaji!D6+CP!D6+Rohini!D6+'Model Town'!D6+'Pacific Mall'!D6 -> 250427.5 | F7: ='Noida Sec - 18'!E6+'Noida Sec -143'!E6+'Faridabad Sec15'!E6+DLF!E6+'Gurgaon Sec-15'!E6+'Paschim Vihar'!E6+Kalkaji!E6+CP!E6+Rohini!E6+'Model Town'!E6+'Pacific Mall'!E6 -> 268883.8 | G7: ='Noida Sec - 18'!F6+'Noida Sec -143'!F6+'Faridabad Sec15'!F6+DLF!F6+'Gurgaon Sec-15'!F6+'Paschim Vihar'!F6+Kalkaji!F6+CP!F6+Rohini!F6+'Model Town'!F6+'Pacific Mall'!F6 -> 267299.42 | H7: ='Noida Sec - 18'!G6+'Noida Sec -143'!G6+'Faridabad Sec15'!G6+DLF!G6+'Gurgaon Sec-15'!G6+'Paschim Vihar'!G6+Kalkaji!G6+CP!G6+Rohini!G6+'Model Town'!G6+'Pacific Mall'!G6 -> 254022.52 | I7: ='Noida Sec - 18'!H6+'Noida Sec -143'!H6+'Faridabad Sec15'!H6+DLF!H6+'Gurgaon Sec-15'!H6+'Paschim Vihar'!H6+Kalkaji!H6+CP!H6+Rohini!H6+'Model Town'!H6+'Pacific Mall'!H6 -> 270740.17 | J7: ='Noida Sec - 18'!I6+'Noida Sec -143'!I6+'Faridabad Sec15'!I6+DLF!I6+'Gurgaon Sec-15'!I6+'Paschim Vihar'!I6+Kalkaji!I6+CP!I6+Rohini!I6+'Model Town'!I6+'Pacific Mall'!I6 -> 300905.03 | K7: ='Noida Sec - 18'!J6+'Noida Sec -143'!J6+'Faridabad Sec15'!J6+DLF!J6+'Gurgaon Sec-15'!J6+'Paschim Vihar'!J6+Kalkaji!J6+CP!J6+Rohini!J6+'Model Town'!J6+'Pacific Mall'!J6+'Gurgaon Sec - 10'!J6 -> 291445.37 | L7: ='Noida Sec - 18'!K6+'Noida Sec -143'!K6+'Faridabad Sec15'!K6+DLF!K6+'Gurgaon Sec-15'!K6+'Paschim Vihar'!K6+Kalkaji!K6+CP!K6+Rohini!K6+'Model Town'!K6+'Pacific Mall'!K6+'Gurgaon Sec - 10'!K6 -> 285924.53 | M7: ='Noida Sec - 18'!L6+'Noida Sec -143'!L6+DLF!L6+'Faridabad Sec15'!L6+'Gurgaon Sec-15'!L6+'Gurgaon Sec - 10'!L6+'Paschim Vihar'!L6+Kalkaji!L6+CP!L6+Rohini!L6+'Model Town'!L6+'Pacific Mall'!L6 -> 296116.67 | N7: ='Noida Sec - 18'!M6+'Noida Sec -143'!M6+DLF!M6+'Faridabad Sec15'!M6+'Gurgaon Sec-15'!M6+'Gurgaon Sec - 10'!M6+'Paschim Vihar'!M6+Kalkaji!M6+CP!M6+Rohini!M6+'Model Town'!M6+'Pacific Mall'!M6+'Shalimar Bagh'!M6 -> 344801.16
A8: Closing Stock | B8: Procurement | C8: ='Noida Sec - 18'!B7+'Noida Sec -143'!B7+DLF!B7+'Faridabad Sec15'!B7+'Gurgaon Sec-15'!B7+'Gurgaon Sec - 10'!B7+'Paschim Vihar'!B7+Kalkaji!B7+CP!B7+Rohini!B7+'Model Town'!B7+'Pacific Mall'!B7 -> 976756 | D8: ='Noida Sec - 18'!C7+'Noida Sec -143'!C7+DLF!C7+'Faridabad Sec15'!C7+'Gurgaon Sec-15'!C7+'Gurgaon Sec - 10'!C7+'Paschim Vihar'!C7+Kalkaji!C7+CP!C7+Rohini!C7+'Model Town'!C7+'Pacific Mall'!C7 -> 1011915 | E8: ='Noida Sec - 18'!D7+'Noida Sec -143'!D7+DLF!D7+'Faridabad Sec15'!D7+'Gurgaon Sec-15'!D7+'Gurgaon Sec - 10'!D7+'Paschim Vihar'!D7+Kalkaji!D7+CP!D7+Rohini!D7+'Model Town'!D7+'Pacific Mall'!D7 -> 1043813.5 | F8: ='Noida Sec - 18'!E7+'Noida Sec -143'!E7+DLF!E7+'Faridabad Sec15'!E7+'Gurgaon Sec-15'!E7+'Gurgaon Sec - 10'!E7+'Paschim Vihar'!E7+Kalkaji!E7+CP!E7+Rohini!E7+'Model Town'!E7+'Pacific Mall'!E7 -> 1053063.8 | G8: ='Noida Sec - 18'!F7+'Noida Sec -143'!F7+DLF!F7+'Faridabad Sec15'!F7+'Gurgaon Sec-15'!F7+'Gurgaon Sec - 10'!F7+'Paschim Vihar'!F7+Kalkaji!F7+CP!F7+Rohini!F7+'Model Town'!F7+'Pacific Mall'!F7 -> 931666.9 | H8: ='Noida Sec - 18'!G7+'Noida Sec -143'!G7+DLF!G7+'Faridabad Sec15'!G7+'Gurgaon Sec-15'!G7+'Gurgaon Sec - 10'!G7+'Paschim Vihar'!G7+Kalkaji!G7+CP!G7+Rohini!G7+'Model Town'!G7+'Pacific Mall'!G7 -> 970596.89 | I8: ='Noida Sec - 18'!H7+'Noida Sec -143'!H7+DLF!H7+'Faridabad Sec15'!H7+'Gurgaon Sec-15'!H7+'Gurgaon Sec - 10'!H7+'Paschim Vihar'!H7+Kalkaji!H7+CP!H7+Rohini!H7+'Model Town'!H7+'Pacific Mall'!H7 -> 977614.19 | J8: ='Noida Sec - 18'!I7+'Noida Sec -143'!I7+DLF!I7+'Faridabad Sec15'!I7+'Gurgaon Sec-15'!I7+'Gurgaon Sec - 10'!I7+'Paschim Vihar'!I7+Kalkaji!I7+CP!I7+Rohini!I7+'Model Town'!I7+'Pacific Mall'!I7 -> 1023788.5 | ... M8: ='Noida Sec - 18'!L7+'Noida Sec -143'!L7+DLF!L7+'Faridabad Sec15'!L7+'Gurgaon Sec-15'!L7+'Gurgaon Sec - 10'!L7+'Paschim Vihar'!L7+Kalkaji!L7+CP!L7+Rohini!L7+'Model Town'!L7+'Pacific Mall'!L7 -> 847710.85 | N8: ='Noida Sec - 18'!M7+'Noida Sec -143'!M7+DLF!M7+'Faridabad Sec15'!M7+'Gurgaon Sec-15'!M7+'Gurgaon Sec - 10'!M7+'Paschim Vihar'!M7+Kalkaji!M7+CP!M7+Rohini!M7+'Model Town'!M7+'Pacific Mall'!M7+'Shalimar Bagh'!M7 -> 865957.47
A10: Gross Revenue | B10: Operation | C10: ='Noida Sec - 18'!B9+'Noida Sec -143'!B9+'Faridabad Sec15'!B9+DLF!B9+'Gurgaon Sec-15'!B9+'Paschim Vihar'!B9+Kalkaji!B9+CP!B9+Rohini!B9+'Model Town'!B9+'Pacific Mall'!B9+'Gurgaon Sec - 10'!B9+'Shalimar Bagh'!B9 -> 16506267 | D10: ='Noida Sec - 18'!C9+'Noida Sec -143'!C9+'Faridabad Sec15'!C9+DLF!C9+'Gurgaon Sec-15'!C9+'Paschim Vihar'!C9+Kalkaji!C9+CP!C9+Rohini!C9+'Model Town'!C9+'Pacific Mall'!C9+'Gurgaon Sec - 10'!C9+'Shalimar Bagh'!C9 -> 17850038 | E10: ='Noida Sec - 18'!D9+'Noida Sec -143'!D9+'Faridabad Sec15'!D9+DLF!D9+'Gurgaon Sec-15'!D9+'Paschim Vihar'!D9+Kalkaji!D9+CP!D9+Rohini!D9+'Model Town'!D9+'Pacific Mall'!D9+'Gurgaon Sec - 10'!D9+'Shalimar Bagh'!D9 -> 17762029 | F10: ='Noida Sec - 18'!E9+'Noida Sec -143'!E9+'Faridabad Sec15'!E9+DLF!E9+'Gurgaon Sec-15'!E9+'Paschim Vihar'!E9+Kalkaji!E9+CP!E9+Rohini!E9+'Model Town'!E9+'Pacific Mall'!E9+'Gurgaon Sec - 10'!E9+'Shalimar Bagh'!E9 -> 18827858 | G10: ='Noida Sec - 18'!F9+'Noida Sec -143'!F9+'Faridabad Sec15'!F9+DLF!F9+'Gurgaon Sec-15'!F9+'Paschim Vihar'!F9+Kalkaji!F9+CP!F9+Rohini!F9+'Model Town'!F9+'Pacific Mall'!F9+'Gurgaon Sec - 10'!F9+'Shalimar Bagh'!F9 -> 18611135 | H10: ='Noida Sec - 18'!G9+'Noida Sec -143'!G9+'Faridabad Sec15'!G9+DLF!G9+'Gurgaon Sec-15'!G9+'Paschim Vihar'!G9+Kalkaji!G9+CP!G9+Rohini!G9+'Model Town'!G9+'Pacific Mall'!G9+'Gurgaon Sec - 10'!G9+'Shalimar Bagh'!G9 -> 16760496 | I10: ='Noida Sec - 18'!H9+'Noida Sec -143'!H9+'Faridabad Sec15'!H9+DLF!H9+'Gurgaon Sec-15'!H9+'Paschim Vihar'!H9+Kalkaji!H9+CP!H9+Rohini!H9+'Model Town'!H9+'Pacific Mall'!H9+'Gurgaon Sec - 10'!H9+'Shalimar Bagh'!H9 -> 16220749 | J10: ='Noida Sec - 18'!I9+'Noida Sec -143'!I9+'Faridabad Sec15'!I9+DLF!I9+'Gurgaon Sec-15'!I9+'Paschim Vihar'!I9+Kalkaji!I9+CP!I9+Rohini!I9+'Model Town'!I9+'Pacific Mall'!I9+'Gurgaon Sec - 10'!I9+'Shalimar Bagh'!I9 -> 16064434 | ... N10: ='Noida Sec - 18'!M9+'Noida Sec -143'!M9+'Faridabad Sec15'!M9+DLF!M9+'Gurgaon Sec-15'!M9+'Paschim Vihar'!M9+Kalkaji!M9+CP!M9+Rohini!M9+'Model Town'!M9+'Pacific Mall'!M9+'Gurgaon Sec - 10'!M9+'Shalimar Bagh'!M9 -> 23420696 | O10: =+SUM(C10:N10) -> 2.192413e+08
A11: Catering & Fairs | B11: Operation | C11: ='Noida Sec - 18'!B10+'Noida Sec -143'!B10+'Faridabad Sec15'!B10+DLF!B10+'Gurgaon Sec-15'!B10+'Paschim Vihar'!B10+Kalkaji!B10+CP!B10+Rohini!B10+'Model Town'!B10+'Pacific Mall'!B10 -> 0 | D11: ='Noida Sec - 18'!C10+'Noida Sec -143'!C10+'Faridabad Sec15'!C10+DLF!C10+'Gurgaon Sec-15'!C10+'Paschim Vihar'!C10+Kalkaji!C10+CP!C10+Rohini!C10+'Model Town'!C10+'Pacific Mall'!C10 -> 0 | E11: ='Noida Sec - 18'!D10+'Noida Sec -143'!D10+'Faridabad Sec15'!D10+DLF!D10+'Gurgaon Sec-15'!D10+'Paschim Vihar'!D10+Kalkaji!D10+CP!D10+Rohini!D10+'Model Town'!D10+'Pacific Mall'!D10 -> 34020 | F11: ='Noida Sec - 18'!E10+'Noida Sec -143'!E10+'Faridabad Sec15'!E10+DLF!E10+'Gurgaon Sec-15'!E10+'Paschim Vihar'!E10+Kalkaji!E10+CP!E10+Rohini!E10+'Model Town'!E10+'Pacific Mall'!E10 -> 0 | G11: ='Noida Sec - 18'!F10+'Noida Sec -143'!F10+'Faridabad Sec15'!F10+DLF!F10+'Gurgaon Sec-15'!F10+'Paschim Vihar'!F10+Kalkaji!F10+CP!F10+Rohini!F10+'Model Town'!F10+'Pacific Mall'!F10 -> 0 | H11: ='Noida Sec - 18'!G10+'Noida Sec -143'!G10+'Faridabad Sec15'!G10+DLF!G10+'Gurgaon Sec-15'!G10+'Paschim Vihar'!G10+Kalkaji!G10+CP!G10+Rohini!G10+'Model Town'!G10+'Pacific Mall'!G10 -> 0 | I11: ='Noida Sec - 18'!H10+'Noida Sec -143'!H10+'Faridabad Sec15'!H10+DLF!H10+'Gurgaon Sec-15'!H10+'Paschim Vihar'!H10+Kalkaji!H10+CP!H10+Rohini!H10+'Model Town'!H10+'Pacific Mall'!H10 -> 0 | J11: ='Noida Sec - 18'!I10+'Noida Sec -143'!I10+'Faridabad Sec15'!I10+DLF!I10+'Gurgaon Sec-15'!I10+'Paschim Vihar'!I10+Kalkaji!I10+CP!I10+Rohini!I10+'Model Town'!I10+'Pacific Mall'!I10 -> 0 | K11: ='Noida Sec - 18'!J10+'Noida Sec -143'!J10+'Faridabad Sec15'!J10+DLF!J10+'Gurgaon Sec-15'!J10+'Paschim Vihar'!J10+Kalkaji!J10+CP!J10+Rohini!J10+'Model Town'!J10+'Pacific Mall'!J10+'Gurgaon Sec - 10'!J10 -> 0 | L11: ='Noida Sec - 18'!K10+'Noida Sec -143'!K10+'Faridabad Sec15'!K10+DLF!K10+'Gurgaon Sec-15'!K10+'Paschim Vihar'!K10+Kalkaji!K10+CP!K10+Rohini!K10+'Model Town'!K10+'Pacific Mall'!K10 -> 0 | M11: ='Noida Sec - 18'!L10+'Noida Sec -143'!L10+'Faridabad Sec15'!L10+DLF!L10+'Gurgaon Sec-15'!L10+'Paschim Vihar'!L10+Kalkaji!L10+CP!L10+Rohini!L10+'Model Town'!L10+'Pacific Mall'!L10+'Gurgaon Sec - 10'!L10+'Shalimar Bagh'!L10 -> 0 | N11: ='Noida Sec - 18'!M10+'Noida Sec -143'!M10+'Faridabad Sec15'!M10+DLF!M10+'Gurgaon Sec-15'!M10+'Paschim Vihar'!M10+Kalkaji!M10+CP!M10+Rohini!M10+'Model Town'!M10+'Pacific Mall'!M10+'Gurgaon Sec - 10'!M10+'Shalimar Bagh'!M10 -> 0 | O11: =+SUM(C11:N11) -> 34020
A12: Less Tax | B12: Operation | C12: ='Noida Sec - 18'!B11+'Noida Sec -143'!B11+'Faridabad Sec15'!B11+DLF!B11+'Gurgaon Sec-15'!B11+'Paschim Vihar'!B11+Kalkaji!B11+CP!B11+Rohini!B11+'Model Town'!B11+'Pacific Mall'!B11 -> 786012.7 | D12: ='Noida Sec - 18'!C11+'Noida Sec -143'!C11+'Faridabad Sec15'!C11+DLF!C11+'Gurgaon Sec-15'!C11+'Paschim Vihar'!C11+Kalkaji!C11+CP!C11+Rohini!C11+'Model Town'!C11+'Pacific Mall'!C11 -> 850001.81 | E12: ='Noida Sec - 18'!D11+'Noida Sec -143'!D11+'Faridabad Sec15'!D11+DLF!D11+'Gurgaon Sec-15'!D11+'Paschim Vihar'!D11+Kalkaji!D11+CP!D11+Rohini!D11+'Model Town'!D11+'Pacific Mall'!D11 -> 847430.88 | F12: ='Noida Sec - 18'!E11+'Noida Sec -143'!E11+'Faridabad Sec15'!E11+DLF!E11+'Gurgaon Sec-15'!E11+'Paschim Vihar'!E11+Kalkaji!E11+CP!E11+Rohini!E11+'Model Town'!E11+'Pacific Mall'!E11 -> 896564.69 | G12: ='Noida Sec - 18'!F11+'Noida Sec -143'!F11+'Faridabad Sec15'!F11+DLF!F11+'Gurgaon Sec-15'!F11+'Paschim Vihar'!F11+Kalkaji!F11+CP!F11+Rohini!F11+'Model Town'!F11+'Pacific Mall'!F11 -> 886244.52 | H12: ='Noida Sec - 18'!G11+'Noida Sec -143'!G11+'Faridabad Sec15'!G11+DLF!G11+'Gurgaon Sec-15'!G11+'Paschim Vihar'!G11+Kalkaji!G11+CP!G11+Rohini!G11+'Model Town'!G11+'Pacific Mall'!G11 -> 798118.86 | I12: ='Noida Sec - 18'!H11+'Noida Sec -143'!H11+'Faridabad Sec15'!H11+DLF!H11+'Gurgaon Sec-15'!H11+'Paschim Vihar'!H11+Kalkaji!H11+CP!H11+Rohini!H11+'Model Town'!H11+'Pacific Mall'!H11 -> 772416.64 | J12: ='Noida Sec - 18'!I11+'Noida Sec -143'!I11+'Faridabad Sec15'!I11+DLF!I11+'Gurgaon Sec-15'!I11+'Paschim Vihar'!I11+Kalkaji!I11+CP!I11+Rohini!I11+'Model Town'!I11+'Pacific Mall'!I11 -> 764973.06 | K12: ='Noida Sec - 18'!J11+'Noida Sec -143'!J11+'Faridabad Sec15'!J11+DLF!J11+'Gurgaon Sec-15'!J11+'Paschim Vihar'!J11+Kalkaji!J11+CP!J11+Rohini!J11+'Model Town'!J11+'Pacific Mall'!J11+'Gurgaon Sec - 10'!J11 -> 808781.85 | L12: ='Noida Sec - 18'!K11+'Noida Sec -143'!K11+'Faridabad Sec15'!K11+DLF!K11+'Gurgaon Sec-15'!K11+'Paschim Vihar'!K11+Kalkaji!K11+CP!K11+Rohini!K11+'Model Town'!K11+'Pacific Mall'!K11 -> 920371.85 | M12: ='Noida Sec - 18'!L11+'Noida Sec -143'!L11+'Faridabad Sec15'!L11+DLF!L11+'Gurgaon Sec-15'!L11+'Paschim Vihar'!L11+Kalkaji!L11+CP!L11+Rohini!L11+'Model Town'!L11+'Pacific Mall'!L11+'Gurgaon Sec - 10'!L11+'Shalimar Bagh'!L11 -> 962717.84 | N12: ='Noida Sec - 18'!M11+'Noida Sec -143'!M11+'Faridabad Sec15'!M11+DLF!M11+'Gurgaon Sec-15'!M11+'Paschim Vihar'!M11+Kalkaji!M11+CP!M11+Rohini!M11+'Model Town'!M11+'Pacific Mall'!M11+'Gurgaon Sec - 10'!M11+'Shalimar Bagh'!M11 -> 1115271.2 | O12: =+SUM(C12:N12) -> 10408906
A13: Less Commission | B13: Operation | C13: ='Noida Sec - 18'!B12+'Noida Sec -143'!B12+'Faridabad Sec15'!B12+DLF!B12+'Gurgaon Sec-15'!B12+'Paschim Vihar'!B12+Kalkaji!B12+CP!B12+Rohini!B12+'Model Town'!B12+'Pacific Mall'!B12 -> 1017799.9 | D13: ='Noida Sec - 18'!C12+'Noida Sec -143'!C12+'Faridabad Sec15'!C12+DLF!C12+'Gurgaon Sec-15'!C12+'Paschim Vihar'!C12+Kalkaji!C12+CP!C12+Rohini!C12+'Model Town'!C12+'Pacific Mall'!C12 -> 1203038 | E13: ='Noida Sec - 18'!D12+'Noida Sec -143'!D12+'Faridabad Sec15'!D12+DLF!D12+'Gurgaon Sec-15'!D12+'Paschim Vihar'!D12+Kalkaji!D12+CP!D12+Rohini!D12+'Model Town'!D12+'Pacific Mall'!D12 -> 1241370.1 | F13: ='Noida Sec - 18'!E12+'Noida Sec -143'!E12+'Faridabad Sec15'!E12+DLF!E12+'Gurgaon Sec-15'!E12+'Paschim Vihar'!E12+Kalkaji!E12+CP!E12+Rohini!E12+'Model Town'!E12+'Pacific Mall'!E12 -> 1406953.7 | G13: ='Noida Sec - 18'!F12+'Noida Sec -143'!F12+'Faridabad Sec15'!F12+DLF!F12+'Gurgaon Sec-15'!F12+'Paschim Vihar'!F12+Kalkaji!F12+CP!F12+Rohini!F12+'Model Town'!F12+'Pacific Mall'!F12 -> 1282423.1 | H13: ='Noida Sec - 18'!G12+'Noida Sec -143'!G12+'Faridabad Sec15'!G12+DLF!G12+'Gurgaon Sec-15'!G12+'Paschim Vihar'!G12+Kalkaji!G12+CP!G12+Rohini!G12+'Model Town'!G12+'Pacific Mall'!G12 -> 1162069.4 | I13: ='Noida Sec - 18'!H12+'Noida Sec -143'!H12+'Faridabad Sec15'!H12+DLF!H12+'Gurgaon Sec-15'!H12+'Paschim Vihar'!H12+Kalkaji!H12+CP!H12+Rohini!H12+'Model Town'!H12+'Pacific Mall'!H12 -> 1165725.8 | J13: ='Noida Sec - 18'!I12+'Noida Sec -143'!I12+'Faridabad Sec15'!I12+DLF!I12+'Gurgaon Sec-15'!I12+'Paschim Vihar'!I12+Kalkaji!I12+CP!I12+Rohini!I12+'Model Town'!I12+'Pacific Mall'!I12 -> 1060975.2 | K13: ='Noida Sec - 18'!J12+'Noida Sec -143'!J12+'Faridabad Sec15'!J12+DLF!J12+'Gurgaon Sec-15'!J12+'Paschim Vihar'!J12+Kalkaji!J12+CP!J12+Rohini!J12+'Model Town'!J12+'Pacific Mall'!J12+'Gurgaon Sec - 10'!J12 -> 1081776.9 | L13: ='Noida Sec - 18'!K12+'Noida Sec -143'!K12+DLF!K12+'Faridabad Sec15'!K12+'Gurgaon Sec-15'!K12+'Gurgaon Sec - 10'!K12+'Paschim Vihar'!K12+Kalkaji!K12+CP!K12+Rohini!K12+'Model Town'!K12+'Pacific Mall'!K12 -> 1296527.2 | M13: ='Noida Sec - 18'!L12+'Noida Sec -143'!L12+DLF!L12+'Faridabad Sec15'!L12+'Gurgaon Sec-15'!L12+'Gurgaon Sec - 10'!L12+'Paschim Vihar'!L12+Kalkaji!L12+CP!L12+Rohini!L12+'Model Town'!L12+'Pacific Mall'!L12 -> 1344867.6 | N13: ='Noida Sec - 18'!M12+'Noida Sec -143'!M12+'Faridabad Sec15'!M12+DLF!M12+'Gurgaon Sec-15'!M12+'Paschim Vihar'!M12+Kalkaji!M12+CP!M12+Rohini!M12+'Model Town'!M12+'Pacific Mall'!M12+'Gurgaon Sec - 10'!M12+'Shalimar Bagh'!M12 -> 1826332.2 | O13: =+SUM(C13:N13) -> 15089859
A14: Commission % | C14: =C13/C10 -> 0.061661423 | D14: =D13/D10 -> 0.067396945 | E14: =E13/E10 -> 0.069888982 | F14: =F13/F10 -> 0.074727229 | G14: =G13/G10 -> 0.068906226 | H14: =H13/H10 -> 0.069333833 | I14: =I13/I10 -> 0.071866333 | J14: =J13/J10 -> 0.066044974 | ... M14: =M13/M10 -> 0.066521374 | N14: =N13/(N10-N12) -> 0.081878387
A15: Net Revenues from F&B Sales | C15: =C10+C11-C12-C13 -> 14702454 | D15: =D10+D11-D12-D13 -> 15796998 | E15: =E10+E11-E12-E13 -> 15707248 | F15: =F10+F11-F12-F13 -> 16524340 | G15: =G10+G11-G12-G13 -> 16442467 | H15: =H10+H11-H12-H13 -> 14800308 | I15: =I10+I11-I12-I13 -> 14282607 | J15: =J10+J11-J12-J13 -> 14238486 | ... N15: =N10+N11-N12-N13 -> 20479092 | O15: =sum(C15:N15) -> 1.9377656e+08 | P15: =O15/$O$15 -> 1 | Q15: Average
A16: F&B Cost | B16: Operation | C16: =C4+C5-C6-C8 -> 4483905.2 | D16: =D4+D5-D6-D8 -> 4495472.2 | E16: =E4+E5-E6-E8 -> 4536115.7 | F16: =F4+F5-F6-F8 -> 4738866 | G16: =G4+G5-G6-G8 -> 4685914 | H16: =H4+H5-H6-H8 -> 4482570.6 | I16: =I4+I5-I6-I8 -> 3971741.8 | J16: =J4+J5-J6-J8 -> 3992020.6 | ... N16: =N4+N5-N6-N8 -> 5676318.5 | O16: =sum(C16:N16) -> 55382872 | P16: =O16/$O$15 -> 0.28580791 | Q16: =AVERAGE(C16:N16)/11 -> 419567.21
A17: Electricity | B17: Operation | C17: ='Noida Sec - 18'!B15+'Noida Sec -143'!B15+'Faridabad Sec15'!B15+DLF!B15+'Gurgaon Sec-15'!B15+'Paschim Vihar'!B15+Kalkaji!B15+CP!B15+Rohini!B15+'Model Town'!B15+'Pacific Mall'!B15 -> 976118.67 | D17: ='Noida Sec - 18'!C15+'Noida Sec -143'!C15+'Faridabad Sec15'!C15+DLF!C15+'Gurgaon Sec-15'!C15+'Paschim Vihar'!C15+Kalkaji!C15+CP!C15+Rohini!C15+'Model Town'!C15+'Pacific Mall'!C15 -> 1053906.5 | E17: ='Noida Sec - 18'!D15+'Noida Sec -143'!D15+'Faridabad Sec15'!D15+DLF!D15+'Gurgaon Sec-15'!D15+'Paschim Vihar'!D15+Kalkaji!D15+CP!D15+Rohini!D15+'Model Town'!D15+'Pacific Mall'!D15 -> 1205832.4 | F17: ='Noida Sec - 18'!E15+'Noida Sec -143'!E15+'Faridabad Sec15'!E15+DLF!E15+'Gurgaon Sec-15'!E15+'Paschim Vihar'!E15+Kalkaji!E15+CP!E15+Rohini!E15+'Model Town'!E15+'Pacific Mall'!E15 -> 1161765.2 | G17: ='Noida Sec - 18'!F15+'Noida Sec -143'!F15+'Faridabad Sec15'!F15+DLF!F15+'Gurgaon Sec-15'!F15+'Paschim Vihar'!F15+Kalkaji!F15+CP!F15+Rohini!F15+'Model Town'!F15+'Pacific Mall'!F15 -> 1099231.8 | H17: ='Noida Sec - 18'!G15+'Noida Sec -143'!G15+'Faridabad Sec15'!G15+DLF!G15+'Gurgaon Sec-15'!G15+'Paschim Vihar'!G15+Kalkaji!G15+CP!G15+Rohini!G15+'Model Town'!G15+'Pacific Mall'!G15 -> 1034760.3 | I17: ='Noida Sec -143'!H15+'Noida Sec -143'!H15+'Faridabad Sec15'!H15+DLF!H15+'Gurgaon Sec-15'!H15+'Paschim Vihar'!H15+Kalkaji!H15+CP!H15+Rohini!H15+'Model Town'!H15+'Pacific Mall'!H15 -> 1013794.2 | J17: ='Noida Sec - 18'!I15+'Noida Sec -143'!I15+'Faridabad Sec15'!I15+DLF!I15+'Gurgaon Sec-15'!I15+'Paschim Vihar'!I15+Kalkaji!I15+CP!I15+Rohini!I15+'Model Town'!I15+'Pacific Mall'!I15 -> 798388.74 | K17: ='Noida Sec - 18'!J15+'Noida Sec -143'!J15+'Faridabad Sec15'!J15+DLF!J15+'Gurgaon Sec-15'!J15+'Paschim Vihar'!J15+Kalkaji!J15+CP!J15+Rohini!J15+'Model Town'!J15+'Pacific Mall'!J15+'Gurgaon Sec - 10'!J15 -> 794077.74 | L17: ='Noida Sec - 18'!K15+'Noida Sec -143'!K15+DLF!K15+'Faridabad Sec15'!K15+'Gurgaon Sec-15'!K15+'Gurgaon Sec - 10'!K15+'Paschim Vihar'!K15+Kalkaji!K15+CP!K15+Rohini!K15+'Model Town'!K15+'Pacific Mall'!K15 -> 854411 | M17: ='Noida Sec - 18'!L15+'Noida Sec -143'!L15+DLF!L15+'Faridabad Sec15'!L15+'Gurgaon Sec-15'!L15+'Gurgaon Sec - 10'!L15+'Paschim Vihar'!L15+Kalkaji!L15+CP!L15+Rohini!L15+'Model Town'!L15+'Pacific Mall'!L15 -> 827419.9 | N17: ='Noida Sec - 18'!M15+'Noida Sec -143'!M15+DLF!M15+'Faridabad Sec15'!M15+'Gurgaon Sec-15'!M15+'Gurgaon Sec - 10'!M15+'Paschim Vihar'!M15+Kalkaji!M15+CP!M15+Rohini!M15+'Model Town'!M15+'Pacific Mall'!M15 -> 960724.29 | O17: =sum(C17:N17) -> 11780431 | P17: =O17/$O$15 -> 0.06079389 | Q17: =AVERAGE(C17:N17)/11 -> 89245.687
A18: Telephone/Internet | B18: Operation | C18: ='Noida Sec - 18'!B16+'Noida Sec -143'!B16+'Faridabad Sec15'!B16+DLF!B16+'Gurgaon Sec-15'!B16+'Paschim Vihar'!B16+Kalkaji!B16+CP!B16+Rohini!B16+'Model Town'!B16+'Pacific Mall'!B16 -> 16363 | D18: ='Noida Sec - 18'!C16+'Noida Sec -143'!C16+'Faridabad Sec15'!C16+DLF!C16+'Gurgaon Sec-15'!C16+'Paschim Vihar'!C16+Kalkaji!C16+CP!C16+Rohini!C16+'Model Town'!C16+'Pacific Mall'!C16 -> 12493 | E18: ='Noida Sec - 18'!D16+'Noida Sec -143'!D16+'Faridabad Sec15'!D16+DLF!D16+'Gurgaon Sec-15'!D16+'Paschim Vihar'!D16+Kalkaji!D16+CP!D16+Rohini!D16+'Model Town'!D16+'Pacific Mall'!D16 -> 16726 | F18: ='Noida Sec - 18'!E16+'Noida Sec -143'!E16+'Faridabad Sec15'!E16+DLF!E16+'Gurgaon Sec-15'!E16+'Paschim Vihar'!E16+Kalkaji!E16+CP!E16+Rohini!E16+'Model Town'!E16+'Pacific Mall'!E16 -> 14739.667 | G18: ='Noida Sec - 18'!F16+'Noida Sec -143'!F16+'Faridabad Sec15'!F16+DLF!F16+'Gurgaon Sec-15'!F16+'Paschim Vihar'!F16+Kalkaji!F16+CP!F16+Rohini!F16+'Model Town'!F16+'Pacific Mall'!F16 -> 21453.667 | H18: ='Noida Sec - 18'!G16+'Noida Sec -143'!G16+'Faridabad Sec15'!G16+DLF!G16+'Gurgaon Sec-15'!G16+'Paschim Vihar'!G16+Kalkaji!G16+CP!G16+Rohini!G16+'Model Town'!G16+'Pacific Mall'!G16 -> 17236.5 | I18: ='Noida Sec - 18'!H16+'Noida Sec -143'!H16+'Faridabad Sec15'!H16+DLF!H16+'Gurgaon Sec-15'!H16+'Paschim Vihar'!H16+Kalkaji!H16+CP!H16+Rohini!H16+'Model Town'!H16+'Pacific Mall'!H16 -> 16714.5 | J18: ='Noida Sec - 18'!I16+'Noida Sec -143'!I16+'Faridabad Sec15'!I16+DLF!I16+'Gurgaon Sec-15'!I16+'Paschim Vihar'!I16+Kalkaji!I16+CP!I16+Rohini!I16+'Model Town'!I16+'Pacific Mall'!I16 -> 16551.5 | K18: ='Noida Sec - 18'!J16+'Noida Sec -143'!J16+'Faridabad Sec15'!J16+DLF!J16+'Gurgaon Sec-15'!J16+'Paschim Vihar'!J16+Kalkaji!J16+CP!J16+Rohini!J16+'Model Town'!J16+'Pacific Mall'!J16+'Gurgaon Sec - 10'!J16 -> 18700.5 | L18: ='Noida Sec - 18'!K16+'Noida Sec -143'!K16+DLF!K16+'Faridabad Sec15'!K16+'Gurgaon Sec-15'!K16+'Gurgaon Sec - 10'!K16+'Paschim Vihar'!K16+Kalkaji!K16+CP!K16+Rohini!K16+'Model Town'!K16+'Pacific Mall'!K16 -> 17293 | M18: ='Noida Sec - 18'!L16+'Noida Sec -143'!L16+DLF!L16+'Faridabad Sec15'!L16+'Gurgaon Sec-15'!L16+'Gurgaon Sec - 10'!L16+'Paschim Vihar'!L16+Kalkaji!L16+CP!L16+Rohini!L16+'Model Town'!L16+'Pacific Mall'!L16 -> 17963.333 | N18: ='Noida Sec - 18'!M16+'Noida Sec -143'!M16+DLF!M16+'Faridabad Sec15'!M16+'Gurgaon Sec-15'!M16+'Gurgaon Sec - 10'!M16+'Paschim Vihar'!M16+Kalkaji!M16+CP!M16+Rohini!M16+'Model Town'!M16+'Pacific Mall'!M16 -> 16958.833 | O18: =sum(C18:N18) -> 203193.5 | P18: =O18/$O$15 -> 0.0010485969 | Q18: =AVERAGE(C18:N18)/11 -> 1539.3447
A19: Gas | B19: Operation | C19: ='Noida Sec - 18'!B17+'Noida Sec -143'!B17+'Faridabad Sec15'!B17+DLF!B17+'Gurgaon Sec-15'!B17+'Paschim Vihar'!B17+Kalkaji!B17+CP!B17+Rohini!B17+'Model Town'!B17+'Pacific Mall'!B17 -> 457528.12 | D19: ='Noida Sec - 18'!C17+'Noida Sec -143'!C17+'Faridabad Sec15'!C17+DLF!C17+'Gurgaon Sec-15'!C17+'Paschim Vihar'!C17+Kalkaji!C17+CP!C17+Rohini!C17+'Model Town'!C17+'Pacific Mall'!C17 -> 467109.22 | E19: ='Noida Sec - 18'!D17+'Noida Sec -143'!D17+'Faridabad Sec15'!D17+DLF!D17+'Gurgaon Sec-15'!D17+'Paschim Vihar'!D17+Kalkaji!D17+CP!D17+Rohini!D17+'Model Town'!D17+'Pacific Mall'!D17 -> 412683 | F19: ='Noida Sec - 18'!E17+'Noida Sec -143'!E17+'Faridabad Sec15'!E17+DLF!E17+'Gurgaon Sec-15'!E17+'Paschim Vihar'!E17+Kalkaji!E17+CP!E17+Rohini!E17+'Model Town'!E17+'Pacific Mall'!E17 -> 462577.07 | G19: ='Noida Sec - 18'!F17+'Noida Sec -143'!F17+'Faridabad Sec15'!F17+DLF!F17+'Gurgaon Sec-15'!F17+'Paschim Vihar'!F17+Kalkaji!F17+CP!F17+Rohini!F17+'Model Town'!F17+'Pacific Mall'!F17 -> 460647.17 | H19: ='Noida Sec - 18'!G17+'Noida Sec -143'!G17+'Faridabad Sec15'!G17+DLF!G17+'Gurgaon Sec-15'!G17+'Paschim Vihar'!G17+Kalkaji!G17+CP!G17+Rohini!G17+'Model Town'!G17+'Pacific Mall'!G17 -> 388897.66 | I19: ='Noida Sec - 18'!H17+'Noida Sec -143'!H17+'Faridabad Sec15'!H17+DLF!H17+'Gurgaon Sec-15'!H17+'Paschim Vihar'!H17+Kalkaji!H17+CP!H17+Rohini!H17+'Model Town'!H17+'Pacific Mall'!H17 -> 410212.91 | J19: ='Noida Sec - 18'!I17+'Noida Sec -143'!I17+'Faridabad Sec15'!I17+DLF!I17+'Gurgaon Sec-15'!I17+'Paschim Vihar'!I17+Kalkaji!I17+CP!I17+Rohini!I17+'Model Town'!I17+'Pacific Mall'!I17 -> 411242.41 | K19: ='Noida Sec - 18'!J17+'Noida Sec -143'!J17+'Faridabad Sec15'!J17+DLF!J17+'Gurgaon Sec-15'!J17+'Paschim Vihar'!J17+Kalkaji!J17+CP!J17+Rohini!J17+'Model Town'!J17+'Pacific Mall'!J17+'Gurgaon Sec - 10'!J17 -> 414262.84 | L19: ='Noida Sec - 18'!K17+'Noida Sec -143'!K17+DLF!K17+'Faridabad Sec15'!K17+'Gurgaon Sec-15'!K17+'Gurgaon Sec - 10'!K17+'Paschim Vihar'!K17+Kalkaji!K17+CP!K17+Rohini!K17+'Model Town'!K17+'Pacific Mall'!K17 -> 469708.5 | M19: ='Noida Sec - 18'!L17+'Noida Sec -143'!L17+DLF!L17+'Faridabad Sec15'!L17+'Gurgaon Sec-15'!L17+'Gurgaon Sec - 10'!L17+'Paschim Vihar'!L17+Kalkaji!L17+CP!L17+Rohini!L17+'Model Town'!L17+'Pacific Mall'!L17 -> 414365 | N19: ='Noida Sec - 18'!M17+'Noida Sec -143'!M17+DLF!M17+'Faridabad Sec15'!M17+'Gurgaon Sec-15'!M17+'Gurgaon Sec - 10'!M17+'Paschim Vihar'!M17+Kalkaji!M17+CP!M17+Rohini!M17+'Model Town'!M17+'Pacific Mall'!M17 -> 569160.5 | O19: =sum(C19:N19) -> 5338394.4 | P19: =O19/$O$15 -> 0.027549227 | Q19: =AVERAGE(C19:N19)/11 -> 40442.382
A20: Rent & Revenue Share | B20: Accounts | C20: ='Noida Sec - 18'!B18+'Noida Sec -143'!B18+'Faridabad Sec15'!B18+DLF!B18+'Gurgaon Sec-15'!B18+'Paschim Vihar'!B18+Kalkaji!B18+CP!B18+Rohini!B18+'Model Town'!B18+'Pacific Mall'!B18 -> 3613825.5 | D20: ='Noida Sec - 18'!C18+'Noida Sec -143'!C18+'Faridabad Sec15'!C18+DLF!C18+'Gurgaon Sec-15'!C18+'Paschim Vihar'!C18+Kalkaji!C18+CP!C18+Rohini!C18+'Model Town'!C18+'Pacific Mall'!C18 -> 3770381.3 | E20: ='Noida Sec - 18'!D18+'Noida Sec -143'!D18+'Faridabad Sec15'!D18+DLF!D18+'Gurgaon Sec-15'!D18+'Paschim Vihar'!D18+Kalkaji!D18+CP!D18+Rohini!D18+'Model Town'!D18+'Pacific Mall'!D18 -> 3770380.5 | F20: ='Noida Sec - 18'!E18+'Noida Sec -143'!E18+'Faridabad Sec15'!E18+DLF!E18+'Gurgaon Sec-15'!E18+'Paschim Vihar'!E18+Kalkaji!E18+CP!E18+Rohini!E18+'Model Town'!E18+'Pacific Mall'!E18 -> 3770380 | G20: ='Noida Sec - 18'!F18+'Noida Sec -143'!F18+'Faridabad Sec15'!F18+DLF!F18+'Gurgaon Sec-15'!F18+'Paschim Vihar'!F18+Kalkaji!F18+CP!F18+Rohini!F18+'Model Town'!F18+'Pacific Mall'!F18 -> 3770381.3 | H20: ='Noida Sec - 18'!G18+'Noida Sec -143'!G18+'Faridabad Sec15'!G18+DLF!G18+'Gurgaon Sec-15'!G18+'Paschim Vihar'!G18+Kalkaji!G18+CP!G18+Rohini!G18+'Model Town'!G18+'Pacific Mall'!G18 -> 3770380.5 | I20: ='Noida Sec - 18'!H18+'Noida Sec -143'!H18+'Faridabad Sec15'!H18+DLF!H18+'Gurgaon Sec-15'!H18+'Paschim Vihar'!H18+Kalkaji!H18+CP!H18+Rohini!H18+'Model Town'!H18+'Pacific Mall'!H18 -> 3770381 | J20: ='Noida Sec - 18'!I18+'Noida Sec -143'!I18+'Faridabad Sec15'!I18+DLF!I18+'Gurgaon Sec-15'!I18+'Paschim Vihar'!I18+Kalkaji!I18+CP!I18+Rohini!I18+'Model Town'!I18+'Pacific Mall'!I18 -> 3770381.3 | K20: ='Noida Sec - 18'!J18+'Noida Sec -143'!J18+'Faridabad Sec15'!J18+DLF!J18+'Gurgaon Sec-15'!J18+'Paschim Vihar'!J18+Kalkaji!J18+CP!J18+Rohini!J18+'Model Town'!J18+'Pacific Mall'!J18+'Gurgaon Sec - 10'!J18 -> 3759303.3 | L20: ='Noida Sec - 18'!K18+'Noida Sec -143'!K18+DLF!K18+'Faridabad Sec15'!K18+'Gurgaon Sec-15'!K18+'Gurgaon Sec - 10'!K18+'Paschim Vihar'!K18+Kalkaji!K18+CP!K18+Rohini!K18+'Model Town'!K18+'Pacific Mall'!K18 -> 3759509.2 | M20: ='Noida Sec - 18'!L18+'Noida Sec -143'!L18+DLF!L18+'Faridabad Sec15'!L18+'Gurgaon Sec-15'!L18+'Gurgaon Sec - 10'!L18+'Paschim Vihar'!L18+Kalkaji!L18+CP!L18+Rohini!L18+'Model Town'!L18+'Pacific Mall'!L18 -> 3759898.3 | N20: ='Noida Sec - 18'!M18+'Noida Sec -143'!M18+DLF!M18+'Faridabad Sec15'!M18+'Gurgaon Sec-15'!M18+'Gurgaon Sec - 10'!M18+'Paschim Vihar'!M18+Kalkaji!M18+CP!M18+Rohini!M18+'Model Town'!M18+'Pacific Mall'!M18+'Shalimar Bagh'!M18 -> 3821494.5 | O20: =sum(C20:N20) -> 45106697 | P20: =O20/$O$15 -> 0.23277685 | Q20: =AVERAGE(C20:N20)/11 -> 341717.4
A21: Insurance | B21: Accounts | C21: ='Noida Sec - 18'!B19+'Noida Sec -143'!B19+'Faridabad Sec15'!B19+DLF!B19+'Gurgaon Sec-15'!B19+'Paschim Vihar'!B19+Kalkaji!B19+CP!B19+Rohini!B19+'Model Town'!B19+'Pacific Mall'!B19 -> 0 | D21: ='Noida Sec - 18'!C19+'Noida Sec -143'!C19+'Faridabad Sec15'!C19+DLF!C19+'Gurgaon Sec-15'!C19+'Paschim Vihar'!C19+Kalkaji!C19+CP!C19+Rohini!C19+'Model Town'!C19+'Pacific Mall'!C19 -> 12761.936 | E21: ='Noida Sec - 18'!D19+'Noida Sec -143'!D19+'Faridabad Sec15'!D19+DLF!D19+'Gurgaon Sec-15'!D19+'Paschim Vihar'!D19+Kalkaji!D19+CP!D19+Rohini!D19+'Model Town'!D19+'Pacific Mall'!D19 -> 12761.936 | F21: ='Noida Sec - 18'!E19+'Noida Sec -143'!E19+'Faridabad Sec15'!E19+DLF!E19+'Gurgaon Sec-15'!E19+'Paschim Vihar'!E19+Kalkaji!E19+CP!E19+Rohini!E19+'Model Town'!E19+'Pacific Mall'!E19 -> 12761.936 | G21: ='Noida Sec - 18'!F19+'Noida Sec -143'!F19+'Faridabad Sec15'!F19+DLF!F19+'Gurgaon Sec-15'!F19+'Paschim Vihar'!F19+Kalkaji!F19+CP!F19+Rohini!F19+'Model Town'!F19+'Pacific Mall'!F19 -> 12761.936 | H21: ='Noida Sec - 18'!G19+'Noida Sec -143'!G19+'Faridabad Sec15'!G19+DLF!G19+'Gurgaon Sec-15'!G19+'Paschim Vihar'!G19+Kalkaji!G19+CP!G19+Rohini!G19+'Model Town'!G19+'Pacific Mall'!G19 -> 12761.936 | I21: ='Noida Sec - 18'!H19+'Noida Sec -143'!H19+'Faridabad Sec15'!H19+DLF!H19+'Gurgaon Sec-15'!H19+'Paschim Vihar'!H19+Kalkaji!H19+CP!H19+Rohini!H19+'Model Town'!H19+'Pacific Mall'!H19 -> 12761.936 | J21: ='Noida Sec - 18'!I19+'Noida Sec -143'!I19+'Faridabad Sec15'!I19+DLF!I19+'Gurgaon Sec-15'!I19+'Paschim Vihar'!I19+Kalkaji!I19+CP!I19+Rohini!I19+'Model Town'!I19+'Pacific Mall'!I19 -> 12761.936 | K21: ='Noida Sec - 18'!J19+'Noida Sec -143'!J19+'Faridabad Sec15'!J19+DLF!J19+'Gurgaon Sec-15'!J19+'Paschim Vihar'!J19+Kalkaji!J19+CP!J19+Rohini!J19+'Model Town'!J19+'Pacific Mall'!J19+'Gurgaon Sec - 10'!J19 -> 14416.769 | L21: ='Noida Sec - 18'!K19+'Noida Sec -143'!K19+DLF!K19+'Faridabad Sec15'!K19+'Gurgaon Sec-15'!K19+'Gurgaon Sec - 10'!K19+'Paschim Vihar'!K19+Kalkaji!K19+CP!K19+Rohini!K19+'Model Town'!K19+'Pacific Mall'!K19 -> 14416.769 | M21: ='Noida Sec - 18'!L19+'Noida Sec -143'!L19+DLF!L19+'Faridabad Sec15'!L19+'Gurgaon Sec-15'!L19+'Gurgaon Sec - 10'!L19+'Paschim Vihar'!L19+Kalkaji!L19+CP!L19+Rohini!L19+'Model Town'!L19+'Pacific Mall'!L19 -> 14416.769 | N21: ='Noida Sec - 18'!M19+'Noida Sec -143'!M19+DLF!M19+'Faridabad Sec15'!M19+'Gurgaon Sec-15'!M19+'Gurgaon Sec - 10'!M19+'Paschim Vihar'!M19+Kalkaji!M19+CP!M19+Rohini!M19+'Model Town'!M19+'Pacific Mall'!M19 -> 14416.769 | O21: =sum(C21:N21) -> 147000.63 | P21: =O21/$O$15 -> 0.00075860893 | Q21: =AVERAGE(C21:N21)/11 -> 1113.6411
A22: Software | B22: Operation | C22: ='Noida Sec - 18'!B20+'Noida Sec -143'!B20+'Faridabad Sec15'!B20+DLF!B20+'Gurgaon Sec-15'!B20+'Paschim Vihar'!B20+Kalkaji!B20+CP!B20+Rohini!B20+'Model Town'!B20+'Pacific Mall'!B20 -> 83255.583 | D22: ='Noida Sec - 18'!C20+'Noida Sec -143'!C20+'Faridabad Sec15'!C20+DLF!C20+'Gurgaon Sec-15'!C20+'Paschim Vihar'!C20+Kalkaji!C20+CP!C20+Rohini!C20+'Model Town'!C20+'Pacific Mall'!C20 -> 81166 | E22: ='Noida Sec - 18'!D20+'Noida Sec -143'!D20+'Faridabad Sec15'!D20+DLF!D20+'Gurgaon Sec-15'!D20+'Paschim Vihar'!D20+Kalkaji!D20+CP!D20+Rohini!D20+'Model Town'!D20+'Pacific Mall'!D20 -> 81166 | F22: ='Noida Sec - 18'!E20+'Noida Sec -143'!E20+'Faridabad Sec15'!E20+DLF!E20+'Gurgaon Sec-15'!E20+'Paschim Vihar'!E20+Kalkaji!E20+CP!E20+Rohini!E20+'Model Town'!E20+'Pacific Mall'!E20 -> 81166 | G22: ='Noida Sec - 18'!F20+'Noida Sec -143'!F20+'Faridabad Sec15'!F20+DLF!F20+'Gurgaon Sec-15'!F20+'Paschim Vihar'!F20+Kalkaji!F20+CP!F20+Rohini!F20+'Model Town'!F20+'Pacific Mall'!F20 -> 81166 | H22: ='Noida Sec - 18'!G20+'Noida Sec -143'!G20+'Faridabad Sec15'!G20+DLF!G20+'Gurgaon Sec-15'!G20+'Paschim Vihar'!G20+Kalkaji!G20+CP!G20+Rohini!G20+'Model Town'!G20+'Pacific Mall'!G20 -> 79076.417 | I22: ='Noida Sec - 18'!H20+'Noida Sec -143'!H20+'Faridabad Sec15'!H20+DLF!H20+'Gurgaon Sec-15'!H20+'Paschim Vihar'!H20+Kalkaji!H20+CP!H20+Rohini!H20+'Model Town'!H20+'Pacific Mall'!H20 -> 74927.25 | J22: ='Noida Sec - 18'!I20+'Noida Sec -143'!I20+'Faridabad Sec15'!I20+DLF!I20+'Gurgaon Sec-15'!I20+'Paschim Vihar'!I20+Kalkaji!I20+CP!I20+Rohini!I20+'Model Town'!I20+'Pacific Mall'!I20 -> 74927.25 | K22: ='Noida Sec - 18'!J20+'Noida Sec -143'!J20+'Faridabad Sec15'!J20+DLF!J20+'Gurgaon Sec-15'!J20+'Paschim Vihar'!J20+Kalkaji!J20+CP!J20+Rohini!J20+'Model Town'!J20+'Pacific Mall'!J20+'Gurgaon Sec - 10'!J20 -> 82784.083 | L22: ='Noida Sec - 18'!K20+'Noida Sec -143'!K20+DLF!K20+'Faridabad Sec15'!K20+'Gurgaon Sec-15'!K20+'Gurgaon Sec - 10'!K20+'Paschim Vihar'!K20+Kalkaji!K20+CP!K20+Rohini!K20+'Model Town'!K20+'Pacific Mall'!K20 -> 82784.083 | M22: ='Noida Sec - 18'!L20+'Noida Sec -143'!L20+DLF!L20+'Faridabad Sec15'!L20+'Gurgaon Sec-15'!L20+'Gurgaon Sec - 10'!L20+'Paschim Vihar'!L20+Kalkaji!L20+CP!L20+Rohini!L20+'Model Town'!L20+'Pacific Mall'!L20 -> 80947.583 | N22: ='Noida Sec - 18'!M20+'Noida Sec -143'!M20+DLF!M20+'Faridabad Sec15'!M20+'Gurgaon Sec-15'!M20+'Gurgaon Sec - 10'!M20+'Paschim Vihar'!M20+Kalkaji!M20+CP!M20+Rohini!M20+'Model Town'!M20+'Pacific Mall'!M20 -> 80947.583 | O22: =sum(C22:N22) -> 964313.83 | P22: =O22/$O$15 -> 0.0049764215 | Q22: =AVERAGE(C22:N22)/11 -> 7305.4078
A23: Staff Salary | B23: HR | C23: ='Noida Sec - 18'!B21+'Noida Sec -143'!B21+'Faridabad Sec15'!B21+DLF!B21+'Gurgaon Sec-15'!B21+'Paschim Vihar'!B21+Kalkaji!B21+CP!B21+Rohini!B21+'Model Town'!B21+'Pacific Mall'!B21 -> 3513263.6 | D23: ='Noida Sec - 18'!C21+'Noida Sec -143'!C21+'Faridabad Sec15'!C21+DLF!C21+'Gurgaon Sec-15'!C21+'Paschim Vihar'!C21+Kalkaji!C21+CP!C21+Rohini!C21+'Model Town'!C21+'Pacific Mall'!C21 -> 3508561.2 | E23: ='Noida Sec - 18'!D21+'Noida Sec -143'!D21+'Faridabad Sec15'!D21+DLF!D21+'Gurgaon Sec-15'!D21+'Paschim Vihar'!D21+Kalkaji!D21+CP!D21+Rohini!D21+'Model Town'!D21+'Pacific Mall'!D21 -> 3615510.4 | F23: ='Noida Sec - 18'!E21+'Noida Sec -143'!E21+'Faridabad Sec15'!E21+DLF!E21+'Gurgaon Sec-15'!E21+'Paschim Vihar'!E21+Kalkaji!E21+CP!E21+Rohini!E21+'Model Town'!E21+'Pacific Mall'!E21 -> 3598622.3 | G23: ='Noida Sec - 18'!F21+'Noida Sec -143'!F21+'Faridabad Sec15'!F21+DLF!F21+'Gurgaon Sec-15'!F21+'Paschim Vihar'!F21+Kalkaji!F21+CP!F21+Rohini!F21+'Model Town'!F21+'Pacific Mall'!F21 -> 3604374.4 | H23: ='Noida Sec - 18'!G21+'Noida Sec -143'!G21+'Faridabad Sec15'!G21+DLF!G21+'Gurgaon Sec-15'!G21+'Paschim Vihar'!G21+Kalkaji!G21+CP!G21+Rohini!G21+'Model Town'!G21+'Pacific Mall'!G21 -> 3630726.1 | I23: ='Noida Sec - 18'!H21+'Noida Sec -143'!H21+'Faridabad Sec15'!H21+DLF!H21+'Gurgaon Sec-15'!H21+'Paschim Vihar'!H21+Kalkaji!H21+CP!H21+Rohini!H21+'Model Town'!H21+'Pacific Mall'!H21 -> 3557967.5 | J23: ='Noida Sec - 18'!I21+'Noida Sec -143'!I21+'Faridabad Sec15'!I21+DLF!I21+'Gurgaon Sec-15'!I21+'Paschim Vihar'!I21+Kalkaji!I21+CP!I21+Rohini!I21+'Model Town'!I21+'Pacific Mall'!I21 -> 3555118 | K23: ='Noida Sec - 18'!J21+'Noida Sec -143'!J21+'Faridabad Sec15'!J21+DLF!J21+'Gurgaon Sec-15'!J21+'Paschim Vihar'!J21+Kalkaji!J21+CP!J21+Rohini!J21+'Model Town'!J21+'Pacific Mall'!J21+'Gurgaon Sec - 10'!J21 -> 3714348.8 | L23: ='Noida Sec - 18'!K21+'Noida Sec -143'!K21+DLF!K21+'Faridabad Sec15'!K21+'Gurgaon Sec-15'!K21+'Gurgaon Sec - 10'!K21+'Paschim Vihar'!K21+Kalkaji!K21+CP!K21+Rohini!K21+'Model Town'!K21+'Pacific Mall'!K21 -> 3886180.8 | M23: ='Noida Sec - 18'!L21+'Noida Sec -143'!L21+DLF!L21+'Faridabad Sec15'!L21+'Gurgaon Sec-15'!L21+'Gurgaon Sec - 10'!L21+'Paschim Vihar'!L21+Kalkaji!L21+CP!L21+Rohini!L21+'Model Town'!L21+'Pacific Mall'!L21 -> 3807968.8 | N23: ='Noida Sec - 18'!M21+'Noida Sec -143'!M21+DLF!M21+'Faridabad Sec15'!M21+'Gurgaon Sec-15'!M21+'Gurgaon Sec - 10'!M21+'Paschim Vihar'!M21+Kalkaji!M21+CP!M21+Rohini!M21+'Model Town'!M21+'Pacific Mall'!M21+'Shalimar Bagh'!M21 -> 3840778.6 | O23: =sum(C23:N23) -> 43833420 | P23: =O23/$O$15 -> 0.226206 | Q23: =AVERAGE(C23:N23)/11 -> 332071.37
A24: AMC | B24: Operation | C24: ='Noida Sec - 18'!B22+'Noida Sec -143'!B22+'Faridabad Sec15'!B22+DLF!B22+'Gurgaon Sec-15'!B22+'Paschim Vihar'!B22+Kalkaji!B22+CP!B22+Rohini!B22+'Model Town'!B22+'Pacific Mall'!B22 -> 97907.75 | D24: ='Noida Sec - 18'!C22+'Noida Sec -143'!C22+'Faridabad Sec15'!C22+DLF!C22+'Gurgaon Sec-15'!C22+'Paschim Vihar'!C22+Kalkaji!C22+CP!C22+Rohini!C22+'Model Town'!C22+'Pacific Mall'!C22 -> 98143.75 | E24: ='Noida Sec - 18'!D22+'Noida Sec -143'!D22+'Faridabad Sec15'!D22+DLF!D22+'Gurgaon Sec-15'!D22+'Paschim Vihar'!D22+Kalkaji!D22+CP!D22+Rohini!D22+'Model Town'!D22+'Pacific Mall'!D22 -> 99313.917 | F24: ='Noida Sec - 18'!E22+'Noida Sec -143'!E22+'Faridabad Sec15'!E22+DLF!E22+'Gurgaon Sec-15'!E22+'Paschim Vihar'!E22+Kalkaji!E22+CP!E22+Rohini!E22+'Model Town'!E22+'Pacific Mall'!E22 -> 99549.917 | G24: ='Noida Sec - 18'!F22+'Noida Sec -143'!F22+'Faridabad Sec15'!F22+DLF!F22+'Gurgaon Sec-15'!F22+'Paschim Vihar'!F22+Kalkaji!F22+CP!F22+Rohini!F22+'Model Town'!F22+'Pacific Mall'!F22 -> 102499.92 | H24: ='Noida Sec - 18'!G22+'Noida Sec -143'!G22+'Faridabad Sec15'!G22+DLF!G22+'Gurgaon Sec-15'!G22+'Paschim Vihar'!G22+Kalkaji!G22+CP!G22+Rohini!G22+'Model Town'!G22+'Pacific Mall'!G22 -> 102499.92 | I24: ='Noida Sec - 18'!H22+'Noida Sec -143'!H22+'Faridabad Sec15'!H22+DLF!H22+'Gurgaon Sec-15'!H22+'Paschim Vihar'!H22+Kalkaji!H22+CP!H22+Rohini!H22+'Model Town'!H22+'Pacific Mall'!H22 -> 105449.5 | J24: ='Noida Sec - 18'!I22+'Noida Sec -143'!I22+'Faridabad Sec15'!I22+DLF!I22+'Gurgaon Sec-15'!I22+'Paschim Vihar'!I22+Kalkaji!I22+CP!I22+Rohini!I22+'Model Town'!I22+'Pacific Mall'!I22 -> 100377.5 | K24: ='Noida Sec - 18'!J22+'Noida Sec -143'!J22+'Faridabad Sec15'!J22+DLF!J22+'Gurgaon Sec-15'!J22+'Paschim Vihar'!J22+Kalkaji!J22+CP!J22+Rohini!J22+'Model Town'!J22+'Pacific Mall'!J22+'Gurgaon Sec - 10'!J22 -> 100257.5 | L24: ='Noida Sec - 18'!K22+'Noida Sec -143'!K22+DLF!K22+'Faridabad Sec15'!K22+'Gurgaon Sec-15'!K22+'Gurgaon Sec - 10'!K22+'Paschim Vihar'!K22+Kalkaji!K22+CP!K22+Rohini!K22+'Model Town'!K22+'Pacific Mall'!K22 -> 104977.5 | M24: ='Noida Sec - 18'!L22+'Noida Sec -143'!L22+DLF!L22+'Faridabad Sec15'!L22+'Gurgaon Sec-15'!L22+'Gurgaon Sec - 10'!L22+'Paschim Vihar'!L22+Kalkaji!L22+CP!L22+Rohini!L22+'Model Town'!L22+'Pacific Mall'!L22 -> 104977.5 | N24: ='Noida Sec - 18'!M22+'Noida Sec -143'!M22+DLF!M22+'Faridabad Sec15'!M22+'Gurgaon Sec-15'!M22+'Gurgaon Sec - 10'!M22+'Paschim Vihar'!M22+Kalkaji!M22+CP!M22+Rohini!M22+'Model Town'!M22+'Pacific Mall'!M22 -> 104977.5 | O24: =sum(C24:N24) -> 1220932.2 | P24: =O24/$O$15 -> 0.0063007217 | Q24: =AVERAGE(C24:N24)/11 -> 9249.4861
A25: Subscription | B25: Operation | C25: ='Noida Sec - 18'!B23+'Noida Sec -143'!B23+'Faridabad Sec15'!B23+DLF!B23+'Gurgaon Sec-15'!B23+'Paschim Vihar'!B23+Kalkaji!B23+CP!B23+Rohini!B23+'Model Town'!B23+'Pacific Mall'!B23 -> 7978.25 | D25: ='Noida Sec - 18'!C23+'Noida Sec -143'!C23+'Faridabad Sec15'!C23+DLF!C23+'Gurgaon Sec-15'!C23+'Paschim Vihar'!C23+Kalkaji!C23+CP!C23+Rohini!C23+'Model Town'!C23+'Pacific Mall'!C23 -> 7978.25 | E25: ='Noida Sec - 18'!D23+'Noida Sec -143'!D23+'Faridabad Sec15'!D23+DLF!D23+'Gurgaon Sec-15'!D23+'Paschim Vihar'!D23+Kalkaji!D23+CP!D23+Rohini!D23+'Model Town'!D23+'Pacific Mall'!D23 -> 7978.25 | F25: ='Noida Sec - 18'!E23+'Noida Sec -143'!E23+'Faridabad Sec15'!E23+DLF!E23+'Gurgaon Sec-15'!E23+'Paschim Vihar'!E23+Kalkaji!E23+CP!E23+Rohini!E23+'Model Town'!E23+'Pacific Mall'!E23 -> 7978.25 | G25: ='Noida Sec - 18'!F23+'Noida Sec -143'!F23+'Faridabad Sec15'!F23+DLF!F23+'Gurgaon Sec-15'!F23+'Paschim Vihar'!F23+Kalkaji!F23+CP!F23+Rohini!F23+'Model Town'!F23+'Pacific Mall'!F23 -> 7978.25 | H25: ='Noida Sec - 18'!G23+'Noida Sec -143'!G23+'Faridabad Sec15'!G23+DLF!G23+'Gurgaon Sec-15'!G23+'Paschim Vihar'!G23+Kalkaji!G23+CP!G23+Rohini!G23+'Model Town'!G23+'Pacific Mall'!G23 -> 7978.25 | I25: ='Noida Sec - 18'!H23+'Noida Sec -143'!H23+'Faridabad Sec15'!H23+DLF!H23+'Gurgaon Sec-15'!H23+'Paschim Vihar'!H23+Kalkaji!H23+CP!H23+Rohini!H23+'Model Town'!H23+'Pacific Mall'!H23 -> 9394.25 | J25: ='Noida Sec - 18'!I23+'Noida Sec -143'!I23+'Faridabad Sec15'!I23+DLF!I23+'Gurgaon Sec-15'!I23+'Paschim Vihar'!I23+Kalkaji!I23+CP!I23+Rohini!I23+'Model Town'!I23+'Pacific Mall'!I23 -> 9394.25 | K25: ='Noida Sec - 18'!J23+'Noida Sec -143'!J23+'Faridabad Sec15'!J23+DLF!J23+'Gurgaon Sec-15'!J23+'Paschim Vihar'!J23+Kalkaji!J23+CP!J23+Rohini!J23+'Model Town'!J23+'Pacific Mall'!J23+'Gurgaon Sec - 10'!J23 -> 9394.25 | L25: ='Noida Sec - 18'!K23+'Noida Sec -143'!K23+DLF!K23+'Faridabad Sec15'!K23+'Gurgaon Sec-15'!K23+'Gurgaon Sec - 10'!K23+'Paschim Vihar'!K23+Kalkaji!K23+CP!K23+Rohini!K23+'Model Town'!K23+'Pacific Mall'!K23 -> 14822.25 | M25: ='Noida Sec - 18'!L23+'Noida Sec -143'!L23+DLF!L23+'Faridabad Sec15'!L23+'Gurgaon Sec-15'!L23+'Gurgaon Sec - 10'!L23+'Paschim Vihar'!L23+Kalkaji!L23+CP!L23+Rohini!L23+'Model Town'!L23+'Pacific Mall'!L23 -> 14822.25 | N25: ='Noida Sec - 18'!M23+'Noida Sec -143'!M23+DLF!M23+'Faridabad Sec15'!M23+'Gurgaon Sec-15'!M23+'Gurgaon Sec - 10'!M23+'Paschim Vihar'!M23+Kalkaji!M23+CP!M23+Rohini!M23+'Model Town'!M23+'Pacific Mall'!M23 -> 14822.25 | O25: =sum(C25:N25) -> 120519 | P25: =O25/$O$15 -> 0.0006219483 | Q25: =AVERAGE(C25:N25)/11 -> 913.02273
A26: Repairs & Maintenance | B26: Operation | C26: ='Noida Sec - 18'!B24+'Noida Sec -143'!B24+'Faridabad Sec15'!B24+DLF!B24+'Gurgaon Sec-15'!B24+'Paschim Vihar'!B24+Kalkaji!B24+CP!B24+Rohini!B24+'Model Town'!B24+'Pacific Mall'!B24 -> 31978 | D26: ='Noida Sec - 18'!C24+'Noida Sec -143'!C24+'Faridabad Sec15'!C24+DLF!C24+'Gurgaon Sec-15'!C24+'Paschim Vihar'!C24+Kalkaji!C24+CP!C24+Rohini!C24+'Model Town'!C24+'Pacific Mall'!C24 -> 17647 | E26: ='Noida Sec - 18'!D24+'Noida Sec -143'!D24+'Faridabad Sec15'!D24+DLF!D24+'Gurgaon Sec-15'!D24+'Paschim Vihar'!D24+Kalkaji!D24+CP!D24+Rohini!D24+'Model Town'!D24+'Pacific Mall'!D24 -> 39307 | F26: ='Noida Sec - 18'!E24+'Noida Sec -143'!E24+'Faridabad Sec15'!E24+DLF!E24+'Gurgaon Sec-15'!E24+'Paschim Vihar'!E24+Kalkaji!E24+CP!E24+Rohini!E24+'Model Town'!E24+'Pacific Mall'!E24 -> 34351 | G26: ='Noida Sec - 18'!F24+'Noida Sec -143'!F24+'Faridabad Sec15'!F24+DLF!F24+'Gurgaon Sec-15'!F24+'Paschim Vihar'!F24+Kalkaji!F24+CP!F24+Rohini!F24+'Model Town'!F24+'Pacific Mall'!F24 -> 143401 | H26: ='Noida Sec - 18'!G24+'Noida Sec -143'!G24+'Faridabad Sec15'!G24+DLF!G24+'Gurgaon Sec-15'!G24+'Paschim Vihar'!G24+Kalkaji!G24+CP!G24+Rohini!G24+'Model Town'!G24+'Pacific Mall'!G24 -> 86511 | I26: ='Noida Sec - 18'!H24+'Noida Sec -143'!H24+'Faridabad Sec15'!H24+DLF!H24+'Gurgaon Sec-15'!H24+'Paschim Vihar'!H24+Kalkaji!H24+CP!H24+Rohini!H24+'Model Town'!H24+'Pacific Mall'!H24 -> 61040 | J26: ='Noida Sec - 18'!I24+'Noida Sec -143'!I24+'Faridabad Sec15'!I24+DLF!I24+'Gurgaon Sec-15'!I24+'Paschim Vihar'!I24+Kalkaji!I24+CP!I24+Rohini!I24+'Model Town'!I24+'Pacific Mall'!I24 -> 136540 | K26: ='Noida Sec - 18'!J24+'Noida Sec -143'!J24+'Faridabad Sec15'!J24+DLF!J24+'Gurgaon Sec-15'!J24+'Paschim Vihar'!J24+Kalkaji!J24+CP!J24+Rohini!J24+'Model Town'!J24+'Pacific Mall'!J24 -> 27917 | L26: ='Noida Sec - 18'!K24+'Noida Sec -143'!K24+DLF!K24+'Faridabad Sec15'!K24+'Gurgaon Sec-15'!K24+'Gurgaon Sec - 10'!K24+'Paschim Vihar'!K24+Kalkaji!K24+CP!K24+Rohini!K24+'Model Town'!K24+'Pacific Mall'!K24 -> 43556 | M26: ='Noida Sec - 18'!L24+'Noida Sec -143'!L24+DLF!L24+'Faridabad Sec15'!L24+'Gurgaon Sec-15'!L24+'Gurgaon Sec - 10'!L24+'Paschim Vihar'!L24+Kalkaji!L24+CP!L24+Rohini!L24+'Model Town'!L24+'Pacific Mall'!L24 -> 200241 | N26: ='Noida Sec - 18'!M24+'Noida Sec -143'!M24+DLF!M24+'Faridabad Sec15'!M24+'Gurgaon Sec-15'!M24+'Gurgaon Sec - 10'!M24+'Paschim Vihar'!M24+Kalkaji!M24+CP!M24+Rohini!M24+'Model Town'!M24+'Pacific Mall'!M24 -> 64438.82 | O26: =sum(C26:N26) -> 886927.82 | P26: =O26/$O$15 -> 0.0045770646 | Q26: =AVERAGE(C26:N26)/11 -> 6719.1502
A27: Miscellaneous Expenses | B27: Accounts | C27: ='Noida Sec - 18'!B25+'Noida Sec -143'!B25+'Faridabad Sec15'!B25+DLF!B25+'Gurgaon Sec-15'!B25+'Paschim Vihar'!B25+Kalkaji!B25+CP!B25+Rohini!B25+'Model Town'!B25+'Pacific Mall'!B25 -> 94756.87 | D27: ='Noida Sec - 18'!C25+'Noida Sec -143'!C25+'Faridabad Sec15'!C25+DLF!C25+'Gurgaon Sec-15'!C25+'Paschim Vihar'!C25+Kalkaji!C25+CP!C25+Rohini!C25+'Model Town'!C25+'Pacific Mall'!C25 -> 110055.62 | E27: ='Noida Sec - 18'!D25+'Noida Sec -143'!D25+'Faridabad Sec15'!D25+DLF!D25+'Gurgaon Sec-15'!D25+'Paschim Vihar'!D25+Kalkaji!D25+CP!D25+Rohini!D25+'Model Town'!D25+'Pacific Mall'!D25 -> 124906.5 | F27: ='Noida Sec - 18'!E25+'Noida Sec -143'!E25+'Faridabad Sec15'!E25+DLF!E25+'Gurgaon Sec-15'!E25+'Paschim Vihar'!E25+Kalkaji!E25+CP!E25+Rohini!E25+'Model Town'!E25+'Pacific Mall'!E25 -> 80255.397 | G27: ='Noida Sec - 18'!F25+'Noida Sec -143'!F25+'Faridabad Sec15'!F25+DLF!F25+'Gurgaon Sec-15'!F25+'Paschim Vihar'!F25+Kalkaji!F25+CP!F25+Rohini!F25+'Model Town'!F25+'Pacific Mall'!F25 -> 284362.95 | H27: ='Noida Sec - 18'!G25+'Noida Sec -143'!G25+'Faridabad Sec15'!G25+DLF!G25+'Gurgaon Sec-15'!G25+'Paschim Vihar'!G25+Kalkaji!G25+CP!G25+Rohini!G25+'Model Town'!G25+'Pacific Mall'!G25 -> 187513.94 | I27: ='Noida Sec - 18'!H25+'Noida Sec -143'!H25+'Faridabad Sec15'!H25+DLF!H25+'Gurgaon Sec-15'!H25+'Paschim Vihar'!H25+Kalkaji!H25+CP!H25+Rohini!H25+'Model Town'!H25+'Pacific Mall'!H25 -> 147122.04 | J27: ='Noida Sec - 18'!I25+'Noida Sec -143'!I25+'Faridabad Sec15'!I25+DLF!I25+'Gurgaon Sec-15'!I25+'Paschim Vihar'!I25+Kalkaji!I25+CP!I25+Rohini!I25+'Model Town'!I25+'Pacific Mall'!I25 -> 181422.14 | K27: ='Noida Sec - 18'!J25+'Noida Sec -143'!J25+'Faridabad Sec15'!J25+DLF!J25+'Gurgaon Sec-15'!J25+'Paschim Vihar'!J25+Kalkaji!J25+CP!J25+Rohini!J25+'Model Town'!J25+'Pacific Mall'!J25 -> 139650.94 | L27: ='Noida Sec - 18'!K25+'Noida Sec -143'!K25+DLF!K25+'Faridabad Sec15'!K25+'Gurgaon Sec-15'!K25+'Gurgaon Sec - 10'!K25+'Paschim Vihar'!K25+Kalkaji!K25+CP!K25+Rohini!K25+'Model Town'!K25+'Pacific Mall'!K25 -> 153833.11 | M27: ='Noida Sec - 18'!L25+'Noida Sec -143'!L25+DLF!L25+'Faridabad Sec15'!L25+'Gurgaon Sec-15'!L25+'Gurgaon Sec - 10'!L25+'Paschim Vihar'!L25+Kalkaji!L25+CP!L25+Rohini!L25+'Model Town'!L25+'Pacific Mall'!L25 -> 294015.03 | N27: ='Noida Sec - 18'!M25+'Noida Sec -143'!M25+DLF!M25+'Faridabad Sec15'!M25+'Gurgaon Sec-15'!M25+'Gurgaon Sec - 10'!M25+'Paschim Vihar'!M25+Kalkaji!M25+CP!M25+Rohini!M25+'Model Town'!M25+'Pacific Mall'!M25 -> 187135.1 | O27: =sum(C27:N27) -> 1985029.6 | P27: =O27/$O$15 -> 0.01024391 | Q27: =AVERAGE(C27:N27)/11 -> 15038.103
A28: CAM | B28: Accounts | C28: ='Noida Sec - 18'!B26+'Noida Sec -143'!B26+'Faridabad Sec15'!B26+DLF!B26+'Gurgaon Sec-15'!B26+'Paschim Vihar'!B26+Kalkaji!B26+CP!B26+Rohini!B26+'Model Town'!B26+'Pacific Mall'!B26 -> 212132.5 | D28: ='Noida Sec - 18'!C26+'Noida Sec -143'!C26+'Faridabad Sec15'!C26+DLF!C26+'Gurgaon Sec-15'!C26+'Paschim Vihar'!C26+Kalkaji!C26+CP!C26+Rohini!C26+'Model Town'!C26+'Pacific Mall'!C26 -> 216928.5 | E28: ='Noida Sec - 18'!D26+'Noida Sec -143'!D26+'Faridabad Sec15'!D26+DLF!D26+'Gurgaon Sec-15'!D26+'Paschim Vihar'!D26+Kalkaji!D26+CP!D26+Rohini!D26+'Model Town'!D26+'Pacific Mall'!D26 -> 219902.5 | F28: ='Noida Sec - 18'!E26+'Noida Sec -143'!E26+'Faridabad Sec15'!E26+DLF!E26+'Gurgaon Sec-15'!E26+'Paschim Vihar'!E26+Kalkaji!E26+CP!E26+Rohini!E26+'Model Town'!E26+'Pacific Mall'!E26 -> 219042.5 | G28: ='Noida Sec - 18'!F26+'Noida Sec -143'!F26+'Faridabad Sec15'!F26+DLF!F26+'Gurgaon Sec-15'!F26+'Paschim Vihar'!F26+Kalkaji!F26+CP!F26+Rohini!F26+'Model Town'!F26+'Pacific Mall'!F26 -> 221288.5 | H28: ='Noida Sec - 18'!G26+'Noida Sec -143'!G26+'Faridabad Sec15'!G26+DLF!G26+'Gurgaon Sec-15'!G26+'Paschim Vihar'!G26+Kalkaji!G26+CP!G26+Rohini!G26+'Model Town'!G26+'Pacific Mall'!G26 -> 221288.5 | I28: ='Noida Sec - 18'!H26+'Noida Sec -143'!H26+'Faridabad Sec15'!H26+DLF!H26+'Gurgaon Sec-15'!H26+'Paschim Vihar'!H26+Kalkaji!H26+CP!H26+Rohini!H26+'Model Town'!H26+'Pacific Mall'!H26 -> 221288.5 | J28: ='Noida Sec - 18'!I26+'Noida Sec -143'!I26+'Faridabad Sec15'!I26+DLF!I26+'Gurgaon Sec-15'!I26+'Paschim Vihar'!I26+Kalkaji!I26+CP!I26+Rohini!I26+'Model Town'!I26+'Pacific Mall'!I26 -> 214880.5 | K28: ='Noida Sec - 18'!J26+'Noida Sec -143'!J26+'Faridabad Sec15'!J26+DLF!J26+'Gurgaon Sec-15'!J26+'Paschim Vihar'!J26+Kalkaji!J26+CP!J26+Rohini!J26+'Model Town'!J26+'Pacific Mall'!J26 -> 212962.5 | L28: ='Noida Sec - 18'!K26+'Noida Sec -143'!K26+DLF!K26+'Faridabad Sec15'!K26+'Gurgaon Sec-15'!K26+'Gurgaon Sec - 10'!K26+'Paschim Vihar'!K26+Kalkaji!K26+CP!K26+Rohini!K26+'Model Town'!K26+'Pacific Mall'!K26 -> 212170.5 | M28: ='Noida Sec - 18'!L26+'Noida Sec -143'!L26+DLF!L26+'Faridabad Sec15'!L26+'Gurgaon Sec-15'!L26+'Gurgaon Sec - 10'!L26+'Paschim Vihar'!L26+Kalkaji!L26+CP!L26+Rohini!L26+'Model Town'!L26+'Pacific Mall'!L26 -> 213194.5 | N28: ='Noida Sec - 18'!M26+'Noida Sec -143'!M26+DLF!M26+'Faridabad Sec15'!M26+'Gurgaon Sec-15'!M26+'Gurgaon Sec - 10'!M26+'Paschim Vihar'!M26+Kalkaji!M26+CP!M26+Rohini!M26+'Model Town'!M26+'Pacific Mall'!M26+'Shalimar Bagh'!M26 -> 221907.39 | O28: =sum(C28:N28) -> 2606986.9 | P28: =O28/$O$15 -> 0.013453572 | Q28: =AVERAGE(C28:N28)/11 -> 19749.901
A29: Ads Account | B29: Accounts | C29: ='Ads Account'!B6 -> 773726.67 | D29: ='Ads Account'!C6 -> 632593.56 | E29: ='Ads Account'!D6 -> 574335.34 | F29: ='Ads Account'!E6 -> 547564.9 | G29: ='Ads Account'!F6 -> 668555.48 | H29: ='Ads Account'!G6 -> 421036.56 | I29: ='Ads Account'!H6 -> 488867.74 | J29: ='Ads Account'!I6 -> 497839.81 | ... N29: ='Ads Account'!M6 -> 711696.38 | O29: =sum(C29:N29) -> 7296855.5 | P29: =O29/$O$15 -> 0.037656028 | Q29: =AVERAGE(C29:N29)/11 -> 55279.208
A30: HO+CK Cost | B30: Accounts | C30: ='Noida Sec - 18'!B27+'Noida Sec -143'!B27+'Faridabad Sec15'!B27+DLF!B27+'Gurgaon Sec-15'!B27+'Paschim Vihar'!B27+Kalkaji!B27+CP!B27+Rohini!B27+'Model Town'!B27+'Pacific Mall'!B27 -> 2677264.4 | D30: ='Noida Sec - 18'!C27+'Noida Sec -143'!C27+'Faridabad Sec15'!C27+DLF!C27+'Gurgaon Sec-15'!C27+'Paschim Vihar'!C27+Kalkaji!C27+CP!C27+Rohini!C27+'Model Town'!C27+'Pacific Mall'!C27 -> 2785745.2 | E30: ='Noida Sec - 18'!D27+'Noida Sec -143'!D27+'Faridabad Sec15'!D27+DLF!D27+'Gurgaon Sec-15'!D27+'Paschim Vihar'!D27+Kalkaji!D27+CP!D27+Rohini!D27+'Model Town'!D27+'Pacific Mall'!D27 -> 2709914.1 | F30: ='Noida Sec - 18'!E27+'Noida Sec -143'!E27+'Faridabad Sec15'!E27+DLF!E27+'Gurgaon Sec-15'!E27+'Paschim Vihar'!E27+Kalkaji!E27+CP!E27+Rohini!E27+'Model Town'!E27+'Pacific Mall'!E27 -> 2900178.6 | G30: ='Noida Sec - 18'!F27+'Noida Sec -143'!F27+'Faridabad Sec15'!F27+DLF!F27+'Gurgaon Sec-15'!F27+'Paschim Vihar'!F27+Kalkaji!F27+CP!F27+Rohini!F27+'Model Town'!F27+'Pacific Mall'!F27 -> 2971472.4 | H30: ='Noida Sec - 18'!G27+'Noida Sec -143'!G27+'Faridabad Sec15'!G27+DLF!G27+'Gurgaon Sec-15'!G27+'Paschim Vihar'!G27+Kalkaji!G27+CP!G27+Rohini!G27+'Model Town'!G27+'Pacific Mall'!G27 -> 2664980.2 | I30: ='Noida Sec - 18'!H27+'Noida Sec -143'!H27+'Faridabad Sec15'!H27+DLF!H27+'Gurgaon Sec-15'!H27+'Paschim Vihar'!H27+Kalkaji!H27+CP!H27+Rohini!H27+'Model Town'!H27+'Pacific Mall'!H27 -> 2748602.5 | J30: ='Noida Sec - 18'!I27+'Noida Sec -143'!I27+'Faridabad Sec15'!I27+DLF!I27+'Gurgaon Sec-15'!I27+'Paschim Vihar'!I27+Kalkaji!I27+CP!I27+Rohini!I27+'Model Town'!I27+'Pacific Mall'!I27 -> 2541424.8 | K30: ='Noida Sec - 18'!J27+'Noida Sec -143'!J27+'Faridabad Sec15'!J27+DLF!J27+'Gurgaon Sec-15'!J27+'Paschim Vihar'!J27+Kalkaji!J27+CP!J27+Rohini!J27+'Model Town'!J27+'Pacific Mall'!J27+'Gurgaon Sec - 10'!J27 -> 2672294.2 | L30: ='Noida Sec - 18'!K27+'Noida Sec -143'!K27+DLF!K27+'Faridabad Sec15'!K27+'Gurgaon Sec-15'!K27+'Gurgaon Sec - 10'!K27+'Paschim Vihar'!K27+Kalkaji!K27+CP!K27+Rohini!K27+'Model Town'!K27+'Pacific Mall'!K27 -> 2729986.8 | M30: ='Noida Sec - 18'!L27+'Noida Sec -143'!L27+DLF!L27+'Faridabad Sec15'!L27+'Gurgaon Sec-15'!L27+'Gurgaon Sec - 10'!L27+'Paschim Vihar'!L27+Kalkaji!L27+CP!L27+Rohini!L27+'Model Town'!L27+'Pacific Mall'!L27 -> 2778963.1 | N30: ='Noida Sec - 18'!M27+'Noida Sec -143'!M27+DLF!M27+'Faridabad Sec15'!M27+'Gurgaon Sec-15'!M27+'Gurgaon Sec - 10'!M27+'Paschim Vihar'!M27+Kalkaji!M27+CP!M27+Rohini!M27+'Model Town'!M27+'Pacific Mall'!M27+'Shalimar Bagh'!M27 -> 3242871.9 | O30: =sum(C30:N30) -> 33423698 | P30: =O30/$O$15 -> 0.17248577 | Q30: =AVERAGE(C30:N30)/11 -> 253209.84
A31: Operating Expenses | C31: =+SUM(C16:C30) -> 17040004 | D31: =+SUM(D16:D30) -> 17270943 | E31: =+SUM(E16:E30) -> 17426834 | F31: =+SUM(F16:F30) -> 17729799 | G31: =+SUM(G16:G30) -> 18135489 | H31: =+SUM(H16:H30) -> 17108218 | I31: =+SUM(I16:I30) -> 16610266 | J31: =+SUM(J16:J30) -> 16313271 | ... N31: =+SUM(N16:N30) -> 19528649 | O31: =sum(C31:N31) -> 2.1029727e+08 | P31: =O31/$O$15 -> 1.0852565 | Q31: =AVERAGE(C31:N31) -> 17524773
A32: Store Level EBITDA | C32: =C15-C31 -> -2337550 | D32: =D15-D31 -> -1473944.9 | E32: =E15-E31 -> -1719586 | F32: =F15-F31 -> -1205458.7 | G32: =G15-G31 -> -1693021.4 | H32: =H15-H31 -> -2307910.6 | I32: =I15-I31 -> -2327658.6 | J32: =J15-J31 -> -2074784.7 | ... N32: =N15-N31 -> 950443.44 | O32: =sum(C32:N32) -> -16520714 | P32: =O32/$O$15 -> -0.085256518 | Q32: =AVERAGE(C32:N32) -> -1376726.2 | S32: 25419194
A33: EBITDA Margin % | C33: =C32/C15 -> -0.15899047 | D33: =D32/D15 -> -0.09330538 | E33: =E32/E15 -> -0.10947723 | F33: =F32/F15 -> -0.072950489 | G33: =G32/G15 -> -0.10296638 | H33: =H32/H15 -> -0.15593667 | I33: =I32/I15 -> -0.16297155 | J33: =J32/J15 -> -0.14571666 | ... N33: =N32/N15 -> 0.046410428 | S33: =O32 -> -16520714
A34: Food Cost | C34: =(C16/C15) -> 0.30497665 | D34: =(D16/D15) -> 0.28457762 | E34: =(E16/E15) -> 0.28879125 | F34: =(F16/F15) -> 0.28678095 | G34: =(G16/G15) -> 0.28498849 | H34: =(H16/H15) -> 0.30287009 | I34: =(I16/I15) -> 0.27808241 | J34: =(J16/J15) -> 0.28036833 | ... N34: =(N16/N15) -> 0.27717627 | S34: =S32+S33 -> 8898479.2
C37: =C32+C30 -> 339714.38 | D37: =D32+D30 -> 1311800.2 | E37: =E32+E30 -> 990328.14 | F37: =F32+F30 -> 1694720 | G37: =G32+G30 -> 1278451 | H37: =H32+H30 -> 357069.61 | I37: =I32+I30 -> 420943.89 | J37: =J32+J30 -> 466640.12 | ... N37: =N32+N30 -> 4193315.4

Sheet Noida Sec - 18
A1: Dosa Coffee - Noida Sector 18 | B1: 45748 | C1: 45778 | D1: 45809 | E1: 45839 | F1: 45870 | G1: 45901 | H1: 45931 | I1: 45962 | J1: 45992 | K1: 46023 | L1: 46054 | M1: 46082 | N1: FY 2025-26
A2: Food Cost Calculation
A3: Opening Stock | B3: 86720 | C3: =B7 -> 80160 | D3: =C7 -> 90114.76 | E3: =D7 -> 88290 | F3: =E7 -> 73436.88 | G3: =F7 -> 76787 | H3: =G7 -> 80448.91 | I3: =H7 -> 77436.86 | J3: =I7 -> 83465.48 | ... M3: =L7 -> 72558 | N3: =+SUM(J3:L3) -> 253855.99
A4: Purchases Food (Less Purchase Return) | B4: 454058.29 | C4: 453168 | D4: 415149 | E4: 471364 | F4: 477271.41 | G4: 426384.89 | H4: 398331 | I4: =398546.35 -> 398546.35 | J4: 396075 | K4: 427467 | L4: =392811.93 -> 392811.93 | M4: 498553 | N4: =sum(B4:M4) -> 5209179.9
A5: Transferred Out | B5: 0 | C5: 0 | D5: 0 | E5: 0 | F5: 0 | G5: 0 | H5: 0 | I5: 0 | J5: 0 | K5: 0 | L5: 0 | M5: 0 | N5: =+SUM(J5:L5) -> 0
A6: Wastage & Date Expired | B6: 28788 | C6: 24643.81 | D6: 13426 | E6: 17770.78 | F6: 15477 | G6: 1278.017 | H6: 15898 | I6: 16758.1 | J6: 12784.81 | K6: 16181.72 | L6: 12642.26 | M6: 14347 | N6: =+SUM(J6:L6) -> 41608.79
A7: Closing Stock | B7: 80160 | C7: 90114.76 | D7: 88290 | E7: 73436.88 | F7: 76787 | G7: 80448.91 | H7: 77436.86 | I7: 83465.48 | J7: 92362 | K7: 78028.51 | L7: 72558 | M7: 76058 | N7: =sum(B7:M7) -> 969146.4
A9: Gross Revenue | B9: =1787921.99*1.05+36815.11*1.05 -> 1915974 | C9: =1685620.88*1.05+42010.58*1.05 -> 1814013 | D9: =+(1545618-112.34)*1.05+37198*1.05+90*1.05 -> 1661933.3 | E9: =1871385.89*1.05 -> 1964955.2 | F9: =1797909.74*1.05 -> 1887805.2 | G9: =1583571.54*1.05 -> 1662750.1 | H9: =1532946.93*1.05+35979*1.05 -> 1647372.2 | I9: =1444428.39*1.05+10*1.05+33558.65*1.05 -> 1551896.9 | J9: =29901*1.05+1426925*1.05 -> 1529667.3 | K9: =1719108.36*1.05+36148.88*1.05 -> 1843020.1 | L9: =1558225.61*1.05+45729.2*1.05 -> 1684152.6 | M9: =1771108.35*1.05+51734.88*1.05 -> 1913985.4 | N9: =+SUM(B9:M9) -> 21077525
A10: Catering & Fairs | B10: 0 | C10: 0 | D10: =32400*1.05 -> 34020 | E10: 0 | F10: 0 | G10: 0 | H10: 0 | I10: 0 | J10: 0 | K10: 0 | L10: 0 | M10: 0 | N10: =+SUM(B10:M10) -> 34020
A11: Less Tax | B11: =(B9+B10)/1.05*0.05 -> 91236.855 | C11: =(C9+C10)/1.05*0.05 -> 86381.573 | D11: =(D9+D10)/1.05*0.05 -> 80759.683 | E11: =(E9+E10)/1.05*0.05 -> 93569.295 | F11: =(F9+F10)/1.05*0.05 -> 89895.487 | G11: =(G9+G10)/1.05*0.05 -> 79178.577 | H11: =(H9+H10)/1.05*0.05 -> 78446.296 | I11: =(I9+I10)/1.05*0.05 -> 73899.852 | ... M11: =(M9+M10)/1.05*0.05 -> 91142.162 | N11: =+SUM(B11:M11) -> 1005311.7
A12: Less Commission | B12: =84300.76+1183.6+15174.14+213.1+52109.11+9379.64+1239.49+223.11 -> 163822.95 | C12: =96874.61+242.1+17195.34+51062.15+9769.5+3110.39+559.87+9213.94+1763.37 -> 189791.27 | D12: =1891+85744+340.48+15434.03+54674.8+9841+905.9+699.28+163.06+125.87+196.32+35.34 -> 170051.08 | E12: =72531.95+13115.76+3743+99976+18669.49+604.08+55.44+53.3 -> 208749.02 | F12: =+96716.72+17409.016+60321.26+10857.86+636.32+114.54+132.74 -> 186188.46 | G12: =89234.7+2306.97+16062.25+415.25+31769.85+11597.61+7806.18+813.8+146.49 -> 160153.1 | H12: =85644.09*1.18+45275.72*1.18+(391.7+1203.78)*1.18 -> 156368.04 | I12: =29708.63+77546.41*1.18+2034.33*1.18+11992.48*1.18+1094.76*1.18 -> 139056.85 | J12: =70758.73+12736.57+40294+7253+1464.33+263.58 -> 132770.21 | K12: =86873.36*1.18+46746.35*1.18+3213.17*1.18 -> 161462.8 | L12: =38755.77*1.18+107691.44*1.18+2319.19*1.18+159.77 -> 175704.12 | M12: =43214.79*1.18+122071.62*1.18+3600.28*1.18+59.56 -> 199345.85 | N12: =+SUM(B12:M12) -> 2043463.7
A13: Net Revenues from F&B Sales | B13: =B9+B10-B11-B12 -> 1660914.1 | C13: =C9+C10-C11-C12 -> 1537840.2 | D13: =D9+D10-D11-D12 -> 1445142.6 | E13: =E9+E10-E11-E12 -> 1662636.9 | F13: =F9+F10-F11-F12 -> 1611721.3 | G13: =G9+G10-G11-G12 -> 1423418.4 | H13: =H9+H10-H11-H12 -> 1412557.9 | I13: =I9+I10-I11-I12 -> 1338940.2 | ... M13: =M9+M10-M11-M12 -> 1623497.4 | N13: =sum(B13:M13) -> 18062770 | O13: =N13/$N$7 -> 18.637814
A14: F&B Cost | B14: =+B3+B4-B5-B7 -> 460618.29 | C14: =+C3+C4-C5-C7 -> 443213.24 | D14: =+D3+D4-D5-D7 -> 416973.76 | E14: =+E3+E4-E5-E7 -> 486217.12 | F14: =+F3+F4-F5-F7 -> 473921.29 | G14: =+G3+G4-G5-G7 -> 422722.98 | H14: =+H3+H4-H5-H7 -> 401343.05 | I14: =+I3+I4-I5-I7 -> 392517.73 | ... M14: =+M3+M4-M5-M7 -> 495053 | N14: =sum(B14:M14) -> 5219841.9 | O14: =N14/$N$13 -> 0.28898347
A15: Electricity | B15: =68475+4000 -> 72475 | C15: =75565+1256 -> 76821 | D15: =72595+4000 -> 76595 | E15: =71404+3500 -> 74904 | F15: 72778 | G15: =66596 -> 66596 | H15: 61278 | I15: 52303 | J15: 38359 | K15: =40600+1950 -> 42550 | L15: 43171 | M15: 56365 | N15: =sum(B15:M15) -> 734195 | O15: =N15/$N$13 -> 0.040646867
A16: Telephone/Internet | B16: =6018/3 -> 2006 | C16: =6018/3+300 -> 2306 | D16: =6018/3 -> 2006 | E16: =6018/3 -> 2006 | F16: =6018/3+302 -> 2308 | G16: =6018/3+602 -> 2608 | H16: =6018/3 -> 2006 | I16: =6018/3 -> 2006 | J16: =6018/3+300 -> 2306 | K16: =6018/4+300 -> 1804.5 | L16: =6018/4+300 -> 1804.5 | M16: =6018/4 -> 1504.5 | N16: =sum(B16:M16) -> 24671.5 | O16: =N16/$N$13 -> 0.0013658758
A17: Gas | B17: 58116 | C17: 78810 | D17: =44412 -> 44412 | E17: =67224.8 -> 67224.8 | F17: =64925.92 -> 64925.92 | G17: 61512 | H17: 63546.91 | I17: 61985 | J17: 64850 | K17: 79501.91 | L17: =54863.86 -> 54863.86 | M17: =73199.17 -> 73199.17 | N17: =sum(B17:M17) -> 772947.57 | O17: =N17/$N$13 -> 0.042792306
A18: Rent & Revenue Share | B18: =342200 -> 342200 | C18: =342200 -> 342200 | D18: =342200 -> 342200 | E18: =342200 -> 342200 | F18: =342200 -> 342200 | G18: =342200 -> 342200 | H18: =342200 -> 342200 | I18: =342200 -> 342200 | ... M18: =342200 -> 342200 | N18: =sum(B18:M18) -> 4106400 | O18: =N18/$N$13 -> 0.22734055
A19: Insurance | B19: 0 | C19: =12189/12 -> 1015.75 | D19: =12189/12 -> 1015.75 | E19: =12189/12 -> 1015.75 | F19: =12189/12 -> 1015.75 | G19: =12189/12 -> 1015.75 | H19: =12189/12 -> 1015.75 | I19: =12189/12 -> 1015.75 | J19: =12189/12 -> 1015.75 | ... M19: =12189/12 -> 1015.75 | N19: =sum(B19:M19) -> 11173.25 | O19: =N19/$N$13 -> 0.00061857899
A20: Software | B20: 6018 | C20: 6018 | D20: 6018 | E20: 6018 | F20: 6018 | G20: 6018 | H20: =72216/12 -> 6018 | I20: =72216/12 -> 6018 | J20: =72216/12 -> 6018 | K20: =72216/12 -> 6018 | L20: =72216/12 -> 6018 | M20: =72216/12 -> 6018 | N20: =sum(B20:M20) -> 72216 | O20: =N20/$N$13 -> 0.0039980579
A21: Staff Salary | B21: =11400+326927.36+165407/12 -> 352111.28 | C21: =336715+1473+165407/12 -> 351971.92 | D21: =345216+165407/12 -> 358999.92 | E21: =376724+165407/12 -> 390507.92 | F21: =378713.01+165407/12 -> 392496.93 | G21: =377946.01+165407/12 -> 391729.93 | H21: =165407/12+367668 -> 381451.92 | I21: =165407/12+392636.01 -> 406419.93 | J21: =165407/12+377724 -> 391507.92 | K21: =165407/12+381962 -> 395745.92 | L21: =165407/12++386979 -> 400762.92 | M21: =165407/12+398773 -> 412556.92 | N21: =sum(B21:M21) -> 4626263.4 | O21: =N21/$N$13 -> 0.25612148
A22: AMC | B22: =1416/3+4720+2950 -> 8142 | C22: =1416/3+5192+2950 -> 8614 | D22: =1416/3+5192+2950 -> 8614 | E22: =5192+2950 -> 8142 | F22: =5192+2950 -> 8142 | G22: =5192+2950 -> 8142 | H22: =5192+2950+35395/12 -> 11091.583 | I22: =4720+2950+35395/12 -> 10619.583 | J22: =35395/12+4720+2950 -> 10619.583 | K22: =35395/12+4720+2950 -> 10619.583 | L22: =35395/12+4720+2950 -> 10619.583 | M22: =35395/12+4720+2950 -> 10619.583 | N22: =sum(B22:M22) -> 113985.5 | O22: =N22/$N$13 -> 0.0063105216
A23: Subscription | B23: 0 | C23: 0 | D23: 0 | E23: 0 | F23: 0 | G23: 0 | H23: =2124/3 -> 708 | I23: =2124/3 -> 708 | J23: =2124/3 -> 708 | K23: =3304/3 -> 1101.3333 | L23: =3304/3 -> 1101.3333 | M23: =3304/3 -> 1101.3333 | N23: =sum(B23:M23) -> 5428 | O23: =N23/$N$13 -> 0.00030050762
A24: Repairs & Maintenance | B24: 260 | C24: 400 | D24: 8271 | E24: 0 | F24: 10980 | G24: 10042 | H24: 150 | I24: 40002 | J24: 4130 | K24: 2000 | L24: 4130 | M24: 660 | N24: =sum(B24:M24) -> 81025 | O24: =N24/$N$13 -> 0.0044857461
A25: Miscellaneous Expenses | B25: =14600.36-4000 -> 10600.36 | C25: =13175.89-1256 -> 11919.89 | D25: =15061+8500/6 -> 16477.667 | E25: =15408.7+8500/6 -> 16825.367 | F25: =58866.58+8500/6 -> 60283.247 | G25: =17813.03+8500/6 -> 19229.697 | H25: =14874.74+8500/6 -> 16291.407 | I25: =13449.65+8500/6 -> 14866.317 | J25: 5081 | K25: =19564.71 -> 19564.71 | L25: 21974 | M25: =17149.9 -> 17149.9 | N25: =sum(B25:M25) -> 230263.56 | O25: =N25/$N$13 -> 0.012747965
A26: CAM | B26: 0 | C26: 0 | D26: 0 | E26: 0 | F26: 0 | G26: 0 | H26: 0 | I26: 0 | J26: 0 | K26: 0 | L26: 0 | M26: 0 | N26: =sum(B26:M26) -> 0 | O26: =N26/$N$13 -> 0
A27: HO+CK Cost | B27: =HO!D29 -> 302446.54 | C27: =HO!H29 -> 271192.72 | D27: =HO!L29 -> 249325.18 | E27: =HO!P29 -> 291808.56 | F27: =HO!D42 -> 291269.26 | G27: =HO!H42 -> 256304.27 | H27: =HO!L42 -> 271838.34 | I27: =HO!P42 -> 238987.2 | J27: =HO!D55 -> 234417.61 | K27: =HO!H55 -> 244902.19 | L27: =HO!L55 -> 221617.49 | M27: =HO!P55 -> 257081.42 | N27: =sum(B27:M27) -> 3131190.7 | O27: =N27/$N$13 -> 0.17335053
A28: Operating Expenses | B28: =+SUM(B14:B27) -> 1614993.5 | C28: =+SUM(C14:C27) -> 1594482.5 | D28: =+SUM(D14:D27) -> 1530908.3 | E28: =+SUM(E14:E27) -> 1686869.5 | F28: =+SUM(F14:F27) -> 1726338.4 | G28: =+SUM(G14:G27) -> 1588120.6 | H28: =+SUM(H14:H27) -> 1558939 | I28: =+SUM(I14:I27) -> 1569648.5 | ... M28: =+SUM(M14:M27) -> 1674524.6 | N28: =sum(B28:M28) -> 19129601 | O28: =N28/$N$13 -> 1.0590625
A29: Store Level EBITDA | B29: =B13-B28 -> 45920.686 | C29: =C13-C28 -> -56642.324 | D29: =D13-D28 -> -85765.691 | E29: =E13-E28 -> -24232.646 | F29: =F13-F28 -> -114617.11 | G29: =G13-G28 -> -164702.18 | H29: =H13-H28 -> -146381.07 | I29: =I13-I28 -> -230708.31 | ... M29: =M13-M28 -> -51027.194 | N29: =sum(B29:M29) -> -1066831.5 | O29: =N29/$N$13 -> -0.059062453
A30: Food Cost | B30: =(B14/B13) -> 0.27732818 | C30: =(C14/C13) -> 0.28820501 | D30: =(D14/D13) -> 0.28853469 | E30: =(E14/E13) -> 0.29243735 | F30: =(F14/F13) -> 0.29404668 | G30: =(G14/G13) -> 0.29697731 | H30: =(H14/H13) -> 0.28412503 | I30: =(I14/I13) -> 0.29315554 | ... M30: =(M14/M13) -> 0.30492997
B32: =B29+B27 -> 348367.22 | C32: =C29+C27 -> 214550.39 | D32: =D29+D27 -> 163559.49 | E32: =E29+E27 -> 267575.92 | F32: =F29+F27 -> 176652.15 | G32: =G29+G27 -> 91602.087 | H32: =H29+H27 -> 125457.27 | I32: =I29+I27 -> 8278.8869 | ... M32: =M29+M27 -> 206054.22
B33: =B32/B13 -> 0.20974427 | C33: =C32/C13 -> 0.1395141 | D33: =D32/D13 -> 0.11317879 | E33: =E32/E13 -> 0.16093467 | F33: =F32/F13 -> 0.10960465 | G33: =G32/G13 -> 0.06435359 | H33: =H32/H13 -> 0.088815667 | I33: =I32/I13 -> 0.0061831641 | ... M33: =M32/M13 -> 0.12691996

Sheet Noida Sec -143
A1: Dosa Coffee - Noida Sector 143 | B1: 45748 | C1: 45778 | D1: 45809 | E1: 45839 | F1: 45870 | G1: 45901 | H1: 45931 | I1: 45962 | J1: 45992 | K1: 46023 | L1: 46054 | M1: 46082 | N1: FY 2025-26
A2: Food Cost Calculation
A3: Opening Stock | B3: 113262.35 | C3: =B7 -> 121260 | D3: =C7 -> 137987.57 | E3: =D7 -> 143225 | F3: =E7 -> 166002.72 | G3: =F7 -> 101188.84 | H3: =G7 -> 111470.17 | I3: =H7 -> 113745 | J3: =I7 -> 115286.64 | ... M3: =L7 -> 102469.89 | N3: =+SUM(J3:L3) -> 333948.64
A4: Purchases Food (Less Purchase Return) | B4: 231341.81 | C4: 240232.19 | D4: 253530.33 | E4: 279888.38 | F4: 260746 | G4: 248834.84 | H4: 229757 | I4: 230448.39 | J4: 230500 | K4: 253056.82 | L4: 233249.39 | M4: 277179 | N4: =sum(B4:M4) -> 2968764.1
A5: Transferred Out | B5: 0 | C5: 0 | D5: 0 | E5: 0 | F5: 0 | G5: 0 | H5: 0 | I5: 0 | J5: 0 | K5: 0 | L5: 0 | M5: 0 | N5: =+SUM(J5:L5) -> 0
A6: Wastage & Date Expired | B6: 16378 | C6: 18212.56 | D6: 26508 | E6: 29066 | F6: 47148 | G6: 34694.08 | H6: 35522 | I6: 87346 | J6: 27518.84 | K6: 27885 | L6: 22240.38 | M6: 28820 | N6: =+SUM(J6:L6) -> 77644.22
A7: Closing Stock | B7: 121260 | C7: 137987.57 | D7: 143225 | E7: 166002.72 | F7: 101188.84 | G7: 111470.17 | H7: 113745 | I7: 115286.64 | J7: 114441 | K7: 104221 | L7: 102469.89 | M7: 103840.45 | N7: =sum(B7:M7) -> 1435138.3
A9: Gross Revenue | B9: =829820.4*1.05+26602.15*1.05 -> 899243.68 | C9: =907085.57*1.05+28781.62*1.05 -> 982660.55 | D9: =867177.71*1.05+27659.83*1.05 -> 939579.42 | E9: =999672.5*1.05 -> 1049656.1 | F9: =965928.68*1.05 -> 1014225.1 | G9: =908088.2*1.05 -> 953492.61 | H9: =845479.53*1.05+25230.54*1.05 -> 914245.57 | I9: =856139.23*1.05+26555.06*1.05 -> 926829 | J9: =829309*1.05+24974.33*1.05 -> 896997.5 | K9: =907487.66*1.05+26687.72*1.05 -> 980884.15 | L9: =843829.49*1.05+30669.41*1.05 -> 918223.84 | M9: =946354.9*1.05+37852.19*1.05 -> 1033417.4 | N9: =+SUM(B9:M9) -> 11509455
A10: Catering & Fairs | B10: 0 | C10: 0 | D10: 0 | E10: 0 | F10: 0 | G10: 0 | H10: 0 | I10: 0 | J10: 0 | K10: 0 | L10: 0 | M10: 0 | N10: =+SUM(B10:M10) -> 0
A11: Less Tax | B11: =(B9+B10)/1.05*0.05 -> 42821.128 | C11: =(C9+C10)/1.05*0.05 -> 46793.359 | D11: =(D9+D10)/1.05*0.05 -> 44741.877 | E11: =(E9+E10)/1.05*0.05 -> 49983.625 | F11: =(F9+F10)/1.05*0.05 -> 48296.434 | G11: =(G9+G10)/1.05*0.05 -> 45404.41 | H11: =(H9+H10)/1.05*0.05 -> 43535.503 | I11: =(I9+I10)/1.05*0.05 -> 44134.715 | ... M11: =(M9+M10)/1.05*0.05 -> 49210.355 | N11: =+SUM(B11:M11) -> 548069.29
A12: Less Commission | B12: =61143.68+540.18+11005.86+97.24+26972.86+4855.17+426.05+76.69 -> 105117.73 | C12: =66745.66+101.36+11912.86+21444.12+3441.69+518.79+93.39+3859.95+619.5 -> 108737.32 | D12: =670.77+63812.93+120.74+11486.33+33118.08+5961+215.75+102.44+38.84+18.44 -> 115545.32 | E12: =41812.54+7526.21+421+61793+11198.6+315.68+47.77+9.05+7.93 -> 123131.78 | F12: =57331.77+10319.71+31488.48+5667.97+521.9+93.94 -> 105423.77 | G12: =59964.66+908.91+10793.64+163.6+15035.37+8486.75+4233.97+468.56+84.34+52.05 -> 100191.85 | H12: =58875.1*1.18+30533*1.18+(903.9+449.75)*1.18 -> 107098.87 | I12: =22678.8*1.18+61970.33*1.18+373.73*1.18+7494.7*1.18+609.37*1.18 -> 109889.78 | J12: =58818.26+10587+30107.66+5419+1872+336.97 -> 107140.89 | K12: =62350.76*1.18+36094.47*1.18+2073.9*1.18 -> 118612.57 | L12: =23049.55*1.18+72317.5*1.18+1444.71*1.18+236.09 -> 114473.97 | M12: =30301.84*1.18+88424.41*1.18+2133.72*1.18+239.65 -> 142854.41 | N12: =+SUM(B12:M12) -> 1358218.3
A13: Net Revenues from F&B Sales | B13: =B9+B10-B11-B12 -> 751304.82 | C13: =C9+C10-C11-C12 -> 827129.87 | D13: =D9+D10-D11-D12 -> 779292.22 | E13: =E9+E10-E11-E12 -> 876540.72 | F13: =F9+F10-F11-F12 -> 860504.91 | G13: =G9+G10-G11-G12 -> 807896.35 | H13: =H9+H10-H11-H12 -> 763611.2 | I13: =I9+I10-I11-I12 -> 772804.51 | ... M13: =M9+M10-M11-M12 -> 841352.68 | N13: =sum(B13:M13) -> 9603167.5 | O13: =N13/$N$7 -> 6.691458
A14: F&B Cost | B14: =+B3+B4-B5-B7 -> 223344.16 | C14: =+C3+C4-C5-C7 -> 223504.62 | D14: =+D3+D4-D5-D7 -> 248292.9 | E14: =+E3+E4-E5-E7 -> 257110.66 | F14: =+F3+F4-F5-F7 -> 325559.88 | G14: =+G3+G4-G5-G7 -> 238553.51 | H14: =+H3+H4-H5-H7 -> 227482.17 | I14: =+I3+I4-I5-I7 -> 228906.75 | ... M14: =+M3+M4-M5-M7 -> 275808.44 | N14: =sum(B14:M14) -> 2978186 | O14: =N14/$N$7 -> 2.075191
A15: Electricity | B15: 41415 | C15: 42059 | D15: =43669 -> 43669 | E15: =44349 -> 44349 | F15: =41826 -> 41826 | G15: 43347 | H15: 40181 | I15: 35861 | J15: 35136 | K15: =33777 -> 33777 | L15: =32865 -> 32865 | M15: 35000 | N15: =sum(B15:M15) -> 469485 | O15: =N15/$N$7 -> 0.32713572
A16: Telephone/Internet | D16: =2700+489 -> 3189 | E16: =2700 -> 2700 | F16: =1060 -> 1060 | G16: =489+1060 -> 1549 | H16: =1060 -> 1060 | I16: =1060+489/2 -> 1304.5 | J16: =1060+489/2 -> 1304.5 | K16: =1060+489 -> 1549 | L16: =1060+489 -> 1549 | M16: =1060 -> 1060 | N16: =sum(B16:M16) -> 16325 | O16: =N16/$N$7 -> 0.01137521
A17: Gas | B17: 0 | C17: 0 | D17: 0 | E17: 0 | F17: 0 | G17: 0 | H17: 0 | I17: 0 | J17: 0 | K17: 0 | L17: 0 | M17: 0 | N17: =sum(B17:M17) -> 0 | O17: =N17/$N$7 -> 0
A18: Rent & Revenue Share | B18: 173000 | C18: 204140 | D18: 204140 | E18: 204140 | F18: 204140 | G18: 204140 | H18: 204140 | I18: 204140 | J18: =129837.95 -> 129837.95 | K18: =141767.93 -> 141767.93 | L18: =132657 -> 132657 | M18: =M13*0.175 -> 147236.72 | N18: =sum(B18:M18) -> 2153479.6 | O18: =N18/$N$7 -> 1.5005381
A19: Insurance | B19: 0 | C19: =9708.84/12 -> 809.07 | D19: =9708.84/12 -> 809.07 | E19: =9708.84/12 -> 809.07 | F19: =9708.84/12 -> 809.07 | G19: =9708.84/12 -> 809.07 | H19: =9708.84/12 -> 809.07 | I19: =9708.84/12 -> 809.07 | J19: =9708.84/12 -> 809.07 | ... M19: =9708.84/12 -> 809.07 | N19: =sum(B19:M19) -> 8899.77
A20: Software | B20: 7857 | C20: 7857 | D20: 7857 | E20: 7857 | F20: 7857 | G20: 7857 | H20: 7857 | I20: 7857 | J20: 7857 | K20: 7857 | L20: =69207/12 -> 5767.25 | M20: =69207/12 -> 5767.25 | N20: =sum(B20:M20) -> 90104.5 | O20: =N20/$N$7 -> 0.062784542
A21: Staff Salary | B21: =8000+221061.04+105791/12 -> 237876.96 | C21: =211124+2000+8000+3071+105791/12 -> 233010.92 | D21: =232145+8000+1600+105791/12 -> 250560.92 | E21: =239820+8000+105791/12 -> 256635.92 | F21: =231421.13+8000+4790+105791/12 -> 253027.05 | G21: =239413+8000+105791/12 -> 256228.92 | H21: =105791/12+8000+2000+240334.03 -> 259149.95 | I21: =105791/12+8000+199586.03 -> 216401.95 | J21: =105791/12+212033+8000+2000 -> 230848.92 | K21: =105791/12+8000+2000+223872 -> 242687.92 | L21: =105791/12+8000+207909+2000 -> 226724.92 | M21: =105791/12+8000+2000+209600 -> 228415.92 | N21: =sum(B21:M21) -> 2891570.2 | O21: =N21/$N$7 -> 2.0148374
A22: AMC | B22: =1416/3+4720+2950 -> 8142 | C22: =1416/3+5192+2950 -> 8614 | D22: =1416/3+5192+2950 -> 8614 | E22: =5192+2950 -> 8142 | F22: =5192+2950 -> 8142 | G22: =5192+2950 -> 8142 | H22: =5192+2950 -> 8142 | I22: =4720+2950 -> 7670 | J22: =4720+2950 -> 7670 | K22: =4720+2950 -> 7670 | L22: =4720+2950 -> 7670 | M22: =4720+2950 -> 7670 | N22: =sum(B22:M22) -> 96288 | O22: =N22/$N$7 -> 0.067093186
A23: Subscription | H23: =2124/3 -> 708 | I23: =2124/3 -> 708 | J23: =2124/3 -> 708 | K23: =3304/3 -> 1101.3333 | L23: =3304/3 -> 1101.3333 | M23: =3304/3 -> 1101.3333 | N23: =sum(B23:M23) -> 5428 | O23: =N23/$N$7 -> 0.0037822139
A24: Repairs & Maintenance | B24: 2050 | C24: 2086 | D24: 650 | E24: 0 | F24: 8800 | G24: 1403 | H24: 829 | I24: 0 | J24: 4130 | K24: 90 | L24: 200 | M24: 0 | N24: =sum(B24:M24) -> 20238 | O24: =N24/$N$7 -> 0.014101777
A25: Miscellaneous Expenses | B25: =2236.31 -> 2236.31 | C25: 10836.2 | D25: 6437.72 | E25: 3523 | F25: 9397.52 | G25: 12884.26 | H25: 4402.74 | I25: 8665.01 | J25: 5081 | K25: 6929.78 | L25: 8029 | M25: =6273.05 -> 6273.05 | N25: =sum(B25:M25) -> 84695.59 | O25: =N25/$N$7 -> 0.05901563
A26: CAM | B26: 21240 | C26: 26036 | D26: 29010 | E26: 28150 | F26: 30396 | G26: 30396 | H26: 30396 | I26: 23988 | J26: 22070 | K26: 21278 | L26: 22302 | M26: 21972 | N26: =sum(B26:M26) -> 307234 | O26: =N26/$N$7 -> 0.21407972
A27: HO+CK Cost | B27: =HO!D30 -> 136809.93 | C27: =HO!H30 -> 145861.45 | D27: =HO!L30 -> 134448.44 | E27: =HO!P30 -> 153841.22 | F27: =HO!D43 -> 155509.91 | G27: =HO!H43 -> 145471.83 | H27: =HO!L43 -> 146952.42 | I27: =HO!P43 -> 137937.74 | J27: =HO!D56 -> 132277.92 | K27: =HO!H56 -> 125319.24 | L27: =HO!L56 -> 117930.85 | M27: =HO!P56 -> 133228.51 | N27: =sum(B27:M27) -> 1665589.5 | O27: =N27/$N$7 -> 1.1605777
A28: Operating Expenses | B28: =+SUM(B14:B27) -> 853971.35 | C28: =+SUM(C14:C27) -> 904814.25 | D28: =+SUM(D14:D27) -> 937678.05 | E28: =+SUM(E14:E27) -> 967257.87 | F28: =+SUM(F14:F27) -> 1046524.4 | G28: =+SUM(G14:G27) -> 950781.58 | H28: =+SUM(H14:H27) -> 932109.35 | I28: =+SUM(I14:I27) -> 874249.02 | ... M28: =+SUM(M14:M27) -> 864342.29 | N28: =sum(B28:M28) -> 10787523 | O28: =N28/$N$7 -> 7.5167134
A29: Store Level EBITDA | B29: =B13-B28 -> -102666.53 | C29: =C13-C28 -> -77684.385 | D29: =D13-D28 -> -158385.83 | E29: =E13-E28 -> -90717.149 | F29: =F13-F28 -> -186019.51 | G29: =G13-G28 -> -142885.23 | H29: =H13-H28 -> -168498.14 | I29: =I13-I28 -> -101444.5 | ... M29: =M13-M28 -> -22989.614 | N29: =sum(B29:M29) -> -1184355.7 | O29: =N29/$N$7 -> -0.82525548
A30: Food Cost | B30: =(B14/B13) -> 0.29727503 | C30: =(C14/C13) -> 0.27021708 | D30: =(D14/D13) -> 0.31861334 | E30: =(E14/E13) -> 0.29332426 | F30: =(F14/F13) -> 0.37833588 | G30: =(G14/G13) -> 0.29527737 | H30: =(H14/H13) -> 0.29790313 | I30: =(I14/I13) -> 0.29620266 | ... M30: =(M14/M13) -> 0.32781549
B32: =B29+B27 -> 34143.393 | C32: =C29+C27 -> 68177.063 | D32: =D29+D27 -> -23937.387 | E32: =E29+E27 -> 63124.073 | F32: =F29+F27 -> -30509.607 | G32: =G29+G27 -> 2586.5933 | H32: =H29+H27 -> -21545.722 | I32: =I29+I27 -> 36493.236 | ... M32: =M29+M27 -> 110238.9
B33: =B32/B13 -> 0.04544546 | C33: =C32/C13 -> 0.082426069 | D33: =D32/D13 -> -0.03071683 | E33: =E32/E13 -> 0.072014992 | F33: =F32/F13 -> -0.035455471 | G33: =G32/G13 -> 0.0032016401 | H33: =H32/H13 -> -0.028215565 | I33: =I32/I13 -> 0.04722182 | ... M33: =M32/M13 -> 0.13102579

Sheet DLF
A1: Dosa Coffee - DLF | B1: 45748 | C1: 45778 | D1: 45809 | E1: 45839 | F1: 45870 | G1: 45901 | H1: 45931 | I1: 45962 | J1: 45992 | K1: 46023 | L1: 46054 | M1: 46082 | N1: FY 2025-26
A2: Food Cost Calculation
A3: Opening Stock | B3: 69947.38 | C3: =B7 -> 59258 | D3: =C7 -> 69444.99 | E3: =D7 -> 60044 | F3: =E7 -> 45426.98 | G3: =F7 -> 53808.21 | H3: =G7 -> 58929 | I3: =H7 -> 48334.34 | J3: =I7 -> 50585.84 | ... L3: =K7 -> 53529.27 | M3: 45608 | N3: =+SUM(J3:L3) -> 160335.81
A4: Purchases Food (Less Purchase Return) | B4: 320692 | C4: 313947 | D4: 297249.26 | E4: 314795.51 | F4: 271499.59 | G4: 248652.14 | H4: 204359.52 | I4: =223183.03 -> 223183.03 | J4: 209421 | K4: 247161 | L4: 267297 | M4: 353180 | N4: =sum(B4:M4) -> 3271437
A5: Transferred Out | B5: 0 | C5: 188.2 | D5: 869.27 | E5: 0 | F5: 0 | G5: 0 | H5: 0 | I5: 3012 | J5: 2081 | K5: 313.08 | L5: 0 | M5: 2549 | N5: =+SUM(J5:L5) -> 2394.08
A6: Wastage & Date Expired | B6: 13084 | C6: 12747.4 | D6: 10061.5 | E6: 12870 | F6: 11107.82 | G6: 10476.72 | H6: 11336.65 | I6: 12109 | J6: 9660 | K6: 7806.86 | L6: 10990.87 | M6: 13146 | N6: =+SUM(J6:L6) -> 28457.73
A7: Closing Stock | B7: 59258 | C7: 69444.99 | D7: 60044 | E7: 45426.98 | F7: 53808.21 | G7: 58929 | H7: 48334.34 | I7: 50585.84 | J7: 56220.7 | K7: 53529.27 | L7: 42647.35 | M7: 53662.56 | N7: =sum(B7:M7) -> 651891.24
A9: Gross Revenue | B9: =1108957.67*1.05+21479.66*1.05 -> 1186959.2 | C9: =1087356.68*1.05+27414.98*1.05 -> 1170510.2 | D9: =1146158*1.05+28806*1.05 -> 1233712.2 | E9: =1413614.41*1.05 -> 1484295.1 | F9: =1178231.92*1.05 -> 1237143.5 | G9: =1144949.94*1.05 -> 1202197.4 | H9: =987131.77*1.05+23319*1.05 -> 1060973.3 | I9: =1025553.59*1.05+21467.61*1.05 -> 1099372.3 | J9: =908955*1.05+20023.42*1.05 -> 975427.34 | K9: =1168323.69*1.05+25445.84*1.05 -> 1253458 | L9: =1264919.22*1.05+31881.8*1.05 -> 1361641.1 | M9: =1597663.94*1.05+50210.8*1.05 -> 1730268.5 | N9: =+SUM(B9:M9) -> 14995958
A10: Catering & Fairs | B10: 0 | C10: 0 | N10: =+SUM(B10:M10) -> 0
A11: Less Tax | B11: =(B9+B10)/1.05*0.05 -> 56521.866 | C11: =(C9+C10)/1.05*0.05 -> 55738.583 | D11: =(D9+D10)/1.05*0.05 -> 58748.2 | E11: =(E9+E10)/1.05*0.05 -> 70680.72 | F11: =(F9+F10)/1.05*0.05 -> 58911.596 | G11: =(G9+G10)/1.05*0.05 -> 57247.497 | H11: =(H9+H10)/1.05*0.05 -> 50522.539 | I11: =(I9+I10)/1.05*0.05 -> 52351.06 | ... M11: =(M9+M10)/1.05*0.05 -> 82393.737 | N11: =+SUM(B11:M11) -> 714093.25
A12: Less Commission | B12: =12313+2216+41.6+7.5+48974 -> 63552.1 | C12: =63157+15+11370.98+10193.15+1647.24+1834.75+296.5+5.58+1 -> 88521.2 | D12: =66458+11962+15915.46+9158+2864+1648+73.93+13.32 -> 108092.71 | E12: =38209+6877+72514+13052.68+1789+322 -> 132763.68 | F12: =28959.75+59581.3+10724+5212.74+925.89+166.66 -> 105570.34 | G12: =57044.96+21668.61+10268.04+3900.4+903.54+162.43 -> 93947.98 | H12: =53733.54*1.18+16043.69*1.18+537.71*1.18+1161.28*1.18 -> 84341.94 | I12: =15286.3*1.18+49400.78*1.18+391.18*1.18+5712.64*1.18+118.23*1.18 -> 83672.773 | J12: =46336+167+8340.57+19888.98+3578.07 -> 78310.62 | K12: =59179.83+10652.37+26992.14*1.18+1015.75*1.18 -> 102881.51 | L12: =22775.77*1.18+73674.45*1.18+1083.67*1.18 -> 115089.99 | M12: =116064.71*1.18+43739.79*1.18+808.8*1.18 -> 189523.69 | N12: =+SUM(B12:M12) -> 1246268.5
A13: Net Revenues from F&B Sales | B13: =B9+B10-B11-B12 -> 1066885.2 | C13: =C9+C10-C11-C12 -> 1026250.5 | D13: =D9+D10-D11-D12 -> 1066871.3 | E13: =E9+E10-E11-E12 -> 1280850.7 | F13: =F9+F10-F11-F12 -> 1072661.6 | G13: =G9+G10-G11-G12 -> 1051002 | H13: =H9+H10-H11-H12 -> 926108.83 | I13: =I9+I10-I11-I12 -> 963348.43 | ... M13: =M9+M10-M11-M12 -> 1458351 | N13: =sum(B13:M13) -> 13035596 | O13: =N13/$N$7 -> 19.996582
A14: F&B Cost | B14: =+B3+B4-B5-B7 -> 331381.38 | C14: =+C3+C4-C5-C7 -> 303571.81 | D14: =+D3+D4-D5-D7 -> 305780.98 | E14: =+E3+E4-E5-E7 -> 329412.53 | F14: =+F3+F4-F5-F7 -> 263118.36 | G14: =+G3+G4-G5-G7 -> 243531.35 | H14: =+H3+H4-H5-H7 -> 214954.18 | I14: =+I3+I4-I5-I7 -> 217919.53 | ... M14: =+M3+M4-M5-M7 -> 342576.44 | N14: =sum(B14:M14) -> 3281670 | O14: =N14/$N$7 -> 5.0340759
A15: Electricity | B15: 43747 | C15: 34837.8 | D15: 51583.7 | E15: 58116.98 | F15: 52151.54 | G15: 51591 | H15: 53451 | I15: 39131 | J15: 33071 | K15: 35312 | L15: =40776.78 -> 40776.78 | M15: =41665.7 -> 41665.7 | N15: =sum(B15:M15) -> 535435.5 | O15: =N15/$N$7 -> 0.8213571
A16: Telephone/Internet | B16: =1060 -> 1060 | C16: =1060 -> 1060 | D16: 1060 | E16: 1060 | F16: 2003 | G16: =943+199 -> 1142 | H16: =943+548 -> 1491 | I16: =199+943 -> 1142 | J16: =942+548 -> 1490 | K16: =2238/3+548 -> 1294 | L16: =2238/3+942 -> 1688 | M16: =2238/3+942 -> 1688 | N16: =sum(B16:M16) -> 16178 | O16: =N16/$N$7 -> 0.024817023
A17: Gas | N17: =sum(B17:M17) -> 0 | O17: =N17/$N$7 -> 0
A18: Rent & Revenue Share | B18: =139240 -> 139240 | C18: =139240 -> 139240 | D18: =139240 -> 139240 | E18: =139240 -> 139240 | F18: =139240 -> 139240 | G18: =139240 -> 139240 | H18: =139240 -> 139240 | I18: =139240 -> 139240 | ... M18: =139240 -> 139240 | N18: =sum(B18:M18) -> 1670880 | O18: =N18/$N$7 -> 2.5631269
A19: Insurance | B19: 0 | C19: =12662/12 -> 1055.1667 | D19: =12662/12 -> 1055.1667 | E19: =12662/12 -> 1055.1667 | F19: =12662/12 -> 1055.1667 | G19: =12662/12 -> 1055.1667 | H19: =12662/12 -> 1055.1667 | I19: =12662/12 -> 1055.1667 | J19: =12662/12 -> 1055.1667 | ... M19: =12662/12 -> 1055.1667 | N19: =sum(B19:M19) -> 11606.833
A20: Software | B20: =57171/12 -> 4764.25 | C20: =57171/12 -> 4764.25 | D20: =57171/12 -> 4764.25 | E20: =57171/12 -> 4764.25 | F20: =57171/12 -> 4764.25 | G20: =57171/12 -> 4764.25 | H20: =57171/12 -> 4764.25 | I20: =57171/12 -> 4764.25 | ... M20: =57171/12 -> 4764.25 | N20: =sum(B20:M20) -> 57171 | O20: =N20/$N$7 -> 0.087700212
A21: Staff Salary | B21: =+210960.686+8230+74614/12 -> 225408.52 | C21: =217635+8230+74614/12 -> 232082.83 | D21: =235127.51+8230+74614/12 -> 249575.34 | E21: =225230+8230+74614/12 -> 239677.83 | F21: =226129+8230+74614/12 -> 240576.83 | G21: =215848+8230+74614/12 -> 230295.83 | H21: =74614/12+229414+8230 -> 243861.83 | I21: =74614/12+8230+223343.02 -> 237790.85 | J21: =74614/12+220314+8230 -> 234761.83 | K21: =74614/12+8230+252334 -> 266781.83 | L21: =74614/12+251813+9250 -> 267280.83 | M21: =74614/12+9250+217639 -> 233106.83 | N21: =sum(B21:M21) -> 2901201.2 | O21: =N21/$N$7 -> 4.4504375
A22: AMC | B22: =2950+4720 -> 7670 | C22: =4720+2950 -> 7670 | D22: =5192+2950 -> 8142 | E22: =5192+2950 -> 8142 | F22: =5192+2950 -> 8142 | G22: =5192+2950 -> 8142 | H22: =5192+2950 -> 8142 | I22: =4760+2950 -> 7710 | J22: =4720+2950 -> 7670 | K22: =4720+2950 -> 7670 | L22: =4720+2950 -> 7670 | M22: =4720+2950 -> 7670 | N22: =sum(B22:M22) -> 94440 | O22: =N22/$N$7 -> 0.14487079
A23: Subscription | B23: =2124/3 -> 708 | C23: =2124/3 -> 708 | D23: =2124/3 -> 708 | E23: =2124/3 -> 708 | F23: =2124/3 -> 708 | G23: =2124/3 -> 708 | H23: =2124/3 -> 708 | I23: =2124/3 -> 708 | J23: =2124/3 -> 708 | K23: =3304/3 -> 1101.3333 | L23: =3304/3 -> 1101.3333 | M23: =3304/3 -> 1101.3333 | N23: =sum(B23:M23) -> 9676 | O23: =N23/$N$7 -> 0.014842967
A24: Repairs & Maintenance | B24: 1140 | C24: 200 | D24: 200 | E24: 0 | F24: =5260 -> 5260 | G24: 2723 | H24: 11534 | I24: 8260 | J24: 0 | K24: 0 | L24: 4130 | M24: 0 | N24: =sum(B24:M24) -> 33447 | O24: =N24/$N$7 -> 0.051307638
A25: Miscellaneous Expenses | B25: 6279.72 | C25: 5899.06 | D25: 20694 | E25: 5205.55 | F25: 11043 | G25: 9094.71 | H25: 10776.74 | I25: 5693.53 | J25: 6759.53 | K25: 7595.71 | L25: 31397 | M25: 10202.69 | N25: =sum(B25:M25) -> 130641.24 | O25: =N25/$N$7 -> 0.20040343
A26: CAM | B26: 40031.5 | C26: 40031.5 | D26: 40031.5 | E26: 40031.5 | F26: 40031.5 | G26: 40031.5 | H26: 40031.5 | I26: 40031.5 | J26: 40031.5 | K26: 40031.5 | L26: 40031.5 | M26: 40031.5 | N26: =sum(B26:M26) -> 480378 | O26: =N26/$N$7 -> 0.736899
A27: HO+CK Cost | B27: =HO!D32 -> 194275.99 | C27: =HO!H32 -> 180975.67 | D27: =HO!L32 -> 184063.41 | E27: =HO!P32 -> 224801.47 | F27: =HO!D45 -> 193850.73 | G27: =HO!H45 -> 189246.03 | H27: =HO!L45 -> 178224.12 | I27: =HO!P45 -> 171947.89 | J27: =HO!D58 -> 150606.58 | K27: =HO!H58 -> 167625.67 | L27: =HO!L58 -> 183362.65 | M27: =HO!P58 -> 230930.43 | N27: =sum(B27:M27) -> 2249910.6 | O27: =N27/$N$7 -> 3.4513589
A28: Operating Expenses | B28: =+SUM(B14:B27) -> 995706.36 | C28: =+SUM(C14:C27) -> 952096.08 | D28: =+SUM(D14:D27) -> 1006898.4 | E28: =+SUM(E14:E27) -> 1052215.3 | F28: =+SUM(F14:F27) -> 961944.38 | G28: =+SUM(G14:G27) -> 921564.84 | H28: =+SUM(H14:H27) -> 908233.79 | I28: =+SUM(I14:I27) -> 875393.72 | ... M28: =+SUM(M14:M27) -> 1054032.3 | N28: =sum(B28:M28) -> 11472635 | O28: =N28/$N$7 -> 17.599002
A29: Store Level EBITDA | B29: =B13-B28 -> 71178.869 | C29: =C13-C28 -> 74154.375 | D29: =D13-D28 -> 59972.938 | E29: =E13-E28 -> 228635.45 | F29: =F13-F28 -> 110717.2 | G29: =G13-G28 -> 129437.12 | H29: =H13-H28 -> 17875.041 | I29: =I13-I28 -> 87954.709 | ... M29: =M13-M28 -> 404318.7 | N29: =sum(B29:M29) -> 1562961 | O29: =N29/$N$7 -> 2.3975794
A30: Food Cost | B30: =(B14/B13) -> 0.3106064 | C30: =(C14/C13) -> 0.29580675 | D30: =(D14/D13) -> 0.28661469 | E30: =(E14/E13) -> 0.25718261 | F30: =(F14/F13) -> 0.24529485 | G30: =(G14/G13) -> 0.23171351 | H30: =(H14/H13) -> 0.23210467 | I30: =(I14/I13) -> 0.2262105 | ... M30: =(M14/M13) -> 0.23490671
B32: =B29+B27 -> 265454.86 | C32: =C29+C27 -> 255130.04 | D32: =D29+D27 -> 244036.35 | E32: =E29+E27 -> 453436.92 | F32: =F29+F27 -> 304567.93 | G32: =G29+G27 -> 318683.15 | H32: =H29+H27 -> 196099.16 | I32: =I29+I27 -> 259902.6 | ... M32: =M29+M27 -> 635249.13
B33: =B32/B13 -> 0.24881295 | C33: =C32/C13 -> 0.24860407 | D33: =D32/D13 -> 0.2287402 | E33: =E32/E13 -> 0.35401231 | F33: =F32/F13 -> 0.28393664 | G33: =G32/G13 -> 0.30321842 | H33: =H32/H13 -> 0.21174527 | I33: =I32/I13 -> 0.26979086 | ... M33: =M32/M13 -> 0.43559411

Sheet Faridabad Sec15
A1: Dosa Coffee - Faridabad Sec 15 | B1: 45748 | C1: 45778 | D1: 45809 | E1: 45839 | F1: 45870 | G1: 45901 | H1: 45931 | I1: 45962 | J1: 45992 | K1: 46023 | L1: 46054 | M1: 46082 | N1: FY 2025-26
A2: Food Cost Calculation
A3: Opening Stock | B3: 125397 | C3: =153084.38 -> 153084.38 | D3: =C7 -> 120005.31 | E3: =D7 -> 128804.55 | F3: =E7 -> 139768.21 | G3: =F7 -> 133202.64 | H3: =G7 -> 125007 | I3: =H7 -> 121734 | J3: =I7 -> 122019.97 | K3: =J7 -> 128793 | ... M3: =L7 -> 76833.44 | N3: =+SUM(J3:L3) -> 340201.49
A4: Purchases Food (Less Purchase Return) | B4: 256616.68 | C4: 273611.29 | D4: 276539.31 | E4: 290367.37 | F4: 266167 | G4: 222383.61 | H4: 222787 | I4: 234815.53 | J4: 243097 | K4: 267681.4 | L4: 256276.51 | M4: 300024 | N4: =sum(B4:M4) -> 3110366.7
A5: Transferred Out | B5: 0 | C5: 11365.4 | D5: 6528 | E5: 0 | F5: 0 | G5: 0 | H5: 0 | I5: 21784.15 | J5: 0 | K5: 0 | L5: 43712 | M5: 0 | N5: =+SUM(J5:L5) -> 43712
A6: Wastage & Date Expired | B6: 32987 | C6: 35506.54 | D6: 35222 | E6: 13771.31 | F6: 16588 | G6: 14620 | H6: 16183 | I6: 14582.21 | J6: 15320.76 | K6: 14101 | L6: 11649.52 | M6: 30140 | N6: =+SUM(J6:L6) -> 41071.28
A7: Closing Stock | B7: 144247 | C7: 120005.31 | D7: 128804.55 | E7: 139768.21 | F7: 133202.64 | G7: 125007 | H7: 121734 | I7: 122019.97 | J7: 128793 | K7: 89388.52 | L7: 76833.44 | M7: 58922.74 | N7: =sum(B7:M7) -> 1388726.4
A9: Gross Revenue | B9: =913194.25*1.05+27880.38*1.05 -> 988128.36 | C9: =1011098.42*1.05+28836.6*1.05 -> 1091931.8 | D9: =942666.19*1.05+30089*1.05 -> 1021392.9 | E9: =988755.81*1.05 -> 1038193.6 | F9: =940546.16*1.05 -> 987573.47 | G9: =852450.12*1.05 -> 895072.63 | H9: =828935.24*1.05+26443.42*1.05 -> 898147.59 | I9: =727678.73*1.05+21378.92*1.05 -> 786510.53 | J9: =768946.68*1.05+24050*1.05+50*1.05 -> 832699.01 | K9: =996179*1.05+28993.81*1.05 -> 1076431.5 | L9: =822981.49*1.05+31019.91 -> 895150.47 | M9: =1075363.04*1.05+41265.5*1.05 -> 1172460 | N9: =+SUM(B9:M9) -> 11683692
A10: Catering & Fairs | B10: 0 | C10: 0 | N10: =+SUM(B10:M10) -> 0
A11: Less Tax | B11: =(B9+B10)/1.05*0.05 -> 47053.732 | C11: =(C9+C10)/1.05*0.05 -> 51996.751 | D11: =(D9+D10)/1.05*0.05 -> 48637.76 | E11: =(E9+E10)/1.05*0.05 -> 49437.791 | F11: =(F9+F10)/1.05*0.05 -> 47027.308 | G11: =(G9+G10)/1.05*0.05 -> 42622.506 | H11: =(H9+H10)/1.05*0.05 -> 42768.933 | I11: =(I9+I10)/1.05*0.05 -> 37452.882 | ... M11: =(M9+M10)/1.05*0.05 -> 55831.427 | N11: =+SUM(B11:M11) -> 556366.28
A12: Less Commission | B12: =28018.47+5043+294.75+53.06+1465+64032+476.19 -> 99382.47 | C12: =66640.47+784.25+12316.44+24904.67+6251.7+4482.86+1125.31+274.42+23.7+25.7 -> 116829.52 | D12: =+424.74+69269.44+76.45+12468.5+23684.37+12888.39+4263+2319.91+301.92+54.34 -> 125751.06 | E12: =43779.76+7880.41+62574.82+19523.47+1356.9+244.24 -> 135359.6 | F12: =34497.83+64600.47+11628.08+6209.6+1365.87+245.86 -> 118547.71 | G12: =61164.56+24091.4+11009.63+4330.87+1435.06+258.3 -> 102289.82 | H12: =60956.81*1.18+28473.47*1.18 -> 105527.73 | I12: =15091.3*1.18+50058*1.18+266.8*1.18+7810.36*1.18+405.15*1.18 -> 86885.3 | J12: =56428.02+10157.05+21128.59+3803 -> 91516.66 | K12: =68055.34+12249.97+27564.94*1.18+1853.44*1.18 -> 115019 | L12: =21072.59*1.18+72312.54*1.18+1420.39*1.18 -> 111870.51 | M12: =96070.27*1.18+32569.02*1.18+1251.55*1.18 -> 153271.19 | N12: =+SUM(B12:M12) -> 1362250.6
A13: Net Revenues from F&B Sales | B13: =B9+B10-B11-B12 -> 841692.16 | C13: =C9+C10-C11-C12 -> 923105.5 | D13: =D9+D10-D11-D12 -> 847004.13 | E13: =E9+E10-E11-E12 -> 853396.21 | F13: =F9+F10-F11-F12 -> 821998.45 | G13: =G9+G10-G11-G12 -> 750160.3 | H13: =H9+H10-H11-H12 -> 749850.93 | I13: =I9+I10-I11-I12 -> 662172.35 | ... M13: =M9+M10-M11-M12 -> 963357.35 | N13: =sum(B13:M13) -> 9765075 | O13: =N13/$N$7 -> 7.0316767
A14: F&B Cost | B14: =+B3+B4-B5-B7 -> 237766.68 | C14: =+C3+C4-C5-C7 -> 295324.96 | D14: =+D3+D4-D5-D7 -> 261212.07 | E14: =+E3+E4-E5-E7 -> 279403.71 | F14: =+F3+F4-F5-F7 -> 272732.57 | G14: =+G3+G4-G5-G7 -> 230579.25 | H14: =+H3+H4-H5-H7 -> 226060 | I14: =+I3+I4-I5-I7 -> 212745.41 | ... M14: =+M3+M4-M5-M7 -> 317934.7 | N14: =sum(B14:M14) -> 3102288.8 | O14: =N14/$N$7 -> 2.2339093
A15: Electricity | B15: =16520+7265+53506 -> 77291 | C15: =53506+16520 -> 70026 | D15: =68364+16520+14990 -> 99874 | E15: =80172+16520+27700 -> 124392 | F15: =72417+16520+18100 -> 107037 | G15: =70198+16520+9300+3000 -> 99018 | H15: =69238+16520+10700 -> 96458 | I15: =66317+16520 -> 82837 | J15: =48477+26320 -> 74797 | K15: =47366+16520+6000 -> 69886 | L15: =47631+16520+5200 -> 69351 | M15: =45689+16520+5200 -> 67409 | N15: =sum(B15:M15) -> 1038376 | O15: =N15/$N$7 -> 0.74771821
A16: Telephone/Internet | B16: =200+1296 -> 1496 | C16: =200+1296 -> 1496 | D16: =1414 -> 1414 | E16: 1414 | F16: =202+2709 -> 2911 | G16: =1295 -> 1295 | H16: =200+1295 -> 1495 | I16: =200+1295 -> 1495 | J16: =200+1295 -> 1495 | K16: =1296+201 -> 1497 | L16: =1296+201 -> 1497 | M16: =1296+201 -> 1497 | N16: =sum(B16:M16) -> 19002 | O16: =N16/$N$7 -> 0.013683041
A17: Gas | N17: =sum(B17:M17) -> 0 | O17: =N17/$N$7 -> 0
A18: Rent & Revenue Share | B18: =82500+82500 -> 165000 | C18: =97350+97350 -> 194700 | D18: =97350+97350 -> 194700 | E18: =97350+97350 -> 194700 | F18: =97350+97350 -> 194700 | G18: =97350+97350 -> 194700 | H18: =97350+97350 -> 194700 | I18: =97350+97350 -> 194700 | J18: =97350+97350 -> 194700 | K18: =53100+53100 -> 106200 | L18: =115700 -> 115700 | M18: =53100+53100 -> 106200 | N18: =sum(B18:M18) -> 2050700 | O18: =N18/$N$7 -> 1.4766768
A19: Insurance | B19: 0 | C19: =11106.97/12 -> 925.58083 | D19: =11106.97/12 -> 925.58083 | E19: =11106.97/12 -> 925.58083 | F19: =11106.97/12 -> 925.58083 | G19: =11106.97/12 -> 925.58083 | H19: =11106.97/12 -> 925.58083 | I19: =11106.97/12 -> 925.58083 | J19: =11106.97/12 -> 925.58083 | ... M19: =11106.97/12 -> 925.58083 | N19: =sum(B19:M19) -> 10181.389
A20: Software | B20: 5514 | C20: 5514 | D20: 5514 | E20: 5514 | F20: 5514 | G20: 5514 | H20: 5514 | I20: 5514 | J20: 5514 | K20: 5514 | L20: =69207/12 -> 5767.25 | M20: =69207/12 -> 5767.25 | N20: =sum(B20:M20) -> 66674.5 | O20: =N20/$N$7 -> 0.048011258
A21: Staff Salary | B21: =14500+1330+237280+19200+87867/12 -> 279632.25 | C21: =240450.18+14500+87867/12 -> 262272.43 | D21: =262976+14500+87867/12 -> 284798.25 | E21: =227531+14500+87867/12 -> 249353.25 | F21: =237030+14500+1000+87867/12 -> 259852.25 | G21: =233830+14500+87867/12 -> 255652.25 | H21: =87867/12+221765+14500 -> 243587.25 | I21: =87867/12+14500+217742.99 -> 239565.24 | J21: =87867/12+215598+14500 -> 237420.25 | K21: =87867/12+14500+212047 -> 233869.25 | L21: =87867/12+168973+14500 -> 190795.25 | M21: =87867/12+14500+197158 -> 218980.25 | N21: =sum(B21:M21) -> 2955778.2 | O21: =N21/$N$7 -> 2.1284093
A22: AMC | B22: =2950+4720 -> 7670 | C22: =5192+2950 -> 8142 | D22: =5192+2950 -> 8142 | E22: =5192+2950 -> 8142 | F22: =5192+2950 -> 8142 | G22: =5192+2950 -> 8142 | H22: =5192+2950 -> 8142 | I22: =4760+2950 -> 7710 | J22: =4720+2950 -> 7670 | K22: =4720+2950 -> 7670 | L22: =4720+2950 -> 7670 | M22: =2950+4720 -> 7670 | N22: =sum(B22:M22) -> 94912 | O22: =N22/$N$7 -> 0.068344637
A23: Subscription | B23: =2124/3 -> 708 | C23: =2124/3 -> 708 | D23: =2124/3 -> 708 | E23: =2124/3 -> 708 | F23: =2124/3 -> 708 | G23: =2124/3 -> 708 | H23: =2124/3 -> 708 | I23: =2124/3 -> 708 | J23: =2124/3 -> 708 | K23: =3304/3 -> 1101.3333 | L23: =3304/3 -> 1101.3333 | M23: =3304/3 -> 1101.3333 | N23: =sum(B23:M23) -> 9676 | O23: =N23/$N$7 -> 0.0069675352
A24: Repairs & Maintenance | B24: 3950 | C24: 1004 | D24: 11205 | E24: 0 | F24: 15099 | G24: 10406 | H24: 9344 | I24: 4130 | J24: 0 | K24: 4000 | L24: 4271 | M24: 0 | N24: =sum(B24:M24) -> 63409 | O24: =N24/$N$7 -> 0.045659822
A25: Miscellaneous Expenses | B25: 5194.98 | C25: 13237.29 | D25: 6747 | E25: 1051 | F25: =23691.79 -> 23691.79 | G25: 14722 | H25: 8566.51 | I25: 4216.84 | J25: 8408.88 | K25: 7756 | L25: 32086.71 | M25: 16132.59 | N25: =sum(B25:M25) -> 141811.59 | O25: =N25/$N$7 -> 0.10211629
A26: CAM | B26: 0 | C26: 0 | D26: 0 | E26: 0 | N26: =sum(B26:M26) -> 0 | O26: =N26/$N$7 -> 0
A27: HO+CK Cost | B27: =HO!D31 -> 153269.14 | C27: =HO!H31 -> 162786.41 | D27: =HO!L31 -> 146130.53 | E27: =HO!P31 -> 149779.14 | F27: =HO!D44 -> 148551.04 | G27: =HO!H44 -> 135075.73 | H27: =HO!L44 -> 144304.34 | I27: =HO!P44 -> 118191.02 | J27: =HO!D57 -> 124202.46 | K27: =HO!H57 -> 139854.08 | L27: =HO!L57 -> 114925.08 | M27: =HO!P57 -> 152548 | N27: =sum(B27:M27) -> 1689617 | O27: =N27/$N$7 -> 1.2166666
A28: Operating Expenses | B28: =+SUM(B14:B27) -> 937492.05 | C28: =+SUM(C14:C27) -> 1016136.7 | D28: =+SUM(D14:D27) -> 1021370.4 | E28: =+SUM(E14:E27) -> 1015382.7 | F28: =+SUM(F14:F27) -> 1039864.2 | G28: =+SUM(G14:G27) -> 956737.81 | H28: =+SUM(H14:H27) -> 939804.68 | I28: =+SUM(I14:I27) -> 872738.09 | ... M28: =+SUM(M14:M27) -> 896165.7 | N28: =sum(B28:M28) -> 11242426 | O28: =N28/$N$7 -> 8.0954942
A29: Store Level EBITDA | B29: =B13-B28 -> -95799.887 | C29: =C13-C28 -> -93031.174 | D29: =D13-D28 -> -174366.3 | E29: =E13-E28 -> -161986.47 | F29: =F13-F28 -> -217865.78 | G29: =G13-G28 -> -206577.51 | H29: =H13-H28 -> -189953.75 | I29: =I13-I28 -> -210565.74 | ... M29: =M13-M28 -> 67191.648 | N29: =sum(B29:M29) -> -1477351.5 | O29: =N29/$N$7 -> -1.0638175
A30: Food Cost | B30: =(B14/B13) -> 0.28248651 | C30: =(C14/C13) -> 0.31992547 | D30: =(D14/D13) -> 0.30839527 | E30: =(E14/E13) -> 0.3274021 | F30: =(F14/F13) -> 0.33179207 | G30: =(G14/G13) -> 0.3073733 | H30: =(H14/H13) -> 0.30147325 | I30: =(I14/I13) -> 0.32128404 | ... M30: =(M14/M13) -> 0.33002779
B32: =B29+B27 -> 57469.25 | C32: =C29+C27 -> 69755.239 | D32: =D29+D27 -> -28235.771 | E32: =E29+E27 -> -12207.331 | F32: =F29+F27 -> -69314.741 | G32: =G29+G27 -> -71501.781 | H32: =H29+H27 -> -45649.411 | I32: =I29+I27 -> -92374.721 | ... M32: =M29+M27 -> 219739.64
B33: =B32/B13 -> 0.068278229 | C33: =C32/C13 -> 0.075565836 | D33: =D32/D13 -> -0.033336049 | E33: =E32/E13 -> -0.014304412 | F33: =F32/F13 -> -0.084324661 | G33: =G32/G13 -> -0.095315336 | H33: =H32/H13 -> -0.060877982 | I33: =I32/I13 -> -0.13950253 | ... M33: =M32/M13 -> 0.22809775

Sheet Gurgaon Sec-15
A1: Dosa Coffee - Huda Market | B1: 45748 | C1: 45778 | D1: 45809 | E1: 45839 | F1: 45870 | G1: 45901 | H1: 45931 | I1: 45962 | J1: 45992 | K1: 46023 | L1: 46054 | M1: 46082 | N1: FY 2025-26
A2: Food Cost Calculation
A3: Opening Stock | B3: =116825.73 -> 116825.73 | C3: =B7 -> 107230 | D3: =C7 -> 109842.78 | E3: =D7 -> 72014 | F3: =E7 -> 59525 | G3: =F7 -> 52696 | H3: =G7 -> 68179.71 | I3: =H7 -> 63056 | J3: =I7 -> 68716.95 | ... M3: =L7 -> 69332.2 | N3: =+SUM(J3:L3) -> 204750.57
A4: Purchases Food (Less Purchase Return) | B4: 377262.34 | C4: 431890.82 | D4: 451452.93 | E4: 500983.54 | F4: 489196.06 | G4: 469298.77 | H4: 446758.22 | I4: 422824.08 | J4: 452952 | K4: 442554.6 | L4: 428650 | M4: 472671.97 | N4: =sum(B4:M4) -> 5386495.3
A5: Transferred Out | B5: 0 | C5: 2893.57 | D5: 1252 | E5: 556 | F5: 0 | G5: 0 | H5: 0 | I5: 540.27 | J5: 0 | K5: 0 | L5: 0 | M5: 565.98 | N5: =+SUM(J5:L5) -> 0
A6: Wastage & Date Expired | B6: 22016 | C6: 24394.33 | D6: 23635 | E6: 21895 | F6: 19185 | G6: 17545.17 | H6: 20717 | I6: 18406 | J6: 16389.96 | K6: 17632.92 | L6: 13833.74 | M6: 17137.3 | N6: =+SUM(J6:L6) -> 47856.62
A7: Closing Stock | B7: 107230 | C7: 109842.78 | D7: 72014 | E7: 59525 | F7: 52696 | G7: 68179.71 | H7: 63056 | I7: 68716.95 | J7: 76057 | K7: 59976.62 | L7: 69332.2 | M7: 69049 | N7: =sum(B7:M7) -> 875675.26
A9: Gross Revenue | B9: =1532644.49*1.05+28257.35*1.05 -> 1638946.9 | C9: =1753623.27*1.05+34898.54*1.05 -> 1877947.9 | D9: =1909680.29*1.05+33128*1.05 -> 2039948.7 | E9: =1987853.41*1.05 -> 2087246.1 | F9: =2011838.45*1.05 -> 2112430.4 | G9: =1884689.11*1.05 -> 1978923.6 | H9: =1802131.33*1.05+10*1.05+31992.95*1.05 -> 1925841 | I9: =1687150.93*1.05+24986.36*1.05 -> 1797744.2 | J9: =1760062.48*1.05+23348.94*1.05 -> 1872582 | K9: =1842625.38*1.05+24464.61*1.05 -> 1960444.5 | L9: =1648189.76*1.05+25591.13*1.05 -> 1757469.9 | M9: =1947081.18*1.05+41555.24*1.05 -> 2088068.2 | N9: =+SUM(B9:M9) -> 23137593
A10: Catering & Fairs | B10: 0 | C10: 0 | D10: 0 | N10: =+SUM(B10:M10) -> 0
A11: Less Tax | B11: =(B9+B10)/1.05*0.05 -> 78045.092 | C11: =(C9+C10)/1.05*0.05 -> 89426.091 | D11: =(D9+D10)/1.05*0.05 -> 97140.414 | E11: =(E9+E10)/1.05*0.05 -> 99392.67 | F11: =(F9+F10)/1.05*0.05 -> 100591.92 | G11: =(G9+G10)/1.05*0.05 -> 94234.455 | H11: =(H9+H10)/1.05*0.05 -> 91706.714 | I11: =(I9+I10)/1.05*0.05 -> 85606.864 | ... M11: =(M9+M10)/1.05*0.05 -> 99431.821 | N11: =+SUM(B11:M11) -> 1101790.2
A12: Less Commission | B12: =37213+6698+452.88+81.52+65191.95+816.48 -> 110453.83 | C12: =80164.6+900.93+14591.8+5210.94+5736.19+937.97+370.98+454.16+66.78+81.74 -> 108516.09 | D12: =1067.52+76618.24+192.15+13791.28+19789.95+14008+3562.21+2521.59+787.39+141.72 -> 132480.05 | E12: =53635.84+9654+79593+14326.81+5006+901 -> 163116.65 | F12: =50144.81+73117.4+13161.14+9026.09+4110.76+739.94 -> 150300.14 | G12: =76313.18+38658.88+13736.37+6958.64+4808.54+865.53 -> 141341.14 | H12: =74842.89*1.18+36469.91*1.18+3810.63*1.18 -> 135845.65 | I12: =25505.31*1.18+58653.03*1.18+2253.03*1.18+10468.73*1.18+1255.92*1.18 -> 115800.5 | J12: =55761.22+10037.02+33893.47+5994.76 -> 105686.47 | K12: =59395.2+10691.14+32921.9*1.18+3631.47*1.18 -> 113219.32 | L12: =25309.77*1.18+63140.88*1.18+3472.24*1.18 -> 108469.01 | M12: =98058.13*1.18+38298.02*1.18+2959.93*1.18 -> 164392.97 | N12: =+SUM(B12:M12) -> 1549621.8
A13: Net Revenues from F&B Sales | B13: =B9+B10-B11-B12 -> 1450448 | C13: =C9+C10-C11-C12 -> 1680005.7 | D13: =D9+D10-D11-D12 -> 1810328.2 | E13: =E9+E10-E11-E12 -> 1824736.8 | F13: =F9+F10-F11-F12 -> 1861538.3 | G13: =G9+G10-G11-G12 -> 1743348 | H13: =H9+H10-H11-H12 -> 1698288.6 | I13: =I9+I10-I11-I12 -> 1596336.8 | ... M13: =M9+M10-M11-M12 -> 1824243.4 | N13: =sum(B13:M13) -> 20486181 | O13: =N13/$N$7 -> 23.394724
A14: F&B Cost | B14: =+B3+B4-B5-B7 -> 386858.07 | C14: =+C3+C4-C5-C7 -> 426384.47 | D14: =+D3+D4-D5-D7 -> 488029.71 | E14: =+E3+E4-E5-E7 -> 512916.54 | F14: =+F3+F4-F5-F7 -> 496025.06 | G14: =+G3+G4-G5-G7 -> 453815.06 | H14: =+H3+H4-H5-H7 -> 451881.93 | I14: =+I3+I4-I5-I7 -> 416622.86 | ... M14: =+M3+M4-M5-M7 -> 472389.19 | N14: =sum(B14:M14) -> 5428464.2 | O14: =N14/$N$13 -> 0.26498175
A15: Electricity | B15: =65295+23600+3000 -> 91895 | C15: =65295+23600+3000 -> 91895 | D15: =74807+23600+3000 -> 101407 | E15: =81815+23600+10900 -> 116315 | F15: =73605+14700+23600 -> 111905 | G15: =72758+23600+5100 -> 101458 | H15: =75351+55479+23600+5100+2500 -> 162030 | I15: =68974+23600 -> 92574 | J15: =86829+27800 -> 114629 | K15: =66676+23600+6300 -> 96576 | L15: =65311+23600 -> 88911 | M15: =69977+23600 -> 93577 | N15: =sum(B15:M15) -> 1263172 | O15: =N15/$N$13 -> 0.06165971
A16: Telephone/Internet | B16: =202+1413 -> 1615 | C16: =222 -> 222 | D16: =1414 -> 1414 | E16: 1414 | F16: =403+1414 -> 1817 | G16: =1414+202 -> 1616 | H16: =1414+202 -> 1616 | I16: 1616 | J16: =489+1414 -> 1903 | K16: =1414+221 -> 1635 | L16: =4246/3+221 -> 1636.3333 | M16: =4246/3+222 -> 1637.3333 | N16: =sum(B16:M16) -> 18141.667 | O16: =N16/$N$13 -> 0.00088555628
A17: Gas | N17: =sum(B17:M17) -> 0 | O17: =N17/$N$13 -> 0
A18: Rent & Revenue Share | B18: =105000+105000 -> 210000 | C18: =123900+123900 -> 247800 | D18: =123900+123900 -> 247800 | E18: =123900+123900 -> 247800 | F18: =123900+123900 -> 247800 | G18: =123900+123900 -> 247800 | H18: =123900+123900 -> 247800 | I18: =123900+123900 -> 247800 | J18: =123900+123900 -> 247800 | ... M18: =123900+123900 -> 247800 | N18: =sum(B18:M18) -> 2935800 | O18: =N18/$N$13 -> 0.14330636
A19: Insurance | B19: 0 | C19: =16727/12 -> 1393.9167 | D19: =16727/12 -> 1393.9167 | E19: =16727/12 -> 1393.9167 | F19: =16727/12 -> 1393.9167 | G19: =16727/12 -> 1393.9167 | H19: =16727/12 -> 1393.9167 | I19: =16727/12 -> 1393.9167 | J19: =16727/12 -> 1393.9167 | ... M19: =16727/12 -> 1393.9167 | N19: =sum(B19:M19) -> 15333.083 | O19: =N19/$N$13 -> 0.00074845981
A20: Software | B20: =12630 -> 12630 | C20: =12630 -> 12630 | D20: =12630 -> 12630 | E20: =12630 -> 12630 | F20: =12630 -> 12630 | G20: =12630 -> 12630 | H20: =12630 -> 12630 | I20: =12630 -> 12630 | ... L20: =12630 -> 12630 | M20: 12630 | N20: =sum(B20:M20) -> 151560 | O20: =N20/$N$13 -> 0.0073981577
A21: Staff Salary | B21: =1500+321929.58+12630+173179/12 -> 350491.16 | C21: =328085+12630+173179/12 -> 355146.58 | D21: =333508.36+12630+173179/12 -> 360569.94 | E21: =336832+12630+173179/12 -> 363893.58 | F21: =347536.59+12630+173179/12 -> 374598.17 | G21: =349257.02+12630+173179/12 -> 376318.6 | H21: =173179/12+330208+12630 -> 357269.58 | I21: =173179/12+12630+307161.72 -> 334223.3 | J21: =173179/12+326046+12630 -> 353107.58 | K21: =173179/12+12630+303483 -> 330544.58 | L21: =173179/12+288843+12630 -> 315904.58 | M21: =173179/12+12630+278960 -> 306021.58 | N21: =sum(B21:M21) -> 4178089.3 | O21: =N21/$N$13 -> 0.20394671
A22: AMC | B22: =75225/12+4720+2950 -> 13938.75 | C22: =75225/12+4720+2950 -> 13938.75 | D22: =75225/12+5192+2950 -> 14410.75 | E22: =75225/12+5192+2950 -> 14410.75 | F22: =75225/12+5192+2950 -> 14410.75 | G22: =75225/12+5192+2950 -> 14410.75 | H22: =75225/12+5192+2950 -> 14410.75 | I22: =75225/12+4760+2950 -> 13978.75 | J22: =75225/12+4720+2950 -> 13938.75 | K22: =75225/12+4720+2950 -> 13938.75 | L22: =75225/12+4720+2950 -> 13938.75 | M22: =75225/12+2950+4720 -> 13938.75 | N22: =sum(B22:M22) -> 169665 | O22: =N22/$N$13 -> 0.0082819241
A23: Subscription | B23: =2124/3 -> 708 | C23: =2124/3 -> 708 | D23: =2124/3 -> 708 | E23: =2124/3 -> 708 | F23: =2124/3 -> 708 | G23: =2124/3 -> 708 | H23: =2124/3 -> 708 | I23: =2124/3 -> 708 | J23: =2124/3 -> 708 | K23: =3304/3 -> 1101.3333 | L23: =3304/3 -> 1101.3333 | M23: =3304/3 -> 1101.3333 | N23: =sum(B23:M23) -> 9676 | O23: =N23/$N$13 -> 0.00047231838
A24: Repairs & Maintenance | B24: 480 | C24: 550 | D24: 0 | E24: 34351 | F24: 5357 | G24: 4709 | H24: 6868 | I24: 5959 | J24: 4130 | K24: 6999 | L24: 348 | M24: 57740 | N24: =sum(B24:M24) -> 127491 | O24: =N24/$N$13 -> 0.0062232681
A25: Miscellaneous Expenses | B25: 5696.35 | C25: 6165.8 | D25: 12870 | E25: 11702 | F25: 48488.39 | G25: 20073.7 | H25: 27256.64 | I25: 22254.54 | J25: 16487.72 | K25: 22045 | L25: 20182 | M25: 22642.87 | N25: =sum(B25:M25) -> 235865.01 | O25: =N25/$N$13 -> 0.011513371
A26: CAM | N26: =sum(B26:M26) -> 0 | O26: =N26/$N$13 -> 0
A27: HO+CK Cost | B27: =HO!D33 -> 264121.4 | C27: =HO!H33 -> 296263.11 | D27: =HO!L33 -> 312329.33 | E27: =HO!P33 -> 320258.63 | F27: =HO!D46 -> 336416.03 | G27: =HO!H46 -> 313911.57 | H27: =HO!L46 -> 326825.51 | I27: =HO!P46 -> 284929.87 | J27: =HO!D59 -> 297033 | K27: =HO!H59 -> 269499.47 | L27: =HO!L59 -> 242884.87 | M27: =HO!P59 -> 288869.63 | N27: =sum(B27:M27) -> 3553342.4 | O27: =N27/$N$13 -> 0.1734507
A28: Operating Expenses | B28: =+SUM(B14:B27) -> 1338433.7 | C28: =+SUM(C14:C27) -> 1453097.6 | D28: =+SUM(D14:D27) -> 1553562.6 | E28: =+SUM(E14:E27) -> 1637793.4 | F28: =+SUM(F14:F27) -> 1651549.3 | G28: =+SUM(G14:G27) -> 1548844.6 | H28: =+SUM(H14:H27) -> 1610690.3 | I28: =+SUM(I14:I27) -> 1434690.2 | ... M28: =+SUM(M14:M27) -> 1519741.6 | N28: =sum(B28:M28) -> 18086600 | O28: =N28/$N$13 -> 0.88286828
A29: Store Level EBITDA | B29: =B13-B28 -> 112014.27 | C29: =C13-C28 -> 226908.09 | D29: =D13-D28 -> 256765.59 | E29: =E13-E28 -> 186943.34 | F29: =F13-F28 -> 209988.99 | G29: =G13-G28 -> 194503.37 | H29: =H13-H28 -> 87598.298 | I29: =I13-I28 -> 161646.55 | ... M29: =M13-M28 -> 304501.84 | N29: =sum(B29:M29) -> 2399581.7 | O29: =N29/$N$13 -> 0.11713172
A30: Food Cost | B30: =(B14/B13) -> 0.26671626 | C30: =(C14/C13) -> 0.25379942 | D30: =(D14/D13) -> 0.26958079 | E30: =(E14/E13) -> 0.2810907 | F30: =(F14/F13) -> 0.26645976 | G30: =(G14/G13) -> 0.26031238 | H30: =(H14/H13) -> 0.26608076 | I30: =(I14/I13) -> 0.26098682 | ... M30: =(M14/M13) -> 0.25895074
B32: =B29+B27 -> 376135.68 | C32: =C29+C27 -> 523171.2 | D32: =D29+D27 -> 569094.92 | E32: =E29+E27 -> 507201.97 | F32: =F29+F27 -> 546405.02 | G32: =G29+G27 -> 508414.94 | H32: =H29+H27 -> 414423.81 | I32: =I29+I27 -> 446576.42 | ... M32: =M29+M27 -> 593371.47
B33: =B32/B13 -> 0.25932379 | C33: =C32/C13 -> 0.31141037 | D33: =D32/D13 -> 0.31436007 | E33: =E32/E13 -> 0.27795898 | F33: =F32/F13 -> 0.29352338 | G33: =G32/G13 -> 0.29163136 | H33: =H32/H13 -> 0.24402437 | I33: =I32/I13 -> 0.27975075 | ... M33: =M32/M13 -> 0.32526989

Sheet Gurgaon Sec - 10
A1: Dosa Coffee - Gurgaon Sec 10 | B1: 45748 | C1: 45778 | D1: 45809 | E1: 45839 | F1: 45870 | G1: 45901 | H1: 45931 | I1: 45962 | J1: 45992 | K1: 46023 | L1: 46054 | M1: 46082 | N1: FY 2025-26
A2: Food Cost Calculation
A3: Opening Stock | J3: 0 | K3: =J7 -> 55143 | L3: =K7 -> 46769 | M3: =L7 -> 54676.86 | N3: =+SUM(J3:L3) -> 101912
A4: Purchases Food (Less Purchase Return) | J4: 162031 | K4: 163779.66 | L4: 159214.08 | M4: 212981.84 | N4: =sum(B4:M4) -> 698006.58
A5: Transferred Out | J5: 0 | K5: 149.27 | L5: 0 | M5: 0 | N5: =+SUM(J5:L5) -> 149.27
A6: Wastage & Date Expired | J6: 12958 | K6: 6745 | L6: 5639.5 | M6: 4696 | N6: =+SUM(J6:L6) -> 25342.5
A7: Closing Stock | J7: 55143 | K7: 46769 | L7: 54676.86 | M7: 44644.25 | N7: =sum(B7:M7) -> 201233.11
A9: Gross Revenue | J9: =260754*1.05+648.81*1.05 -> 274472.95 | K9: =643649.7*1.05+11841.79*1.05+30*1.05 -> 688297.56 | L9: =622269.5*1.05+15204.17*1.05 -> 669347.35 | M9: =790545.24*1.05+24441.96*1.05 -> 855736.56 | N9: =+SUM(B9:M9) -> 2487854.4
A10: Catering & Fairs | N10: =+SUM(B10:M10) -> 0
A11: Less Tax | J11: =(J9+J10)/1.05*0.05 -> 13070.14 | K11: =(K9+K10)/1.05*0.05 -> 32776.075 | L11: =(L9+L10)/1.05*0.05 -> 31873.683 | M11: =(M9+M10)/1.05*0.05 -> 40749.36 | N11: =+SUM(B11:M11) -> 118469.26
A12: Less Commission | J12: =2245.81+404.25+3155.89+568.05 -> 6374 | K12: =27034+4866.26+6491.95*1.18+47.79*1.18 -> 39617.153 | L12: =10258.51*1.18+34826.35*1.05+240.75*1.18 -> 48956.794 | M12: =55963.65*1.18+20819.37*1.18+254.65*1.18 -> 90904.451 | N12: =+SUM(B12:M12) -> 185852.4
A13: Net Revenues from F&B Sales | B13: =B9+B10-B11-B12 -> 0 | C13: =C9+C10-C11-C12 -> 0 | D13: =D9+D10-D11-D12 -> 0 | E13: =E9+E10-E11-E12 -> 0 | F13: =F9+F10-F11-F12 -> 0 | G13: =G9+G10-G11-G12 -> 0 | H13: =H9+H10-H11-H12 -> 0 | I13: =I9+I10-I11-I12 -> 0 | ... M13: =M9+M10-M11-M12 -> 724082.75 | N13: =sum(B13:M13) -> 2183532.8 | O13: =N13/$N$7 -> 10.850763
A14: F&B Cost | J14: =+J3+J4-J5-J7 -> 106888 | K14: =+K3+K4-K5-K7 -> 172004.39 | L14: =+L3+L4-L5-L7 -> 151306.22 | M14: =+M3+M4-M5-M7 -> 223014.45 | N14: =sum(B14:M14) -> 653213.06 | O14: =N14/$N$13 -> 0.29915423
A15: Electricity | J15: =3501+5699+12180 -> 21380 | K15: =5199+24361+59917-10000 -> 79477 | L15: =30000+23600+3100 -> 56700 | M15: =44165+23600 -> 67765 | N15: =sum(B15:M15) -> 225322 | O15: =N15/$N$13 -> 0.10319149
A16: Telephone/Internet | J16: 0 | K16: 0 | L16: 548 | M16: 550 | N16: =sum(B16:M16) -> 1098 | O16: =N16/$N$13 -> 0.00050285483
A17: Gas | J17: 0 | K17: 0 | L17: 0 | M17: 0 | N17: =sum(B17:M17) -> 0 | O17: =N17/$N$13 -> 0
A18: Rent & Revenue Share | J18: =31612+31612 -> 63224 | K18: =70000+70000 -> 140000 | L18: =70000+70000 -> 140000 | M18: =70000+70000 -> 140000 | N18: =sum(B18:M18) -> 483224 | O18: =N18/$N$13 -> 0.22130375
A19: Insurance | J19: =4767/12 -> 397.25 | K19: =4767/12 -> 397.25 | L19: =4767/12 -> 397.25 | M19: =4767/12 -> 397.25 | N19: =sum(B19:M19) -> 1589 | O19: =N19/$N$13 -> 0.00072771979
A20: Software | J20: =94282/12 -> 7856.8333 | K20: =94282/12 -> 7856.8333 | L20: =94282/12 -> 7856.8333 | M20: =94282/12 -> 7856.8333 | N20: =sum(B20:M20) -> 31427.333 | O20: =N20/$N$13 -> 0.014392884
A21: Staff Salary | J21: =11000+64944+20544+1461 -> 97949 | K21: =11000+233817 -> 244817 | L21: =222722+11000+1000 -> 234722 | M21: =11000+253403 -> 264403 | N21: =sum(B21:M21) -> 841891 | O21: =N21/$N$13 -> 0.38556371
A22: AMC | J22: 0 | K22: 4720 | L22: =4720 -> 4720 | M22: =4720 -> 4720 | N22: =sum(B22:M22) -> 14160 | O22: =N22/$N$13 -> 0.0064849038
A23: Subscription | J23: 0 | K23: =3304/3 -> 1101.3333 | L23: =3304/3 -> 1101.3333 | M23: =3304/3 -> 1101.3333 | N23: =sum(B23:M23) -> 3304 | O23: =N23/$N$13 -> 0.0015131442
A24: Repairs & Maintenance | J24: 0 | K24: 0 | L24: 1469 | M24: 0 | N24: =sum(B24:M24) -> 1469 | O24: =N24/$N$13 -> 0.00067276297
A25: Miscellaneous Expenses | J25: 1925.63 | K25: 3180 | L25: 10817.87 | M25: 14479.03 | N25: =sum(B25:M25) -> 30402.53 | O25: =N25/$N$13 -> 0.013923551
A26: CAM | J26: 0 | K26: 0 | L26: 0 | M26: 0 | N26: =sum(B26:M26) -> 0 | O26: =N26/$N$13 -> 0
A27: HO+CK Cost | J27: =HO!D60 -> 45151.604 | K27: =HO!H60 -> 94639.757 | L27: =HO!L60 -> 91318.444 | M27: =HO!P60 -> 114658.77 | N27: =sum(B27:M27) -> 345768.58 | O27: =N27/$N$13 -> 0.15835282
A28: Operating Expenses | B28: =+SUM(B14:B27) -> 0 | C28: =+SUM(C14:C27) -> 0 | D28: =+SUM(D14:D27) -> 0 | E28: =+SUM(E14:E27) -> 0 | F28: =+SUM(F14:F27) -> 0 | G28: =+SUM(G14:G27) -> 0 | H28: =+SUM(H14:H27) -> 0 | I28: =+SUM(I14:I27) -> 0 | ... M28: =+SUM(M14:M27) -> 838945.67 | N28: =sum(B28:M28) -> 2632868.5 | O28: =N28/$N$13 -> 1.2057838
A29: Store Level EBITDA | B29: =B13-B28 -> 0 | C29: =C13-C28 -> 0 | D29: =D13-D28 -> 0 | E29: =E13-E28 -> 0 | F29: =F13-F28 -> 0 | G29: =G13-G28 -> 0 | H29: =H13-H28 -> 0 | I29: =I13-I28 -> 0 | ... M29: =M13-M28 -> -114862.92 | N29: =sum(B29:M29) -> -449335.73 | O29: =N29/$N$13 -> -0.20578383
A30: Food Cost | B30: =(B14/B13) -> #DIV/0! | C30: =(C14/C13) -> #DIV/0! | D30: =(D14/D13) -> #DIV/0! | E30: =(E14/E13) -> #DIV/0! | F30: =(F14/F13) -> #DIV/0! | G30: =(G14/G13) -> #DIV/0! | H30: =(H14/H13) -> #DIV/0! | I30: =(I14/I13) -> #DIV/0! | ... M30: =(M14/M13) -> 0.30799581
J32: =J29+J27 -> -44591.903 | K32: =K29+K27 -> -37649.47 | L32: =L29+L27 -> -21121.631 | M32: =M29+M27 -> -204.14727
J33: =J32/J13 -> -0.17485045 | K33: =K32/K13 -> -0.061128762 | L33: =L32/L13 -> -0.035889593 | M33: =M32/M13 -> -0.00028193914

Sheet Paschim Vihar
A1: Dosa Coffee - Paschim Vihar | B1: 45748 | C1: 45778 | D1: 45809 | E1: 45839 | F1: 45870 | G1: 45901 | H1: 45931 | I1: 45962 | J1: 45992 | K1: 46023 | L1: 46054 | M1: 46082 | N1: FY 2025-26
A2: Food Cost Calculation
A3: Opening Stock | B3: 66707.07 | C3: =B7 -> 61792 | D3: =C7 -> 72325.4 | E3: =D7 -> 83083 | F3: =E7 -> 92860 | G3: =F7 -> 64313.88 | H3: =G7 -> 90986.19 | I3: =H7 -> 63542.88 | J3: =I7 -> 66406.54 | ... M3: =L7 -> 85288.19 | N3: =+SUM(J3:L3) -> 252085.3
A4: Purchases Food (Less Purchase Return) | B4: 282726 | C4: 326707.4 | D4: 315811 | E4: 333793 | F4: 337931.11 | G4: 312856.54 | H4: 264529 | I4: 248847.17 | J4: 289788 | K4: 324721 | L4: 295892.49 | M4: 365725 | N4: =sum(B4:M4) -> 3699327.7
A5: Transferred Out | B5: 0 | C5: 0 | D5: 0 | E5: 0 | F5: 0 | G5: 0 | H5: 0 | I5: 0 | J5: 0 | K5: 0 | L5: 0 | M5: 0 | N5: =+SUM(J5:L5) -> 0
A6: Wastage & Date Expired | B6: 15255 | C6: 19710.94 | D6: 19590 | E6: 25009 | F6: 25777 | G6: 23188.85 | H6: 23153.98 | I6: 24470.83 | J6: 22949 | K6: 29212.17 | L6: 31776.85 | M6: 28870.67 | N6: =+SUM(J6:L6) -> 83938.02
A7: Closing Stock | B7: 61792 | C7: 72325.4 | D7: 83083 | E7: 92860 | F7: 64313.88 | G7: 90986.19 | H7: 63542.88 | I7: 66406.54 | J7: 92190 | K7: 93488.76 | L7: 85288.19 | M7: 78348 | N7: =sum(B7:M7) -> 944624.84
A9: Gross Revenue | B9: =1081350.48*1.05+18668.48*1.05 -> 1155019.9 | C9: =1239735.51*1.05+23565.46*1.05+30*1.05 -> 1326497.5 | D9: =(1212149.69-158.24)*1.05+22468.26*1.05 -> 1296182.7 | E9: =1247234.07*1.05 -> 1309595.8 | F9: =1287588.28*1.05 -> 1351967.7 | G9: =1079515.72*1.05 -> 1133491.5 | H9: =1085387.04*1.05+10*1.05+21459.3*1.05 -> 1162199.2 | I9: =991288.66*1.05+19062.81*1.05 -> 1060869 | J9: =1091453.96*1.05+21054.3*1.05 -> 1168133.7 | K9: =1311460.89*1.05+23044.5*1.05 -> 1401230.7 | L9: =1105086.74*1.05+24117.41*1.05 -> 1185664.4 | M9: =1313732.41*1.05+30*1.05+30408.37*1.05 -> 1411379.3 | N9: =+SUM(B9:M9) -> 14962231
A10: Catering & Fairs | B10: 0 | C10: 0 | N10: =+SUM(B10:M10) -> 0
A11: Less Tax | B11: =(B9+B10)/1.05*0.05 -> 55000.948 | C11: =(C9+C10)/1.05*0.05 -> 63166.548 | D11: =(D9+D10)/1.05*0.05 -> 61722.986 | E11: =(E9+E10)/1.05*0.05 -> 62361.704 | F11: =(F9+F10)/1.05*0.05 -> 64379.414 | G11: =(G9+G10)/1.05*0.05 -> 53975.786 | H11: =(H9+H10)/1.05*0.05 -> 55342.817 | I11: =(I9+I10)/1.05*0.05 -> 50517.573 | ... M11: =(M9+M10)/1.05*0.05 -> 67208.539 | N11: =+SUM(B11:M11) -> 712487.2
A12: Less Commission | B12: =15440.81+4329.1+180.28-7.76+32.45-1.4+42980.43+440.88+7736.48+79.36 -> 71210.63 | C12: =54941.77+9889.52+25127.04+5349.54+4522.83+962.92+265.15+47.73 -> 101106.5 | D12: =53370.99+9606.78+30895.69+5561+378.61+68.15 -> 99881.22 | E12: =33019.53+5945.3+53396.84+9611.43+3159.42*1.18 -> 105701.22 | F12: =53964.39+9713.59+35734.79+6432.32+1989 -> 107834.09 | G12: =52749.42*1.18+24365.35*1.18+1611.84*1.18 -> 92897.4 | H12: =50170.93*1.18+26993.57*1.18+2247.01*1.18 -> 93705.582 | I12: =(15837.79+44792.94)*1.18+877.49*1.18+6276.49*1.18+1509.03*1.18 -> 81766.613 | J12: =49548.25*1.18+28704*1.18+2549.5*1.18 -> 95346.065 | K12: =54788*1.18+31995.64*1.18+3334.05*1.18 -> 106338.87 | L12: =25778.02*1.18+57258.85*1.18+2491.56*1.18 -> 100923.55 | M12: =30604.81*1.18+71010.22*1.18+3364*1.18+5.34 -> 123880.6 | N12: =+SUM(B12:M12) -> 1180592.3
A13: Net Revenues from F&B Sales | B13: =B9+B10-B11-B12 -> 1028808.3 | C13: =C9+C10-C11-C12 -> 1162224.5 | D13: =D9+D10-D11-D12 -> 1134578.5 | E13: =E9+E10-E11-E12 -> 1141532.9 | F13: =F9+F10-F11-F12 -> 1179754.2 | G13: =G9+G10-G11-G12 -> 986618.32 | H13: =H9+H10-H11-H12 -> 1013150.8 | I13: =I9+I10-I11-I12 -> 928584.86 | ... M13: =M9+M10-M11-M12 -> 1220290.2 | N13: =sum(B13:M13) -> 13069152 | O13: =N13/$N$7 -> 13.835283
A14: F&B Cost | B14: =+B3+B4-B5-B7 -> 287641.07 | C14: =+C3+C4-C5-C7 -> 316174 | D14: =+D3+D4-D5-D7 -> 305053.4 | E14: =+E3+E4-E5-E7 -> 324016 | F14: =+F3+F4-F5-F7 -> 366477.23 | G14: =+G3+G4-G5-G7 -> 286184.23 | H14: =+H3+H4-H5-H7 -> 291972.31 | I14: =+I3+I4-I5-I7 -> 245983.51 | ... M14: =+M3+M4-M5-M7 -> 372665.19 | N14: =sum(B14:M14) -> 3687686.8 | O14: =N14/$N$7 -> 3.9038639
A15: Electricity | B15: 68460 | C15: 82980 | D15: 90500 | E15: 83480 | F15: 84170 | G15: 86540 | H15: 77010 | I15: 56450 | J15: =47360 -> 47360 | K15: 55020 | L15: =45390 -> 45390 | M15: 69420 | N15: =sum(B15:M15) -> 846780 | O15: =N15/$N$7 -> 0.89641937
A16: Telephone/Internet | B16: 1413 | C16: =1296 -> 1296 | D16: =1296+201+1414 -> 2911 | E16: =4241/3 -> 1413.6667 | F16: =4241/3 -> 1413.6667 | G16: =2709/2+201 -> 1555.5 | H16: =2709/2+201 -> 1555.5 | I16: =1296+201 -> 1497 | J16: =201+1414 -> 1615 | K16: =201+1414 -> 1615 | L16: =1413+199 -> 1612 | M16: 1612 | N16: =sum(B16:M16) -> 19509.333 | O16: =N16/$N$7 -> 0.020652996
A17: Gas | B17: 43326 | C17: 46012 | D17: =44151 -> 44151 | E17: 47117.36 | F17: =50350.87 -> 50350.87 | G17: 43843 | H17: 46835 | I17: 42941.41 | J17: 44310 | K17: 47588.85 | L17: 36641.77 | M17: 60706.33 | N17: =sum(B17:M17) -> 553823.59 | O17: =N17/$N$7 -> 0.58628946
A18: Rent & Revenue Share | B18: =6490+102660+6490+102660 -> 218300 | C18: =6490+102660+6490+102660 -> 218300 | D18: =6490+102660+6490+102660 -> 218300 | E18: =6490+102660+6490+102660 -> 218300 | F18: =6490+102660+6490+102660 -> 218300 | G18: =6490+102660+6490+102660 -> 218300 | H18: =6490+102660+6490+102660 -> 218300 | I18: =6490+102660+6490+102660 -> 218300 | ... M18: =6490+102660+6490+102660 -> 218300 | N18: =sum(B18:M18) -> 2619600 | O18: =N18/$N$7 -> 2.7731644
A19: Insurance Premium | B19: 0 | C19: =13600.61/12 -> 1133.3842 | D19: =13600.61/12 -> 1133.3842 | E19: =13600.61/12 -> 1133.3842 | F19: =13600.61/12 -> 1133.3842 | G19: =13600.61/12 -> 1133.3842 | H19: =13600.61/12 -> 1133.3842 | I19: =13600.61/12 -> 1133.3842 | J19: =13600.61/12 -> 1133.3842 | ... M19: =13600.61/12 -> 1133.3842 | N19: =sum(B19:M19) -> 12467.226
A20: Software | B20: =69207/12 -> 5767.25 | C20: =69207/12 -> 5767.25 | D20: =69207/12 -> 5767.25 | E20: =69207/12 -> 5767.25 | F20: =69207/12 -> 5767.25 | G20: =69207/12 -> 5767.25 | H20: =69207/12 -> 5767.25 | I20: =69207/12 -> 5767.25 | ... M20: =69207/12 -> 5767.25 | N20: =sum(B20:M20) -> 69207 | O20: =N20/$N$7 -> 0.073264006
A21: Staff Salary | B21: =251172.03+120559/12 -> 261218.61 | C21: =267647+120559/12 -> 277693.58 | D21: =262742.03+120559/12 -> 272788.61 | E21: =264441+120559/12 -> 274487.58 | F21: =267053+120559/12 -> 277099.58 | G21: =266543.36+120559/12 -> 276589.94 | H21: =120559/12+266133 -> 276179.58 | I21: =120559/12+279790.03 -> 289836.61 | J21: =120559/12+270612 -> 280658.58 | K21: =120559/12+265895 -> 275941.58 | L21: =120559/12+263693 -> 273739.58 | M21: =120559/12+288361 -> 298407.58 | N21: =sum(B21:M21) -> 3334641.5 | O21: =N21/$N$7 -> 3.5301226
A22: AMC | B22: =4720+2360 -> 7080 | C22: =5192+2360 -> 7552 | D22: =5192+2360 -> 7552 | E22: =2360+5192 -> 7552 | F22: =2360+5192 -> 7552 | G22: =2360+5192 -> 7552 | H22: =2360+5192 -> 7552 | I22: =4720+2360 -> 7080 | J22: =2360+4720 -> 7080 | K22: =4720+2360 -> 7080 | L22: =4720+2360 -> 7080 | M22: =2360+4720 -> 7080 | N22: =sum(B22:M22) -> 87792 | O22: =N22/$N$7 -> 0.092938483
A23: Subscription | B23: =2124/3+6425/12 -> 1243.4167 | C23: =2124/3+6425/12 -> 1243.4167 | D23: =2124/3+6425/12 -> 1243.4167 | E23: =2124/3+6425/12 -> 1243.4167 | F23: =2124/3+6425/12 -> 1243.4167 | G23: =6425/12+2124/3 -> 1243.4167 | H23: =6425/12+2124/3 -> 1243.4167 | I23: =6425/12+2124/3 -> 1243.4167 | J23: =6425/12+2124/3 -> 1243.4167 | K23: =6425/12+3304/3 -> 1636.75 | L23: =6425/12+3304/3 -> 1636.75 | M23: =6425/12+3304/3 -> 1636.75 | N23: =sum(B23:M23) -> 16101 | O23: =N23/$N$7 -> 0.017044862
A24: Repairs & Maintenance | B24: 13350 | C24: 840 | D24: 2212 | E24: 0 | F24: 7846 | G24: 668 | H24: 2950 | I24: 0 | J24: 0 | K24: 0 | L24: =159735 -> 159735 | M24: 0 | N24: =sum(B24:M24) -> 187601 | O24: =N24/$N$7 -> 0.19859842
A25: Miscellaneous Expenses | B25: 9819.05 | C25: =11526.68 -> 11526.68 | D25: 14609 | E25: 15329.72 | F25: 13750 | G25: 9384 | H25: 15347 | I25: 9683.7 | J25: 15691.5 | K25: 15084 | L25: 9097.89 | M25: 12059 | N25: =sum(B25:M25) -> 151381.54 | O25: =N25/$N$7 -> 0.16025573
A26: CAM | N26: =sum(B26:M26) -> 0 | O26: =N26/$N$7 -> 0
A27: HO+CK Cost | B27: =HO!D34 -> 187342.32 | C27: =HO!H34 -> 204954.2 | D27: =HO!L34 -> 195744.69 | E27: =HO!P34 -> 200349.86 | F27: =HO!D47 -> 213204.44 | G27: =HO!H47 -> 177652.95 | H27: =HO!L47 -> 194974.82 | I27: =HO!P47 -> 165742.94 | J27: =HO!D61 -> 180083.6 | K27: =HO!H61 -> 188719.86 | L27: =HO!L61 -> 159555.3 | M27: =HO!P61 -> 193233.41 | N27: =sum(B27:M27) -> 2261558.4 | O27: =N27/$N$7 -> 2.3941339
A28: Operating Expenses | B28: =+SUM(B14:B27) -> 1104960.7 | C28: =+SUM(C14:C27) -> 1175472.5 | D28: =+SUM(D14:D27) -> 1161965.8 | E28: =+SUM(E14:E27) -> 1180190.2 | F28: =+SUM(F14:F27) -> 1248307.8 | G28: =+SUM(G14:G27) -> 1116413.7 | H28: =+SUM(H14:H27) -> 1140820.3 | I28: =+SUM(I14:I27) -> 1045659.2 | ... M28: =+SUM(M14:M27) -> 1242020.9 | N28: =sum(B28:M28) -> 13848149 | O28: =N28/$N$7 -> 14.659946
A29: Store Level EBITDA | B29: =B13-B28 -> -76152.394 | C29: =C13-C28 -> -13248.048 | D29: =D13-D28 -> -27387.262 | E29: =E13-E28 -> -38657.385 | F29: =F13-F28 -> -68553.646 | G29: =G13-G28 -> -129795.35 | H29: =H13-H28 -> -127669.5 | I29: =I13-I28 -> -117074.37 | ... M29: =M13-M28 -> -21730.71 | N29: =sum(B29:M29) -> -778997.53 | O29: =N29/$N$7 -> -0.8246634
A30: Food Cost | B30: =(B14/B13) -> 0.27958665 | C30: =(C14/C13) -> 0.27204211 | D30: =(D14/D13) -> 0.26886937 | E30: =(E14/E13) -> 0.2838429 | F30: =(F14/F13) -> 0.31063863 | G30: =(G14/G13) -> 0.2900658 | H30: =(H14/H13) -> 0.28818249 | I30: =(I14/I13) -> 0.26490149 | ... M30: =(M14/M13) -> 0.30539063
B32: =B29+B27 -> 111189.93 | C32: =C29+C27 -> 191706.16 | D32: =D29+D27 -> 168357.43 | E32: =E29+E27 -> 161692.47 | F32: =F29+F27 -> 144650.79 | G32: =G29+G27 -> 47857.596 | H32: =H29+H27 -> 67305.314 | I32: =I29+I27 -> 48668.573 | ... M32: =M29+M27 -> 171502.7
B33: =B32/B13 -> 0.10807643 | C33: =C32/C13 -> 0.16494762 | D33: =D32/D13 -> 0.14838764 | E33: =E32/E13 -> 0.14164505 | F33: =F32/F13 -> 0.12261096 | G33: =G32/G13 -> 0.048506697 | H33: =H32/H13 -> 0.066431687 | I33: =I32/I13 -> 0.052411551 | ... M33: =M32/M13 -> 0.14054255

Sheet Kalkaji
A1: Dosa Coffee - Kalkaji | B1: 45748 | C1: 45778 | D1: 45809 | E1: 45839 | F1: 45870 | G1: 45901 | H1: 45931 | I1: 45962 | J1: 45992 | K1: 46023 | L1: 46054 | M1: 46082 | N1: FY 2025-26
A2: Food Cost Calculation
A3: Opening Stock | B3: 95441.89 | C3: =B7 -> 97685 | D3: =C7 -> 62429.51 | E3: =D7 -> 60155 | F3: =E7 -> 59845 | G3: =F7 -> 54714 | H3: =G7 -> 58911.63 | I3: =H7 -> 56153.61 | J3: =I7 -> 60628.64 | ... M3: =L7 -> 59877.28 | N3: =+SUM(J3:L3) -> 192378.64
A4: Purchases Food (Less Purchase Return) | B4: 278705.79 | C4: 305513.39 | D4: 264173.35 | E4: 316005.58 | F4: 282024 | G4: 281193.94 | H4: 235791 | I4: 238123 | J4: 263296 | K4: 298060 | L4: 304269.58 | M4: 411008 | N4: =sum(B4:M4) -> 3478163.6
A5: Transferred Out | B5: 0 | C5: 0 | D5: 0 | E5: 0 | F5: 0 | G5: 0 | H5: 0 | I5: 0 | J5: 0 | K5: 0 | L5: 0 | M5: 0 | N5: =+SUM(J5:L5) -> 0
A6: Wastage & Date Expired | B6: 13493 | C6: 15516.67 | D6: 1176 | E6: 15396 | F6: 14301.65 | G6: 15109.73 | H6: 15200 | I6: 14636.27 | J6: 13138 | K6: 16181.63 | L6: 16591.25 | M6: 21115.88 | N6: =+SUM(J6:L6) -> 45910.88
A7: Closing Stock | B7: 97685 | C7: 62429.51 | D7: 60155 | E7: 59845 | F7: 54714 | G7: 58911.63 | H7: 56153.61 | I7: 60628.64 | J7: 66975 | K7: 64775 | L7: 59877.28 | M7: 64172 | N7: =sum(B7:M7) -> 766321.67
A9: Gross Revenue | B9: =949019.88*1.05+31238.66*1.05 -> 1029271.5 | C9: =1059982.18*1.05+38284.43*1.05 -> 1153179.9 | D9: =(961309-341.78)*1.05+29639.28*1.05 -> 1040136.8 | E9: =1157860*1.05 -> 1215753 | F9: =1065911.11*1.05 -> 1119206.7 | G9: =1053956.85*1.05 -> 1106654.7 | H9: =952315.24*1.05+29536.8*1.05 -> 1030944.6 | I9: =902376.58*1.05+27977.92*1.05 -> 976872.22 | J9: =943985.31*1.05+30744.62*1.05 -> 1023466.4 | K9: =1162212.77*1.05+32111.79*1.05 -> 1254040.8 | L9: =1225301.37*1.05+43193.28*1.05 -> 1331919.4 | M9: =1502381.58*1.05+57843.12*1.05 -> 1638235.9 | N9: =+SUM(B9:M9) -> 13919682
A10: Catering & Fairs | B10: 0 | C10: 0 | N10: =+SUM(B10:M10) -> 0
A11: Less Tax | B11: =(B9+B10)/1.05*0.05 -> 49012.927 | C11: =(C9+C10)/1.05*0.05 -> 54913.33 | D11: =(D9+D10)/1.05*0.05 -> 49530.325 | E11: =(E9+E10)/1.05*0.05 -> 57893 | F11: =(F9+F10)/1.05*0.05 -> 53295.556 | G11: =(G9+G10)/1.05*0.05 -> 52697.842 | H11: =(H9+H10)/1.05*0.05 -> 49092.602 | I11: =(I9+I10)/1.05*0.05 -> 46517.725 | ... M11: =(M9+M10)/1.05*0.05 -> 78011.235 | N11: =+SUM(B11:M11) -> 662842
A12: Less Commission | B12: =36565.33+6581.77+198.27+35.69+71886.5+315.51+12939.56+56.8 -> 128579.43 | C12: =88421.95+15915.96+33541.21+6051.36+6037.41+1089.24+63.09+114.21+31.92 -> 151266.35 | D12: =67854.25+12213.7+43070.76+7752.79+95.82+17.25 -> 131004.57 | E12: =51404.65+9299.86+85365.2+15365.73+22.88*1.18+22.68*1.18 -> 161489.2 | F12: =80473.94+14485.3+39321.37+7077.89+1989 -> 143347.5 | G12: =79852.58*1.18+31716.22*1.18+140.15*1.18 -> 131816.56 | H12: =68453.66*1.18+31901.06*1.18+204.92*1.18 -> 118660.38 | I12: =(24858+64481.55)*1.18+122.01*1.18+9301.55*1.18+182.62*1.18 -> 116755.96 | J12: =71668.44*1.18+31667.57*1.18+786.4*1.18 -> 122864.44 | K12: =74872.26*1.18+44254.48*1.18+905.34*1.18 -> 141637.85 | L12: =32663.51*1.18+101232.67*1.18+801.52*1.18+237.86*1.18 -> 159223.96 | M12: =49950.83*1.18+134304.47*1.18+1047.55*1.18+205.02 -> 218862.38 | N12: =+SUM(B12:M12) -> 1725508.6
A13: Net Revenues from F&B Sales | B13: =B9+B10-B11-B12 -> 851679.11 | C13: =C9+C10-C11-C12 -> 947000.26 | D13: =D9+D10-D11-D12 -> 859601.93 | E13: =E9+E10-E11-E12 -> 996370.8 | F13: =F9+F10-F11-F12 -> 922563.61 | G13: =G9+G10-G11-G12 -> 922140.29 | H13: =H9+H10-H11-H12 -> 863191.66 | I13: =I9+I10-I11-I12 -> 813598.54 | ... M13: =M9+M10-M11-M12 -> 1341362.3 | N13: =sum(B13:M13) -> 11531331 | O13: =N13/$N$7 -> 15.047638
A14: F&B Cost | B14: =+B3+B4-B5-B7 -> 276462.68 | C14: =+C3+C4-C5-C7 -> 340768.88 | D14: =+D3+D4-D5-D7 -> 266447.86 | E14: =+E3+E4-E5-E7 -> 316315.58 | F14: =+F3+F4-F5-F7 -> 287155 | G14: =+G3+G4-G5-G7 -> 276996.31 | H14: =+H3+H4-H5-H7 -> 238549.02 | I14: =+I3+I4-I5-I7 -> 233647.97 | ... M14: =+M3+M4-M5-M7 -> 406713.28 | N14: =sum(B14:M14) -> 3509433.5 | O14: =N14/$N$7 -> 4.5795828
A15: Electricity | B15: 42430 | C15: 51530 | D15: 61060 | E15: 71310 | F15: =76140 -> 76140 | G15: 62810 | H15: 58390 | I15: =44030 -> 44030 | J15: 34240 | K15: =40760 -> 40760 | L15: 37610 | M15: =47740 -> 47740 | N15: =sum(B15:M15) -> 628050 | O15: =N15/$N$7 -> 0.81956445
A16: Telephone/Internet | B16: 2574 | C16: 2574 | D16: =1295 -> 1295 | E16: 1295 | F16: 2591 | G16: 1296 | H16: 1296 | I16: 1296 | J16: =1295 -> 1295 | K16: 1296 | L16: =1296 -> 1296 | M16: =1296 -> 1296 | N16: =sum(B16:M16) -> 19400 | O16: =N16/$N$7 -> 0.02531574
A17: Gas | N17: =sum(B17:M17) -> 0 | O17: =N17/$N$7 -> 0
A18: Rent & Revenue Share | B18: =138000 -> 138000 | C18: =162840 -> 162840 | D18: =162840 -> 162840 | E18: =162840 -> 162840 | F18: =162840 -> 162840 | G18: =162840 -> 162840 | H18: =162840 -> 162840 | I18: =162840 -> 162840 | J18: =162840 -> 162840 | ... M18: =162840 -> 162840 | N18: =sum(B18:M18) -> 1929240 | O18: =N18/$N$7 -> 2.5175329
A19: Insurance | B19: 0 | C19: =10394.5/12 -> 866.20833 | D19: =10394.5/12 -> 866.20833 | E19: =10394.5/12 -> 866.20833 | F19: =10394.5/12 -> 866.20833 | G19: =10394.5/12 -> 866.20833 | H19: =10394.5/12 -> 866.20833 | I19: =10394.5/12 -> 866.20833 | J19: =10394.5/12 -> 866.20833 | ... M19: =10394.5/12 -> 866.20833 | N19: =sum(B19:M19) -> 9528.2917
A20: Software | B20: =69207/12 -> 5767.25 | C20: =69207/12 -> 5767.25 | D20: =69207/12 -> 5767.25 | E20: =69207/12 -> 5767.25 | F20: =69207/12 -> 5767.25 | G20: =69207/12 -> 5767.25 | H20: =69207/12 -> 5767.25 | I20: =69207/12 -> 5767.25 | ... M20: =69207/12 -> 5767.25 | N20: =sum(B20:M20) -> 69207 | O20: =N20/$N$7 -> 0.090310639
A21: Staff Salary | B21: =22000+249715.67+2000+124322/12 -> 284075.84 | C21: =278891+124322/12 -> 289251.17 | D21: =258471.67+124322/12 -> 268831.84 | E21: =241848+124322/12 -> 252208.17 | F21: =236988.84+124322/12 -> 247349.01 | G21: =236003.33+124322/12 -> 246363.5 | H21: =124322/12+215774 -> 226134.17 | I21: =124322/12+223201.34 -> 233561.51 | J21: =124322/12+245520 -> 255880.17 | K21: =124322/12+248399 -> 258759.17 | L21: =124322/12+268658 -> 279018.17 | M21: =124322/12+255408 -> 265768.17 | N21: =sum(B21:M21) -> 3107200.9 | O21: =N21/$N$7 -> 4.0546953
A22: AMC | B22: =4720+2950 -> 7670 | C22: =5192+2950 -> 8142 | D22: =4012+2950 -> 6962 | E22: =2950+5192 -> 8142 | F22: =5192+2950 -> 8142 | G22: =5192+2950 -> 8142 | H22: =2950+5192 -> 8142 | I22: =4720+2950 -> 7670 | J22: =2950+4720 -> 7670 | K22: =4720+2950 -> 7670 | L22: =4720+2950 -> 7670 | M22: =4720+2950 -> 7670 | N22: =sum(B22:M22) -> 93692 | O22: =N22/$N$7 -> 0.12226197
A23: Subscription | B23: =2124/3+6425/12 -> 1243.4167 | C23: =2124/3+6425/12 -> 1243.4167 | D23: =2124/3+6425/12 -> 1243.4167 | E23: =2124/3+6425/12 -> 1243.4167 | F23: =2124/3+6425/12 -> 1243.4167 | G23: =2124/3+6425/12 -> 1243.4167 | H23: =2124/3+6425/12 -> 1243.4167 | I23: =2124/3+6425/12 -> 1243.4167 | J23: =2124/3+6425/12 -> 1243.4167 | K23: =6425/12+3304/3 -> 1636.75 | L23: =6425/12+3304/3 -> 1636.75 | M23: =6425/12+3304/3 -> 1636.75 | N23: =sum(B23:M23) -> 16101 | O23: =N23/$N$7 -> 0.021010759
A24: Repairs & Maintenance | B24: 1920 | C24: 5547 | D24: 3538 | E24: 0 | F24: 11605 | G24: =460 -> 460 | H24: 0 | I24: 49692 | J24: 0 | K24: 0 | L24: =150 -> 150 | M24: 340 | N24: =sum(B24:M24) -> 73252 | O24: =N24/$N$7 -> 0.095589102
A25: Miscellaneous Expenses | B25: 10132.87 | C25: 11031.53 | D25: 12526 | E25: 4836.64 | F25: 22883 | G25: =22321 -> 22321 | H25: 12650 | I25: 42035 | J25: 9697 | K25: 7368.41 | L25: 9505.61 | M25: 12935.06 | N25: =sum(B25:M25) -> 177922.12 | O25: =N25/$N$7 -> 0.23217681
A26: CAM | N26: =sum(B26:M26) -> 0 | O26: =N26/$N$7 -> 0
A27: HO+CK Cost | B27: =HO!D35 -> 155087.73 | C27: =HO!H35 -> 167000.17 | D27: =HO!L35 -> 148303.99 | E27: =HO!P35 -> 174872.54 | F27: =HO!D48 -> 166725.12 | G27: =HO!H48 -> 166042.88 | H27: =HO!L48 -> 166116.09 | I27: =HO!P48 -> 145219.06 | J27: =HO!D62 -> 150818.62 | K27: =HO!H62 -> 161755.66 | L27: =HO!L62 -> 172122.29 | M27: =HO!P62 -> 212405.22 | N27: =sum(B27:M27) -> 1986469.4 | O27: =N27/$N$7 -> 2.5922135
A28: Operating Expenses | B28: =+SUM(B14:B27) -> 925363.78 | C28: =+SUM(C14:C27) -> 1046561.6 | D28: =+SUM(D14:D27) -> 939681.56 | E28: =+SUM(E14:E27) -> 999696.8 | F28: =+SUM(F14:F27) -> 993307 | G28: =+SUM(G14:G27) -> 955148.56 | H28: =+SUM(H14:H27) -> 881994.15 | I28: =+SUM(I14:I27) -> 927868.41 | ... M28: =+SUM(M14:M27) -> 1125977.9 | N28: =sum(B28:M28) -> 11619496 | O28: =N28/$N$7 -> 15.162688
A29: Store Level EBITDA | B29: =B13-B28 -> -73684.669 | C29: =C13-C28 -> -99561.362 | D29: =D13-D28 -> -80079.627 | E29: =E13-E28 -> -3326.0015 | F29: =F13-F28 -> -70743.387 | G29: =G13-G28 -> -33008.268 | H29: =H13-H28 -> -18802.483 | I29: =I13-I28 -> -114269.87 | ... M29: =M13-M28 -> 215384.38 | N29: =sum(B29:M29) -> -88164.736 | O29: =N29/$N$7 -> -0.11504925
A30: Food Cost | B30: =(B14/B13) -> 0.32460897 | C30: =(C14/C13) -> 0.35984032 | D30: =(D14/D13) -> 0.30996657 | E30: =(E14/E13) -> 0.31746773 | F30: =(F14/F13) -> 0.31125767 | G30: =(G14/G13) -> 0.30038413 | H30: =(H14/H13) -> 0.27635695 | I30: =(I14/I13) -> 0.28717845 | ... M30: =(M14/M13) -> 0.30320911
B32: =B29+B27 -> 81403.057 | C32: =C29+C27 -> 67438.808 | D32: =D29+D27 -> 68224.358 | E32: =E29+E27 -> 171546.54 | F32: =F29+F27 -> 95981.728 | G32: =G29+G27 -> 133034.61 | H32: =H29+H27 -> 147313.6 | I32: =I29+I27 -> 30949.187 | ... M32: =M29+M27 -> 427789.6
B33: =B32/B13 -> 0.095579492 | C33: =C32/C13 -> 0.071213083 | D33: =D32/D13 -> 0.079367386 | E33: =E32/E13 -> 0.17217138 | F33: =F32/F13 -> 0.10403806 | G33: =G32/G13 -> 0.14426721 | H33: =H32/H13 -> 0.17066152 | I33: =I32/I13 -> 0.038039875 | ... M33: =M32/M13 -> 0.31892174

Sheet CP
A1: Dosa Coffee - Connaught Place | B1: 45748 | C1: 45778 | D1: 45809 | E1: 45839 | F1: 45870 | G1: 45901 | H1: 45931 | I1: 45962 | J1: 45992 | K1: 46023 | L1: 46054 | M1: 46082 | N1: FY 2025-26
A2: Food Cost Calculation
A3: Opening Stock | B3: 132472.22 | C3: =B7 -> 131604 | D3: =C7 -> 145611.46 | E3: =D7 -> 176614 | F3: =E7 -> 110267 | G3: =F7 -> 71785.74 | H3: =G7 -> 54025 | I3: =H7 -> 114942.97 | J3: =I7 -> 111461.81 | ... M3: =L7 -> 52290.73 | N3: =+SUM(J3:L3) -> 336444.81
A4: Purchases Food (Less Purchase Return) | B4: 604206.17 | C4: 615366.91 | D4: 712163.64 | E4: 661512.31 | F4: 652755.89 | G4: 613813.96 | H4: 588386.72 | I4: 613969.27 | J4: 876850.56 | K4: 723099 | L4: 1058524.1 | M4: 991269.96 | N4: =sum(B4:M4) -> 8711918.5
A5: Transferred Out | B5: 0 | C5: 0 | D5: 0 | E5: 0 | F5: 0 | G5: 0 | H5: 0 | I5: 0 | J5: 0 | K5: 0 | L5: 0 | M5: 0 | N5: =+SUM(J5:L5) -> 0
A6: Wastage & Date Expired | B6: 31832 | C6: 31904 | D6: 42936 | E6: 53107 | F6: 34043.9 | G6: 37897.95 | H6: 43202 | I6: 28115 | J6: 73825 | K6: 63780.8 | L6: 74900 | M6: 78263.77 | N6: =+SUM(J6:L6) -> 212505.8
A7: Closing Stock | B7: 131604 | C7: 145611.46 | D7: 176614 | E7: 110267 | F7: =71785.74 -> 71785.74 | G7: 54025 | H7: 114942.97 | I7: 111461.81 | J7: 172057 | K7: 52926 | L7: 52290.73 | M7: 77223.28 | N7: =sum(B7:M7) -> 1270809
A9: Gross Revenue | B9: =2430078.54*1.05+10416.48*1.05 -> 2562519.8 | C9: =2350403*1.05+7194.05*1.05+10*1.05 -> 2475487.4 | D9: =(2623906.93-148.12)*1.05+9790.08*1.05 -> 2765226.3 | E9: =2701704.98*1.05 -> 2836790.2 | F9: =2810915.09*1.05 -> 2951460.8 | G9: =2541942.94*1.05 -> 2669040.1 | H9: =2144586.16*1.05+7839.35*1.05 -> 2260046.8 | I9: =2540620.94*1.05+6152.28*1.05 -> 2674111.9 | J9: =2889105.4*1.05+7582.47*1.05 -> 3041522.3 | K9: =3180014*1.05+6344.71*1.05 -> 3345676.6 | L9: =4507882.21*1.05+7169.11*1.05 -> 4740803.9 | M9: =4152000.44*1.05+7408.53*1.05 -> 4367379.4 | N9: =+SUM(B9:M9) -> 36690066
A10: Catering & Fairs | B10: 0 | C10: 0 | N10: =+SUM(B10:M10) -> 0
A11: Less Tax | B11: =(B9+B10)/1.05*0.05 -> 122024.75 | C11: =(C9+C10)/1.05*0.05 -> 117880.35 | D11: =(D9+D10)/1.05*0.05 -> 131677.44 | E11: =(E9+E10)/1.05*0.05 -> 135085.25 | F11: =(F9+F10)/1.05*0.05 -> 140545.75 | G11: =(G9+G10)/1.05*0.05 -> 127097.15 | H11: =(H9+H10)/1.05*0.05 -> 107621.28 | I11: =(I9+I10)/1.05*0.05 -> 127338.66 | ... M11: =(M9+M10)/1.05*0.05 -> 207970.45 | N11: =+SUM(B11:M11) -> 1747146
A12: Less Commission | B12: =9923.48+1872.83+869.8+1294.95+156.56+233.09+23656.38+1490.52+4258.14+268.3 -> 44024.05 | C12: =17978.66+3236.18+16091.76+2070.8+2896.51+372.75+2285.45+411.38 -> 45343.49 | D12: =23333+4200.08+19127.34+3442+3657+658.28 -> 54417.7 | E12: =18265+2851+505.65+22643.73+4075.88+1541.04*1.18 -> 50159.687 | F12: =+19343.87+3481.9+15486.66+2787+1989 -> 43088.43 | G12: =17458.14*1.18+13461.6*1.18+919.01*1.18 -> 37569.725 | H12: =18574.86*1.18+13613.57*1.18+5461.48*1.18 -> 44426.894 | I12: =(7755.21+17699.47)*1.18+2262.27*1.18+1701.21*1.18+1737.63*1.18 -> 36763.832 | J12: =21053.55*1.18+14490*1.18+4122.06*1.18 -> 46805.42 | K12: =19855.98*1.18+13916.8*1.18 -> 39851.88 | L12: =16584.96*1.18+22480.1*1.18 -> 46096.771 | M12: =25949.79*1.18+24515.1*1.18 -> 59548.57 | N12: =+SUM(B12:M12) -> 548096.45
A13: Net Revenues from F&B Sales | B13: =B9+B10-B11-B12 -> 2396471 | C13: =C9+C10-C11-C12 -> 2312263.6 | D13: =D9+D10-D11-D12 -> 2579131.2 | E13: =E9+E10-E11-E12 -> 2651545.3 | F13: =F9+F10-F11-F12 -> 2767826.7 | G13: =G9+G10-G11-G12 -> 2504373.2 | H13: =H9+H10-H11-H12 -> 2107998.6 | I13: =I9+I10-I11-I12 -> 2510009.4 | ... M13: =M9+M10-M11-M12 -> 4099860.4 | N13: =sum(B13:M13) -> 34394823
A14: F&B Cost | B14: =+B3+B4-B5-B7 -> 605074.39 | C14: =+C3+C4-C5-C7 -> 601359.45 | D14: =+D3+D4-D5-D7 -> 681161.1 | E14: =+E3+E4-E5-E7 -> 727859.31 | F14: =+F3+F4-F5-F7 -> 691237.15 | G14: =+G3+G4-G5-G7 -> 631574.7 | H14: =+H3+H4-H5-H7 -> 527468.75 | I14: =+I3+I4-I5-I7 -> 617450.43 | ... M14: =+M3+M4-M5-M7 -> 966337.41 | N14: =sum(B14:M14) -> 8767167.4 | O14: =N14/$N$13 -> 0.25489788
A15: Electricity | B15: =153639+961892/12 -> 233796.67 | C15: =191494+961892/12 -> 271651.67 | D15: =191649+961892/12 -> 271806.67 | E15: =151000+961892/12 -> 231157.67 | F15: =151000+728+961892/12 -> 231885.67 | G15: =138481+961892/12 -> 218638.67 | H15: =132053++961892/12 -> 212210.67 | I15: =195973/2+961892/12 -> 178144.17 | J15: =195973/2+961892/12 -> 178144.17 | K15: =87485+961892/12 -> 167642.67 | L15: =91020++961892/12 -> 171177.67 | M15: =24000+961892/12+213288-91020 -> 226425.67 | N15: =sum(B15:M15) -> 2592682 | O15: =N15/$N$13 -> 0.075380007
A16: Telephone/Internet | B16: 1969 | C16: 1969 | D16: 1969 | E16: 1969 | F16: =5310/3 -> 1770 | G16: =5310/3+202 -> 1972 | H16: =5310/3 -> 1770 | I16: =5310/3 -> 1770 | J16: 1770 | K16: =1770+202 -> 1972 | L16: =1770+202 -> 1972 | M16: 1972 | N16: =sum(B16:M16) -> 22844 | O16: =N16/$N$13 -> 0.00066416972
A17: Gas | B17: 97556 | C17: 100500 | D17: 82175 | E17: 95100 | F17: =46545+62060 -> 108605 | G17: =72000 -> 72000 | H17: 81836 | I17: 90000 | J17: 85528 | K17: 99913 | L17: =115000 -> 115000 | M17: =184000-45000+30000 -> 169000 | N17: =sum(B17:M17) -> 1197213 | O17: =N17/$N$13 -> 0.034807942
A18: Rent & Revenue Share | B18: =1180000 -> 1180000 | C18: =1180000 -> 1180000 | D18: =1180000 -> 1180000 | E18: =1180000 -> 1180000 | F18: =1180000 -> 1180000 | G18: =1180000 -> 1180000 | H18: =1180000 -> 1180000 | I18: =1180000 -> 1180000 | ... M18: =1180000 -> 1180000 | N18: =sum(B18:M18) -> 14160000 | O18: =N18/$N$13 -> 0.41168986
A19: Insurance | B19: 0 | C19: =32829.89/12 -> 2735.8242 | D19: =32829.89/12 -> 2735.8242 | E19: =32829.89/12 -> 2735.8242 | F19: =32829.89/12 -> 2735.8242 | G19: =32829.89/12 -> 2735.8242 | H19: =32829.89/12 -> 2735.8242 | I19: =32829.89/12 -> 2735.8242 | J19: =32829.89/12 -> 2735.8242 | ... M19: =32829.89/12 -> 2735.8242 | N19: =sum(B19:M19) -> 30094.066 | O19: =N19/$N$13 -> 0.00087495917
A20: Software | B20: =112336/12 -> 9361.3333 | C20: =112336/12 -> 9361.3333 | D20: =112336/12 -> 9361.3333 | E20: =112336/12 -> 9361.3333 | F20: =112336/12 -> 9361.3333 | G20: =112336/12 -> 9361.3333 | H20: =93279/12 -> 7773.25 | I20: =93279/12 -> 7773.25 | J20: =93279/12 -> 7773.25 | K20: =93279/12 -> 7773.25 | L20: =93279/12 -> 7773.25 | M20: =93279/12 -> 7773.25 | N20: =sum(B20:M20) -> 102807.5 | O20: =N20/$N$13 -> 0.0029890399
A21: Staff Salary | B21: =18000+514052.03+1750+174208/12 -> 548319.36 | C21: =498600+18000+174208/12 -> 531117.33 | D21: =486581+18000+174208/12 -> 519098.33 | E21: =450710+18000+34193+174208/12 -> 517420.33 | F21: =411311+18000+43225+174208/12 -> 487053.33 | G21: =445584.47+42666+18000+174208/12 -> 520767.8 | H21: =174208/12+448835+34838.6+18000 -> 516190.93 | I21: =174208/12+18000+40000+449066.67 -> 521584 | J21: =174208/12+453934+18000+41935 -> 528386.33 | K21: =174208/12+18000+42580+2975+447023 -> 525095.33 | L21: =174208/12+530923+18000+28571 -> 592011.33 | M21: =174208/12+18000+40645+500050 -> 573212.33 | N21: =sum(B21:M21) -> 6380256.8 | O21: =N21/$N$13 -> 0.1855005
A22: AMC | B22: =4720+7080 -> 11800 | C22: =5192+7080 -> 12272 | D22: =5192+7080 -> 12272 | E22: =7080+5192 -> 12272 | F22: =5192+7080 -> 12272 | G22: =5192+7080 -> 12272 | H22: =7080+5192 -> 12272 | I22: =4720+7080 -> 11800 | J22: =7080+4720 -> 11800 | K22: =4720+7080 -> 11800 | L22: =4720+7080 -> 11800 | M22: =4720+7080 -> 11800 | N22: =sum(B22:M22) -> 144432 | O22: =N22/$N$13 -> 0.0041992366
A23: Subscription | B23: =2124/3 -> 708 | C23: =2124/3 -> 708 | D23: =2124/3 -> 708 | E23: =2124/3 -> 708 | F23: =2124/3 -> 708 | G23: =2124/3 -> 708 | H23: =2124/3 -> 708 | I23: =2124/3 -> 708 | J23: =2124/3 -> 708 | K23: =3304/3 -> 1101.3333 | L23: =3304/3 -> 1101.3333 | M23: =3304/3 -> 1101.3333 | N23: =sum(B23:M23) -> 9676 | O23: =N23/$N$13 -> 0.00028132141
A24: Repairs & Maintenance | B24: 2130 | C24: 0 | D24: 5464 | E24: 0 | F24: 33346 | G24: =25018 -> 25018 | H24: 10587 | I24: 0 | J24: 4530 | K24: 12708 | L24: 1650 | M24: 0 | N24: =sum(B24:M24) -> 95433 | O24: =N24/$N$13 -> 0.0027746327
A25: Miscellaneous Expenses | B25: 20806.85 | C25: 10005 | D25: 8401 | E25: 6355.68 | F25: 27118 | G25: =26250.47 -> 26250.47 | H25: 19419 | I25: 23127.41 | J25: 23513.8 | K25: 26854 | L25: =106951 -> 106951 | M25: 30328.47 | N25: =sum(B25:M25) -> 329130.68 | O25: =N25/$N$13 -> 0.0095691924
A26: CAM | N26: =sum(B26:M26) -> 0 | O26: =N26/$N$13 -> 0
A27: HO+CK Cost | B27: =HO!D36 -> 436388.81 | C27: =HO!H36 -> 407759.56 | D27: =HO!L36 -> 444968.1 | E27: =HO!P36 -> 465371.38 | F27: =HO!D49 -> 500199.89 | G27: =HO!H49 -> 450943.67 | H27: =HO!L49 -> 405671.76 | I27: =HO!P49 -> 448011.13 | J27: =HO!D63 -> 504557.76 | K27: =HO!H63 -> 483491.71 | L27: =HO!L63 -> 693434.62 | M27: =HO!P63 -> 649214.43 | N27: =sum(B27:M27) -> 5890012.8 | O27: =N27/$N$13 -> 0.17124707
A28: Operating Expenses | B28: =+SUM(B14:B27) -> 3147910.4 | C28: =+SUM(C14:C27) -> 3129439.2 | D28: =+SUM(D14:D27) -> 3220120.4 | E28: =+SUM(E14:E27) -> 3250310.5 | F28: =+SUM(F14:F27) -> 3286292.2 | G28: =+SUM(G14:G27) -> 3152242.5 | H28: =+SUM(H14:H27) -> 2978643.2 | I28: =+SUM(I14:I27) -> 3083104.2 | ... M28: =+SUM(M14:M27) -> 3819900.7 | N28: =sum(B28:M28) -> 39721749 | O28: =N28/$N$13 -> 1.1548758
A29: Store Level EBITDA | B29: =B13-B28 -> -751439.44 | C29: =C13-C28 -> -817175.61 | D29: =D13-D28 -> -640989.16 | E29: =E13-E28 -> -598765.24 | F29: =F13-F28 -> -518465.54 | G29: =G13-G28 -> -647869.26 | H29: =H13-H28 -> -870644.56 | I29: =I13-I28 -> -573094.82 | ... M29: =M13-M28 -> 279959.68 | N29: =sum(B29:M29) -> -5326926.1 | O29: =N29/$N$13 -> -0.15487581
A30: Food Cost | B30: =(B14/B13) -> 0.25248559 | C30: =(C14/C13) -> 0.26007392 | D30: =(D14/D13) -> 0.26410487 | E30: =(E14/E13) -> 0.27450382 | F30: =(F14/F13) -> 0.24974004 | G30: =(G14/G13) -> 0.25218873 | H30: =(H14/H13) -> 0.25022253 | I30: =(I14/I13) -> 0.24599527 | ... M30: =(M14/M13) -> 0.23570008
B32: =B29+B27 -> -315050.63 | C32: =C29+C27 -> -409416.05 | D32: =D29+D27 -> -196021.07 | E32: =E29+E27 -> -133393.85 | F32: =F29+F27 -> -18265.647 | G32: =G29+G27 -> -196925.58 | H32: =H29+H27 -> -464972.81 | I32: =I29+I27 -> -125083.7 | ... M32: =M29+M27 -> 929174.11
B33: =B32/B13 -> -0.13146441 | C33: =C32/C13 -> -0.17706288 | D33: =D32/D13 -> -0.076002752 | E33: =E32/E13 -> -0.050307968 | F33: =F32/F13 -> -0.0065992744 | G33: =G32/G13 -> -0.078632682 | H33: =H32/H13 -> -0.22057548 | I33: =I32/I13 -> -0.049833956 | ... M33: =M32/M13 -> 0.22663555

Sheet Rohini
A1: Dosa Coffee - Rohini | B1: 45748 | C1: 45778 | D1: 45809 | E1: 45839 | F1: 45870 | G1: 45901 | H1: 45931 | I1: 45962 | J1: 45992 | K1: 46023 | L1: 46054 | M1: 46082 | N1: FY 2025-26
A2: Food Cost Calculation
A3: Opening Stock | B3: 78958 | C3: =B7 -> 55358 | D3: =C7 -> 60812.82 | E3: =D7 -> 58295 | F3: =E7 -> 101648 | G3: =F7 -> 138147.56 | H3: =G7 -> 125279 | I3: =H7 -> 135028 | J3: =I7 -> 160292.87 | ... M3: =L7 -> 108316.14 | N3: =+SUM(J3:L3) -> 464080.87
A4: Purchases Food (Less Purchase Return) | B4: 321066.13 | C4: 404521.9 | D4: 414481.78 | E4: 462946.55 | F4: 470724 | G4: 362752.08 | H4: 389411.55 | I4: =381061.24 -> 381061.24 | J4: 398273 | K4: 460181 | L4: 401477.98 | M4: 525695.97 | N4: =sum(B4:M4) -> 4992593.2
A5: Transferred Out | B5: 0 | C5: 0 | D5: 0 | E5: 0 | F5: 0 | G5: 0 | H5: 0 | I5: 0 | J5: 0 | K5: 0 | L5: 0 | M5: 0 | N5: =+SUM(J5:L5) -> 0
A6: Wastage & Date Expired | B6: 29120 | C6: 29093.54 | D6: 27548 | E6: 30161 | F6: 31076.73 | G6: 38116 | H6: 29838 | I6: 22199.78 | J6: 28347 | K6: 30924 | L6: 30485.51 | M6: 35340 | N6: =+SUM(J6:L6) -> 89756.51
A7: Closing Stock | B7: 55358 | C7: 60812.82 | D7: 58295 | E7: 101648 | F7: 138147.56 | G7: 125279 | H7: 135028 | I7: 160292.87 | J7: 155683 | K7: 148105 | L7: 108316.14 | M7: 104699.97 | N7: =sum(B7:M7) -> 1351665.4
A9: Gross Revenue | B9: =1398384.43*1.05+18404.84*1.05 -> 1487628.7 | C9: =1745448.86*1.05+26883.67*1.05 -> 1860949.2 | D9: =(1694569.15-163.02)*1.05+27224.37*1.05 -> 1807712 | E9: =1709367.9*1.05 -> 1794836.3 | F9: =1795423.15*1.05 -> 1885194.3 | G9: =1477963*1.05 -> 1551861.1 | H9: =1618159.73*1.05+30363.23*1.05 -> 1730949.1 | I9: =1419174*1.05+116970.67*1.05+21828.87*1.05+70293*1.05+27475*1.05 -> 1738528.6 | J9: =1687342 -> 1687342 | K9: =1929818.81*1.05+27669.61*1.05 -> 2055362.8 | L9: =1808724.29*1.05+36707.9*1.05 -> 1937703.8 | M9: =2134101.58*1.05+46165.95*1.05 -> 2289280.9 | N9: =+SUM(B9:M9) -> 21827349
A10: Catering & Fairs | B10: 0 | C10: 0 | N10: =+SUM(B10:M10) -> 0
A11: Less Tax | B11: =(B9+B10)/1.05*0.05 -> 70839.463 | C11: =(C9+C10)/1.05*0.05 -> 88616.626 | D11: =(D9+D10)/1.05*0.05 -> 86081.525 | E11: =(E9+E10)/1.05*0.05 -> 85468.395 | F11: =(F9+F10)/1.05*0.05 -> 89771.158 | G11: =(G9+G10)/1.05*0.05 -> 73898.15 | H11: =(H9+H10)/1.05*0.05 -> 82426.148 | I11: =(I9+I10)/1.05*0.05 -> 82787.077 | ... M11: =(M9+M10)/1.05*0.05 -> 109013.38 | N11: =+SUM(B11:M11) -> 1039397.6
A12: Less Commission | B12: =38487.92+6927.83+225.12-26.28+40.52-4.73+42502.43+778.56+7650.42+140.14 -> 96721.93 | C12: =63406.76+11413.22+41773.88+10633.61+7519.3+957.03+669.51+120.51 -> 136493.82 | D12: =64358.46+11584.52+52812.99+9508+293.11+52.76 -> 138609.84 | E12: =57556.99+10360+72474.81+13045.46+4135.23*1.18 -> 158316.83 | F12: =74642.55+13435.66+59181.52+10652.65+1989 -> 159901.38 | G12: =66657.35*1.18+52586.69*1.18+2625*1.18 -> 143805.47 | H12: =71357.49*1.18+59254.82*1.18+4032.67*1.18 -> 158881.08 | I12: =(38281.76+55889.89)*1.18+2481.33*1.18+18476.43*1.18+2318.87*1.18 -> 138588.97 | J12: =58886.79*1.18+58695.19*1.18+1959.94*1.18 -> 141059.47 | K12: =66782.03*1.18+66864*1.18+4003.08*1.18 -> 162425.95 | L12: =58662.31*1.18+87621.45*1.18+2575.36*1.18 -> 175653.76 | M12: =73628.42*1.18+109052.14*1.18+4061.21*1.18 -> 220355.29 | N12: =+SUM(B12:M12) -> 1830813.8
A13: Net Revenues from F&B Sales | B13: =B9+B10-B11-B12 -> 1320067.3 | C13: =C9+C10-C11-C12 -> 1635838.7 | D13: =D9+D10-D11-D12 -> 1583020.7 | E13: =E9+E10-E11-E12 -> 1551051.1 | F13: =F9+F10-F11-F12 -> 1635521.8 | G13: =G9+G10-G11-G12 -> 1334157.5 | H13: =H9+H10-H11-H12 -> 1489641.9 | I13: =I9+I10-I11-I12 -> 1517152.6 | ... M13: =M9+M10-M11-M12 -> 1959912.2 | N13: =sum(B13:M13) -> 18957138 | O13: =N13/$N$7 -> 14.025023
A14: F&B Cost | B14: =+B3+B4-B5-B7 -> 344666.13 | C14: =+C3+C4-C5-C7 -> 399067.08 | D14: =+D3+D4-D5-D7 -> 416999.6 | E14: =+E3+E4-E5-E7 -> 419593.55 | F14: =+F3+F4-F5-F7 -> 434224.44 | G14: =+G3+G4-G5-G7 -> 375620.64 | H14: =+H3+H4-H5-H7 -> 379662.55 | I14: =+I3+I4-I5-I7 -> 355796.37 | ... M14: =+M3+M4-M5-M7 -> 529312.14 | N14: =sum(B14:M14) -> 4966851.2 | O14: =N14/$N$7 -> 3.674616
A15: Electricity | B15: =85890+39414/2 -> 105597 | C15: 99810 | D15: 154890 | E15: =100730+25925/7 -> 104433.57 | F15: =87570+25925/7 -> 91273.571 | G15: =84410+25925/7 -> 88113.571 | H15: =79800+25925/7 -> 83503.571 | I15: =59120+25925/7 -> 62823.571 | J15: =62920+25925/7 -> 66623.571 | K15: =65360+25925/7 -> 69063.571 | L15: =68700+25925/7 -> 72403.571 | M15: 80000 | N15: =sum(B15:M15) -> 1078535.6 | O15: =N15/$N$7 -> 0.79793091
A16: Telephone/Internet | F16: =2590/2 -> 1295 | G16: =2590/2 -> 1295 | H16: =2590/2 -> 1295 | I16: 1295 | J16: =2591 -> 2591 | K16: =2709/2 -> 1354.5 | L16: =2709/2 -> 1354.5 | M16: =1355 -> 1355 | N16: =sum(B16:M16) -> 11835 | O16: =N16/$N$7 -> 0.0087558654
A17: Gas | B17: 38361 | C17: 38748.5 | D17: 39925 | E17: =38546.91 -> 38546.91 | F17: =43411 -> 43411 | G17: =33799.72 -> 33799.72 | H17: 36907 | I17: =34253 -> 34253 | J17: 38118 | K17: 39769.41 | L17: =33691.84 -> 33691.84 | M17: 40000 | N17: =sum(B17:M17) -> 455531.38 | O17: =N17/$N$7 -> 0.33701491
A18: Rent & Revenue Share | B18: =91875+91875 -> 183750 | C18: =108412.5+108412.5 -> 216825 | D18: =108412.5+108412.5 -> 216825 | E18: =108412.5+108412.5 -> 216825 | F18: =108412.5+108412.5 -> 216825 | G18: =108412.5+108412.5 -> 216825 | H18: =108412.5+108412.5 -> 216825 | I18: =108412.5+108412.5 -> 216825 | J18: =108412.5+108412.5 -> 216825 | ... L18: =108412.5+108412.5 -> 216825 | M18: =113832.24+113832.24 -> 227664.48 | N18: =sum(B18:M18) -> 2579664.5 | O18: =N18/$N$7 -> 1.9085082
A19: Insurance | B19: 0 | C19: =11617.69/12 -> 968.14083 | D19: =11617.69/12 -> 968.14083 | E19: =11617.69/12 -> 968.14083 | F19: =11617.69/12 -> 968.14083 | G19: =11617.69/12 -> 968.14083 | H19: =11617.69/12 -> 968.14083 | I19: =11617.69/12 -> 968.14083 | J19: =11617.69/12 -> 968.14083 | ... M19: =11617.69/12 -> 968.14083 | N19: =sum(B19:M19) -> 10649.549
A20: Software | B20: =94282/12 -> 7856.8333 | C20: =69207/12 -> 5767.25 | D20: =69207/12 -> 5767.25 | E20: =69207/12 -> 5767.25 | F20: =69207/12 -> 5767.25 | G20: =69207/12 -> 5767.25 | H20: =69207/12 -> 5767.25 | I20: =69207/12 -> 5767.25 | J20: =69207/12 -> 5767.25 | ... M20: =69207/12 -> 5767.25 | N20: =sum(B20:M20) -> 71296.583 | O20: =N20/$N$7 -> 0.052747215
A21: Staff Salary | B21: =305773.65+152922/12 -> 318517.15 | C21: =299019+152922/12 -> 311762.5 | D21: =304187+152922/12 -> 316930.5 | E21: =335691.48+152922/12 -> 348434.98 | F21: =345530+152922/12 -> 358273.5 | G21: =344192.03+152922/12 -> 356935.53 | H21: =152922/12+336973.03 -> 349716.53 | I21: =152922/12+330828.69 -> 343572.19 | J21: =152922/12+337918 -> 350661.5 | K21: =152922/12+344508 -> 357251.5 | L21: =152922/12+336105 -> 348848.5 | M21: =152922/12+325807 -> 338550.5 | N21: =sum(B21:M21) -> 4099454.9 | O21: =N21/$N$7 -> 3.0328919
A22: AMC | B22: =7670+2950 -> 10620 | C22: =5192+2950 -> 8142 | D22: =5192+2950 -> 8142 | E22: =2950+5192 -> 8142 | F22: =5192+2950 -> 8142 | G22: =5192+2950 -> 8142 | H22: =2950+5192 -> 8142 | I22: =4720+2950 -> 7670 | J22: =2950+4720 -> 7670 | K22: =4720+2950 -> 7670 | L22: =4720+2950 -> 7670 | M22: =4720+2950 -> 7670 | N22: =sum(B22:M22) -> 97822 | O22: =N22/$N$7 -> 0.072371463
A23: Subscription | B23: =2124/3+6425/12 -> 1243.4167 | C23: =2124/3+6425/12 -> 1243.4167 | D23: =2124/3+6425/12 -> 1243.4167 | E23: =2124/3+6425/12 -> 1243.4167 | F23: =2124/3+6425/12 -> 1243.4167 | G23: =2124/3+6425/12 -> 1243.4167 | H23: =2124/3+6425/12 -> 1243.4167 | I23: =2124/3+6425/12 -> 1243.4167 | J23: =2124/3+6425/12 -> 1243.4167 | K23: =6425/12+3304/3 -> 1636.75 | L23: =6425/12+3304/3 -> 1636.75 | M23: =6425/12+3304/3 -> 1636.75 | N23: =sum(B23:M23) -> 16101 | O23: =N23/$N$7 -> 0.011911972
A24: Repairs & Maintenance | B24: 2475 | C24: 5120 | D24: 3800 | E24: 0 | F24: 24576 | G24: =15390 -> 15390 | H24: 0 | I24: 5900 | J24: 10797 | K24: 5605 | L24: 13066 | M24: =1178.82 -> 1178.82 | N24: =sum(B24:M24) -> 87907.82 | O24: =N24/$N$7 -> 0.065036674
A25: Miscellaneous Expenses | B25: 6705 | C25: 16026.06 | D25: 8299.3 | E25: 5736.86 | F25: 27000 | G25: 15738.7 | H25: 10067 | I25: 11966.33 | J25: 16028 | K25: 13774 | L25: 20155.33 | M25: 20215 | N25: =sum(B25:M25) -> 171711.58 | O25: =N25/$N$7 -> 0.12703705
A26: CAM | N26: =sum(B26:M26) -> 0 | O26: =N26/$N$7 -> 0
A27: HO+CK Cost | B27: =HO!D37 -> 240379.55 | C27: =HO!H37 -> 288474.41 | D27: =HO!L37 -> 273112.78 | E27: =HO!P37 -> 272224.19 | F27: =HO!D50 -> 295570.47 | G27: =HO!H50 -> 240231.73 | H27: =HO!L50 -> 286672.69 | I27: =HO!P50 -> 270796.29 | J27: =HO!D64 -> 259536.26 | K27: =HO!H64 -> 275829 | L27: =HO!L64 -> 259094.64 | M27: =HO!P64 -> 310352.84 | N27: =sum(B27:M27) -> 3272274.8 | O27: =N27/$N$7 -> 2.4209208
A28: Operating Expenses | B28: =+SUM(B14:B27) -> 1260171.1 | C28: =+SUM(C14:C27) -> 1391954.4 | D28: =+SUM(D14:D27) -> 1446903 | E28: =+SUM(E14:E27) -> 1421915.9 | F28: =+SUM(F14:F27) -> 1508569.8 | G28: =+SUM(G14:G27) -> 1360070.7 | H28: =+SUM(H14:H27) -> 1380770.2 | I28: =+SUM(I14:I27) -> 1318876.6 | ... M28: =+SUM(M14:M27) -> 1564670.9 | N28: =sum(B28:M28) -> 16919636 | O28: =N28/$N$7 -> 12.517622
A29: Store Level EBITDA | B29: =B13-B28 -> 59896.26 | C29: =C13-C28 -> 243884.35 | D29: =D13-D28 -> 136117.67 | E29: =E13-E28 -> 129135.19 | F29: =F13-F28 -> 126951.99 | G29: =G13-G28 -> -25913.161 | H29: =H13-H28 -> 108871.73 | I29: =I13-I28 -> 198276.01 | ... M29: =M13-M28 -> 395241.32 | N29: =sum(B29:M29) -> 2037501.7 | O29: =N29/$N$7 -> 1.507401
A30: Food Cost | B30: =(B14/B13) -> 0.26109738 | C30: =(C14/C13) -> 0.24395258 | D30: =(D14/D13) -> 0.26342019 | E30: =(E14/E13) -> 0.27052207 | F30: =(F14/F13) -> 0.26549597 | G30: =(G14/G13) -> 0.28154145 | H30: =(H14/H13) -> 0.25486834 | I30: =(I14/I13) -> 0.23451588 | ... M30: =(M14/M13) -> 0.27006931
B32: =B29+B27 -> 300275.81 | C32: =C29+C27 -> 532358.76 | D32: =D29+D27 -> 409230.45 | E32: =E29+E27 -> 401359.39 | F32: =F29+F27 -> 422522.45 | G32: =G29+G27 -> 214318.56 | H32: =H29+H27 -> 395544.42 | I32: =I29+I27 -> 469072.3 | ... M32: =M29+M27 -> 705594.16
B33: =B32/B13 -> 0.22747007 | C33: =C32/C13 -> 0.32543475 | D33: =D32/D13 -> 0.25851239 | E33: =E32/E13 -> 0.25876607 | F33: =F32/F13 -> 0.25834107 | G33: =G32/G13 -> 0.16063962 | H33: =H32/H13 -> 0.26552988 | I33: =I32/I13 -> 0.30917939 | ... M33: =M32/M13 -> 0.36001314

Sheet Model Town
A1: Dosa Coffee - Model Town | B1: 45748 | C1: 45778 | D1: 45809 | E1: 45839 | F1: 45870 | G1: 45901 | H1: 45931 | I1: 45962 | J1: 45992 | K1: 46023 | L1: 46054 | M1: 46082 | N1: FY 2025-26
A2: Food Cost Calculation
A3: Opening Stock | B3: 68612 | C3: =B7 -> 87356 | D3: =C7 -> 111010 | E3: =D7 -> 145516 | F3: =E7 -> 167134 | G3: =F7 -> 144518.11 | H3: =G7 -> 162929.28 | I3: =H7 -> 147828.1 | J3: =I7 -> 153984.77 | ... M3: =L7 -> 97794 | N3: =+SUM(J3:L3) -> 480584.77
A4: Purchases Food (Less Purchase Return) | B4: 498950 | C4: 570167 | D4: 537453 | E4: 558784 | F4: 498624 | G4: 507366.83 | H4: 460970.25 | I4: =441928.22 -> 441928.22 | J4: =479784 -> 479784 | K4: 522700 | L4: 524706.25 | M4: 621646 | N4: =sum(B4:M4) -> 6223079.5
A5: Transferred Out | B5: 0 | C5: 0 | D5: 0 | E5: 0 | F5: 0 | G5: 0 | H5: 0 | I5: 0 | J5: 0 | K5: 0 | L5: 0 | M5: 0 | N5: =+SUM(J5:L5) -> 0
A6: Wastage & Date Expired | B6: 31479 | C6: 36240.45 | D6: 28976 | E6: 24275.71 | F6: 23605.32 | G6: 34052 | H6: 31282.54 | I6: 36313.84 | J6: 32339 | K6: 31022.68 | L6: 45842.15 | M6: 38741.71 | N6: =+SUM(J6:L6) -> 109203.83
A7: Closing Stock | B7: 87356 | C7: 111010 | D7: 145516 | E7: 167134 | F7: =144518.11 -> 144518.11 | G7: 162929.28 | H7: 147828.1 | I7: 153984.77 | J7: 186940 | K7: =139660 -> 139660 | L7: 97794 | M7: 80927.75 | N7: =sum(B7:M7) -> 1625598
A9: Gross Revenue | B9: =1841701.76*1.05+140*1.05+20906.41*1.05 -> 1955885.6 | C9: =2086060.37*1.05+31354.93*1.05+30*1.05 -> 2223317.6 | D9: =(1908092.47-224)*1.05+27994.35*1.05 -> 2032656 | E9: =1927927.62*1.05 -> 2024324 | F9: =1936762.7*1.05 -> 2033600.8 | G9: =1797391.81*1.05 -> 1887261.4 | H9: =1832244.94*1.05+10*1.05+26355.1*1.05 -> 1951540.5 | I9: =1750268.6*1.05+24161.17*1.05 -> 1863151.3 | J9: =1798229.52*1.05+25322.08*1.05 -> 1914729.2 | K9: =2183384.7*1.05+32157.92*1.05 -> 2326319.8 | L9: =2151769.36*1.05+33923.87*1.05 -> 2294977.9 | M9: =2622582.13*1.05+47854.81*1.05 -> 2803958.8 | N9: =+SUM(B9:M9) -> 25311723
A10: Catering & Fairs | B10: 0 | C10: 0 | N10: =+SUM(B10:M10) -> 0
A11: Less Tax | B11: =(B9+B10)/1.05*0.05 -> 93137.409 | C11: =(C9+C10)/1.05*0.05 -> 105872.26 | D11: =(D9+D10)/1.05*0.05 -> 96793.141 | E11: =(E9+E10)/1.05*0.05 -> 96396.381 | F11: =(F9+F10)/1.05*0.05 -> 96838.135 | G11: =(G9+G10)/1.05*0.05 -> 89869.591 | H11: =(H9+H10)/1.05*0.05 -> 92930.502 | I11: =(I9+I10)/1.05*0.05 -> 88721.489 | ... M11: =(M9+M10)/1.05*0.05 -> 133521.85 | N11: =+SUM(B11:M11) -> 1205320.1
A12: Less Commission | B12: =19349+3432.84+501.4+319.04+48044.23+1049.76+8647.96+188.96 -> 81533.19 | C12: =73447.5+13220.45+13685.62+2749.32+2464.55+494.88+268.02+178.07+80.29 -> 106588.7 | D12: =65601+11808.19+26647.8+4796+771+138.79+290.84*1.18 -> 110105.97 | E12: =30368.56+5465.79+60714.72+10928.65+129.01+273.94*1.18 -> 107929.98 | F12: =58210.35+10477.86+32594.49+5866.94+1989 -> 109138.64 | G12: =67375.4*1.18+28097.99*1.18+552.74*1.18 -> 113310.83 | H12: =62412.39*1.18+30922.24*1.18+1955.89*1.18 -> 112442.81 | I12: =(18116.15+57234.74)*1.18+2075.96*1.18+7701.55*1.18+1559.87*1.18 -> 102292.16 | J12: =60791.98*1.18+28285.82*1.18+3835.94*1.18 -> 109638.21 | K12: =76906.01*1.18+36452.84*1.18+3257.89*1.18 -> 137607.75 | L12: =31963.2*1.18+80767.44*1.18+3342.06*1.18 -> 136965.79 | M12: =40892.24*1.18+114351.58*1.18+4221.17*1.18 -> 188168.69 | N12: =+SUM(B12:M12) -> 1415722.7 | T12: =8749.04*0.18 -> 1574.8272
A13: Net Revenues from F&B Sales | B13: =B9+B10-B11-B12 -> 1781215 | C13: =C9+C10-C11-C12 -> 2010856.6 | D13: =D9+D10-D11-D12 -> 1825756.8 | E13: =E9+E10-E11-E12 -> 1819997.6 | F13: =F9+F10-F11-F12 -> 1827624.1 | G13: =G9+G10-G11-G12 -> 1684081 | H13: =H9+H10-H11-H12 -> 1746167.2 | I13: =I9+I10-I11-I12 -> 1672137.6 | ... M13: =M9+M10-M11-M12 -> 2482268.3 | N13: =sum(B13:M13) -> 22690680 | O13: =N13/$N$7 -> 13.958359
A14: F&B Cost | B14: =+B3+B4-B5-B7 -> 480206 | C14: =+C3+C4-C5-C7 -> 546513 | D14: =+D3+D4-D5-D7 -> 502947 | E14: =+E3+E4-E5-E7 -> 537166 | F14: =+F3+F4-F5-F7 -> 521239.89 | G14: =+G3+G4-G5-G7 -> 488955.66 | H14: =+H3+H4-H5-H7 -> 476071.43 | I14: =+I3+I4-I5-I7 -> 435771.55 | ... M14: =+M3+M4-M5-M7 -> 638512.25 | N14: =sum(B14:M14) -> 6210763.8 | O14: =N14/$N$7 -> 3.8206025
A15: Electricity | B15: 121130 | C15: 156150 | D15: 168900 | E15: 169880 | F15: 149710 | G15: 139570 | H15: 117890 | I15: =87060 -> 87060 | J15: 87850 | K15: 90370 | L15: 98500 | M15: 105000 | N15: =sum(B15:M15) -> 1492010 | O15: =N15/$N$7 -> 0.91782224
A16: Telephone/Internet | B16: 4230 | C16: =1246 -> 1246 | D16: =1246+222 -> 1468 | E16: 1468 | F16: =2400 -> 2400 | G16: =1330+518 -> 1848 | H16: =5310/3+300 -> 2070 | I16: =5310/3+300 -> 2070 | J16: =5310/3+219 -> 1989 | K16: =5310/3+219 -> 1989 | L16: =5310/3+219 -> 1989 | M16: =5310/3 -> 1770 | N16: =sum(B16:M16) -> 24537 | O16: =N16/$N$7 -> 0.015094138
A17: Gas | B17: =50461+52142 -> 102603 | C17: =93380 -> 93380 | D17: 87105 | E17: =30556+58645 -> 89201 | F17: =71342.68 -> 71342.68 | G17: 66119 | H17: 72429 | I17: 67063 | J17: 64354 | K17: 79413.33 | L17: 68035.53 | M17: 80000 | N17: =sum(B17:M17) -> 941045.54 | O17: =N17/$N$7 -> 0.57889191
A18: Rent & Revenue Share | B18: =472000 -> 472000 | C18: =472000 -> 472000 | D18: =472000 -> 472000 | E18: =472000 -> 472000 | F18: =472000 -> 472000 | G18: =472000 -> 472000 | H18: =472000 -> 472000 | I18: =472000 -> 472000 | ... M18: =472000 -> 472000 | N18: =sum(B18:M18) -> 5664000 | O18: =N18/$N$7 -> 3.4842562
A19: Insurance | B19: 0 | C19: =22306.73/12 -> 1858.8942 | D19: =22306.73/12 -> 1858.8942 | E19: =22306.73/12 -> 1858.8942 | F19: =22306.73/12 -> 1858.8942 | G19: =22306.73/12 -> 1858.8942 | H19: =22306.73/12 -> 1858.8942 | I19: =22306.73/12 -> 1858.8942 | J19: =22306.73/12 -> 1858.8942 | ... M19: =22306.73/12 -> 1858.8942 | N19: =sum(B19:M19) -> 20447.836 | O19: =N19/$N$7 -> 0.012578655
A20: Software | B20: =118354/12 -> 9862.8333 | C20: =118354/12 -> 9862.8333 | D20: =118354/12 -> 9862.8333 | E20: =118354/12 -> 9862.8333 | F20: =118354/12 -> 9862.8333 | G20: =118354/12 -> 9862.8333 | H20: =87621/12 -> 7301.75 | I20: =87621/12 -> 7301.75 | J20: =87621/12 -> 7301.75 | K20: =87621/12 -> 7301.75 | L20: =87621/12 -> 7301.75 | M20: =87621/12 -> 7301.75 | N20: =sum(B20:M20) -> 102987.5 | O20: =N20/$N$7 -> 0.063353609
A21: Staff Salary | B21: =361768.33+92091/12 -> 369442.58 | C21: =351012.15+92091/12 -> 358686.4 | D21: =411550+92091/12 -> 419224.25 | E21: =405480+92091/12 -> 413154.25 | F21: =384197+92091/12 -> 391871.25 | G21: =414738+92091/12 -> 422412.25 | H21: =92091/12+399164 -> 406838.25 | I21: =92091/12+7000+428285.67 -> 442959.92 | J21: =92091/12+410722+7000 -> 425396.25 | K21: =92091/12+7000+421758 -> 436432.25 | L21: =92091/12+387138+7000 -> 401812.25 | M21: =92091/12+7000+368937 -> 383611.25 | N21: =sum(B21:M21) -> 4871841.2 | O21: =N21/$N$7 -> 2.9969532
A22: AMC | B22: 10455 | C22: =5192+5145 -> 10337 | D22: =11210/12+5192+5145 -> 11271.167 | E22: =11210/12+5145+5192 -> 11271.167 | F22: =11210/12+5192+5145 -> 11271.167 | G22: =11210/12+5192+5145 -> 11271.167 | H22: =11210/12+5145+5192 -> 11271.167 | I22: =11210/12+4720+5145 -> 10799.167 | J22: =11210/12+5145+4720 -> 10799.167 | K22: =11210/12+4720+5145 -> 10799.167 | L22: =11210/12+4720+5145 -> 10799.167 | M22: =11210/12+4720+5145 -> 10799.167 | N22: =sum(B22:M22) -> 131143.67 | O22: =N22/$N$7 -> 0.080674106
A23: Subscription | B23: =2124/3 -> 708 | C23: =2124/3 -> 708 | D23: =2124/3 -> 708 | E23: =2124/3 -> 708 | F23: =2124/3 -> 708 | G23: =2124/3 -> 708 | H23: =2124/3 -> 708 | I23: =2124/3 -> 708 | J23: =2124/3 -> 708 | K23: =3304/3 -> 1101.3333 | L23: =3304/3 -> 1101.3333 | M23: =3304/3 -> 1101.3333 | N23: =sum(B23:M23) -> 9676 | O23: =N23/$N$7 -> 0.0059522711
A24: Repairs & Maintenance | B24: 3835 | C24: 1450 | D24: 2617 | E24: 0 | F24: 14602 | G24: =15242 -> 15242 | H24: 10232 | I24: 13806 | J24: 200 | K24: 12154 | L24: =4602 -> 4602 | M24: 0 | N24: =sum(B24:M24) -> 78740 | O24: =N24/$N$7 -> 0.048437559
A25: Miscellaneous Expenses | B25: 8612.56 | C25: 6587.6 | D25: 10172.81 | E25: 5596.44 | F25: 19430 | G25: =18871.4 -> 18871.4 | H25: 9358 | I25: 21597.6 | J25: 14775.51 | K25: 13260.5 | L25: 12589.3 | M25: 13882.44 | N25: =sum(B25:M25) -> 154734.16 | O25: =N25/$N$7 -> 0.095185993
A26: CAM | N26: =sum(B26:M26) -> 0 | O26: =N26/$N$7 -> 0
A27: HO+CK Cost | B27: =HO!D38 -> 324352.89 | C27: =HO!H38 -> 354607.5 | D27: =HO!L38 -> 314991.17 | E27: =HO!P38 -> 319426.87 | F27: =HO!D51 -> 330287.07 | G27: =HO!H51 -> 303239.81 | H27: =HO!L51 -> 336039.46 | I27: =HO!P51 -> 298459.54 | J27: =HO!D65 -> 303439.99 | K27: =HO!H65 -> 319295.12 | L27: =HO!L65 -> 317895.05 | M27: =HO!P65 -> 393068.11 | N27: =sum(B27:M27) -> 3915102.6 | O27: =N27/$N$7 -> 2.4084076
A28: Operating Expenses | B28: =+SUM(B14:B27) -> 1907437.9 | C28: =+SUM(C14:C27) -> 2013387.2 | D28: =+SUM(D14:D27) -> 2003126.1 | E28: =+SUM(E14:E27) -> 2031593.5 | F28: =+SUM(F14:F27) -> 1996583.8 | G28: =+SUM(G14:G27) -> 1951959 | H28: =+SUM(H14:H27) -> 1924068 | I28: =+SUM(I14:I27) -> 1861455.4 | ... M28: =+SUM(M14:M27) -> 2108905.2 | N28: =sum(B28:M28) -> 23617029 | O28: =N28/$N$7 -> 14.52821
A29: Store Level EBITDA | B29: =B13-B28 -> -126222.88 | C29: =C13-C28 -> -2530.628 | D29: =D13-D28 -> -177369.27 | E29: =E13-E28 -> -211595.82 | F29: =F13-F28 -> -168959.73 | G29: =G13-G28 -> -267878.04 | H29: =H13-H28 -> -177900.73 | I29: =I13-I28 -> -189317.81 | ... M29: =M13-M28 -> 373363.06 | N29: =sum(B29:M29) -> -926349.35 | O29: =N29/$N$7 -> -0.56985143
A30: Food Cost | B30: =(B14/B13) -> 0.26959463 | C30: =(C14/C13) -> 0.27178119 | D30: =(D14/D13) -> 0.27547316 | E30: =(E14/E13) -> 0.29514654 | F30: =(F14/F13) -> 0.28520083 | G30: =(G14/G13) -> 0.29033976 | H30: =(H14/H13) -> 0.27263794 | I30: =(I14/I13) -> 0.26060747 | ... M30: =(M14/M13) -> 0.25722935
B32: =B29+B27 -> 198130.01 | C32: =C29+C27 -> 352076.87 | D32: =D29+D27 -> 137621.89 | E32: =E29+E27 -> 107831.06 | F32: =F29+F27 -> 161327.35 | G32: =G29+G27 -> 35361.772 | H32: =H29+H27 -> 158138.74 | I32: =I29+I27 -> 109141.73 | ... M32: =M29+M27 -> 766431.17
B33: =B32/B13 -> 0.11123307 | C33: =C32/C13 -> 0.17508801 | D33: =D32/D13 -> 0.075377997 | E33: =E32/E13 -> 0.05924791 | F33: =F32/F13 -> 0.088271625 | G33: =G32/G13 -> 0.020997668 | H33: =H32/H13 -> 0.09056334 | I33: =I32/I13 -> 0.065270783 | ... M33: =M32/M13 -> 0.30876243

Sheet Pacific Mall
A1: Dosa Coffee - Pacific Mall | B1: 45748 | C1: 45778 | D1: 45809 | E1: 45839 | F1: 45870 | G1: 45901 | H1: 45931 | I1: 45962 | J1: 45992 | K1: 46023 | L1: 46054 | M1: 46082 | N1: FY 2025-26
A2: Food Cost Calculation
A3: Opening Stock | B3: 39372.36 | C3: =B7 -> 30806 | D3: =C7 -> 32330.4 | E3: =D7 -> 27772.98 | F3: =E7 -> 37150 | G3: =F7 -> 40504.92 | H3: =G7 -> 34431 | I3: =H7 -> 35812.43 | J3: =I7 -> 30939.03 | ... M3: =L7 -> 25626.77 | N3: =+SUM(J3:L3) -> 93205.54
A4: Purchases Food (Less Purchase Return) | B4: 361024 | C4: 364288.95 | D4: 370711.93 | E4: 444258 | F4: 397187 | G4: 312095 | H4: 353291.84 | I4: 346673.11 | J4: 395628 | K4: 420156.65 | L4: 352463.98 | M4: 448119.91 | N4: =sum(B4:M4) -> 4565898.4
A5: Transferred Out | B5: 0 | C5: 1724.83 | D5: 0 | E5: 0 | F5: 0 | G5: 0 | H5: 0 | I5: 0 | J5: 0 | K5: 0 | L5: 0 | M5: 0 | N5: =+SUM(J5:L5) -> 0
A6: Wastage & Date Expired | B6: 22587 | C6: 24175.49 | D6: 21349 | E6: 25562 | F6: 28989 | G6: 27044 | H6: 28407 | I6: 25968 | J6: 26215 | K6: 24450.75 | L6: 19524.64 | M6: 19830.83 | N6: =+SUM(J6:L6) -> 70190.39
A7: Closing Stock | B7: 30806 | C7: 32330.4 | D7: 27772.98 | E7: 37150 | F7: 40504.92 | G7: 34431 | H7: 35812.43 | I7: 30939.03 | J7: 32629 | K7: 29637.51 | L7: 25626.77 | M7: 21771.51 | N7: =sum(B7:M7) -> 379411.55
A9: Gross Revenue | B9: =1606370.56*1.05 -> 1686689.1 | C9: =1771104.2*1.05+13222.49*1.05 -> 1873543 | D9: =(1818571.5-134.88)*1.05+13513.97*1.05 -> 1923548.1 | E9: =1925917.21*1.05 -> 2022213.1 | F9: =1933835.07*1.05 -> 2030526.8 | G9: =1626442*1.05+11416*1.05 -> 1719750.9 | H9: =1550288.4*1.05+10177.83*1.05 -> 1638489.5 | I9: =1502280.44*1.05+10622.84*1.05 -> 1588548.4 | J9: =1675562.22*1.05+7656.14*1.05 -> 1767379.3 | K9: =1732893.52*1.05+10858.77*1.05 -> 1830939.9 | L9: =1360755.81*1.05+10691.87*1.05 -> 1440020.1 | M9: =1926907.75*1.05+13170.61*1.05 -> 2037082.3 | N9: =+SUM(B9:M9) -> 21558731
A10: Catering & Fairs | B10: 0 | C10: 0 | N10: =+SUM(B10:M10) -> 0
A11: Less Tax | B11: =(B9+B10)/1.05*0.05 -> 80318.528 | C11: =(C9+C10)/1.05*0.05 -> 89216.334 | D11: =(D9+D10)/1.05*0.05 -> 91597.53 | E11: =(E9+E10)/1.05*0.05 -> 96295.86 | F11: =(F9+F10)/1.05*0.05 -> 96691.754 | G11: =(G9+G10)/1.05*0.05 -> 81892.9 | H11: =(H9+H10)/1.05*0.05 -> 78023.311 | I11: =(I9+I10)/1.05*0.05 -> 75645.164 | ... M11: =(M9+M10)/1.05*0.05 -> 97003.918 | N11: =+SUM(B11:M11) -> 1026606.2
A12: Less Commission | B12: =12267.67+2208.17+1271.04+31391.55+519.21+5650.48+93.46 -> 53401.58 | C12: =31538.87+5677+7572.58+1168.6+1363.07+210.35+1960.42+352.88 -> 49843.77 | D12: =31994.99+5759+12602.08+2268.32+2378.18+428 -> 55430.57 | E12: =18198+3275.92+32022.81+5764.1+826.46*1.18 -> 60236.053 | F12: =26992.23+4858.6+16307.42+2935.35+1989 -> 53082.6 | G12: =27212.62*1.18+10127.31*1.18+580.04*1.18 -> 44745.565 | H12: =24246.04*1.18+14249.05*1.18+2544.59*1.18 -> 48426.822 | I12: =(9940.06+26049)*1.18+929.95*1.18+3557.4*1.18+1474.79*1.18 -> 49502.416 | J12: =20445.53*1.18+12889.12*1.18+4177.61*1.18 -> 44264.467 | K12: =27375.71*1.18+18913.4*1.18+2738.5*1.18 -> 57852.58 | L12: =15375.4*1.18+26562.74*1.18+1654.54*1.18 -> 51439.362 | M12: =26948.89*1.18+32705.63*1.18+4094.7*1.18 -> 75224.08 | N12: =+SUM(B12:M12) -> 643449.86
A13: Net Revenues from F&B Sales | B13: =B9+B10-B11-B12 -> 1552969 | C13: =C9+C10-C11-C12 -> 1734482.9 | D13: =D9+D10-D11-D12 -> 1776520 | E13: =E9+E10-E11-E12 -> 1865681.2 | F13: =F9+F10-F11-F12 -> 1880752.5 | G13: =G9+G10-G11-G12 -> 1593112.4 | H13: =H9+H10-H11-H12 -> 1512039.4 | I13: =I9+I10-I11-I12 -> 1463400.9 | ... M13: =M9+M10-M11-M12 -> 1864854.3 | N13: =sum(B13:M13) -> 19888674 | O13: =N13/$N$7 -> 52.419792
A14: F&B Cost | B14: =+B3+B4-B5-B7 -> 369590.36 | C14: =+C3+C4-C5-C7 -> 361039.72 | D14: =+D3+D4-D5-D7 -> 375269.35 | E14: =+E3+E4-E5-E7 -> 434880.98 | F14: =+F3+F4-F5-F7 -> 393832.08 | G14: =+G3+G4-G5-G7 -> 318168.92 | H14: =+H3+H4-H5-H7 -> 351910.41 | I14: =+I3+I4-I5-I7 -> 351546.51 | ... M14: =+M3+M4-M5-M7 -> 451975.17 | N14: =sum(B14:M14) -> 4581774.4 | O14: =N14/$N$13 -> 0.23037103
A15: Electricity | B15: =77882 -> 77882 | C15: 76146 | D15: =75983+9564 -> 85547 | E15: =76044+7383 -> 83427 | F15: =68289+12066 -> 80355 | G15: =64779.64+12298.44 -> 77078.08 | H15: =63674+8815 -> 72489 | I15: =57518+9657 -> 67175 | J15: =52433+10055 -> 62488 | K15: =63555+10421.76 -> 73976.76 | L15: =60616+9947.88 -> 70563.88 | M15: =+9356.92+61000 -> 70356.92 | N15: =sum(B15:M15) -> 897484.64 | O15: =N15/$N$13 -> 0.045125413
A16: Telephone/Internet | C16: 324 | F16: 1885 | G16: =2120/2 -> 1060 | H16: =2120/2 -> 1060 | I16: 1060 | J16: 942 | K16: =473+2442/3 -> 1287 | L16: =2442/3+203 -> 1017 | M16: =2442/3+203 -> 1017 | N16: =sum(B16:M16) -> 9652 | O16: =N16/$N$13 -> 0.00048530132
A17: Gas | B17: =106326.86+11239.26 -> 117566.12 | C17: 109658.72 | D17: 114915 | E17: 125387 | F17: 122011.7 | G17: =109713.94+1910 -> 111623.94 | H17: 108659 | I17: 115000 | J17: =117102.84 -> 117102.84 | K17: 123522 | L17: =106132 -> 106132 | M17: 146255 | N17: =sum(B17:M17) -> 1417833.3 | O17: =N17/$N$13 -> 0.071288477
A18: Rent & Revenue Share | B18: =326539.52+65796 -> 392335.52 | C18: =326539.52+14857.35+50939.45 -> 392336.32 | D18: =326539.52+65796 -> 392335.52 | E18: =326539+65796 -> 392335 | F18: =326539.52+14857.35+50939.45 -> 392336.32 | G18: =326539.52+65796 -> 392335.52 | H18: =65797+326539 -> 392336 | I18: =326539.52+50444.21+15352.59 -> 392336.32 | J18: =65796.8+326539.52 -> 392336.32 | K18: =326539.52+14857.35+50939.45 -> 392336.32 | L18: =326539.52+65796.8 -> 392336.32 | M18: =326539.52+65796.8 -> 392336.32 | N18: =sum(B18:M18) -> 4708031.8 | O18: =N18/$N$13 -> 0.23671923
A19: Insurance | B19: 0 | C19: 0 | D19: 0 | E19: 0 | F19: 0 | G19: 0 | H19: 0 | I19: 0 | J19: =13085/12+2006/12 -> 1257.5833 | K19: =13085/12+2006/12 -> 1257.5833 | L19: =13085/12+2006/12 -> 1257.5833 | M19: =13085/12+2006/12 -> 1257.5833 | N19: =sum(B19:M19) -> 5030.3333 | O19: =N19/$N$13 -> 0.00025292451
A20: Software | B20: =94282/12 -> 7856.8333 | C20: =94282/12 -> 7856.8333 | D20: =94282/12 -> 7856.8333 | E20: =94282/12 -> 7856.8333 | F20: =94282/12 -> 7856.8333 | G20: =69207/12 -> 5767.25 | H20: =69207/12 -> 5767.25 | I20: =69207/12 -> 5767.25 | J20: =69207/12 -> 5767.25 | K20: =69207/12 -> 5767.25 | L20: =69207/12 -> 5767.25 | M20: =69207/12 -> 5767.25 | N20: =sum(B20:M20) -> 79654.917 | O20: =N20/$N$13 -> 0.004005039
A21: Staff Salary | B21: =3250+271699.35+1500+116646/12 -> 286169.85 | C21: =292595+3250+116646/12 -> 305565.5 | D21: =304412+116646/12 -> 314132.5 | E21: =283128+116646/12 -> 292848.5 | F21: =304206+5000+3250+116646/12 -> 322176.5 | G21: =282711+5000+116646/12 -> 297431.5 | H21: =116646/12+282867+5000 -> 297587.5 | I21: =116646/12+5000+274482 -> 289202.5 | J21: =116646/12+313050+5000 -> 327770.5 | K21: =116646/12+5000+303534 -> 318254.5 | L21: =116646/12+266628 -> 276348.5 | M21: =116646/12+10000+269591 -> 289311.5 | N21: =sum(B21:M21) -> 3616799.4 | O21: =N21/$N$13 -> 0.18185221
A22: AMC | B22: =4720 -> 4720 | C22: =4720 -> 4720 | D22: =5192 -> 5192 | E22: 5192 | F22: =5192+2950 -> 8142 | G22: =5192+2950 -> 8142 | H22: =2950+5192 -> 8142 | I22: =4720+2950 -> 7670 | J22: =2950+4720 -> 7670 | K22: =4720+2950 -> 7670 | L22: =4720+2950 -> 7670 | M22: =4720+2950 -> 7670 | N22: =sum(B22:M22) -> 82600 | O22: =N22/$N$13 -> 0.0041531174
A23: Subscription | B23: =2124/3 -> 708 | C23: =2124/3 -> 708 | D23: =2124/3 -> 708 | E23: =2124/3 -> 708 | F23: =2124/3 -> 708 | G23: =2124/3 -> 708 | H23: =2124/3 -> 708 | I23: =2124/3 -> 708 | J23: =2124/3 -> 708 | K23: =3304/3 -> 1101.3333 | L23: =3304/3 -> 1101.3333 | M23: =3304/3 -> 1101.3333 | N23: =sum(B23:M23) -> 9676 | O23: =N23/$N$13 -> 0.00048650804
A24: Repairs & Maintenance | B24: 388 | C24: 450 | D24: 1350 | E24: 0 | F24: 5930 | G24: 450 | H24: 8546 | I24: 8791 | J24: 0 | K24: 0 | L24: =6490 -> 6490 | M24: 4520 | N24: =sum(B24:M24) -> 36915 | O24: =N24/$N$13 -> 0.0018560815
A25: Miscellaneous Expenses | B25: 8672.82 | C25: 6820.51 | D25: =17236-9564 -> 7672 | E25: 4093.14 | F25: =21278 -> 21278 | G25: 18944 | H25: 12987 | I25: 17315.86 | J25: 18127 | K25: 10421 | L25: 11229.32 | M25: 10835 | N25: =sum(B25:M25) -> 148395.65 | O25: =N25/$N$13 -> 0.0074613142
A26: CAM | B26: 150861 | C26: 150861 | D26: 150861 | E26: 150861 | F26: 150861 | G26: 150861 | H26: 150861 | I26: 150861 | J26: 150861 | K26: 150861 | L26: 150861 | M26: 159903.89 | N26: =sum(B26:M26) -> 1819374.9 | O26: =N26/$N$13 -> 0.091477936
A27: HO+CK Cost | B27: =HO!D39 -> 282790.11 | C27: =HO!H39 -> 305869.97 | D27: =HO!L39 -> 306496.52 | E27: =HO!P39 -> 327444.76 | F27: =HO!D52 -> 339888.4 | G27: =HO!H52 -> 286859.79 | H27: =HO!L52 -> 290982.96 | I27: =HO!P52 -> 261202.16 | J27: =HO!D66 -> 290168.78 | K27: =HO!H66 -> 259055.07 | L27: =HO!L66 -> 204821.83 | M27: =HO!P66 -> 295300.37 | N27: =sum(B27:M27) -> 3450880.7 | O27: =N27/$N$13 -> 0.17350984
A28: Operating Expenses | B28: =+SUM(B14:B27) -> 1699540.6 | C28: =+SUM(C14:C27) -> 1722356.6 | D28: =+SUM(D14:D27) -> 1762335.7 | E28: =+SUM(E14:E27) -> 1825034.2 | F28: =+SUM(F14:F27) -> 1847260.8 | G28: =+SUM(G14:G27) -> 1669430 | H28: =+SUM(H14:H27) -> 1702036.1 | I28: =+SUM(I14:I27) -> 1668635.6 | ... M28: =+SUM(M14:M27) -> 1837607.3 | N28: =sum(B28:M28) -> 20864103 | O28: =N28/$N$13 -> 1.0490444
A29: Store Level EBITDA | B29: =B13-B28 -> -146571.63 | C29: =C13-C28 -> 12126.344 | D29: =D13-D28 -> 14184.298 | E29: =E13-E28 -> 40646.94 | F29: =F13-F28 -> 33491.633 | G29: =G13-G28 -> -76317.564 | H29: =H13-H28 -> -189996.71 | I29: =I13-I28 -> -205234.73 | ... M29: =M13-M28 -> 27246.941 | N29: =sum(B29:M29) -> -975428.56 | O29: =N29/$N$13 -> -0.049044423
A30: Food Cost | B30: =(B14/B13) -> 0.23798953 | C30: =(C14/C13) -> 0.20815409 | D30: =(D14/D13) -> 0.21123846 | E30: =(E14/E13) -> 0.23309502 | F30: =(F14/F13) -> 0.20940134 | G30: =(G14/G13) -> 0.19971529 | H30: =(H14/H13) -> 0.23273891 | I30: =(I14/I13) -> 0.24022571 | ... M30: =(M14/M13) -> 0.24236487
B32: =B29+B27 -> 136218.48 | C32: =C29+C27 -> 317996.32 | D32: =D29+D27 -> 320680.82 | E32: =E29+E27 -> 368091.7 | F32: =F29+F27 -> 373380.04 | G32: =G29+G27 -> 210542.23 | H32: =H29+H27 -> 100986.25 | I32: =I29+I27 -> 55967.424 | ... M32: =M29+M27 -> 322547.31
B33: =B32/B13 -> 0.087714873 | C33: =C32/C13 -> 0.18333782 | D33: =D32/D13 -> 0.18051067 | E33: =E32/E13 -> 0.19729615 | F33: =F32/F13 -> 0.19852694 | G33: =G32/G13 -> 0.13215779 | H33: =H32/H13 -> 0.066788106 | I33: =I32/I13 -> 0.038244766 | ... M33: =M32/M13 -> 0.17296114

Sheet Shalimar Bagh
A1: Dosa Coffee - Shalimar Bagh | B1: 45748 | C1: 45778 | D1: 45809 | E1: 45839 | F1: 45870 | G1: 45901 | H1: 45931 | I1: 45962 | J1: 45992 | K1: 46023 | L1: 46054 | M1: 46082 | N1: FY 2025-26
A2: Food Cost Calculation
A3: Opening Stock | M3: 0 | N3: =+SUM(J3:L3) -> 0
A4: Purchases Food (Less Purchase Return) | M4: 102302.79 | N4: =sum(B4:M4) -> 102302.79
A5: Transferred Out | M5: 0 | N5: =+SUM(J5:L5) -> 0
A6: Wastage & Date Expired | M6: 14352 | N6: =+SUM(J6:L6) -> 0
A7: Closing Stock | M7: 32637.96 | N7: =sum(B7:M7) -> 32637.96
A9: Gross Revenue | M9: =75660.1*1.05 -> 79443.105 | N9: =+SUM(B9:M9) -> 79443.105
A10: Catering & Fairs | M10: 0 | N10: =+SUM(B10:M10) -> 0
A11: Less Tax | M11: =(M9+M10)/1.05*0.05 -> 3783.005 | N11: =+SUM(B11:M11) -> 3783.005
A12: Less Commission | M12: 0 | N12: =+SUM(B12:M12) -> 0
A13: Net Revenues from F&B Sales | B13: =B9+B10-B11-B12 -> 0 | C13: =C9+C10-C11-C12 -> 0 | D13: =D9+D10-D11-D12 -> 0 | E13: =E9+E10-E11-E12 -> 0 | F13: =F9+F10-F11-F12 -> 0 | G13: =G9+G10-G11-G12 -> 0 | H13: =H9+H10-H11-H12 -> 0 | I13: =I9+I10-I11-I12 -> 0 | ... M13: =M9+M10-M11-M12 -> 75660.1 | N13: =sum(B13:M13) -> 75660.1 | O13: =N13/$N$7 -> 2.3181627
A14: F&B Cost | M14: =+M3+M4-M5-M7 -> 69664.83 | N14: =sum(B14:M14) -> 69664.83 | O14: =N14/$N$13 -> 0.92076048
A15: Electricity | N15: =sum(B15:M15) -> 0 | O15: =N15/$N$13 -> 0
A16: Telephone/Internet | N16: =sum(B16:M16) -> 0 | O16: =N16/$N$13 -> 0
A17: Gas | N17: =sum(B17:M17) -> 0 | O17: =N17/$N$13 -> 0
A18: Rent & Revenue Share | M18: =45677 -> 45677 | N18: =sum(B18:M18) -> 45677 | O18: =N18/$N$13 -> 0.60371319
A19: Insurance | N19: =sum(B19:M19) -> 0 | O19: =N19/$N$13 -> 0
A20: Software | N20: =sum(B20:M20) -> 0 | O20: =N20/$N$13 -> 0
A21: Staff Salary | M21: =220354/31*4 -> 28432.774 | N21: =sum(B21:M21) -> 28432.774 | O21: =N21/$N$13 -> 0.37579615
A22: AMC | N22: =sum(B22:M22) -> 0 | O22: =N22/$N$13 -> 0
A23: Subscription | N23: =sum(B23:M23) -> 0 | O23: =N23/$N$13 -> 0
A24: Repairs & Maintenance | N24: =sum(B24:M24) -> 0 | O24: =N24/$N$13 -> 0
A25: Miscellaneous Expenses | N25: =sum(B25:M25) -> 0 | O25: =N25/$N$13 -> 0
A26: CAM | N26: =sum(B26:M26) -> 0 | O26: =N26/$N$13 -> 0
A27: HO+CK Cost | M27: =HO!P67 -> 11980.805 | N27: =sum(B27:M27) -> 11980.805 | O27: =N27/$N$13 -> 0.15835037
A28: Operating Expenses | B28: =+SUM(B14:B27) -> 0 | C28: =+SUM(C14:C27) -> 0 | D28: =+SUM(D14:D27) -> 0 | E28: =+SUM(E14:E27) -> 0 | F28: =+SUM(F14:F27) -> 0 | G28: =+SUM(G14:G27) -> 0 | H28: =+SUM(H14:H27) -> 0 | I28: =+SUM(I14:I27) -> 0 | ... M28: =+SUM(M14:M27) -> 155755.41 | N28: =sum(B28:M28) -> 155755.41 | O28: =N28/$N$13 -> 2.0586202
A29: Store Level EBITDA | B29: =B13-B28 -> 0 | C29: =C13-C28 -> 0 | D29: =D13-D28 -> 0 | E29: =E13-E28 -> 0 | F29: =F13-F28 -> 0 | G29: =G13-G28 -> 0 | H29: =H13-H28 -> 0 | I29: =I13-I28 -> 0 | ... M29: =M13-M28 -> -80095.309 | N29: =sum(B29:M29) -> -80095.309 | O29: =N29/$N$13 -> -1.0586202
A30: Food Cost | B30: =(B14/B13) -> #DIV/0! | C30: =(C14/C13) -> #DIV/0! | D30: =(D14/D13) -> #DIV/0! | E30: =(E14/E13) -> #DIV/0! | F30: =(F14/F13) -> #DIV/0! | G30: =(G14/G13) -> #DIV/0! | H30: =(H14/H13) -> #DIV/0! | I30: =(I14/I13) -> #DIV/0! | ... M30: =(M14/M13) -> 0.92076048
B32: =B29+B27 -> 0 | C32: =C29+C27 -> 0 | D32: =D29+D27 -> 0 | E32: =E29+E27 -> 0 | F32: =F29+F27 -> 0 | G32: =G29+G27 -> 0 | H32: =H29+H27 -> 0 | I32: =I29+I27 -> 0 | ... L32: =L29+L27 -> 0
B33: =B32/B13 -> #DIV/0! | C33: =C32/C13 -> #DIV/0! | D33: =D32/D13 -> #DIV/0! | E33: =E32/E13 -> #DIV/0! | F33: =F32/F13 -> #DIV/0! | G33: =G32/G13 -> #DIV/0! | H33: =H32/H13 -> #DIV/0! | I33: =I32/I13 -> #DIV/0! | ... L33: =L32/L13 -> #DIV/0!

Sheet Ads Account
A1: Dosa Coffee - NCR | B1: 45770 | C1: 45800 | D1: 45831 | E1: 45861 | F1: 45900 | G1: 45925 | H1: 45953 | I1: 45984 | J1: 46014 | K1: 46046 | L1: 46077 | M1: 46105 | N1: FY 25-26
A2: Advertisement & Promotion | N2: =+SUM(B2:M2) -> 0
A3: Others | B3: =6644+35000/3 -> 18310.667 | C3: =77492/3 -> 25830.667 | D3: =35000/3+10000 -> 21666.667 | E3: =3540+25000+19829+184881.6 -> 233250.6 | F3: =31513+34567+26000 -> 92080 | G3: 0 | H3: 30150 | I3: =134560+35000 -> 169560 | J3: =8500+18050+149652 -> 176202 | K3: =10000+179300 -> 189300 | L3: =269246+177000 -> 446246 | M3: =16000+20025+329156-177000-14160 -> 174021
A4: Zomato | B4: 469670 | C4: =71493.84+47195+208650.55 -> 327339.39 | D4: =65856+53305+134495 -> 253656 | E4: =53509+21877+151328 -> 226714 | F4: =49234.31+73015.06+128980.32 -> 251229.69 | G4: =48013.93+68747+131764.64 -> 248525.57 | H4: =49103.24+64893.93*1.18+91395*1.18 -> 233524.18 | I4: =83703.93+69599.95+49697.31 -> 203001.19 | J4: =19832*1.18+61548+11078.64+78247+14084 -> 188359.4 | K4: =42038.73+73952.4+13311.43+77934.14 -> 207236.7 | L4: =46087*1.18+93225.63*1.18+85096.35*1.18 -> 264802.6 | M4: =58196.44*1.18+113445.14*1.18+117805.31*1.18 -> 341547.33
A5: Swiggy | B5: 285746 | C5: =79437.5+76361+123625 -> 279423.5 | D5: =48786.6+21253+8781+3874+83360.39+10504.88+103775.8+18677 -> 299012.67 | E5: =17350+3123+3753+675+53135+9564.3 -> 87600.3 | F5: =48619+5062.92+80527+14224.87+112014+64798 -> 325245.79 | G5: =24920+7412+4485.61+1334.16+36230+10285+6526.99+1851.3+50508+16836+9091.45+3030.48 -> 172510.99 | H5: =42206*1.18+50723*1.18+97913*1.18 -> 225193.56 | I5: =31858+5734.46+28962.5+5213+15765.58+6399.14+8623.44+19256.5+3466 -> 125278.62 | J5: =54678+9842+48979+8816+82560+14860 -> 219735 | K5: =29289.94*1.05+12839.17+45538.78+6369.99+59090.66+21397+14487.89 -> 190477.93 | L5: =20215*1.18+18131.9*1.18+44940.78*1.18 -> 98279.462 | M5: =32513.04*1.18+43386.97*1.18+90310.2*1.18 -> 196128.05
A6: Total | B6: =sum(B3:B5) -> 773726.67 | C6: =sum(C3:C5) -> 632593.56 | D6: =sum(D3:D5) -> 574335.34 | E6: =sum(E3:E5) -> 547564.9 | F6: =sum(F3:F5) -> 668555.48 | G6: =sum(G3:G5) -> 421036.56 | H6: =sum(H3:H5) -> 488867.74 | I6: =sum(I3:I5) -> 497839.81 | ... M6: =sum(M3:M5) -> 711696.38

Sheet Misc Expenses
B1: Paschim Vihar | C1: Okhla | D1: Rohini | E1: Kalkaji | F1: Pacific Mall | G1: CP | H1: Model Town | I1: Faridabad | J1: DLF | K1: Huda Market | L1: Noida Sec 18 | M1: Noida Sec 143 | N1: Head office | O1: Total
A2: Actual
A3: Travelling Expenses | B3: 0 | C3: 0 | D3: 0 | E3: 0 | F3: 0 | G3: 0 | H3: 0 | I3: 8136 | J3: 491 | K3: 5181 | L3: 0 | M3: 0 | N3: 0 | O3: =sum(B3:N3) -> 13808
A4: Motor car Expenses | B4: 0 | C4: 0 | D4: 0 | E4: 0 | F4: 0 | G4: 0 | H4: 0 | I4: 0 | J4: 0 | K4: 0 | L4: 0 | M4: 0 | N4: 0 | O4: =sum(B4:N4) -> 0
A5: Freight Charges | C5: 12634 | E5: 682 | F5: 367 | N5: 160 | O5: =sum(B5:N5) -> 13843
A6: Professional Fees | K6: 21240 | L6: 21240 | O6: =sum(B6:N6) -> 42480
A7: Parking Expenses | C7: 22750 | F7: 3150 | O7: =sum(B7:N7) -> 25900
A8: Merchant Funded Promotion | I8: 713.68 | J8: 302.4 | K8: 1029.13 | L8: 2195.37 | M8: 1907.67 | O8: =sum(B8:N8) -> 6148.25
A9: Customer Compensation | I9: 1080.71 | J9: 1715.6 | K9: 2816 | L9: 1238 | M9: 1271 | O9: =sum(B9:N9) -> 8121.31
A10: Round Up | N10: 527.23 | O10: =sum(B10:N10) -> 527.23
A11: Staff Welfare | I11: 1400 | J11: 2950 | K11: 1400 | L11: 4455 | M11: 1000 | O11: =sum(B11:N11) -> 11205
A12: Maintenance Expenses | B12: 4562 | C12: 4562 | D12: 4562 | E12: 4562 | F12: 4562 | G12: 4562 | H12: 4562 | O12: =sum(B12:N12) -> 31934
A13: Staff Electricity | K13: 800 | O13: =sum(B13:N13) -> 800
A14: DG Charges | L14: 1900 | O14: =sum(B14:N14) -> 1900
A15: Local Authority Expenses | B15: 5000 | C15: 700 | D15: 3000 | E15: 3000 | G15: 5000 | H15: 4000 | L15: 4000 | O15: =sum(B15:N15) -> 24700
A16: Travelling Expense | B16: 95 | C16: 2367 | D16: 7770 | E16: 9400 | F16: 2630 | G16: 4721 | H16: 200 | L16: 7353 | O16: =sum(B16:N16) -> 34536
A17: Staff Welfare Expenses | B17: 1014 | C17: 4840 | D17: 900 | E17: 529 | F17: 1818 | G17: 5047 | H17: 1500 | O17: =sum(B17:N17) -> 15648
A18: Swiggy Cancellation Charges | I18: 1975 | J18: 325 | K18: 3634 | L18: 1136 | M18: 1213 | O18: =sum(B18:N18) -> 8283
A19: Credit Card Settlement Charges | B19: 1494.19 | D19: 2804.19 | E19: 915.02 | F19: 3924 | G19: 167.53 | H19: 1393.4 | I19: 933.66 | J19: 2500.53 | K19: 3427.31 | L19: 9458.88 | M19: 1304 | O19: =sum(B19:N19) -> 28322.71
A20: General Expenses | B20: 70 | C20: 160 | D20: 5019 | E20: 1156 | F20: 3467 | G20: 1070 | H20: 3175 | L20: 570 | M20: 413 | O20: =sum(B20:N20) -> 15100
A21: House Keeping Charges | B21: 1000 | C21: 9000 | D21: 2300 | E21: 1400 | G21: 3609 | H21: 4000 | I21: 6986 | K21: 3300 | L21: 3963 | M21: 779 | N21: 150 | O21: =sum(B21:N21) -> 36487
A22: Printing & Stationery | B22: 515 | C22: 25550 | D22: 645 | E22: 1239 | F22: 1360 | G22: 2942 | H22: 600 | I22: 970 | J22: 870 | K22: 815 | L22: 700 | M22: 1210 | O22: =sum(B22:N22) -> 37416
A23: General Expenses | I23: 1300 | J23: 661 | K23: 3662 | O23: =sum(B23:N23) -> 5623
A24: Bank Charges | I24: 196.66 | J24: 1227.52 | K24: 1183.95 | L24: 657.33 | M24: 299.85 | O24: =sum(B24:N24) -> 3565.31
B25: =sum(B2:B24) -> 13750.19 | C25: =sum(C2:C24) -> 82563 | D25: =sum(D2:D24) -> 27000.19 | E25: =sum(E2:E24) -> 22883.02 | F25: =sum(F2:F24) -> 21278 | G25: =sum(G2:G24) -> 27118.53 | H25: =sum(H2:H24) -> 19430.4 | I25: =sum(I2:I24) -> 23691.71 | ... O25: =sum(O2:O24) -> 366347.81
A28: Repairs & Maintenance
A29: Repairs & Maintenance
A30: - Petty Cash Expenses | O30: -
A31: Repairs & Maintenance - Plant | B31: 7846 | C31: =5192+24072+225+400+5739+8354+11186+802+17708 -> 73678 | D31: 24576 | E31: 11605 | F31: 5930 | G31: 33346 | H31: 14602 | I31: 15099 | J31: 5260 | K31: 5357 | L31: 10980 | M31: 8800 | N31: 0 | O31: =sum(B31:N31) -> 217079
B32: =sum(B30:B31) -> 7846 | C32: =sum(C30:C31) -> 73678 | D32: =sum(D30:D31) -> 24576 | E32: =sum(E30:E31) -> 11605 | F32: =sum(F30:F31) -> 5930 | G32: =sum(G30:G31) -> 33346 | H32: =sum(H30:H31) -> 14602 | I32: =sum(I30:I31) -> 15099 | ... N32: =sum(N30:N31) -> 0 | O32: =sum(O31) -> 217079

Sheet CK
A1: Capital Deployed
B2: 45748 | C2: 45778 | D2: 45809 | E2: 45839 | F2: 45870 | G2: 45901 | H2: 45931 | I2: 45962 | J2: 45992 | K2: 46023 | L2: 46054 | M2: 46082 | N2: FY 2024-25
A3: Food Cost Calculation
A4: Opening Stock | B4: 2933146.2 | C4: =B7 -> 2891332.9 | D4: =C7 -> 3379383.5 | E4: =D7 -> 2966407 | F4: =E7 -> 3056346 | G4: =F7 -> 2433562.5 | H4: =G7 -> 2497823 | I4: =H7 -> 2959165.1 | J4: =I7 -> 2347751.3 | ... M4: =L7 -> 1456275.2
A5: Purchases Food (Less Purchase Return) | B5: =4123389.06+129854.85 -> 4253243.9 | C5: =4778522.13+400709 -> 5179231.1 | D5: =3898241.18+219009 -> 4117250.2 | E5: =4905526+77907 -> 4983433 | F5: =3770435.4+219224 -> 3989659.4 | G5: =4187600.86+319939 -> 4507539.9 | H5: =4378931.29 -> 4378931.3 | I5: =3446086.26 -> 3446086.3 | J5: =3933774.29 -> 3933774.3 | K5: =4600274.18 -> 4600274.2 | L5: =4862265.14+2812+605 -> 4865682.1 | M5: =5597455.7 -> 5597455.7 | N5: =SUM(B5:M5) -> 53852561
A6: Transferred Out | B6: =4451303.19+30882 -> 4482185.2 | C6: =4644293.38+44290.58 -> 4688584 | D6: =4591421 -> 4591421 | E6: =4774983 -> 4774983 | F6: =4583558.93 -> 4583558.9 | G6: 4537718.5 | H6: 4023434.9 | I6: =4064636.63 -> 4064636.6 | J6: =4965652-38545.77-411631 -> 4515475.2 | K6: =4986541.8-184706 -> 4801835.8 | L6: 5216369.7 | M6: 5701018.7 | N6: =SUM(B6:M6) -> 55981222
A7: Closing Stock | B7: =2565799.5+325533.41 -> 2891332.9 | C7: =3182236.6+197146.94 -> 3379383.5 | D7: =2661902+304505 -> 2966407 | E7: =2836804+219542 -> 3056346 | F7: =2261900.52+171661.93 -> 2433562.5 | G7: =2150288.03+347534.95 -> 2497823 | H7: =2696627.59+262537.5 -> 2959165.1 | I7: =2207781.84+139969.43 -> 2347751.3 | J7: =1651715+149728 -> 1801443 | K7: =1362715.27+195186 -> 1557901.3 | L7: =1233873.18+222402 -> 1456275.2 | M7: =1185355.13+126339 -> 1311694.1
A9: Consumption | B9: =B4+B5-B6-B7 -> -187128 | C9: =C4+C5-C6-C7 -> 2596.54 | D9: =D4+D5-D6-D7 -> -61194.28 | E9: =E4+E5-E6-E7 -> 118511 | F9: =F4+F5-F6-F7 -> 28884.02 | G9: =G4+G5-G6-G7 -> -94439.22 | H9: =H4+H5-H6-H7 -> -105845.73 | I9: =I4+I5-I6-I7 -> -7136.55 | ... M9: =M4+M5-M6-M7 -> 41018.08 | N9: =sum(B9:M9) -> -507208.13
A10: Wastage | B10: =10411.24+94864 -> 105275.24 | C10: =106519+10529 -> 117048 | D10: =8401+81508 -> 89909 | E10: =100108+8818 -> 108926 | F10: =7935.76+91537.74 -> 99473.5 | G10: =10002+88001 -> 98003 | H10: =8243.81+86358.72 -> 94602.53 | I10: =7781.61+89249.73 -> 97031.34 | J10: =5416+87394 -> 92810 | K10: =7721+79048 -> 86769 | L10: =4453.99+80620 -> 85073.99 | M10: =15526.09 -> 15526.09 | N10: =sum(B10:M10) -> 1090447.7
A11: Electricity | B11: =191320+14033+42100/3 -> 219386.33 | C11: =220030+14033+42100/3 -> 248096.33 | D11: =218940+14033+42100/3 -> 247006.33 | E11: =15236+218940 -> 234176 | F11: =244020+10362 -> 254382 | G11: =10266+193720 -> 203986 | H11: =195780+12571.01 -> 208351.01 | I11: =117400+4905 -> 122305 | J11: =140350+5000 -> 145350 | K11: =121370+7744 -> 129114 | L11: =163500+13362 -> 176862 | M11: =8890+175000 -> 183890 | N11: =sum(B11:M11) -> 2372905
A12: Water Supply Charges | B12: 46500 | C12: 46500 | D12: 45000 | E12: =43500 -> 43500 | F12: 46500 | G12: 46500 | H12: 48000 | I12: =45000 -> 45000 | J12: 45000 | K12: 45000 | L12: 43500 | M12: =46500 -> 46500 | N12: =sum(B12:M12) -> 547500
A13: Telephone/Internet | B13: 600 | C13: =4136 -> 4136 | D13: =2875+600 -> 3475 | E13: =5310/3+600 -> 2370 | F13: =5310/3+4160 -> 5930 | G13: =5310/3 -> 1770 | H13: =600 -> 600 | I13: 600 | J13: =4134/3+2828/3+600 -> 2920.6667 | K13: =4134/3+2828/3+600 -> 2920.6667 | L13: =4134/3+2828/3+600 -> 2920.6667 | M13: =2828+600 -> 3428 | N13: =sum(B13:M13) -> 31671
A14: Gas | B14: =47754+122664 -> 170418 | C14: =33193+130059.89 -> 163252.89 | D14: =31014+133378.79 -> 164392.79 | E14: =139346.88+34965 -> 174311.88 | F14: =135061.34+27735 -> 162796.34 | G14: =111777.6+28440 -> 140217.6 | H14: =107670+28440 -> 136110 | I14: =27285+99892 -> 127177 | J14: =28890+106540 -> 135430 | K14: =122498+35511 -> 158009 | L14: =118305.01+41784 -> 160089.01 | M14: =14816+45000+120000 -> 179816 | N14: =sum(B14:M14) -> 1872020.5
A15: Insurance & licenses | B15: 0 | C15: =20822/12 -> 1735.1667 | D15: =20822/12 -> 1735.1667 | E15: =20822/12 -> 1735.1667 | F15: =20822/12 -> 1735.1667 | G15: =20822/12 -> 1735.1667 | H15: =20822/12 -> 1735.1667 | I15: =20822/12 -> 1735.1667 | J15: =20822/12 -> 1735.1667 | K15: =20822/12+21800/12 -> 3551.8333 | L15: =20822/12+21800/12 -> 3551.8333 | M15: =20822/12+21800/12 -> 3551.8333 | N15: =sum(B15:M15) -> 24536.833
A16: Rent & CAM | B16: =284970 -> 284970 | C16: =284970 -> 284970 | D16: =284970 -> 284970 | E16: =284970 -> 284970 | F16: =284970 -> 284970 | G16: =284970 -> 284970 | H16: =284970 -> 284970 | I16: =284970 -> 284970 | ... M16: =284970 -> 284970 | N16: =sum(B16:M16) -> 3419640
A17: Software | B17: =100300/12 -> 8358.3333 | C17: =100300/12 -> 8358.3333 | D17: =100300/12 -> 8358.3333 | E17: =100300/12 -> 8358.3333 | F17: =100300/12 -> 8358.3333 | G17: =100300/12 -> 8358.3333 | H17: =100300/12 -> 8358.3333 | I17: =100300/12 -> 8358.3333 | ... M17: =100300/12 -> 8358.3333 | N17: =sum(B17:M17) -> 100300
A18: Staff Salary | B18: =22000+22420+2516+682535.77+56230/12+258567/12 -> 755704.85 | C18: =677655+22000+22420+3412++56230/12+258567/12 -> 751720.08 | D18: =664272.18+22000+22420+3372+56230/12+258567/12 -> 738297.26 | E18: =667187+22000+22420+4284+56230/12+258567/12 -> 742124.08 | F18: =693558.01+22000+22420+56230/12+258567/12 -> 764211.09 | G18: =650002.38+56230/12+22000+22420+3972+258567/12 -> 724627.46 | H18: =56230/12+258567/12+660685+22000+22420 -> 731338.08 | I18: =56230/12+258567/12+22000+22420+622783 -> 693436.08 | J18: =56230/12+258567/12+613742+22000+22420+14000 -> 698395.08 | K18: =56230/12+258567/12+22000+22420+14000+635419 -> 720072.08 | L18: =56230/12+258567/12+588980+22000+22420 -> 659633.08 | M18: =56230/12+258567/12+22000+3500+22420+616790 -> 690943.08 | N18: =sum(B18:M18) -> 8670502.3
A19: Staff Welfare | N19: =sum(B19:M19) -> 0
A20: Repairs & Maintenance | B20: 29330 | C20: 5757 | D20: 5510 | E20: 13614 | F20: 73678 | G20: 80573 | H20: 85300 | I20: 49692 | J20: 31273 | K20: 113570 | L20: 72337 | M20: =159859 -> 159859 | N20: =sum(B20:M20) -> 720493
A21: Membership & Subscription | N21: =sum(B21:M21) -> 0
A22: AMC | B22: 14160 | C22: =14160+7080 -> 21240 | D22: =14632+8850 -> 23482 | E22: =8850+14632 -> 23482 | F22: =14632+8850 -> 23482 | G22: =14632+8850 -> 23482 | H22: =8850+14632 -> 23482 | I22: =14160+8850 -> 23010 | J22: =8850+14160 -> 23010 | K22: =14160+8850 -> 23010 | L22: =14160+8850 -> 23010 | M22: =8850 -> 8850 | N22: =sum(B22:M22) -> 253700
A23: Miscellaneous Expenses | B23: 32215 | C23: 46084 | D23: 83404 | E23: 53000 | F23: 82563 | G23: 101211 | H23: 81655 | I23: 42035 | J23: 102206 | K23: 66192 | L23: =96567 -> 96567 | M23: 109034.78 | N23: =sum(B23:M23) -> 896166.78
A24: Conveyance | B24: 0 | C24: =900+1700 -> 2600 | N24: =sum(B24:M24) -> 2600
A25: Transport Charges | B25: =123480+122304+70514 -> 316298 | C25: =157447+107632+92305 -> 357384 | D25: =92400+76450+74631 -> 243481 | E25: =117600+80114+67043 -> 264757 | F25: =101584+96810+102097 -> 300491 | G25: =6615+96760+139176.5+69036 -> 311587.5 | H25: =94872+141967+120439 -> 357278 | I25: =73780+145140+100117 -> 319037 | J25: =121894+147840+103786 -> 373520 | K25: =141002+86610+122602 -> 350214 | L25: =165033+179832+111807 -> 456672 | M25: =166498+195982+129062 -> 491542 | N25: =sum(B25:M25) -> 4142261.5
A26: Operating Expenses | B26: =SUM(B10:B25) -> 1983215.8 | C26: =SUM(C10:C25) -> 2058881.8 | D26: =SUM(D10:D25) -> 1939020.9 | E26: =SUM(E10:E25) -> 1955324.5 | F26: =SUM(F10:F25) -> 2108570.4 | G26: =SUM(G11:G25) -> 1929018.1 | H26: =SUM(H11:H25) -> 1967177.6 | I26: =SUM(I11:I25) -> 1717355.6 | J26: =SUM(J11:J25) -> 1852168.2 | K26: =SUM(K11:K25) -> 1904981.9 | L26: =SUM(L11:L25) -> 1988470.9 | M26: =SUM(M11:M25) -> 2170743 | N26: =sum(B26:M26) -> 23574929

Sheet HO
A2: Head Office Expenses | B2: 45748 | C2: 45778 | D2: 45809 | E2: 45839 | F2: 45870 | G2: 45901 | H2: 45931 | I2: 45962 | J2: 45992 | K2: 46023 | L2: 46054 | M2: 46082 | N2: FY 2024-25
A3: Central Kitchen Expenses | B3: =CK!B26 -> 1983215.8 | C3: =CK!C26 -> 2058881.8 | D3: =CK!D26 -> 1939020.9 | E3: =CK!E26 -> 1955324.5 | F3: =CK!F26 -> 2108570.4 | G3: =CK!G26 -> 1929018.1 | H3: =CK!H26 -> 1967177.6 | I3: =CK!I26 -> 1717355.6 | ... M3: =CK!M26 -> 2170743 | N3: =sum(B3:M3) -> 23574929
A4: Guest House Expenses | B4: =150+2428+3000+23600+23600 -> 52778 | C4: =+150+2428+3000+23600+23600 -> 52778 | D4: =23600+23600+150+3000+2428 -> 52778 | E4: =23600+23600+150+2428+3000 -> 52778 | F4: =150+2428+3000+23600+23600 -> 52778 | G4: =150+3028+3000+3000+23600+23600 -> 56378 | H4: =23600+23600+150+2428+3000 -> 52778 | I4: =24780+24780+8030+2428+3000+150 -> 63168 | J4: =23600+23600+150+2428+3000 -> 52778 | K4: =24780+24780+2428+3350+150 -> 55488 | L4: =24780+24780+150+2428+3000 -> 55138 | M4: =24780+24780+150+2428+3000 -> 55138 | N4: =sum(B4:M4) -> 654756
A5: Delhi Office Rent & Electricity | B5: =45000 -> 45000 | C5: =53100 -> 53100 | D5: =53100 -> 53100 | E5: =53100 -> 53100 | F5: =53100 -> 53100 | G5: =53100 -> 53100 | H5: =53100 -> 53100 | I5: =53100 -> 53100 | J5: =53100 -> 53100 | K5: =55755 -> 55755 | L5: =55755 -> 55755 | M5: =55755 -> 55755 | N5: =sum(B5:M5) -> 637065
A6: General Expenses | N6: =sum(B6:M6) -> 0
A7: Insurance Premium | B7: 0 | C7: =22302/12 -> 1858.5 | D7: =22302/12 -> 1858.5 | E7: =22302/12 -> 1858.5 | F7: =22302/12 -> 1858.5 | G7: =22302/12 -> 1858.5 | H7: =22302/12 -> 1858.5 | I7: =22302/12 -> 1858.5 | J7: =22302/12 -> 1858.5 | ... M7: =22302/12 -> 1858.5 | N7: =sum(B7:M7) -> 20443.5
A8: Telephone Expenses | M8: 3536 | N8: =sum(B8:M8) -> 3536
A9: Head Office Salary | B9: =419266+6000+224921/12+66000/12 -> 449509.42 | C9: =480066+224921/12+66000/12 -> 504309.42 | D9: =478499.33+224921/12+66000/12 -> 502742.75 | E9: =349357+130709+224921/12+66000/12 -> 504309.42 | F9: =349357+130709+224921/12+66000/12 -> 504309.42 | G9: =349357+130709+224921/12+66000/12 -> 504309.42 | H9: =224921/12+349357+130709+66000/12 -> 504309.42 | I9: =224921/12+476419.33+76679+66000/12 -> 577341.75 | J9: =224921/12+349357+138739+79278+66000/12 -> 591617.42 | K9: =224921/12+480066+79278+66000/12 -> 583587.42 | L9: =224921/12+479012+66000/12+54385 -> 557640.42 | M9: =224921/12+66000/12+459266+55074 -> 538583.42 | N9: =sum(B9:M9) -> 6322569.7
A10: Leave Encashment | N10: =sum(B10:M10) -> 0
A11: Miscellaneous Expenses | B11: 18384.22 | C11: 25286.45 | D11: =52318-40125+33795 -> 45988 | E11: =9344+33512 -> 42856 | F11: =837+33158 -> 33995 | G11: =22457.27+33158 -> 55615.27 | H11: =33158+13163 -> 46321 | I11: =489 -> 489 | J11: 6929 | K11: -1595 | L11: 1332.27 | M11: =98502 -> 98502 | N11: =sum(B11:M11) -> 374103.21
A12: Motor Car Expenses & Fuel | N12: =sum(B12:M12) -> 0
A13: Office Expenses | N13: =sum(B13:M13) -> 0
A14: Professional and Consultancy Fees | B14: =52510 -> 52510 | C14: =52510 -> 52510 | D14: =52510+7080+7080 -> 66670 | E14: =52510+7080+7080+21240 -> 87910 | F14: =52510+23400 -> 75910 | G14: =+52510 -> 52510 | H14: 52510 | I14: 52510 | J14: 52510 | K14: 52510 | L14: =52510 -> 52510 | M14: =52510 -> 52510 | N14: =sum(B14:M14) -> 703080
A15: Mystery Audit | B15: =60180/3 -> 20060 | C15: =60180/3 -> 20060 | D15: =60180/3 -> 20060 | E15: =60180/3 -> 20060 | F15: =60180/3 -> 20060 | G15: =60180/3 -> 20060 | H15: =60180/3 -> 20060 | I15: =60180/3 -> 20060 | J15: =60180/3 -> 20060 | K15: 21240 | L15: 21240 | M15: 21240
A16: Printing & Stationary | N16: =sum(B16:M16) -> 0
A17: Repair & Maintenance | N17: =sum(B17:M17) -> 0
A18: Software Charges | N18: =sum(B18:M18) -> 0
A19: Staff Incentive | N19: =sum(B19:M19) -> 0
A20: Staff Food & Perks | N20: =sum(B20:M20) -> 0
A21: Subscription & Membership | N21: =sum(B21:M21) -> 0
A22: Transportation and Labour | N22: =sum(B22:M22) -> 0
A23: Travelling and Conveyance | B23: 55807 | C23: =16961 -> 16961 | D23: 40125 | E23: =181982.26 -> 181982.26 | F23: 120891 | G23: 0 | H23: 50488 | I23: 55542 | J23: 41273 | K23: 56161 | L23: =45018 -> 45018 | M23: =245006 -> 245006 | N23: =sum(B23:M23) -> 909254.26
A24: Other Sales | D24: -12429 | G24: -7869 | N24: =sum(B24:M24) -> -20298
N25: =sum(B25:M25) -> 0
A26: Total HO Expenses | B26: =+SUM(B3:B24) -> 2677264.4 | C26: =+SUM(C3:C24) -> 2785745.2 | D26: =+SUM(D3:D24) -> 2709914.1 | E26: =+SUM(E3:E24) -> 2900178.6 | F26: =+SUM(F3:F24) -> 2971472.4 | G26: =+SUM(G3:G24) -> 2664980.2 | H26: =+SUM(H3:H23) -> 2748602.5 | I26: =+SUM(I3:I23) -> 2541424.8 | J26: =+SUM(J3:J23) -> 2672294.2 | K26: =+SUM(K3:K23) -> 2729986.8 | L26: =+SUM(L3:L24) -> 2778963.1 | M26: =+SUM(M3:M24) -> 3242871.9
B28: Apr'2025 | C28: % Sales Dist | D28: % Dist (HO) | F28: May'2025 | G28: % Sales Dist | H28: % Dist (HO) | J28: June'2025 | K28: % Sales Dist | L28: % Dist (HO) | N28: July'2025 | O28: % Sales Dist | P28: % Dist (HO)
A29: Noida Sector 18 | B29: ='Noida Sec - 18'!B13 -> 1660914.1 | C29: =B29/$B$40 -> 0.1129685 | D29: =C29*$B$26 -> 302446.54 | F29: ='Noida Sec - 18'!C13 -> 1537840.2 | G29: =F29/$F$40 -> 0.097350153 | H29: =G29*$C$26 -> 271192.72 | J29: ='Noida Sec - 18'!D13 -> 1445142.6 | K29: =J29/$J$40 -> 0.092004826 | L29: =K29*$D$26 -> 249325.18 | N29: ='Noida Sec - 18'!E13 -> 1662636.9 | O29: =N29/$N$40 -> 0.10061744 | P29: =O29*$E$26 -> 291808.56
